{
  "type": "Feature",
  "properties": {
    "gn:admin1_code":"03",
    "gn:asciiname":"Antafiandakana",
    "gn:country_code":"MG",
    "gn:dem":29,
    "gn:feature_class":"P",
    "gn:feature_code":"PPL",
    "gn:name":"Antafiandakana",
    "gn:population":0,
    "gn:timezone":"Indian/Antananarivo",
    "iso:country":"MG",
    "wof:name":"Antafiandakana",
    "wof:placetype":"locality"
},
  "geometry": {"coordinates":[47.81667,-15.53333],"type":"Point"}
}