{
  "type": "Feature",
  "properties": {
    "gn:admin1_code":"06",
    "gn:asciiname":"Ankatoka",
    "gn:cc2":"MG",
    "gn:country_code":"MG",
    "gn:dem":170,
    "gn:feature_class":"P",
    "gn:feature_code":"PPL",
    "gn:name":"Ankatoka",
    "gn:population":0,
    "gn:timezone":"Indian/Antananarivo",
    "iso:country":"MG",
    "name:und_x_variant":[
        "Ankaboka",
        "Ankatoka"
    ],
    "wof:name":"Ankatoka",
    "wof:placetype":"locality"
},
  "geometry": {"coordinates":[45.01667,-20.58333],"type":"Point"}
}