{
  "type": "Feature",
  "properties": {
    "gn:admin1_code":"05",
    "gn:asciiname":"Ambolotarabe",
    "gn:country_code":"MG",
    "gn:dem":1070,
    "gn:feature_class":"P",
    "gn:feature_code":"PPL",
    "gn:name":"Ambolotarabe",
    "gn:population":0,
    "gn:timezone":"Indian/Antananarivo",
    "iso:country":"MG",
    "wof:name":"Ambolotarabe",
    "wof:placetype":"locality"
},
  "geometry": {"coordinates":[47.38333,-18.35],"type":"Point"}
}