{
  "type": "Feature",
  "properties": {
    "gn:admin1_code":"03",
    "gn:asciiname":"Andriba",
    "gn:cc2":"MG",
    "gn:country_code":"MG",
    "gn:dem":624,
    "gn:feature_class":"P",
    "gn:feature_code":"PPL",
    "gn:name":"Andriba",
    "gn:population":0,
    "gn:timezone":"Indian/Antananarivo",
    "iso:country":"MG",
    "name:fra_x_preferred":[
        "Andriba"
    ],
    "name:ita_x_preferred":[
        "Andriba"
    ],
    "name:mlg_x_preferred":[
        "Andriba"
    ],
    "name:nld_x_preferred":[
        "Andriba"
    ],
    "name:und_x_variant":[
        "Fort Andriba"
    ],
    "wof:name":"Andriba",
    "wof:placetype":"locality"
},
  "geometry": {"coordinates":[46.93333,-17.58333],"type":"Point"}
}