{
  "type": "Feature",
  "properties": {
    "gn:admin1_code":"05",
    "gn:asciiname":"Antsorindrabe",
    "gn:country_code":"MG",
    "gn:dem":1282,
    "gn:feature_class":"P",
    "gn:feature_code":"PPL",
    "gn:name":"Antsorindrabe",
    "gn:population":0,
    "gn:timezone":"Indian/Antananarivo",
    "iso:country":"MG",
    "wof:name":"Antsorindrabe",
    "wof:placetype":"locality"
},
  "geometry": {"coordinates":[47.26667,-18.03333],"type":"Point"}
}