{
  "type": "Feature",
  "properties": {
    "gn:admin1_code":"03",
    "gn:asciiname":"Belailay",
    "gn:cc2":"MG",
    "gn:country_code":"MG",
    "gn:dem":11,
    "gn:feature_class":"P",
    "gn:feature_code":"PPL",
    "gn:name":"Belailay",
    "gn:population":0,
    "gn:timezone":"Indian/Antananarivo",
    "iso:country":"MG",
    "name:und_x_variant":[
        "Belatay",
        "Belailay"
    ],
    "wof:name":"Belailay",
    "wof:placetype":"locality"
},
  "geometry": {"coordinates":[44.05,-17.95],"type":"Point"}
}