{
  "type": "Feature",
  "properties": {
    "gn:admin1_code":"04",
    "gn:asciiname":"Ampianana",
    "gn:country_code":"MG",
    "gn:dem":290,
    "gn:feature_class":"P",
    "gn:feature_code":"PPL",
    "gn:name":"Ampianana",
    "gn:population":0,
    "gn:timezone":"Indian/Antananarivo",
    "iso:country":"MG",
    "wof:name":"Ampianana",
    "wof:placetype":"locality"
},
  "geometry": {"coordinates":[48.71667,-18.78333],"type":"Point"}
}