{
  "type": "Feature",
  "properties": {
    "gn:admin1_code":"03",
    "gn:asciiname":"Ampombintsihanaka",
    "gn:country_code":"MG",
    "gn:dem":296,
    "gn:feature_class":"P",
    "gn:feature_code":"PPL",
    "gn:name":"Ampombintsihanaka",
    "gn:population":0,
    "gn:timezone":"Indian/Antananarivo",
    "iso:country":"MG",
    "wof:name":"Ampombintsihanaka",
    "wof:placetype":"locality"
},
  "geometry": {"coordinates":[47.85,-16.08333],"type":"Point"}
}