{
  "type": "Feature",
  "properties": {
    "gn:admin1_code":"03",
    "gn:asciiname":"Ambonara",
    "gn:country_code":"MG",
    "gn:dem":289,
    "gn:feature_class":"P",
    "gn:feature_code":"PPL",
    "gn:name":"Ambonara",
    "gn:population":0,
    "gn:timezone":"Indian/Antananarivo",
    "iso:country":"MG",
    "wof:name":"Ambonara",
    "wof:placetype":"locality"
},
  "geometry": {"coordinates":[44.93333,-18.11667000000001],"type":"Point"}
}