{
  "type": "Feature",
  "properties": {
    "gn:admin1_code":"6.0",
    "gn:asciiname":"Tsimaloto",
    "gn:country_code":"MG",
    "gn:dem":19,
    "gn:feature_class":"P",
    "gn:feature_code":"PPL",
    "gn:name":"Tsimaloto",
    "gn:population":0,
    "gn:timezone":"Indian/Antananarivo",
    "iso:country":"MG",
    "wof:name":"Tsimaloto",
    "wof:placetype":"locality"
},
  "geometry": {"coordinates":[44.91667,-19.76667],"type":"Point"}
}