{
  "type": "Feature",
  "properties": {
    "gn:admin1_code":"05",
    "gn:asciiname":"Andrefantsena",
    "gn:country_code":"MG",
    "gn:dem":1554,
    "gn:feature_class":"P",
    "gn:feature_code":"PPL",
    "gn:name":"Andrefantsena",
    "gn:population":0,
    "gn:timezone":"Indian/Antananarivo",
    "iso:country":"MG",
    "wof:name":"Andrefantsena",
    "wof:placetype":"locality"
},
  "geometry": {"coordinates":[47.08333,-19.36667000000001],"type":"Point"}
}