{
  "type": "Feature",
  "properties": {
    "gn:admin1_code":"05",
    "gn:asciiname":"Ambohikely",
    "gn:country_code":"MG",
    "gn:dem":1280,
    "gn:feature_class":"P",
    "gn:feature_code":"PPL",
    "gn:name":"Ambohikely",
    "gn:population":0,
    "gn:timezone":"Indian/Antananarivo",
    "iso:country":"MG",
    "wof:name":"Ambohikely",
    "wof:placetype":"locality"
},
  "geometry": {"coordinates":[47.23333,-18.75],"type":"Point"}
}