{
  "type": "Feature",
  "properties": {
    "gn:admin1_code":"5.0",
    "gn:asciiname":"Tsaratanana",
    "gn:country_code":"MG",
    "gn:dem":1003,
    "gn:feature_class":"P",
    "gn:feature_code":"PPL",
    "gn:name":"Tsaratanana",
    "gn:population":0,
    "gn:timezone":"Indian/Antananarivo",
    "iso:country":"MG",
    "name:ceb_x_preferred":[
        "Tsaratanana"
    ],
    "name:fra_x_preferred":[
        "Tsaratanana"
    ],
    "name:ita_x_preferred":[
        "Tsaratanana"
    ],
    "name:mlg_x_preferred":[
        "Tsaratanana"
    ],
    "name:nld_x_preferred":[
        "Tsaratanana"
    ],
    "name:pol_x_preferred":[
        "Tsaratanana"
    ],
    "name:swe_x_preferred":[
        "Tsaratanana"
    ],
    "name:zho_x_preferred":[
        "\u5bdf\u62c9\u5854\u7d0d\u7d0d"
    ],
    "wof:name":"Tsaratanana",
    "wof:placetype":"locality"
},
  "geometry": {"coordinates":[46.61667,-18.36667000000001],"type":"Point"}
}