{
  "type": "Feature",
  "properties": {
    "gn:admin1_code":"06",
    "gn:asciiname":"Antsovela",
    "gn:cc2":"MG",
    "gn:country_code":"MG",
    "gn:dem":11,
    "gn:feature_class":"P",
    "gn:feature_code":"PPL",
    "gn:name":"Antsovela",
    "gn:population":0,
    "gn:timezone":"Indian/Antananarivo",
    "iso:country":"MG",
    "name:und_x_variant":[
        "Antsovelo",
        "Antsovela"
    ],
    "wof:name":"Antsovela",
    "wof:placetype":"locality"
},
  "geometry": {"coordinates":[46.46667,-25.08333],"type":"Point"}
}