{
  "type": "Feature",
  "properties": {
    "gn:admin1_code":"06",
    "gn:asciiname":"Marovala",
    "gn:cc2":"MG",
    "gn:country_code":"MG",
    "gn:dem":855,
    "gn:feature_class":"P",
    "gn:feature_code":"PPL",
    "gn:name":"Marovala",
    "gn:population":0,
    "gn:timezone":"Indian/Antananarivo",
    "iso:country":"MG",
    "name:und_x_variant":[
        "Marovalo",
        "Marovato",
        "Marovala"
    ],
    "wof:name":"Marovala",
    "wof:placetype":"locality"
},
  "geometry": {"coordinates":[46.03333,-23.16667],"type":"Point"}
}