{
  "type": "Feature",
  "properties": {
    "gn:admin1_code":"06",
    "gn:asciiname":"Amborompotsy",
    "gn:cc2":"MG",
    "gn:country_code":"MG",
    "gn:dem":561,
    "gn:feature_class":"P",
    "gn:feature_code":"PPL",
    "gn:name":"Amborompotsy",
    "gn:population":0,
    "gn:timezone":"Indian/Antananarivo",
    "iso:country":"MG",
    "name:azb_x_preferred":[
        "\u0627\u0645\u0628\u0648\u0631\u0627\u0645\u067e\u0627\u062a\u0633\u06cc"
    ],
    "name:fas_x_preferred":[
        "\u0627\u0645\u0628\u0648\u0631\u0627\u0645\u067e\u0627\u062a\u0633\u06cc"
    ],
    "name:fra_x_preferred":[
        "Amborompotsy"
    ],
    "name:ita_x_preferred":[
        "Amborompotsy"
    ],
    "name:mlg_x_preferred":[
        "Amborompotsy"
    ],
    "name:nld_x_preferred":[
        "Amborompotsy"
    ],
    "name:und_x_variant":[
        "Amboropotsy"
    ],
    "wof:name":"Amborompotsy",
    "wof:placetype":"locality"
},
  "geometry": {"coordinates":[45.36667,-23.28333],"type":"Point"}
}