{
  "type": "Feature",
  "properties": {
    "gn:admin1_code":"03",
    "gn:asciiname":"Beagoago",
    "gn:country_code":"MG",
    "gn:dem":57,
    "gn:feature_class":"P",
    "gn:feature_code":"PPL",
    "gn:name":"Beagoago",
    "gn:population":0,
    "gn:timezone":"Indian/Antananarivo",
    "iso:country":"MG",
    "wof:name":"Beagoago",
    "wof:placetype":"locality"
},
  "geometry": {"coordinates":[47.65,-15.53333],"type":"Point"}
}