{
  "type": "Feature",
  "properties": {
    "gn:admin1_code":"06",
    "gn:asciiname":"Iabondro",
    "gn:cc2":"MG",
    "gn:country_code":"MG",
    "gn:dem":62,
    "gn:feature_class":"P",
    "gn:feature_code":"PPL",
    "gn:name":"Iabondro",
    "gn:population":0,
    "gn:timezone":"Indian/Antananarivo",
    "iso:country":"MG",
    "name:und_x_variant":[
        "Iabodiro",
        "Iabondro"
    ],
    "wof:name":"Iabondro",
    "wof:placetype":"locality"
},
  "geometry": {"coordinates":[44.05,-21.88333],"type":"Point"}
}