{
  "type": "Feature",
  "properties": {
    "gn:admin1_code":"06",
    "gn:asciiname":"Kiteny",
    "gn:country_code":"MG",
    "gn:dem":118,
    "gn:feature_class":"P",
    "gn:feature_code":"PPL",
    "gn:name":"Kiteny",
    "gn:population":0,
    "gn:timezone":"Indian/Antananarivo",
    "iso:country":"MG",
    "wof:name":"Kiteny",
    "wof:placetype":"locality"
},
  "geometry": {"coordinates":[44.33333,-25.05],"type":"Point"}
}