{
  "type": "Feature",
  "properties": {
    "gn:admin1_code":"02",
    "gn:asciiname":"Ankatsaka",
    "gn:country_code":"MG",
    "gn:dem":1381,
    "gn:feature_class":"P",
    "gn:feature_code":"PPL",
    "gn:name":"Ankatsaka",
    "gn:population":0,
    "gn:timezone":"Indian/Antananarivo",
    "iso:country":"MG",
    "wof:name":"Ankatsaka",
    "wof:placetype":"locality"
},
  "geometry": {"coordinates":[47.01667,-20.95],"type":"Point"}
}