{
  "type": "Feature",
  "properties": {
    "gn:admin1_code":"4.0",
    "gn:asciiname":"Saivaza",
    "gn:country_code":"MG",
    "gn:dem":341,
    "gn:feature_class":"P",
    "gn:feature_code":"PPL",
    "gn:name":"Saivaza",
    "gn:population":0,
    "gn:timezone":"Indian/Antananarivo",
    "iso:country":"MG",
    "wof:name":"Saivaza",
    "wof:placetype":"locality"
},
  "geometry": {"coordinates":[48.53333,-19.66667],"type":"Point"}
}