{
  "type": "Feature",
  "properties": {
    "gn:admin1_code":"03",
    "gn:asciiname":"Andranovelo",
    "gn:country_code":"MG",
    "gn:dem":373,
    "gn:feature_class":"P",
    "gn:feature_code":"PPL",
    "gn:name":"Andranovelo",
    "gn:population":0,
    "gn:timezone":"Indian/Antananarivo",
    "iso:country":"MG",
    "wof:name":"Andranovelo",
    "wof:placetype":"locality"
},
  "geometry": {"coordinates":[45.28333,-17.65],"type":"Point"}
}