{
  "type": "Feature",
  "properties": {
    "gn:admin1_code":"05",
    "gn:asciiname":"Fokotapia",
    "gn:country_code":"MG",
    "gn:dem":1397,
    "gn:feature_class":"P",
    "gn:feature_code":"PPL",
    "gn:name":"Fokotapia",
    "gn:population":0,
    "gn:timezone":"Indian/Antananarivo",
    "iso:country":"MG",
    "wof:name":"Fokotapia",
    "wof:placetype":"locality"
},
  "geometry": {"coordinates":[47.18333,-19.08333],"type":"Point"}
}