{
  "type": "Feature",
  "properties": {
    "gn:admin1_code":"05",
    "gn:asciiname":"Amboanjobe",
    "gn:country_code":"MG",
    "gn:dem":1404,
    "gn:feature_class":"P",
    "gn:feature_code":"PPL",
    "gn:name":"Amboanjobe",
    "gn:population":0,
    "gn:timezone":"Indian/Antananarivo",
    "iso:country":"MG",
    "wof:name":"Amboanjobe",
    "wof:placetype":"locality"
},
  "geometry": {"coordinates":[47.23333,-19.05],"type":"Point"}
}