{
  "type": "Feature",
  "properties": {
    "gn:admin1_code":"02",
    "gn:asciiname":"Antanjomanga",
    "gn:country_code":"MG",
    "gn:dem":366,
    "gn:feature_class":"P",
    "gn:feature_code":"PPL",
    "gn:name":"Antanjomanga",
    "gn:population":0,
    "gn:timezone":"Indian/Antananarivo",
    "iso:country":"MG",
    "wof:name":"Antanjomanga",
    "wof:placetype":"locality"
},
  "geometry": {"coordinates":[48.16667,-20.53333],"type":"Point"}
}