{
  "type": "Feature",
  "properties": {
    "gn:admin1_code":"2.0",
    "gn:asciiname":"Tanambao",
    "gn:cc2":"MG",
    "gn:country_code":"MG",
    "gn:dem":168,
    "gn:feature_class":"P",
    "gn:feature_code":"PPL",
    "gn:name":"Tanambao",
    "gn:population":0,
    "gn:timezone":"Indian/Antananarivo",
    "iso:country":"MG",
    "name:und_x_variant":[
        "Antanambao",
        "Tanambao"
    ],
    "wof:name":"Tanambao",
    "wof:placetype":"locality"
},
  "geometry": {"coordinates":[47.31667,-22.08333],"type":"Point"}
}