{
  "type": "Feature",
  "properties": {
    "gn:admin1_code":"02",
    "gn:asciiname":"Ampamary",
    "gn:country_code":"MG",
    "gn:dem":1149,
    "gn:feature_class":"P",
    "gn:feature_code":"PPL",
    "gn:name":"Ampamary",
    "gn:population":0,
    "gn:timezone":"Indian/Antananarivo",
    "iso:country":"MG",
    "wof:name":"Ampamary",
    "wof:placetype":"locality"
},
  "geometry": {"coordinates":[46.93333,-21.15],"type":"Point"}
}