{
  "type": "Feature",
  "properties": {
    "gn:admin1_code":"06",
    "gn:asciiname":"Ambararatanaomby",
    "gn:country_code":"MG",
    "gn:dem":422,
    "gn:feature_class":"P",
    "gn:feature_code":"PPL",
    "gn:name":"Ambararatanaomby",
    "gn:population":0,
    "gn:timezone":"Indian/Antananarivo",
    "iso:country":"MG",
    "wof:name":"Ambararatanaomby",
    "wof:placetype":"locality"
},
  "geometry": {"coordinates":[45.08333,-21.11667000000001],"type":"Point"}
}