{
  "type": "Feature",
  "properties": {
    "gn:admin1_code":"06",
    "gn:asciiname":"Ambatofotsy",
    "gn:country_code":"MG",
    "gn:dem":200,
    "gn:feature_class":"P",
    "gn:feature_code":"PPL",
    "gn:name":"Ambatofotsy",
    "gn:population":0,
    "gn:timezone":"Indian/Antananarivo",
    "iso:country":"MG",
    "wof:name":"Ambatofotsy",
    "wof:placetype":"locality"
},
  "geometry": {"coordinates":[45.85,-24.68333],"type":"Point"}
}