{
  "type": "Feature",
  "properties": {
    "gn:admin1_code":"03",
    "gn:asciiname":"Androy",
    "gn:country_code":"MG",
    "gn:dem":106,
    "gn:feature_class":"P",
    "gn:feature_code":"PPL",
    "gn:name":"Androy",
    "gn:population":0,
    "gn:timezone":"Indian/Antananarivo",
    "iso:country":"MG",
    "wof:name":"Androy",
    "wof:placetype":"locality"
},
  "geometry": {"coordinates":[47.85,-14.36667],"type":"Point"}
}