{
  "type": "Feature",
  "properties": {
    "gn:admin1_code":"03",
    "gn:asciiname":"Androy",
    "gn:country_code":"MG",
    "gn:dem":106,
    "gn:feature_class":"P",
    "gn:feature_code":"PPL",
    "gn:name":"Androy",
    "gn:population":0,
    "gn:timezone":"Indian/Antananarivo",
    "iso:country":"MG",
    "name:ara_x_preferred":[
        "\u0623\u0646\u062f\u0631\u0648\u064a"
    ],
    "name:bre_x_preferred":[
        "Androy"
    ],
    "name:bul_x_preferred":[
        "\u0410\u043d\u0434\u0440\u043e\u0439"
    ],
    "name:ceb_x_preferred":[
        "Androy Region"
    ],
    "name:dan_x_preferred":[
        "Androy"
    ],
    "name:deu_x_preferred":[
        "Androy"
    ],
    "name:ell_x_preferred":[
        "\u0391\u03bd\u03c4\u03c1\u03cc\u03b9"
    ],
    "name:epo_x_preferred":[
        "Androy"
    ],
    "name:est_x_preferred":[
        "Androy piirkond"
    ],
    "name:fas_x_preferred":[
        "\u0622\u0646\u062f\u0631\u0648\u06cc"
    ],
    "name:fra_x_preferred":[
        "Androy"
    ],
    "name:ind_x_preferred":[
        "Androy"
    ],
    "name:kor_x_preferred":[
        "\uc548\ub4dc\ub85c\uc774 \uad6c"
    ],
    "name:mlg_x_preferred":[
        "Androy"
    ],
    "name:nld_x_preferred":[
        "Androy"
    ],
    "name:nor_x_preferred":[
        "Androy"
    ],
    "name:pol_x_preferred":[
        "Androy"
    ],
    "name:por_x_preferred":[
        "Androy"
    ],
    "name:ron_x_preferred":[
        "Regiunea Androy"
    ],
    "name:swa_x_preferred":[
        "Androy"
    ],
    "name:swe_x_preferred":[
        "Androyregionen"
    ],
    "name:urd_x_preferred":[
        "\u0622\u0646\u062f\u0631\u0648\u06cc"
    ],
    "name:zho_x_preferred":[
        "\u5b89\u5fb7\u7f85\u4f0a\u5340"
    ],
    "wof:name":"Androy",
    "wof:placetype":"locality"
},
  "geometry": {"coordinates":[47.85,-14.36667],"type":"Point"}
}