{
  "type": "Feature",
  "properties": {
    "gn:admin1_code":"2.0",
    "gn:asciiname":"Tsiananatondro",
    "gn:country_code":"MG",
    "gn:dem":1210,
    "gn:feature_class":"P",
    "gn:feature_code":"PPL",
    "gn:name":"Tsiananatondro",
    "gn:population":0,
    "gn:timezone":"Indian/Antananarivo",
    "iso:country":"MG",
    "wof:name":"Tsiananatondro",
    "wof:placetype":"locality"
},
  "geometry": {"coordinates":[47.28333,-21.23333],"type":"Point"}
}