{
  "type": "Feature",
  "properties": {
    "gn:admin1_code":"03",
    "gn:asciiname":"Antobinimadama",
    "gn:cc2":"MG",
    "gn:country_code":"MG",
    "gn:dem":719,
    "gn:feature_class":"P",
    "gn:feature_code":"PPL",
    "gn:name":"Antobinimadama",
    "gn:population":0,
    "gn:timezone":"Indian/Antananarivo",
    "iso:country":"MG",
    "name:und_x_variant":[
        "Antobinimadamo",
        "Antobinimadama"
    ],
    "wof:name":"Antobinimadama",
    "wof:placetype":"locality"
},
  "geometry": {"coordinates":[46.68333,-17.68332999999999],"type":"Point"}
}