{
  "type": "Feature",
  "properties": {
    "gn:admin1_code":"2.0",
    "gn:asciiname":"Tsaratanteraka",
    "gn:cc2":"MG",
    "gn:country_code":"MG",
    "gn:dem":251,
    "gn:feature_class":"P",
    "gn:feature_code":"PPL",
    "gn:name":"Tsaratanteraka",
    "gn:population":0,
    "gn:timezone":"Indian/Antananarivo",
    "iso:country":"MG",
    "name:und_x_variant":[
        "Tsaratandreka",
        "Tsaratanteraka"
    ],
    "wof:name":"Tsaratanteraka",
    "wof:placetype":"locality"
},
  "geometry": {"coordinates":[47.45,-21.91667],"type":"Point"}
}