{
  "type": "Feature",
  "properties": {
    "gn:admin1_code":"03",
    "gn:asciiname":"Ambaro",
    "gn:country_code":"MG",
    "gn:dem":12,
    "gn:feature_class":"P",
    "gn:feature_code":"PPL",
    "gn:name":"Ambaro",
    "gn:population":0,
    "gn:timezone":"Indian/Antananarivo",
    "iso:country":"MG",
    "wof:name":"Ambaro",
    "wof:placetype":"locality"
},
  "geometry": {"coordinates":[46.53333,-15.63333],"type":"Point"}
}