{
  "type": "Feature",
  "properties": {
    "gn:admin1_code":"05",
    "gn:asciiname":"Anjanahary",
    "gn:country_code":"MG",
    "gn:dem":1283,
    "gn:feature_class":"P",
    "gn:feature_code":"PPL",
    "gn:name":"Anjanahary",
    "gn:population":0,
    "gn:timezone":"Indian/Antananarivo",
    "iso:country":"MG",
    "wof:name":"Anjanahary",
    "wof:placetype":"locality"
},
  "geometry": {"coordinates":[47.536,-18.895],"type":"Point"}
}