{
  "type": "Feature",
  "properties": {
    "gn:admin1_code":"03",
    "gn:asciiname":"Anahidrano",
    "gn:country_code":"MG",
    "gn:dem":37,
    "gn:feature_class":"P",
    "gn:feature_code":"PPL",
    "gn:name":"Anahidrano",
    "gn:population":0,
    "gn:timezone":"Indian/Antananarivo",
    "iso:country":"MG",
    "wof:name":"Anahidrano",
    "wof:placetype":"locality"
},
  "geometry": {"coordinates":[47.65,-15.48333],"type":"Point"}
}