{
  "type": "Feature",
  "properties": {
    "gn:admin1_code":"06",
    "gn:asciiname":"Ikongo",
    "gn:country_code":"MG",
    "gn:dem":25,
    "gn:feature_class":"P",
    "gn:feature_code":"PPL",
    "gn:name":"Ikongo",
    "gn:population":0,
    "gn:timezone":"Indian/Antananarivo",
    "iso:country":"MG",
    "name:ceb_x_preferred":[
        "Ikongo"
    ],
    "name:deu_x_preferred":[
        "Ikongo"
    ],
    "name:fra_x_preferred":[
        "Ikongo"
    ],
    "name:ita_x_preferred":[
        "Ikongo"
    ],
    "name:mlg_x_preferred":[
        "Ikongo"
    ],
    "name:nld_x_preferred":[
        "Ikongo"
    ],
    "name:pol_x_preferred":[
        "Ikongo"
    ],
    "name:por_x_preferred":[
        "Ikongo"
    ],
    "name:swe_x_preferred":[
        "Ikongo"
    ],
    "name:zho_x_preferred":[
        "\u4f0a\u5b54\u53e4"
    ],
    "wof:name":"Ikongo",
    "wof:placetype":"locality"
},
  "geometry": {"coordinates":[43.55,-21.76667],"type":"Point"}
}