{
  "type": "Feature",
  "properties": {
    "gn:admin1_code":"06",
    "gn:asciiname":"Ikongo",
    "gn:country_code":"MG",
    "gn:dem":25,
    "gn:feature_class":"P",
    "gn:feature_code":"PPL",
    "gn:name":"Ikongo",
    "gn:population":0,
    "gn:timezone":"Indian/Antananarivo",
    "iso:country":"MG",
    "wof:name":"Ikongo",
    "wof:placetype":"locality"
},
  "geometry": {"coordinates":[43.55,-21.76667],"type":"Point"}
}