{
  "type": "Feature",
  "properties": {
    "gn:admin1_code":"03",
    "gn:asciiname":"Ambohimiandra",
    "gn:country_code":"MG",
    "gn:dem":206,
    "gn:feature_class":"P",
    "gn:feature_code":"PPL",
    "gn:name":"Ambohimiandra",
    "gn:population":0,
    "gn:timezone":"Indian/Antananarivo",
    "iso:country":"MG",
    "wof:name":"Ambohimiandra",
    "wof:placetype":"locality"
},
  "geometry": {"coordinates":[47.83333,-16.15],"type":"Point"}
}