{
  "type": "Feature",
  "properties": {
    "gn:admin1_code":"05",
    "gn:asciiname":"Amberobe",
    "gn:country_code":"MG",
    "gn:dem":1595,
    "gn:feature_class":"P",
    "gn:feature_code":"PPL",
    "gn:name":"Amberobe",
    "gn:population":0,
    "gn:timezone":"Indian/Antananarivo",
    "iso:country":"MG",
    "wof:name":"Amberobe",
    "wof:placetype":"locality"
},
  "geometry": {"coordinates":[47.16667,-19.78333],"type":"Point"}
}