{
  "type": "Feature",
  "properties": {
    "gn:admin1_code":"5.0",
    "gn:asciiname":"Sabotsy",
    "gn:country_code":"MG",
    "gn:dem":1160,
    "gn:feature_class":"P",
    "gn:feature_code":"PPL",
    "gn:name":"Sabotsy",
    "gn:population":0,
    "gn:timezone":"Indian/Antananarivo",
    "iso:country":"MG",
    "wof:name":"Sabotsy",
    "wof:placetype":"locality"
},
  "geometry": {"coordinates":[47.05,-18.73333],"type":"Point"}
}