{
  "type": "Feature",
  "properties": {
    "gn:admin1_code":"06",
    "gn:asciiname":"Ambatomifikitsa",
    "gn:country_code":"MG",
    "gn:dem":440,
    "gn:feature_class":"P",
    "gn:feature_code":"PPL",
    "gn:name":"Ambatomifikitsa",
    "gn:population":0,
    "gn:timezone":"Indian/Antananarivo",
    "iso:country":"MG",
    "wof:name":"Ambatomifikitsa",
    "wof:placetype":"locality"
},
  "geometry": {"coordinates":[44.81667,-24.03333],"type":"Point"}
}