{
  "type": "Feature",
  "properties": {
    "gn:admin1_code":"06",
    "gn:asciiname":"Befaitsy",
    "gn:country_code":"MG",
    "gn:dem":46,
    "gn:feature_class":"P",
    "gn:feature_code":"PPL",
    "gn:name":"Befaitsy",
    "gn:population":0,
    "gn:timezone":"Indian/Antananarivo",
    "iso:country":"MG",
    "wof:name":"Befaitsy",
    "wof:placetype":"locality"
},
  "geometry": {"coordinates":[46.25,-24.88333],"type":"Point"}
}