{
  "type": "Feature",
  "properties": {
    "gn:admin1_code":"05",
    "gn:asciiname":"Mangasoavina",
    "gn:country_code":"MG",
    "gn:dem":1127,
    "gn:feature_class":"P",
    "gn:feature_code":"PPL",
    "gn:name":"Mangasoavina",
    "gn:population":0,
    "gn:timezone":"Indian/Antananarivo",
    "iso:country":"MG",
    "wof:name":"Mangasoavina",
    "wof:placetype":"locality"
},
  "geometry": {"coordinates":[47.03333,-18.16667],"type":"Point"}
}