{
  "type": "Feature",
  "properties": {
    "gn:admin1_code":"6.0",
    "gn:asciiname":"Vohipotsy",
    "gn:country_code":"MG",
    "gn:dem":399,
    "gn:feature_class":"P",
    "gn:feature_code":"PPL",
    "gn:name":"Vohipotsy",
    "gn:population":0,
    "gn:timezone":"Indian/Antananarivo",
    "iso:country":"MG",
    "wof:name":"Vohipotsy",
    "wof:placetype":"locality"
},
  "geometry": {"coordinates":[44.71667,-23.91667],"type":"Point"}
}