{
  "type": "Feature",
  "properties": {
    "gn:admin1_code":"06",
    "gn:asciiname":"Laparoy",
    "gn:cc2":"MG",
    "gn:country_code":"MG",
    "gn:dem":196,
    "gn:feature_class":"P",
    "gn:feature_code":"PPL",
    "gn:name":"Laparoy",
    "gn:population":0,
    "gn:timezone":"Indian/Antananarivo",
    "iso:country":"MG",
    "name:und_x_variant":[
        "Lapahoy",
        "Lapaproy",
        "Laparoy"
    ],
    "wof:name":"Laparoy",
    "wof:placetype":"locality"
},
  "geometry": {"coordinates":[45.73333,-25.05],"type":"Point"}
}