{
  "type": "Feature",
  "properties": {
    "gn:admin1_code":"03",
    "gn:asciiname":"Ankobakobaka",
    "gn:country_code":"MG",
    "gn:dem":219,
    "gn:feature_class":"P",
    "gn:feature_code":"PPL",
    "gn:name":"Ankobakobaka",
    "gn:population":0,
    "gn:timezone":"Indian/Antananarivo",
    "iso:country":"MG",
    "wof:name":"Ankobakobaka",
    "wof:placetype":"locality"
},
  "geometry": {"coordinates":[48.28333,-15.13333],"type":"Point"}
}