{
  "type": "Feature",
  "properties": {
    "gn:admin1_code":"03",
    "gn:asciiname":"Kimanambolo",
    "gn:country_code":"MG",
    "gn:dem":37,
    "gn:feature_class":"P",
    "gn:feature_code":"PPL",
    "gn:name":"Kimanambolo",
    "gn:population":0,
    "gn:timezone":"Indian/Antananarivo",
    "iso:country":"MG",
    "wof:name":"Kimanambolo",
    "wof:placetype":"locality"
},
  "geometry": {"coordinates":[44.21667,-17.43333],"type":"Point"}
}