{
  "type": "Feature",
  "properties": {
    "gn:admin1_code":"03",
    "gn:asciiname":"Andampy",
    "gn:cc2":"MG",
    "gn:country_code":"MG",
    "gn:dem":7,
    "gn:feature_class":"P",
    "gn:feature_code":"PPL",
    "gn:name":"Andampy",
    "gn:population":0,
    "gn:timezone":"Indian/Antananarivo",
    "iso:country":"MG",
    "name:und_x_variant":[
        "Andapy",
        "Andampy"
    ],
    "wof:name":"Andampy",
    "wof:placetype":"locality"
},
  "geometry": {"coordinates":[48.05,-14.66667],"type":"Point"}
}