{
  "type": "Feature",
  "properties": {
    "gn:admin1_code":"5.0",
    "gn:asciiname":"Soamahamanina",
    "gn:cc2":"MG",
    "gn:country_code":"MG",
    "gn:dem":1346,
    "gn:feature_class":"P",
    "gn:feature_code":"PPL",
    "gn:name":"Soamahamanina",
    "gn:population":0,
    "gn:timezone":"Indian/Antananarivo",
    "iso:country":"MG",
    "name:fra_x_preferred":[
        "Soamahamanina"
    ],
    "name:ita_x_preferred":[
        "Soamahamanina"
    ],
    "name:mlg_x_preferred":[
        "Soamahamanina"
    ],
    "name:nld_x_preferred":[
        "Soamahamanina"
    ],
    "name:und_x_variant":[
        "Soamhamanina",
        "Soamahamanina"
    ],
    "wof:name":"Soamahamanina",
    "wof:placetype":"locality"
},
  "geometry": {"coordinates":[47.01667,-18.98333],"type":"Point"}
}