{
  "type": "Feature",
  "properties": {
    "gn:admin1_code":"01",
    "gn:asciiname":"Ampijoroana",
    "gn:country_code":"MG",
    "gn:dem":280,
    "gn:feature_class":"P",
    "gn:feature_code":"PPL",
    "gn:name":"Ampijoroana",
    "gn:population":0,
    "gn:timezone":"Indian/Antananarivo",
    "iso:country":"MG",
    "wof:name":"Ampijoroana",
    "wof:placetype":"locality"
},
  "geometry": {"coordinates":[49.65,-13.65],"type":"Point"}
}