{
  "type": "Feature",
  "properties": {
    "gn:admin1_code":"06",
    "gn:asciiname":"Enanafia",
    "gn:country_code":"MG",
    "gn:dem":225,
    "gn:feature_class":"P",
    "gn:feature_code":"PPL",
    "gn:name":"Enanafia",
    "gn:population":0,
    "gn:timezone":"Indian/Antananarivo",
    "iso:country":"MG",
    "wof:name":"Enanafia",
    "wof:placetype":"locality"
},
  "geometry": {"coordinates":[47.13333,-24.45],"type":"Point"}
}