{
  "type": "Feature",
  "properties": {
    "gn:admin1_code":"04",
    "gn:asciiname":"Rantabe",
    "gn:cc2":"MG",
    "gn:country_code":"MG",
    "gn:dem":6,
    "gn:feature_class":"P",
    "gn:feature_code":"PPL",
    "gn:name":"Rantabe",
    "gn:population":0,
    "gn:timezone":"Indian/Antananarivo",
    "iso:country":"MG",
    "name:fra_x_preferred":[
        "Rantabe"
    ],
    "name:ita_x_preferred":[
        "Rantabe"
    ],
    "name:mlg_x_preferred":[
        "Rantabe"
    ],
    "name:nld_x_preferred":[
        "Rantabe"
    ],
    "name:und_x_variant":[
        "Rantambe",
        "Rantabe"
    ],
    "wof:name":"Rantabe",
    "wof:placetype":"locality"
},
  "geometry": {"coordinates":[49.65,-16.86667000000001],"type":"Point"}
}