{
  "type": "Feature",
  "properties": {
    "gn:admin1_code":"03",
    "gn:asciiname":"Analila",
    "gn:country_code":"MG",
    "gn:dem":1155,
    "gn:feature_class":"P",
    "gn:feature_code":"PPL",
    "gn:name":"Analila",
    "gn:population":0,
    "gn:timezone":"Indian/Antananarivo",
    "iso:country":"MG",
    "wof:name":"Analila",
    "wof:placetype":"locality"
},
  "geometry": {"coordinates":[49.05,-14.45],"type":"Point"}
}