{
  "type": "Feature",
  "properties": {
    "gn:admin1_code":"6.0",
    "gn:asciiname":"Tsianaloka",
    "gn:cc2":"MG",
    "gn:country_code":"MG",
    "gn:dem":725,
    "gn:feature_class":"P",
    "gn:feature_code":"PPL",
    "gn:name":"Tsianaloka",
    "gn:population":0,
    "gn:timezone":"Indian/Antananarivo",
    "iso:country":"MG",
    "name:und_x_variant":[
        "Tsianalloka",
        "Tsianaloka"
    ],
    "wof:name":"Tsianaloka",
    "wof:placetype":"locality"
},
  "geometry": {"coordinates":[44.93333,-22.71667],"type":"Point"}
}