{
  "type": "Feature",
  "properties": {
    "gn:admin1_code":"5.0",
    "gn:asciiname":"Tsiandramana",
    "gn:country_code":"MG",
    "gn:dem":1618,
    "gn:feature_class":"P",
    "gn:feature_code":"PPL",
    "gn:name":"Tsiandramana",
    "gn:population":0,
    "gn:timezone":"Indian/Antananarivo",
    "iso:country":"MG",
    "wof:name":"Tsiandramana",
    "wof:placetype":"locality"
},
  "geometry": {"coordinates":[46.91667,-19.35],"type":"Point"}
}