{
  "type": "Feature",
  "properties": {
    "gn:admin1_code":"02",
    "gn:asciiname":"Antanatanana",
    "gn:country_code":"MG",
    "gn:dem":4,
    "gn:feature_class":"P",
    "gn:feature_code":"PPL",
    "gn:name":"Antanatanana",
    "gn:population":0,
    "gn:timezone":"Indian/Antananarivo",
    "iso:country":"MG",
    "wof:name":"Antanatanana",
    "wof:placetype":"locality"
},
  "geometry": {"coordinates":[47.56667,-23.53333],"type":"Point"}
}