{
  "type": "Feature",
  "properties": {
    "gn:admin1_code":"05",
    "gn:asciiname":"Concession de Balman",
    "gn:country_code":"MG",
    "gn:dem":1041,
    "gn:feature_class":"P",
    "gn:feature_code":"PPL",
    "gn:name":"Concession de Balman",
    "gn:population":0,
    "gn:timezone":"Indian/Antananarivo",
    "iso:country":"MG",
    "wof:name":"Concession de Balman",
    "wof:placetype":"locality"
},
  "geometry": {"coordinates":[46.66667,-18.95],"type":"Point"}
}