{
  "type": "Feature",
  "properties": {
    "gn:admin1_code":"5.0",
    "gn:asciiname":"Soavimanjaka",
    "gn:country_code":"MG",
    "gn:dem":1131,
    "gn:feature_class":"P",
    "gn:feature_code":"PPL",
    "gn:name":"Soavimanjaka",
    "gn:population":0,
    "gn:timezone":"Indian/Antananarivo",
    "iso:country":"MG",
    "wof:name":"Soavimanjaka",
    "wof:placetype":"locality"
},
  "geometry": {"coordinates":[46.68333,-18.35],"type":"Point"}
}