{
  "type": "Feature",
  "properties": {
    "gn:admin1_code":"03",
    "gn:asciiname":"Anosikapika",
    "gn:country_code":"MG",
    "gn:dem":5,
    "gn:feature_class":"P",
    "gn:feature_code":"PPL",
    "gn:name":"Anosikapika",
    "gn:population":0,
    "gn:timezone":"Indian/Antananarivo",
    "iso:country":"MG",
    "wof:name":"Anosikapika",
    "wof:placetype":"locality"
},
  "geometry": {"coordinates":[46.66667,-16.15],"type":"Point"}
}