{
  "type": "Feature",
  "properties": {
    "gn:admin1_code":"06",
    "gn:asciiname":"Benono",
    "gn:cc2":"MG",
    "gn:country_code":"MG",
    "gn:dem":604,
    "gn:feature_class":"P",
    "gn:feature_code":"PPL",
    "gn:name":"Benono",
    "gn:population":0,
    "gn:timezone":"Indian/Antananarivo",
    "iso:country":"MG",
    "name:und_x_variant":[
        "Beronono",
        "Benono"
    ],
    "wof:name":"Benono",
    "wof:placetype":"locality"
},
  "geometry": {"coordinates":[45.63333,-23.48333],"type":"Point"}
}