{
  "type": "Feature",
  "properties": {
    "gn:admin1_code":"04",
    "gn:asciiname":"Antsirakaomby",
    "gn:country_code":"MG",
    "gn:dem":274,
    "gn:feature_class":"P",
    "gn:feature_code":"PPL",
    "gn:name":"Antsirakaomby",
    "gn:population":0,
    "gn:timezone":"Indian/Antananarivo",
    "iso:country":"MG",
    "wof:name":"Antsirakaomby",
    "wof:placetype":"locality"
},
  "geometry": {"coordinates":[48.66667,-18.81667],"type":"Point"}
}