{
  "type": "Feature",
  "properties": {
    "gn:admin1_code":"04",
    "gn:asciiname":"Maroleotra",
    "gn:country_code":"MG",
    "gn:dem":429,
    "gn:feature_class":"P",
    "gn:feature_code":"PPL",
    "gn:name":"Maroleotra",
    "gn:population":0,
    "gn:timezone":"Indian/Antananarivo",
    "iso:country":"MG",
    "wof:name":"Maroleotra",
    "wof:placetype":"locality"
},
  "geometry": {"coordinates":[48.13333,-20.05],"type":"Point"}
}