{
  "type": "Feature",
  "properties": {
    "gn:admin1_code":"05",
    "gn:asciiname":"Ambatoharanana",
    "gn:country_code":"MG",
    "gn:dem":1026,
    "gn:feature_class":"P",
    "gn:feature_code":"PPL",
    "gn:name":"Ambatoharanana",
    "gn:population":0,
    "gn:timezone":"Indian/Antananarivo",
    "iso:country":"MG",
    "wof:name":"Ambatoharanana",
    "wof:placetype":"locality"
},
  "geometry": {"coordinates":[47.48333,-18.45],"type":"Point"}
}