{
  "type": "Feature",
  "properties": {
    "gn:admin1_code":"03",
    "gn:asciiname":"Ambodimandresy",
    "gn:country_code":"MG",
    "gn:dem":774,
    "gn:feature_class":"P",
    "gn:feature_code":"PPL",
    "gn:name":"Ambodimandresy",
    "gn:population":0,
    "gn:timezone":"Indian/Antananarivo",
    "iso:country":"MG",
    "wof:name":"Ambodimandresy",
    "wof:placetype":"locality"
},
  "geometry": {"coordinates":[48.95,-14.85],"type":"Point"}
}