{
  "type": "Feature",
  "properties": {
    "gn:admin1_code":"5.0",
    "gn:asciiname":"Sahanivotry-Manandona",
    "gn:country_code":"MG",
    "gn:dem":1381,
    "gn:feature_class":"P",
    "gn:feature_code":"PPL",
    "gn:name":"Sahanivotry-Manandona",
    "gn:population":0,
    "gn:timezone":"Indian/Antananarivo",
    "iso:country":"MG",
    "wof:name":"Sahanivotry-Manandona",
    "wof:placetype":"locality"
},
  "geometry": {"coordinates":[47.08333,-20.11667000000001],"type":"Point"}
}