{
  "type": "Feature",
  "properties": {
    "gn:admin1_code":"5.0",
    "gn:asciiname":"Tsaramasoandro",
    "gn:country_code":"MG",
    "gn:dem":1252,
    "gn:feature_class":"P",
    "gn:feature_code":"PPL",
    "gn:name":"Tsaramasoandro",
    "gn:population":0,
    "gn:timezone":"Indian/Antananarivo",
    "iso:country":"MG",
    "wof:name":"Tsaramasoandro",
    "wof:placetype":"locality"
},
  "geometry": {"coordinates":[47.61667,-18.65],"type":"Point"}
}