{
  "type": "Feature",
  "properties": {
    "gn:admin1_code":"03",
    "gn:asciiname":"Ambodivato",
    "gn:cc2":"MG",
    "gn:country_code":"MG",
    "gn:dem":729,
    "gn:feature_class":"P",
    "gn:feature_code":"PPL",
    "gn:name":"Ambodivato",
    "gn:population":0,
    "gn:timezone":"Indian/Antananarivo",
    "iso:country":"MG",
    "name:und_x_variant":[
        "Yodivalo",
        "Vodivato",
        "Ambodivato"
    ],
    "wof:name":"Ambodivato",
    "wof:placetype":"locality"
},
  "geometry": {"coordinates":[48.98333,-16.35],"type":"Point"}
}