{
  "type": "Feature",
  "properties": {
    "gn:admin1_code":"6.0",
    "gn:asciiname":"Tanambao",
    "gn:country_code":"MG",
    "gn:dem":161,
    "gn:feature_class":"P",
    "gn:feature_code":"PPL",
    "gn:name":"Tanambao",
    "gn:population":0,
    "gn:timezone":"Indian/Antananarivo",
    "iso:country":"MG",
    "wof:name":"Tanambao",
    "wof:placetype":"locality"
},
  "geometry": {"coordinates":[44.51667,-23.41667],"type":"Point"}
}