{
  "type": "Feature",
  "properties": {
    "gn:admin1_code":"03",
    "gn:asciiname":"Mozambika",
    "gn:cc2":"MG",
    "gn:country_code":"MG",
    "gn:dem":-9999,
    "gn:feature_class":"P",
    "gn:feature_code":"PPL",
    "gn:name":"Mozambika",
    "gn:population":0,
    "gn:timezone":"Indian/Antananarivo",
    "iso:country":"MG",
    "name:und_x_variant":[
        "Masombiky",
        "Mozambika"
    ],
    "wof:name":"Mozambika",
    "wof:placetype":"locality"
},
  "geometry": {"coordinates":[44.23333,-18.96667],"type":"Point"}
}