{
  "type": "Feature",
  "properties": {
    "gn:admin1_code":"03",
    "gn:asciiname":"Ampany",
    "gn:country_code":"MG",
    "gn:dem":258,
    "gn:feature_class":"P",
    "gn:feature_code":"PPL",
    "gn:name":"Ampany",
    "gn:population":0,
    "gn:timezone":"Indian/Antananarivo",
    "iso:country":"MG",
    "wof:name":"Ampany",
    "wof:placetype":"locality"
},
  "geometry": {"coordinates":[44.86667,-18.26667],"type":"Point"}
}