{
  "type": "Feature",
  "properties": {
    "gn:admin1_code":"06",
    "gn:asciiname":"Andolobory",
    "gn:country_code":"MG",
    "gn:dem":298,
    "gn:feature_class":"P",
    "gn:feature_code":"PPL",
    "gn:name":"Andolobory",
    "gn:population":0,
    "gn:timezone":"Indian/Antananarivo",
    "iso:country":"MG",
    "wof:name":"Andolobory",
    "wof:placetype":"locality"
},
  "geometry": {"coordinates":[45.21667,-24.66667],"type":"Point"}
}