{
  "type": "Feature",
  "properties": {
    "gn:admin1_code":"03",
    "gn:asciiname":"Ambohibe Atsinanana",
    "gn:cc2":"MG",
    "gn:country_code":"MG",
    "gn:dem":98,
    "gn:feature_class":"P",
    "gn:feature_code":"PPL",
    "gn:name":"Ambohibe Atsinanana",
    "gn:population":0,
    "gn:timezone":"Indian/Antananarivo",
    "iso:country":"MG",
    "name:und_x_variant":[
        "Ambahibe Sud",
        "Ambohibe Atsinanana"
    ],
    "wof:name":"Ambohibe Atsinanana",
    "wof:placetype":"locality"
},
  "geometry": {"coordinates":[47.68333,-15.71667],"type":"Point"}
}