{
  "type": "Feature",
  "properties": {
    "gn:admin1_code":"06",
    "gn:asciiname":"Mandonariva",
    "gn:country_code":"MG",
    "gn:dem":476,
    "gn:feature_class":"P",
    "gn:feature_code":"PPL",
    "gn:name":"Mandonariva",
    "gn:population":0,
    "gn:timezone":"Indian/Antananarivo",
    "iso:country":"MG",
    "wof:name":"Mandonariva",
    "wof:placetype":"locality"
},
  "geometry": {"coordinates":[45.23333,-21.33333],"type":"Point"}
}