{
  "type": "Feature",
  "properties": {
    "gn:admin1_code":"6.0",
    "gn:asciiname":"Sakaomby",
    "gn:country_code":"MG",
    "gn:dem":330,
    "gn:feature_class":"P",
    "gn:feature_code":"PPL",
    "gn:name":"Sakaomby",
    "gn:population":0,
    "gn:timezone":"Indian/Antananarivo",
    "iso:country":"MG",
    "wof:name":"Sakaomby",
    "wof:placetype":"locality"
},
  "geometry": {"coordinates":[45.63333,-24.88333],"type":"Point"}
}