{
  "type": "Feature",
  "properties": {
    "gn:admin1_code":"01",
    "gn:asciiname":"Antananitapy",
    "gn:country_code":"MG",
    "gn:dem":43,
    "gn:feature_class":"P",
    "gn:feature_code":"PPL",
    "gn:name":"Antananitapy",
    "gn:population":0,
    "gn:timezone":"Indian/Antananarivo",
    "iso:country":"MG",
    "wof:name":"Antananitapy",
    "wof:placetype":"locality"
},
  "geometry": {"coordinates":[49.08333,-13.23333],"type":"Point"}
}