{
  "type": "Feature",
  "properties": {
    "gn:admin1_code":"6.0",
    "gn:asciiname":"Sarodrano",
    "gn:country_code":"MG",
    "gn:dem":220,
    "gn:feature_class":"P",
    "gn:feature_code":"PPL",
    "gn:name":"Sarodrano",
    "gn:population":0,
    "gn:timezone":"Indian/Antananarivo",
    "iso:country":"MG",
    "wof:name":"Sarodrano",
    "wof:placetype":"locality"
},
  "geometry": {"coordinates":[44.55,-23.83333],"type":"Point"}
}