{
  "type": "Feature",
  "properties": {
    "gn:admin1_code":"6.0",
    "gn:asciiname":"Tangioky",
    "gn:country_code":"MG",
    "gn:dem":114,
    "gn:feature_class":"P",
    "gn:feature_code":"PPL",
    "gn:name":"Tangioky",
    "gn:population":0,
    "gn:timezone":"Indian/Antananarivo",
    "iso:country":"MG",
    "wof:name":"Tangioky",
    "wof:placetype":"locality"
},
  "geometry": {"coordinates":[45.38333,-25.16667],"type":"Point"}
}