{
  "type": "Feature",
  "properties": {
    "gn:admin1_code":"04",
    "gn:asciiname":"Ambohimilanja",
    "gn:country_code":"MG",
    "gn:dem":604,
    "gn:feature_class":"P",
    "gn:feature_code":"PPL",
    "gn:name":"Ambohimilanja",
    "gn:population":0,
    "gn:timezone":"Indian/Antananarivo",
    "iso:country":"MG",
    "wof:name":"Ambohimilanja",
    "wof:placetype":"locality"
},
  "geometry": {"coordinates":[47.98333,-19.93333],"type":"Point"}
}