{
  "type": "Feature",
  "properties": {
    "gn:admin1_code":"02",
    "gn:asciiname":"Ampasimalemy",
    "gn:country_code":"MG",
    "gn:dem":253,
    "gn:feature_class":"P",
    "gn:feature_code":"PPL",
    "gn:name":"Ampasimalemy",
    "gn:population":0,
    "gn:timezone":"Indian/Antananarivo",
    "iso:country":"MG",
    "name:azb_x_preferred":[
        "\u0627\u0645\u067e\u0627\u0633\u06cc\u0645\u0627\u0644\u0645\u06cc"
    ],
    "name:fas_x_preferred":[
        "\u0627\u0645\u067e\u0627\u0633\u06cc\u0645\u0627\u0644\u0645\u06cc"
    ],
    "name:fra_x_preferred":[
        "Ampasimalemy"
    ],
    "name:ita_x_preferred":[
        "Ampasimalemy"
    ],
    "name:mlg_x_preferred":[
        "Ampasimalemy"
    ],
    "name:nld_x_preferred":[
        "Ampasimalemy"
    ],
    "wof:name":"Ampasimalemy",
    "wof:placetype":"locality"
},
  "geometry": {"coordinates":[47.48333,-21.95],"type":"Point"}
}