{
  "type": "Feature",
  "properties": {
    "gn:admin1_code":"03",
    "gn:asciiname":"Ambohimanjaka Atsimo",
    "gn:cc2":"MG",
    "gn:country_code":"MG",
    "gn:dem":685,
    "gn:feature_class":"P",
    "gn:feature_code":"PPL",
    "gn:name":"Ambohimanjaka Atsimo",
    "gn:population":0,
    "gn:timezone":"Indian/Antananarivo",
    "iso:country":"MG",
    "name:und_x_variant":[
        "Ambohimanjaka-Sud",
        "Ambohimanjaka Atsimo"
    ],
    "wof:name":"Ambohimanjaka Atsimo",
    "wof:placetype":"locality"
},
  "geometry": {"coordinates":[47.35,-17.73333],"type":"Point"}
}