{
  "type": "Feature",
  "properties": {
    "gn:admin1_code":"06",
    "gn:asciiname":"Bevato",
    "gn:country_code":"MG",
    "gn:dem":375,
    "gn:feature_class":"P",
    "gn:feature_code":"PPL",
    "gn:name":"Bevato",
    "gn:population":0,
    "gn:timezone":"Indian/Antananarivo",
    "iso:country":"MG",
    "wof:name":"Bevato",
    "wof:placetype":"locality"
},
  "geometry": {"coordinates":[44.61667,-23.93333],"type":"Point"}
}