{
  "type": "Feature",
  "properties": {
    "gn:admin1_code":"03",
    "gn:asciiname":"Anamboriana",
    "gn:country_code":"MG",
    "gn:dem":966,
    "gn:feature_class":"P",
    "gn:feature_code":"PPL",
    "gn:name":"Anamboriana",
    "gn:population":0,
    "gn:timezone":"Indian/Antananarivo",
    "iso:country":"MG",
    "wof:name":"Anamboriana",
    "wof:placetype":"locality"
},
  "geometry": {"coordinates":[49.11667,-14.58333],"type":"Point"}
}