{
  "type": "Feature",
  "properties": {
    "gn:admin1_code":"04",
    "gn:asciiname":"Amboakarivo",
    "gn:country_code":"MG",
    "gn:dem":6,
    "gn:feature_class":"P",
    "gn:feature_code":"PPL",
    "gn:name":"Amboakarivo",
    "gn:population":0,
    "gn:timezone":"Indian/Antananarivo",
    "iso:country":"MG",
    "wof:name":"Amboakarivo",
    "wof:placetype":"locality"
},
  "geometry": {"coordinates":[49.35,-18.21667],"type":"Point"}
}