{
  "type": "Feature",
  "properties": {
    "gn:admin1_code":"05",
    "gn:asciiname":"Andrembesoa",
    "gn:country_code":"MG",
    "gn:dem":1145,
    "gn:feature_class":"P",
    "gn:feature_code":"PPL",
    "gn:name":"Andrembesoa",
    "gn:population":0,
    "gn:timezone":"Indian/Antananarivo",
    "iso:country":"MG",
    "name:bul_x_preferred":[
        "\u0410\u043d\u0434\u0436\u0435\u043c\u0431\u0435\u0441\u0443\u0430"
    ],
    "name:fra_x_preferred":[
        "Andrembesoa"
    ],
    "name:ita_x_preferred":[
        "Andrembesoa"
    ],
    "name:mlg_x_preferred":[
        "Andrembesoa"
    ],
    "name:nld_x_preferred":[
        "Andrembesoa"
    ],
    "name:pol_x_preferred":[
        "Andrembesoa"
    ],
    "wof:name":"Andrembesoa",
    "wof:placetype":"locality"
},
  "geometry": {"coordinates":[46.65,-20.15],"type":"Point"}
}