{
  "type": "Feature",
  "properties": {
    "gn:admin1_code":"05",
    "gn:asciiname":"Anosimanjaka",
    "gn:country_code":"MG",
    "gn:dem":927,
    "gn:feature_class":"P",
    "gn:feature_code":"PPL",
    "gn:name":"Anosimanjaka",
    "gn:population":0,
    "gn:timezone":"Indian/Antananarivo",
    "iso:country":"MG",
    "wof:name":"Anosimanjaka",
    "wof:placetype":"locality"
},
  "geometry": {"coordinates":[47.61667,-18.26667],"type":"Point"}
}