{
  "type": "Feature",
  "properties": {
    "gn:admin1_code":"02",
    "gn:asciiname":"Marearano",
    "gn:country_code":"MG",
    "gn:dem":557,
    "gn:feature_class":"P",
    "gn:feature_code":"PPL",
    "gn:name":"Marearano",
    "gn:population":0,
    "gn:timezone":"Indian/Antananarivo",
    "iso:country":"MG",
    "wof:name":"Marearano",
    "wof:placetype":"locality"
},
  "geometry": {"coordinates":[46.91667,-22.85],"type":"Point"}
}