{
  "type": "Feature",
  "properties": {
    "gn:admin1_code":"04",
    "gn:asciiname":"Ambinanysahantsanda",
    "gn:country_code":"MG",
    "gn:dem":102,
    "gn:feature_class":"P",
    "gn:feature_code":"PPL",
    "gn:name":"Ambinanysahantsanda",
    "gn:population":0,
    "gn:timezone":"Indian/Antananarivo",
    "iso:country":"MG",
    "wof:name":"Ambinanysahantsanda",
    "wof:placetype":"locality"
},
  "geometry": {"coordinates":[49.06667,-18.28333],"type":"Point"}
}