{
  "type": "Feature",
  "properties": {
    "gn:admin1_code":"06",
    "gn:asciiname":"Befeva",
    "gn:country_code":"MG",
    "gn:dem":73,
    "gn:feature_class":"P",
    "gn:feature_code":"PPL",
    "gn:name":"Befeva",
    "gn:population":0,
    "gn:timezone":"Indian/Antananarivo",
    "iso:country":"MG",
    "wof:name":"Befeva",
    "wof:placetype":"locality"
},
  "geometry": {"coordinates":[45.41667,-19.41667],"type":"Point"}
}