{
  "type": "Feature",
  "properties": {
    "gn:admin1_code":"4.0",
    "gn:asciiname":"Tolandravina",
    "gn:cc2":"MG",
    "gn:country_code":"MG",
    "gn:dem":725,
    "gn:feature_class":"P",
    "gn:feature_code":"PPL",
    "gn:name":"Tolandravina",
    "gn:population":0,
    "gn:timezone":"Indian/Antananarivo",
    "iso:country":"MG",
    "name:und_x_variant":[
        "Antaolandravina",
        "Tolandravina"
    ],
    "wof:name":"Tolandravina",
    "wof:placetype":"locality"
},
  "geometry": {"coordinates":[47.96667,-19.78333],"type":"Point"}
}