{
  "type": "Feature",
  "properties": {
    "gn:admin1_code":"02",
    "gn:asciiname":"Andriamborompotsy",
    "gn:country_code":"MG",
    "gn:dem":1169,
    "gn:feature_class":"P",
    "gn:feature_code":"PPL",
    "gn:name":"Andriamborompotsy",
    "gn:population":0,
    "gn:timezone":"Indian/Antananarivo",
    "iso:country":"MG",
    "wof:name":"Andriamborompotsy",
    "wof:placetype":"locality"
},
  "geometry": {"coordinates":[46.96667,-22.03333],"type":"Point"}
}