{
  "type": "Feature",
  "properties": {
    "gn:admin1_code":"06",
    "gn:asciiname":"Ankarandoha",
    "gn:country_code":"MG",
    "gn:dem":54,
    "gn:feature_class":"P",
    "gn:feature_code":"PPL",
    "gn:name":"Ankarandoha",
    "gn:population":0,
    "gn:timezone":"Indian/Antananarivo",
    "iso:country":"MG",
    "wof:name":"Ankarandoha",
    "wof:placetype":"locality"
},
  "geometry": {"coordinates":[43.73333,-21.88333],"type":"Point"}
}