{
  "type": "Feature",
  "properties": {
    "gn:admin1_code":"05",
    "gn:asciiname":"Andakana",
    "gn:country_code":"MG",
    "gn:dem":802,
    "gn:feature_class":"P",
    "gn:feature_code":"PPL",
    "gn:name":"Andakana",
    "gn:population":0,
    "gn:timezone":"Indian/Antananarivo",
    "iso:country":"MG",
    "name:azb_x_preferred":[
        "\u0627\u0646\u062f\u0627\u06a9\u0627\u0646\u0627"
    ],
    "name:fas_x_preferred":[
        "\u0627\u0646\u062f\u0627\u06a9\u0627\u0646\u0627"
    ],
    "name:fra_x_preferred":[
        "Andakana"
    ],
    "name:ita_x_preferred":[
        "Andakana"
    ],
    "name:mlg_x_preferred":[
        "Andakana"
    ],
    "name:nld_x_preferred":[
        "Andakana"
    ],
    "wof:name":"Andakana",
    "wof:placetype":"locality"
},
  "geometry": {"coordinates":[45.63333,-18.95],"type":"Point"}
}