{
  "type": "Feature",
  "properties": {
    "gn:admin1_code":"05",
    "gn:asciiname":"Ambohijanamasoandro",
    "gn:cc2":"MG",
    "gn:country_code":"MG",
    "gn:dem":1234,
    "gn:feature_class":"P",
    "gn:feature_code":"PPL",
    "gn:name":"Ambohijanamasoandro",
    "gn:population":0,
    "gn:timezone":"Indian/Antananarivo",
    "iso:country":"MG",
    "name:und_x_variant":[
        "Bemasoandro",
        "Ambohijanamasoandro"
    ],
    "wof:name":"Ambohijanamasoandro",
    "wof:placetype":"locality"
},
  "geometry": {"coordinates":[47.18333,-18.86667000000001],"type":"Point"}
}