{
  "type": "Feature",
  "properties": {
    "gn:admin1_code":"06",
    "gn:asciiname":"Ampanihy",
    "gn:country_code":"MG",
    "gn:dem":102,
    "gn:feature_class":"P",
    "gn:feature_code":"PPL",
    "gn:name":"Ampanihy",
    "gn:population":0,
    "gn:timezone":"Indian/Antananarivo",
    "iso:country":"MG",
    "name:azb_x_preferred":[
        "\u0627\u0645\u067e\u0627\u0646\u06cc\u0647\u06cc"
    ],
    "name:ces_x_preferred":[
        "Ampanihy"
    ],
    "name:deu_x_preferred":[
        "Ampanihy"
    ],
    "name:fas_x_preferred":[
        "\u0627\u0645\u067e\u0627\u0646\u06cc\u0647\u06cc"
    ],
    "name:fra_x_preferred":[
        "Ampanihy"
    ],
    "name:jpn_x_preferred":[
        "\u30a2\u30f3\u30d1\u30cb\u30d2"
    ],
    "name:mlg_x_preferred":[
        "Ampanihy"
    ],
    "name:nld_x_preferred":[
        "Ampanihy"
    ],
    "name:nor_x_preferred":[
        "Ampanihy"
    ],
    "name:pol_x_preferred":[
        "Ampanihy"
    ],
    "name:swe_x_preferred":[
        "Ampanihy"
    ],
    "name:zho_x_preferred":[
        "\u5b89\u5e15\u5c3c\u5e0c"
    ],
    "wof:name":"Ampanihy",
    "wof:placetype":"locality"
},
  "geometry": {"coordinates":[44.88333,-19.93333],"type":"Point"}
}