{
  "type": "Feature",
  "properties": {
    "gn:admin1_code":"02",
    "gn:asciiname":"Anorana",
    "gn:country_code":"MG",
    "gn:dem":1352,
    "gn:feature_class":"P",
    "gn:feature_code":"PPL",
    "gn:name":"Anorana",
    "gn:population":0,
    "gn:timezone":"Indian/Antananarivo",
    "iso:country":"MG",
    "wof:name":"Anorana",
    "wof:placetype":"locality"
},
  "geometry": {"coordinates":[46.75,-20.35],"type":"Point"}
}