{
  "type": "Feature",
  "properties": {
    "gn:admin1_code":"04",
    "gn:asciiname":"Bandabe",
    "gn:country_code":"MG",
    "gn:dem":153,
    "gn:feature_class":"P",
    "gn:feature_code":"PPL",
    "gn:name":"Bandabe",
    "gn:population":0,
    "gn:timezone":"Indian/Antananarivo",
    "iso:country":"MG",
    "wof:name":"Bandabe",
    "wof:placetype":"locality"
},
  "geometry": {"coordinates":[49.68333,-16.26667],"type":"Point"}
}