{
  "type": "Feature",
  "properties": {
    "gn:admin1_code":"3.0",
    "gn:asciiname":"Sasahia",
    "gn:country_code":"MG",
    "gn:dem":37,
    "gn:feature_class":"P",
    "gn:feature_code":"PPL",
    "gn:name":"Sasahia",
    "gn:population":0,
    "gn:timezone":"Indian/Antananarivo",
    "iso:country":"MG",
    "wof:name":"Sasahia",
    "wof:placetype":"locality"
},
  "geometry": {"coordinates":[46.06667,-15.96667],"type":"Point"}
}