{
  "type": "Feature",
  "properties": {
    "gn:admin1_code":"06",
    "gn:asciiname":"Andranomanitsy",
    "gn:country_code":"MG",
    "gn:dem":567,
    "gn:feature_class":"P",
    "gn:feature_code":"PPL",
    "gn:name":"Andranomanitsy",
    "gn:population":0,
    "gn:timezone":"Indian/Antananarivo",
    "iso:country":"MG",
    "wof:name":"Andranomanitsy",
    "wof:placetype":"locality"
},
  "geometry": {"coordinates":[45.33333,-23.63333],"type":"Point"}
}