{
  "type": "Feature",
  "properties": {
    "gn:admin1_code":"02",
    "gn:asciiname":"Ivandrika",
    "gn:cc2":"MG",
    "gn:country_code":"MG",
    "gn:dem":3,
    "gn:feature_class":"P",
    "gn:feature_code":"PPL",
    "gn:name":"Ivandrika",
    "gn:population":0,
    "gn:timezone":"Indian/Antananarivo",
    "iso:country":"MG",
    "name:und_x_variant":[
        "Vandrika",
        "Ivandrika"
    ],
    "wof:name":"Ivandrika",
    "wof:placetype":"locality"
},
  "geometry": {"coordinates":[47.73333,-22.86667000000001],"type":"Point"}
}