{
  "type": "Feature",
  "properties": {
    "gn:admin1_code":"02",
    "gn:asciiname":"Imalaza",
    "gn:country_code":"MG",
    "gn:dem":795,
    "gn:feature_class":"P",
    "gn:feature_code":"PPL",
    "gn:name":"Imalaza",
    "gn:population":0,
    "gn:timezone":"Indian/Antananarivo",
    "iso:country":"MG",
    "wof:name":"Imalaza",
    "wof:placetype":"locality"
},
  "geometry": {"coordinates":[46.48333,-20.86667000000001],"type":"Point"}
}