{
  "type": "Feature",
  "properties": {
    "gn:admin1_code":"06",
    "gn:asciiname":"Ambalapaiso",
    "gn:cc2":"MG",
    "gn:country_code":"MG",
    "gn:dem":23,
    "gn:feature_class":"P",
    "gn:feature_code":"PPL",
    "gn:name":"Ambalapaiso",
    "gn:population":0,
    "gn:timezone":"Indian/Antananarivo",
    "iso:country":"MG",
    "name:und_x_variant":[
        "Ambalapiso",
        "Ambalapaiso"
    ],
    "wof:name":"Ambalapaiso",
    "wof:placetype":"locality"
},
  "geometry": {"coordinates":[47.21667,-24.11667000000001],"type":"Point"}
}