{
  "type": "Feature",
  "properties": {
    "gn:admin1_code":"06",
    "gn:asciiname":"Jafaro",
    "gn:country_code":"MG",
    "gn:dem":219,
    "gn:feature_class":"P",
    "gn:feature_code":"PPL",
    "gn:name":"Jafaro",
    "gn:population":0,
    "gn:timezone":"Indian/Antananarivo",
    "iso:country":"MG",
    "name:fra_x_preferred":[
        "Jafaro"
    ],
    "name:ita_x_preferred":[
        "Jafaro"
    ],
    "name:mlg_x_preferred":[
        "Jafaro"
    ],
    "name:nld_x_preferred":[
        "Jafaro"
    ],
    "name:urd_x_preferred":[
        "\u062c\u0639\u0641\u0631\u0648"
    ],
    "wof:name":"Jafaro",
    "wof:placetype":"locality"
},
  "geometry": {"coordinates":[45.51667,-24.91667],"type":"Point"}
}