{
  "type": "Feature",
  "properties": {
    "gn:admin1_code":"03",
    "gn:asciiname":"Andranomena",
    "gn:country_code":"MG",
    "gn:dem":155,
    "gn:feature_class":"P",
    "gn:feature_code":"PPL",
    "gn:name":"Andranomena",
    "gn:population":0,
    "gn:timezone":"Indian/Antananarivo",
    "iso:country":"MG",
    "wof:name":"Andranomena",
    "wof:placetype":"locality"
},
  "geometry": {"coordinates":[47.46667,-15.65],"type":"Point"}
}