{
  "type": "Feature",
  "properties": {
    "gn:admin1_code":"2.0",
    "gn:asciiname":"Tsiombivositra",
    "gn:country_code":"MG",
    "gn:dem":93,
    "gn:feature_class":"P",
    "gn:feature_code":"PPL",
    "gn:name":"Tsiombivositra",
    "gn:population":0,
    "gn:timezone":"Indian/Antananarivo",
    "iso:country":"MG",
    "wof:name":"Tsiombivositra",
    "wof:placetype":"locality"
},
  "geometry": {"coordinates":[47.85,-21.55],"type":"Point"}
}