{
  "type": "Feature",
  "properties": {
    "gn:admin1_code":"05",
    "gn:asciiname":"Ankazofotsy",
    "gn:country_code":"MG",
    "gn:dem":1268,
    "gn:feature_class":"P",
    "gn:feature_code":"PPL",
    "gn:name":"Ankazofotsy",
    "gn:population":0,
    "gn:timezone":"Indian/Antananarivo",
    "iso:country":"MG",
    "wof:name":"Ankazofotsy",
    "wof:placetype":"locality"
},
  "geometry": {"coordinates":[47.91667,-18.86667000000001],"type":"Point"}
}