{
  "type": "Feature",
  "properties": {
    "gn:admin1_code":"3.0",
    "gn:asciiname":"Sarotravoaka",
    "gn:country_code":"MG",
    "gn:dem":50,
    "gn:feature_class":"P",
    "gn:feature_code":"PPL",
    "gn:name":"Sarotravoaka",
    "gn:population":0,
    "gn:timezone":"Indian/Antananarivo",
    "iso:country":"MG",
    "wof:name":"Sarotravoaka",
    "wof:placetype":"locality"
},
  "geometry": {"coordinates":[44.56667,-17.06667],"type":"Point"}
}