{
  "type": "Feature",
  "properties": {
    "gn:admin1_code":"02",
    "gn:asciiname":"Manolotrony",
    "gn:country_code":"MG",
    "gn:dem":970,
    "gn:feature_class":"P",
    "gn:feature_code":"PPL",
    "gn:name":"Manolotrony",
    "gn:population":0,
    "gn:timezone":"Indian/Antananarivo",
    "iso:country":"MG",
    "wof:name":"Manolotrony",
    "wof:placetype":"locality"
},
  "geometry": {"coordinates":[46.86667,-21.01667],"type":"Point"}
}