{
  "type": "Feature",
  "properties": {
    "gn:admin1_code":"06",
    "gn:asciiname":"Ambatovita",
    "gn:country_code":"MG",
    "gn:dem":822,
    "gn:feature_class":"P",
    "gn:feature_code":"PPL",
    "gn:name":"Ambatovita",
    "gn:population":0,
    "gn:timezone":"Indian/Antananarivo",
    "iso:country":"MG",
    "wof:name":"Ambatovita",
    "wof:placetype":"locality"
},
  "geometry": {"coordinates":[46.08333,-23.25],"type":"Point"}
}