{
  "type": "Feature",
  "properties": {
    "gn:admin1_code":"4.0",
    "gn:asciiname":"Tombohantrova",
    "gn:cc2":"MG",
    "gn:country_code":"MG",
    "gn:dem":881,
    "gn:feature_class":"P",
    "gn:feature_code":"PPL",
    "gn:name":"Tombohantrova",
    "gn:population":0,
    "gn:timezone":"Indian/Antananarivo",
    "iso:country":"MG",
    "name:und_x_variant":[
        "Tomboatrova",
        "Tombohantrova"
    ],
    "wof:name":"Tombohantrova",
    "wof:placetype":"locality"
},
  "geometry": {"coordinates":[47.78333,-20.26667],"type":"Point"}
}