{
  "type": "Feature",
  "properties": {
    "gn:admin1_code":"03",
    "gn:asciiname":"Ambodipaiso",
    "gn:country_code":"MG",
    "gn:dem":1142,
    "gn:feature_class":"P",
    "gn:feature_code":"PPL",
    "gn:name":"Ambodipaiso",
    "gn:population":0,
    "gn:timezone":"Indian/Antananarivo",
    "iso:country":"MG",
    "wof:name":"Ambodipaiso",
    "wof:placetype":"locality"
},
  "geometry": {"coordinates":[49.03333,-14.38333],"type":"Point"}
}