{
  "type": "Feature",
  "properties": {
    "gn:admin1_code":"02",
    "gn:asciiname":"Atahateja",
    "gn:country_code":"MG",
    "gn:dem":1147,
    "gn:feature_class":"P",
    "gn:feature_code":"PPL",
    "gn:name":"Atahateja",
    "gn:population":0,
    "gn:timezone":"Indian/Antananarivo",
    "iso:country":"MG",
    "wof:name":"Atahateja",
    "wof:placetype":"locality"
},
  "geometry": {"coordinates":[47.35,-21.58333],"type":"Point"}
}