{
  "type": "Feature",
  "properties": {
    "gn:admin1_code":"2.0",
    "gn:asciiname":"Soavarina",
    "gn:cc2":"MG",
    "gn:country_code":"MG",
    "gn:dem":802,
    "gn:feature_class":"P",
    "gn:feature_code":"PPL",
    "gn:name":"Soavarina",
    "gn:population":0,
    "gn:timezone":"Indian/Antananarivo",
    "iso:country":"MG",
    "name:und_x_variant":[
        "Soavariana",
        "Soavarina"
    ],
    "wof:name":"Soavarina",
    "wof:placetype":"locality"
},
  "geometry": {"coordinates":[46.96667,-23.66667],"type":"Point"}
}