{
  "type": "Feature",
  "properties": {
    "gn:admin1_code":"06",
    "gn:asciiname":"Ampilafily",
    "gn:cc2":"MG",
    "gn:country_code":"MG",
    "gn:dem":361,
    "gn:feature_class":"P",
    "gn:feature_code":"PPL",
    "gn:name":"Ampilafily",
    "gn:population":0,
    "gn:timezone":"Indian/Antananarivo",
    "iso:country":"MG",
    "name:und_x_variant":[
        "Ampilofily",
        "Ampilafily"
    ],
    "wof:name":"Ampilafily",
    "wof:placetype":"locality"
},
  "geometry": {"coordinates":[45.35,-24.33333],"type":"Point"}
}