{
  "type": "Feature",
  "properties": {
    "gn:admin1_code":"03",
    "gn:asciiname":"Ambodirano",
    "gn:country_code":"MG",
    "gn:dem":120,
    "gn:feature_class":"P",
    "gn:feature_code":"PPL",
    "gn:name":"Ambodirano",
    "gn:population":0,
    "gn:timezone":"Indian/Antananarivo",
    "iso:country":"MG",
    "wof:name":"Ambodirano",
    "wof:placetype":"locality"
},
  "geometry": {"coordinates":[45.95,-16.68333],"type":"Point"}
}