{
  "type": "Feature",
  "properties": {
    "gn:admin1_code":"02",
    "gn:asciiname":"Morafeno",
    "gn:country_code":"MG",
    "gn:dem":939,
    "gn:feature_class":"P",
    "gn:feature_code":"PPL",
    "gn:name":"Morafeno",
    "gn:population":0,
    "gn:timezone":"Indian/Antananarivo",
    "iso:country":"MG",
    "wof:name":"Morafeno",
    "wof:placetype":"locality"
},
  "geometry": {"coordinates":[46.68333,-21.95],"type":"Point"}
}