{
  "type": "Feature",
  "properties": {
    "gn:admin1_code":"05",
    "gn:asciiname":"Miarimbovo",
    "gn:cc2":"MG",
    "gn:country_code":"MG",
    "gn:dem":767,
    "gn:feature_class":"P",
    "gn:feature_code":"PPL",
    "gn:name":"Miarimbovo",
    "gn:population":0,
    "gn:timezone":"Indian/Antananarivo",
    "iso:country":"MG",
    "name:und_x_variant":[
        "Miarambovo",
        "Miarimbovo"
    ],
    "wof:name":"Miarimbovo",
    "wof:placetype":"locality"
},
  "geometry": {"coordinates":[46.18333,-19.28333],"type":"Point"}
}