{
  "type": "Feature",
  "properties": {
    "gn:admin1_code":"6.0",
    "gn:asciiname":"Tanantsoa",
    "gn:country_code":"MG",
    "gn:dem":369,
    "gn:feature_class":"P",
    "gn:feature_code":"PPL",
    "gn:name":"Tanantsoa",
    "gn:population":0,
    "gn:timezone":"Indian/Antananarivo",
    "iso:country":"MG",
    "wof:name":"Tanantsoa",
    "wof:placetype":"locality"
},
  "geometry": {"coordinates":[46.06667,-24.15],"type":"Point"}
}