{
  "type": "Feature",
  "properties": {
    "gn:admin1_code":"06",
    "gn:asciiname":"Analamivory",
    "gn:country_code":"MG",
    "gn:dem":226,
    "gn:feature_class":"P",
    "gn:feature_code":"PPL",
    "gn:name":"Analamivory",
    "gn:population":0,
    "gn:timezone":"Indian/Antananarivo",
    "iso:country":"MG",
    "wof:name":"Analamivory",
    "wof:placetype":"locality"
},
  "geometry": {"coordinates":[44.56667,-23.36667000000001],"type":"Point"}
}