{
  "type": "Feature",
  "properties": {
    "gn:admin1_code":"6.0",
    "gn:asciiname":"Tsiafantoka",
    "gn:country_code":"MG",
    "gn:dem":223,
    "gn:feature_class":"P",
    "gn:feature_code":"PPL",
    "gn:name":"Tsiafantoka",
    "gn:population":0,
    "gn:timezone":"Indian/Antananarivo",
    "iso:country":"MG",
    "wof:name":"Tsiafantoka",
    "wof:placetype":"locality"
},
  "geometry": {"coordinates":[44.43333,-23.65],"type":"Point"}
}