{
  "type": "Feature",
  "properties": {
    "gn:admin1_code":"02",
    "gn:asciiname":"Lomanosiny",
    "gn:cc2":"MG",
    "gn:country_code":"MG",
    "gn:dem":705,
    "gn:feature_class":"P",
    "gn:feature_code":"PPL",
    "gn:name":"Lomanosiny",
    "gn:population":0,
    "gn:timezone":"Indian/Antananarivo",
    "iso:country":"MG",
    "name:und_x_variant":[
        "Lomanosina",
        "Lomanosiny"
    ],
    "wof:name":"Lomanosiny",
    "wof:placetype":"locality"
},
  "geometry": {"coordinates":[46.83333,-22.28333],"type":"Point"}
}