{
  "type": "Feature",
  "properties": {
    "gn:admin1_code":"01",
    "gn:asciiname":"Antsohy Ambany",
    "gn:cc2":"MG",
    "gn:country_code":"MG",
    "gn:dem":98,
    "gn:feature_class":"P",
    "gn:feature_code":"PPL",
    "gn:name":"Antsohy Ambany",
    "gn:population":0,
    "gn:timezone":"Indian/Antananarivo",
    "iso:country":"MG",
    "name:und_x_variant":[
        "Antsohianabo",
        "Antsohy Ambany"
    ],
    "wof:name":"Antsohy Ambany",
    "wof:placetype":"locality"
},
  "geometry": {"coordinates":[49.31667,-13.16667],"type":"Point"}
}