{
  "type": "Feature",
  "properties": {
    "gn:admin1_code":"6.0",
    "gn:asciiname":"Vatovondrona",
    "gn:country_code":"MG",
    "gn:dem":3,
    "gn:feature_class":"P",
    "gn:feature_code":"PPL",
    "gn:name":"Vatovondrona",
    "gn:population":0,
    "gn:timezone":"Indian/Antananarivo",
    "iso:country":"MG",
    "wof:name":"Vatovondrona",
    "wof:placetype":"locality"
},
  "geometry": {"coordinates":[47.25,-24.25],"type":"Point"}
}