{
  "type": "Feature",
  "properties": {
    "gn:admin1_code":"06",
    "gn:asciiname":"Amboraho",
    "gn:country_code":"MG",
    "gn:dem":68,
    "gn:feature_class":"P",
    "gn:feature_code":"PPL",
    "gn:name":"Amboraho",
    "gn:population":0,
    "gn:timezone":"Indian/Antananarivo",
    "iso:country":"MG",
    "wof:name":"Amboraho",
    "wof:placetype":"locality"
},
  "geometry": {"coordinates":[43.68333,-21.85],"type":"Point"}
}