{
  "type": "Feature",
  "properties": {
    "gn:admin1_code":"03",
    "gn:asciiname":"Marohimony",
    "gn:country_code":"MG",
    "gn:dem":29,
    "gn:feature_class":"P",
    "gn:feature_code":"PPL",
    "gn:name":"Marohimony",
    "gn:population":0,
    "gn:timezone":"Indian/Antananarivo",
    "iso:country":"MG",
    "wof:name":"Marohimony",
    "wof:placetype":"locality"
},
  "geometry": {"coordinates":[44.46667,-18.63333],"type":"Point"}
}