{
  "type": "Feature",
  "properties": {
    "gn:admin1_code":"04",
    "gn:asciiname":"Ambodinonoka",
    "gn:country_code":"MG",
    "gn:dem":797,
    "gn:feature_class":"P",
    "gn:feature_code":"PPL",
    "gn:name":"Ambodinonoka",
    "gn:population":0,
    "gn:timezone":"Indian/Antananarivo",
    "iso:country":"MG",
    "wof:name":"Ambodinonoka",
    "wof:placetype":"locality"
},
  "geometry": {"coordinates":[48.41667,-19.23333],"type":"Point"}
}