{
  "type": "Feature",
  "properties": {
    "gn:admin1_code":"06",
    "gn:asciiname":"Belambo",
    "gn:country_code":"MG",
    "gn:dem":760,
    "gn:feature_class":"P",
    "gn:feature_code":"PPL",
    "gn:name":"Belambo",
    "gn:population":0,
    "gn:timezone":"Indian/Antananarivo",
    "iso:country":"MG",
    "wof:name":"Belambo",
    "wof:placetype":"locality"
},
  "geometry": {"coordinates":[45.68333,-24.01667],"type":"Point"}
}