{
  "type": "Feature",
  "properties": {
    "gn:admin1_code":"03",
    "gn:asciiname":"Antanambe",
    "gn:country_code":"MG",
    "gn:dem":253,
    "gn:feature_class":"P",
    "gn:feature_code":"PPL",
    "gn:name":"Antanambe",
    "gn:population":0,
    "gn:timezone":"Indian/Antananarivo",
    "iso:country":"MG",
    "name:fra_x_preferred":[
        "Antanambe"
    ],
    "name:ita_x_preferred":[
        "Antanambe"
    ],
    "name:mlg_x_preferred":[
        "Antanambe"
    ],
    "name:nld_x_preferred":[
        "Antanambe"
    ],
    "name:pol_x_preferred":[
        "Antanambe"
    ],
    "wof:name":"Antanambe",
    "wof:placetype":"locality"
},
  "geometry": {"coordinates":[48.53333,-15.01667],"type":"Point"}
}