{
  "type": "Feature",
  "properties": {
    "gn:admin1_code":"06",
    "gn:asciiname":"Miary",
    "gn:country_code":"MG",
    "gn:dem":1177,
    "gn:feature_class":"P",
    "gn:feature_code":"PPL",
    "gn:name":"Miary",
    "gn:population":0,
    "gn:timezone":"Indian/Antananarivo",
    "iso:country":"MG",
    "wof:name":"Miary",
    "wof:placetype":"locality"
},
  "geometry": {"coordinates":[45.81667,-24.08333],"type":"Point"}
}