{
  "type": "Feature",
  "properties": {
    "gn:admin1_code":"01",
    "gn:asciiname":"Beanamalaho",
    "gn:cc2":"MG",
    "gn:country_code":"MG",
    "gn:dem":528,
    "gn:feature_class":"P",
    "gn:feature_code":"PPL",
    "gn:name":"Beanamalaho",
    "gn:population":0,
    "gn:timezone":"Indian/Antananarivo",
    "iso:country":"MG",
    "name:und_x_variant":[
        "Beanamalao",
        "Beanamalaho"
    ],
    "wof:name":"Beanamalaho",
    "wof:placetype":"locality"
},
  "geometry": {"coordinates":[49.25,-12.68333],"type":"Point"}
}