{
  "type": "Feature",
  "properties": {
    "gn:admin1_code":"02",
    "gn:asciiname":"Leoposa",
    "gn:country_code":"MG",
    "gn:dem":754,
    "gn:feature_class":"P",
    "gn:feature_code":"PPL",
    "gn:name":"Leoposa",
    "gn:population":0,
    "gn:timezone":"Indian/Antananarivo",
    "iso:country":"MG",
    "wof:name":"Leoposa",
    "wof:placetype":"locality"
},
  "geometry": {"coordinates":[45.35,-22.66667],"type":"Point"}
}