{
  "type": "Feature",
  "properties": {
    "gn:admin1_code":"6.0",
    "gn:asciiname":"Tsimatahosy",
    "gn:country_code":"MG",
    "gn:dem":107,
    "gn:feature_class":"P",
    "gn:feature_code":"PPL",
    "gn:name":"Tsimatahosy",
    "gn:population":0,
    "gn:timezone":"Indian/Antananarivo",
    "iso:country":"MG",
    "wof:name":"Tsimatahosy",
    "wof:placetype":"locality"
},
  "geometry": {"coordinates":[44.53333,-23.51667],"type":"Point"}
}