{
  "type": "Feature",
  "properties": {
    "gn:admin1_code":"01",
    "gn:asciiname":"Ambanjahilatra",
    "gn:country_code":"MG",
    "gn:dem":350,
    "gn:feature_class":"P",
    "gn:feature_code":"PPL",
    "gn:name":"Ambanjahilatra",
    "gn:population":0,
    "gn:timezone":"Indian/Antananarivo",
    "iso:country":"MG",
    "wof:name":"Ambanjahilatra",
    "wof:placetype":"locality"
},
  "geometry": {"coordinates":[49.58333,-14.08333],"type":"Point"}
}