{
  "type": "Feature",
  "properties": {
    "gn:admin1_code":"03",
    "gn:asciiname":"Ambalakitata",
    "gn:cc2":"MG",
    "gn:country_code":"MG",
    "gn:dem":87,
    "gn:feature_class":"P",
    "gn:feature_code":"PPL",
    "gn:name":"Ambalakitata",
    "gn:population":0,
    "gn:timezone":"Indian/Antananarivo",
    "iso:country":"MG",
    "name:und_x_variant":[
        "Ambalakitatra",
        "Ambalakitata"
    ],
    "wof:name":"Ambalakitata",
    "wof:placetype":"locality"
},
  "geometry": {"coordinates":[47.26667,-15.73333],"type":"Point"}
}