{
  "type": "Feature",
  "properties": {
    "gn:admin1_code":"03",
    "gn:asciiname":"Mahabo",
    "gn:country_code":"MG",
    "gn:dem":7,
    "gn:feature_class":"P",
    "gn:feature_code":"PPL",
    "gn:name":"Mahabo",
    "gn:population":0,
    "gn:timezone":"Indian/Antananarivo",
    "iso:country":"MG",
    "name:fra_x_preferred":[
        "Mahabo"
    ],
    "name:ita_x_preferred":[
        "Mahabo"
    ],
    "name:mlg_x_preferred":[
        "Mahabo"
    ],
    "name:nld_x_preferred":[
        "Mahabo"
    ],
    "name:pol_x_preferred":[
        "Mahabo"
    ],
    "name:swe_x_preferred":[
        "Mahabo"
    ],
    "name:zho_x_preferred":[
        "\u99ac\u54c8\u5e03"
    ],
    "wof:name":"Mahabo",
    "wof:placetype":"locality"
},
  "geometry": {"coordinates":[45.55,-16.01667],"type":"Point"}
}