{
  "type": "Feature",
  "properties": {
    "gn:admin1_code":"02",
    "gn:asciiname":"Ambararata",
    "gn:country_code":"MG",
    "gn:dem":557,
    "gn:feature_class":"P",
    "gn:feature_code":"PPL",
    "gn:name":"Ambararata",
    "gn:population":0,
    "gn:timezone":"Indian/Antananarivo",
    "iso:country":"MG",
    "name:azb_x_preferred":[
        "\u0627\u0645\u0628\u0627\u0631\u0627\u0631\u0627\u062a\u0627"
    ],
    "name:fas_x_preferred":[
        "\u0627\u0645\u0628\u0627\u0631\u0627\u0631\u0627\u062a\u0627"
    ],
    "name:fra_x_preferred":[
        "Ambararata"
    ],
    "name:ita_x_preferred":[
        "Ambararata"
    ],
    "name:mlg_x_preferred":[
        "Ambararata"
    ],
    "name:nld_x_preferred":[
        "Ambararata"
    ],
    "wof:name":"Ambararata",
    "wof:placetype":"locality"
},
  "geometry": {"coordinates":[45.88333,-21.05],"type":"Point"}
}