{
  "type": "Feature",
  "properties": {
    "gn:admin1_code":"02",
    "gn:asciiname":"Iakondro",
    "gn:cc2":"MG",
    "gn:country_code":"MG",
    "gn:dem":10,
    "gn:feature_class":"P",
    "gn:feature_code":"PPL",
    "gn:name":"Iakondro",
    "gn:population":0,
    "gn:timezone":"Indian/Antananarivo",
    "iso:country":"MG",
    "name:und_x_variant":[
        "Akondro",
        "Ankondro",
        "Iakondro"
    ],
    "wof:name":"Iakondro",
    "wof:placetype":"locality"
},
  "geometry": {"coordinates":[47.53333,-23.91667],"type":"Point"}
}