{
  "type": "Feature",
  "properties": {
    "gn:admin1_code":"02",
    "gn:asciiname":"Ankinofika",
    "gn:cc2":"MG",
    "gn:country_code":"MG",
    "gn:dem":442,
    "gn:feature_class":"P",
    "gn:feature_code":"PPL",
    "gn:name":"Ankinofika",
    "gn:population":0,
    "gn:timezone":"Indian/Antananarivo",
    "iso:country":"MG",
    "name:und_x_variant":[
        "Ankihefika",
        "Ankinofika"
    ],
    "wof:name":"Ankinofika",
    "wof:placetype":"locality"
},
  "geometry": {"coordinates":[45.35,-22.11667000000001],"type":"Point"}
}