{
  "type": "Feature",
  "properties": {
    "gn:admin1_code":"05",
    "gn:asciiname":"Anivorano",
    "gn:country_code":"MG",
    "gn:dem":935,
    "gn:feature_class":"P",
    "gn:feature_code":"PPL",
    "gn:name":"Anivorano",
    "gn:population":0,
    "gn:timezone":"Indian/Antananarivo",
    "iso:country":"MG",
    "wof:name":"Anivorano",
    "wof:placetype":"locality"
},
  "geometry": {"coordinates":[46.75,-18.05],"type":"Point"}
}