{
  "type": "Feature",
  "properties": {
    "gn:admin1_code":"06",
    "gn:asciiname":"Bekako Atsimo",
    "gn:country_code":"MG",
    "gn:dem":258,
    "gn:feature_class":"P",
    "gn:feature_code":"PPL",
    "gn:name":"Bekako Atsimo",
    "gn:population":0,
    "gn:timezone":"Indian/Antananarivo",
    "iso:country":"MG",
    "wof:name":"Bekako Atsimo",
    "wof:placetype":"locality"
},
  "geometry": {"coordinates":[44.66667,-24.58333],"type":"Point"}
}