{
  "type": "Feature",
  "properties": {
    "gn:admin1_code":"03",
    "gn:asciiname":"Ambalajia",
    "gn:country_code":"MG",
    "gn:dem":262,
    "gn:feature_class":"P",
    "gn:feature_code":"PPL",
    "gn:name":"Ambalajia",
    "gn:population":0,
    "gn:timezone":"Indian/Antananarivo",
    "iso:country":"MG",
    "name:azb_x_preferred":[
        "\u0627\u0645\u0628\u0627\u0644\u0627\u062c\u06cc\u0627"
    ],
    "name:fas_x_preferred":[
        "\u0627\u0645\u0628\u0627\u0644\u0627\u062c\u06cc\u0627"
    ],
    "name:fra_x_preferred":[
        "Ambalajia"
    ],
    "name:ita_x_preferred":[
        "Ambalajia"
    ],
    "name:mlg_x_preferred":[
        "Ambalajia"
    ],
    "name:nld_x_preferred":[
        "Ambalajia"
    ],
    "wof:name":"Ambalajia",
    "wof:placetype":"locality"
},
  "geometry": {"coordinates":[46.11667,-17.48333],"type":"Point"}
}