{
  "type": "Feature",
  "properties": {
    "gn:admin1_code":"06",
    "gn:asciiname":"Bevalay",
    "gn:cc2":"MG",
    "gn:country_code":"MG",
    "gn:dem":172,
    "gn:feature_class":"P",
    "gn:feature_code":"PPL",
    "gn:name":"Bevalay",
    "gn:population":0,
    "gn:timezone":"Indian/Antananarivo",
    "iso:country":"MG",
    "name:und_x_variant":[
        "Bevala",
        "Bevalay"
    ],
    "wof:name":"Bevalay",
    "wof:placetype":"locality"
},
  "geometry": {"coordinates":[45.96667,-24.53333],"type":"Point"}
}