{
  "type": "Feature",
  "properties": {
    "gn:admin1_code":"6.0",
    "gn:asciiname":"Tomboarivo",
    "gn:country_code":"MG",
    "gn:dem":524,
    "gn:feature_class":"P",
    "gn:feature_code":"PPL",
    "gn:name":"Tomboarivo",
    "gn:population":0,
    "gn:timezone":"Indian/Antananarivo",
    "iso:country":"MG",
    "wof:name":"Tomboarivo",
    "wof:placetype":"locality"
},
  "geometry": {"coordinates":[45.68333,-24.26667],"type":"Point"}
}