{
  "type": "Feature",
  "properties": {
    "gn:admin1_code":"06",
    "gn:asciiname":"Ambaraka",
    "gn:country_code":"MG",
    "gn:dem":437,
    "gn:feature_class":"P",
    "gn:feature_code":"PPL",
    "gn:name":"Ambaraka",
    "gn:population":0,
    "gn:timezone":"Indian/Antananarivo",
    "iso:country":"MG",
    "wof:name":"Ambaraka",
    "wof:placetype":"locality"
},
  "geometry": {"coordinates":[45.35,-24.15],"type":"Point"}
}