{
  "type": "Feature",
  "properties": {
    "gn:admin1_code":"05",
    "gn:asciiname":"Ambatofotsikely",
    "gn:country_code":"MG",
    "gn:dem":1010,
    "gn:feature_class":"P",
    "gn:feature_code":"PPL",
    "gn:name":"Ambatofotsikely",
    "gn:population":0,
    "gn:timezone":"Indian/Antananarivo",
    "iso:country":"MG",
    "wof:name":"Ambatofotsikely",
    "wof:placetype":"locality"
},
  "geometry": {"coordinates":[46.46667,-19.46667],"type":"Point"}
}