{
  "type": "Feature",
  "properties": {
    "gn:admin1_code":"6.0",
    "gn:asciiname":"Terahanaombitelo",
    "gn:cc2":"MG",
    "gn:country_code":"MG",
    "gn:dem":156,
    "gn:feature_class":"P",
    "gn:feature_code":"PPL",
    "gn:name":"Terahanaombitelo",
    "gn:population":0,
    "gn:timezone":"Indian/Antananarivo",
    "iso:country":"MG",
    "name:und_x_variant":[
        "Terakombetelo",
        "Terahanaombitelo"
    ],
    "wof:name":"Terahanaombitelo",
    "wof:placetype":"locality"
},
  "geometry": {"coordinates":[44.71667,-24.88333],"type":"Point"}
}