{
  "type": "Feature",
  "properties": {
    "gn:admin1_code":"05",
    "gn:asciiname":"Mandrosoa",
    "gn:country_code":"MG",
    "gn:dem":1366,
    "gn:feature_class":"P",
    "gn:feature_code":"PPL",
    "gn:name":"Mandrosoa",
    "gn:population":0,
    "gn:timezone":"Indian/Antananarivo",
    "iso:country":"MG",
    "wof:name":"Mandrosoa",
    "wof:placetype":"locality"
},
  "geometry": {"coordinates":[47.63333,-18.65],"type":"Point"}
}