{
  "type": "Feature",
  "properties": {
    "gn:admin1_code":"6.0",
    "gn:asciiname":"Vorondreo",
    "gn:country_code":"MG",
    "gn:dem":50,
    "gn:feature_class":"P",
    "gn:feature_code":"PPL",
    "gn:name":"Vorondreo",
    "gn:population":0,
    "gn:timezone":"Indian/Antananarivo",
    "iso:country":"MG",
    "wof:name":"Vorondreo",
    "wof:placetype":"locality"
},
  "geometry": {"coordinates":[43.85,-23.28333],"type":"Point"}
}