{
  "type": "Feature",
  "properties": {
    "gn:admin1_code":"06",
    "gn:asciiname":"Ambory",
    "gn:country_code":"MG",
    "gn:dem":232,
    "gn:feature_class":"P",
    "gn:feature_code":"PPL",
    "gn:name":"Ambory",
    "gn:population":0,
    "gn:timezone":"Indian/Antananarivo",
    "iso:country":"MG",
    "wof:name":"Ambory",
    "wof:placetype":"locality"
},
  "geometry": {"coordinates":[45.41667,-24.88333],"type":"Point"}
}