{
  "type": "Feature",
  "properties": {
    "gn:admin1_code":"03",
    "gn:asciiname":"Antseza",
    "gn:country_code":"MG",
    "gn:dem":22,
    "gn:feature_class":"P",
    "gn:feature_code":"PPL",
    "gn:name":"Antseza",
    "gn:population":0,
    "gn:timezone":"Indian/Antananarivo",
    "iso:country":"MG",
    "wof:name":"Antseza",
    "wof:placetype":"locality"
},
  "geometry": {"coordinates":[45.86667,-16.21667],"type":"Point"}
}