{
  "type": "Feature",
  "properties": {
    "gn:admin1_code":"01",
    "gn:asciiname":"Amborano",
    "gn:country_code":"MG",
    "gn:dem":231,
    "gn:feature_class":"P",
    "gn:feature_code":"PPL",
    "gn:name":"Amborano",
    "gn:population":0,
    "gn:timezone":"Indian/Antananarivo",
    "iso:country":"MG",
    "wof:name":"Amborano",
    "wof:placetype":"locality"
},
  "geometry": {"coordinates":[50.06667,-15.03333],"type":"Point"}
}