{
  "type": "Feature",
  "properties": {
    "gn:admin1_code":"02",
    "gn:asciiname":"Antsary",
    "gn:cc2":"MG",
    "gn:country_code":"MG",
    "gn:dem":8,
    "gn:feature_class":"P",
    "gn:feature_code":"PPL",
    "gn:name":"Antsary",
    "gn:population":0,
    "gn:timezone":"Indian/Antananarivo",
    "iso:country":"MG",
    "name:und_x_variant":[
        "Tantsary",
        "Iantsary",
        "Antsary"
    ],
    "wof:name":"Antsary",
    "wof:placetype":"locality"
},
  "geometry": {"coordinates":[47.98333,-22.21667],"type":"Point"}
}