{
  "type": "Feature",
  "properties": {
    "gn:admin1_code":"05",
    "gn:asciiname":"Ambohiboahangy",
    "gn:country_code":"MG",
    "gn:dem":1296,
    "gn:feature_class":"P",
    "gn:feature_code":"PPL",
    "gn:name":"Ambohiboahangy",
    "gn:population":0,
    "gn:timezone":"Indian/Antananarivo",
    "iso:country":"MG",
    "wof:name":"Ambohiboahangy",
    "wof:placetype":"locality"
},
  "geometry": {"coordinates":[47.26667,-18.68333],"type":"Point"}
}