{
  "type": "Feature",
  "properties": {
    "gn:admin1_code":"06",
    "gn:asciiname":"Ampandrihosy",
    "gn:cc2":"MG",
    "gn:country_code":"MG",
    "gn:dem":76,
    "gn:feature_class":"P",
    "gn:feature_code":"PPL",
    "gn:name":"Ampandrihosy",
    "gn:population":0,
    "gn:timezone":"Indian/Antananarivo",
    "iso:country":"MG",
    "name:und_x_variant":[
        "Ampandrakosy",
        "Ampandrihosy"
    ],
    "wof:name":"Ampandrihosy",
    "wof:placetype":"locality"
},
  "geometry": {"coordinates":[43.58333,-22.78333],"type":"Point"}
}