{
  "type": "Feature",
  "properties": {
    "gn:admin1_code":"06",
    "gn:asciiname":"Anjatakary",
    "gn:country_code":"MG",
    "gn:dem":381,
    "gn:feature_class":"P",
    "gn:feature_code":"PPL",
    "gn:name":"Anjatakary",
    "gn:population":0,
    "gn:timezone":"Indian/Antananarivo",
    "iso:country":"MG",
    "wof:name":"Anjatakary",
    "wof:placetype":"locality"
},
  "geometry": {"coordinates":[45.38333,-24.55],"type":"Point"}
}