{
  "type": "Feature",
  "properties": {
    "gn:admin1_code":"04",
    "gn:asciiname":"Betampona",
    "gn:country_code":"MG",
    "gn:dem":227,
    "gn:feature_class":"P",
    "gn:feature_code":"PPL",
    "gn:name":"Betampona",
    "gn:population":0,
    "gn:timezone":"Indian/Antananarivo",
    "iso:country":"MG",
    "wof:name":"Betampona",
    "wof:placetype":"locality"
},
  "geometry": {"coordinates":[48.83333,-19.21667],"type":"Point"}
}