{
  "type": "Feature",
  "properties": {
    "gn:admin1_code":"06",
    "gn:asciiname":"Manantalin",
    "gn:country_code":"MG",
    "gn:dem":108,
    "gn:feature_class":"P",
    "gn:feature_code":"PPL",
    "gn:name":"Manantalin",
    "gn:population":0,
    "gn:timezone":"Indian/Antananarivo",
    "iso:country":"MG",
    "wof:name":"Manantalin",
    "wof:placetype":"locality"
},
  "geometry": {"coordinates":[46.61667,-24.81667],"type":"Point"}
}