{
  "type": "Feature",
  "properties": {
    "gn:admin1_code":"02",
    "gn:asciiname":"Amboasary",
    "gn:country_code":"MG",
    "gn:dem":1175,
    "gn:feature_class":"P",
    "gn:feature_code":"PPL",
    "gn:name":"Amboasary",
    "gn:population":0,
    "gn:timezone":"Indian/Antananarivo",
    "iso:country":"MG",
    "wof:name":"Amboasary",
    "wof:placetype":"locality"
},
  "geometry": {"coordinates":[47.11667,-21.08333],"type":"Point"}
}