{
  "type": "Feature",
  "properties": {
    "gn:admin1_code":"03",
    "gn:asciiname":"Ambatofolaka",
    "gn:cc2":"MG",
    "gn:country_code":"MG",
    "gn:dem":424,
    "gn:feature_class":"P",
    "gn:feature_code":"PPL",
    "gn:name":"Ambatofolaka",
    "gn:population":0,
    "gn:timezone":"Indian/Antananarivo",
    "iso:country":"MG",
    "name:und_x_variant":[
        "Ambatolalaka",
        "Ambatofolaka"
    ],
    "wof:name":"Ambatofolaka",
    "wof:placetype":"locality"
},
  "geometry": {"coordinates":[49.45,-16.36667000000001],"type":"Point"}
}