{
  "type": "Feature",
  "properties": {
    "gn:admin1_code":"2.0",
    "gn:asciiname":"Sarobaratra",
    "gn:country_code":"MG",
    "gn:dem":216,
    "gn:feature_class":"P",
    "gn:feature_code":"PPL",
    "gn:name":"Sarobaratra",
    "gn:population":0,
    "gn:timezone":"Indian/Antananarivo",
    "iso:country":"MG",
    "name:fra_x_preferred":[
        "Sarobaratra"
    ],
    "name:ita_x_preferred":[
        "Sarobaratra"
    ],
    "name:mlg_x_preferred":[
        "Sarobaratra"
    ],
    "name:nld_x_preferred":[
        "Sarobaratra"
    ],
    "wof:name":"Sarobaratra",
    "wof:placetype":"locality"
},
  "geometry": {"coordinates":[47.48333,-21.98333],"type":"Point"}
}