{
  "type": "Feature",
  "properties": {
    "gn:admin1_code":"06",
    "gn:asciiname":"Analalentike",
    "gn:country_code":"MG",
    "gn:dem":183,
    "gn:feature_class":"P",
    "gn:feature_code":"PPL",
    "gn:name":"Analalentike",
    "gn:population":0,
    "gn:timezone":"Indian/Antananarivo",
    "iso:country":"MG",
    "wof:name":"Analalentike",
    "wof:placetype":"locality"
},
  "geometry": {"coordinates":[44.11667,-23.76667],"type":"Point"}
}