{
  "type": "Feature",
  "properties": {
    "gn:admin1_code":"6.0",
    "gn:asciiname":"Tsimanandrafozana",
    "gn:country_code":"MG",
    "gn:dem":11,
    "gn:feature_class":"P",
    "gn:feature_code":"PPL",
    "gn:name":"Tsimanandrafozana",
    "gn:population":0,
    "gn:timezone":"Indian/Antananarivo",
    "iso:country":"MG",
    "wof:name":"Tsimanandrafozana",
    "wof:placetype":"locality"
},
  "geometry": {"coordinates":[44.41667,-19.78333],"type":"Point"}
}