{
  "type": "Feature",
  "properties": {
    "gn:admin1_code":"02",
    "gn:asciiname":"Iara",
    "gn:cc2":"MG",
    "gn:country_code":"MG",
    "gn:dem":65,
    "gn:feature_class":"P",
    "gn:feature_code":"PPL",
    "gn:name":"Iara",
    "gn:population":0,
    "gn:timezone":"Indian/Antananarivo",
    "iso:country":"MG",
    "name:und_x_variant":[
        "Antaninarenina",
        "Antaninerenina",
        "Iara"
    ],
    "wof:name":"Iara",
    "wof:placetype":"locality"
},
  "geometry": {"coordinates":[47.43333,-23.08333],"type":"Point"}
}