{
  "type": "Feature",
  "properties": {
    "gn:admin1_code":"06",
    "gn:asciiname":"Manandrea",
    "gn:country_code":"MG",
    "gn:dem":133,
    "gn:feature_class":"P",
    "gn:feature_code":"PPL",
    "gn:name":"Manandrea",
    "gn:population":0,
    "gn:timezone":"Indian/Antananarivo",
    "iso:country":"MG",
    "wof:name":"Manandrea",
    "wof:placetype":"locality"
},
  "geometry": {"coordinates":[44.83333,-21.73333],"type":"Point"}
}