{
  "type": "Feature",
  "properties": {
    "gn:admin1_code":"7670850",
    "gn:asciiname":"Maevatanana",
    "gn:country_code":"MG",
    "gn:dem":64,
    "gn:feature_class":"P",
    "gn:feature_code":"PPLA",
    "gn:name":"Maevatanana",
    "gn:population":24000,
    "gn:timezone":"Indian/Antananarivo",
    "iso:country":"MG",
    "name:und_x_variant":[
        "Mevatanana",
        "Maevetanana",
        "Mavatanana",
        "Maevatanana"
    ],
    "wof:name":"Maevatanana",
    "wof:placetype":"locality",
    "wof:population":24000
},
  "geometry": {"coordinates":[46.83333,-16.95],"type":"Point"}
}