{
  "type": "Feature",
  "properties": {
    "gn:admin1_code":"7670850",
    "gn:asciiname":"Maevatanana",
    "gn:country_code":"MG",
    "gn:dem":64,
    "gn:feature_class":"P",
    "gn:feature_code":"PPLA",
    "gn:name":"Maevatanana",
    "gn:population":24000,
    "gn:timezone":"Indian/Antananarivo",
    "iso:country":"MG",
    "name:ceb_x_preferred":[
        "Maevatanana"
    ],
    "name:dan_x_preferred":[
        "Maevatanana"
    ],
    "name:deu_x_preferred":[
        "Maevatanana"
    ],
    "name:fra_x_preferred":[
        "Maevatanana"
    ],
    "name:hrv_x_preferred":[
        "Maevatanana"
    ],
    "name:ita_x_preferred":[
        "Maevatanana"
    ],
    "name:mlg_x_preferred":[
        "Maevatanana"
    ],
    "name:nld_x_preferred":[
        "Maevatanana"
    ],
    "name:pol_x_preferred":[
        "Maevatanana"
    ],
    "name:ron_x_preferred":[
        "Maevatanana"
    ],
    "name:swe_x_preferred":[
        "Maevatanana"
    ],
    "name:und_x_variant":[
        "Mevatanana",
        "Maevetanana",
        "Mavatanana",
        "Maevatanana"
    ],
    "name:urd_x_preferred":[
        "\u0645\u0627\u0626\u0648\u0627\u062a\u0627\u0646\u0627\u0646\u0627"
    ],
    "name:zho_x_preferred":[
        "\u99ac\u57c3\u74e6\u5854\u7d0d\u7d0d"
    ],
    "wof:name":"Maevatanana",
    "wof:placetype":"locality",
    "wof:population":24000
},
  "geometry": {"coordinates":[46.83333,-16.95],"type":"Point"}
}