{
  "type": "Feature",
  "properties": {
    "gn:admin1_code":"04",
    "gn:asciiname":"Ambodiharamy",
    "gn:country_code":"MG",
    "gn:dem":639,
    "gn:feature_class":"P",
    "gn:feature_code":"PPL",
    "gn:name":"Ambodiharamy",
    "gn:population":0,
    "gn:timezone":"Indian/Antananarivo",
    "iso:country":"MG",
    "wof:name":"Ambodiharamy",
    "wof:placetype":"locality"
},
  "geometry": {"coordinates":[48.15,-19.85],"type":"Point"}
}