{
  "type": "Feature",
  "properties": {
    "gn:admin1_code":"06",
    "gn:asciiname":"Ambahivahy",
    "gn:cc2":"MG",
    "gn:country_code":"MG",
    "gn:dem":371,
    "gn:feature_class":"P",
    "gn:feature_code":"PPL",
    "gn:name":"Ambahivahy",
    "gn:population":0,
    "gn:timezone":"Indian/Antananarivo",
    "iso:country":"MG",
    "name:und_x_variant":[
        "Amoahivahy",
        "Ambahivahy"
    ],
    "wof:name":"Ambahivahy",
    "wof:placetype":"locality"
},
  "geometry": {"coordinates":[44.33333,-21.68333],"type":"Point"}
}