{
  "type": "Feature",
  "properties": {
    "gn:admin1_code":"05",
    "gn:asciiname":"Ambohitrony",
    "gn:country_code":"MG",
    "gn:dem":1413,
    "gn:feature_class":"P",
    "gn:feature_code":"PPL",
    "gn:name":"Ambohitrony",
    "gn:population":0,
    "gn:timezone":"Indian/Antananarivo",
    "iso:country":"MG",
    "wof:name":"Ambohitrony",
    "wof:placetype":"locality"
},
  "geometry": {"coordinates":[47.76667,-18.75],"type":"Point"}
}