{
  "type": "Feature",
  "properties": {
    "gn:admin1_code":"05",
    "gn:asciiname":"Ankitelov",
    "gn:country_code":"MG",
    "gn:dem":1409,
    "gn:feature_class":"P",
    "gn:feature_code":"PPL",
    "gn:name":"Ankitelov",
    "gn:population":0,
    "gn:timezone":"Indian/Antananarivo",
    "iso:country":"MG",
    "wof:name":"Ankitelov",
    "wof:placetype":"locality"
},
  "geometry": {"coordinates":[46.83333,-18.88333],"type":"Point"}
}