{
  "type": "Feature",
  "properties": {
    "gn:asciiname":"Anteza Firaisana",
    "gn:country_code":"MG",
    "gn:dem":1188,
    "gn:feature_class":"P",
    "gn:feature_code":"PPL",
    "gn:name":"Anteza Firaisana",
    "gn:population":0,
    "gn:timezone":"Indian/Antananarivo",
    "iso:country":"MG",
    "wof:name":"Anteza Firaisana",
    "wof:placetype":"locality"
},
  "geometry": {"coordinates":[46.58658,-19.11498],"type":"Point"}
}