{
  "type": "Feature",
  "properties": {
    "gn:admin1_code":"2.0",
    "gn:asciiname":"Sakaovy",
    "gn:country_code":"MG",
    "gn:dem":1596,
    "gn:feature_class":"P",
    "gn:feature_code":"PPL",
    "gn:name":"Sakaovy",
    "gn:population":0,
    "gn:timezone":"Indian/Antananarivo",
    "iso:country":"MG",
    "wof:name":"Sakaovy",
    "wof:placetype":"locality"
},
  "geometry": {"coordinates":[47.26667,-20.75],"type":"Point"}
}