{
  "type": "Feature",
  "properties": {
    "gn:admin1_code":"03",
    "gn:asciiname":"Andrafiatokana",
    "gn:country_code":"MG",
    "gn:dem":56,
    "gn:feature_class":"P",
    "gn:feature_code":"PPL",
    "gn:name":"Andrafiatokana",
    "gn:population":0,
    "gn:timezone":"Indian/Antananarivo",
    "iso:country":"MG",
    "wof:name":"Andrafiatokana",
    "wof:placetype":"locality"
},
  "geometry": {"coordinates":[47.61667,-14.56667],"type":"Point"}
}