{
  "type": "Feature",
  "properties": {
    "gn:admin1_code":"03",
    "gn:asciiname":"Ambonarabe",
    "gn:cc2":"MG",
    "gn:country_code":"MG",
    "gn:dem":288,
    "gn:feature_class":"P",
    "gn:feature_code":"PPL",
    "gn:name":"Ambonarabe",
    "gn:population":0,
    "gn:timezone":"Indian/Antananarivo",
    "iso:country":"MG",
    "name:und_x_variant":[
        "Amboharabe",
        "Ambonarabe"
    ],
    "wof:name":"Ambonarabe",
    "wof:placetype":"locality"
},
  "geometry": {"coordinates":[44.53333,-18.01667],"type":"Point"}
}