{
  "type": "Feature",
  "properties": {
    "gn:admin1_code":"04",
    "gn:asciiname":"Mahambolona",
    "gn:country_code":"MG",
    "gn:dem":87,
    "gn:feature_class":"P",
    "gn:feature_code":"PPL",
    "gn:name":"Mahambolona",
    "gn:population":0,
    "gn:timezone":"Indian/Antananarivo",
    "iso:country":"MG",
    "wof:name":"Mahambolona",
    "wof:placetype":"locality"
},
  "geometry": {"coordinates":[49.33333,-17.93332999999999],"type":"Point"}
}