{
  "type": "Feature",
  "properties": {
    "gn:admin1_code":"5.0",
    "gn:asciiname":"Tsarahonenana",
    "gn:country_code":"MG",
    "gn:dem":1414,
    "gn:feature_class":"P",
    "gn:feature_code":"PPL",
    "gn:name":"Tsarahonenana",
    "gn:population":0,
    "gn:timezone":"Indian/Antananarivo",
    "iso:country":"MG",
    "name:fra_x_preferred":[
        "Tsarahonenana"
    ],
    "name:ita_x_preferred":[
        "Tsarahonenana"
    ],
    "name:mlg_x_preferred":[
        "Tsarahonenana"
    ],
    "name:nld_x_preferred":[
        "Tsarahonenana"
    ],
    "wof:name":"Tsarahonenana",
    "wof:placetype":"locality"
},
  "geometry": {"coordinates":[47.56667,-19.21667],"type":"Point"}
}