{
  "type": "Feature",
  "properties": {
    "gn:admin1_code":"02",
    "gn:asciiname":"Ihorombe",
    "gn:country_code":"MG",
    "gn:dem":835,
    "gn:feature_class":"P",
    "gn:feature_code":"PPL",
    "gn:name":"Ihorombe",
    "gn:population":0,
    "gn:timezone":"Indian/Antananarivo",
    "iso:country":"MG",
    "wof:name":"Ihorombe",
    "wof:placetype":"locality"
},
  "geometry": {"coordinates":[46.55,-20.96667],"type":"Point"}
}