{
  "type": "Feature",
  "properties": {
    "gn:admin1_code":"02",
    "gn:asciiname":"Ihorombe",
    "gn:country_code":"MG",
    "gn:dem":835,
    "gn:feature_class":"P",
    "gn:feature_code":"PPL",
    "gn:name":"Ihorombe",
    "gn:population":0,
    "gn:timezone":"Indian/Antananarivo",
    "iso:country":"MG",
    "name:ara_x_preferred":[
        "\u0625\u06cc\u0647\u0648\u0631\u0648\u0645\u0628\u064a"
    ],
    "name:bre_x_preferred":[
        "Ihorombe"
    ],
    "name:bul_x_preferred":[
        "\u0418\u0445\u043e\u0440\u043e\u043c\u0431\u0435"
    ],
    "name:ceb_x_preferred":[
        "Ihorombe Region"
    ],
    "name:dan_x_preferred":[
        "Ihorombe"
    ],
    "name:deu_x_preferred":[
        "Ihorombe"
    ],
    "name:ell_x_preferred":[
        "\u0399\u03c7\u03bf\u03c1\u03cc\u03bc\u03c0\u03b5"
    ],
    "name:fas_x_preferred":[
        "\u0627\u06cc\u0647\u0648\u0631\u0648\u0645\u0628\u0647"
    ],
    "name:fra_x_preferred":[
        "Ihorombe"
    ],
    "name:ind_x_preferred":[
        "Ihorombe"
    ],
    "name:kor_x_preferred":[
        "\uc774\ud638\ub86c\ubca0 \uad6c"
    ],
    "name:mlg_x_preferred":[
        "Ihorombe"
    ],
    "name:nld_x_preferred":[
        "Ihorombe"
    ],
    "name:nor_x_preferred":[
        "Ihorombe"
    ],
    "name:pol_x_preferred":[
        "Ihorombe"
    ],
    "name:por_x_preferred":[
        "Ihorombe"
    ],
    "name:ron_x_preferred":[
        "Regiunea Ihorombe"
    ],
    "name:swa_x_preferred":[
        "Ihorombe"
    ],
    "name:swe_x_preferred":[
        "Ihoromberegionen"
    ],
    "name:urd_x_preferred":[
        "\u0627\u06cc\u06c1\u0648\u0631\u0648\u0645\u0628\u06d2"
    ],
    "name:zho_x_preferred":[
        "\u4f0a\u970d\u7f85\u8c9d\u5340"
    ],
    "wof:name":"Ihorombe",
    "wof:placetype":"locality"
},
  "geometry": {"coordinates":[46.55,-20.96667],"type":"Point"}
}