{
  "type": "Feature",
  "properties": {
    "gn:admin1_code":"03",
    "gn:asciiname":"Ambevongo",
    "gn:country_code":"MG",
    "gn:dem":17,
    "gn:feature_class":"P",
    "gn:feature_code":"PPL",
    "gn:name":"Ambevongo",
    "gn:population":0,
    "gn:timezone":"Indian/Antananarivo",
    "iso:country":"MG",
    "wof:name":"Ambevongo",
    "wof:placetype":"locality"
},
  "geometry": {"coordinates":[47.45,-15.45],"type":"Point"}
}