{
  "type": "Feature",
  "properties": {
    "gn:admin1_code":"6.0",
    "gn:asciiname":"Sambalahy",
    "gn:country_code":"MG",
    "gn:dem":796,
    "gn:feature_class":"P",
    "gn:feature_code":"PPL",
    "gn:name":"Sambalahy",
    "gn:population":0,
    "gn:timezone":"Indian/Antananarivo",
    "iso:country":"MG",
    "wof:name":"Sambalahy",
    "wof:placetype":"locality"
},
  "geometry": {"coordinates":[45.76667,-22.96667],"type":"Point"}
}