{
  "type": "Feature",
  "properties": {
    "gn:admin1_code":"02",
    "gn:asciiname":"Ankorabe",
    "gn:country_code":"MG",
    "gn:dem":983,
    "gn:feature_class":"P",
    "gn:feature_code":"PPL",
    "gn:name":"Ankorabe",
    "gn:population":0,
    "gn:timezone":"Indian/Antananarivo",
    "iso:country":"MG",
    "wof:name":"Ankorabe",
    "wof:placetype":"locality"
},
  "geometry": {"coordinates":[46.88333,-22.43333],"type":"Point"}
}