{
  "type": "Feature",
  "properties": {
    "gn:admin1_code":"01",
    "gn:asciiname":"Ambatomitangolo",
    "gn:cc2":"MG",
    "gn:country_code":"MG",
    "gn:dem":49,
    "gn:feature_class":"P",
    "gn:feature_code":"PPL",
    "gn:name":"Ambatomitangolo",
    "gn:population":0,
    "gn:timezone":"Indian/Antananarivo",
    "iso:country":"MG",
    "name:und_x_variant":[
        "Ambatomitongola",
        "Ambatomitangolo"
    ],
    "wof:name":"Ambatomitangolo",
    "wof:placetype":"locality"
},
  "geometry": {"coordinates":[48.95,-12.46667],"type":"Point"}
}