{
  "type": "Feature",
  "properties": {
    "gn:admin1_code":"03",
    "gn:asciiname":"Ampombimanangy",
    "gn:cc2":"MG",
    "gn:country_code":"MG",
    "gn:dem":75,
    "gn:feature_class":"P",
    "gn:feature_code":"PPL",
    "gn:name":"Ampombimanangy",
    "gn:population":0,
    "gn:timezone":"Indian/Antananarivo",
    "iso:country":"MG",
    "name:und_x_variant":[
        "Ampombomanangy",
        "Ampombimanagy",
        "Ampombimanangy"
    ],
    "wof:name":"Ampombimanangy",
    "wof:placetype":"locality"
},
  "geometry": {"coordinates":[47.41667,-16.06667],"type":"Point"}
}