{
  "type": "Feature",
  "properties": {
    "gn:admin1_code":"06",
    "gn:asciiname":"Maninday II",
    "gn:cc2":"MG",
    "gn:country_code":"MG",
    "gn:dem":591,
    "gn:feature_class":"P",
    "gn:feature_code":"PPL",
    "gn:name":"Maninday II",
    "gn:population":0,
    "gn:timezone":"Indian/Antananarivo",
    "iso:country":"MG",
    "name:und_x_variant":[
        "Maninday",
        "Maninday II"
    ],
    "wof:name":"Maninday II",
    "wof:placetype":"locality"
},
  "geometry": {"coordinates":[44.76667,-22.73333],"type":"Point"}
}