{
  "type": "Feature",
  "properties": {
    "gn:admin1_code":"06",
    "gn:asciiname":"Morafeno",
    "gn:cc2":"MG",
    "gn:country_code":"MG",
    "gn:dem":22,
    "gn:feature_class":"P",
    "gn:feature_code":"PPL",
    "gn:name":"Morafeno",
    "gn:population":0,
    "gn:timezone":"Indian/Antananarivo",
    "iso:country":"MG",
    "name:fra_x_preferred":[
        "Morafeno"
    ],
    "name:ita_x_preferred":[
        "Morafeno"
    ],
    "name:nld_x_preferred":[
        "Morafeno"
    ],
    "name:und_x_variant":[
        "Morateno"
    ],
    "wof:name":"Morafeno",
    "wof:placetype":"locality"
},
  "geometry": {"coordinates":[43.46667,-21.78333],"type":"Point"}
}