{
  "type": "Feature",
  "properties": {
    "gn:admin1_code":"06",
    "gn:asciiname":"Anbaladoda",
    "gn:country_code":"MG",
    "gn:dem":36,
    "gn:feature_class":"P",
    "gn:feature_code":"PPL",
    "gn:name":"Anbaladoda",
    "gn:population":0,
    "gn:timezone":"Indian/Antananarivo",
    "iso:country":"MG",
    "wof:name":"Anbaladoda",
    "wof:placetype":"locality"
},
  "geometry": {"coordinates":[44.13333,-24.95],"type":"Point"}
}