{
  "type": "Feature",
  "properties": {
    "gn:admin1_code":"2.0",
    "gn:asciiname":"Voditanjona",
    "gn:country_code":"MG",
    "gn:dem":78,
    "gn:feature_class":"P",
    "gn:feature_code":"PPL",
    "gn:name":"Voditanjona",
    "gn:population":0,
    "gn:timezone":"Indian/Antananarivo",
    "iso:country":"MG",
    "wof:name":"Voditanjona",
    "wof:placetype":"locality"
},
  "geometry": {"coordinates":[47.66667,-22.13333],"type":"Point"}
}