{
  "type": "Feature",
  "properties": {
    "gn:admin1_code":"03",
    "gn:asciiname":"Ankatafa",
    "gn:cc2":"MG",
    "gn:country_code":"MG",
    "gn:dem":47,
    "gn:feature_class":"P",
    "gn:feature_code":"PPL",
    "gn:name":"Ankatafa",
    "gn:population":0,
    "gn:timezone":"Indian/Antananarivo",
    "iso:country":"MG",
    "name:ceb_x_preferred":[
        "Ankatafa"
    ],
    "name:fra_x_preferred":[
        "Ankatafa"
    ],
    "name:ita_x_preferred":[
        "Ankatafa"
    ],
    "name:nld_x_preferred":[
        "Ankatafa"
    ],
    "name:swe_x_preferred":[
        "Ankatafa"
    ],
    "name:und_x_variant":[
        "Ankatafy"
    ],
    "wof:name":"Ankatafa",
    "wof:placetype":"locality"
},
  "geometry": {"coordinates":[47.86667,-14.26667],"type":"Point"}
}