{
  "type": "Feature",
  "properties": {
    "gn:admin1_code":"04",
    "gn:asciiname":"Beramanja",
    "gn:country_code":"MG",
    "gn:dem":770,
    "gn:feature_class":"P",
    "gn:feature_code":"PPL",
    "gn:name":"Beramanja",
    "gn:population":0,
    "gn:timezone":"Indian/Antananarivo",
    "iso:country":"MG",
    "name:fra_x_preferred":[
        "Beramanja"
    ],
    "name:ita_x_preferred":[
        "Beramanja"
    ],
    "name:mlg_x_preferred":[
        "Beramanja"
    ],
    "name:nld_x_preferred":[
        "Beramanja"
    ],
    "wof:name":"Beramanja",
    "wof:placetype":"locality"
},
  "geometry": {"coordinates":[48.63333,-17.36667000000001],"type":"Point"}
}