{
  "type": "Feature",
  "properties": {
    "gn:admin1_code":"03",
    "gn:asciiname":"Berohay",
    "gn:country_code":"MG",
    "gn:dem":245,
    "gn:feature_class":"P",
    "gn:feature_code":"PPL",
    "gn:name":"Berohay",
    "gn:population":0,
    "gn:timezone":"Indian/Antananarivo",
    "iso:country":"MG",
    "wof:name":"Berohay",
    "wof:placetype":"locality"
},
  "geometry": {"coordinates":[44.78333,-17.88332999999999],"type":"Point"}
}