{
  "type": "Feature",
  "properties": {
    "gn:admin1_code":"06",
    "gn:asciiname":"Anjampoty",
    "gn:country_code":"MG",
    "gn:dem":115,
    "gn:feature_class":"P",
    "gn:feature_code":"PPL",
    "gn:name":"Anjampoty",
    "gn:population":0,
    "gn:timezone":"Indian/Antananarivo",
    "iso:country":"MG",
    "wof:name":"Anjampoty",
    "wof:placetype":"locality"
},
  "geometry": {"coordinates":[45.26667,-25.21667],"type":"Point"}
}