{
  "type": "Feature",
  "properties": {
    "gn:admin1_code":"06",
    "gn:asciiname":"Amitijihy",
    "gn:country_code":"MG",
    "gn:dem":213,
    "gn:feature_class":"P",
    "gn:feature_code":"PPL",
    "gn:name":"Amitijihy",
    "gn:population":0,
    "gn:timezone":"Indian/Antananarivo",
    "iso:country":"MG",
    "wof:name":"Amitijihy",
    "wof:placetype":"locality"
},
  "geometry": {"coordinates":[44.68333,-20.76667],"type":"Point"}
}