{
  "type": "Feature",
  "properties": {
    "gn:admin1_code":"05",
    "gn:asciiname":"Manjiandrano",
    "gn:country_code":"MG",
    "gn:dem":1534,
    "gn:feature_class":"P",
    "gn:feature_code":"PPL",
    "gn:name":"Manjiandrano",
    "gn:population":0,
    "gn:timezone":"Indian/Antananarivo",
    "iso:country":"MG",
    "wof:name":"Manjiandrano",
    "wof:placetype":"locality"
},
  "geometry": {"coordinates":[46.98333,-19.35],"type":"Point"}
}