{
  "type": "Feature",
  "properties": {
    "gn:asciiname":"Point Loulou",
    "gn:country_code":"MG",
    "gn:dem":129,
    "gn:feature_class":"P",
    "gn:feature_code":"PPL",
    "gn:name":"Point Loulou",
    "gn:population":0,
    "gn:timezone":"Indian/Antananarivo",
    "iso:country":"MG",
    "wof:name":"Point Loulou",
    "wof:placetype":"locality"
},
  "geometry": {"coordinates":[48.18938,-13.25202],"type":"Point"}
}