{
  "type": "Feature",
  "properties": {
    "gn:admin1_code":"5.0",
    "gn:asciiname":"Tsiahirika",
    "gn:country_code":"MG",
    "gn:dem":930,
    "gn:feature_class":"P",
    "gn:feature_code":"PPL",
    "gn:name":"Tsiahirika",
    "gn:population":0,
    "gn:timezone":"Indian/Antananarivo",
    "iso:country":"MG",
    "wof:name":"Tsiahirika",
    "wof:placetype":"locality"
},
  "geometry": {"coordinates":[46.25,-18.56667],"type":"Point"}
}