{
  "type": "Feature",
  "properties": {
    "gn:admin1_code":"06",
    "gn:asciiname":"Amanendraka",
    "gn:country_code":"MG",
    "gn:dem":159,
    "gn:feature_class":"P",
    "gn:feature_code":"PPL",
    "gn:name":"Amanendraka",
    "gn:population":0,
    "gn:timezone":"Indian/Antananarivo",
    "iso:country":"MG",
    "wof:name":"Amanendraka",
    "wof:placetype":"locality"
},
  "geometry": {"coordinates":[45.33333,-25.53333],"type":"Point"}
}