{
  "type": "Feature",
  "properties": {
    "gn:admin1_code":"03",
    "gn:asciiname":"Androamitsaka",
    "gn:cc2":"MG",
    "gn:country_code":"MG",
    "gn:dem":149,
    "gn:feature_class":"P",
    "gn:feature_code":"PPL",
    "gn:name":"Androamitsaka",
    "gn:population":0,
    "gn:timezone":"Indian/Antananarivo",
    "iso:country":"MG",
    "name:und_x_variant":[
        "Androimitsaka",
        "Androamitsaka"
    ],
    "wof:name":"Androamitsaka",
    "wof:placetype":"locality"
},
  "geometry": {"coordinates":[47.95,-15.73333],"type":"Point"}
}