{
  "type": "Feature",
  "properties": {
    "gn:admin1_code":"04",
    "gn:asciiname":"Ambinaninakia",
    "gn:country_code":"MG",
    "gn:dem":183,
    "gn:feature_class":"P",
    "gn:feature_code":"PPL",
    "gn:name":"Ambinaninakia",
    "gn:population":0,
    "gn:timezone":"Indian/Antananarivo",
    "iso:country":"MG",
    "wof:name":"Ambinaninakia",
    "wof:placetype":"locality"
},
  "geometry": {"coordinates":[49.15,-18.11667000000001],"type":"Point"}
}