{
  "type": "Feature",
  "properties": {
    "gn:admin1_code":"02",
    "gn:asciiname":"Ambondro",
    "gn:country_code":"MG",
    "gn:dem":989,
    "gn:feature_class":"P",
    "gn:feature_code":"PPL",
    "gn:name":"Ambondro",
    "gn:population":0,
    "gn:timezone":"Indian/Antananarivo",
    "iso:country":"MG",
    "wof:name":"Ambondro",
    "wof:placetype":"locality"
},
  "geometry": {"coordinates":[46.08333,-23.56667],"type":"Point"}
}