{
  "type": "Feature",
  "properties": {
    "gn:admin1_code":"06",
    "gn:asciiname":"Marovila",
    "gn:country_code":"MG",
    "gn:dem":720,
    "gn:feature_class":"P",
    "gn:feature_code":"PPL",
    "gn:name":"Marovila",
    "gn:population":0,
    "gn:timezone":"Indian/Antananarivo",
    "iso:country":"MG",
    "wof:name":"Marovila",
    "wof:placetype":"locality"
},
  "geometry": {"coordinates":[45.75,-23.11667000000001],"type":"Point"}
}