{
  "type": "Feature",
  "properties": {
    "gn:admin1_code":"01",
    "gn:asciiname":"Ambahisotry",
    "gn:country_code":"MG",
    "gn:dem":739,
    "gn:feature_class":"P",
    "gn:feature_code":"PPL",
    "gn:name":"Ambahisotry",
    "gn:population":0,
    "gn:timezone":"Indian/Antananarivo",
    "iso:country":"MG",
    "wof:name":"Ambahisotry",
    "wof:placetype":"locality"
},
  "geometry": {"coordinates":[49.36667,-13.45],"type":"Point"}
}