{
  "type": "Feature",
  "properties": {
    "gn:admin1_code":"04",
    "gn:asciiname":"Morateno",
    "gn:country_code":"MG",
    "gn:dem":864,
    "gn:feature_class":"P",
    "gn:feature_code":"PPL",
    "gn:name":"Morateno",
    "gn:population":0,
    "gn:timezone":"Indian/Antananarivo",
    "iso:country":"MG",
    "wof:name":"Morateno",
    "wof:placetype":"locality"
},
  "geometry": {"coordinates":[48.46667,-17.83333],"type":"Point"}
}