{
  "type": "Feature",
  "properties": {
    "gn:admin1_code":"03",
    "gn:asciiname":"Antsambalahy",
    "gn:country_code":"MG",
    "gn:dem":670,
    "gn:feature_class":"P",
    "gn:feature_code":"PPL",
    "gn:name":"Antsambalahy",
    "gn:population":0,
    "gn:timezone":"Indian/Antananarivo",
    "iso:country":"MG",
    "name:fra_x_preferred":[
        "Antsambalahy"
    ],
    "name:ita_x_preferred":[
        "Antsambalahy"
    ],
    "name:mlg_x_preferred":[
        "Antsambalahy"
    ],
    "name:nld_x_preferred":[
        "Antsambalahy"
    ],
    "wof:name":"Antsambalahy",
    "wof:placetype":"locality"
},
  "geometry": {"coordinates":[48.93333,-14.91667],"type":"Point"}
}