{
  "type": "Feature",
  "properties": {
    "gn:admin1_code":"05",
    "gn:asciiname":"Ambohidramanalina",
    "gn:country_code":"MG",
    "gn:dem":678,
    "gn:feature_class":"P",
    "gn:feature_code":"PPL",
    "gn:name":"Ambohidramanalina",
    "gn:population":0,
    "gn:timezone":"Indian/Antananarivo",
    "iso:country":"MG",
    "wof:name":"Ambohidramanalina",
    "wof:placetype":"locality"
},
  "geometry": {"coordinates":[45.85,-19.65],"type":"Point"}
}