{
  "type": "Feature",
  "properties": {
    "gn:admin1_code":"3.0",
    "gn:asciiname":"Tsiazohenana",
    "gn:country_code":"MG",
    "gn:dem":14,
    "gn:feature_class":"P",
    "gn:feature_code":"PPL",
    "gn:name":"Tsiazohenana",
    "gn:population":0,
    "gn:timezone":"Indian/Antananarivo",
    "iso:country":"MG",
    "wof:name":"Tsiazohenana",
    "wof:placetype":"locality"
},
  "geometry": {"coordinates":[44.05,-17.48333],"type":"Point"}
}