{
  "type": "Feature",
  "properties": {
    "gn:admin1_code":"02",
    "gn:asciiname":"Ambohimirana",
    "gn:country_code":"MG",
    "gn:dem":1392,
    "gn:feature_class":"P",
    "gn:feature_code":"PPL",
    "gn:name":"Ambohimirana",
    "gn:population":0,
    "gn:timezone":"Indian/Antananarivo",
    "iso:country":"MG",
    "wof:name":"Ambohimirana",
    "wof:placetype":"locality"
},
  "geometry": {"coordinates":[47.33333,-20.18333],"type":"Point"}
}