{
  "type": "Feature",
  "properties": {
    "gn:admin1_code":"04",
    "gn:asciiname":"Manakambahiny",
    "gn:country_code":"MG",
    "gn:dem":911,
    "gn:feature_class":"P",
    "gn:feature_code":"PPL",
    "gn:name":"Manakambahiny",
    "gn:population":0,
    "gn:timezone":"Indian/Antananarivo",
    "iso:country":"MG",
    "wof:name":"Manakambahiny",
    "wof:placetype":"locality"
},
  "geometry": {"coordinates":[48.45,-18.01667],"type":"Point"}
}