{
  "type": "Feature",
  "properties": {
    "gn:admin1_code":"2.0",
    "gn:asciiname":"Sohatorendrika",
    "gn:country_code":"MG",
    "gn:dem":1759,
    "gn:feature_class":"P",
    "gn:feature_code":"PPL",
    "gn:name":"Sohatorendrika",
    "gn:population":0,
    "gn:timezone":"Indian/Antananarivo",
    "iso:country":"MG",
    "wof:name":"Sohatorendrika",
    "wof:placetype":"locality"
},
  "geometry": {"coordinates":[47.25,-20.16667],"type":"Point"}
}