{
  "type": "Feature",
  "properties": {
    "gn:admin1_code":"3.0",
    "gn:asciiname":"Saririaky",
    "gn:cc2":"MG",
    "gn:country_code":"MG",
    "gn:dem":34,
    "gn:feature_class":"P",
    "gn:feature_code":"PPL",
    "gn:name":"Saririaky",
    "gn:population":0,
    "gn:timezone":"Indian/Antananarivo",
    "iso:country":"MG",
    "name:und_x_variant":[
        "Sariaka",
        "Saririaka",
        "Saririaky"
    ],
    "wof:name":"Saririaky",
    "wof:placetype":"locality"
},
  "geometry": {"coordinates":[44.51667,-18.76667],"type":"Point"}
}