{
  "type": "Feature",
  "properties": {
    "gn:admin1_code":"6.0",
    "gn:asciiname":"Soaloka",
    "gn:cc2":"MG",
    "gn:country_code":"MG",
    "gn:dem":159,
    "gn:feature_class":"P",
    "gn:feature_code":"PPL",
    "gn:name":"Soaloka",
    "gn:population":0,
    "gn:timezone":"Indian/Antananarivo",
    "iso:country":"MG",
    "name:fra_x_preferred":[
        "Soaloka"
    ],
    "name:ita_x_preferred":[
        "Soaloka"
    ],
    "name:mlg_x_preferred":[
        "Soaloka"
    ],
    "name:nld_x_preferred":[
        "Soaloka"
    ],
    "name:und_x_variant":[
        "Soaloko"
    ],
    "wof:name":"Soaloka",
    "wof:placetype":"locality"
},
  "geometry": {"coordinates":[45.25,-18.53333],"type":"Point"}
}