{
  "type": "Feature",
  "properties": {
    "gn:admin1_code":"06",
    "gn:asciiname":"Antevamena",
    "gn:country_code":"MG",
    "gn:dem":141,
    "gn:feature_class":"P",
    "gn:feature_code":"PPL",
    "gn:name":"Antevamena",
    "gn:population":0,
    "gn:timezone":"Indian/Antananarivo",
    "iso:country":"MG",
    "wof:name":"Antevamena",
    "wof:placetype":"locality"
},
  "geometry": {"coordinates":[43.55,-22.45],"type":"Point"}
}