{
  "type": "Feature",
  "properties": {
    "gn:admin1_code":"05",
    "gn:asciiname":"Ambatotelo",
    "gn:country_code":"MG",
    "gn:dem":1354,
    "gn:feature_class":"P",
    "gn:feature_code":"PPL",
    "gn:name":"Ambatotelo",
    "gn:population":0,
    "gn:timezone":"Indian/Antananarivo",
    "iso:country":"MG",
    "wof:name":"Ambatotelo",
    "wof:placetype":"locality"
},
  "geometry": {"coordinates":[47.58333,-18.66667],"type":"Point"}
}