{
  "type": "Feature",
  "properties": {
    "gn:admin1_code":"06",
    "gn:asciiname":"Ambatomanaky",
    "gn:cc2":"MG",
    "gn:country_code":"MG",
    "gn:dem":383,
    "gn:feature_class":"P",
    "gn:feature_code":"PPL",
    "gn:name":"Ambatomanaky",
    "gn:population":0,
    "gn:timezone":"Indian/Antananarivo",
    "iso:country":"MG",
    "name:und_x_variant":[
        "Ambatomenakia",
        "Ambatomanaky"
    ],
    "wof:name":"Ambatomanaky",
    "wof:placetype":"locality"
},
  "geometry": {"coordinates":[46.35,-23.93333],"type":"Point"}
}