{
  "type": "Feature",
  "properties": {
    "gn:admin1_code":"06",
    "gn:asciiname":"Manorira",
    "gn:country_code":"MG",
    "gn:dem":281,
    "gn:feature_class":"P",
    "gn:feature_code":"PPL",
    "gn:name":"Manorira",
    "gn:population":0,
    "gn:timezone":"Indian/Antananarivo",
    "iso:country":"MG",
    "wof:name":"Manorira",
    "wof:placetype":"locality"
},
  "geometry": {"coordinates":[46.46667,-24.11667000000001],"type":"Point"}
}