{
  "type": "Feature",
  "properties": {
    "gn:admin1_code":"03",
    "gn:asciiname":"Befotaka",
    "gn:country_code":"MG",
    "gn:dem":14,
    "gn:feature_class":"P",
    "gn:feature_code":"PPL",
    "gn:name":"Befotaka",
    "gn:population":0,
    "gn:timezone":"Indian/Antananarivo",
    "iso:country":"MG",
    "name:fra_x_preferred":[
        "Befotaka"
    ],
    "name:ita_x_preferred":[
        "Befotaka"
    ],
    "name:mlg_x_preferred":[
        "Befotaka"
    ],
    "name:nld_x_preferred":[
        "Befotaka"
    ],
    "name:por_x_preferred":[
        "Befotaka"
    ],
    "wof:name":"Befotaka",
    "wof:placetype":"locality"
},
  "geometry": {"coordinates":[48.01667,-14.53333],"type":"Point"}
}