{
  "type": "Feature",
  "properties": {
    "gn:admin1_code":"03",
    "gn:asciiname":"Manorotoro",
    "gn:country_code":"MG",
    "gn:dem":804,
    "gn:feature_class":"P",
    "gn:feature_code":"PPL",
    "gn:name":"Manorotoro",
    "gn:population":0,
    "gn:timezone":"Indian/Antananarivo",
    "iso:country":"MG",
    "wof:name":"Manorotoro",
    "wof:placetype":"locality"
},
  "geometry": {"coordinates":[47.86667,-17.63332999999999],"type":"Point"}
}