{
  "type": "Feature",
  "properties": {
    "gn:admin1_code":"03",
    "gn:asciiname":"Anjiabe",
    "gn:country_code":"MG",
    "gn:dem":114,
    "gn:feature_class":"P",
    "gn:feature_code":"PPL",
    "gn:name":"Anjiabe",
    "gn:population":0,
    "gn:timezone":"Indian/Antananarivo",
    "iso:country":"MG",
    "name:fra_x_preferred":[
        "Anjiabe"
    ],
    "name:ita_x_preferred":[
        "Anjiabe"
    ],
    "name:mlg_x_preferred":[
        "Anjiabe"
    ],
    "name:nld_x_preferred":[
        "Anjiabe"
    ],
    "wof:name":"Anjiabe",
    "wof:placetype":"locality"
},
  "geometry": {"coordinates":[47.23333,-16.23333],"type":"Point"}
}