{
  "type": "Feature",
  "properties": {
    "gn:admin1_code":"2.0",
    "gn:asciiname":"Vohimary",
    "gn:country_code":"MG",
    "gn:dem":386,
    "gn:feature_class":"P",
    "gn:feature_code":"PPL",
    "gn:name":"Vohimary",
    "gn:population":0,
    "gn:timezone":"Indian/Antananarivo",
    "iso:country":"MG",
    "name:fra_x_preferred":[
        "Vohimary"
    ],
    "name:ita_x_preferred":[
        "Vohimary"
    ],
    "name:mlg_x_preferred":[
        "Vohimary"
    ],
    "name:nld_x_preferred":[
        "Vohimary"
    ],
    "wof:name":"Vohimary",
    "wof:placetype":"locality"
},
  "geometry": {"coordinates":[45.36667,-21.88333],"type":"Point"}
}