{
  "type": "Feature",
  "properties": {
    "gn:admin1_code":"02",
    "gn:asciiname":"Ianakondro",
    "gn:cc2":"MG",
    "gn:country_code":"MG",
    "gn:dem":895,
    "gn:feature_class":"P",
    "gn:feature_code":"PPL",
    "gn:name":"Ianakondro",
    "gn:population":0,
    "gn:timezone":"Indian/Antananarivo",
    "iso:country":"MG",
    "name:und_x_variant":[
        "Lanakondro",
        "Ianakondro"
    ],
    "wof:name":"Ianakondro",
    "wof:placetype":"locality"
},
  "geometry": {"coordinates":[45.61667,-22.16667],"type":"Point"}
}