{
  "type": "Feature",
  "properties": {
    "gn:admin1_code":"01",
    "gn:asciiname":"Ankaramy",
    "gn:country_code":"MG",
    "gn:dem":3,
    "gn:feature_class":"P",
    "gn:feature_code":"PPL",
    "gn:name":"Ankaramy",
    "gn:population":0,
    "gn:timezone":"Indian/Antananarivo",
    "iso:country":"MG",
    "wof:name":"Ankaramy",
    "wof:placetype":"locality"
},
  "geometry": {"coordinates":[49.66667,-12.86667],"type":"Point"}
}