{
  "type": "Feature",
  "properties": {
    "gn:admin1_code":"2.0",
    "gn:asciiname":"Soavina",
    "gn:cc2":"MG",
    "gn:country_code":"MG",
    "gn:dem":1100,
    "gn:feature_class":"P",
    "gn:feature_code":"PPL",
    "gn:name":"Soavina",
    "gn:population":0,
    "gn:timezone":"Indian/Antananarivo",
    "iso:country":"MG",
    "name:und_x_variant":[
        "Isoavina",
        "Soavina"
    ],
    "wof:name":"Soavina",
    "wof:placetype":"locality"
},
  "geometry": {"coordinates":[46.91667,-20.38333],"type":"Point"}
}