{
  "type": "Feature",
  "properties": {
    "gn:admin1_code":"01",
    "gn:asciiname":"Andrahary",
    "gn:country_code":"MG",
    "gn:dem":283,
    "gn:feature_class":"P",
    "gn:feature_code":"PPL",
    "gn:name":"Andrahary",
    "gn:population":0,
    "gn:timezone":"Indian/Antananarivo",
    "iso:country":"MG",
    "wof:name":"Andrahary",
    "wof:placetype":"locality"
},
  "geometry": {"coordinates":[49.21667,-13.51667],"type":"Point"}
}