{
  "type": "Feature",
  "properties": {
    "gn:admin1_code":"02",
    "gn:asciiname":"Befatora",
    "gn:country_code":"MG",
    "gn:dem":140,
    "gn:feature_class":"P",
    "gn:feature_code":"PPL",
    "gn:name":"Befatora",
    "gn:population":0,
    "gn:timezone":"Indian/Antananarivo",
    "iso:country":"MG",
    "wof:name":"Befatora",
    "wof:placetype":"locality"
},
  "geometry": {"coordinates":[47.41667,-22.86667000000001],"type":"Point"}
}