{
  "type": "Feature",
  "properties": {
    "gn:admin1_code":"4.0",
    "gn:asciiname":"Tetezambahatra",
    "gn:cc2":"MG",
    "gn:country_code":"MG",
    "gn:dem":364,
    "gn:feature_class":"P",
    "gn:feature_code":"PPL",
    "gn:name":"Tetezambahatra",
    "gn:population":0,
    "gn:timezone":"Indian/Antananarivo",
    "iso:country":"MG",
    "name:und_x_variant":[
        "Antetezambahatra",
        "Tetezambahatra"
    ],
    "wof:name":"Tetezambahatra",
    "wof:placetype":"locality"
},
  "geometry": {"coordinates":[48.81667,-19.21667],"type":"Point"}
}