{
  "type": "Feature",
  "properties": {
    "gn:admin1_code":"03",
    "gn:asciiname":"Anjalazala",
    "gn:cc2":"MG",
    "gn:country_code":"MG",
    "gn:dem":149,
    "gn:feature_class":"P",
    "gn:feature_code":"PPL",
    "gn:name":"Anjalazala",
    "gn:population":0,
    "gn:timezone":"Indian/Antananarivo",
    "iso:country":"MG",
    "name:fra_x_preferred":[
        "Anjalazala"
    ],
    "name:ita_x_preferred":[
        "Anjalazala"
    ],
    "name:mlg_x_preferred":[
        "Anjalazala"
    ],
    "name:nld_x_preferred":[
        "Anjalazala"
    ],
    "name:und_x_variant":[
        "Anjalajala"
    ],
    "wof:name":"Anjalazala",
    "wof:placetype":"locality"
},
  "geometry": {"coordinates":[48.18333,-15.01667],"type":"Point"}
}