{
  "type": "Feature",
  "properties": {
    "gn:admin1_code":"06",
    "gn:asciiname":"Imangaika",
    "gn:country_code":"MG",
    "gn:dem":152,
    "gn:feature_class":"P",
    "gn:feature_code":"PPL",
    "gn:name":"Imangaika",
    "gn:population":0,
    "gn:timezone":"Indian/Antananarivo",
    "iso:country":"MG",
    "wof:name":"Imangaika",
    "wof:placetype":"locality"
},
  "geometry": {"coordinates":[46.96667,-24.91667],"type":"Point"}
}