{
  "type": "Feature",
  "properties": {
    "gn:admin1_code":"01",
    "gn:asciiname":"Matsoborilava",
    "gn:cc2":"MG",
    "gn:country_code":"MG",
    "gn:dem":76,
    "gn:feature_class":"P",
    "gn:feature_code":"PPL",
    "gn:name":"Matsoborilava",
    "gn:population":0,
    "gn:timezone":"Indian/Antananarivo",
    "iso:country":"MG",
    "name:und_x_variant":[
        "Matsaborilava",
        "Matsoborilava"
    ],
    "wof:name":"Matsoborilava",
    "wof:placetype":"locality"
},
  "geometry": {"coordinates":[49.01667,-13.28333],"type":"Point"}
}