{
  "type": "Feature",
  "properties": {
    "gn:admin1_code":"06",
    "gn:asciiname":"Bezaha",
    "gn:country_code":"MG",
    "gn:dem":600,
    "gn:feature_class":"P",
    "gn:feature_code":"PPL",
    "gn:name":"Bezaha",
    "gn:population":0,
    "gn:timezone":"Indian/Antananarivo",
    "iso:country":"MG",
    "name:fra_x_preferred":[
        "Bezaha"
    ],
    "name:ita_x_preferred":[
        "Bezaha"
    ],
    "name:mlg_x_preferred":[
        "Bezaha"
    ],
    "name:nld_x_preferred":[
        "Bezaha"
    ],
    "name:zho_x_preferred":[
        "\u8c9d\u624e\u54c8"
    ],
    "wof:name":"Bezaha",
    "wof:placetype":"locality"
},
  "geometry": {"coordinates":[44.05,-22.76667],"type":"Point"}
}