{
  "type": "Feature",
  "properties": {
    "gn:admin1_code":"01",
    "gn:asciiname":"Ambanikibo",
    "gn:cc2":"MG",
    "gn:country_code":"MG",
    "gn:dem":50,
    "gn:feature_class":"P",
    "gn:feature_code":"PPL",
    "gn:name":"Ambanikibo",
    "gn:population":0,
    "gn:timezone":"Indian/Antananarivo",
    "iso:country":"MG",
    "name:und_x_variant":[
        "Ambanihiko",
        "Ambanikibo"
    ],
    "wof:name":"Ambanikibo",
    "wof:placetype":"locality"
},
  "geometry": {"coordinates":[48.83333,-13.58333],"type":"Point"}
}