{
  "type": "Feature",
  "properties": {
    "gn:admin1_code":"01",
    "gn:asciiname":"Anjiabe",
    "gn:country_code":"MG",
    "gn:dem":57,
    "gn:feature_class":"P",
    "gn:feature_code":"PPL",
    "gn:name":"Anjiabe",
    "gn:population":0,
    "gn:timezone":"Indian/Antananarivo",
    "iso:country":"MG",
    "name:fra_x_preferred":[
        "Anjiabe"
    ],
    "name:ita_x_preferred":[
        "Anjiabe"
    ],
    "name:mlg_x_preferred":[
        "Anjiabe"
    ],
    "name:nld_x_preferred":[
        "Anjiabe"
    ],
    "wof:name":"Anjiabe",
    "wof:placetype":"locality"
},
  "geometry": {"coordinates":[49.83333,-13.06667],"type":"Point"}
}