{
  "type": "Feature",
  "properties": {
    "gn:admin1_code":"02",
    "gn:asciiname":"Bemahabo",
    "gn:country_code":"MG",
    "gn:dem":713,
    "gn:feature_class":"P",
    "gn:feature_code":"PPL",
    "gn:name":"Bemahabo",
    "gn:population":0,
    "gn:timezone":"Indian/Antananarivo",
    "iso:country":"MG",
    "wof:name":"Bemahabo",
    "wof:placetype":"locality"
},
  "geometry": {"coordinates":[46.33333,-22.65],"type":"Point"}
}