{
  "type": "Feature",
  "properties": {
    "gn:admin1_code":"2.0",
    "gn:asciiname":"Vohimena",
    "gn:country_code":"MG",
    "gn:dem":1246,
    "gn:feature_class":"P",
    "gn:feature_code":"PPL",
    "gn:name":"Vohimena",
    "gn:population":0,
    "gn:timezone":"Indian/Antananarivo",
    "iso:country":"MG",
    "wof:name":"Vohimena",
    "wof:placetype":"locality"
},
  "geometry": {"coordinates":[46.95,-20.85],"type":"Point"}
}