{
  "type": "Feature",
  "properties": {
    "gn:admin1_code":"06",
    "gn:asciiname":"Mitsitiky",
    "gn:cc2":"MG",
    "gn:country_code":"MG",
    "gn:dem":62,
    "gn:feature_class":"P",
    "gn:feature_code":"PPL",
    "gn:name":"Mitsitiky",
    "gn:population":0,
    "gn:timezone":"Indian/Antananarivo",
    "iso:country":"MG",
    "name:und_x_variant":[
        "Milsitiha",
        "Mitsitika",
        "Mitsitiky"
    ],
    "wof:name":"Mitsitiky",
    "wof:placetype":"locality"
},
  "geometry": {"coordinates":[44.38333,-20.65],"type":"Point"}
}