{
  "type": "Feature",
  "properties": {
    "gn:admin1_code":"4.0",
    "gn:asciiname":"Tolongoina",
    "gn:country_code":"MG",
    "gn:dem":489,
    "gn:feature_class":"P",
    "gn:feature_code":"PPL",
    "gn:name":"Tolongoina",
    "gn:population":0,
    "gn:timezone":"Indian/Antananarivo",
    "iso:country":"MG",
    "name:deu_x_preferred":[
        "Tolongoina"
    ],
    "name:fra_x_preferred":[
        "Tolongoina"
    ],
    "name:ita_x_preferred":[
        "Tolongoina"
    ],
    "name:mlg_x_preferred":[
        "Tolongoina"
    ],
    "name:nld_x_preferred":[
        "Tolongoina"
    ],
    "wof:name":"Tolongoina",
    "wof:placetype":"locality"
},
  "geometry": {"coordinates":[49.28333,-16.58333],"type":"Point"}
}