{
  "type": "Feature",
  "properties": {
    "gn:admin1_code":"06",
    "gn:asciiname":"Ranohendry",
    "gn:country_code":"MG",
    "gn:dem":784,
    "gn:feature_class":"P",
    "gn:feature_code":"PPL",
    "gn:name":"Ranohendry",
    "gn:population":0,
    "gn:timezone":"Indian/Antananarivo",
    "iso:country":"MG",
    "wof:name":"Ranohendry",
    "wof:placetype":"locality"
},
  "geometry": {"coordinates":[45.85,-23.05],"type":"Point"}
}