{
  "type": "Feature",
  "properties": {
    "gn:admin1_code":"06",
    "gn:asciiname":"Belolo",
    "gn:country_code":"MG",
    "gn:dem":114,
    "gn:feature_class":"P",
    "gn:feature_code":"PPL",
    "gn:name":"Belolo",
    "gn:population":0,
    "gn:timezone":"Indian/Antananarivo",
    "iso:country":"MG",
    "wof:name":"Belolo",
    "wof:placetype":"locality"
},
  "geometry": {"coordinates":[43.71667,-22.21667],"type":"Point"}
}