{
  "type": "Feature",
  "properties": {
    "gn:admin1_code":"02",
    "gn:asciiname":"Manitsy Atsinanana",
    "gn:cc2":"MG",
    "gn:country_code":"MG",
    "gn:dem":624,
    "gn:feature_class":"P",
    "gn:feature_code":"PPL",
    "gn:name":"Manitsy Atsinanana",
    "gn:population":0,
    "gn:timezone":"Indian/Antananarivo",
    "iso:country":"MG",
    "name:und_x_variant":[
        "Manitsy",
        "Manitsy Atsinanana"
    ],
    "wof:name":"Manitsy Atsinanana",
    "wof:placetype":"locality"
},
  "geometry": {"coordinates":[46.66667,-23.25],"type":"Point"}
}