{
  "type": "Feature",
  "properties": {
    "gn:admin1_code":"01",
    "gn:asciiname":"Marotaolana",
    "gn:cc2":"MG",
    "gn:country_code":"MG",
    "gn:dem":237,
    "gn:feature_class":"P",
    "gn:feature_code":"PPL",
    "gn:name":"Marotaolana",
    "gn:population":0,
    "gn:timezone":"Indian/Antananarivo",
    "iso:country":"MG",
    "name:und_x_variant":[
        "Marotolana",
        "Marotaolana"
    ],
    "wof:name":"Marotaolana",
    "wof:placetype":"locality"
},
  "geometry": {"coordinates":[48.61667,-14.01667],"type":"Point"}
}