{
  "type": "Feature",
  "properties": {
    "gn:admin1_code":"02",
    "gn:asciiname":"Ampasitanjona",
    "gn:country_code":"MG",
    "gn:dem":1251,
    "gn:feature_class":"P",
    "gn:feature_code":"PPL",
    "gn:name":"Ampasitanjona",
    "gn:population":0,
    "gn:timezone":"Indian/Antananarivo",
    "iso:country":"MG",
    "wof:name":"Ampasitanjona",
    "wof:placetype":"locality"
},
  "geometry": {"coordinates":[47.25,-21.21667],"type":"Point"}
}