{
  "type": "Feature",
  "properties": {
    "gn:admin1_code":"01",
    "gn:asciiname":"Lambert",
    "gn:country_code":"MG",
    "gn:dem":-9999,
    "gn:feature_class":"P",
    "gn:feature_code":"PPL",
    "gn:name":"Lambert",
    "gn:population":0,
    "gn:timezone":"Indian/Antananarivo",
    "iso:country":"MG",
    "wof:name":"Lambert",
    "wof:placetype":"locality"
},
  "geometry": {"coordinates":[48.18333,-13.31667],"type":"Point"}
}