{
  "type": "Feature",
  "properties": {
    "gn:admin1_code":"02",
    "gn:asciiname":"Mahatsinjo",
    "gn:country_code":"MG",
    "gn:dem":80,
    "gn:feature_class":"P",
    "gn:feature_code":"PPL",
    "gn:name":"Mahatsinjo",
    "gn:population":0,
    "gn:timezone":"Indian/Antananarivo",
    "iso:country":"MG",
    "wof:name":"Mahatsinjo",
    "wof:placetype":"locality"
},
  "geometry": {"coordinates":[47.38333,-22.65],"type":"Point"}
}