{
  "type": "Feature",
  "properties": {
    "gn:admin1_code":"06",
    "gn:asciiname":"Antsokay",
    "gn:country_code":"MG",
    "gn:dem":7,
    "gn:feature_class":"P",
    "gn:feature_code":"PPL",
    "gn:name":"Antsokay",
    "gn:population":0,
    "gn:timezone":"Indian/Antananarivo",
    "iso:country":"MG",
    "wof:name":"Antsokay",
    "wof:placetype":"locality"
},
  "geometry": {"coordinates":[43.75,-23.41667],"type":"Point"}
}