{
  "type": "Feature",
  "properties": {
    "gn:admin1_code":"06",
    "gn:asciiname":"Ilafy",
    "gn:country_code":"MG",
    "gn:dem":70,
    "gn:feature_class":"P",
    "gn:feature_code":"PPL",
    "gn:name":"Ilafy",
    "gn:population":0,
    "gn:timezone":"Indian/Antananarivo",
    "iso:country":"MG",
    "name:fra_x_preferred":[
        "Ilafy"
    ],
    "name:ind_x_preferred":[
        "Ilafy"
    ],
    "name:ita_x_preferred":[
        "Ilafy"
    ],
    "name:mlg_x_preferred":[
        "Ilafy"
    ],
    "name:nld_x_preferred":[
        "Ilafy"
    ],
    "wof:name":"Ilafy",
    "wof:placetype":"locality"
},
  "geometry": {"coordinates":[45.33333,-19.78333],"type":"Point"}
}