{
  "type": "Feature",
  "properties": {
    "gn:admin1_code":"05",
    "gn:asciiname":"Maintiakoho",
    "gn:country_code":"MG",
    "gn:dem":925,
    "gn:feature_class":"P",
    "gn:feature_code":"PPL",
    "gn:name":"Maintiakoho",
    "gn:population":0,
    "gn:timezone":"Indian/Antananarivo",
    "iso:country":"MG",
    "wof:name":"Maintiakoho",
    "wof:placetype":"locality"
},
  "geometry": {"coordinates":[46.41667,-19.18333],"type":"Point"}
}