{
  "type": "Feature",
  "properties": {
    "gn:admin1_code":"05",
    "gn:asciiname":"Ambodiampaly",
    "gn:country_code":"MG",
    "gn:dem":1174,
    "gn:feature_class":"P",
    "gn:feature_code":"PPL",
    "gn:name":"Ambodiampaly",
    "gn:population":0,
    "gn:timezone":"Indian/Antananarivo",
    "iso:country":"MG",
    "wof:name":"Ambodiampaly",
    "wof:placetype":"locality"
},
  "geometry": {"coordinates":[46.78333,-18.83333],"type":"Point"}
}