{
  "type": "Feature",
  "properties": {
    "gn:admin1_code":"02",
    "gn:asciiname":"Andrekosy",
    "gn:country_code":"MG",
    "gn:dem":927,
    "gn:feature_class":"P",
    "gn:feature_code":"PPL",
    "gn:name":"Andrekosy",
    "gn:population":0,
    "gn:timezone":"Indian/Antananarivo",
    "iso:country":"MG",
    "wof:name":"Andrekosy",
    "wof:placetype":"locality"
},
  "geometry": {"coordinates":[46.21667,-20.75],"type":"Point"}
}