{
  "type": "Feature",
  "properties": {
    "gn:admin1_code":"06",
    "gn:asciiname":"Bebakaka",
    "gn:country_code":"MG",
    "gn:dem":513,
    "gn:feature_class":"P",
    "gn:feature_code":"PPL",
    "gn:name":"Bebakaka",
    "gn:population":0,
    "gn:timezone":"Indian/Antananarivo",
    "iso:country":"MG",
    "wof:name":"Bebakaka",
    "wof:placetype":"locality"
},
  "geometry": {"coordinates":[45.06667,-24.05],"type":"Point"}
}