{
  "type": "Feature",
  "properties": {
    "gn:admin1_code":"06",
    "gn:asciiname":"Ambiatoka",
    "gn:country_code":"MG",
    "gn:dem":266,
    "gn:feature_class":"P",
    "gn:feature_code":"PPL",
    "gn:name":"Ambiatoka",
    "gn:population":0,
    "gn:timezone":"Indian/Antananarivo",
    "iso:country":"MG",
    "wof:name":"Ambiatoka",
    "wof:placetype":"locality"
},
  "geometry": {"coordinates":[44.75,-21.08333],"type":"Point"}
}