{
  "type": "Feature",
  "properties": {
    "gn:admin1_code":"02",
    "gn:asciiname":"Marindrano",
    "gn:country_code":"MG",
    "gn:dem":224,
    "gn:feature_class":"P",
    "gn:feature_code":"PPL",
    "gn:name":"Marindrano",
    "gn:population":0,
    "gn:timezone":"Indian/Antananarivo",
    "iso:country":"MG",
    "wof:name":"Marindrano",
    "wof:placetype":"locality"
},
  "geometry": {"coordinates":[47.53333,-21.68333],"type":"Point"}
}