{
  "type": "Feature",
  "properties": {
    "gn:admin1_code":"06",
    "gn:asciiname":"Ambabaky",
    "gn:country_code":"MG",
    "gn:dem":426,
    "gn:feature_class":"P",
    "gn:feature_code":"PPL",
    "gn:name":"Ambabaky",
    "gn:population":0,
    "gn:timezone":"Indian/Antananarivo",
    "iso:country":"MG",
    "wof:name":"Ambabaky",
    "wof:placetype":"locality"
},
  "geometry": {"coordinates":[45.03333,-22.21667],"type":"Point"}
}