{
  "type": "Feature",
  "properties": {
    "gn:admin1_code":"04",
    "gn:asciiname":"Ambodirafia",
    "gn:cc2":"MG",
    "gn:country_code":"MG",
    "gn:dem":557,
    "gn:feature_class":"P",
    "gn:feature_code":"PPL",
    "gn:name":"Ambodirafia",
    "gn:population":0,
    "gn:timezone":"Indian/Antananarivo",
    "iso:country":"MG",
    "name:und_x_variant":[
        "Ambodirofia",
        "Ambodirafia"
    ],
    "wof:name":"Ambodirafia",
    "wof:placetype":"locality"
},
  "geometry": {"coordinates":[48.93333,-17.38332999999999],"type":"Point"}
}