{
  "type": "Feature",
  "properties": {
    "gn:admin1_code":"04",
    "gn:asciiname":"Ambohikarabo",
    "gn:country_code":"MG",
    "gn:dem":478,
    "gn:feature_class":"P",
    "gn:feature_code":"PPL",
    "gn:name":"Ambohikarabo",
    "gn:population":0,
    "gn:timezone":"Indian/Antananarivo",
    "iso:country":"MG",
    "wof:name":"Ambohikarabo",
    "wof:placetype":"locality"
},
  "geometry": {"coordinates":[49.45,-16.25],"type":"Point"}
}