{
  "type": "Feature",
  "properties": {
    "gn:admin1_code":"06",
    "gn:asciiname":"Betaimbala",
    "gn:country_code":"MG",
    "gn:dem":624,
    "gn:feature_class":"P",
    "gn:feature_code":"PPL",
    "gn:name":"Betaimbala",
    "gn:population":0,
    "gn:timezone":"Indian/Antananarivo",
    "iso:country":"MG",
    "wof:name":"Betaimbala",
    "wof:placetype":"locality"
},
  "geometry": {"coordinates":[45.61667,-23.71667],"type":"Point"}
}