{
  "type": "Feature",
  "properties": {
    "gn:admin1_code":"02",
    "gn:asciiname":"Ampataka",
    "gn:country_code":"MG",
    "gn:dem":51,
    "gn:feature_class":"P",
    "gn:feature_code":"PPL",
    "gn:name":"Ampataka",
    "gn:population":0,
    "gn:timezone":"Indian/Antananarivo",
    "iso:country":"MG",
    "name:azb_x_preferred":[
        "\u0627\u0645\u067e\u0627\u062a\u0627\u06a9\u0627"
    ],
    "name:fas_x_preferred":[
        "\u0627\u0645\u067e\u0627\u062a\u0627\u06a9\u0627"
    ],
    "name:fra_x_preferred":[
        "Ampataka"
    ],
    "name:ita_x_preferred":[
        "Ampataka"
    ],
    "name:mlg_x_preferred":[
        "Ampataka"
    ],
    "name:nld_x_preferred":[
        "Ampataka"
    ],
    "wof:name":"Ampataka",
    "wof:placetype":"locality"
},
  "geometry": {"coordinates":[47.46667,-23.35],"type":"Point"}
}