{
  "type": "Feature",
  "properties": {
    "gn:admin1_code":"02",
    "gn:asciiname":"Benato",
    "gn:country_code":"MG",
    "gn:dem":763,
    "gn:feature_class":"P",
    "gn:feature_code":"PPL",
    "gn:name":"Benato",
    "gn:population":0,
    "gn:timezone":"Indian/Antananarivo",
    "iso:country":"MG",
    "wof:name":"Benato",
    "wof:placetype":"locality"
},
  "geometry": {"coordinates":[45.48333,-22.71667],"type":"Point"}
}