{
  "type": "Feature",
  "properties": {
    "gn:admin1_code":"06",
    "gn:asciiname":"Mahavelo",
    "gn:cc2":"MG",
    "gn:country_code":"MG",
    "gn:dem":39,
    "gn:feature_class":"P",
    "gn:feature_code":"PPL",
    "gn:name":"Mahavelo",
    "gn:population":0,
    "gn:timezone":"Indian/Antananarivo",
    "iso:country":"MG",
    "name:und_x_variant":[
        "Mahavelona",
        "Mahavelo"
    ],
    "wof:name":"Mahavelo",
    "wof:placetype":"locality"
},
  "geometry": {"coordinates":[44.63333,-19.66667],"type":"Point"}
}