{
  "type": "Feature",
  "properties": {
    "gn:admin1_code":"05",
    "gn:asciiname":"Ankondondona",
    "gn:country_code":"MG",
    "gn:dem":1152,
    "gn:feature_class":"P",
    "gn:feature_code":"PPL",
    "gn:name":"Ankondondona",
    "gn:population":0,
    "gn:timezone":"Indian/Antananarivo",
    "iso:country":"MG",
    "wof:name":"Ankondondona",
    "wof:placetype":"locality"
},
  "geometry": {"coordinates":[47.78333,-18.08333],"type":"Point"}
}