{
  "type": "Feature",
  "properties": {
    "gn:admin1_code":"02",
    "gn:asciiname":"Nasandratony",
    "gn:cc2":"MG",
    "gn:country_code":"MG",
    "gn:dem":1099,
    "gn:feature_class":"P",
    "gn:feature_code":"PPL",
    "gn:name":"Nasandratony",
    "gn:population":0,
    "gn:timezone":"Indian/Antananarivo",
    "iso:country":"MG",
    "name:und_x_variant":[
        "Isandratrony",
        "Nasandratony"
    ],
    "wof:name":"Nasandratony",
    "wof:placetype":"locality"
},
  "geometry": {"coordinates":[47.03333,-21.35],"type":"Point"}
}