{
  "type": "Feature",
  "properties": {
    "gn:admin1_code":"06",
    "gn:asciiname":"Anja-Ampandrabe",
    "gn:country_code":"MG",
    "gn:dem":509,
    "gn:feature_class":"P",
    "gn:feature_code":"PPL",
    "gn:name":"Anja-Ampandrabe",
    "gn:population":0,
    "gn:timezone":"Indian/Antananarivo",
    "iso:country":"MG",
    "wof:name":"Anja-Ampandrabe",
    "wof:placetype":"locality"
},
  "geometry": {"coordinates":[44.63333,-22.78333],"type":"Point"}
}