{
  "type": "Feature",
  "properties": {
    "gn:admin1_code":"02",
    "gn:asciiname":"Maromena",
    "gn:country_code":"MG",
    "gn:dem":420,
    "gn:feature_class":"P",
    "gn:feature_code":"PPL",
    "gn:name":"Maromena",
    "gn:population":0,
    "gn:timezone":"Indian/Antananarivo",
    "iso:country":"MG",
    "wof:name":"Maromena",
    "wof:placetype":"locality"
},
  "geometry": {"coordinates":[47.63333,-21.26667],"type":"Point"}
}