{
  "type": "Feature",
  "properties": {
    "gn:admin1_code":"05",
    "gn:asciiname":"Andranofeno",
    "gn:country_code":"MG",
    "gn:dem":1390,
    "gn:feature_class":"P",
    "gn:feature_code":"PPL",
    "gn:name":"Andranofeno",
    "gn:population":0,
    "gn:timezone":"Indian/Antananarivo",
    "iso:country":"MG",
    "wof:name":"Andranofeno",
    "wof:placetype":"locality"
},
  "geometry": {"coordinates":[47.16667,-18.06667],"type":"Point"}
}