{
  "type": "Feature",
  "properties": {
    "gn:admin1_code":"03",
    "gn:asciiname":"Anandrobato",
    "gn:country_code":"MG",
    "gn:dem":1067,
    "gn:feature_class":"P",
    "gn:feature_code":"PPL",
    "gn:name":"Anandrobato",
    "gn:population":0,
    "gn:timezone":"Indian/Antananarivo",
    "iso:country":"MG",
    "wof:name":"Anandrobato",
    "wof:placetype":"locality"
},
  "geometry": {"coordinates":[48.73333,-14.55],"type":"Point"}
}