{
  "type": "Feature",
  "properties": {
    "gn:admin1_code":"3.0",
    "gn:asciiname":"Saboany",
    "gn:cc2":"MG",
    "gn:country_code":"MG",
    "gn:dem":11,
    "gn:feature_class":"P",
    "gn:feature_code":"PPL",
    "gn:name":"Saboany",
    "gn:population":0,
    "gn:timezone":"Indian/Antananarivo",
    "iso:country":"MG",
    "name:und_x_variant":[
        "Sakoany",
        "Saboany"
    ],
    "wof:name":"Saboany",
    "wof:placetype":"locality"
},
  "geometry": {"coordinates":[46.23333,-15.85],"type":"Point"}
}