{
  "type": "Feature",
  "properties": {
    "gn:admin1_code":"06",
    "gn:asciiname":"Ampamandrika",
    "gn:country_code":"MG",
    "gn:dem":118,
    "gn:feature_class":"P",
    "gn:feature_code":"PPL",
    "gn:name":"Ampamandrika",
    "gn:population":0,
    "gn:timezone":"Indian/Antananarivo",
    "iso:country":"MG",
    "wof:name":"Ampamandrika",
    "wof:placetype":"locality"
},
  "geometry": {"coordinates":[45.58333,-20.26667],"type":"Point"}
}