{
  "type": "Feature",
  "properties": {
    "gn:admin1_code":"04",
    "gn:asciiname":"Andranomainty",
    "gn:country_code":"MG",
    "gn:dem":718,
    "gn:feature_class":"P",
    "gn:feature_code":"PPL",
    "gn:name":"Andranomainty",
    "gn:population":0,
    "gn:timezone":"Indian/Antananarivo",
    "iso:country":"MG",
    "wof:name":"Andranomainty",
    "wof:placetype":"locality"
},
  "geometry": {"coordinates":[48.35,-19.58333],"type":"Point"}
}