{
  "type": "Feature",
  "properties": {
    "gn:admin1_code":"06",
    "gn:asciiname":"Besavoa",
    "gn:country_code":"MG",
    "gn:dem":249,
    "gn:feature_class":"P",
    "gn:feature_code":"PPL",
    "gn:name":"Besavoa",
    "gn:population":0,
    "gn:timezone":"Indian/Antananarivo",
    "iso:country":"MG",
    "wof:name":"Besavoa",
    "wof:placetype":"locality"
},
  "geometry": {"coordinates":[44.68333,-24.75],"type":"Point"}
}