{
  "type": "Feature",
  "properties": {
    "gn:admin1_code":"02",
    "gn:asciiname":"Iakasy",
    "gn:country_code":"MG",
    "gn:dem":357,
    "gn:feature_class":"P",
    "gn:feature_code":"PPL",
    "gn:name":"Iakasy",
    "gn:population":0,
    "gn:timezone":"Indian/Antananarivo",
    "iso:country":"MG",
    "wof:name":"Iakasy",
    "wof:placetype":"locality"
},
  "geometry": {"coordinates":[45.25,-21.91667],"type":"Point"}
}