{
  "type": "Feature",
  "properties": {
    "gn:admin1_code":"02",
    "gn:asciiname":"Andrombato",
    "gn:country_code":"MG",
    "gn:dem":1226,
    "gn:feature_class":"P",
    "gn:feature_code":"PPL",
    "gn:name":"Andrombato",
    "gn:population":0,
    "gn:timezone":"Indian/Antananarivo",
    "iso:country":"MG",
    "wof:name":"Andrombato",
    "wof:placetype":"locality"
},
  "geometry": {"coordinates":[46.75,-22.23333],"type":"Point"}
}