{
  "type": "Feature",
  "properties": {
    "gn:admin1_code":"06",
    "gn:asciiname":"Ampotaka Atsimo",
    "gn:cc2":"MG",
    "gn:country_code":"MG",
    "gn:dem":64,
    "gn:feature_class":"P",
    "gn:feature_code":"PPL",
    "gn:name":"Ampotaka Atsimo",
    "gn:population":0,
    "gn:timezone":"Indian/Antananarivo",
    "iso:country":"MG",
    "name:und_x_variant":[
        "Ampotaka Sud",
        "Ampotaka Atsimo"
    ],
    "wof:name":"Ampotaka Atsimo",
    "wof:placetype":"locality"
},
  "geometry": {"coordinates":[44.66667,-25.06667],"type":"Point"}
}