{
  "type": "Feature",
  "properties": {
    "gn:admin1_code":"01",
    "gn:asciiname":"Betaimborona",
    "gn:country_code":"MG",
    "gn:dem":83,
    "gn:feature_class":"P",
    "gn:feature_code":"PPL",
    "gn:name":"Betaimborona",
    "gn:population":0,
    "gn:timezone":"Indian/Antananarivo",
    "iso:country":"MG",
    "wof:name":"Betaimborona",
    "wof:placetype":"locality"
},
  "geometry": {"coordinates":[49.21667,-13.26667],"type":"Point"}
}