{
  "type": "Feature",
  "properties": {
    "gn:admin1_code":"04",
    "gn:asciiname":"Ambinanivavony",
    "gn:cc2":"MG",
    "gn:country_code":"MG",
    "gn:dem":532,
    "gn:feature_class":"P",
    "gn:feature_code":"PPL",
    "gn:name":"Ambinanivavony",
    "gn:population":0,
    "gn:timezone":"Indian/Antananarivo",
    "iso:country":"MG",
    "name:und_x_variant":[
        "Ambinanivavany",
        "Ambinanibavoni",
        "Ambinanyvavony",
        "Ambinanivavony"
    ],
    "wof:name":"Ambinanivavony",
    "wof:placetype":"locality"
},
  "geometry": {"coordinates":[48.91667,-18.11667000000001],"type":"Point"}
}