{
  "type": "Feature",
  "properties": {
    "gn:admin1_code":"02",
    "gn:asciiname":"Ambalavao Nord",
    "gn:country_code":"MG",
    "gn:dem":1460,
    "gn:feature_class":"P",
    "gn:feature_code":"PPL",
    "gn:name":"Ambalavao Nord",
    "gn:population":0,
    "gn:timezone":"Indian/Antananarivo",
    "iso:country":"MG",
    "wof:name":"Ambalavao Nord",
    "wof:placetype":"locality"
},
  "geometry": {"coordinates":[47.05,-21.76667],"type":"Point"}
}