{
  "type": "Feature",
  "properties": {
    "gn:admin1_code":"01",
    "gn:asciiname":"Ambodivoahangy",
    "gn:country_code":"MG",
    "gn:dem":206,
    "gn:feature_class":"P",
    "gn:feature_code":"PPL",
    "gn:name":"Ambodivoahangy",
    "gn:population":0,
    "gn:timezone":"Indian/Antananarivo",
    "iso:country":"MG",
    "wof:name":"Ambodivoahangy",
    "wof:placetype":"locality"
},
  "geometry": {"coordinates":[50.11667,-14.93333],"type":"Point"}
}