{
  "type": "Feature",
  "properties": {
    "gn:admin1_code":"03",
    "gn:asciiname":"Ankisompy",
    "gn:country_code":"MG",
    "gn:dem":275,
    "gn:feature_class":"P",
    "gn:feature_code":"PPL",
    "gn:name":"Ankisompy",
    "gn:population":0,
    "gn:timezone":"Indian/Antananarivo",
    "iso:country":"MG",
    "wof:name":"Ankisompy",
    "wof:placetype":"locality"
},
  "geometry": {"coordinates":[47.83333,-16.25],"type":"Point"}
}