{
  "type": "Feature",
  "properties": {
    "gn:admin1_code":"02",
    "gn:asciiname":"Menamaty Iloto",
    "gn:cc2":"MG",
    "gn:country_code":"MG",
    "gn:dem":377,
    "gn:feature_class":"P",
    "gn:feature_code":"PPL",
    "gn:name":"Menamaty Iloto",
    "gn:population":0,
    "gn:timezone":"Indian/Antananarivo",
    "iso:country":"MG",
    "name:und_x_variant":[
        "Iloto",
        "Menamaty Iloto"
    ],
    "wof:name":"Menamaty Iloto",
    "wof:placetype":"locality"
},
  "geometry": {"coordinates":[45.38333,-21.95],"type":"Point"}
}