{
  "type": "Feature",
  "properties": {
    "gn:admin1_code":"2.0",
    "gn:asciiname":"Vohidravina",
    "gn:country_code":"MG",
    "gn:dem":19,
    "gn:feature_class":"P",
    "gn:feature_code":"PPL",
    "gn:name":"Vohidravina",
    "gn:population":0,
    "gn:timezone":"Indian/Antananarivo",
    "iso:country":"MG",
    "wof:name":"Vohidravina",
    "wof:placetype":"locality"
},
  "geometry": {"coordinates":[47.75,-22.23333],"type":"Point"}
}