{
  "type": "Feature",
  "properties": {
    "gn:admin1_code":"2.0",
    "gn:asciiname":"Saonjovy",
    "gn:country_code":"MG",
    "gn:dem":685,
    "gn:feature_class":"P",
    "gn:feature_code":"PPL",
    "gn:name":"Saonjovy",
    "gn:population":0,
    "gn:timezone":"Indian/Antananarivo",
    "iso:country":"MG",
    "wof:name":"Saonjovy",
    "wof:placetype":"locality"
},
  "geometry": {"coordinates":[46.21667,-21.25],"type":"Point"}
}