{
  "type": "Feature",
  "properties": {
    "gn:admin1_code":"06",
    "gn:asciiname":"Fihake",
    "gn:cc2":"MG",
    "gn:country_code":"MG",
    "gn:dem":671,
    "gn:feature_class":"P",
    "gn:feature_code":"PPL",
    "gn:name":"Fihake",
    "gn:population":0,
    "gn:timezone":"Indian/Antananarivo",
    "iso:country":"MG",
    "name:und_x_variant":[
        "Fihaka",
        "Fihiake",
        "Fihake"
    ],
    "wof:name":"Fihake",
    "wof:placetype":"locality"
},
  "geometry": {"coordinates":[44.66667,-22.51667],"type":"Point"}
}