{
  "type": "Feature",
  "properties": {
    "gn:admin1_code":"02",
    "gn:asciiname":"Ambodiara II",
    "gn:cc2":"MG",
    "gn:country_code":"MG",
    "gn:dem":72,
    "gn:feature_class":"P",
    "gn:feature_code":"PPL",
    "gn:name":"Ambodiara II",
    "gn:population":0,
    "gn:timezone":"Indian/Antananarivo",
    "iso:country":"MG",
    "name:und_x_variant":[
        "Ambodiara",
        "Ambodiara II"
    ],
    "wof:name":"Ambodiara II",
    "wof:placetype":"locality"
},
  "geometry": {"coordinates":[48.35,-20.48333],"type":"Point"}
}