{
  "type": "Feature",
  "properties": {
    "gn:admin1_code":"06",
    "gn:asciiname":"Androtsy",
    "gn:cc2":"MG",
    "gn:country_code":"MG",
    "gn:dem":485,
    "gn:feature_class":"P",
    "gn:feature_code":"PPL",
    "gn:name":"Androtsy",
    "gn:population":0,
    "gn:timezone":"Indian/Antananarivo",
    "iso:country":"MG",
    "name:und_x_variant":[
        "Androtsa",
        "Androtsy"
    ],
    "wof:name":"Androtsy",
    "wof:placetype":"locality"
},
  "geometry": {"coordinates":[45.18333,-24.08333],"type":"Point"}
}