{
  "type": "Feature",
  "properties": {
    "gn:admin1_code":"05",
    "gn:asciiname":"Ambatomalaza",
    "gn:country_code":"MG",
    "gn:dem":1345,
    "gn:feature_class":"P",
    "gn:feature_code":"PPL",
    "gn:name":"Ambatomalaza",
    "gn:population":0,
    "gn:timezone":"Indian/Antananarivo",
    "iso:country":"MG",
    "wof:name":"Ambatomalaza",
    "wof:placetype":"locality"
},
  "geometry": {"coordinates":[47.63333,-18.61667000000001],"type":"Point"}
}