{
  "type": "Feature",
  "properties": {
    "gn:admin1_code":"6.0",
    "gn:asciiname":"Soakija",
    "gn:country_code":"MG",
    "gn:dem":1203,
    "gn:feature_class":"P",
    "gn:feature_code":"PPL",
    "gn:name":"Soakija",
    "gn:population":0,
    "gn:timezone":"Indian/Antananarivo",
    "iso:country":"MG",
    "wof:name":"Soakija",
    "wof:placetype":"locality"
},
  "geometry": {"coordinates":[46.36667,-23.73333],"type":"Point"}
}