{
  "type": "Feature",
  "properties": {
    "gn:admin1_code":"03",
    "gn:asciiname":"Anaborano",
    "gn:country_code":"MG",
    "gn:dem":327,
    "gn:feature_class":"P",
    "gn:feature_code":"PPL",
    "gn:name":"Anaborano",
    "gn:population":0,
    "gn:timezone":"Indian/Antananarivo",
    "iso:country":"MG",
    "wof:name":"Anaborano",
    "wof:placetype":"locality"
},
  "geometry": {"coordinates":[45.56667,-17.68332999999999],"type":"Point"}
}