{
  "type": "Feature",
  "properties": {
    "gn:admin1_code":"03",
    "gn:asciiname":"Ampombidamiaka",
    "gn:cc2":"MG",
    "gn:country_code":"MG",
    "gn:dem":295,
    "gn:feature_class":"P",
    "gn:feature_code":"PPL",
    "gn:name":"Ampombidamiaka",
    "gn:population":0,
    "gn:timezone":"Indian/Antananarivo",
    "iso:country":"MG",
    "name:und_x_variant":[
        "Ampombodamiaka",
        "Ampombidamiaka"
    ],
    "wof:name":"Ampombidamiaka",
    "wof:placetype":"locality"
},
  "geometry": {"coordinates":[48.36667,-15.91667],"type":"Point"}
}