{
  "type": "Feature",
  "properties": {
    "gn:admin1_code":"05",
    "gn:asciiname":"Ankomakoma",
    "gn:cc2":"MG",
    "gn:country_code":"MG",
    "gn:dem":1675,
    "gn:feature_class":"P",
    "gn:feature_code":"PPL",
    "gn:name":"Ankomakoma",
    "gn:population":0,
    "gn:timezone":"Indian/Antananarivo",
    "iso:country":"MG",
    "name:und_x_variant":[
        "Ankomakana",
        "Ankomakoma"
    ],
    "wof:name":"Ankomakoma",
    "wof:placetype":"locality"
},
  "geometry": {"coordinates":[47.55,-19.65],"type":"Point"}
}