{
  "type": "Feature",
  "properties": {
    "gn:admin1_code":"06",
    "gn:asciiname":"Andohabato",
    "gn:cc2":"MG",
    "gn:country_code":"MG",
    "gn:dem":533,
    "gn:feature_class":"P",
    "gn:feature_code":"PPL",
    "gn:name":"Andohabato",
    "gn:population":0,
    "gn:timezone":"Indian/Antananarivo",
    "iso:country":"MG",
    "name:und_x_variant":[
        "Antohabato",
        "Andohabato"
    ],
    "wof:name":"Andohabato",
    "wof:placetype":"locality"
},
  "geometry": {"coordinates":[45.05,-23.96667],"type":"Point"}
}