{
  "type": "Feature",
  "properties": {
    "gn:admin1_code":"6.0",
    "gn:asciiname":"Sevohitse",
    "gn:country_code":"MG",
    "gn:dem":126,
    "gn:feature_class":"P",
    "gn:feature_code":"PPL",
    "gn:name":"Sevohitse",
    "gn:population":0,
    "gn:timezone":"Indian/Antananarivo",
    "iso:country":"MG",
    "wof:name":"Sevohitse",
    "wof:placetype":"locality"
},
  "geometry": {"coordinates":[46.08333,-25.15],"type":"Point"}
}