{
  "type": "Feature",
  "properties": {
    "gn:asciiname":"Ankibanivato",
    "gn:country_code":"MG",
    "gn:dem":13,
    "gn:feature_class":"P",
    "gn:feature_code":"PPL",
    "gn:name":"Ankibanivato",
    "gn:population":0,
    "gn:timezone":"Indian/Antananarivo",
    "iso:country":"MG",
    "wof:name":"Ankibanivato",
    "wof:placetype":"locality"
},
  "geometry": {"coordinates":[48.18455,-13.33563],"type":"Point"}
}