{
  "type": "Feature",
  "properties": {
    "gn:admin1_code":"02",
    "gn:asciiname":"Manaka",
    "gn:country_code":"MG",
    "gn:dem":1224,
    "gn:feature_class":"P",
    "gn:feature_code":"PPL",
    "gn:name":"Manaka",
    "gn:population":0,
    "gn:timezone":"Indian/Antananarivo",
    "iso:country":"MG",
    "wof:name":"Manaka",
    "wof:placetype":"locality"
},
  "geometry": {"coordinates":[46.91667,-24.21667],"type":"Point"}
}