{
  "type": "Feature",
  "properties": {
    "gn:admin1_code":"04",
    "gn:asciiname":"Andranovakoana",
    "gn:country_code":"MG",
    "gn:dem":701,
    "gn:feature_class":"P",
    "gn:feature_code":"PPL",
    "gn:name":"Andranovakoana",
    "gn:population":0,
    "gn:timezone":"Indian/Antananarivo",
    "iso:country":"MG",
    "wof:name":"Andranovakoana",
    "wof:placetype":"locality"
},
  "geometry": {"coordinates":[47.91667,-20.41667],"type":"Point"}
}