{
  "type": "Feature",
  "properties": {
    "gn:admin1_code":"4.0",
    "gn:asciiname":"Sahakevo",
    "gn:cc2":"MG",
    "gn:country_code":"MG",
    "gn:dem":703,
    "gn:feature_class":"P",
    "gn:feature_code":"PPL",
    "gn:name":"Sahakevo",
    "gn:population":0,
    "gn:timezone":"Indian/Antananarivo",
    "iso:country":"MG",
    "name:und_x_variant":[
        "Sohakaivo",
        "Sahakevo"
    ],
    "wof:name":"Sahakevo",
    "wof:placetype":"locality"
},
  "geometry": {"coordinates":[47.85,-20.26667],"type":"Point"}
}