{
  "type": "Feature",
  "properties": {
    "gn:admin1_code":"02",
    "gn:asciiname":"Iapety",
    "gn:cc2":"MG",
    "gn:country_code":"MG",
    "gn:dem":1002,
    "gn:feature_class":"P",
    "gn:feature_code":"PPL",
    "gn:name":"Iapety",
    "gn:population":0,
    "gn:timezone":"Indian/Antananarivo",
    "iso:country":"MG",
    "name:und_x_variant":[
        "Ianapety",
        "Iapety"
    ],
    "wof:name":"Iapety",
    "wof:placetype":"locality"
},
  "geometry": {"coordinates":[46.13333,-22.83333],"type":"Point"}
}