{
  "type": "Feature",
  "properties": {
    "gn:admin1_code":"06",
    "gn:asciiname":"Bemita",
    "gn:country_code":"MG",
    "gn:dem":158,
    "gn:feature_class":"P",
    "gn:feature_code":"PPL",
    "gn:name":"Bemita",
    "gn:population":0,
    "gn:timezone":"Indian/Antananarivo",
    "iso:country":"MG",
    "wof:name":"Bemita",
    "wof:placetype":"locality"
},
  "geometry": {"coordinates":[45.31667,-25.01667],"type":"Point"}
}