{
  "type": "Feature",
  "properties": {
    "gn:admin1_code":"02",
    "gn:asciiname":"Ianamalemy",
    "gn:country_code":"MG",
    "gn:dem":23,
    "gn:feature_class":"P",
    "gn:feature_code":"PPL",
    "gn:name":"Ianamalemy",
    "gn:population":0,
    "gn:timezone":"Indian/Antananarivo",
    "iso:country":"MG",
    "wof:name":"Ianamalemy",
    "wof:placetype":"locality"
},
  "geometry": {"coordinates":[48.38333,-20.93333],"type":"Point"}
}