{
  "type": "Feature",
  "properties": {
    "gn:admin1_code":"01",
    "gn:asciiname":"Antsalaka Atsimo",
    "gn:cc2":"MG",
    "gn:country_code":"MG",
    "gn:dem":600,
    "gn:feature_class":"P",
    "gn:feature_code":"PPL",
    "gn:name":"Antsalaka Atsimo",
    "gn:population":0,
    "gn:timezone":"Indian/Antananarivo",
    "iso:country":"MG",
    "name:fra_x_preferred":[
        "Antsalaka"
    ],
    "name:ita_x_preferred":[
        "Antsalaka"
    ],
    "name:mlg_x_preferred":[
        "Antsalaka"
    ],
    "name:nld_x_preferred":[
        "Antsalaka"
    ],
    "name:und_x_variant":[
        "Antsalaka",
        "Antsolaka",
        "Antsalaka Atsimo"
    ],
    "wof:name":"Antsalaka Atsimo",
    "wof:placetype":"locality"
},
  "geometry": {"coordinates":[49.25,-12.63333],"type":"Point"}
}