{
  "type": "Feature",
  "properties": {
    "gn:admin1_code":"03",
    "gn:asciiname":"Ambondro-Ampasy",
    "gn:country_code":"MG",
    "gn:dem":30,
    "gn:feature_class":"P",
    "gn:feature_code":"PPL",
    "gn:name":"Ambondro-Ampasy",
    "gn:population":0,
    "gn:timezone":"Indian/Antananarivo",
    "iso:country":"MG",
    "wof:name":"Ambondro-Ampasy",
    "wof:placetype":"locality"
},
  "geometry": {"coordinates":[47.28333,-15.01667],"type":"Point"}
}