{
  "type": "Feature",
  "properties": {
    "gn:admin1_code":"03",
    "gn:asciiname":"Antatama",
    "gn:cc2":"MG",
    "gn:country_code":"MG",
    "gn:dem":84,
    "gn:feature_class":"P",
    "gn:feature_code":"PPL",
    "gn:name":"Antatama",
    "gn:population":0,
    "gn:timezone":"Indian/Antananarivo",
    "iso:country":"MG",
    "name:und_x_variant":[
        "Antatamo",
        "Antatama"
    ],
    "wof:name":"Antatama",
    "wof:placetype":"locality"
},
  "geometry": {"coordinates":[47.23333,-15.75],"type":"Point"}
}