{
  "type": "Feature",
  "properties": {
    "gn:admin1_code":"02",
    "gn:asciiname":"Folatsandry",
    "gn:country_code":"MG",
    "gn:dem":1002,
    "gn:feature_class":"P",
    "gn:feature_code":"PPL",
    "gn:name":"Folatsandry",
    "gn:population":0,
    "gn:timezone":"Indian/Antananarivo",
    "iso:country":"MG",
    "wof:name":"Folatsandry",
    "wof:placetype":"locality"
},
  "geometry": {"coordinates":[45.73333,-22.41667],"type":"Point"}
}