{
  "type": "Feature",
  "properties": {
    "gn:admin1_code":"03",
    "gn:asciiname":"Bebao",
    "gn:country_code":"MG",
    "gn:dem":122,
    "gn:feature_class":"P",
    "gn:feature_code":"PPL",
    "gn:name":"Bebao",
    "gn:population":0,
    "gn:timezone":"Indian/Antananarivo",
    "iso:country":"MG",
    "wof:name":"Bebao",
    "wof:placetype":"locality"
},
  "geometry": {"coordinates":[44.43333,-18.45],"type":"Point"}
}