{
  "type": "Feature",
  "properties": {
    "gn:admin1_code":"06",
    "gn:asciiname":"Andoharano",
    "gn:country_code":"MG",
    "gn:dem":336,
    "gn:feature_class":"P",
    "gn:feature_code":"PPL",
    "gn:name":"Andoharano",
    "gn:population":0,
    "gn:timezone":"Indian/Antananarivo",
    "iso:country":"MG",
    "wof:name":"Andoharano",
    "wof:placetype":"locality"
},
  "geometry": {"coordinates":[45.26667,-24.53333],"type":"Point"}
}