{
  "type": "Feature",
  "properties": {
    "gn:admin1_code":"05",
    "gn:asciiname":"Amboasary",
    "gn:country_code":"MG",
    "gn:dem":1293,
    "gn:feature_class":"P",
    "gn:feature_code":"PPL",
    "gn:name":"Amboasary",
    "gn:population":0,
    "gn:timezone":"Indian/Antananarivo",
    "iso:country":"MG",
    "name:ceb_x_preferred":[
        "Amboasary"
    ],
    "name:deu_x_preferred":[
        "Amboasary"
    ],
    "name:fas_x_preferred":[
        "\u0627\u0645\u0628\u0648\u0627\u0633\u0627\u0631\u06cc"
    ],
    "name:fra_x_preferred":[
        "Amboasary"
    ],
    "name:nld_x_preferred":[
        "Amboasary"
    ],
    "name:pol_x_preferred":[
        "Amboasary"
    ],
    "name:spa_x_preferred":[
        "Amboasary"
    ],
    "wof:name":"Amboasary",
    "wof:placetype":"locality"
},
  "geometry": {"coordinates":[47.93333,-18.46667],"type":"Point"}
}