{
  "type": "Feature",
  "properties": {
    "gn:admin1_code":"04",
    "gn:asciiname":"Antohaky",
    "gn:country_code":"MG",
    "gn:dem":87,
    "gn:feature_class":"P",
    "gn:feature_code":"PPL",
    "gn:name":"Antohaky",
    "gn:population":0,
    "gn:timezone":"Indian/Antananarivo",
    "iso:country":"MG",
    "wof:name":"Antohaky",
    "wof:placetype":"locality"
},
  "geometry": {"coordinates":[49.36667,-17.85],"type":"Point"}
}