{
  "type": "Feature",
  "properties": {
    "gn:admin1_code":"04",
    "gn:asciiname":"Ambodisakoana",
    "gn:cc2":"MG",
    "gn:country_code":"MG",
    "gn:dem":268,
    "gn:feature_class":"P",
    "gn:feature_code":"PPL",
    "gn:name":"Ambodisakoana",
    "gn:population":0,
    "gn:timezone":"Indian/Antananarivo",
    "iso:country":"MG",
    "name:und_x_variant":[
        "Ambodisakoa",
        "Ambodisakoana"
    ],
    "wof:name":"Ambodisakoana",
    "wof:placetype":"locality"
},
  "geometry": {"coordinates":[49.21667,-17.78333],"type":"Point"}
}