{
  "type": "Feature",
  "properties": {
    "gn:admin1_code":"05",
    "gn:asciiname":"Antananolofotsy",
    "gn:cc2":"MG",
    "gn:country_code":"MG",
    "gn:dem":1125,
    "gn:feature_class":"P",
    "gn:feature_code":"PPL",
    "gn:name":"Antananolofotsy",
    "gn:population":0,
    "gn:timezone":"Indian/Antananarivo",
    "iso:country":"MG",
    "name:und_x_variant":[
        "Antanamahaolofotsy",
        "Antananolofotsy"
    ],
    "wof:name":"Antananolofotsy",
    "wof:placetype":"locality"
},
  "geometry": {"coordinates":[46.65,-20.16667],"type":"Point"}
}