{
  "type": "Feature",
  "properties": {
    "gn:admin1_code":"04",
    "gn:asciiname":"Ampanalana",
    "gn:cc2":"MG",
    "gn:country_code":"MG",
    "gn:dem":6,
    "gn:feature_class":"P",
    "gn:feature_code":"PPL",
    "gn:name":"Ampanalana",
    "gn:population":0,
    "gn:timezone":"Indian/Antananarivo",
    "iso:country":"MG",
    "name:und_x_variant":[
        "Panalana",
        "Ampanalana"
    ],
    "wof:name":"Ampanalana",
    "wof:placetype":"locality"
},
  "geometry": {"coordinates":[48.73333,-20.08333],"type":"Point"}
}