{
  "type": "Feature",
  "properties": {
    "gn:admin1_code":"02",
    "gn:asciiname":"Beamalona",
    "gn:country_code":"MG",
    "gn:dem":946,
    "gn:feature_class":"P",
    "gn:feature_code":"PPL",
    "gn:name":"Beamalona",
    "gn:population":0,
    "gn:timezone":"Indian/Antananarivo",
    "iso:country":"MG",
    "wof:name":"Beamalona",
    "wof:placetype":"locality"
},
  "geometry": {"coordinates":[46.55,-23.11667000000001],"type":"Point"}
}