{
  "type": "Feature",
  "properties": {
    "gn:admin1_code":"6.0",
    "gn:asciiname":"Zantelo",
    "gn:country_code":"MG",
    "gn:dem":172,
    "gn:feature_class":"P",
    "gn:feature_code":"PPL",
    "gn:name":"Zantelo",
    "gn:population":0,
    "gn:timezone":"Indian/Antananarivo",
    "iso:country":"MG",
    "wof:name":"Zantelo",
    "wof:placetype":"locality"
},
  "geometry": {"coordinates":[45.28333,-25.51667],"type":"Point"}
}