{
  "type": "Feature",
  "properties": {
    "gn:admin1_code":"06",
    "gn:asciiname":"Ankasy",
    "gn:country_code":"MG",
    "gn:dem":38,
    "gn:feature_class":"P",
    "gn:feature_code":"PPL",
    "gn:name":"Ankasy",
    "gn:population":0,
    "gn:timezone":"Indian/Antananarivo",
    "iso:country":"MG",
    "wof:name":"Ankasy",
    "wof:placetype":"locality"
},
  "geometry": {"coordinates":[43.73333,-23.33333],"type":"Point"}
}