{
  "type": "Feature",
  "properties": {
    "gn:admin1_code":"06",
    "gn:asciiname":"Mandatsa",
    "gn:country_code":"MG",
    "gn:dem":208,
    "gn:feature_class":"P",
    "gn:feature_code":"PPL",
    "gn:name":"Mandatsa",
    "gn:population":0,
    "gn:timezone":"Indian/Antananarivo",
    "iso:country":"MG",
    "wof:name":"Mandatsa",
    "wof:placetype":"locality"
},
  "geometry": {"coordinates":[43.68333,-22.43333],"type":"Point"}
}