{
  "type": "Feature",
  "properties": {
    "gn:admin1_code":"6.0",
    "gn:asciiname":"Tsivainanaka",
    "gn:country_code":"MG",
    "gn:dem":104,
    "gn:feature_class":"P",
    "gn:feature_code":"PPL",
    "gn:name":"Tsivainanaka",
    "gn:population":0,
    "gn:timezone":"Indian/Antananarivo",
    "iso:country":"MG",
    "wof:name":"Tsivainanaka",
    "wof:placetype":"locality"
},
  "geometry": {"coordinates":[45.51667,-25.23333],"type":"Point"}
}