{
  "type": "Feature",
  "properties": {
    "gn:admin1_code":"06",
    "gn:asciiname":"Andreniatamena",
    "gn:cc2":"MG",
    "gn:country_code":"MG",
    "gn:dem":69,
    "gn:feature_class":"P",
    "gn:feature_code":"PPL",
    "gn:name":"Andreniatamena",
    "gn:population":0,
    "gn:timezone":"Indian/Antananarivo",
    "iso:country":"MG",
    "name:und_x_variant":[
        "Andrenialamena",
        "Andreniatamena"
    ],
    "wof:name":"Andreniatamena",
    "wof:placetype":"locality"
},
  "geometry": {"coordinates":[44.41667,-20.63333],"type":"Point"}
}