{
  "type": "Feature",
  "properties": {
    "gn:admin1_code":"06",
    "gn:asciiname":"Betahotsako",
    "gn:cc2":"MG",
    "gn:country_code":"MG",
    "gn:dem":233,
    "gn:feature_class":"P",
    "gn:feature_code":"PPL",
    "gn:name":"Betahotsako",
    "gn:population":0,
    "gn:timezone":"Indian/Antananarivo",
    "iso:country":"MG",
    "name:und_x_variant":[
        "Botahotsako",
        "Betahontsako",
        "Betahotsako"
    ],
    "wof:name":"Betahotsako",
    "wof:placetype":"locality"
},
  "geometry": {"coordinates":[46.05,-24.48333],"type":"Point"}
}