{
  "type": "Feature",
  "properties": {
    "gn:admin1_code":"1.0",
    "gn:asciiname":"Tsarahiaka",
    "gn:country_code":"MG",
    "gn:dem":393,
    "gn:feature_class":"P",
    "gn:feature_code":"PPL",
    "gn:name":"Tsarahiaka",
    "gn:population":0,
    "gn:timezone":"Indian/Antananarivo",
    "iso:country":"MG",
    "wof:name":"Tsarahiaka",
    "wof:placetype":"locality"
},
  "geometry": {"coordinates":[49.66667,-13.53333],"type":"Point"}
}