{
  "type": "Feature",
  "properties": {
    "gn:admin1_code":"01",
    "gn:asciiname":"Ambodipont",
    "gn:country_code":"MG",
    "gn:dem":472,
    "gn:feature_class":"P",
    "gn:feature_code":"PPL",
    "gn:name":"Ambodipont",
    "gn:population":0,
    "gn:timezone":"Indian/Antananarivo",
    "iso:country":"MG",
    "wof:name":"Ambodipont",
    "wof:placetype":"locality"
},
  "geometry": {"coordinates":[49.63333,-14.63333],"type":"Point"}
}