{
  "type": "Feature",
  "properties": {
    "gn:admin1_code":"4.0",
    "gn:asciiname":"Tetezampaho",
    "gn:country_code":"MG",
    "gn:dem":316,
    "gn:feature_class":"P",
    "gn:feature_code":"PPL",
    "gn:name":"Tetezampaho",
    "gn:population":0,
    "gn:timezone":"Indian/Antananarivo",
    "iso:country":"MG",
    "wof:name":"Tetezampaho",
    "wof:placetype":"locality"
},
  "geometry": {"coordinates":[48.65,-19.38333],"type":"Point"}
}