{
  "type": "Feature",
  "properties": {
    "gn:admin1_code":"02",
    "gn:asciiname":"Ilempombe",
    "gn:country_code":"MG",
    "gn:dem":946,
    "gn:feature_class":"P",
    "gn:feature_code":"PPL",
    "gn:name":"Ilempombe",
    "gn:population":0,
    "gn:timezone":"Indian/Antananarivo",
    "iso:country":"MG",
    "wof:name":"Ilempombe",
    "wof:placetype":"locality"
},
  "geometry": {"coordinates":[46.98333,-21.93333],"type":"Point"}
}