{
  "type": "Feature",
  "properties": {
    "gn:admin1_code":"02",
    "gn:asciiname":"Andakary",
    "gn:cc2":"MG",
    "gn:country_code":"MG",
    "gn:dem":4,
    "gn:feature_class":"P",
    "gn:feature_code":"PPL",
    "gn:name":"Andakary",
    "gn:population":0,
    "gn:timezone":"Indian/Antananarivo",
    "iso:country":"MG",
    "name:und_x_variant":[
        "Andakana",
        "Andakary"
    ],
    "wof:name":"Andakary",
    "wof:placetype":"locality"
},
  "geometry": {"coordinates":[47.88333,-22.48333],"type":"Point"}
}