{
  "type": "Feature",
  "properties": {
    "gn:admin1_code":"01",
    "gn:asciiname":"Anketrakabe",
    "gn:cc2":"MG",
    "gn:country_code":"MG",
    "gn:dem":340,
    "gn:feature_class":"P",
    "gn:feature_code":"PPL",
    "gn:name":"Anketrakabe",
    "gn:population":0,
    "gn:timezone":"Indian/Antananarivo",
    "iso:country":"MG",
    "name:fra_x_preferred":[
        "Anketrakabe"
    ],
    "name:ita_x_preferred":[
        "Anketrakabe"
    ],
    "name:mlg_x_preferred":[
        "Anketrakabe"
    ],
    "name:nld_x_preferred":[
        "Anketrakabe"
    ],
    "name:und_x_variant":[
        "Ankotrakabe",
        "Anketrakabe"
    ],
    "wof:name":"Anketrakabe",
    "wof:placetype":"locality"
},
  "geometry": {"coordinates":[49.33333,-12.55],"type":"Point"}
}