{
  "type": "Feature",
  "properties": {
    "gn:admin1_code":"04",
    "gn:asciiname":"Anjahamarina",
    "gn:country_code":"MG",
    "gn:dem":64,
    "gn:feature_class":"P",
    "gn:feature_code":"PPL",
    "gn:name":"Anjahamarina",
    "gn:population":0,
    "gn:timezone":"Indian/Antananarivo",
    "iso:country":"MG",
    "wof:name":"Anjahamarina",
    "wof:placetype":"locality"
},
  "geometry": {"coordinates":[49.23333,-18.05],"type":"Point"}
}