{
  "type": "Feature",
  "properties": {
    "gn:admin1_code":"02",
    "gn:asciiname":"Ambalakazaha",
    "gn:country_code":"MG",
    "gn:dem":383,
    "gn:feature_class":"P",
    "gn:feature_code":"PPL",
    "gn:name":"Ambalakazaha",
    "gn:population":0,
    "gn:timezone":"Indian/Antananarivo",
    "iso:country":"MG",
    "wof:name":"Ambalakazaha",
    "wof:placetype":"locality"
},
  "geometry": {"coordinates":[47.83333,-20.78333],"type":"Point"}
}