{
  "type": "Feature",
  "properties": {
    "gn:admin1_code":"06",
    "gn:asciiname":"Ianakomanary",
    "gn:country_code":"MG",
    "gn:dem":559,
    "gn:feature_class":"P",
    "gn:feature_code":"PPL",
    "gn:name":"Ianakomanary",
    "gn:population":0,
    "gn:timezone":"Indian/Antananarivo",
    "iso:country":"MG",
    "wof:name":"Ianakomanary",
    "wof:placetype":"locality"
},
  "geometry": {"coordinates":[45.41667,-23.56667],"type":"Point"}
}