{
  "type": "Feature",
  "properties": {
    "gn:admin1_code":"01",
    "gn:asciiname":"Ambodikatakata",
    "gn:country_code":"MG",
    "gn:dem":10,
    "gn:feature_class":"P",
    "gn:feature_code":"PPL",
    "gn:name":"Ambodikatakata",
    "gn:population":0,
    "gn:timezone":"Indian/Antananarivo",
    "iso:country":"MG",
    "wof:name":"Ambodikatakata",
    "wof:placetype":"locality"
},
  "geometry": {"coordinates":[48.88333,-13.11667],"type":"Point"}
}