{
  "type": "Feature",
  "properties": {
    "gn:admin1_code":"02",
    "gn:asciiname":"Analatelo",
    "gn:country_code":"MG",
    "gn:dem":39,
    "gn:feature_class":"P",
    "gn:feature_code":"PPL",
    "gn:name":"Analatelo",
    "gn:population":0,
    "gn:timezone":"Indian/Antananarivo",
    "iso:country":"MG",
    "wof:name":"Analatelo",
    "wof:placetype":"locality"
},
  "geometry": {"coordinates":[48.03333,-21.58333],"type":"Point"}
}