{
  "type": "Feature",
  "properties": {
    "gn:admin1_code":"03",
    "gn:asciiname":"Andalivao",
    "gn:country_code":"MG",
    "gn:dem":175,
    "gn:feature_class":"P",
    "gn:feature_code":"PPL",
    "gn:name":"Andalivao",
    "gn:population":0,
    "gn:timezone":"Indian/Antananarivo",
    "iso:country":"MG",
    "wof:name":"Andalivao",
    "wof:placetype":"locality"
},
  "geometry": {"coordinates":[46.41667,-16.96667],"type":"Point"}
}