{
  "type": "Feature",
  "properties": {
    "gn:admin1_code":"2.0",
    "gn:asciiname":"Vatombe",
    "gn:cc2":"MG",
    "gn:country_code":"MG",
    "gn:dem":832,
    "gn:feature_class":"P",
    "gn:feature_code":"PPL",
    "gn:name":"Vatombe",
    "gn:population":0,
    "gn:timezone":"Indian/Antananarivo",
    "iso:country":"MG",
    "name:und_x_variant":[
        "Vatambe",
        "Vatombe"
    ],
    "wof:name":"Vatombe",
    "wof:placetype":"locality"
},
  "geometry": {"coordinates":[45.48333,-22.36667000000001],"type":"Point"}
}