{
  "type": "Feature",
  "properties": {
    "gn:admin1_code":"06",
    "gn:asciiname":"Amboloando",
    "gn:country_code":"MG",
    "gn:dem":70,
    "gn:feature_class":"P",
    "gn:feature_code":"PPL",
    "gn:name":"Amboloando",
    "gn:population":0,
    "gn:timezone":"Indian/Antananarivo",
    "iso:country":"MG",
    "wof:name":"Amboloando",
    "wof:placetype":"locality"
},
  "geometry": {"coordinates":[45.43333,-19.45],"type":"Point"}
}