{
  "type": "Feature",
  "properties": {
    "gn:admin1_code":"06",
    "gn:asciiname":"Analavory",
    "gn:country_code":"MG",
    "gn:dem":502,
    "gn:feature_class":"P",
    "gn:feature_code":"PPL",
    "gn:name":"Analavory",
    "gn:population":0,
    "gn:timezone":"Indian/Antananarivo",
    "iso:country":"MG",
    "wof:name":"Analavory",
    "wof:placetype":"locality"
},
  "geometry": {"coordinates":[45.53333,-24.15],"type":"Point"}
}