{
  "type": "Feature",
  "properties": {
    "gn:admin1_code":"2.0",
    "gn:asciiname":"Vohilava",
    "gn:cc2":"MG",
    "gn:country_code":"MG",
    "gn:dem":4,
    "gn:feature_class":"P",
    "gn:feature_code":"PPL",
    "gn:name":"Vohilava",
    "gn:population":0,
    "gn:timezone":"Indian/Antananarivo",
    "iso:country":"MG",
    "name:und_x_variant":[
        "Farivola",
        "Vohilava"
    ],
    "wof:name":"Vohilava",
    "wof:placetype":"locality"
},
  "geometry": {"coordinates":[47.68333,-23.31667],"type":"Point"}
}