{
  "type": "Feature",
  "properties": {
    "gn:admin1_code":"06",
    "gn:asciiname":"Betobory",
    "gn:country_code":"MG",
    "gn:dem":122,
    "gn:feature_class":"P",
    "gn:feature_code":"PPL",
    "gn:name":"Betobory",
    "gn:population":0,
    "gn:timezone":"Indian/Antananarivo",
    "iso:country":"MG",
    "wof:name":"Betobory",
    "wof:placetype":"locality"
},
  "geometry": {"coordinates":[44.53333,-20.78333],"type":"Point"}
}