{
  "type": "Feature",
  "properties": {
    "gn:admin1_code":"3.0",
    "gn:asciiname":"Tsarahonenana",
    "gn:country_code":"MG",
    "gn:dem":663,
    "gn:feature_class":"P",
    "gn:feature_code":"PPL",
    "gn:name":"Tsarahonenana",
    "gn:population":0,
    "gn:timezone":"Indian/Antananarivo",
    "iso:country":"MG",
    "wof:name":"Tsarahonenana",
    "wof:placetype":"locality"
},
  "geometry": {"coordinates":[46.93333,-17.56667],"type":"Point"}
}