{
  "type": "Feature",
  "properties": {
    "gn:admin1_code":"03",
    "gn:asciiname":"Ambodibonara",
    "gn:country_code":"MG",
    "gn:dem":323,
    "gn:feature_class":"P",
    "gn:feature_code":"PPL",
    "gn:name":"Ambodibonara",
    "gn:population":0,
    "gn:timezone":"Indian/Antananarivo",
    "iso:country":"MG",
    "wof:name":"Ambodibonara",
    "wof:placetype":"locality"
},
  "geometry": {"coordinates":[48.88333,-15.91667],"type":"Point"}
}