{
  "type": "Feature",
  "properties": {
    "gn:admin1_code":"02",
    "gn:asciiname":"Andrairay",
    "gn:country_code":"MG",
    "gn:dem":201,
    "gn:feature_class":"P",
    "gn:feature_code":"PPL",
    "gn:name":"Andrairay",
    "gn:population":0,
    "gn:timezone":"Indian/Antananarivo",
    "iso:country":"MG",
    "wof:name":"Andrairay",
    "wof:placetype":"locality"
},
  "geometry": {"coordinates":[47.36667,-22.13333],"type":"Point"}
}