{
  "type": "Feature",
  "properties": {
    "gn:admin1_code":"06",
    "gn:asciiname":"Antanimora",
    "gn:country_code":"MG",
    "gn:dem":803,
    "gn:feature_class":"P",
    "gn:feature_code":"PPL",
    "gn:name":"Antanimora",
    "gn:population":0,
    "gn:timezone":"Indian/Antananarivo",
    "iso:country":"MG",
    "wof:name":"Antanimora",
    "wof:placetype":"locality"
},
  "geometry": {"coordinates":[45.98333,-23.66667],"type":"Point"}
}