{
  "type": "Feature",
  "properties": {
    "gn:admin1_code":"06",
    "gn:asciiname":"Ambolovoriky",
    "gn:country_code":"MG",
    "gn:dem":71,
    "gn:feature_class":"P",
    "gn:feature_code":"PPL",
    "gn:name":"Ambolovoriky",
    "gn:population":0,
    "gn:timezone":"Indian/Antananarivo",
    "iso:country":"MG",
    "wof:name":"Ambolovoriky",
    "wof:placetype":"locality"
},
  "geometry": {"coordinates":[44.43333,-20.56667],"type":"Point"}
}