{
  "type": "Feature",
  "properties": {
    "gn:admin1_code":"06",
    "gn:asciiname":"Antanamasy",
    "gn:country_code":"MG",
    "gn:dem":1,
    "gn:feature_class":"P",
    "gn:feature_code":"PPL",
    "gn:name":"Antanamasy",
    "gn:population":0,
    "gn:timezone":"Indian/Antananarivo",
    "iso:country":"MG",
    "wof:name":"Antanamasy",
    "wof:placetype":"locality"
},
  "geometry": {"coordinates":[46.85,-25.03333],"type":"Point"}
}