{
  "type": "Feature",
  "properties": {
    "gn:admin1_code":"04",
    "gn:asciiname":"Andranonaomby",
    "gn:cc2":"MG",
    "gn:country_code":"MG",
    "gn:dem":35,
    "gn:feature_class":"P",
    "gn:feature_code":"PPL",
    "gn:name":"Andranonaomby",
    "gn:population":0,
    "gn:timezone":"Indian/Antananarivo",
    "iso:country":"MG",
    "name:und_x_variant":[
        "Andranaomby",
        "Andranonaomby"
    ],
    "wof:name":"Andranonaomby",
    "wof:placetype":"locality"
},
  "geometry": {"coordinates":[49.43333,-17.48333],"type":"Point"}
}