{
  "type": "Feature",
  "properties": {
    "gn:admin1_code":"06",
    "gn:asciiname":"Ambaninato",
    "gn:cc2":"MG",
    "gn:country_code":"MG",
    "gn:dem":240,
    "gn:feature_class":"P",
    "gn:feature_code":"PPL",
    "gn:name":"Ambaninato",
    "gn:population":0,
    "gn:timezone":"Indian/Antananarivo",
    "iso:country":"MG",
    "name:und_x_variant":[
        "Ambananata",
        "Ambaninato"
    ],
    "wof:name":"Ambaninato",
    "wof:placetype":"locality"
},
  "geometry": {"coordinates":[46.25,-24.66667],"type":"Point"}
}