{
  "type": "Feature",
  "properties": {
    "gn:admin1_code":"03",
    "gn:asciiname":"Andavakakoho",
    "gn:country_code":"MG",
    "gn:dem":41,
    "gn:feature_class":"P",
    "gn:feature_code":"PPL",
    "gn:name":"Andavakakoho",
    "gn:population":0,
    "gn:timezone":"Indian/Antananarivo",
    "iso:country":"MG",
    "wof:name":"Andavakakoho",
    "wof:placetype":"locality"
},
  "geometry": {"coordinates":[46.88333,-16.83333],"type":"Point"}
}