{
  "type": "Feature",
  "properties": {
    "gn:admin1_code":"04",
    "gn:asciiname":"Maroahitra",
    "gn:country_code":"MG",
    "gn:dem":34,
    "gn:feature_class":"P",
    "gn:feature_code":"PPL",
    "gn:name":"Maroahitra",
    "gn:population":0,
    "gn:timezone":"Indian/Antananarivo",
    "iso:country":"MG",
    "wof:name":"Maroahitra",
    "wof:placetype":"locality"
},
  "geometry": {"coordinates":[48.75,-19.85],"type":"Point"}
}