{
  "type": "Feature",
  "properties": {
    "gn:admin1_code":"03",
    "gn:asciiname":"Ambalakitata",
    "gn:country_code":"MG",
    "gn:dem":36,
    "gn:feature_class":"P",
    "gn:feature_code":"PPL",
    "gn:name":"Ambalakitata",
    "gn:population":0,
    "gn:timezone":"Indian/Antananarivo",
    "iso:country":"MG",
    "wof:name":"Ambalakitata",
    "wof:placetype":"locality"
},
  "geometry": {"coordinates":[47.23333,-15.71667],"type":"Point"}
}