{
  "type": "Feature",
  "properties": {
    "gn:admin1_code":"05",
    "gn:asciiname":"Ambohimanana",
    "gn:country_code":"MG",
    "gn:dem":847,
    "gn:feature_class":"P",
    "gn:feature_code":"PPL",
    "gn:name":"Ambohimanana",
    "gn:population":0,
    "gn:timezone":"Indian/Antananarivo",
    "iso:country":"MG",
    "wof:name":"Ambohimanana",
    "wof:placetype":"locality"
},
  "geometry": {"coordinates":[45.83333,-18.78333],"type":"Point"}
}