{
  "type": "Feature",
  "properties": {
    "gn:admin1_code":"05",
    "gn:asciiname":"Ampitiliana",
    "gn:country_code":"MG",
    "gn:dem":911,
    "gn:feature_class":"P",
    "gn:feature_code":"PPL",
    "gn:name":"Ampitiliana",
    "gn:population":0,
    "gn:timezone":"Indian/Antananarivo",
    "iso:country":"MG",
    "wof:name":"Ampitiliana",
    "wof:placetype":"locality"
},
  "geometry": {"coordinates":[46.36667,-18.98333],"type":"Point"}
}