{
  "type": "Feature",
  "properties": {
    "gn:admin1_code":"02",
    "gn:asciiname":"Ambalavao Sud",
    "gn:country_code":"MG",
    "gn:dem":827,
    "gn:feature_class":"P",
    "gn:feature_code":"PPL",
    "gn:name":"Ambalavao Sud",
    "gn:population":0,
    "gn:timezone":"Indian/Antananarivo",
    "iso:country":"MG",
    "wof:name":"Ambalavao Sud",
    "wof:placetype":"locality"
},
  "geometry": {"coordinates":[46.45,-21.13333],"type":"Point"}
}