{
  "type": "Feature",
  "properties": {
    "gn:admin1_code":"03",
    "gn:asciiname":"Ampapamena",
    "gn:cc2":"MG",
    "gn:country_code":"MG",
    "gn:dem":-9999,
    "gn:feature_class":"P",
    "gn:feature_code":"PPL",
    "gn:name":"Ampapamena",
    "gn:population":0,
    "gn:timezone":"Indian/Antananarivo",
    "iso:country":"MG",
    "name:und_x_variant":[
        "Ampampamena",
        "Ampapamena"
    ],
    "wof:name":"Ampapamena",
    "wof:placetype":"locality"
},
  "geometry": {"coordinates":[45.35,-16.06667],"type":"Point"}
}