{
  "type": "Feature",
  "properties": {
    "gn:admin1_code":"01",
    "gn:asciiname":"Fotsialalana",
    "gn:cc2":"MG",
    "gn:country_code":"MG",
    "gn:dem":589,
    "gn:feature_class":"P",
    "gn:feature_code":"PPL",
    "gn:name":"Fotsialalana",
    "gn:population":0,
    "gn:timezone":"Indian/Antananarivo",
    "iso:country":"MG",
    "name:und_x_variant":[
        "Fotsialanga",
        "Fotsialanana",
        "Fotsialalana"
    ],
    "wof:name":"Fotsialalana",
    "wof:placetype":"locality"
},
  "geometry": {"coordinates":[49.53333,-13.88333],"type":"Point"}
}