{
  "type": "Feature",
  "properties": {
    "gn:admin1_code":"03",
    "gn:asciiname":"Ankomany",
    "gn:cc2":"MG",
    "gn:country_code":"MG",
    "gn:dem":15,
    "gn:feature_class":"P",
    "gn:feature_code":"PPL",
    "gn:name":"Ankomany",
    "gn:population":0,
    "gn:timezone":"Indian/Antananarivo",
    "iso:country":"MG",
    "name:und_x_variant":[
        "Komany",
        "Ankomany"
    ],
    "wof:name":"Ankomany",
    "wof:placetype":"locality"
},
  "geometry": {"coordinates":[46.56667,-15.48333],"type":"Point"}
}