{
  "type": "Feature",
  "properties": {
    "gn:admin1_code":"01",
    "gn:asciiname":"Amparibe",
    "gn:country_code":"MG",
    "gn:dem":267,
    "gn:feature_class":"P",
    "gn:feature_code":"PPL",
    "gn:name":"Amparibe",
    "gn:population":0,
    "gn:timezone":"Indian/Antananarivo",
    "iso:country":"MG",
    "wof:name":"Amparibe",
    "wof:placetype":"locality"
},
  "geometry": {"coordinates":[49.93333,-13.58333],"type":"Point"}
}