{
  "type": "Feature",
  "properties": {
    "gn:admin1_code":"05",
    "gn:asciiname":"Andranomahavelona",
    "gn:country_code":"MG",
    "gn:dem":1341,
    "gn:feature_class":"P",
    "gn:feature_code":"PPL",
    "gn:name":"Andranomahavelona",
    "gn:population":0,
    "gn:timezone":"Indian/Antananarivo",
    "iso:country":"MG",
    "wof:name":"Andranomahavelona",
    "wof:placetype":"locality"
},
  "geometry": {"coordinates":[47.05,-18.93333],"type":"Point"}
}