{
  "type": "Feature",
  "properties": {
    "gn:admin1_code":"01",
    "gn:asciiname":"Behofika",
    "gn:country_code":"MG",
    "gn:dem":335,
    "gn:feature_class":"P",
    "gn:feature_code":"PPL",
    "gn:name":"Behofika",
    "gn:population":0,
    "gn:timezone":"Indian/Antananarivo",
    "iso:country":"MG",
    "wof:name":"Behofika",
    "wof:placetype":"locality"
},
  "geometry": {"coordinates":[49.71667,-14.21667],"type":"Point"}
}