{
  "type": "Feature",
  "properties": {
    "gn:admin1_code":"02",
    "gn:asciiname":"Ambandrika",
    "gn:country_code":"MG",
    "gn:dem":24,
    "gn:feature_class":"P",
    "gn:feature_code":"PPL",
    "gn:name":"Ambandrika",
    "gn:population":0,
    "gn:timezone":"Indian/Antananarivo",
    "iso:country":"MG",
    "name:azb_x_preferred":[
        "\u0627\u0645\u0628\u0627\u0646\u062f\u0631\u06cc\u06a9\u0627"
    ],
    "name:fas_x_preferred":[
        "\u0627\u0645\u0628\u0627\u0646\u062f\u0631\u06cc\u06a9\u0627"
    ],
    "name:fra_x_preferred":[
        "Ambandrika"
    ],
    "name:ita_x_preferred":[
        "Ambandrika"
    ],
    "name:mlg_x_preferred":[
        "Ambandrika"
    ],
    "name:nld_x_preferred":[
        "Ambandrika"
    ],
    "wof:name":"Ambandrika",
    "wof:placetype":"locality"
},
  "geometry": {"coordinates":[48.18333,-21.36667000000001],"type":"Point"}
}