{
  "type": "Feature",
  "properties": {
    "gn:admin1_code":"03",
    "gn:asciiname":"Ankilahilamamoa",
    "gn:cc2":"MG",
    "gn:country_code":"MG",
    "gn:dem":250,
    "gn:feature_class":"P",
    "gn:feature_code":"PPL",
    "gn:name":"Ankilahilamamoa",
    "gn:population":0,
    "gn:timezone":"Indian/Antananarivo",
    "iso:country":"MG",
    "name:und_x_variant":[
        "Mamoa",
        "Ankilahilamamoa"
    ],
    "wof:name":"Ankilahilamamoa",
    "wof:placetype":"locality"
},
  "geometry": {"coordinates":[48.36667,-15.33333],"type":"Point"}
}