{
  "type": "Feature",
  "properties": {
    "gn:admin1_code":"03",
    "gn:asciiname":"Marosakoa",
    "gn:cc2":"MG",
    "gn:country_code":"MG",
    "gn:dem":28,
    "gn:feature_class":"P",
    "gn:feature_code":"PPL",
    "gn:name":"Marosakoa",
    "gn:population":0,
    "gn:timezone":"Indian/Antananarivo",
    "iso:country":"MG",
    "name:fra_x_preferred":[
        "Marosakoa"
    ],
    "name:ita_x_preferred":[
        "Marosakoa"
    ],
    "name:mlg_x_preferred":[
        "Marosakoa"
    ],
    "name:nld_x_preferred":[
        "Marosakoa"
    ],
    "name:und_x_variant":[
        "Ambodisakoa",
        "Marosakao",
        "Marosakoa"
    ],
    "wof:name":"Marosakoa",
    "wof:placetype":"locality"
},
  "geometry": {"coordinates":[46.76667,-16.66667],"type":"Point"}
}