{
  "type": "Feature",
  "properties": {
    "gn:admin1_code":"04",
    "gn:asciiname":"Ambalarongana",
    "gn:country_code":"MG",
    "gn:dem":331,
    "gn:feature_class":"P",
    "gn:feature_code":"PPL",
    "gn:name":"Ambalarongana",
    "gn:population":0,
    "gn:timezone":"Indian/Antananarivo",
    "iso:country":"MG",
    "wof:name":"Ambalarongana",
    "wof:placetype":"locality"
},
  "geometry": {"coordinates":[48.81667,-19.15],"type":"Point"}
}