{
  "type": "Feature",
  "properties": {
    "gn:admin1_code":"06",
    "gn:asciiname":"Lanampolo",
    "gn:country_code":"MG",
    "gn:dem":694,
    "gn:feature_class":"P",
    "gn:feature_code":"PPL",
    "gn:name":"Lanampolo",
    "gn:population":0,
    "gn:timezone":"Indian/Antananarivo",
    "iso:country":"MG",
    "wof:name":"Lanampolo",
    "wof:placetype":"locality"
},
  "geometry": {"coordinates":[44.01667,-22.61667000000001],"type":"Point"}
}