{
  "type": "Feature",
  "properties": {
    "gn:admin1_code":"2.0",
    "gn:asciiname":"Vohidava",
    "gn:country_code":"MG",
    "gn:dem":105,
    "gn:feature_class":"P",
    "gn:feature_code":"PPL",
    "gn:name":"Vohidava",
    "gn:population":0,
    "gn:timezone":"Indian/Antananarivo",
    "iso:country":"MG",
    "wof:name":"Vohidava",
    "wof:placetype":"locality"
},
  "geometry": {"coordinates":[48.33333,-20.48333],"type":"Point"}
}