{
  "type": "Feature",
  "properties": {
    "gn:admin1_code":"01",
    "gn:asciiname":"Ambinanifaho",
    "gn:cc2":"MG",
    "gn:country_code":"MG",
    "gn:dem":27,
    "gn:feature_class":"P",
    "gn:feature_code":"PPL",
    "gn:name":"Ambinanifaho",
    "gn:population":0,
    "gn:timezone":"Indian/Antananarivo",
    "iso:country":"MG",
    "name:azb_x_preferred":[
        "\u0627\u0645\u0628\u06cc\u0646\u0627\u0646\u06cc\u0641\u0627\u0647\u0648"
    ],
    "name:fas_x_preferred":[
        "\u0627\u0645\u0628\u06cc\u0646\u0627\u0646\u06cc\u0641\u0627\u0647\u0648"
    ],
    "name:fra_x_preferred":[
        "Ambinanifaho"
    ],
    "name:ita_x_preferred":[
        "Ambinanifaho"
    ],
    "name:mlg_x_preferred":[
        "Ambinanifaho"
    ],
    "name:nld_x_preferred":[
        "Ambinanifaho"
    ],
    "name:und_x_variant":[
        "Ambinanyfaho"
    ],
    "wof:name":"Ambinanifaho",
    "wof:placetype":"locality"
},
  "geometry": {"coordinates":[50.13333,-14.61667],"type":"Point"}
}