{
  "type": "Feature",
  "properties": {
    "gn:admin1_code":"01",
    "gn:asciiname":"Ambinanifaho",
    "gn:cc2":"MG",
    "gn:country_code":"MG",
    "gn:dem":27,
    "gn:feature_class":"P",
    "gn:feature_code":"PPL",
    "gn:name":"Ambinanifaho",
    "gn:population":0,
    "gn:timezone":"Indian/Antananarivo",
    "iso:country":"MG",
    "name:und_x_variant":[
        "Ambinanyfaho",
        "Ambinanifaho"
    ],
    "wof:name":"Ambinanifaho",
    "wof:placetype":"locality"
},
  "geometry": {"coordinates":[50.13333,-14.61667],"type":"Point"}
}