{
  "type": "Feature",
  "properties": {
    "gn:admin1_code":"2.0",
    "gn:asciiname":"Tetezamalama",
    "gn:country_code":"MG",
    "gn:dem":1071,
    "gn:feature_class":"P",
    "gn:feature_code":"PPL",
    "gn:name":"Tetezamalama",
    "gn:population":0,
    "gn:timezone":"Indian/Antananarivo",
    "iso:country":"MG",
    "wof:name":"Tetezamalama",
    "wof:placetype":"locality"
},
  "geometry": {"coordinates":[47.33333,-21.56667],"type":"Point"}
}