{
  "type": "Feature",
  "properties": {
    "gn:admin1_code":"02",
    "gn:asciiname":"Bevaho",
    "gn:country_code":"MG",
    "gn:dem":599,
    "gn:feature_class":"P",
    "gn:feature_code":"PPL",
    "gn:name":"Bevaho",
    "gn:population":0,
    "gn:timezone":"Indian/Antananarivo",
    "iso:country":"MG",
    "wof:name":"Bevaho",
    "wof:placetype":"locality"
},
  "geometry": {"coordinates":[47.01667,-22.61667000000001],"type":"Point"}
}