{
  "type": "Feature",
  "properties": {
    "gn:admin1_code":"03",
    "gn:asciiname":"Antsakoambe",
    "gn:country_code":"MG",
    "gn:dem":331,
    "gn:feature_class":"P",
    "gn:feature_code":"PPL",
    "gn:name":"Antsakoambe",
    "gn:population":0,
    "gn:timezone":"Indian/Antananarivo",
    "iso:country":"MG",
    "wof:name":"Antsakoambe",
    "wof:placetype":"locality"
},
  "geometry": {"coordinates":[48.23333,-15.85],"type":"Point"}
}