{
  "type": "Feature",
  "properties": {
    "gn:admin1_code":"03",
    "gn:asciiname":"Ampandrana",
    "gn:country_code":"MG",
    "gn:dem":1121,
    "gn:feature_class":"P",
    "gn:feature_code":"PPL",
    "gn:name":"Ampandrana",
    "gn:population":0,
    "gn:timezone":"Indian/Antananarivo",
    "iso:country":"MG",
    "wof:name":"Ampandrana",
    "wof:placetype":"locality"
},
  "geometry": {"coordinates":[48.58333,-14.71667],"type":"Point"}
}