{
  "type": "Feature",
  "properties": {
    "gn:admin1_code":"04",
    "gn:asciiname":"Niarovana",
    "gn:country_code":"MG",
    "gn:dem":597,
    "gn:feature_class":"P",
    "gn:feature_code":"PPL",
    "gn:name":"Niarovana",
    "gn:population":0,
    "gn:timezone":"Indian/Antananarivo",
    "iso:country":"MG",
    "wof:name":"Niarovana",
    "wof:placetype":"locality"
},
  "geometry": {"coordinates":[47.96667,-19.96667],"type":"Point"}
}