{
  "type": "Feature",
  "properties": {
    "gn:admin1_code":"6.0",
    "gn:asciiname":"Tafia Ambany",
    "gn:country_code":"MG",
    "gn:dem":800,
    "gn:feature_class":"P",
    "gn:feature_code":"PPL",
    "gn:name":"Tafia Ambany",
    "gn:population":0,
    "gn:timezone":"Indian/Antananarivo",
    "iso:country":"MG",
    "wof:name":"Tafia Ambany",
    "wof:placetype":"locality"
},
  "geometry": {"coordinates":[45.88333,-23.11667000000001],"type":"Point"}
}