{
  "type": "Feature",
  "properties": {
    "gn:admin1_code":"06",
    "gn:asciiname":"Fangadiendraka",
    "gn:country_code":"MG",
    "gn:dem":182,
    "gn:feature_class":"P",
    "gn:feature_code":"PPL",
    "gn:name":"Fangadiendraka",
    "gn:population":0,
    "gn:timezone":"Indian/Antananarivo",
    "iso:country":"MG",
    "wof:name":"Fangadiendraka",
    "wof:placetype":"locality"
},
  "geometry": {"coordinates":[46.23333,-24.58333],"type":"Point"}
}