{
  "type": "Feature",
  "properties": {
    "gn:admin1_code":"03",
    "gn:asciiname":"Andilambe",
    "gn:cc2":"MG",
    "gn:country_code":"MG",
    "gn:dem":655,
    "gn:feature_class":"P",
    "gn:feature_code":"PPL",
    "gn:name":"Andilambe",
    "gn:population":0,
    "gn:timezone":"Indian/Antananarivo",
    "iso:country":"MG",
    "name:und_x_variant":[
        "Andilamb",
        "Andilambe"
    ],
    "wof:name":"Andilambe",
    "wof:placetype":"locality"
},
  "geometry": {"coordinates":[48.96667,-15.36667],"type":"Point"}
}