{
  "type": "Feature",
  "properties": {
    "gn:admin1_code":"4.0",
    "gn:asciiname":"Sahanivany",
    "gn:country_code":"MG",
    "gn:dem":27,
    "gn:feature_class":"P",
    "gn:feature_code":"PPL",
    "gn:name":"Sahanivany",
    "gn:population":0,
    "gn:timezone":"Indian/Antananarivo",
    "iso:country":"MG",
    "wof:name":"Sahanivany",
    "wof:placetype":"locality"
},
  "geometry": {"coordinates":[48.76667,-19.76667],"type":"Point"}
}