{
  "type": "Feature",
  "properties": {
    "gn:admin1_code":"02",
    "gn:asciiname":"Anivorano",
    "gn:country_code":"MG",
    "gn:dem":25,
    "gn:feature_class":"P",
    "gn:feature_code":"PPL",
    "gn:name":"Anivorano",
    "gn:population":0,
    "gn:timezone":"Indian/Antananarivo",
    "iso:country":"MG",
    "wof:name":"Anivorano",
    "wof:placetype":"locality"
},
  "geometry": {"coordinates":[48.31667,-20.85],"type":"Point"}
}