{
  "type": "Feature",
  "properties": {
    "gn:admin1_code":"02",
    "gn:asciiname":"Manampotsy",
    "gn:cc2":"MG",
    "gn:country_code":"MG",
    "gn:dem":15,
    "gn:feature_class":"P",
    "gn:feature_code":"PPL",
    "gn:name":"Manampotsy",
    "gn:population":0,
    "gn:timezone":"Indian/Antananarivo",
    "iso:country":"MG",
    "name:und_x_variant":[
        "Manampontsy",
        "Manampotsy"
    ],
    "wof:name":"Manampotsy",
    "wof:placetype":"locality"
},
  "geometry": {"coordinates":[48.31667,-21.11667000000001],"type":"Point"}
}