{
  "type": "Feature",
  "properties": {
    "gn:admin1_code":"06",
    "gn:asciiname":"Ankazomivola",
    "gn:country_code":"MG",
    "gn:dem":1116,
    "gn:feature_class":"P",
    "gn:feature_code":"PPL",
    "gn:name":"Ankazomivola",
    "gn:population":0,
    "gn:timezone":"Indian/Antananarivo",
    "iso:country":"MG",
    "wof:name":"Ankazomivola",
    "wof:placetype":"locality"
},
  "geometry": {"coordinates":[46.21667,-23.06667],"type":"Point"}
}