{
  "type": "Feature",
  "properties": {
    "gn:admin1_code":"02",
    "gn:asciiname":"Ambohimandroso",
    "gn:country_code":"MG",
    "gn:dem":941,
    "gn:feature_class":"P",
    "gn:feature_code":"PPL",
    "gn:name":"Ambohimandroso",
    "gn:population":0,
    "gn:timezone":"Indian/Antananarivo",
    "iso:country":"MG",
    "name:azb_x_preferred":[
        "\u0627\u0645\u0628\u0648\u0647\u06cc\u0645\u0627\u0646\u062f\u0631\u0627\u0633"
    ],
    "name:fas_x_preferred":[
        "\u0627\u0645\u0628\u0648\u0647\u06cc\u0645\u0627\u0646\u062f\u0631\u0627\u0633"
    ],
    "name:fra_x_preferred":[
        "Ambohimandroso"
    ],
    "name:ita_x_preferred":[
        "Ambohimandroso"
    ],
    "name:mlg_x_preferred":[
        "Ambohimandroso"
    ],
    "name:nld_x_preferred":[
        "Ambohimandroso"
    ],
    "name:pol_x_preferred":[
        "Ambohimandroso"
    ],
    "wof:name":"Ambohimandroso",
    "wof:placetype":"locality"
},
  "geometry": {"coordinates":[46.95,-21.88333],"type":"Point"}
}