{
  "type": "Feature",
  "properties": {
    "gn:admin1_code":"03",
    "gn:asciiname":"Ambalanano",
    "gn:country_code":"MG",
    "gn:dem":102,
    "gn:feature_class":"P",
    "gn:feature_code":"PPL",
    "gn:name":"Ambalanano",
    "gn:population":0,
    "gn:timezone":"Indian/Antananarivo",
    "iso:country":"MG",
    "wof:name":"Ambalanano",
    "wof:placetype":"locality"
},
  "geometry": {"coordinates":[46.85,-16.95],"type":"Point"}
}