{
  "type": "Feature",
  "properties": {
    "gn:admin1_code":"2.0",
    "gn:asciiname":"Sambohova",
    "gn:country_code":"MG",
    "gn:dem":1084,
    "gn:feature_class":"P",
    "gn:feature_code":"PPL",
    "gn:name":"Sambohova",
    "gn:population":0,
    "gn:timezone":"Indian/Antananarivo",
    "iso:country":"MG",
    "wof:name":"Sambohova",
    "wof:placetype":"locality"
},
  "geometry": {"coordinates":[47.23333,-21.71667],"type":"Point"}
}