{
  "type": "Feature",
  "properties": {
    "gn:admin1_code":"05",
    "gn:asciiname":"Ambohimanatrika",
    "gn:country_code":"MG",
    "gn:dem":1375,
    "gn:feature_class":"P",
    "gn:feature_code":"PPL",
    "gn:name":"Ambohimanatrika",
    "gn:population":0,
    "gn:timezone":"Indian/Antananarivo",
    "iso:country":"MG",
    "wof:name":"Ambohimanatrika",
    "wof:placetype":"locality"
},
  "geometry": {"coordinates":[47.45,-18.68333],"type":"Point"}
}