{
  "type": "Feature",
  "properties": {
    "gn:admin1_code":"06",
    "gn:asciiname":"Anaviavy",
    "gn:cc2":"MG",
    "gn:country_code":"MG",
    "gn:dem":390,
    "gn:feature_class":"P",
    "gn:feature_code":"PPL",
    "gn:name":"Anaviavy",
    "gn:population":0,
    "gn:timezone":"Indian/Antananarivo",
    "iso:country":"MG",
    "name:und_x_variant":[
        "Anavlavy",
        "Anaviavy"
    ],
    "wof:name":"Anaviavy",
    "wof:placetype":"locality"
},
  "geometry": {"coordinates":[44.43333,-23.18333],"type":"Point"}
}