{
  "type": "Feature",
  "properties": {
    "gn:admin1_code":"02",
    "gn:asciiname":"Androrangavola",
    "gn:country_code":"MG",
    "gn:dem":226,
    "gn:feature_class":"P",
    "gn:feature_code":"PPL",
    "gn:name":"Androrangavola",
    "gn:population":0,
    "gn:timezone":"Indian/Antananarivo",
    "iso:country":"MG",
    "wof:name":"Androrangavola",
    "wof:placetype":"locality"
},
  "geometry": {"coordinates":[48.23333,-20.51667],"type":"Point"}
}