{
  "type": "Feature",
  "properties": {
    "gn:admin1_code":"03",
    "gn:asciiname":"Andranosoa",
    "gn:country_code":"MG",
    "gn:dem":399,
    "gn:feature_class":"P",
    "gn:feature_code":"PPL",
    "gn:name":"Andranosoa",
    "gn:population":0,
    "gn:timezone":"Indian/Antananarivo",
    "iso:country":"MG",
    "wof:name":"Andranosoa",
    "wof:placetype":"locality"
},
  "geometry": {"coordinates":[44.96667,-17.41667],"type":"Point"}
}