{
  "type": "Feature",
  "properties": {
    "gn:admin1_code":"4.0",
    "gn:asciiname":"Sahahindrano",
    "gn:country_code":"MG",
    "gn:dem":365,
    "gn:feature_class":"P",
    "gn:feature_code":"PPL",
    "gn:name":"Sahahindrano",
    "gn:population":0,
    "gn:timezone":"Indian/Antananarivo",
    "iso:country":"MG",
    "wof:name":"Sahahindrano",
    "wof:placetype":"locality"
},
  "geometry": {"coordinates":[49.26667,-17.56667],"type":"Point"}
}