{
  "type": "Feature",
  "properties": {
    "gn:admin1_code":"06",
    "gn:asciiname":"Ambaromidada Atsinanana",
    "gn:cc2":"MG",
    "gn:country_code":"MG",
    "gn:dem":70,
    "gn:feature_class":"P",
    "gn:feature_code":"PPL",
    "gn:name":"Ambaromidada Atsinanana",
    "gn:population":0,
    "gn:timezone":"Indian/Antananarivo",
    "iso:country":"MG",
    "name:und_x_variant":[
        "Ambaromidada Est",
        "Ambaromidada Atsinanana"
    ],
    "wof:name":"Ambaromidada Atsinanana",
    "wof:placetype":"locality"
},
  "geometry": {"coordinates":[45.63333,-25.38333],"type":"Point"}
}