{
  "type": "Feature",
  "properties": {
    "gn:admin1_code":"02",
    "gn:asciiname":"Antranomera",
    "gn:country_code":"MG",
    "gn:dem":1321,
    "gn:feature_class":"P",
    "gn:feature_code":"PPL",
    "gn:name":"Antranomera",
    "gn:population":0,
    "gn:timezone":"Indian/Antananarivo",
    "iso:country":"MG",
    "wof:name":"Antranomera",
    "wof:placetype":"locality"
},
  "geometry": {"coordinates":[46.85,-21.33333],"type":"Point"}
}