{
  "type": "Feature",
  "properties": {
    "gn:admin1_code":"06",
    "gn:asciiname":"Betsingilo",
    "gn:country_code":"MG",
    "gn:dem":178,
    "gn:feature_class":"P",
    "gn:feature_code":"PPL",
    "gn:name":"Betsingilo",
    "gn:population":0,
    "gn:timezone":"Indian/Antananarivo",
    "iso:country":"MG",
    "wof:name":"Betsingilo",
    "wof:placetype":"locality"
},
  "geometry": {"coordinates":[46.21667,-24.26667],"type":"Point"}
}