{
  "type": "Feature",
  "properties": {
    "gn:admin1_code":"02",
    "gn:asciiname":"Marovana",
    "gn:country_code":"MG",
    "gn:dem":116,
    "gn:feature_class":"P",
    "gn:feature_code":"PPL",
    "gn:name":"Marovana",
    "gn:population":0,
    "gn:timezone":"Indian/Antananarivo",
    "iso:country":"MG",
    "wof:name":"Marovana",
    "wof:placetype":"locality"
},
  "geometry": {"coordinates":[47.46667,-22.35],"type":"Point"}
}