{
  "type": "Feature",
  "properties": {
    "gn:admin1_code":"03",
    "gn:asciiname":"Anaborengy",
    "gn:country_code":"MG",
    "gn:dem":20,
    "gn:feature_class":"P",
    "gn:feature_code":"PPL",
    "gn:name":"Anaborengy",
    "gn:population":0,
    "gn:timezone":"Indian/Antananarivo",
    "iso:country":"MG",
    "wof:name":"Anaborengy",
    "wof:placetype":"locality"
},
  "geometry": {"coordinates":[45.96667,-16.08333],"type":"Point"}
}