{
  "type": "Feature",
  "properties": {
    "gn:admin1_code":"02",
    "gn:asciiname":"Andemaka Avaratra",
    "gn:country_code":"MG",
    "gn:dem":535,
    "gn:feature_class":"P",
    "gn:feature_code":"PPL",
    "gn:name":"Andemaka Avaratra",
    "gn:population":0,
    "gn:timezone":"Indian/Antananarivo",
    "iso:country":"MG",
    "wof:name":"Andemaka Avaratra",
    "wof:placetype":"locality"
},
  "geometry": {"coordinates":[47.55,-21.03333],"type":"Point"}
}