{
  "type": "Feature",
  "properties": {
    "gn:admin1_code":"02",
    "gn:asciiname":"Lopary",
    "gn:country_code":"MG",
    "gn:dem":3,
    "gn:feature_class":"P",
    "gn:feature_code":"PPL",
    "gn:name":"Lopary",
    "gn:population":0,
    "gn:timezone":"Indian/Antananarivo",
    "iso:country":"MG",
    "name:fra_x_preferred":[
        "Lopary"
    ],
    "name:ita_x_preferred":[
        "Lopary"
    ],
    "name:mlg_x_preferred":[
        "Lopary"
    ],
    "name:nld_x_preferred":[
        "Lopary"
    ],
    "wof:name":"Lopary",
    "wof:placetype":"locality"
},
  "geometry": {"coordinates":[47.66667,-23.18333],"type":"Point"}
}