{
  "type": "Feature",
  "properties": {
    "gn:admin1_code":"02",
    "gn:asciiname":"Ampitsahandakana",
    "gn:country_code":"MG",
    "gn:dem":1409,
    "gn:feature_class":"P",
    "gn:feature_code":"PPL",
    "gn:name":"Ampitsahandakana",
    "gn:population":0,
    "gn:timezone":"Indian/Antananarivo",
    "iso:country":"MG",
    "wof:name":"Ampitsahandakana",
    "wof:placetype":"locality"
},
  "geometry": {"coordinates":[47.58333,-20.25],"type":"Point"}
}