{
  "type": "Feature",
  "properties": {
    "gn:admin1_code":"04",
    "gn:asciiname":"Ambodivongo",
    "gn:country_code":"MG",
    "gn:dem":321,
    "gn:feature_class":"P",
    "gn:feature_code":"PPL",
    "gn:name":"Ambodivongo",
    "gn:population":0,
    "gn:timezone":"Indian/Antananarivo",
    "iso:country":"MG",
    "name:azb_x_preferred":[
        "\u0627\u0645\u0628\u0648\u062f\u06cc\u0648\u0627\u0646\u0642\u0648"
    ],
    "name:fas_x_preferred":[
        "\u0627\u0645\u0628\u0648\u062f\u06cc\u0648\u0627\u0646\u06af\u0648"
    ],
    "name:fra_x_preferred":[
        "Ambodivongo"
    ],
    "name:ita_x_preferred":[
        "Ambodivongo"
    ],
    "name:mlg_x_preferred":[
        "Ambodivongo"
    ],
    "name:nld_x_preferred":[
        "Ambodivongo"
    ],
    "wof:name":"Ambodivongo",
    "wof:placetype":"locality"
},
  "geometry": {"coordinates":[49.16667,-17.16667],"type":"Point"}
}