{
  "type": "Feature",
  "properties": {
    "gn:admin1_code":"06",
    "gn:asciiname":"Marohaika",
    "gn:cc2":"MG",
    "gn:country_code":"MG",
    "gn:dem":184,
    "gn:feature_class":"P",
    "gn:feature_code":"PPL",
    "gn:name":"Marohaika",
    "gn:population":0,
    "gn:timezone":"Indian/Antananarivo",
    "iso:country":"MG",
    "name:und_x_variant":[
        "Maroalika",
        "Marohaika"
    ],
    "wof:name":"Marohaika",
    "wof:placetype":"locality"
},
  "geometry": {"coordinates":[46.36667,-25.13333],"type":"Point"}
}