{
  "type": "Feature",
  "properties": {
    "gn:admin1_code":"02",
    "gn:asciiname":"Besavoa",
    "gn:cc2":"MG",
    "gn:country_code":"MG",
    "gn:dem":554,
    "gn:feature_class":"P",
    "gn:feature_code":"PPL",
    "gn:name":"Besavoa",
    "gn:population":0,
    "gn:timezone":"Indian/Antananarivo",
    "iso:country":"MG",
    "name:und_x_variant":[
        "Besavaka",
        "Besavoa"
    ],
    "wof:name":"Besavoa",
    "wof:placetype":"locality"
},
  "geometry": {"coordinates":[45.81667,-21.41667],"type":"Point"}
}