{
  "type": "Feature",
  "properties": {
    "gn:admin1_code":"2.0",
    "gn:asciiname":"Vohimasina",
    "gn:country_code":"MG",
    "gn:dem":501,
    "gn:feature_class":"P",
    "gn:feature_code":"PPL",
    "gn:name":"Vohimasina",
    "gn:population":0,
    "gn:timezone":"Indian/Antananarivo",
    "iso:country":"MG",
    "wof:name":"Vohimasina",
    "wof:placetype":"locality"
},
  "geometry": {"coordinates":[47.81667,-20.93333],"type":"Point"}
}