{
  "type": "Feature",
  "properties": {
    "gn:admin1_code":"05",
    "gn:asciiname":"Ankofafa",
    "gn:country_code":"MG",
    "gn:dem":1019,
    "gn:feature_class":"P",
    "gn:feature_code":"PPL",
    "gn:name":"Ankofafa",
    "gn:population":0,
    "gn:timezone":"Indian/Antananarivo",
    "iso:country":"MG",
    "wof:name":"Ankofafa",
    "wof:placetype":"locality"
},
  "geometry": {"coordinates":[45.63333,-18.81667],"type":"Point"}
}