{
  "type": "Feature",
  "properties": {
    "gn:admin1_code":"03",
    "gn:asciiname":"Ambanjabe",
    "gn:country_code":"MG",
    "gn:dem":315,
    "gn:feature_class":"P",
    "gn:feature_code":"PPL",
    "gn:name":"Ambanjabe",
    "gn:population":0,
    "gn:timezone":"Indian/Antananarivo",
    "iso:country":"MG",
    "name:azb_x_preferred":[
        "\u0627\u0645\u0628\u0627\u0646\u062c\u0627\u0628"
    ],
    "name:fas_x_preferred":[
        "\u0627\u0645\u0628\u0627\u0646\u062c\u0627\u0628"
    ],
    "name:fra_x_preferred":[
        "Ambanjabe"
    ],
    "name:ita_x_preferred":[
        "Ambanjabe"
    ],
    "name:mlg_x_preferred":[
        "Ambanjabe"
    ],
    "name:nld_x_preferred":[
        "Ambanjabe"
    ],
    "wof:name":"Ambanjabe",
    "wof:placetype":"locality"
},
  "geometry": {"coordinates":[45.61667,-17.71667],"type":"Point"}
}