{
  "type": "Feature",
  "properties": {
    "gn:admin1_code":"03",
    "gn:asciiname":"Ambanjabe",
    "gn:country_code":"MG",
    "gn:dem":315,
    "gn:feature_class":"P",
    "gn:feature_code":"PPL",
    "gn:name":"Ambanjabe",
    "gn:population":0,
    "gn:timezone":"Indian/Antananarivo",
    "iso:country":"MG",
    "wof:name":"Ambanjabe",
    "wof:placetype":"locality"
},
  "geometry": {"coordinates":[45.61667,-17.71667],"type":"Point"}
}