{
  "type": "Feature",
  "properties": {
    "gn:admin1_code":"03",
    "gn:asciiname":"Ampandrakely",
    "gn:country_code":"MG",
    "gn:dem":29,
    "gn:feature_class":"P",
    "gn:feature_code":"PPL",
    "gn:name":"Ampandrakely",
    "gn:population":0,
    "gn:timezone":"Indian/Antananarivo",
    "iso:country":"MG",
    "wof:name":"Ampandrakely",
    "wof:placetype":"locality"
},
  "geometry": {"coordinates":[45.61667,-16.13332999999999],"type":"Point"}
}