{
  "type": "Feature",
  "properties": {
    "gn:admin1_code":"06",
    "gn:asciiname":"Analamebo",
    "gn:country_code":"MG",
    "gn:dem":536,
    "gn:feature_class":"P",
    "gn:feature_code":"PPL",
    "gn:name":"Analamebo",
    "gn:population":0,
    "gn:timezone":"Indian/Antananarivo",
    "iso:country":"MG",
    "wof:name":"Analamebo",
    "wof:placetype":"locality"
},
  "geometry": {"coordinates":[45.55,-24.01667],"type":"Point"}
}