{
  "type": "Feature",
  "properties": {
    "gn:admin1_code":"06",
    "gn:asciiname":"Mitsinjo",
    "gn:country_code":"MG",
    "gn:dem":747,
    "gn:feature_class":"P",
    "gn:feature_code":"PPL",
    "gn:name":"Mitsinjo",
    "gn:population":0,
    "gn:timezone":"Indian/Antananarivo",
    "iso:country":"MG",
    "wof:name":"Mitsinjo",
    "wof:placetype":"locality"
},
  "geometry": {"coordinates":[44.91667,-22.73333],"type":"Point"}
}