{
  "type": "Feature",
  "properties": {
    "gn:admin1_code":"05",
    "gn:asciiname":"Mangatany",
    "gn:country_code":"MG",
    "gn:dem":1370,
    "gn:feature_class":"P",
    "gn:feature_code":"PPL",
    "gn:name":"Mangatany",
    "gn:population":0,
    "gn:timezone":"Indian/Antananarivo",
    "iso:country":"MG",
    "wof:name":"Mangatany",
    "wof:placetype":"locality"
},
  "geometry": {"coordinates":[47.38333,-19.01667],"type":"Point"}
}