{
  "type": "Feature",
  "properties": {
    "gn:admin1_code":"06",
    "gn:asciiname":"Ankijabe",
    "gn:country_code":"MG",
    "gn:dem":128,
    "gn:feature_class":"P",
    "gn:feature_code":"PPL",
    "gn:name":"Ankijabe",
    "gn:population":0,
    "gn:timezone":"Indian/Antananarivo",
    "iso:country":"MG",
    "name:fra_x_preferred":[
        "Ankijabe"
    ],
    "name:ita_x_preferred":[
        "Ankijabe"
    ],
    "name:mlg_x_preferred":[
        "Ankijabe"
    ],
    "name:nld_x_preferred":[
        "Ankijabe"
    ],
    "wof:name":"Ankijabe",
    "wof:placetype":"locality"
},
  "geometry": {"coordinates":[44.08333,-21.38333],"type":"Point"}
}