{
  "type": "Feature",
  "properties": {
    "gn:admin1_code":"01",
    "gn:asciiname":"Matsaborimanga",
    "gn:country_code":"MG",
    "gn:dem":45,
    "gn:feature_class":"P",
    "gn:feature_code":"PPL",
    "gn:name":"Matsaborimanga",
    "gn:population":0,
    "gn:timezone":"Indian/Antananarivo",
    "iso:country":"MG",
    "wof:name":"Matsaborimanga",
    "wof:placetype":"locality"
},
  "geometry": {"coordinates":[49.05,-12.86667],"type":"Point"}
}