{
  "type": "Feature",
  "properties": {
    "gn:admin1_code":"02",
    "gn:asciiname":"Kijaofotsy",
    "gn:country_code":"MG",
    "gn:dem":1116,
    "gn:feature_class":"P",
    "gn:feature_code":"PPL",
    "gn:name":"Kijaofotsy",
    "gn:population":0,
    "gn:timezone":"Indian/Antananarivo",
    "iso:country":"MG",
    "wof:name":"Kijaofotsy",
    "wof:placetype":"locality"
},
  "geometry": {"coordinates":[47.28333,-21.66667],"type":"Point"}
}