{
  "type": "Feature",
  "properties": {
    "gn:admin1_code":"06",
    "gn:asciiname":"Antsakoamalangy",
    "gn:country_code":"MG",
    "gn:dem":210,
    "gn:feature_class":"P",
    "gn:feature_code":"PPL",
    "gn:name":"Antsakoamalangy",
    "gn:population":0,
    "gn:timezone":"Indian/Antananarivo",
    "iso:country":"MG",
    "wof:name":"Antsakoamalangy",
    "wof:placetype":"locality"
},
  "geometry": {"coordinates":[46.28333,-24.53333],"type":"Point"}
}