{
  "type": "Feature",
  "properties": {
    "gn:admin1_code":"06",
    "gn:asciiname":"Andefopaly",
    "gn:country_code":"MG",
    "gn:dem":171,
    "gn:feature_class":"P",
    "gn:feature_code":"PPL",
    "gn:name":"Andefopaly",
    "gn:population":0,
    "gn:timezone":"Indian/Antananarivo",
    "iso:country":"MG",
    "wof:name":"Andefopaly",
    "wof:placetype":"locality"
},
  "geometry": {"coordinates":[45.08333,-25.36667000000001],"type":"Point"}
}