{
  "type": "Feature",
  "properties": {
    "gn:admin1_code":"6.0",
    "gn:asciiname":"Vohitovo",
    "gn:country_code":"MG",
    "gn:dem":77,
    "gn:feature_class":"P",
    "gn:feature_code":"PPL",
    "gn:name":"Vohitovo",
    "gn:population":0,
    "gn:timezone":"Indian/Antananarivo",
    "iso:country":"MG",
    "wof:name":"Vohitovo",
    "wof:placetype":"locality"
},
  "geometry": {"coordinates":[44.11667,-21.85],"type":"Point"}
}