{
  "type": "Feature",
  "properties": {
    "gn:admin1_code":"03",
    "gn:asciiname":"Andranovendrana",
    "gn:country_code":"MG",
    "gn:dem":1078,
    "gn:feature_class":"P",
    "gn:feature_code":"PPL",
    "gn:name":"Andranovendrana",
    "gn:population":0,
    "gn:timezone":"Indian/Antananarivo",
    "iso:country":"MG",
    "wof:name":"Andranovendrana",
    "wof:placetype":"locality"
},
  "geometry": {"coordinates":[48.93333,-14.55],"type":"Point"}
}