{
  "type": "Feature",
  "properties": {
    "gn:admin1_code":"6.0",
    "gn:asciiname":"Zabely",
    "gn:country_code":"MG",
    "gn:dem":59,
    "gn:feature_class":"P",
    "gn:feature_code":"PPL",
    "gn:name":"Zabely",
    "gn:population":0,
    "gn:timezone":"Indian/Antananarivo",
    "iso:country":"MG",
    "wof:name":"Zabely",
    "wof:placetype":"locality"
},
  "geometry": {"coordinates":[43.63333,-21.96667],"type":"Point"}
}