{
  "type": "Feature",
  "properties": {
    "gn:admin1_code":"03",
    "gn:asciiname":"Bemanevika Ambany",
    "gn:cc2":"MG",
    "gn:country_code":"MG",
    "gn:dem":749,
    "gn:feature_class":"P",
    "gn:feature_code":"PPL",
    "gn:name":"Bemanevika Ambany",
    "gn:population":0,
    "gn:timezone":"Indian/Antananarivo",
    "iso:country":"MG",
    "name:und_x_variant":[
        "Bamanevika Ambany",
        "Bemanevika Ambany"
    ],
    "wof:name":"Bemanevika Ambany",
    "wof:placetype":"locality"
},
  "geometry": {"coordinates":[48.78333,-15.13333],"type":"Point"}
}