{
  "type": "Feature",
  "properties": {
    "gn:admin1_code":"02",
    "gn:asciiname":"Mangoa",
    "gn:cc2":"MG",
    "gn:country_code":"MG",
    "gn:dem":582,
    "gn:feature_class":"P",
    "gn:feature_code":"PPL",
    "gn:name":"Mangoa",
    "gn:population":0,
    "gn:timezone":"Indian/Antananarivo",
    "iso:country":"MG",
    "name:und_x_variant":[
        "Amanoa",
        "Mangoa"
    ],
    "wof:name":"Mangoa",
    "wof:placetype":"locality"
},
  "geometry": {"coordinates":[46.91667,-22.93333],"type":"Point"}
}