{
  "type": "Feature",
  "properties": {
    "gn:admin1_code":"02",
    "gn:asciiname":"Ambodirafia",
    "gn:country_code":"MG",
    "gn:dem":313,
    "gn:feature_class":"P",
    "gn:feature_code":"PPL",
    "gn:name":"Ambodirafia",
    "gn:population":0,
    "gn:timezone":"Indian/Antananarivo",
    "iso:country":"MG",
    "wof:name":"Ambodirafia",
    "wof:placetype":"locality"
},
  "geometry": {"coordinates":[47.85,-21.08333],"type":"Point"}
}