{
  "type": "Feature",
  "properties": {
    "gn:admin1_code":"04",
    "gn:asciiname":"Antanandehibe",
    "gn:country_code":"MG",
    "gn:dem":591,
    "gn:feature_class":"P",
    "gn:feature_code":"PPL",
    "gn:name":"Antanandehibe",
    "gn:population":0,
    "gn:timezone":"Indian/Antananarivo",
    "iso:country":"MG",
    "wof:name":"Antanandehibe",
    "wof:placetype":"locality"
},
  "geometry": {"coordinates":[48.35,-19.66667],"type":"Point"}
}