{
  "type": "Feature",
  "properties": {
    "gn:admin1_code":"02",
    "gn:asciiname":"Beronono",
    "gn:country_code":"MG",
    "gn:dem":88,
    "gn:feature_class":"P",
    "gn:feature_code":"PPL",
    "gn:name":"Beronono",
    "gn:population":0,
    "gn:timezone":"Indian/Antananarivo",
    "iso:country":"MG",
    "wof:name":"Beronono",
    "wof:placetype":"locality"
},
  "geometry": {"coordinates":[47.46667,-22.96667],"type":"Point"}
}