{
  "type": "Feature",
  "properties": {
    "gn:admin1_code":"03",
    "gn:asciiname":"Ambinda",
    "gn:country_code":"MG",
    "gn:dem":18,
    "gn:feature_class":"P",
    "gn:feature_code":"PPL",
    "gn:name":"Ambinda",
    "gn:population":0,
    "gn:timezone":"Indian/Antananarivo",
    "iso:country":"MG",
    "wof:name":"Ambinda",
    "wof:placetype":"locality"
},
  "geometry": {"coordinates":[44.13333,-17.88332999999999],"type":"Point"}
}