{
  "type": "Feature",
  "properties": {
    "gn:admin1_code":"03",
    "gn:asciiname":"Ambalahonko",
    "gn:country_code":"MG",
    "gn:dem":-9999,
    "gn:feature_class":"P",
    "gn:feature_code":"PPL",
    "gn:name":"Ambalahonko",
    "gn:population":0,
    "gn:timezone":"Indian/Antananarivo",
    "iso:country":"MG",
    "name:azb_x_preferred":[
        "\u0627\u0645\u0628\u0627\u0644\u0627\u0647\u0648\u0646\u06a9\u0648"
    ],
    "name:ceb_x_preferred":[
        "Ambalahonko"
    ],
    "name:fas_x_preferred":[
        "\u0627\u0645\u0628\u0627\u0644\u0627\u0647\u0648\u0646\u06a9\u0648"
    ],
    "name:fra_x_preferred":[
        "Ambalahonko"
    ],
    "name:ita_x_preferred":[
        "Ambalahonko"
    ],
    "name:mlg_x_preferred":[
        "Ambalahonko"
    ],
    "name:nld_x_preferred":[
        "Ambalahonko"
    ],
    "name:swe_x_preferred":[
        "Ambalahonko"
    ],
    "wof:name":"Ambalahonko",
    "wof:placetype":"locality"
},
  "geometry": {"coordinates":[44.35,-16.78333],"type":"Point"}
}