{
  "type": "Feature",
  "properties": {
    "gn:admin1_code":"06",
    "gn:asciiname":"Ambindamahery",
    "gn:country_code":"MG",
    "gn:dem":927,
    "gn:feature_class":"P",
    "gn:feature_code":"PPL",
    "gn:name":"Ambindamahery",
    "gn:population":0,
    "gn:timezone":"Indian/Antananarivo",
    "iso:country":"MG",
    "wof:name":"Ambindamahery",
    "wof:placetype":"locality"
},
  "geometry": {"coordinates":[45.88333,-23.93333],"type":"Point"}
}