{
  "type": "Feature",
  "properties": {
    "gn:admin1_code":"02",
    "gn:asciiname":"Andanoa",
    "gn:cc2":"MG",
    "gn:country_code":"MG",
    "gn:dem":670,
    "gn:feature_class":"P",
    "gn:feature_code":"PPL",
    "gn:name":"Andanoa",
    "gn:population":0,
    "gn:timezone":"Indian/Antananarivo",
    "iso:country":"MG",
    "name:und_x_variant":[
        "Landanoa",
        "Iandanoa",
        "Andanoa"
    ],
    "wof:name":"Andanoa",
    "wof:placetype":"locality"
},
  "geometry": {"coordinates":[45.95,-21.15],"type":"Point"}
}