{
  "type": "Feature",
  "properties": {
    "gn:admin1_code":"04",
    "gn:asciiname":"Andapa",
    "gn:country_code":"MG",
    "gn:dem":38,
    "gn:feature_class":"P",
    "gn:feature_code":"PPL",
    "gn:name":"Andapa",
    "gn:population":0,
    "gn:timezone":"Indian/Antananarivo",
    "iso:country":"MG",
    "name:azb_x_preferred":[
        "\u0627\u0646\u062f\u0627\u067e\u0627"
    ],
    "name:cat_x_preferred":[
        "Andapa"
    ],
    "name:ceb_x_preferred":[
        "Andapa"
    ],
    "name:dan_x_preferred":[
        "Andapa"
    ],
    "name:deu_x_preferred":[
        "Andapa"
    ],
    "name:fas_x_preferred":[
        "\u0627\u0646\u062f\u0627\u067e\u0627"
    ],
    "name:fra_x_preferred":[
        "Andapa"
    ],
    "name:ita_x_preferred":[
        "Andapa"
    ],
    "name:mlg_x_preferred":[
        "Andapa"
    ],
    "name:nld_x_preferred":[
        "Andapa"
    ],
    "name:nor_x_preferred":[
        "Andapa"
    ],
    "name:pol_x_preferred":[
        "Andapa"
    ],
    "name:rus_x_preferred":[
        "\u0410\u043d\u0434\u0430\u043f\u0430"
    ],
    "name:swe_x_preferred":[
        "Andapa"
    ],
    "name:zho_x_preferred":[
        "\u5b89\u9054\u5e15"
    ],
    "wof:name":"Andapa",
    "wof:placetype":"locality"
},
  "geometry": {"coordinates":[49.38333,-17.26667],"type":"Point"}
}