{
  "type": "Feature",
  "properties": {
    "gn:admin1_code":"06",
    "gn:asciiname":"Anjoho",
    "gn:country_code":"MG",
    "gn:dem":853,
    "gn:feature_class":"P",
    "gn:feature_code":"PPL",
    "gn:name":"Anjoho",
    "gn:population":0,
    "gn:timezone":"Indian/Antananarivo",
    "iso:country":"MG",
    "wof:name":"Anjoho",
    "wof:placetype":"locality"
},
  "geometry": {"coordinates":[46.23333,-23.45],"type":"Point"}
}