{
  "type": "Feature",
  "properties": {
    "gn:admin1_code":"04",
    "gn:asciiname":"Ambatomanga",
    "gn:country_code":"MG",
    "gn:dem":627,
    "gn:feature_class":"P",
    "gn:feature_code":"PPL",
    "gn:name":"Ambatomanga",
    "gn:population":0,
    "gn:timezone":"Indian/Antananarivo",
    "iso:country":"MG",
    "name:fra_x_preferred":[
        "Ambatomanga"
    ],
    "name:nld_x_preferred":[
        "Ambatomanga"
    ],
    "wof:name":"Ambatomanga",
    "wof:placetype":"locality"
},
  "geometry": {"coordinates":[48.05,-19.65],"type":"Point"}
}