{
  "type": "Feature",
  "properties": {
    "gn:admin1_code":"04",
    "gn:asciiname":"Ambodivoapaka",
    "gn:country_code":"MG",
    "gn:dem":63,
    "gn:feature_class":"P",
    "gn:feature_code":"PPL",
    "gn:name":"Ambodivoapaka",
    "gn:population":0,
    "gn:timezone":"Indian/Antananarivo",
    "iso:country":"MG",
    "wof:name":"Ambodivoapaka",
    "wof:placetype":"locality"
},
  "geometry": {"coordinates":[49.46667,-17.05],"type":"Point"}
}