{
  "type": "Feature",
  "properties": {
    "gn:admin1_code":"3.0",
    "gn:asciiname":"Vodiala",
    "gn:country_code":"MG",
    "gn:dem":698,
    "gn:feature_class":"P",
    "gn:feature_code":"PPL",
    "gn:name":"Vodiala",
    "gn:population":0,
    "gn:timezone":"Indian/Antananarivo",
    "iso:country":"MG",
    "wof:name":"Vodiala",
    "wof:placetype":"locality"
},
  "geometry": {"coordinates":[47.86667,-17.35],"type":"Point"}
}