{
  "type": "Feature",
  "properties": {
    "gn:admin1_code":"06",
    "gn:asciiname":"Ankiliabo",
    "gn:country_code":"MG",
    "gn:dem":43,
    "gn:feature_class":"P",
    "gn:feature_code":"PPL",
    "gn:name":"Ankiliabo",
    "gn:population":0,
    "gn:timezone":"Indian/Antananarivo",
    "iso:country":"MG",
    "wof:name":"Ankiliabo",
    "wof:placetype":"locality"
},
  "geometry": {"coordinates":[44.95,-19.53333],"type":"Point"}
}