{
  "type": "Feature",
  "properties": {
    "gn:admin1_code":"01",
    "gn:asciiname":"Amboditetezano",
    "gn:cc2":"MG",
    "gn:country_code":"MG",
    "gn:dem":184,
    "gn:feature_class":"P",
    "gn:feature_code":"PPL",
    "gn:name":"Amboditetezano",
    "gn:population":0,
    "gn:timezone":"Indian/Antananarivo",
    "iso:country":"MG",
    "name:und_x_variant":[
        "Ambody-Pont",
        "Amboditetezano"
    ],
    "wof:name":"Amboditetezano",
    "wof:placetype":"locality"
},
  "geometry": {"coordinates":[49.35,-12.65],"type":"Point"}
}