{
  "type": "Feature",
  "properties": {
    "gn:admin1_code":"06",
    "gn:asciiname":"Mitrieka",
    "gn:country_code":"MG",
    "gn:dem":141,
    "gn:feature_class":"P",
    "gn:feature_code":"PPL",
    "gn:name":"Mitrieka",
    "gn:population":0,
    "gn:timezone":"Indian/Antananarivo",
    "iso:country":"MG",
    "wof:name":"Mitrieka",
    "wof:placetype":"locality"
},
  "geometry": {"coordinates":[44.91667,-25.28333],"type":"Point"}
}