{
  "type": "Feature",
  "properties": {
    "gn:admin1_code":"7670856",
    "gn:asciiname":"Alarobia",
    "gn:country_code":"MG",
    "gn:dem":1389,
    "gn:feature_class":"P",
    "gn:feature_code":"PPL",
    "gn:name":"Alarobia",
    "gn:population":16000,
    "gn:timezone":"Indian/Antananarivo",
    "iso:country":"MG",
    "name:und_x_variant":[
        "Alarobi"
    ],
    "wof:name":"Alarobia",
    "wof:placetype":"locality",
    "wof:population":16000
},
  "geometry": {"coordinates":[47.73333,-18.96667],"type":"Point"}
}