{
  "type": "Feature",
  "properties": {
    "gn:admin1_code":"06",
    "gn:asciiname":"Antenindahy",
    "gn:cc2":"MG",
    "gn:country_code":"MG",
    "gn:dem":417,
    "gn:feature_class":"P",
    "gn:feature_code":"PPL",
    "gn:name":"Antenindahy",
    "gn:population":0,
    "gn:timezone":"Indian/Antananarivo",
    "iso:country":"MG",
    "name:und_x_variant":[
        "Antenondahy",
        "Antenindahy"
    ],
    "wof:name":"Antenindahy",
    "wof:placetype":"locality"
},
  "geometry": {"coordinates":[45.21667,-24.28333],"type":"Point"}
}