{
  "type": "Feature",
  "properties": {
    "gn:asciiname":"Manga Be",
    "gn:country_code":"MG",
    "gn:dem":1233,
    "gn:feature_class":"P",
    "gn:feature_code":"PPL",
    "gn:name":"Manga Be",
    "gn:population":0,
    "gn:timezone":"Indian/Antananarivo",
    "iso:country":"MG",
    "name:und_x_variant":[
        "Mangabe"
    ],
    "wof:name":"Manga Be",
    "wof:placetype":"locality"
},
  "geometry": {"coordinates":[47.08334,-18.41667],"type":"Point"}
}