{
  "type": "Feature",
  "properties": {
    "gn:admin1_code":"05",
    "gn:asciiname":"Iharana",
    "gn:country_code":"MG",
    "gn:dem":1547,
    "gn:feature_class":"P",
    "gn:feature_code":"PPL",
    "gn:name":"Iharana",
    "gn:population":0,
    "gn:timezone":"Indian/Antananarivo",
    "iso:country":"MG",
    "wof:name":"Iharana",
    "wof:placetype":"locality"
},
  "geometry": {"coordinates":[47.53333,-19.53333],"type":"Point"}
}