{
  "type": "Feature",
  "properties": {
    "gn:admin1_code":"06",
    "gn:asciiname":"Andramba",
    "gn:cc2":"MG",
    "gn:country_code":"MG",
    "gn:dem":409,
    "gn:feature_class":"P",
    "gn:feature_code":"PPL",
    "gn:name":"Andramba",
    "gn:population":0,
    "gn:timezone":"Indian/Antananarivo",
    "iso:country":"MG",
    "name:und_x_variant":[
        "Andramba Ambony",
        "Andramba Haut",
        "Andramba"
    ],
    "wof:name":"Andramba",
    "wof:placetype":"locality"
},
  "geometry": {"coordinates":[45.28333,-23.41667],"type":"Point"}
}