{
  "type": "Feature",
  "properties": {
    "gn:admin1_code":"2.0",
    "gn:asciiname":"Tsinirahana",
    "gn:cc2":"MG",
    "gn:country_code":"MG",
    "gn:dem":1424,
    "gn:feature_class":"P",
    "gn:feature_code":"PPL",
    "gn:name":"Tsinirahana",
    "gn:population":0,
    "gn:timezone":"Indian/Antananarivo",
    "iso:country":"MG",
    "name:und_x_variant":[
        "Tsianirahana",
        "Tsinirahana"
    ],
    "wof:name":"Tsinirahana",
    "wof:placetype":"locality"
},
  "geometry": {"coordinates":[46.85,-20.78333],"type":"Point"}
}