{
  "type": "Feature",
  "properties": {
    "gn:admin1_code":"03",
    "gn:asciiname":"Ankarefo",
    "gn:country_code":"MG",
    "gn:dem":593,
    "gn:feature_class":"P",
    "gn:feature_code":"PPL",
    "gn:name":"Ankarefo",
    "gn:population":0,
    "gn:timezone":"Indian/Antananarivo",
    "iso:country":"MG",
    "wof:name":"Ankarefo",
    "wof:placetype":"locality"
},
  "geometry": {"coordinates":[45.55,-17.83333],"type":"Point"}
}