{
  "type": "Feature",
  "properties": {
    "gn:admin1_code":"05",
    "gn:asciiname":"Faliarivo",
    "gn:country_code":"MG",
    "gn:dem":1258,
    "gn:feature_class":"P",
    "gn:feature_code":"PPL",
    "gn:name":"Faliarivo",
    "gn:population":0,
    "gn:timezone":"Indian/Antananarivo",
    "iso:country":"MG",
    "wof:name":"Faliarivo",
    "wof:placetype":"locality"
},
  "geometry": {"coordinates":[46.88333,-19.11667000000001],"type":"Point"}
}