{
  "type": "Feature",
  "properties": {
    "gn:admin1_code":"02",
    "gn:asciiname":"Ambakobe",
    "gn:cc2":"MG",
    "gn:country_code":"MG",
    "gn:dem":138,
    "gn:feature_class":"P",
    "gn:feature_code":"PPL",
    "gn:name":"Ambakobe",
    "gn:population":0,
    "gn:timezone":"Indian/Antananarivo",
    "iso:country":"MG",
    "name:und_x_variant":[
        "Ambalafary",
        "Ambakobe"
    ],
    "wof:name":"Ambakobe",
    "wof:placetype":"locality"
},
  "geometry": {"coordinates":[48.08333,-20.68333],"type":"Point"}
}