{
  "type": "Feature",
  "properties": {
    "gn:admin1_code":"02",
    "gn:asciiname":"Ambohimasina",
    "gn:cc2":"MG",
    "gn:country_code":"MG",
    "gn:dem":393,
    "gn:feature_class":"P",
    "gn:feature_code":"PPL",
    "gn:name":"Ambohimasina",
    "gn:population":0,
    "gn:timezone":"Indian/Antananarivo",
    "iso:country":"MG",
    "name:und_x_variant":[
        "Vohimasina",
        "Ambohimasina"
    ],
    "wof:name":"Ambohimasina",
    "wof:placetype":"locality"
},
  "geometry": {"coordinates":[47.75,-21.08333],"type":"Point"}
}