{
  "type": "Feature",
  "properties": {
    "gn:admin1_code":"03",
    "gn:asciiname":"Antsiketraka",
    "gn:country_code":"MG",
    "gn:dem":33,
    "gn:feature_class":"P",
    "gn:feature_code":"PPL",
    "gn:name":"Antsiketraka",
    "gn:population":0,
    "gn:timezone":"Indian/Antananarivo",
    "iso:country":"MG",
    "wof:name":"Antsiketraka",
    "wof:placetype":"locality"
},
  "geometry": {"coordinates":[46.13333,-16.26667],"type":"Point"}
}