{
  "type": "Feature",
  "properties": {
    "gn:admin1_code":"03",
    "gn:asciiname":"Ambondro",
    "gn:country_code":"MG",
    "gn:dem":14,
    "gn:feature_class":"P",
    "gn:feature_code":"PPL",
    "gn:name":"Ambondro",
    "gn:population":0,
    "gn:timezone":"Indian/Antananarivo",
    "iso:country":"MG",
    "name:azb_x_preferred":[
        "\u0627\u0645\u0628\u0627\u0646\u062f\u0631\u0648"
    ],
    "name:fas_x_preferred":[
        "\u0627\u0645\u0628\u0627\u0646\u062f\u0631\u0648"
    ],
    "name:fra_x_preferred":[
        "Ambondro"
    ],
    "name:ita_x_preferred":[
        "Ambondro"
    ],
    "name:mlg_x_preferred":[
        "Ambondro"
    ],
    "name:nld_x_preferred":[
        "Ambondro"
    ],
    "wof:name":"Ambondro",
    "wof:placetype":"locality"
},
  "geometry": {"coordinates":[47.38333,-15.06667],"type":"Point"}
}