{
  "type": "Feature",
  "properties": {
    "gn:admin1_code":"02",
    "gn:asciiname":"Anjamana",
    "gn:country_code":"MG",
    "gn:dem":1310,
    "gn:feature_class":"P",
    "gn:feature_code":"PPL",
    "gn:name":"Anjamana",
    "gn:population":0,
    "gn:timezone":"Indian/Antananarivo",
    "iso:country":"MG",
    "wof:name":"Anjamana",
    "wof:placetype":"locality"
},
  "geometry": {"coordinates":[47.18333,-20.41667],"type":"Point"}
}