{
  "type": "Feature",
  "properties": {
    "gn:admin1_code":"04",
    "gn:asciiname":"Ambia",
    "gn:country_code":"MG",
    "gn:dem":5,
    "gn:feature_class":"P",
    "gn:feature_code":"PPL",
    "gn:name":"Ambia",
    "gn:population":0,
    "gn:timezone":"Indian/Antananarivo",
    "iso:country":"MG",
    "name:ceb_x_preferred":[
        "Ambia"
    ],
    "name:deu_x_preferred":[
        "Ambia"
    ],
    "name:fra_x_preferred":[
        "Ambia"
    ],
    "name:nld_x_preferred":[
        "Ambia"
    ],
    "name:por_x_preferred":[
        "Ambia"
    ],
    "name:swe_x_preferred":[
        "Ambia"
    ],
    "wof:name":"Ambia",
    "wof:placetype":"locality"
},
  "geometry": {"coordinates":[49.76667,-15.41667],"type":"Point"}
}