{
  "type": "Feature",
  "properties": {
    "gn:admin1_code":"06",
    "gn:asciiname":"Ampamosira",
    "gn:country_code":"MG",
    "gn:dem":553,
    "gn:feature_class":"P",
    "gn:feature_code":"PPL",
    "gn:name":"Ampamosira",
    "gn:population":0,
    "gn:timezone":"Indian/Antananarivo",
    "iso:country":"MG",
    "wof:name":"Ampamosira",
    "wof:placetype":"locality"
},
  "geometry": {"coordinates":[46.56667,-24.71667],"type":"Point"}
}