{
  "type": "Feature",
  "properties": {
    "gn:admin1_code":"02",
    "gn:asciiname":"Mahazenda",
    "gn:country_code":"MG",
    "gn:dem":266,
    "gn:feature_class":"P",
    "gn:feature_code":"PPL",
    "gn:name":"Mahazenda",
    "gn:population":0,
    "gn:timezone":"Indian/Antananarivo",
    "iso:country":"MG",
    "wof:name":"Mahazenda",
    "wof:placetype":"locality"
},
  "geometry": {"coordinates":[47.45,-21.86667000000001],"type":"Point"}
}