{
  "type": "Feature",
  "properties": {
    "gn:admin1_code":"03",
    "gn:asciiname":"Andraratranina",
    "gn:cc2":"MG",
    "gn:country_code":"MG",
    "gn:dem":1098,
    "gn:feature_class":"P",
    "gn:feature_code":"PPL",
    "gn:name":"Andraratranina",
    "gn:population":0,
    "gn:timezone":"Indian/Antananarivo",
    "iso:country":"MG",
    "name:und_x_variant":[
        "Andratranina",
        "Andraratrina",
        "Andraratranina"
    ],
    "wof:name":"Andraratranina",
    "wof:placetype":"locality"
},
  "geometry": {"coordinates":[48.63333,-14.51667],"type":"Point"}
}