{
  "type": "Feature",
  "properties": {
    "gn:admin1_code":"3.0",
    "gn:asciiname":"Sadadiana",
    "gn:country_code":"MG",
    "gn:dem":15,
    "gn:feature_class":"P",
    "gn:feature_code":"PPL",
    "gn:name":"Sadadiana",
    "gn:population":0,
    "gn:timezone":"Indian/Antananarivo",
    "iso:country":"MG",
    "wof:name":"Sadadiana",
    "wof:placetype":"locality"
},
  "geometry": {"coordinates":[45.25,-15.95],"type":"Point"}
}