{
  "type": "Feature",
  "properties": {
    "gn:admin1_code":"04",
    "gn:asciiname":"Andasinindriatsara",
    "gn:country_code":"MG",
    "gn:dem":440,
    "gn:feature_class":"P",
    "gn:feature_code":"PPL",
    "gn:name":"Andasinindriatsara",
    "gn:population":0,
    "gn:timezone":"Indian/Antananarivo",
    "iso:country":"MG",
    "wof:name":"Andasinindriatsara",
    "wof:placetype":"locality"
},
  "geometry": {"coordinates":[48.13333,-16.45],"type":"Point"}
}