{
  "type": "Feature",
  "properties": {
    "gn:admin1_code":"03",
    "gn:asciiname":"Ambendrana",
    "gn:country_code":"MG",
    "gn:dem":728,
    "gn:feature_class":"P",
    "gn:feature_code":"PPL",
    "gn:name":"Ambendrana",
    "gn:population":0,
    "gn:timezone":"Indian/Antananarivo",
    "iso:country":"MG",
    "wof:name":"Ambendrana",
    "wof:placetype":"locality"
},
  "geometry": {"coordinates":[48.95,-16.36667000000001],"type":"Point"}
}