{
  "type": "Feature",
  "properties": {
    "gn:admin1_code":"2.0",
    "gn:asciiname":"Tanambao",
    "gn:country_code":"MG",
    "gn:dem":333,
    "gn:feature_class":"P",
    "gn:feature_code":"PPL",
    "gn:name":"Tanambao",
    "gn:population":0,
    "gn:timezone":"Indian/Antananarivo",
    "iso:country":"MG",
    "wof:name":"Tanambao",
    "wof:placetype":"locality"
},
  "geometry": {"coordinates":[47.28333,-22.53333],"type":"Point"}
}