{
  "type": "Feature",
  "properties": {
    "gn:admin1_code":"02",
    "gn:asciiname":"Ambakona",
    "gn:country_code":"MG",
    "gn:dem":322,
    "gn:feature_class":"P",
    "gn:feature_code":"PPL",
    "gn:name":"Ambakona",
    "gn:population":0,
    "gn:timezone":"Indian/Antananarivo",
    "iso:country":"MG",
    "wof:name":"Ambakona",
    "wof:placetype":"locality"
},
  "geometry": {"coordinates":[47.83333,-20.98333],"type":"Point"}
}