{
  "type": "Feature",
  "properties": {
    "gn:admin1_code":"02",
    "gn:asciiname":"Ambalamalemy",
    "gn:country_code":"MG",
    "gn:dem":792,
    "gn:feature_class":"P",
    "gn:feature_code":"PPL",
    "gn:name":"Ambalamalemy",
    "gn:population":0,
    "gn:timezone":"Indian/Antananarivo",
    "iso:country":"MG",
    "wof:name":"Ambalamalemy",
    "wof:placetype":"locality"
},
  "geometry": {"coordinates":[46.43333,-21.08333],"type":"Point"}
}