{
  "type": "Feature",
  "properties": {
    "gn:admin1_code":"01",
    "gn:asciiname":"Manirenja",
    "gn:country_code":"MG",
    "gn:dem":44,
    "gn:feature_class":"P",
    "gn:feature_code":"PPL",
    "gn:name":"Manirenja",
    "gn:population":0,
    "gn:timezone":"Indian/Antananarivo",
    "iso:country":"MG",
    "wof:name":"Manirenja",
    "wof:placetype":"locality"
},
  "geometry": {"coordinates":[48.53333,-13.91667],"type":"Point"}
}