{
  "type": "Feature",
  "properties": {
    "gn:admin1_code":"01",
    "gn:asciiname":"Beanamalaho",
    "gn:country_code":"MG",
    "gn:dem":163,
    "gn:feature_class":"P",
    "gn:feature_code":"PPL",
    "gn:name":"Beanamalaho",
    "gn:population":0,
    "gn:timezone":"Indian/Antananarivo",
    "iso:country":"MG",
    "wof:name":"Beanamalaho",
    "wof:placetype":"locality"
},
  "geometry": {"coordinates":[48.15,-13.86667],"type":"Point"}
}