{
  "type": "Feature",
  "properties": {
    "gn:admin1_code":"05",
    "gn:asciiname":"Antanimbarive",
    "gn:cc2":"MG",
    "gn:country_code":"MG",
    "gn:dem":821,
    "gn:feature_class":"P",
    "gn:feature_code":"PPL",
    "gn:name":"Antanimbarive",
    "gn:population":0,
    "gn:timezone":"Indian/Antananarivo",
    "iso:country":"MG",
    "name:und_x_variant":[
        "Antanimbarbe",
        "Antanimbarive"
    ],
    "wof:name":"Antanimbarive",
    "wof:placetype":"locality"
},
  "geometry": {"coordinates":[47.45,-17.95],"type":"Point"}
}