{
  "type": "Feature",
  "properties": {
    "gn:admin1_code":"03",
    "gn:asciiname":"Ankitra",
    "gn:country_code":"MG",
    "gn:dem":331,
    "gn:feature_class":"P",
    "gn:feature_code":"PPL",
    "gn:name":"Ankitra",
    "gn:population":0,
    "gn:timezone":"Indian/Antananarivo",
    "iso:country":"MG",
    "wof:name":"Ankitra",
    "wof:placetype":"locality"
},
  "geometry": {"coordinates":[44.53333,-17.96667],"type":"Point"}
}