{
  "type": "Feature",
  "properties": {
    "gn:admin1_code":"05",
    "gn:asciiname":"Andranovelona",
    "gn:country_code":"MG",
    "gn:dem":1504,
    "gn:feature_class":"P",
    "gn:feature_code":"PPL",
    "gn:name":"Andranovelona",
    "gn:population":0,
    "gn:timezone":"Indian/Antananarivo",
    "iso:country":"MG",
    "name:fra_x_preferred":[
        "Andranovelona"
    ],
    "name:ita_x_preferred":[
        "Andranovelona"
    ],
    "name:mlg_x_preferred":[
        "Andranovelona"
    ],
    "name:nld_x_preferred":[
        "Andranovelona"
    ],
    "name:pol_x_preferred":[
        "Andranovelona"
    ],
    "wof:name":"Andranovelona",
    "wof:placetype":"locality"
},
  "geometry": {"coordinates":[47.28333,-18.63333],"type":"Point"}
}