{
  "type": "Feature",
  "properties": {
    "gn:admin1_code":"03",
    "gn:asciiname":"Amparihy",
    "gn:country_code":"MG",
    "gn:dem":692,
    "gn:feature_class":"P",
    "gn:feature_code":"PPL",
    "gn:name":"Amparihy",
    "gn:population":0,
    "gn:timezone":"Indian/Antananarivo",
    "iso:country":"MG",
    "name:azb_x_preferred":[
        "\u0627\u0645\u067e\u0627\u0631\u0647\u06cc"
    ],
    "name:fas_x_preferred":[
        "\u0627\u0645\u067e\u0627\u0631\u0647\u06cc"
    ],
    "name:fra_x_preferred":[
        "Amparihy"
    ],
    "name:ita_x_preferred":[
        "Amparihy"
    ],
    "name:mlg_x_preferred":[
        "Amparihy"
    ],
    "name:nld_x_preferred":[
        "Amparihy"
    ],
    "wof:name":"Amparihy",
    "wof:placetype":"locality"
},
  "geometry": {"coordinates":[47.83333,-16.96667],"type":"Point"}
}