{
  "type": "Feature",
  "properties": {
    "gn:admin1_code":"03",
    "gn:asciiname":"Amparihy",
    "gn:country_code":"MG",
    "gn:dem":692,
    "gn:feature_class":"P",
    "gn:feature_code":"PPL",
    "gn:name":"Amparihy",
    "gn:population":0,
    "gn:timezone":"Indian/Antananarivo",
    "iso:country":"MG",
    "wof:name":"Amparihy",
    "wof:placetype":"locality"
},
  "geometry": {"coordinates":[47.83333,-16.96667],"type":"Point"}
}