{
  "type": "Feature",
  "properties": {
    "gn:admin1_code":"01",
    "gn:asciiname":"Masomamangy",
    "gn:country_code":"MG",
    "gn:dem":53,
    "gn:feature_class":"P",
    "gn:feature_code":"PPL",
    "gn:name":"Masomamangy",
    "gn:population":0,
    "gn:timezone":"Indian/Antananarivo",
    "iso:country":"MG",
    "wof:name":"Masomamangy",
    "wof:placetype":"locality"
},
  "geometry": {"coordinates":[49.96667,-14.01667],"type":"Point"}
}