{
  "type": "Feature",
  "properties": {
    "gn:admin1_code":"06",
    "gn:asciiname":"Bemoka",
    "gn:country_code":"MG",
    "gn:dem":97,
    "gn:feature_class":"P",
    "gn:feature_code":"PPL",
    "gn:name":"Bemoka",
    "gn:population":0,
    "gn:timezone":"Indian/Antananarivo",
    "iso:country":"MG",
    "wof:name":"Bemoka",
    "wof:placetype":"locality"
},
  "geometry": {"coordinates":[43.71667,-22.18333],"type":"Point"}
}