{
  "type": "Feature",
  "properties": {
    "gn:admin1_code":"7670850",
    "gn:admin2_code":"11072831",
    "gn:asciiname":"Ampotaka",
    "gn:cc2":"MG",
    "gn:country_code":"MG",
    "gn:dem":887,
    "gn:feature_class":"P",
    "gn:feature_code":"PPL",
    "gn:name":"Ampotaka",
    "gn:population":0,
    "gn:timezone":"Indian/Antananarivo",
    "iso:country":"MG",
    "name:und_x_variant":[
        "Ampataka",
        "Ampotaka Sud",
        "Ampotaka"
    ],
    "wof:name":"Ampotaka",
    "wof:placetype":"locality"
},
  "geometry": {"coordinates":[46.93333,-17.78333],"type":"Point"}
}