{
  "type": "Feature",
  "properties": {
    "gn:admin1_code":"06",
    "gn:asciiname":"Ankeramena",
    "gn:country_code":"MG",
    "gn:dem":315,
    "gn:feature_class":"P",
    "gn:feature_code":"PPL",
    "gn:name":"Ankeramena",
    "gn:population":0,
    "gn:timezone":"Indian/Antananarivo",
    "iso:country":"MG",
    "wof:name":"Ankeramena",
    "wof:placetype":"locality"
},
  "geometry": {"coordinates":[45.23333,-24.45],"type":"Point"}
}