{
  "type": "Feature",
  "properties": {
    "gn:admin1_code":"04",
    "gn:asciiname":"Ambodivohitra",
    "gn:country_code":"MG",
    "gn:dem":376,
    "gn:feature_class":"P",
    "gn:feature_code":"PPL",
    "gn:name":"Ambodivohitra",
    "gn:population":0,
    "gn:timezone":"Indian/Antananarivo",
    "iso:country":"MG",
    "wof:name":"Ambodivohitra",
    "wof:placetype":"locality"
},
  "geometry": {"coordinates":[49.25,-17.01667],"type":"Point"}
}