{
  "type": "Feature",
  "properties": {
    "gn:admin1_code":"4.0",
    "gn:asciiname":"Sakalava",
    "gn:country_code":"MG",
    "gn:dem":232,
    "gn:feature_class":"P",
    "gn:feature_code":"PPL",
    "gn:name":"Sakalava",
    "gn:population":0,
    "gn:timezone":"Indian/Antananarivo",
    "iso:country":"MG",
    "wof:name":"Sakalava",
    "wof:placetype":"locality"
},
  "geometry": {"coordinates":[48.33333,-19.83333],"type":"Point"}
}