{
  "type": "Feature",
  "properties": {
    "gn:admin1_code":"03",
    "gn:asciiname":"Ambodiadabo",
    "gn:country_code":"MG",
    "gn:dem":161,
    "gn:feature_class":"P",
    "gn:feature_code":"PPL",
    "gn:name":"Ambodiadabo",
    "gn:population":0,
    "gn:timezone":"Indian/Antananarivo",
    "iso:country":"MG",
    "wof:name":"Ambodiadabo",
    "wof:placetype":"locality"
},
  "geometry": {"coordinates":[47.71667,-14.76667],"type":"Point"}
}