{
  "type": "Feature",
  "properties": {
    "gn:admin1_code":"02",
    "gn:asciiname":"Madiorano",
    "gn:country_code":"MG",
    "gn:dem":538,
    "gn:feature_class":"P",
    "gn:feature_code":"PPL",
    "gn:name":"Madiorano",
    "gn:population":0,
    "gn:timezone":"Indian/Antananarivo",
    "iso:country":"MG",
    "wof:name":"Madiorano",
    "wof:placetype":"locality"
},
  "geometry": {"coordinates":[47.48333,-21.51667],"type":"Point"}
}