{
  "type": "Feature",
  "properties": {
    "gn:admin1_code":"05",
    "gn:asciiname":"Ampitantafika",
    "gn:cc2":"MG",
    "gn:country_code":"MG",
    "gn:dem":1565,
    "gn:feature_class":"P",
    "gn:feature_code":"PPL",
    "gn:name":"Ampitantafika",
    "gn:population":0,
    "gn:timezone":"Indian/Antananarivo",
    "iso:country":"MG",
    "name:und_x_variant":[
        "Ampitatafika",
        "Ampitantafika"
    ],
    "wof:name":"Ampitantafika",
    "wof:placetype":"locality"
},
  "geometry": {"coordinates":[47.35,-19.56667],"type":"Point"}
}