{
  "type": "Feature",
  "properties": {
    "gn:admin1_code":"02",
    "gn:asciiname":"Fanivelona",
    "gn:country_code":"MG",
    "gn:dem":9,
    "gn:feature_class":"P",
    "gn:feature_code":"PPL",
    "gn:name":"Fanivelona",
    "gn:population":0,
    "gn:timezone":"Indian/Antananarivo",
    "iso:country":"MG",
    "wof:name":"Fanivelona",
    "wof:placetype":"locality"
},
  "geometry": {"coordinates":[48.48333,-20.61667000000001],"type":"Point"}
}