{
  "type": "Feature",
  "properties": {
    "gn:admin1_code":"02",
    "gn:asciiname":"Antsakoana",
    "gn:cc2":"MG",
    "gn:country_code":"MG",
    "gn:dem":644,
    "gn:feature_class":"P",
    "gn:feature_code":"PPL",
    "gn:name":"Antsakoana",
    "gn:population":0,
    "gn:timezone":"Indian/Antananarivo",
    "iso:country":"MG",
    "name:und_x_variant":[
        "Antsahoano",
        "Antsakoana"
    ],
    "wof:name":"Antsakoana",
    "wof:placetype":"locality"
},
  "geometry": {"coordinates":[46.28333,-20.95],"type":"Point"}
}