{
  "type": "Feature",
  "properties": {
    "gn:admin1_code":"04",
    "gn:asciiname":"Niarovana",
    "gn:cc2":"MG",
    "gn:country_code":"MG",
    "gn:dem":50,
    "gn:feature_class":"P",
    "gn:feature_code":"PPL",
    "gn:name":"Niarovana",
    "gn:population":0,
    "gn:timezone":"Indian/Antananarivo",
    "iso:country":"MG",
    "name:und_x_variant":[
        "Niarovana Vohimisaingo",
        "Niarovana"
    ],
    "wof:name":"Niarovana",
    "wof:placetype":"locality"
},
  "geometry": {"coordinates":[48.75,-19.66667],"type":"Point"}
}