{
  "type": "Feature",
  "properties": {
    "gn:admin1_code":"03",
    "gn:asciiname":"Maizimazava",
    "gn:country_code":"MG",
    "gn:dem":16,
    "gn:feature_class":"P",
    "gn:feature_code":"PPL",
    "gn:name":"Maizimazava",
    "gn:population":0,
    "gn:timezone":"Indian/Antananarivo",
    "iso:country":"MG",
    "wof:name":"Maizimazava",
    "wof:placetype":"locality"
},
  "geometry": {"coordinates":[46.93333,-15.81667],"type":"Point"}
}