{
  "type": "Feature",
  "properties": {
    "gn:admin1_code":"06",
    "gn:asciiname":"Anjamaro",
    "gn:country_code":"MG",
    "gn:dem":264,
    "gn:feature_class":"P",
    "gn:feature_code":"PPL",
    "gn:name":"Anjamaro",
    "gn:population":0,
    "gn:timezone":"Indian/Antananarivo",
    "iso:country":"MG",
    "wof:name":"Anjamaro",
    "wof:placetype":"locality"
},
  "geometry": {"coordinates":[45.11667,-24.73333],"type":"Point"}
}