{
  "type": "Feature",
  "properties": {
    "gn:admin1_code":"03",
    "gn:asciiname":"Ampijoroana",
    "gn:country_code":"MG",
    "gn:dem":49,
    "gn:feature_class":"P",
    "gn:feature_code":"PPL",
    "gn:name":"Ampijoroana",
    "gn:population":0,
    "gn:timezone":"Indian/Antananarivo",
    "iso:country":"MG",
    "wof:name":"Ampijoroana",
    "wof:placetype":"locality"
},
  "geometry": {"coordinates":[47.61667,-16.08333],"type":"Point"}
}