{
  "type": "Feature",
  "properties": {
    "gn:admin1_code":"01",
    "gn:asciiname":"Ambatomalaza",
    "gn:country_code":"MG",
    "gn:dem":53,
    "gn:feature_class":"P",
    "gn:feature_code":"PPL",
    "gn:name":"Ambatomalaza",
    "gn:population":0,
    "gn:timezone":"Indian/Antananarivo",
    "iso:country":"MG",
    "wof:name":"Ambatomalaza",
    "wof:placetype":"locality"
},
  "geometry": {"coordinates":[50.01667,-13.88333],"type":"Point"}
}