{
  "type": "Feature",
  "properties": {
    "gn:admin1_code":"5.0",
    "gn:asciiname":"Tsiazompaniry",
    "gn:country_code":"MG",
    "gn:dem":1005,
    "gn:feature_class":"P",
    "gn:feature_code":"PPL",
    "gn:name":"Tsiazompaniry",
    "gn:population":0,
    "gn:timezone":"Indian/Antananarivo",
    "iso:country":"MG",
    "wof:name":"Tsiazompaniry",
    "wof:placetype":"locality"
},
  "geometry": {"coordinates":[46.46667,-18.73333],"type":"Point"}
}