{
  "type": "Feature",
  "properties": {
    "gn:admin1_code":"03",
    "gn:asciiname":"Ambodifiakarana",
    "gn:country_code":"MG",
    "gn:dem":795,
    "gn:feature_class":"P",
    "gn:feature_code":"PPL",
    "gn:name":"Ambodifiakarana",
    "gn:population":0,
    "gn:timezone":"Indian/Antananarivo",
    "iso:country":"MG",
    "wof:name":"Ambodifiakarana",
    "wof:placetype":"locality"
},
  "geometry": {"coordinates":[47.93333,-17.13332999999999],"type":"Point"}
}