{
  "type": "Feature",
  "properties": {
    "gn:admin1_code":"05",
    "gn:asciiname":"Ambodipaiso",
    "gn:country_code":"MG",
    "gn:dem":1190,
    "gn:feature_class":"P",
    "gn:feature_code":"PPL",
    "gn:name":"Ambodipaiso",
    "gn:population":0,
    "gn:timezone":"Indian/Antananarivo",
    "iso:country":"MG",
    "wof:name":"Ambodipaiso",
    "wof:placetype":"locality"
},
  "geometry": {"coordinates":[47.73333,-18.38333],"type":"Point"}
}