{
  "type": "Feature",
  "properties": {
    "gn:admin1_code":"06",
    "gn:asciiname":"Besakoa",
    "gn:country_code":"MG",
    "gn:dem":460,
    "gn:feature_class":"P",
    "gn:feature_code":"PPL",
    "gn:name":"Besakoa",
    "gn:population":0,
    "gn:timezone":"Indian/Antananarivo",
    "iso:country":"MG",
    "wof:name":"Besakoa",
    "wof:placetype":"locality"
},
  "geometry": {"coordinates":[44.83333,-23.86667000000001],"type":"Point"}
}