{
  "type": "Feature",
  "properties": {
    "gn:admin1_code":"05",
    "gn:asciiname":"Andranomahery",
    "gn:country_code":"MG",
    "gn:dem":1218,
    "gn:feature_class":"P",
    "gn:feature_code":"PPL",
    "gn:name":"Andranomahery",
    "gn:population":0,
    "gn:timezone":"Indian/Antananarivo",
    "iso:country":"MG",
    "wof:name":"Andranomahery",
    "wof:placetype":"locality"
},
  "geometry": {"coordinates":[47.41667,-18.48333],"type":"Point"}
}