{
  "type": "Feature",
  "properties": {
    "gn:admin1_code":"03",
    "gn:asciiname":"Andovokobe",
    "gn:country_code":"MG",
    "gn:dem":44,
    "gn:feature_class":"P",
    "gn:feature_code":"PPL",
    "gn:name":"Andovokobe",
    "gn:population":0,
    "gn:timezone":"Indian/Antananarivo",
    "iso:country":"MG",
    "wof:name":"Andovokobe",
    "wof:placetype":"locality"
},
  "geometry": {"coordinates":[47.33333,-15.48333],"type":"Point"}
}