{
  "type": "Feature",
  "properties": {
    "gn:admin1_code":"4.0",
    "gn:asciiname":"Sahalampona",
    "gn:country_code":"MG",
    "gn:dem":83,
    "gn:feature_class":"P",
    "gn:feature_code":"PPL",
    "gn:name":"Sahalampona",
    "gn:population":0,
    "gn:timezone":"Indian/Antananarivo",
    "iso:country":"MG",
    "wof:name":"Sahalampona",
    "wof:placetype":"locality"
},
  "geometry": {"coordinates":[48.85,-18.65],"type":"Point"}
}