{
  "type": "Feature",
  "properties": {
    "gn:admin1_code":"02",
    "gn:asciiname":"Ampitavanana",
    "gn:country_code":"MG",
    "gn:dem":683,
    "gn:feature_class":"P",
    "gn:feature_code":"PPL",
    "gn:name":"Ampitavanana",
    "gn:population":0,
    "gn:timezone":"Indian/Antananarivo",
    "iso:country":"MG",
    "wof:name":"Ampitavanana",
    "wof:placetype":"locality"
},
  "geometry": {"coordinates":[47.51667,-21.23333],"type":"Point"}
}