{
  "type": "Feature",
  "properties": {
    "gn:admin1_code":"03",
    "gn:asciiname":"Ankasetra",
    "gn:country_code":"MG",
    "gn:dem":130,
    "gn:feature_class":"P",
    "gn:feature_code":"PPL",
    "gn:name":"Ankasetra",
    "gn:population":0,
    "gn:timezone":"Indian/Antananarivo",
    "iso:country":"MG",
    "wof:name":"Ankasetra",
    "wof:placetype":"locality"
},
  "geometry": {"coordinates":[47.81667,-14.16667],"type":"Point"}
}