{
  "type": "Feature",
  "properties": {
    "gn:admin1_code":"06",
    "gn:asciiname":"Akobabaky",
    "gn:country_code":"MG",
    "gn:dem":487,
    "gn:feature_class":"P",
    "gn:feature_code":"PPL",
    "gn:name":"Akobabaky",
    "gn:population":0,
    "gn:timezone":"Indian/Antananarivo",
    "iso:country":"MG",
    "wof:name":"Akobabaky",
    "wof:placetype":"locality"
},
  "geometry": {"coordinates":[44.91667,-23.93333],"type":"Point"}
}