{
  "type": "Feature",
  "properties": {
    "gn:admin1_code":"02",
    "gn:asciiname":"Fenoarivo",
    "gn:country_code":"MG",
    "gn:dem":690,
    "gn:feature_class":"P",
    "gn:feature_code":"PPL",
    "gn:name":"Fenoarivo",
    "gn:population":0,
    "gn:timezone":"Indian/Antananarivo",
    "iso:country":"MG",
    "wof:name":"Fenoarivo",
    "wof:placetype":"locality"
},
  "geometry": {"coordinates":[46.36667,-22.36667000000001],"type":"Point"}
}