{
  "type": "Feature",
  "properties": {
    "gn:admin1_code":"4.0",
    "gn:asciiname":"Vohilava",
    "gn:country_code":"MG",
    "gn:dem":24,
    "gn:feature_class":"P",
    "gn:feature_code":"PPL",
    "gn:name":"Vohilava",
    "gn:population":0,
    "gn:timezone":"Indian/Antananarivo",
    "iso:country":"MG",
    "wof:name":"Vohilava",
    "wof:placetype":"locality"
},
  "geometry": {"coordinates":[49.33333,-18.01667],"type":"Point"}
}