{
  "type": "Feature",
  "properties": {
    "gn:admin1_code":"05",
    "gn:asciiname":"Ankazoabo",
    "gn:country_code":"MG",
    "gn:dem":757,
    "gn:feature_class":"P",
    "gn:feature_code":"PPL",
    "gn:name":"Ankazoabo",
    "gn:population":0,
    "gn:timezone":"Indian/Antananarivo",
    "iso:country":"MG",
    "name:fra_x_preferred":[
        "Ankazoabo"
    ],
    "name:ita_x_preferred":[
        "Ankazoabo"
    ],
    "name:mlg_x_preferred":[
        "Ankazoabo"
    ],
    "name:nld_x_preferred":[
        "Ankazoabo"
    ],
    "name:pol_x_preferred":[
        "Ankazoabo"
    ],
    "wof:name":"Ankazoabo",
    "wof:placetype":"locality"
},
  "geometry": {"coordinates":[46.18333,-18.08333],"type":"Point"}
}