{
  "type": "Feature",
  "properties": {
    "gn:admin1_code":"5.0",
    "gn:asciiname":"Talata-maty",
    "gn:country_code":"MG",
    "gn:dem":1279,
    "gn:feature_class":"P",
    "gn:feature_code":"PPL",
    "gn:name":"Talata-maty",
    "gn:population":0,
    "gn:timezone":"Indian/Antananarivo",
    "iso:country":"MG",
    "wof:name":"Talata-maty",
    "wof:placetype":"locality"
},
  "geometry": {"coordinates":[47.45,-18.83333],"type":"Point"}
}