{
  "type": "Feature",
  "properties": {
    "gn:admin1_code":"6.0",
    "gn:asciiname":"Vohimary",
    "gn:country_code":"MG",
    "gn:dem":377,
    "gn:feature_class":"P",
    "gn:feature_code":"PPL",
    "gn:name":"Vohimary",
    "gn:population":0,
    "gn:timezone":"Indian/Antananarivo",
    "iso:country":"MG",
    "wof:name":"Vohimary",
    "wof:placetype":"locality"
},
  "geometry": {"coordinates":[46.21667,-24.05],"type":"Point"}
}