{
  "type": "Feature",
  "properties": {
    "gn:admin1_code":"06",
    "gn:asciiname":"Ankaramany",
    "gn:cc2":"MG",
    "gn:country_code":"MG",
    "gn:dem":12,
    "gn:feature_class":"P",
    "gn:feature_code":"PPL",
    "gn:name":"Ankaramany",
    "gn:population":0,
    "gn:timezone":"Indian/Antananarivo",
    "iso:country":"MG",
    "name:und_x_variant":[
        "Ankaramanihy",
        "Ankaramany"
    ],
    "wof:name":"Ankaramany",
    "wof:placetype":"locality"
},
  "geometry": {"coordinates":[47.28333,-24.41667],"type":"Point"}
}