{
  "type": "Feature",
  "properties": {
    "gn:admin1_code":"02",
    "gn:asciiname":"Lalinia",
    "gn:country_code":"MG",
    "gn:dem":949,
    "gn:feature_class":"P",
    "gn:feature_code":"PPL",
    "gn:name":"Lalinia",
    "gn:population":0,
    "gn:timezone":"Indian/Antananarivo",
    "iso:country":"MG",
    "wof:name":"Lalinia",
    "wof:placetype":"locality"
},
  "geometry": {"coordinates":[46.48333,-21.73333],"type":"Point"}
}