{
  "type": "Feature",
  "properties": {
    "gn:admin1_code":"2.0",
    "gn:asciiname":"Sakamanitra",
    "gn:cc2":"MG",
    "gn:country_code":"MG",
    "gn:dem":646,
    "gn:feature_class":"P",
    "gn:feature_code":"PPL",
    "gn:name":"Sakamanitra",
    "gn:population":0,
    "gn:timezone":"Indian/Antananarivo",
    "iso:country":"MG",
    "name:und_x_variant":[
        "Sakamaina",
        "Sakamanitra"
    ],
    "wof:name":"Sakamanitra",
    "wof:placetype":"locality"
},
  "geometry": {"coordinates":[46.11667,-21.76667],"type":"Point"}
}