{
  "type": "Feature",
  "properties": {
    "gn:admin1_code":"01",
    "gn:asciiname":"Andranofotsy",
    "gn:country_code":"MG",
    "gn:dem":710,
    "gn:feature_class":"P",
    "gn:feature_code":"PPL",
    "gn:name":"Andranofotsy",
    "gn:population":0,
    "gn:timezone":"Indian/Antananarivo",
    "iso:country":"MG",
    "wof:name":"Andranofotsy",
    "wof:placetype":"locality"
},
  "geometry": {"coordinates":[49.46667,-14.18333],"type":"Point"}
}