{
  "type": "Feature",
  "properties": {
    "gn:admin1_code":"06",
    "gn:asciiname":"Manjakarivo",
    "gn:country_code":"MG",
    "gn:dem":66,
    "gn:feature_class":"P",
    "gn:feature_code":"PPL",
    "gn:name":"Manjakarivo",
    "gn:population":0,
    "gn:timezone":"Indian/Antananarivo",
    "iso:country":"MG",
    "wof:name":"Manjakarivo",
    "wof:placetype":"locality"
},
  "geometry": {"coordinates":[44.35,-20.63333],"type":"Point"}
}