{
  "type": "Feature",
  "properties": {
    "gn:admin1_code":"03",
    "gn:asciiname":"Antokotelo",
    "gn:country_code":"MG",
    "gn:dem":443,
    "gn:feature_class":"P",
    "gn:feature_code":"PPL",
    "gn:name":"Antokotelo",
    "gn:population":0,
    "gn:timezone":"Indian/Antananarivo",
    "iso:country":"MG",
    "wof:name":"Antokotelo",
    "wof:placetype":"locality"
},
  "geometry": {"coordinates":[47.85,-16.33333],"type":"Point"}
}