{
  "type": "Feature",
  "properties": {
    "gn:admin1_code":"6.0",
    "gn:asciiname":"Tambohoabo",
    "gn:country_code":"MG",
    "gn:dem":1,
    "gn:feature_class":"P",
    "gn:feature_code":"PPL",
    "gn:name":"Tambohoabo",
    "gn:population":0,
    "gn:timezone":"Indian/Antananarivo",
    "iso:country":"MG",
    "wof:name":"Tambohoabo",
    "wof:placetype":"locality"
},
  "geometry": {"coordinates":[43.75,-23.55],"type":"Point"}
}