{
  "type": "Feature",
  "properties": {
    "gn:admin1_code":"5.0",
    "gn:asciiname":"Tsimbaimamo",
    "gn:country_code":"MG",
    "gn:dem":851,
    "gn:feature_class":"P",
    "gn:feature_code":"PPL",
    "gn:name":"Tsimbaimamo",
    "gn:population":0,
    "gn:timezone":"Indian/Antananarivo",
    "iso:country":"MG",
    "wof:name":"Tsimbaimamo",
    "wof:placetype":"locality"
},
  "geometry": {"coordinates":[46.36667,-19.38333],"type":"Point"}
}