{
  "type": "Feature",
  "properties": {
    "gn:admin1_code":"03",
    "gn:asciiname":"Antsira",
    "gn:country_code":"MG",
    "gn:dem":822,
    "gn:feature_class":"P",
    "gn:feature_code":"PPL",
    "gn:name":"Antsira",
    "gn:population":0,
    "gn:timezone":"Indian/Antananarivo",
    "iso:country":"MG",
    "wof:name":"Antsira",
    "wof:placetype":"locality"
},
  "geometry": {"coordinates":[49.15,-16.01667],"type":"Point"}
}