{
  "type": "Feature",
  "properties": {
    "gn:admin1_code":"6.0",
    "gn:asciiname":"Sevatery",
    "gn:country_code":"MG",
    "gn:dem":525,
    "gn:feature_class":"P",
    "gn:feature_code":"PPL",
    "gn:name":"Sevatery",
    "gn:population":0,
    "gn:timezone":"Indian/Antananarivo",
    "iso:country":"MG",
    "wof:name":"Sevatery",
    "wof:placetype":"locality"
},
  "geometry": {"coordinates":[46.61667,-24.61667000000001],"type":"Point"}
}