{
  "type": "Feature",
  "properties": {
    "gn:admin1_code":"06",
    "gn:asciiname":"Bekofoky",
    "gn:country_code":"MG",
    "gn:dem":106,
    "gn:feature_class":"P",
    "gn:feature_code":"PPL",
    "gn:name":"Bekofoky",
    "gn:population":0,
    "gn:timezone":"Indian/Antananarivo",
    "iso:country":"MG",
    "wof:name":"Bekofoky",
    "wof:placetype":"locality"
},
  "geometry": {"coordinates":[44.51667,-23.51667],"type":"Point"}
}