{
  "type": "Feature",
  "properties": {
    "gn:admin1_code":"4.0",
    "gn:asciiname":"Riamena",
    "gn:country_code":"MG",
    "gn:dem":693,
    "gn:feature_class":"P",
    "gn:feature_code":"PPL",
    "gn:name":"Riamena",
    "gn:population":0,
    "gn:timezone":"Indian/Antananarivo",
    "iso:country":"MG",
    "wof:name":"Riamena",
    "wof:placetype":"locality"
},
  "geometry": {"coordinates":[49.35,-16.15],"type":"Point"}
}