{
  "type": "Feature",
  "properties": {
    "gn:admin1_code":"05",
    "gn:asciiname":"Moranano",
    "gn:country_code":"MG",
    "gn:dem":1522,
    "gn:feature_class":"P",
    "gn:feature_code":"PPL",
    "gn:name":"Moranano",
    "gn:population":0,
    "gn:timezone":"Indian/Antananarivo",
    "iso:country":"MG",
    "wof:name":"Moranano",
    "wof:placetype":"locality"
},
  "geometry": {"coordinates":[47.01667,-19.35],"type":"Point"}
}