{
  "type": "Feature",
  "properties": {
    "gn:admin1_code":"06",
    "gn:asciiname":"Amanda",
    "gn:country_code":"MG",
    "gn:dem":213,
    "gn:feature_class":"P",
    "gn:feature_code":"PPL",
    "gn:name":"Amanda",
    "gn:population":0,
    "gn:timezone":"Indian/Antananarivo",
    "iso:country":"MG",
    "wof:name":"Amanda",
    "wof:placetype":"locality"
},
  "geometry": {"coordinates":[45.28333,-18.71667],"type":"Point"}
}