{
  "type": "Feature",
  "properties": {
    "gn:admin1_code":"4.0",
    "gn:asciiname":"Tsaratampona",
    "gn:country_code":"MG",
    "gn:dem":863,
    "gn:feature_class":"P",
    "gn:feature_code":"PPL",
    "gn:name":"Tsaratampona",
    "gn:population":0,
    "gn:timezone":"Indian/Antananarivo",
    "iso:country":"MG",
    "wof:name":"Tsaratampona",
    "wof:placetype":"locality"
},
  "geometry": {"coordinates":[48.38333,-19.16667],"type":"Point"}
}