{
  "type": "Feature",
  "properties": {
    "gn:admin1_code":"04",
    "gn:asciiname":"Ambohimiangaly",
    "gn:country_code":"MG",
    "gn:dem":764,
    "gn:feature_class":"P",
    "gn:feature_code":"PPL",
    "gn:name":"Ambohimiangaly",
    "gn:population":0,
    "gn:timezone":"Indian/Antananarivo",
    "iso:country":"MG",
    "wof:name":"Ambohimiangaly",
    "wof:placetype":"locality"
},
  "geometry": {"coordinates":[49.05,-16.95],"type":"Point"}
}