{
  "type": "Feature",
  "properties": {
    "gn:admin1_code":"2.0",
    "gn:asciiname":"Voatavolava",
    "gn:country_code":"MG",
    "gn:dem":775,
    "gn:feature_class":"P",
    "gn:feature_code":"PPL",
    "gn:name":"Voatavolava",
    "gn:population":0,
    "gn:timezone":"Indian/Antananarivo",
    "iso:country":"MG",
    "wof:name":"Voatavolava",
    "wof:placetype":"locality"
},
  "geometry": {"coordinates":[45.35,-22.65],"type":"Point"}
}