{
  "type": "Feature",
  "properties": {
    "gn:admin1_code":"6.0",
    "gn:asciiname":"Vohibaka",
    "gn:country_code":"MG",
    "gn:dem":956,
    "gn:feature_class":"P",
    "gn:feature_code":"PPL",
    "gn:name":"Vohibaka",
    "gn:population":0,
    "gn:timezone":"Indian/Antananarivo",
    "iso:country":"MG",
    "wof:name":"Vohibaka",
    "wof:placetype":"locality"
},
  "geometry": {"coordinates":[46.76667,-24.51667],"type":"Point"}
}