{
  "type": "Feature",
  "properties": {
    "gn:admin1_code":"02",
    "gn:asciiname":"Analalava",
    "gn:country_code":"MG",
    "gn:dem":688,
    "gn:feature_class":"P",
    "gn:feature_code":"PPL",
    "gn:name":"Analalava",
    "gn:population":0,
    "gn:timezone":"Indian/Antananarivo",
    "iso:country":"MG",
    "name:azb_x_preferred":[
        "\u0627\u0646\u0627\u0644\u0627\u0644\u0627\u0648\u0627"
    ],
    "name:deu_x_preferred":[
        "Analalava"
    ],
    "name:fas_x_preferred":[
        "\u0627\u0646\u0627\u0644\u0627\u0644\u0627\u0648\u0627"
    ],
    "name:fra_x_preferred":[
        "Analalava"
    ],
    "name:ita_x_preferred":[
        "Analalava"
    ],
    "name:nld_x_preferred":[
        "Analalava"
    ],
    "name:spa_x_preferred":[
        "Analalava"
    ],
    "name:zho_x_preferred":[
        "\u963f\u7d0d\u62c9\u62c9\u74e6"
    ],
    "wof:name":"Analalava",
    "wof:placetype":"locality"
},
  "geometry": {"coordinates":[45.13333,-22.56667],"type":"Point"}
}