{
  "type": "Feature",
  "properties": {
    "gn:admin1_code":"02",
    "gn:asciiname":"Faliarivo",
    "gn:cc2":"MG",
    "gn:country_code":"MG",
    "gn:dem":85,
    "gn:feature_class":"P",
    "gn:feature_code":"PPL",
    "gn:name":"Faliarivo",
    "gn:population":0,
    "gn:timezone":"Indian/Antananarivo",
    "iso:country":"MG",
    "name:und_x_variant":[
        "Fenoarivo",
        "Faliarivo"
    ],
    "wof:name":"Faliarivo",
    "wof:placetype":"locality"
},
  "geometry": {"coordinates":[48.15,-21.06667],"type":"Point"}
}