{
  "type": "Feature",
  "properties": {
    "gn:admin1_code":"06",
    "gn:asciiname":"Mitsinjo",
    "gn:country_code":"MG",
    "gn:dem":503,
    "gn:feature_class":"P",
    "gn:feature_code":"PPL",
    "gn:name":"Mitsinjo",
    "gn:population":0,
    "gn:timezone":"Indian/Antananarivo",
    "iso:country":"MG",
    "name:fra_x_preferred":[
        "Mitsinjo"
    ],
    "name:ita_x_preferred":[
        "Mitsinjo"
    ],
    "name:mlg_x_preferred":[
        "Mitsinjo"
    ],
    "name:nld_x_preferred":[
        "Mitsinjo"
    ],
    "name:zho_x_preferred":[
        "\u7c73\u6b3d\u7956"
    ],
    "wof:name":"Mitsinjo",
    "wof:placetype":"locality"
},
  "geometry": {"coordinates":[44.86667,-23.93333],"type":"Point"}
}