{
  "type": "Feature",
  "properties": {
    "gn:admin1_code":"02",
    "gn:asciiname":"Amparihibe",
    "gn:country_code":"MG",
    "gn:dem":1104,
    "gn:feature_class":"P",
    "gn:feature_code":"PPL",
    "gn:name":"Amparihibe",
    "gn:population":0,
    "gn:timezone":"Indian/Antananarivo",
    "iso:country":"MG",
    "wof:name":"Amparihibe",
    "wof:placetype":"locality"
},
  "geometry": {"coordinates":[47.23333,-21.43333],"type":"Point"}
}