{
  "type": "Feature",
  "properties": {
    "gn:admin1_code":"03",
    "gn:asciiname":"Ambinanin' Ankarany",
    "gn:country_code":"MG",
    "gn:dem":768,
    "gn:feature_class":"P",
    "gn:feature_code":"PPL",
    "gn:name":"Ambinanin\u2019 Ankarany",
    "gn:population":0,
    "gn:timezone":"Indian/Antananarivo",
    "iso:country":"MG",
    "wof:name":"Ambinanin' Ankarany",
    "wof:placetype":"locality"
},
  "geometry": {"coordinates":[49.18333,-16.08333],"type":"Point"}
}