{
  "type": "Feature",
  "properties": {
    "gn:admin1_code":"5.0",
    "gn:asciiname":"Tsiatajavona-Ankaratra",
    "gn:cc2":"MG",
    "gn:country_code":"MG",
    "gn:dem":1580,
    "gn:feature_class":"P",
    "gn:feature_code":"PPL",
    "gn:name":"Tsiatajavona-Ankaratra",
    "gn:population":0,
    "gn:timezone":"Indian/Antananarivo",
    "iso:country":"MG",
    "name:und_x_variant":[
        "Ankeniheny",
        "Tsiatajavona-Ankaratra"
    ],
    "wof:name":"Tsiatajavona-Ankaratra",
    "wof:placetype":"locality"
},
  "geometry": {"coordinates":[47.35,-19.38333],"type":"Point"}
}