{
  "type": "Feature",
  "properties": {
    "gn:admin1_code":"6.0",
    "gn:asciiname":"Soanafindra",
    "gn:country_code":"MG",
    "gn:dem":55,
    "gn:feature_class":"P",
    "gn:feature_code":"PPL",
    "gn:name":"Soanafindra",
    "gn:population":0,
    "gn:timezone":"Indian/Antananarivo",
    "iso:country":"MG",
    "wof:name":"Soanafindra",
    "wof:placetype":"locality"
},
  "geometry": {"coordinates":[44.78333,-19.61667000000001],"type":"Point"}
}