{
  "type": "Feature",
  "properties": {
    "gn:admin1_code":"03",
    "gn:asciiname":"Ankijanilava",
    "gn:country_code":"MG",
    "gn:dem":405,
    "gn:feature_class":"P",
    "gn:feature_code":"PPL",
    "gn:name":"Ankijanilava",
    "gn:population":0,
    "gn:timezone":"Indian/Antananarivo",
    "iso:country":"MG",
    "wof:name":"Ankijanilava",
    "wof:placetype":"locality"
},
  "geometry": {"coordinates":[48.51667,-16.23333],"type":"Point"}
}