{
  "type": "Feature",
  "properties": {
    "gn:admin1_code":"04",
    "gn:asciiname":"Ambohivorikely",
    "gn:cc2":"MG",
    "gn:country_code":"MG",
    "gn:dem":938,
    "gn:feature_class":"P",
    "gn:feature_code":"PPL",
    "gn:name":"Ambohivorikely",
    "gn:population":0,
    "gn:timezone":"Indian/Antananarivo",
    "iso:country":"MG",
    "name:und_x_variant":[
        "Amboavarikely",
        "Ambohivorikely"
    ],
    "wof:name":"Ambohivorikely",
    "wof:placetype":"locality"
},
  "geometry": {"coordinates":[48.48333,-16.96667],"type":"Point"}
}