{
  "type": "Feature",
  "properties": {
    "gn:admin1_code":"06",
    "gn:asciiname":"Ambazoamazava",
    "gn:cc2":"MG",
    "gn:country_code":"MG",
    "gn:dem":133,
    "gn:feature_class":"P",
    "gn:feature_code":"PPL",
    "gn:name":"Ambazoamazava",
    "gn:population":0,
    "gn:timezone":"Indian/Antananarivo",
    "iso:country":"MG",
    "name:und_x_variant":[
        "Ambazamazava",
        "Ambazoamazava"
    ],
    "wof:name":"Ambazoamazava",
    "wof:placetype":"locality"
},
  "geometry": {"coordinates":[45.83333,-25.35],"type":"Point"}
}