{
  "type": "Feature",
  "properties": {
    "gn:admin1_code":"2.0",
    "gn:asciiname":"Tambohobe",
    "gn:country_code":"MG",
    "gn:dem":1242,
    "gn:feature_class":"P",
    "gn:feature_code":"PPL",
    "gn:name":"Tambohobe",
    "gn:population":0,
    "gn:timezone":"Indian/Antananarivo",
    "iso:country":"MG",
    "wof:name":"Tambohobe",
    "wof:placetype":"locality"
},
  "geometry": {"coordinates":[46.86667,-21.95],"type":"Point"}
}