{
  "type": "Feature",
  "properties": {
    "gn:admin1_code":"03",
    "gn:asciiname":"Ambalasatrana",
    "gn:country_code":"MG",
    "gn:dem":146,
    "gn:feature_class":"P",
    "gn:feature_code":"PPL",
    "gn:name":"Ambalasatrana",
    "gn:population":0,
    "gn:timezone":"Indian/Antananarivo",
    "iso:country":"MG",
    "wof:name":"Ambalasatrana",
    "wof:placetype":"locality"
},
  "geometry": {"coordinates":[46.31667,-17.41667],"type":"Point"}
}