{
  "type": "Feature",
  "properties": {
    "gn:admin1_code":"03",
    "gn:asciiname":"Andrano",
    "gn:country_code":"MG",
    "gn:dem":9,
    "gn:feature_class":"P",
    "gn:feature_code":"PPL",
    "gn:name":"Andrano",
    "gn:population":0,
    "gn:timezone":"Indian/Antananarivo",
    "iso:country":"MG",
    "name:ara_x_preferred":[
        "\u0623\u0646\u062f\u0631\u0627\u0646\u0648"
    ],
    "name:azb_x_preferred":[
        "\u0622\u0646\u062f\u0631\u0627\u0646\u0648"
    ],
    "name:bul_x_preferred":[
        "\u0410\u043d\u0434\u0440\u0430\u043d\u043e"
    ],
    "name:ceb_x_preferred":[
        "Andrano"
    ],
    "name:deu_x_preferred":[
        "Andrano"
    ],
    "name:epo_x_preferred":[
        "Andrano"
    ],
    "name:eus_x_preferred":[
        "Andrano"
    ],
    "name:fas_x_preferred":[
        "\u0622\u0646\u062f\u0631\u0627\u0646\u0648"
    ],
    "name:fra_x_preferred":[
        "Andrano"
    ],
    "name:hun_x_preferred":[
        "Andrano"
    ],
    "name:hye_x_preferred":[
        "\u0531\u0576\u0564\u0580\u0561\u0576\u0578"
    ],
    "name:ina_x_preferred":[
        "Andrano"
    ],
    "name:ita_x_preferred":[
        "Andrano"
    ],
    "name:jpn_x_preferred":[
        "\u30a2\u30f3\u30c9\u30e9\u30fc\u30ce"
    ],
    "name:kaz_x_preferred":[
        "\u0410\u043d\u0434\u0440\u0430\u043d\u043e"
    ],
    "name:lat_x_preferred":[
        "Andranum"
    ],
    "name:lmo_x_preferred":[
        "Andrano"
    ],
    "name:msa_x_preferred":[
        "Andrano"
    ],
    "name:nap_x_preferred":[
        "Andrano"
    ],
    "name:nld_x_preferred":[
        "Andrano"
    ],
    "name:pms_x_preferred":[
        "Andrano"
    ],
    "name:pol_x_preferred":[
        "Andrano"
    ],
    "name:por_x_preferred":[
        "Andrano"
    ],
    "name:ron_x_preferred":[
        "Andrano"
    ],
    "name:rus_x_preferred":[
        "\u0410\u043d\u0434\u0440\u0430\u043d\u043e"
    ],
    "name:scn_x_preferred":[
        "Andranu"
    ],
    "name:spa_x_preferred":[
        "Andrano"
    ],
    "name:srp_x_preferred":[
        "\u0410\u043d\u0434\u0440\u0430\u043d\u043e"
    ],
    "name:tgl_x_preferred":[
        "Andrano"
    ],
    "name:ukr_x_preferred":[
        "\u0410\u043d\u0434\u0440\u0430\u043d\u043e"
    ],
    "name:uzb_x_preferred":[
        "Andrano"
    ],
    "name:vie_x_preferred":[
        "Andrano"
    ],
    "name:vol_x_preferred":[
        "Andrano"
    ],
    "name:war_x_preferred":[
        "Andrano"
    ],
    "name:zho_x_preferred":[
        "\u5b89\u5fb7\u62c9\u8bfa"
    ],
    "wof:name":"Andrano",
    "wof:placetype":"locality"
},
  "geometry": {"coordinates":[44.88333,-16.33333],"type":"Point"}
}