{
  "type": "Feature",
  "properties": {
    "gn:admin1_code":"03",
    "gn:asciiname":"Andrano",
    "gn:country_code":"MG",
    "gn:dem":9,
    "gn:feature_class":"P",
    "gn:feature_code":"PPL",
    "gn:name":"Andrano",
    "gn:population":0,
    "gn:timezone":"Indian/Antananarivo",
    "iso:country":"MG",
    "wof:name":"Andrano",
    "wof:placetype":"locality"
},
  "geometry": {"coordinates":[44.88333,-16.33333],"type":"Point"}
}