{
  "type": "Feature",
  "properties": {
    "gn:admin1_code":"05",
    "gn:asciiname":"Ambararatabe",
    "gn:country_code":"MG",
    "gn:dem":791,
    "gn:feature_class":"P",
    "gn:feature_code":"PPL",
    "gn:name":"Ambararatabe",
    "gn:population":0,
    "gn:timezone":"Indian/Antananarivo",
    "iso:country":"MG",
    "wof:name":"Ambararatabe",
    "wof:placetype":"locality"
},
  "geometry": {"coordinates":[46.18333,-18.98333],"type":"Point"}
}