{
  "type": "Feature",
  "properties": {
    "gn:admin1_code":"02",
    "gn:asciiname":"Afisamisoa",
    "gn:country_code":"MG",
    "gn:dem":1033,
    "gn:feature_class":"P",
    "gn:feature_code":"PPL",
    "gn:name":"Afisamisoa",
    "gn:population":0,
    "gn:timezone":"Indian/Antananarivo",
    "iso:country":"MG",
    "wof:name":"Afisamisoa",
    "wof:placetype":"locality"
},
  "geometry": {"coordinates":[46.73333,-21.81667],"type":"Point"}
}