{
  "type": "Feature",
  "properties": {
    "gn:admin1_code":"02",
    "gn:asciiname":"Ambohidahalo",
    "gn:country_code":"MG",
    "gn:dem":974,
    "gn:feature_class":"P",
    "gn:feature_code":"PPL",
    "gn:name":"Ambohidahalo",
    "gn:population":0,
    "gn:timezone":"Indian/Antananarivo",
    "iso:country":"MG",
    "wof:name":"Ambohidahalo",
    "wof:placetype":"locality"
},
  "geometry": {"coordinates":[46.96667,-21.95],"type":"Point"}
}