{
  "type": "Feature",
  "properties": {
    "gn:admin1_code":"06",
    "gn:asciiname":"Lanamboro",
    "gn:country_code":"MG",
    "gn:dem":498,
    "gn:feature_class":"P",
    "gn:feature_code":"PPL",
    "gn:name":"Lanamboro",
    "gn:population":0,
    "gn:timezone":"Indian/Antananarivo",
    "iso:country":"MG",
    "wof:name":"Lanamboro",
    "wof:placetype":"locality"
},
  "geometry": {"coordinates":[45.46667,-24.06667],"type":"Point"}
}