{
  "type": "Feature",
  "properties": {
    "gn:admin1_code":"02",
    "gn:asciiname":"Ambatolampy",
    "gn:country_code":"MG",
    "gn:dem":147,
    "gn:feature_class":"P",
    "gn:feature_code":"PPL",
    "gn:name":"Ambatolampy",
    "gn:population":0,
    "gn:timezone":"Indian/Antananarivo",
    "iso:country":"MG",
    "wof:name":"Ambatolampy",
    "wof:placetype":"locality"
},
  "geometry": {"coordinates":[48.23333,-20.75],"type":"Point"}
}