{
  "type": "Feature",
  "properties": {
    "gn:admin1_code":"6.0",
    "gn:asciiname":"Tsihary",
    "gn:cc2":"MG",
    "gn:country_code":"MG",
    "gn:dem":1,
    "gn:feature_class":"P",
    "gn:feature_code":"PPL",
    "gn:name":"Tsihary",
    "gn:population":0,
    "gn:timezone":"Indian/Antananarivo",
    "iso:country":"MG",
    "name:und_x_variant":[
        "Tsiary",
        "Tsihary"
    ],
    "wof:name":"Tsihary",
    "wof:placetype":"locality"
},
  "geometry": {"coordinates":[46.85,-25.03333],"type":"Point"}
}