{
  "type": "Feature",
  "properties": {
    "gn:admin1_code":"06",
    "gn:asciiname":"Ankirijibe",
    "gn:country_code":"MG",
    "gn:dem":2,
    "gn:feature_class":"P",
    "gn:feature_code":"PPL",
    "gn:name":"Ankirijibe",
    "gn:population":0,
    "gn:timezone":"Indian/Antananarivo",
    "iso:country":"MG",
    "wof:name":"Ankirijibe",
    "wof:placetype":"locality"
},
  "geometry": {"coordinates":[44.31667,-20.25],"type":"Point"}
}