{
  "type": "Feature",
  "properties": {
    "gn:admin1_code":"06",
    "gn:asciiname":"Montifeno",
    "gn:cc2":"MG",
    "gn:country_code":"MG",
    "gn:dem":228,
    "gn:feature_class":"P",
    "gn:feature_code":"PPL",
    "gn:name":"Montifeno",
    "gn:population":0,
    "gn:timezone":"Indian/Antananarivo",
    "iso:country":"MG",
    "name:fra_x_preferred":[
        "Montifeno"
    ],
    "name:mlg_x_preferred":[
        "Montifeno"
    ],
    "name:nld_x_preferred":[
        "Montifeno"
    ],
    "name:und_x_variant":[
        "Montofeno",
        "Montifeno"
    ],
    "wof:name":"Montifeno",
    "wof:placetype":"locality"
},
  "geometry": {"coordinates":[44.76667,-23.48333],"type":"Point"}
}