{
  "type": "Feature",
  "properties": {
    "gn:admin1_code":"3.0",
    "gn:asciiname":"Tsiamalao",
    "gn:cc2":"MG",
    "gn:country_code":"MG",
    "gn:dem":253,
    "gn:feature_class":"P",
    "gn:feature_code":"PPL",
    "gn:name":"Tsiamalao",
    "gn:population":0,
    "gn:timezone":"Indian/Antananarivo",
    "iso:country":"MG",
    "name:und_x_variant":[
        "Antsamalaho",
        "Tsiamalao"
    ],
    "wof:name":"Tsiamalao",
    "wof:placetype":"locality"
},
  "geometry": {"coordinates":[48.45,-15.05],"type":"Point"}
}