{
  "type": "Feature",
  "properties": {
    "gn:admin1_code":"04",
    "gn:asciiname":"Ampitabe I",
    "gn:cc2":"MG",
    "gn:country_code":"MG",
    "gn:dem":175,
    "gn:feature_class":"P",
    "gn:feature_code":"PPL",
    "gn:name":"Ampitabe I",
    "gn:population":0,
    "gn:timezone":"Indian/Antananarivo",
    "iso:country":"MG",
    "name:und_x_variant":[
        "Ampitabe",
        "Ampitabe I"
    ],
    "wof:name":"Ampitabe I",
    "wof:placetype":"locality"
},
  "geometry": {"coordinates":[48.46667,-20.06667],"type":"Point"}
}