{
  "type": "Feature",
  "properties": {
    "gn:admin1_code":"06",
    "gn:asciiname":"Anahidrano",
    "gn:country_code":"MG",
    "gn:dem":160,
    "gn:feature_class":"P",
    "gn:feature_code":"PPL",
    "gn:name":"Anahidrano",
    "gn:population":0,
    "gn:timezone":"Indian/Antananarivo",
    "iso:country":"MG",
    "name:azb_x_preferred":[
        "\u0627\u0646\u0627\u0647\u06cc\u062f\u0631\u0627\u0646\u0648"
    ],
    "name:fas_x_preferred":[
        "\u0627\u0646\u0627\u0647\u06cc\u062f\u0631\u0627\u0646\u0648"
    ],
    "name:fra_x_preferred":[
        "Anahidrano"
    ],
    "name:ita_x_preferred":[
        "Anahidrano"
    ],
    "name:mlg_x_preferred":[
        "Anahidrano"
    ],
    "name:nld_x_preferred":[
        "Anahidrano"
    ],
    "wof:name":"Anahidrano",
    "wof:placetype":"locality"
},
  "geometry": {"coordinates":[45.23333,-18.53333],"type":"Point"}
}