{
  "type": "Feature",
  "properties": {
    "gn:admin1_code":"06",
    "gn:asciiname":"Beongotsy",
    "gn:country_code":"MG",
    "gn:dem":361,
    "gn:feature_class":"P",
    "gn:feature_code":"PPL",
    "gn:name":"Beongotsy",
    "gn:population":0,
    "gn:timezone":"Indian/Antananarivo",
    "iso:country":"MG",
    "wof:name":"Beongotsy",
    "wof:placetype":"locality"
},
  "geometry": {"coordinates":[45.35,-24.36667000000001],"type":"Point"}
}