{
  "type": "Feature",
  "properties": {
    "gn:admin1_code":"06",
    "gn:asciiname":"Fandranarivo",
    "gn:cc2":"MG",
    "gn:country_code":"MG",
    "gn:dem":815,
    "gn:feature_class":"P",
    "gn:feature_code":"PPL",
    "gn:name":"Fandranarivo",
    "gn:population":0,
    "gn:timezone":"Indian/Antananarivo",
    "iso:country":"MG",
    "name:und_x_variant":[
        "Fandranarivo Sud",
        "Fandranarivo"
    ],
    "wof:name":"Fandranarivo",
    "wof:placetype":"locality"
},
  "geometry": {"coordinates":[45.96667,-23.16667],"type":"Point"}
}