{
  "type": "Feature",
  "properties": {
    "gn:admin1_code":"01",
    "gn:asciiname":"Ankatofo",
    "gn:country_code":"MG",
    "gn:dem":108,
    "gn:feature_class":"P",
    "gn:feature_code":"PPL",
    "gn:name":"Ankatofo",
    "gn:population":0,
    "gn:timezone":"Indian/Antananarivo",
    "iso:country":"MG",
    "wof:name":"Ankatofo",
    "wof:placetype":"locality"
},
  "geometry": {"coordinates":[49.11667,-13.16667],"type":"Point"}
}