{
  "type": "Feature",
  "properties": {
    "gn:admin1_code":"05",
    "gn:asciiname":"Ankijana",
    "gn:cc2":"MG",
    "gn:country_code":"MG",
    "gn:dem":997,
    "gn:feature_class":"P",
    "gn:feature_code":"PPL",
    "gn:name":"Ankijana",
    "gn:population":0,
    "gn:timezone":"Indian/Antananarivo",
    "iso:country":"MG",
    "name:und_x_variant":[
        "Ankijand",
        "Ankijana"
    ],
    "wof:name":"Ankijana",
    "wof:placetype":"locality"
},
  "geometry": {"coordinates":[46.41667,-18.85],"type":"Point"}
}