{
  "type": "Feature",
  "properties": {
    "gn:admin1_code":"05",
    "gn:asciiname":"Ambalafeno",
    "gn:country_code":"MG",
    "gn:dem":1094,
    "gn:feature_class":"P",
    "gn:feature_code":"PPL",
    "gn:name":"Ambalafeno",
    "gn:population":0,
    "gn:timezone":"Indian/Antananarivo",
    "iso:country":"MG",
    "wof:name":"Ambalafeno",
    "wof:placetype":"locality"
},
  "geometry": {"coordinates":[46.58333,-19.48333],"type":"Point"}
}