{
  "type": "Feature",
  "properties": {
    "gn:admin1_code":"06",
    "gn:asciiname":"Andoharano",
    "gn:cc2":"MG",
    "gn:country_code":"MG",
    "gn:dem":442,
    "gn:feature_class":"P",
    "gn:feature_code":"PPL",
    "gn:name":"Andoharano",
    "gn:population":0,
    "gn:timezone":"Indian/Antananarivo",
    "iso:country":"MG",
    "name:und_x_variant":[
        "Androharano",
        "Andoharano"
    ],
    "wof:name":"Andoharano",
    "wof:placetype":"locality"
},
  "geometry": {"coordinates":[44.65,-22.13333],"type":"Point"}
}