{
  "type": "Feature",
  "properties": {
    "gn:admin1_code":"04",
    "gn:asciiname":"Ambohimanarivo",
    "gn:country_code":"MG",
    "gn:dem":974,
    "gn:feature_class":"P",
    "gn:feature_code":"PPL",
    "gn:name":"Ambohimanarivo",
    "gn:population":0,
    "gn:timezone":"Indian/Antananarivo",
    "iso:country":"MG",
    "wof:name":"Ambohimanarivo",
    "wof:placetype":"locality"
},
  "geometry": {"coordinates":[48.21667,-18.23333],"type":"Point"}
}