{
  "type": "Feature",
  "properties": {
    "gn:admin1_code":"1.0",
    "gn:asciiname":"Seranampotaka",
    "gn:country_code":"MG",
    "gn:dem":45,
    "gn:feature_class":"P",
    "gn:feature_code":"PPL",
    "gn:name":"Seranampotaka",
    "gn:population":0,
    "gn:timezone":"Indian/Antananarivo",
    "iso:country":"MG",
    "wof:name":"Seranampotaka",
    "wof:placetype":"locality"
},
  "geometry": {"coordinates":[50.08333,-14.11667],"type":"Point"}
}