{
  "type": "Feature",
  "properties": {
    "gn:admin1_code":"06",
    "gn:asciiname":"Bevalala",
    "gn:country_code":"MG",
    "gn:dem":391,
    "gn:feature_class":"P",
    "gn:feature_code":"PPL",
    "gn:name":"Bevalala",
    "gn:population":0,
    "gn:timezone":"Indian/Antananarivo",
    "iso:country":"MG",
    "wof:name":"Bevalala",
    "wof:placetype":"locality"
},
  "geometry": {"coordinates":[46.58333,-24.45],"type":"Point"}
}