{
  "type": "Feature",
  "properties": {
    "gn:admin1_code":"05",
    "gn:asciiname":"Ambohipihaonana",
    "gn:cc2":"MG",
    "gn:country_code":"MG",
    "gn:dem":1582,
    "gn:feature_class":"P",
    "gn:feature_code":"PPL",
    "gn:name":"Ambohipihaonana",
    "gn:population":0,
    "gn:timezone":"Indian/Antananarivo",
    "iso:country":"MG",
    "name:azb_x_preferred":[
        "\u0627\u0645\u0628\u0648\u0647\u06cc\u067e\u06cc\u0647\u0627\u0646\u0627\u0646\u0627"
    ],
    "name:fas_x_preferred":[
        "\u0627\u0645\u0628\u0648\u0647\u06cc\u067e\u06cc\u0647\u0627\u0646\u0627\u0646\u0627"
    ],
    "name:fra_x_preferred":[
        "Ambohipihaonana"
    ],
    "name:ita_x_preferred":[
        "Ambohipihaonana"
    ],
    "name:mlg_x_preferred":[
        "Ambohipihaonana"
    ],
    "name:nld_x_preferred":[
        "Ambohipihaonana"
    ],
    "name:pol_x_preferred":[
        "Ambohipihaonana"
    ],
    "name:und_x_variant":[
        "Ambohidava",
        "Ambohipihaonana"
    ],
    "wof:name":"Ambohipihaonana",
    "wof:placetype":"locality"
},
  "geometry": {"coordinates":[47.41667,-19.43333],"type":"Point"}
}