{
  "type": "Feature",
  "properties": {
    "gn:admin1_code":"05",
    "gn:asciiname":"Ambohipihaonana",
    "gn:cc2":"MG",
    "gn:country_code":"MG",
    "gn:dem":1582,
    "gn:feature_class":"P",
    "gn:feature_code":"PPL",
    "gn:name":"Ambohipihaonana",
    "gn:population":0,
    "gn:timezone":"Indian/Antananarivo",
    "iso:country":"MG",
    "name:und_x_variant":[
        "Ambohidava",
        "Ambohipihaonana"
    ],
    "wof:name":"Ambohipihaonana",
    "wof:placetype":"locality"
},
  "geometry": {"coordinates":[47.41667,-19.43333],"type":"Point"}
}