{
  "type": "Feature",
  "properties": {
    "gn:admin1_code":"03",
    "gn:asciiname":"Ampombibe",
    "gn:country_code":"MG",
    "gn:dem":478,
    "gn:feature_class":"P",
    "gn:feature_code":"PPL",
    "gn:name":"Ampombibe",
    "gn:population":0,
    "gn:timezone":"Indian/Antananarivo",
    "iso:country":"MG",
    "wof:name":"Ampombibe",
    "wof:placetype":"locality"
},
  "geometry": {"coordinates":[48.78333,-15.48333],"type":"Point"}
}