{
  "type": "Feature",
  "properties": {
    "gn:admin1_code":"5.0",
    "gn:asciiname":"Tritriva",
    "gn:country_code":"MG",
    "gn:dem":1668,
    "gn:feature_class":"P",
    "gn:feature_code":"PPL",
    "gn:name":"Tritriva",
    "gn:population":0,
    "gn:timezone":"Indian/Antananarivo",
    "iso:country":"MG",
    "wof:name":"Tritriva",
    "wof:placetype":"locality"
},
  "geometry": {"coordinates":[46.93333,-19.91667],"type":"Point"}
}