{
  "type": "Feature",
  "properties": {
    "gn:admin1_code":"5.0",
    "gn:asciiname":"Tritriva",
    "gn:country_code":"MG",
    "gn:dem":1668,
    "gn:feature_class":"P",
    "gn:feature_code":"PPL",
    "gn:name":"Tritriva",
    "gn:population":0,
    "gn:timezone":"Indian/Antananarivo",
    "iso:country":"MG",
    "name:bul_x_preferred":[
        "\u0422\u0440\u0438\u0442\u0440\u0438\u0432\u0430"
    ],
    "name:fra_x_preferred":[
        "Tritriva"
    ],
    "name:ita_x_preferred":[
        "Tritriva"
    ],
    "name:mlg_x_preferred":[
        "Tritriva"
    ],
    "name:nld_x_preferred":[
        "Tritriva"
    ],
    "name:pol_x_preferred":[
        "Tritriva"
    ],
    "wof:name":"Tritriva",
    "wof:placetype":"locality"
},
  "geometry": {"coordinates":[46.93333,-19.91667],"type":"Point"}
}