{
  "type": "Feature",
  "properties": {
    "gn:admin1_code":"01",
    "gn:asciiname":"Ambalabao",
    "gn:country_code":"MG",
    "gn:dem":299,
    "gn:feature_class":"P",
    "gn:feature_code":"PPL",
    "gn:name":"Ambalabao",
    "gn:population":0,
    "gn:timezone":"Indian/Antananarivo",
    "iso:country":"MG",
    "wof:name":"Ambalabao",
    "wof:placetype":"locality"
},
  "geometry": {"coordinates":[49.26667,-12.81667],"type":"Point"}
}