{
  "type": "Feature",
  "properties": {
    "gn:admin1_code":"03",
    "gn:asciiname":"Antelopolo",
    "gn:country_code":"MG",
    "gn:dem":1084,
    "gn:feature_class":"P",
    "gn:feature_code":"PPL",
    "gn:name":"Antelopolo",
    "gn:population":0,
    "gn:timezone":"Indian/Antananarivo",
    "iso:country":"MG",
    "wof:name":"Antelopolo",
    "wof:placetype":"locality"
},
  "geometry": {"coordinates":[48.95,-14.56667],"type":"Point"}
}