{
  "type": "Feature",
  "properties": {
    "gn:admin1_code":"04",
    "gn:asciiname":"Antanambao",
    "gn:country_code":"MG",
    "gn:dem":216,
    "gn:feature_class":"P",
    "gn:feature_code":"PPL",
    "gn:name":"Antanambao",
    "gn:population":0,
    "gn:timezone":"Indian/Antananarivo",
    "iso:country":"MG",
    "wof:name":"Antanambao",
    "wof:placetype":"locality"
},
  "geometry": {"coordinates":[48.48333,-19.81667],"type":"Point"}
}