{
  "type": "Feature",
  "properties": {
    "gn:admin1_code":"06",
    "gn:asciiname":"Amposaky",
    "gn:cc2":"MG",
    "gn:country_code":"MG",
    "gn:dem":853,
    "gn:feature_class":"P",
    "gn:feature_code":"PPL",
    "gn:name":"Amposaky",
    "gn:population":0,
    "gn:timezone":"Indian/Antananarivo",
    "iso:country":"MG",
    "name:und_x_variant":[
        "Ampisaka",
        "Amposaky"
    ],
    "wof:name":"Amposaky",
    "wof:placetype":"locality"
},
  "geometry": {"coordinates":[46.16667,-23.55],"type":"Point"}
}