{
  "type": "Feature",
  "properties": {
    "gn:admin1_code":"05",
    "gn:asciiname":"Antanimenakely",
    "gn:country_code":"MG",
    "gn:dem":1252,
    "gn:feature_class":"P",
    "gn:feature_code":"PPL",
    "gn:name":"Antanimenakely",
    "gn:population":0,
    "gn:timezone":"Indian/Antananarivo",
    "iso:country":"MG",
    "wof:name":"Antanimenakely",
    "wof:placetype":"locality"
},
  "geometry": {"coordinates":[47.85,-17.93332999999999],"type":"Point"}
}