{
  "type": "Feature",
  "properties": {
    "gn:admin1_code":"05",
    "gn:asciiname":"Ambatolampikely",
    "gn:country_code":"MG",
    "gn:dem":1607,
    "gn:feature_class":"P",
    "gn:feature_code":"PPL",
    "gn:name":"Ambatolampikely",
    "gn:population":0,
    "gn:timezone":"Indian/Antananarivo",
    "iso:country":"MG",
    "wof:name":"Ambatolampikely",
    "wof:placetype":"locality"
},
  "geometry": {"coordinates":[47.61667,-19.88333],"type":"Point"}
}