{
  "type": "Feature",
  "properties": {
    "iso:country":"MG",
    "name:ceb_x_preferred":[
        "Ikongo"
    ],
    "name:deu_x_preferred":[
        "Ikongo"
    ],
    "name:eng_x_preferred":[
        "Ikongo"
    ],
    "name:fra_x_preferred":[
        "Ikongo"
    ],
    "name:ita_x_preferred":[
        "Ikongo"
    ],
    "name:mlg_x_preferred":[
        "Ikongo"
    ],
    "name:nld_x_preferred":[
        "Ikongo"
    ],
    "name:pol_x_preferred":[
        "Ikongo"
    ],
    "name:por_x_preferred":[
        "Ikongo"
    ],
    "name:swe_x_preferred":[
        "Ikongo"
    ],
    "name:unk_x_variant":[
        "Fort Carhot"
    ],
    "name:zho_x_preferred":[
        "\u4f0a\u5b54\u53e4"
    ],
    "qs:gn_country":"MG",
    "qs:gn_fcode":"PPL",
    "qs:gn_pop":32374,
    "qs:name":"Ikongo",
    "qs:name_adm0":"Madagascar",
    "qs:name_adm1":"Fianarantsoa",
    "qs:photos":0,
    "qs:photos_1k":0,
    "qs:photos_9k":1,
    "qs:photos_9r":1,
    "qs:photos_all":1,
    "qs:photos_sr":0,
    "qs:placetype":"Town",
    "qs:pop_sr":"7",
    "qs:woe_adm0":23424883,
    "wof:name":"Ikongo",
    "wof:placetype":"locality",
    "wof:population":32374
},
  "geometry": {"coordinates":[47.43333,-21.88333],"type":"Point"}
}