{
  "type": "Feature",
  "properties": {
    "gn:admin1_code":"06",
    "gn:asciiname":"Anaramalinika",
    "gn:country_code":"MG",
    "gn:dem":304,
    "gn:feature_class":"P",
    "gn:feature_code":"PPL",
    "gn:name":"Anaramalinika",
    "gn:population":0,
    "gn:timezone":"Indian/Antananarivo",
    "iso:country":"MG",
    "wof:name":"Anaramalinika",
    "wof:placetype":"locality"
},
  "geometry": {"coordinates":[44.65,-23.78333],"type":"Point"}
}