{
  "type": "Feature",
  "properties": {
    "gn:admin1_code":"06",
    "gn:asciiname":"Ampilofily",
    "gn:country_code":"MG",
    "gn:dem":300,
    "gn:feature_class":"P",
    "gn:feature_code":"PPL",
    "gn:name":"Ampilofily",
    "gn:population":0,
    "gn:timezone":"Indian/Antananarivo",
    "iso:country":"MG",
    "wof:name":"Ampilofily",
    "wof:placetype":"locality"
},
  "geometry": {"coordinates":[45.83333,-24.35],"type":"Point"}
}