{
  "type": "Feature",
  "properties": {
    "gn:admin1_code":"04",
    "gn:asciiname":"Ambarifoana",
    "gn:country_code":"MG",
    "gn:dem":274,
    "gn:feature_class":"P",
    "gn:feature_code":"PPL",
    "gn:name":"Ambarifoana",
    "gn:population":0,
    "gn:timezone":"Indian/Antananarivo",
    "iso:country":"MG",
    "wof:name":"Ambarifoana",
    "wof:placetype":"locality"
},
  "geometry": {"coordinates":[49.03333,-18.23333],"type":"Point"}
}