{
  "type": "Feature",
  "properties": {
    "gn:admin1_code":"06",
    "gn:asciiname":"Mandavato",
    "gn:country_code":"MG",
    "gn:dem":467,
    "gn:feature_class":"P",
    "gn:feature_code":"PPL",
    "gn:name":"Mandavato",
    "gn:population":0,
    "gn:timezone":"Indian/Antananarivo",
    "iso:country":"MG",
    "wof:name":"Mandavato",
    "wof:placetype":"locality"
},
  "geometry": {"coordinates":[44.51667,-22.88333],"type":"Point"}
}