{
  "type": "Feature",
  "properties": {
    "gn:admin1_code":"06",
    "gn:asciiname":"Anjanasampana",
    "gn:country_code":"MG",
    "gn:dem":120,
    "gn:feature_class":"P",
    "gn:feature_code":"PPL",
    "gn:name":"Anjanasampana",
    "gn:population":0,
    "gn:timezone":"Indian/Antananarivo",
    "iso:country":"MG",
    "wof:name":"Anjanasampana",
    "wof:placetype":"locality"
},
  "geometry": {"coordinates":[45.31667,-25.21667],"type":"Point"}
}