{
  "type": "Feature",
  "properties": {
    "gn:admin1_code":"04",
    "gn:asciiname":"Ambatovola",
    "gn:country_code":"MG",
    "gn:dem":590,
    "gn:feature_class":"P",
    "gn:feature_code":"PPL",
    "gn:name":"Ambatovola",
    "gn:population":0,
    "gn:timezone":"Indian/Antananarivo",
    "iso:country":"MG",
    "name:azb_x_preferred":[
        "\u0627\u0645\u0628\u0627\u062a\u0648\u0644\u0627"
    ],
    "name:fas_x_preferred":[
        "\u0627\u0645\u0628\u0627\u062a\u0648\u0644\u0627"
    ],
    "name:fra_x_preferred":[
        "Ambatovola"
    ],
    "name:ita_x_preferred":[
        "Ambatovola Gara"
    ],
    "name:mlg_x_preferred":[
        "Ambatovola"
    ],
    "name:nld_x_preferred":[
        "Ambatovola"
    ],
    "wof:name":"Ambatovola",
    "wof:placetype":"locality"
},
  "geometry": {"coordinates":[48.56667,-18.88333],"type":"Point"}
}