{
  "type": "Feature",
  "properties": {
    "gn:admin1_code":"02",
    "gn:asciiname":"Anosibevary",
    "gn:cc2":"MG",
    "gn:country_code":"MG",
    "gn:dem":1454,
    "gn:feature_class":"P",
    "gn:feature_code":"PPL",
    "gn:name":"Anosibevary",
    "gn:population":0,
    "gn:timezone":"Indian/Antananarivo",
    "iso:country":"MG",
    "name:und_x_variant":[
        "Anosimbevary",
        "Anosibevary"
    ],
    "wof:name":"Anosibevary",
    "wof:placetype":"locality"
},
  "geometry": {"coordinates":[46.71667,-20.85],"type":"Point"}
}