{
  "type": "Feature",
  "properties": {
    "gn:admin1_code":"01",
    "gn:asciiname":"Amberimay",
    "gn:country_code":"MG",
    "gn:dem":12,
    "gn:feature_class":"P",
    "gn:feature_code":"PPL",
    "gn:name":"Amberimay",
    "gn:population":0,
    "gn:timezone":"Indian/Antananarivo",
    "iso:country":"MG",
    "wof:name":"Amberimay",
    "wof:placetype":"locality"
},
  "geometry": {"coordinates":[47.88333,-13.71667],"type":"Point"}
}