{
  "type": "Feature",
  "properties": {
    "gn:admin1_code":"02",
    "gn:asciiname":"Analamiditra",
    "gn:country_code":"MG",
    "gn:dem":6,
    "gn:feature_class":"P",
    "gn:feature_code":"PPL",
    "gn:name":"Analamiditra",
    "gn:population":0,
    "gn:timezone":"Indian/Antananarivo",
    "iso:country":"MG",
    "wof:name":"Analamiditra",
    "wof:placetype":"locality"
},
  "geometry": {"coordinates":[47.93333,-22.15],"type":"Point"}
}