{
  "type": "Feature",
  "properties": {
    "gn:admin1_code":"02",
    "gn:asciiname":"Berevo",
    "gn:country_code":"MG",
    "gn:dem":596,
    "gn:feature_class":"P",
    "gn:feature_code":"PPL",
    "gn:name":"Berevo",
    "gn:population":0,
    "gn:timezone":"Indian/Antananarivo",
    "iso:country":"MG",
    "wof:name":"Berevo",
    "wof:placetype":"locality"
},
  "geometry": {"coordinates":[45.53333,-21.51667],"type":"Point"}
}