{
  "type": "Feature",
  "properties": {
    "gn:admin1_code":"05",
    "gn:asciiname":"Miarinavaratra",
    "gn:country_code":"MG",
    "gn:dem":1148,
    "gn:feature_class":"P",
    "gn:feature_code":"PPL",
    "gn:name":"Miarinavaratra",
    "gn:population":0,
    "gn:timezone":"Indian/Antananarivo",
    "iso:country":"MG",
    "name:fra_x_preferred":[
        "Miarinavaratra"
    ],
    "name:ita_x_preferred":[
        "Miarinavaratra"
    ],
    "name:mlg_x_preferred":[
        "Miarinavaratra"
    ],
    "name:nld_x_preferred":[
        "Miarinavaratra"
    ],
    "wof:name":"Miarinavaratra",
    "wof:placetype":"locality"
},
  "geometry": {"coordinates":[46.56667,-19.83333],"type":"Point"}
}