{
  "type": "Feature",
  "properties": {
    "gn:admin1_code":"03",
    "gn:asciiname":"Bemafaika Ambony",
    "gn:country_code":"MG",
    "gn:dem":80,
    "gn:feature_class":"P",
    "gn:feature_code":"PPL",
    "gn:name":"Bemafaika Ambony",
    "gn:population":0,
    "gn:timezone":"Indian/Antananarivo",
    "iso:country":"MG",
    "wof:name":"Bemafaika Ambony",
    "wof:placetype":"locality"
},
  "geometry": {"coordinates":[47.56667,-15.16667],"type":"Point"}
}