{
  "type": "Feature",
  "properties": {
    "gn:admin1_code":"06",
    "gn:asciiname":"Bereraka Ambany",
    "gn:country_code":"MG",
    "gn:dem":222,
    "gn:feature_class":"P",
    "gn:feature_code":"PPL",
    "gn:name":"Bereraka Ambany",
    "gn:population":0,
    "gn:timezone":"Indian/Antananarivo",
    "iso:country":"MG",
    "wof:name":"Bereraka Ambany",
    "wof:placetype":"locality"
},
  "geometry": {"coordinates":[45.55,-25.01667],"type":"Point"}
}