{
  "type": "Feature",
  "properties": {
    "gn:admin1_code":"05",
    "gn:asciiname":"Namehana",
    "gn:country_code":"MG",
    "gn:dem":1247,
    "gn:feature_class":"P",
    "gn:feature_code":"PPL",
    "gn:name":"Namehana",
    "gn:population":0,
    "gn:timezone":"Indian/Antananarivo",
    "iso:country":"MG",
    "wof:name":"Namehana",
    "wof:placetype":"locality"
},
  "geometry": {"coordinates":[47.53333,-18.81667],"type":"Point"}
}