{
  "type": "Feature",
  "properties": {
    "gn:admin1_code":"06",
    "gn:asciiname":"Ampapamena",
    "gn:cc2":"MG",
    "gn:country_code":"MG",
    "gn:dem":712,
    "gn:feature_class":"P",
    "gn:feature_code":"PPL",
    "gn:name":"Ampapamena",
    "gn:population":0,
    "gn:timezone":"Indian/Antananarivo",
    "iso:country":"MG",
    "name:und_x_variant":[
        "Papamena",
        "Amparamena",
        "Ampapamena"
    ],
    "wof:name":"Ampapamena",
    "wof:placetype":"locality"
},
  "geometry": {"coordinates":[45.66667,-23.06667],"type":"Point"}
}