{
  "type": "Feature",
  "properties": {
    "gn:admin1_code":"03",
    "gn:asciiname":"Fenoarivo-Bara",
    "gn:cc2":"MG",
    "gn:country_code":"MG",
    "gn:dem":43,
    "gn:feature_class":"P",
    "gn:feature_code":"PPL",
    "gn:name":"Fenoarivo-Bara",
    "gn:population":0,
    "gn:timezone":"Indian/Antananarivo",
    "iso:country":"MG",
    "name:und_x_variant":[
        "Fenoarivo",
        "Fenoarivo-Bara"
    ],
    "wof:name":"Fenoarivo-Bara",
    "wof:placetype":"locality"
},
  "geometry": {"coordinates":[44.63333,-19.06667],"type":"Point"}
}