{
  "type": "Feature",
  "properties": {
    "gn:admin1_code":"06",
    "gn:asciiname":"Manombo",
    "gn:country_code":"MG",
    "gn:dem":114,
    "gn:feature_class":"P",
    "gn:feature_code":"PPL",
    "gn:name":"Manombo",
    "gn:population":0,
    "gn:timezone":"Indian/Antananarivo",
    "iso:country":"MG",
    "wof:name":"Manombo",
    "wof:placetype":"locality"
},
  "geometry": {"coordinates":[44.75,-25.08333],"type":"Point"}
}