{
  "type": "Feature",
  "properties": {
    "gn:admin1_code":"03",
    "gn:asciiname":"Analanantsoa",
    "gn:cc2":"MG",
    "gn:country_code":"MG",
    "gn:dem":159,
    "gn:feature_class":"P",
    "gn:feature_code":"PPL",
    "gn:name":"Analanantsoa",
    "gn:population":0,
    "gn:timezone":"Indian/Antananarivo",
    "iso:country":"MG",
    "name:und_x_variant":[
        "Analahantsoa",
        "Analanantsoa"
    ],
    "wof:name":"Analanantsoa",
    "wof:placetype":"locality"
},
  "geometry": {"coordinates":[48.26667,-14.05],"type":"Point"}
}