{
  "type": "Feature",
  "properties": {
    "gn:admin1_code":"06",
    "gn:asciiname":"Antanimena",
    "gn:country_code":"MG",
    "gn:dem":481,
    "gn:feature_class":"P",
    "gn:feature_code":"PPL",
    "gn:name":"Antanimena",
    "gn:population":0,
    "gn:timezone":"Indian/Antananarivo",
    "iso:country":"MG",
    "name:fra_x_preferred":[
        "Antanimena"
    ],
    "name:ita_x_preferred":[
        "Antanimena"
    ],
    "name:mlg_x_preferred":[
        "Antanimena"
    ],
    "name:nld_x_preferred":[
        "Antanimena"
    ],
    "wof:name":"Antanimena",
    "wof:placetype":"locality"
},
  "geometry": {"coordinates":[45.35,-23.36667000000001],"type":"Point"}
}