{
  "type": "Feature",
  "properties": {
    "gn:admin1_code":"01",
    "gn:asciiname":"Antsambalahy",
    "gn:cc2":"MG",
    "gn:country_code":"MG",
    "gn:dem":49,
    "gn:feature_class":"P",
    "gn:feature_code":"PPL",
    "gn:name":"Antsambalahy",
    "gn:population":0,
    "gn:timezone":"Indian/Antananarivo",
    "iso:country":"MG",
    "name:fra_x_preferred":[
        "Antsambalahy"
    ],
    "name:ita_x_preferred":[
        "Antsambalahy"
    ],
    "name:mlg_x_preferred":[
        "Antsambalahy"
    ],
    "name:nld_x_preferred":[
        "Antsambalahy"
    ],
    "name:und_x_variant":[
        "Antsambalahi"
    ],
    "wof:name":"Antsambalahy",
    "wof:placetype":"locality"
},
  "geometry": {"coordinates":[49.96667,-14.76667],"type":"Point"}
}