{
  "type": "Feature",
  "properties": {
    "gn:admin1_code":"06",
    "gn:asciiname":"Manalobe",
    "gn:cc2":"MG",
    "gn:country_code":"MG",
    "gn:dem":223,
    "gn:feature_class":"P",
    "gn:feature_code":"PPL",
    "gn:name":"Manalobe",
    "gn:population":0,
    "gn:timezone":"Indian/Antananarivo",
    "iso:country":"MG",
    "name:fra_x_preferred":[
        "Manalobe"
    ],
    "name:ita_x_preferred":[
        "Manalobe"
    ],
    "name:mlg_x_preferred":[
        "Manalobe"
    ],
    "name:nld_x_preferred":[
        "Manalobe"
    ],
    "name:und_x_variant":[
        "Manalo"
    ],
    "wof:name":"Manalobe",
    "wof:placetype":"locality"
},
  "geometry": {"coordinates":[44.55,-23.43333],"type":"Point"}
}