{
  "type": "Feature",
  "properties": {
    "gn:admin1_code":"03",
    "gn:asciiname":"Antsatrana",
    "gn:cc2":"MG",
    "gn:country_code":"MG",
    "gn:dem":1068,
    "gn:feature_class":"P",
    "gn:feature_code":"PPL",
    "gn:name":"Antsatrana",
    "gn:population":0,
    "gn:timezone":"Indian/Antananarivo",
    "iso:country":"MG",
    "name:und_x_variant":[
        "Antsantrana",
        "Antsatrana"
    ],
    "wof:name":"Antsatrana",
    "wof:placetype":"locality"
},
  "geometry": {"coordinates":[48.93333,-14.65],"type":"Point"}
}