{
  "type": "Feature",
  "properties": {
    "gn:admin1_code":"01",
    "gn:asciiname":"Befiana",
    "gn:country_code":"MG",
    "gn:dem":279,
    "gn:feature_class":"P",
    "gn:feature_code":"PPL",
    "gn:name":"Befiana",
    "gn:population":0,
    "gn:timezone":"Indian/Antananarivo",
    "iso:country":"MG",
    "wof:name":"Befiana",
    "wof:placetype":"locality"
},
  "geometry": {"coordinates":[49.81667,-13.95],"type":"Point"}
}