{
  "type": "Feature",
  "properties": {
    "gn:admin1_code":"06",
    "gn:asciiname":"Ankatrakatraka",
    "gn:country_code":"MG",
    "gn:dem":404,
    "gn:feature_class":"P",
    "gn:feature_code":"PPL",
    "gn:name":"Ankatrakatraka",
    "gn:population":0,
    "gn:timezone":"Indian/Antananarivo",
    "iso:country":"MG",
    "wof:name":"Ankatrakatraka",
    "wof:placetype":"locality"
},
  "geometry": {"coordinates":[44.58333,-23.98333],"type":"Point"}
}