{
  "type": "Feature",
  "properties": {
    "gn:admin1_code":"06",
    "gn:asciiname":"Behagy",
    "gn:country_code":"MG",
    "gn:dem":239,
    "gn:feature_class":"P",
    "gn:feature_code":"PPL",
    "gn:name":"Behagy",
    "gn:population":0,
    "gn:timezone":"Indian/Antananarivo",
    "iso:country":"MG",
    "wof:name":"Behagy",
    "wof:placetype":"locality"
},
  "geometry": {"coordinates":[46.41667,-24.16667],"type":"Point"}
}