{
  "type": "Feature",
  "properties": {
    "gn:admin1_code":"02",
    "gn:asciiname":"Analabe",
    "gn:country_code":"MG",
    "gn:dem":12,
    "gn:feature_class":"P",
    "gn:feature_code":"PPL",
    "gn:name":"Analabe",
    "gn:population":0,
    "gn:timezone":"Indian/Antananarivo",
    "iso:country":"MG",
    "wof:name":"Analabe",
    "wof:placetype":"locality"
},
  "geometry": {"coordinates":[47.98333,-22.18333],"type":"Point"}
}