{
  "type": "Feature",
  "properties": {
    "gn:admin1_code":"01",
    "gn:asciiname":"Anosiravo",
    "gn:country_code":"MG",
    "gn:dem":49,
    "gn:feature_class":"P",
    "gn:feature_code":"PPL",
    "gn:name":"Anosiravo",
    "gn:population":0,
    "gn:timezone":"Indian/Antananarivo",
    "iso:country":"MG",
    "wof:name":"Anosiravo",
    "wof:placetype":"locality"
},
  "geometry": {"coordinates":[49.35,-12.31667],"type":"Point"}
}