{
  "type": "Feature",
  "properties": {
    "gn:admin1_code":"03",
    "gn:asciiname":"Ambararatabe",
    "gn:country_code":"MG",
    "gn:dem":14,
    "gn:feature_class":"P",
    "gn:feature_code":"PPL",
    "gn:name":"Ambararatabe",
    "gn:population":0,
    "gn:timezone":"Indian/Antananarivo",
    "iso:country":"MG",
    "name:azb_x_preferred":[
        "\u0627\u0645\u0628\u0627\u0631\u0627\u0631\u0627\u062a\u0627\u0628"
    ],
    "name:fas_x_preferred":[
        "\u0627\u0645\u0628\u0627\u0631\u0627\u0631\u0627\u062a\u0627\u0628"
    ],
    "name:fra_x_preferred":[
        "Ambararatabe"
    ],
    "name:ita_x_preferred":[
        "Ambararatabe"
    ],
    "name:mlg_x_preferred":[
        "Ambararatabe"
    ],
    "name:nld_x_preferred":[
        "Ambararatabe"
    ],
    "wof:name":"Ambararatabe",
    "wof:placetype":"locality"
},
  "geometry": {"coordinates":[45.96667,-16.18333],"type":"Point"}
}