{
  "type": "Feature",
  "properties": {
    "gn:admin1_code":"02",
    "gn:asciiname":"Androrangabe",
    "gn:country_code":"MG",
    "gn:dem":60,
    "gn:feature_class":"P",
    "gn:feature_code":"PPL",
    "gn:name":"Androrangabe",
    "gn:population":0,
    "gn:timezone":"Indian/Antananarivo",
    "iso:country":"MG",
    "wof:name":"Androrangabe",
    "wof:placetype":"locality"
},
  "geometry": {"coordinates":[47.81667,-21.18333],"type":"Point"}
}