{
  "type": "Feature",
  "properties": {
    "gn:admin1_code":"06",
    "gn:asciiname":"Bejangoakely",
    "gn:country_code":"MG",
    "gn:dem":119,
    "gn:feature_class":"P",
    "gn:feature_code":"PPL",
    "gn:name":"Bejangoakely",
    "gn:population":0,
    "gn:timezone":"Indian/Antananarivo",
    "iso:country":"MG",
    "wof:name":"Bejangoakely",
    "wof:placetype":"locality"
},
  "geometry": {"coordinates":[44.13333,-21.95],"type":"Point"}
}