{
  "type": "Feature",
  "properties": {
    "gn:admin1_code":"03",
    "gn:asciiname":"Andranofasika",
    "gn:country_code":"MG",
    "gn:dem":679,
    "gn:feature_class":"P",
    "gn:feature_code":"PPL",
    "gn:name":"Andranofasika",
    "gn:population":0,
    "gn:timezone":"Indian/Antananarivo",
    "iso:country":"MG",
    "name:fra_x_preferred":[
        "Andranofasika"
    ],
    "name:ita_x_preferred":[
        "Andranofasika"
    ],
    "name:mlg_x_preferred":[
        "Andranofasika"
    ],
    "name:nld_x_preferred":[
        "Andranofasika"
    ],
    "wof:name":"Andranofasika",
    "wof:placetype":"locality"
},
  "geometry": {"coordinates":[47.43333,-17.48333],"type":"Point"}
}