{
  "type": "Feature",
  "properties": {
    "gn:admin1_code":"06",
    "gn:asciiname":"Bemonto",
    "gn:country_code":"MG",
    "gn:dem":61,
    "gn:feature_class":"P",
    "gn:feature_code":"PPL",
    "gn:name":"Bemonto",
    "gn:population":0,
    "gn:timezone":"Indian/Antananarivo",
    "iso:country":"MG",
    "wof:name":"Bemonto",
    "wof:placetype":"locality"
},
  "geometry": {"coordinates":[45.45,-19.56667],"type":"Point"}
}