{
  "type": "Feature",
  "properties": {
    "gn:admin1_code":"03",
    "gn:asciiname":"Rafialava",
    "gn:country_code":"MG",
    "gn:dem":-9999,
    "gn:feature_class":"P",
    "gn:feature_code":"PPL",
    "gn:name":"Rafialava",
    "gn:population":0,
    "gn:timezone":"Indian/Antananarivo",
    "iso:country":"MG",
    "wof:name":"Rafialava",
    "wof:placetype":"locality"
},
  "geometry": {"coordinates":[47.88333,-14.25],"type":"Point"}
}