{
  "type": "Feature",
  "properties": {
    "gn:admin1_code":"02",
    "gn:asciiname":"Mikaikarivo",
    "gn:cc2":"MG",
    "gn:country_code":"MG",
    "gn:dem":1186,
    "gn:feature_class":"P",
    "gn:feature_code":"PPL",
    "gn:name":"Mikaikarivo",
    "gn:population":0,
    "gn:timezone":"Indian/Antananarivo",
    "iso:country":"MG",
    "name:und_x_variant":[
        "Lazarivo",
        "Mikaikarivo"
    ],
    "wof:name":"Mikaikarivo",
    "wof:placetype":"locality"
},
  "geometry": {"coordinates":[46.75,-24.05],"type":"Point"}
}