{
  "type": "Feature",
  "properties": {
    "gn:admin1_code":"2.0",
    "gn:asciiname":"Vohitromby",
    "gn:country_code":"MG",
    "gn:dem":786,
    "gn:feature_class":"P",
    "gn:feature_code":"PPL",
    "gn:name":"Vohitromby",
    "gn:population":0,
    "gn:timezone":"Indian/Antananarivo",
    "iso:country":"MG",
    "wof:name":"Vohitromby",
    "wof:placetype":"locality"
},
  "geometry": {"coordinates":[46.36667,-21.76667],"type":"Point"}
}