{
  "type": "Feature",
  "properties": {
    "gn:admin1_code":"02",
    "gn:asciiname":"Mangaika",
    "gn:country_code":"MG",
    "gn:dem":115,
    "gn:feature_class":"P",
    "gn:feature_code":"PPL",
    "gn:name":"Mangaika",
    "gn:population":0,
    "gn:timezone":"Indian/Antananarivo",
    "iso:country":"MG",
    "wof:name":"Mangaika",
    "wof:placetype":"locality"
},
  "geometry": {"coordinates":[47.28333,-23.51667],"type":"Point"}
}