{
  "type": "Feature",
  "properties": {
    "gn:admin1_code":"06",
    "gn:asciiname":"Betola",
    "gn:country_code":"MG",
    "gn:dem":458,
    "gn:feature_class":"P",
    "gn:feature_code":"PPL",
    "gn:name":"Betola",
    "gn:population":0,
    "gn:timezone":"Indian/Antananarivo",
    "iso:country":"MG",
    "wof:name":"Betola",
    "wof:placetype":"locality"
},
  "geometry": {"coordinates":[44.26667,-23.13333],"type":"Point"}
}