{
  "type": "Feature",
  "properties": {
    "gn:admin1_code":"05",
    "gn:asciiname":"Ambohibehasina",
    "gn:country_code":"MG",
    "gn:dem":1401,
    "gn:feature_class":"P",
    "gn:feature_code":"PPLL",
    "gn:name":"Ambohibehasina",
    "gn:population":0,
    "gn:timezone":"Indian/Antananarivo",
    "iso:country":"MG",
    "wof:name":"Ambohibehasina",
    "wof:placetype":"locality"
},
  "geometry": {"coordinates":[47.69487,-18.87053],"type":"Point"}
}