{
  "type": "Feature",
  "properties": {
    "gn:admin1_code":"06",
    "gn:asciiname":"Antsoa",
    "gn:country_code":"MG",
    "gn:dem":242,
    "gn:feature_class":"P",
    "gn:feature_code":"PPL",
    "gn:name":"Antsoa",
    "gn:population":0,
    "gn:timezone":"Indian/Antananarivo",
    "iso:country":"MG",
    "wof:name":"Antsoa",
    "wof:placetype":"locality"
},
  "geometry": {"coordinates":[45.13333,-21.61667000000001],"type":"Point"}
}