{
  "type": "Feature",
  "properties": {
    "gn:admin1_code":"2.0",
    "gn:asciiname":"Sahatsiafa",
    "gn:country_code":"MG",
    "gn:dem":996,
    "gn:feature_class":"P",
    "gn:feature_code":"PPL",
    "gn:name":"Sahatsiafa",
    "gn:population":0,
    "gn:timezone":"Indian/Antananarivo",
    "iso:country":"MG",
    "wof:name":"Sahatsiafa",
    "wof:placetype":"locality"
},
  "geometry": {"coordinates":[47.01667,-21.96667],"type":"Point"}
}