{
  "type": "Feature",
  "properties": {
    "gn:admin1_code":"01",
    "gn:asciiname":"Melobody",
    "gn:country_code":"MG",
    "gn:dem":397,
    "gn:feature_class":"P",
    "gn:feature_code":"PPL",
    "gn:name":"Melobody",
    "gn:population":0,
    "gn:timezone":"Indian/Antananarivo",
    "iso:country":"MG",
    "wof:name":"Melobody",
    "wof:placetype":"locality"
},
  "geometry": {"coordinates":[49.53333,-14.06667],"type":"Point"}
}