{
  "type": "Feature",
  "properties": {
    "gn:admin1_code":"06",
    "gn:asciiname":"Masoarivo",
    "gn:country_code":"MG",
    "gn:dem":30,
    "gn:feature_class":"P",
    "gn:feature_code":"PPL",
    "gn:name":"Masoarivo",
    "gn:population":0,
    "gn:timezone":"Indian/Antananarivo",
    "iso:country":"MG",
    "wof:name":"Masoarivo",
    "wof:placetype":"locality"
},
  "geometry": {"coordinates":[44.73333,-19.65],"type":"Point"}
}