{
  "type": "Feature",
  "properties": {
    "gn:admin1_code":"01",
    "gn:asciiname":"Antanambao",
    "gn:country_code":"MG",
    "gn:dem":225,
    "gn:feature_class":"P",
    "gn:feature_code":"PPL",
    "gn:name":"Antanambao",
    "gn:population":0,
    "gn:timezone":"Indian/Antananarivo",
    "iso:country":"MG",
    "wof:name":"Antanambao",
    "wof:placetype":"locality"
},
  "geometry": {"coordinates":[49.46667,-13.18333],"type":"Point"}
}