{
  "type": "Feature",
  "properties": {
    "gn:admin1_code":"05",
    "gn:asciiname":"Anadako",
    "gn:country_code":"MG",
    "gn:dem":798,
    "gn:feature_class":"P",
    "gn:feature_code":"PPL",
    "gn:name":"Anadako",
    "gn:population":0,
    "gn:timezone":"Indian/Antananarivo",
    "iso:country":"MG",
    "wof:name":"Anadako",
    "wof:placetype":"locality"
},
  "geometry": {"coordinates":[46.01667,-18.76667],"type":"Point"}
}