{
  "type": "Feature",
  "properties": {
    "gn:admin1_code":"01",
    "gn:asciiname":"Antsahampano",
    "gn:cc2":"MG",
    "gn:country_code":"MG",
    "gn:dem":39,
    "gn:feature_class":"P",
    "gn:feature_code":"PPL",
    "gn:name":"Antsahampano",
    "gn:population":0,
    "gn:timezone":"Indian/Antananarivo",
    "iso:country":"MG",
    "name:und_x_variant":[
        "Sahampano",
        "Antsahampano"
    ],
    "wof:name":"Antsahampano",
    "wof:placetype":"locality"
},
  "geometry": {"coordinates":[49.18333,-12.31667],"type":"Point"}
}