{
  "type": "Feature",
  "properties": {
    "gn:admin1_code":"03",
    "gn:asciiname":"Marahitra",
    "gn:country_code":"MG",
    "gn:dem":228,
    "gn:feature_class":"P",
    "gn:feature_code":"PPL",
    "gn:name":"Marahitra",
    "gn:population":0,
    "gn:timezone":"Indian/Antananarivo",
    "iso:country":"MG",
    "wof:name":"Marahitra",
    "wof:placetype":"locality"
},
  "geometry": {"coordinates":[47.01667,-16.95],"type":"Point"}
}