{
  "type": "Feature",
  "properties": {
    "gn:admin1_code":"05",
    "gn:asciiname":"Ambohimadinika",
    "gn:country_code":"MG",
    "gn:dem":1976,
    "gn:feature_class":"P",
    "gn:feature_code":"PPL",
    "gn:name":"Ambohimadinika",
    "gn:population":0,
    "gn:timezone":"Indian/Antananarivo",
    "iso:country":"MG",
    "wof:name":"Ambohimadinika",
    "wof:placetype":"locality"
},
  "geometry": {"coordinates":[47.05,-19.63333],"type":"Point"}
}