{
  "type": "Feature",
  "properties": {
    "gn:admin1_code":"04",
    "gn:asciiname":"Beparasy",
    "gn:country_code":"MG",
    "gn:dem":21,
    "gn:feature_class":"P",
    "gn:feature_code":"PPL",
    "gn:name":"Beparasy",
    "gn:population":0,
    "gn:timezone":"Indian/Antananarivo",
    "iso:country":"MG",
    "name:fra_x_preferred":[
        "Beparasy"
    ],
    "name:ita_x_preferred":[
        "Beparasy"
    ],
    "name:mlg_x_preferred":[
        "Beparasy"
    ],
    "name:nld_x_preferred":[
        "Beparasy"
    ],
    "wof:name":"Beparasy",
    "wof:placetype":"locality"
},
  "geometry": {"coordinates":[48.81667,-19.66667],"type":"Point"}
}