{
  "type": "Feature",
  "properties": {
    "gn:admin1_code":"02",
    "gn:asciiname":"Amboavato",
    "gn:country_code":"MG",
    "gn:dem":1284,
    "gn:feature_class":"P",
    "gn:feature_code":"PPL",
    "gn:name":"Amboavato",
    "gn:population":0,
    "gn:timezone":"Indian/Antananarivo",
    "iso:country":"MG",
    "wof:name":"Amboavato",
    "wof:placetype":"locality"
},
  "geometry": {"coordinates":[47.01667,-21.48333],"type":"Point"}
}