{
  "type": "Feature",
  "properties": {
    "gn:admin1_code":"02",
    "gn:asciiname":"Ampasindava",
    "gn:country_code":"MG",
    "gn:dem":62,
    "gn:feature_class":"P",
    "gn:feature_code":"PPL",
    "gn:name":"Ampasindava",
    "gn:population":0,
    "gn:timezone":"Indian/Antananarivo",
    "iso:country":"MG",
    "wof:name":"Ampasindava",
    "wof:placetype":"locality"
},
  "geometry": {"coordinates":[47.35,-23.38333],"type":"Point"}
}