{
  "type": "Feature",
  "properties": {
    "gn:admin1_code":"03",
    "gn:asciiname":"Antanandava",
    "gn:cc2":"MG",
    "gn:country_code":"MG",
    "gn:dem":75,
    "gn:feature_class":"P",
    "gn:feature_code":"PPL",
    "gn:name":"Antanandava",
    "gn:population":0,
    "gn:timezone":"Indian/Antananarivo",
    "iso:country":"MG",
    "name:und_x_variant":[
        "Tanandava",
        "Antanandava"
    ],
    "wof:name":"Antanandava",
    "wof:placetype":"locality"
},
  "geometry": {"coordinates":[45.46667,-16.11667000000001],"type":"Point"}
}