{
  "type": "Feature",
  "properties": {
    "gn:admin1_code":"06",
    "gn:asciiname":"Bevalaha",
    "gn:cc2":"MG",
    "gn:country_code":"MG",
    "gn:dem":130,
    "gn:feature_class":"P",
    "gn:feature_code":"PPL",
    "gn:name":"Bevalaha",
    "gn:population":0,
    "gn:timezone":"Indian/Antananarivo",
    "iso:country":"MG",
    "name:und_x_variant":[
        "Bevalae",
        "Bevalaha"
    ],
    "wof:name":"Bevalaha",
    "wof:placetype":"locality"
},
  "geometry": {"coordinates":[45.41667,-25.11667000000001],"type":"Point"}
}