{
  "type": "Feature",
  "properties": {
    "gn:admin1_code":"2.0",
    "gn:asciiname":"Soalazaina",
    "gn:cc2":"MG",
    "gn:country_code":"MG",
    "gn:dem":726,
    "gn:feature_class":"P",
    "gn:feature_code":"PPL",
    "gn:name":"Soalazaina",
    "gn:population":0,
    "gn:timezone":"Indian/Antananarivo",
    "iso:country":"MG",
    "name:fra_x_preferred":[
        "Soalazaina"
    ],
    "name:ita_x_preferred":[
        "Soalazaina"
    ],
    "name:mlg_x_preferred":[
        "Soalazaina"
    ],
    "name:nld_x_preferred":[
        "Soalazaina"
    ],
    "name:und_x_variant":[
        "Isoalazaina"
    ],
    "wof:name":"Soalazaina",
    "wof:placetype":"locality"
},
  "geometry": {"coordinates":[46.71667,-22.31667],"type":"Point"}
}