{
  "type": "Feature",
  "properties": {
    "gn:admin1_code":"06",
    "gn:asciiname":"Ankilivalo",
    "gn:country_code":"MG",
    "gn:dem":430,
    "gn:feature_class":"P",
    "gn:feature_code":"PPL",
    "gn:name":"Ankilivalo",
    "gn:population":0,
    "gn:timezone":"Indian/Antananarivo",
    "iso:country":"MG",
    "name:fra_x_preferred":[
        "Ankilivalo"
    ],
    "name:ita_x_preferred":[
        "Ankilivalo"
    ],
    "name:mlg_x_preferred":[
        "Ankilivalo"
    ],
    "name:nld_x_preferred":[
        "Ankilivalo"
    ],
    "wof:name":"Ankilivalo",
    "wof:placetype":"locality"
},
  "geometry": {"coordinates":[45.05,-24.13333],"type":"Point"}
}