{
  "type": "Feature",
  "properties": {
    "gn:admin1_code":"6.0",
    "gn:asciiname":"Tsingora Nord",
    "gn:country_code":"MG",
    "gn:dem":422,
    "gn:feature_class":"P",
    "gn:feature_code":"PPL",
    "gn:name":"Tsingora Nord",
    "gn:population":0,
    "gn:timezone":"Indian/Antananarivo",
    "iso:country":"MG",
    "wof:name":"Tsingora Nord",
    "wof:placetype":"locality"
},
  "geometry": {"coordinates":[44.46667,-23.06667],"type":"Point"}
}