{
  "type": "Feature",
  "properties": {
    "gn:admin1_code":"06",
    "gn:asciiname":"Masianaka",
    "gn:country_code":"MG",
    "gn:dem":83,
    "gn:feature_class":"P",
    "gn:feature_code":"PPL",
    "gn:name":"Masianaka",
    "gn:population":0,
    "gn:timezone":"Indian/Antananarivo",
    "iso:country":"MG",
    "name:fra_x_preferred":[
        "Masianaka"
    ],
    "name:ita_x_preferred":[
        "Masianaka"
    ],
    "name:mlg_x_preferred":[
        "Masianaka"
    ],
    "name:nld_x_preferred":[
        "Masianaka"
    ],
    "wof:name":"Masianaka",
    "wof:placetype":"locality"
},
  "geometry": {"coordinates":[47.03333,-24.78333],"type":"Point"}
}