{
  "type": "Feature",
  "properties": {
    "gn:admin1_code":"03",
    "gn:asciiname":"Mahabibo",
    "gn:country_code":"MG",
    "gn:dem":426,
    "gn:feature_class":"P",
    "gn:feature_code":"PPL",
    "gn:name":"Mahabibo",
    "gn:population":0,
    "gn:timezone":"Indian/Antananarivo",
    "iso:country":"MG",
    "wof:name":"Mahabibo",
    "wof:placetype":"locality"
},
  "geometry": {"coordinates":[44.66667,-18.16667],"type":"Point"}
}