{
  "type": "Feature",
  "properties": {
    "gn:asciiname":"Andaboly",
    "gn:country_code":"MG",
    "gn:dem":12,
    "gn:feature_class":"P",
    "gn:feature_code":"PPL",
    "gn:name":"Andaboly",
    "gn:population":0,
    "gn:timezone":"Indian/Antananarivo",
    "iso:country":"MG",
    "wof:name":"Andaboly",
    "wof:placetype":"locality"
},
  "geometry": {"coordinates":[43.67561,-23.34039],"type":"Point"}
}