{
  "type": "Feature",
  "properties": {
    "gn:admin1_code":"06",
    "gn:asciiname":"Marohira Avaratra",
    "gn:cc2":"MG",
    "gn:country_code":"MG",
    "gn:dem":54,
    "gn:feature_class":"P",
    "gn:feature_code":"PPL",
    "gn:name":"Marohira Avaratra",
    "gn:population":0,
    "gn:timezone":"Indian/Antananarivo",
    "iso:country":"MG",
    "name:und_x_variant":[
        "Marohira Nord",
        "Marohira",
        "Marohira Avaratra"
    ],
    "wof:name":"Marohira Avaratra",
    "wof:placetype":"locality"
},
  "geometry": {"coordinates":[45.56667,-25.36667000000001],"type":"Point"}
}