{
  "type": "Feature",
  "properties": {
    "gn:admin1_code":"02",
    "gn:asciiname":"Ambohipopona",
    "gn:country_code":"MG",
    "gn:dem":1460,
    "gn:feature_class":"P",
    "gn:feature_code":"PPL",
    "gn:name":"Ambohipopona",
    "gn:population":0,
    "gn:timezone":"Indian/Antananarivo",
    "iso:country":"MG",
    "wof:name":"Ambohipopona",
    "wof:placetype":"locality"
},
  "geometry": {"coordinates":[47.11667,-21.03333],"type":"Point"}
}