{
  "type": "Feature",
  "properties": {
    "gn:admin1_code":"06",
    "gn:asciiname":"Marotrano",
    "gn:country_code":"MG",
    "gn:dem":418,
    "gn:feature_class":"P",
    "gn:feature_code":"PPL",
    "gn:name":"Marotrano",
    "gn:population":0,
    "gn:timezone":"Indian/Antananarivo",
    "iso:country":"MG",
    "wof:name":"Marotrano",
    "wof:placetype":"locality"
},
  "geometry": {"coordinates":[45.48333,-24.53333],"type":"Point"}
}