{
  "type": "Feature",
  "properties": {
    "gn:admin1_code":"05",
    "gn:asciiname":"Amparihimbozaha",
    "gn:country_code":"MG",
    "gn:dem":841,
    "gn:feature_class":"P",
    "gn:feature_code":"PPL",
    "gn:name":"Amparihimbozaha",
    "gn:population":0,
    "gn:timezone":"Indian/Antananarivo",
    "iso:country":"MG",
    "wof:name":"Amparihimbozaha",
    "wof:placetype":"locality"
},
  "geometry": {"coordinates":[45.98333,-18.66667],"type":"Point"}
}