{
  "type": "Feature",
  "properties": {
    "gn:admin1_code":"04",
    "gn:asciiname":"Ampananana",
    "gn:country_code":"MG",
    "gn:dem":765,
    "gn:feature_class":"P",
    "gn:feature_code":"PPL",
    "gn:name":"Ampananana",
    "gn:population":0,
    "gn:timezone":"Indian/Antananarivo",
    "iso:country":"MG",
    "wof:name":"Ampananana",
    "wof:placetype":"locality"
},
  "geometry": {"coordinates":[48.56667,-17.46667],"type":"Point"}
}