{
  "type": "Feature",
  "properties": {
    "gn:admin1_code":"01",
    "gn:asciiname":"Andratamarina",
    "gn:country_code":"MG",
    "gn:dem":73,
    "gn:feature_class":"P",
    "gn:feature_code":"PPL",
    "gn:name":"Andratamarina",
    "gn:population":0,
    "gn:timezone":"Indian/Antananarivo",
    "iso:country":"MG",
    "name:fra_x_preferred":[
        "Andratamarina"
    ],
    "name:ita_x_preferred":[
        "Andratamarina"
    ],
    "name:mlg_x_preferred":[
        "Andratamarina"
    ],
    "name:nld_x_preferred":[
        "Andratamarina"
    ],
    "wof:name":"Andratamarina",
    "wof:placetype":"locality"
},
  "geometry": {"coordinates":[49.91667,-14.35],"type":"Point"}
}