{
  "type": "Feature",
  "properties": {
    "gn:admin1_code":"03",
    "gn:asciiname":"Beroboka",
    "gn:country_code":"MG",
    "gn:dem":261,
    "gn:feature_class":"P",
    "gn:feature_code":"PPL",
    "gn:name":"Beroboka",
    "gn:population":0,
    "gn:timezone":"Indian/Antananarivo",
    "iso:country":"MG",
    "wof:name":"Beroboka",
    "wof:placetype":"locality"
},
  "geometry": {"coordinates":[45.65,-16.76667],"type":"Point"}
}