{
  "type": "Feature",
  "properties": {
    "gn:admin1_code":"03",
    "gn:asciiname":"Bemarivo-Betsiboka",
    "gn:cc2":"MG",
    "gn:country_code":"MG",
    "gn:dem":200,
    "gn:feature_class":"P",
    "gn:feature_code":"PPL",
    "gn:name":"Bemarivo-Betsiboka",
    "gn:population":0,
    "gn:timezone":"Indian/Antananarivo",
    "iso:country":"MG",
    "name:und_x_variant":[
        "Bemaharive-Betsiboka",
        "Bemarivo",
        "Bemarivo-Betsiboka"
    ],
    "wof:name":"Bemarivo-Betsiboka",
    "wof:placetype":"locality"
},
  "geometry": {"coordinates":[46.98333,-17.01667],"type":"Point"}
}