{
  "type": "Feature",
  "properties": {
    "gn:admin1_code":"06",
    "gn:asciiname":"Reheha",
    "gn:country_code":"MG",
    "gn:dem":630,
    "gn:feature_class":"P",
    "gn:feature_code":"PPL",
    "gn:name":"Reheha",
    "gn:population":0,
    "gn:timezone":"Indian/Antananarivo",
    "iso:country":"MG",
    "wof:name":"Reheha",
    "wof:placetype":"locality"
},
  "geometry": {"coordinates":[45.53333,-23.31667],"type":"Point"}
}