{
  "type": "Feature",
  "properties": {
    "gn:admin1_code":"06",
    "gn:asciiname":"Makaikely",
    "gn:country_code":"MG",
    "gn:dem":254,
    "gn:feature_class":"P",
    "gn:feature_code":"PPL",
    "gn:name":"Makaikely",
    "gn:population":0,
    "gn:timezone":"Indian/Antananarivo",
    "iso:country":"MG",
    "wof:name":"Makaikely",
    "wof:placetype":"locality"
},
  "geometry": {"coordinates":[45.35,-21.46667],"type":"Point"}
}