{
  "type": "Feature",
  "properties": {
    "gn:admin1_code":"05",
    "gn:asciiname":"Antsahalava",
    "gn:country_code":"MG",
    "gn:dem":1679,
    "gn:feature_class":"P",
    "gn:feature_code":"PPL",
    "gn:name":"Antsahalava",
    "gn:population":0,
    "gn:timezone":"Indian/Antananarivo",
    "iso:country":"MG",
    "name:fra_x_preferred":[
        "Antsahalava"
    ],
    "name:ita_x_preferred":[
        "Antsahalava"
    ],
    "name:mlg_x_preferred":[
        "Antsahalava"
    ],
    "name:nld_x_preferred":[
        "Antsahalava"
    ],
    "name:pol_x_preferred":[
        "Antsahalava"
    ],
    "wof:name":"Antsahalava",
    "wof:placetype":"locality"
},
  "geometry": {"coordinates":[47.01667,-19.41667],"type":"Point"}
}