{
  "type": "Feature",
  "properties": {
    "gn:admin1_code":"05",
    "gn:asciiname":"Antsahanavony",
    "gn:cc2":"MG",
    "gn:country_code":"MG",
    "gn:dem":854,
    "gn:feature_class":"P",
    "gn:feature_code":"PPL",
    "gn:name":"Antsahanavony",
    "gn:population":0,
    "gn:timezone":"Indian/Antananarivo",
    "iso:country":"MG",
    "name:und_x_variant":[
        "Andohanavony",
        "Antsahanavony"
    ],
    "wof:name":"Antsahanavony",
    "wof:placetype":"locality"
},
  "geometry": {"coordinates":[46.31667,-17.85],"type":"Point"}
}