{
  "type": "Feature",
  "properties": {
    "gn:admin1_code":"06",
    "gn:asciiname":"Ambatovato",
    "gn:country_code":"MG",
    "gn:dem":176,
    "gn:feature_class":"P",
    "gn:feature_code":"PPL",
    "gn:name":"Ambatovato",
    "gn:population":0,
    "gn:timezone":"Indian/Antananarivo",
    "iso:country":"MG",
    "wof:name":"Ambatovato",
    "wof:placetype":"locality"
},
  "geometry": {"coordinates":[45.66667,-25.16667],"type":"Point"}
}