{
  "type": "Feature",
  "properties": {
    "gn:admin1_code":"01",
    "gn:asciiname":"Misorolava",
    "gn:cc2":"MG",
    "gn:country_code":"MG",
    "gn:dem":36,
    "gn:feature_class":"P",
    "gn:feature_code":"PPL",
    "gn:name":"Misorolava",
    "gn:population":0,
    "gn:timezone":"Indian/Antananarivo",
    "iso:country":"MG",
    "name:und_x_variant":[
        "Mosorolava",
        "Misorolava"
    ],
    "wof:name":"Misorolava",
    "wof:placetype":"locality"
},
  "geometry": {"coordinates":[48.96667,-12.73333],"type":"Point"}
}