{
  "type": "Feature",
  "properties": {
    "gn:admin1_code":"6.0",
    "gn:asciiname":"Terakabo",
    "gn:country_code":"MG",
    "gn:dem":183,
    "gn:feature_class":"P",
    "gn:feature_code":"PPL",
    "gn:name":"Terakabo",
    "gn:population":0,
    "gn:timezone":"Indian/Antananarivo",
    "iso:country":"MG",
    "wof:name":"Terakabo",
    "wof:placetype":"locality"
},
  "geometry": {"coordinates":[45.86667,-25.23333],"type":"Point"}
}