{
  "type": "Feature",
  "properties": {
    "gn:admin1_code":"02",
    "gn:asciiname":"Ambatovory",
    "gn:country_code":"MG",
    "gn:dem":1265,
    "gn:feature_class":"P",
    "gn:feature_code":"PPL",
    "gn:name":"Ambatovory",
    "gn:population":0,
    "gn:timezone":"Indian/Antananarivo",
    "iso:country":"MG",
    "wof:name":"Ambatovory",
    "wof:placetype":"locality"
},
  "geometry": {"coordinates":[46.73333,-20.63333],"type":"Point"}
}