{
  "type": "Feature",
  "properties": {
    "gn:admin1_code":"04",
    "gn:asciiname":"Ambodimanga",
    "gn:country_code":"MG",
    "gn:dem":240,
    "gn:feature_class":"P",
    "gn:feature_code":"PPL",
    "gn:name":"Ambodimanga",
    "gn:population":0,
    "gn:timezone":"Indian/Antananarivo",
    "iso:country":"MG",
    "name:est_x_preferred":[
        "Ambodimanga"
    ],
    "name:fra_x_preferred":[
        "Ambodimanga"
    ],
    "name:ita_x_preferred":[
        "Ambodimanga"
    ],
    "name:nld_x_preferred":[
        "Ambodimanga"
    ],
    "wof:name":"Ambodimanga",
    "wof:placetype":"locality"
},
  "geometry": {"coordinates":[49.56667,-16.35],"type":"Point"}
}