{
  "type": "Feature",
  "properties": {
    "gn:admin1_code":"03",
    "gn:asciiname":"Antongondria",
    "gn:cc2":"MG",
    "gn:country_code":"MG",
    "gn:dem":109,
    "gn:feature_class":"P",
    "gn:feature_code":"PPL",
    "gn:name":"Antongondria",
    "gn:population":0,
    "gn:timezone":"Indian/Antananarivo",
    "iso:country":"MG",
    "name:und_x_variant":[
        "Antongodria",
        "Antongondria"
    ],
    "wof:name":"Antongondria",
    "wof:placetype":"locality"
},
  "geometry": {"coordinates":[47.58333,-15.16667],"type":"Point"}
}