{
  "type": "Feature",
  "properties": {
    "gn:admin1_code":"06",
    "gn:asciiname":"Behara",
    "gn:country_code":"MG",
    "gn:dem":240,
    "gn:feature_class":"P",
    "gn:feature_code":"PPL",
    "gn:name":"Behara",
    "gn:population":0,
    "gn:timezone":"Indian/Antananarivo",
    "iso:country":"MG",
    "name:fra_x_preferred":[
        "Behara"
    ],
    "name:ita_x_preferred":[
        "Behara"
    ],
    "name:mlg_x_preferred":[
        "Behara"
    ],
    "name:nld_x_preferred":[
        "Behara"
    ],
    "name:spa_x_preferred":[
        "Behara"
    ],
    "wof:name":"Behara",
    "wof:placetype":"locality"
},
  "geometry": {"coordinates":[44.51667,-23.86667000000001],"type":"Point"}
}