{
  "type": "Feature",
  "properties": {
    "gn:admin1_code":"06",
    "gn:asciiname":"Iaborotra",
    "gn:cc2":"MG",
    "gn:country_code":"MG",
    "gn:dem":618,
    "gn:feature_class":"P",
    "gn:feature_code":"PPL",
    "gn:name":"Iaborotra",
    "gn:population":0,
    "gn:timezone":"Indian/Antananarivo",
    "iso:country":"MG",
    "name:fra_x_preferred":[
        "Iaborotra"
    ],
    "name:ita_x_preferred":[
        "Iaborotra"
    ],
    "name:mlg_x_preferred":[
        "Iaborotra"
    ],
    "name:nld_x_preferred":[
        "Iaborotra"
    ],
    "name:und_x_variant":[
        "Iaborotsy",
        "Iaboratsy"
    ],
    "wof:name":"Iaborotra",
    "wof:placetype":"locality"
},
  "geometry": {"coordinates":[45.55,-23.21667],"type":"Point"}
}