{
  "type": "Feature",
  "properties": {
    "gn:admin1_code":"06",
    "gn:asciiname":"Beholiva",
    "gn:country_code":"MG",
    "gn:dem":238,
    "gn:feature_class":"P",
    "gn:feature_code":"PPL",
    "gn:name":"Beholiva",
    "gn:population":0,
    "gn:timezone":"Indian/Antananarivo",
    "iso:country":"MG",
    "wof:name":"Beholiva",
    "wof:placetype":"locality"
},
  "geometry": {"coordinates":[44.55,-24.38333],"type":"Point"}
}