{
  "type": "Feature",
  "properties": {
    "gn:admin1_code":"02",
    "gn:asciiname":"Bekinana Avaratra",
    "gn:country_code":"MG",
    "gn:dem":1018,
    "gn:feature_class":"P",
    "gn:feature_code":"PPL",
    "gn:name":"Bekinana Avaratra",
    "gn:population":0,
    "gn:timezone":"Indian/Antananarivo",
    "iso:country":"MG",
    "wof:name":"Bekinana Avaratra",
    "wof:placetype":"locality"
},
  "geometry": {"coordinates":[46.58333,-23.68333],"type":"Point"}
}