{
  "type": "Feature",
  "properties": {
    "gn:admin1_code":"06",
    "gn:asciiname":"Ambondro II",
    "gn:cc2":"MG",
    "gn:country_code":"MG",
    "gn:dem":1330,
    "gn:feature_class":"P",
    "gn:feature_code":"PPL",
    "gn:name":"Ambondro II",
    "gn:population":0,
    "gn:timezone":"Indian/Antananarivo",
    "iso:country":"MG",
    "name:und_x_variant":[
        "Ambondro",
        "Ambondro II"
    ],
    "wof:name":"Ambondro II",
    "wof:placetype":"locality"
},
  "geometry": {"coordinates":[46.33333,-23.21667],"type":"Point"}
}