{
  "type": "Feature",
  "properties": {
    "gn:admin1_code":"03",
    "gn:asciiname":"Ambanibohobe",
    "gn:country_code":"MG",
    "gn:dem":723,
    "gn:feature_class":"P",
    "gn:feature_code":"PPL",
    "gn:name":"Ambanibohobe",
    "gn:population":0,
    "gn:timezone":"Indian/Antananarivo",
    "iso:country":"MG",
    "wof:name":"Ambanibohobe",
    "wof:placetype":"locality"
},
  "geometry": {"coordinates":[48.01667,-17.26667],"type":"Point"}
}