{
  "type": "Feature",
  "properties": {
    "iso:country":"MG",
    "name:ara_x_preferred":[
        "\u0623\u0646\u062a\u0627\u0646\u064a\u0641\u0648\u062a\u0633\u064a"
    ],
    "name:ceb_x_preferred":[
        "Antanifotsy"
    ],
    "name:deu_x_preferred":[
        "Antanifotsy"
    ],
    "name:eng_x_preferred":[
        "Antanifotsy"
    ],
    "name:fas_x_preferred":[
        "\u0622\u0646\u062a\u0627\u0646\u06cc\u0641\u0648\u062a\u0633\u06cc"
    ],
    "name:fra_x_preferred":[
        "Antanifotsy"
    ],
    "name:hbs_x_preferred":[
        "Antanifotsi"
    ],
    "name:hrv_x_preferred":[
        "Antanifotsy"
    ],
    "name:ita_x_preferred":[
        "Antanifotsy"
    ],
    "name:jpn_x_preferred":[
        "\u30a2\u30f3\u30bf\u30cb\u30d5\u30a9\u30b7\u30fc"
    ],
    "name:mlg_x_preferred":[
        "Antanifotsy"
    ],
    "name:nld_x_preferred":[
        "Antanifotsy"
    ],
    "name:pol_x_preferred":[
        "Antanifotsy"
    ],
    "name:por_x_preferred":[
        "Antanifotsy"
    ],
    "name:rus_x_preferred":[
        "\u0410\u043d\u0442\u0430\u043d\u0438\u0444\u0443\u0442\u0441\u0438"
    ],
    "name:rus_x_variant":[
        "\u0410\u043d\u0442\u0430\u043d\u0438\u0444\u0443\u0446\u0438"
    ],
    "name:spa_x_preferred":[
        "Antanifotsy"
    ],
    "name:swa_x_preferred":[
        "Antanifotsy"
    ],
    "name:swe_x_preferred":[
        "Antanifotsy"
    ],
    "name:tur_x_preferred":[
        "Antanifotsy"
    ],
    "name:zho_x_preferred":[
        "\u5b89\u5854\u5c3c\u5bcc\u9f4a"
    ],
    "name:zul_x_preferred":[
        "Antanifotsy"
    ],
    "qs:gn_country":"MG",
    "qs:gn_fcode":"PPL",
    "qs:gn_pop":70626,
    "qs:name":"Antanifotsy",
    "qs:name_adm0":"Madagascar",
    "qs:name_adm1":"Antananarivo",
    "qs:photos":0,
    "qs:photos_1k":0,
    "qs:photos_9k":1,
    "qs:photos_9r":1,
    "qs:photos_all":1,
    "qs:photos_sr":0,
    "qs:placetype":"Town",
    "qs:pop_sr":"8",
    "qs:woe_adm0":23424883,
    "wof:name":"Antanifotsy",
    "wof:placetype":"locality",
    "wof:population":70626
},
  "geometry": {"coordinates":[47.31667,-19.65],"type":"Point"}
}