{
  "type": "Feature",
  "properties": {
    "iso:country":"MG",
    "name:deu_x_preferred":[
        "Antanifotsy"
    ],
    "name:fra_x_preferred":[
        "Antanifotsy"
    ],
    "name:hbs_x_preferred":[
        "Antanifotsi"
    ],
    "name:hrv_x_preferred":[
        "Antanifotsy"
    ],
    "name:mlg_x_preferred":[
        "Antanifotsy"
    ],
    "name:nld_x_preferred":[
        "Antanifotsy"
    ],
    "name:pol_x_preferred":[
        "Antanifotsy"
    ],
    "name:por_x_preferred":[
        "Antanifotsy"
    ],
    "name:rus_x_preferred":[
        "\u0410\u043d\u0442\u0430\u043d\u0438\u0444\u0443\u0442\u0441\u0438"
    ],
    "name:spa_x_preferred":[
        "Antanifotsy"
    ],
    "name:swa_x_preferred":[
        "Antanifotsy"
    ],
    "name:swe_x_preferred":[
        "Antanifotsy"
    ],
    "name:tur_x_preferred":[
        "Antanifotsy"
    ],
    "name:zho_x_preferred":[
        "\u5b89\u5854\u5c3c\u5bcc\u9f4a"
    ],
    "qs:gn_country":"MG",
    "qs:gn_fcode":"PPL",
    "qs:gn_pop":70626,
    "qs:name":"Antanifotsy",
    "qs:name_adm0":"Madagascar",
    "qs:name_adm1":"Antananarivo",
    "qs:photos":0,
    "qs:photos_1k":0,
    "qs:photos_9k":1,
    "qs:photos_9r":1,
    "qs:photos_all":1,
    "qs:photos_sr":0,
    "qs:placetype":"Town",
    "qs:pop_sr":"8",
    "qs:woe_adm0":23424883,
    "wof:name":"Antanifotsy",
    "wof:placetype":"locality",
    "wof:population":70626
},
  "geometry": {"coordinates":[47.31667,-19.65],"type":"Point"}
}