{
  "type": "Feature",
  "properties": {
    "gn:admin1_code":"03",
    "gn:asciiname":"Ambararatabe Avaratra",
    "gn:cc2":"MG",
    "gn:country_code":"MG",
    "gn:dem":1112,
    "gn:feature_class":"P",
    "gn:feature_code":"PPL",
    "gn:name":"Ambararatabe Avaratra",
    "gn:population":0,
    "gn:timezone":"Indian/Antananarivo",
    "iso:country":"MG",
    "name:und_x_variant":[
        "Ambararata",
        "Ambararatabe Nord",
        "Ambararatabe Avaratra"
    ],
    "wof:name":"Ambararatabe Avaratra",
    "wof:placetype":"locality"
},
  "geometry": {"coordinates":[48.81667,-14.38333],"type":"Point"}
}