{
  "type": "Feature",
  "properties": {
    "gn:admin1_code":"03",
    "gn:asciiname":"Maroboa",
    "gn:cc2":"MG",
    "gn:country_code":"MG",
    "gn:dem":76,
    "gn:feature_class":"P",
    "gn:feature_code":"PPL",
    "gn:name":"Maroboa",
    "gn:population":0,
    "gn:timezone":"Indian/Antananarivo",
    "iso:country":"MG",
    "name:und_x_variant":[
        "Maroboay",
        "Maroboa"
    ],
    "wof:name":"Maroboa",
    "wof:placetype":"locality"
},
  "geometry": {"coordinates":[46.55,-17.18333],"type":"Point"}
}