{
  "type": "Feature",
  "properties": {
    "gn:admin1_code":"02",
    "gn:asciiname":"Mahatsinjorano",
    "gn:cc2":"MG",
    "gn:country_code":"MG",
    "gn:dem":679,
    "gn:feature_class":"P",
    "gn:feature_code":"PPL",
    "gn:name":"Mahatsinjorano",
    "gn:population":0,
    "gn:timezone":"Indian/Antananarivo",
    "iso:country":"MG",
    "name:und_x_variant":[
        "Mahatsiniorano",
        "Mahatsinjorano"
    ],
    "wof:name":"Mahatsinjorano",
    "wof:placetype":"locality"
},
  "geometry": {"coordinates":[46.55,-22.33333],"type":"Point"}
}