{
  "type": "Feature",
  "properties": {
    "gn:admin1_code":"04",
    "gn:asciiname":"Lahimena",
    "gn:country_code":"MG",
    "gn:dem":902,
    "gn:feature_class":"P",
    "gn:feature_code":"PPL",
    "gn:name":"Lahimena",
    "gn:population":0,
    "gn:timezone":"Indian/Antananarivo",
    "iso:country":"MG",
    "wof:name":"Lahimena",
    "wof:placetype":"locality"
},
  "geometry": {"coordinates":[48.16667,-18.95],"type":"Point"}
}