{
  "type": "Feature",
  "properties": {
    "gn:admin1_code":"06",
    "gn:asciiname":"Andakana",
    "gn:country_code":"MG",
    "gn:dem":19,
    "gn:feature_class":"P",
    "gn:feature_code":"PPL",
    "gn:name":"Andakana",
    "gn:population":0,
    "gn:timezone":"Indian/Antananarivo",
    "iso:country":"MG",
    "wof:name":"Andakana",
    "wof:placetype":"locality"
},
  "geometry": {"coordinates":[46.86667,-24.98333],"type":"Point"}
}