{
  "type": "Feature",
  "properties": {
    "gn:admin1_code":"2.0",
    "gn:asciiname":"Vohibola",
    "gn:country_code":"MG",
    "gn:dem":635,
    "gn:feature_class":"P",
    "gn:feature_code":"PPL",
    "gn:name":"Vohibola",
    "gn:population":0,
    "gn:timezone":"Indian/Antananarivo",
    "iso:country":"MG",
    "wof:name":"Vohibola",
    "wof:placetype":"locality"
},
  "geometry": {"coordinates":[47.53333,-20.65],"type":"Point"}
}