{
  "type": "Feature",
  "properties": {
    "gn:admin1_code":"02",
    "gn:asciiname":"Ambalabe",
    "gn:country_code":"MG",
    "gn:dem":651,
    "gn:feature_class":"P",
    "gn:feature_code":"PPL",
    "gn:name":"Ambalabe",
    "gn:population":0,
    "gn:timezone":"Indian/Antananarivo",
    "iso:country":"MG",
    "wof:name":"Ambalabe",
    "wof:placetype":"locality"
},
  "geometry": {"coordinates":[46.68333,-23.11667000000001],"type":"Point"}
}