{
  "type": "Feature",
  "properties": {
    "gn:admin1_code":"01",
    "gn:asciiname":"Ambilobe",
    "gn:country_code":"MG",
    "gn:dem":154,
    "gn:feature_class":"P",
    "gn:feature_code":"PPL",
    "gn:name":"Ambilobe",
    "gn:population":0,
    "gn:timezone":"Indian/Antananarivo",
    "iso:country":"MG",
    "name:azb_x_preferred":[
        "\u0627\u0645\u0628\u06cc\u0644\u0627\u0628"
    ],
    "name:cat_x_preferred":[
        "Ambilobe"
    ],
    "name:ceb_x_preferred":[
        "Ambilobe"
    ],
    "name:deu_x_preferred":[
        "Ambilobe"
    ],
    "name:epo_x_preferred":[
        "Ambilobe"
    ],
    "name:fas_x_preferred":[
        "\u0627\u0645\u0628\u06cc\u0644\u0627\u0628"
    ],
    "name:fra_x_preferred":[
        "Ambilobe"
    ],
    "name:hrv_x_preferred":[
        "Ambilobe"
    ],
    "name:hun_x_preferred":[
        "Ambilobe"
    ],
    "name:ita_x_preferred":[
        "Ambilobe"
    ],
    "name:mlg_x_preferred":[
        "Ambilobe"
    ],
    "name:nld_x_preferred":[
        "Ambilobe"
    ],
    "name:nor_x_preferred":[
        "Ambilobe"
    ],
    "name:pol_x_preferred":[
        "Ambilobe"
    ],
    "name:por_x_preferred":[
        "Ambilobe"
    ],
    "name:rus_x_preferred":[
        "\u0410\u043c\u0431\u0438\u043b\u0443\u0431\u0435"
    ],
    "name:spa_x_preferred":[
        "Ambilobe"
    ],
    "name:swe_x_preferred":[
        "Ambilobe"
    ],
    "name:szl_x_preferred":[
        "Ambilobe"
    ],
    "name:zho_x_preferred":[
        "\u5b89\u6bd4\u76e7\u8c9d"
    ],
    "wof:name":"Ambilobe",
    "wof:placetype":"locality"
},
  "geometry": {"coordinates":[49.75,-13.73333],"type":"Point"}
}