{
  "type": "Feature",
  "properties": {
    "gn:admin1_code":"04",
    "gn:asciiname":"Maroseranana",
    "gn:cc2":"MG",
    "gn:country_code":"MG",
    "gn:dem":382,
    "gn:feature_class":"P",
    "gn:feature_code":"PPL",
    "gn:name":"Maroseranana",
    "gn:population":0,
    "gn:timezone":"Indian/Antananarivo",
    "iso:country":"MG",
    "name:und_x_variant":[
        "Maroserana",
        "Maroseranana"
    ],
    "wof:name":"Maroseranana",
    "wof:placetype":"locality"
},
  "geometry": {"coordinates":[48.85,-18.53333],"type":"Point"}
}