{
  "type": "Feature",
  "properties": {
    "gn:admin1_code":"2.0",
    "gn:asciiname":"Tataho",
    "gn:country_code":"MG",
    "gn:dem":18,
    "gn:feature_class":"P",
    "gn:feature_code":"PPL",
    "gn:name":"Tataho",
    "gn:population":0,
    "gn:timezone":"Indian/Antananarivo",
    "iso:country":"MG",
    "name:fra_x_preferred":[
        "Tataho"
    ],
    "name:mlg_x_preferred":[
        "Tataho"
    ],
    "name:nld_x_preferred":[
        "Tataho"
    ],
    "wof:name":"Tataho",
    "wof:placetype":"locality"
},
  "geometry": {"coordinates":[47.96667,-22.21667],"type":"Point"}
}