{
  "type": "Feature",
  "properties": {
    "gn:admin1_code":"02",
    "gn:asciiname":"Mandanona",
    "gn:country_code":"MG",
    "gn:dem":1063,
    "gn:feature_class":"P",
    "gn:feature_code":"PPL",
    "gn:name":"Mandanona",
    "gn:population":0,
    "gn:timezone":"Indian/Antananarivo",
    "iso:country":"MG",
    "wof:name":"Mandanona",
    "wof:placetype":"locality"
},
  "geometry": {"coordinates":[46.41667,-21.23333],"type":"Point"}
}