{
  "type": "Feature",
  "properties": {
    "gn:admin1_code":"03",
    "gn:asciiname":"Miadana",
    "gn:country_code":"MG",
    "gn:dem":31,
    "gn:feature_class":"P",
    "gn:feature_code":"PPL",
    "gn:name":"Miadana",
    "gn:population":0,
    "gn:timezone":"Indian/Antananarivo",
    "iso:country":"MG",
    "wof:name":"Miadana",
    "wof:placetype":"locality"
},
  "geometry": {"coordinates":[47.18333,-15.68333],"type":"Point"}
}