{
  "type": "Feature",
  "properties": {
    "gn:admin1_code":"05",
    "gn:asciiname":"Ambohitrafovoany",
    "gn:country_code":"MG",
    "gn:dem":898,
    "gn:feature_class":"P",
    "gn:feature_code":"PPL",
    "gn:name":"Ambohitrafovoany",
    "gn:population":0,
    "gn:timezone":"Indian/Antananarivo",
    "iso:country":"MG",
    "wof:name":"Ambohitrafovoany",
    "wof:placetype":"locality"
},
  "geometry": {"coordinates":[46.83333,-18.16667],"type":"Point"}
}