{
  "type": "Feature",
  "properties": {
    "gn:admin1_code":"6.0",
    "gn:asciiname":"Tsembasotra",
    "gn:country_code":"MG",
    "gn:dem":227,
    "gn:feature_class":"P",
    "gn:feature_code":"PPL",
    "gn:name":"Tsembasotra",
    "gn:population":0,
    "gn:timezone":"Indian/Antananarivo",
    "iso:country":"MG",
    "wof:name":"Tsembasotra",
    "wof:placetype":"locality"
},
  "geometry": {"coordinates":[45.11667,-21.76667],"type":"Point"}
}