{
  "type": "Feature",
  "properties": {
    "gn:admin1_code":"04",
    "gn:asciiname":"Marangidroa",
    "gn:country_code":"MG",
    "gn:dem":783,
    "gn:feature_class":"P",
    "gn:feature_code":"PPL",
    "gn:name":"Marangidroa",
    "gn:population":0,
    "gn:timezone":"Indian/Antananarivo",
    "iso:country":"MG",
    "wof:name":"Marangidroa",
    "wof:placetype":"locality"
},
  "geometry": {"coordinates":[48.33333,-17.26667],"type":"Point"}
}