{
  "type": "Feature",
  "properties": {
    "gn:admin1_code":"2.0",
    "gn:asciiname":"Vohibato",
    "gn:country_code":"MG",
    "gn:dem":663,
    "gn:feature_class":"P",
    "gn:feature_code":"PPL",
    "gn:name":"Vohibato",
    "gn:population":0,
    "gn:timezone":"Indian/Antananarivo",
    "iso:country":"MG",
    "wof:name":"Vohibato",
    "wof:placetype":"locality"
},
  "geometry": {"coordinates":[46.95,-22.73333],"type":"Point"}
}