{
  "type": "Feature",
  "properties": {
    "gn:admin1_code":"06",
    "gn:asciiname":"Nosy Ambositra",
    "gn:country_code":"MG",
    "gn:dem":57,
    "gn:feature_class":"P",
    "gn:feature_code":"PPL",
    "gn:name":"Nosy Ambositra",
    "gn:population":0,
    "gn:timezone":"Indian/Antananarivo",
    "iso:country":"MG",
    "name:fra_x_preferred":[
        "Nosy Ambositra"
    ],
    "name:ita_x_preferred":[
        "Nosy Ambositra"
    ],
    "name:mlg_x_preferred":[
        "Nosy Ambositra"
    ],
    "wof:name":"Nosy Ambositra",
    "wof:placetype":"locality"
},
  "geometry": {"coordinates":[43.96667,-21.91667],"type":"Point"}
}