{
  "type": "Feature",
  "properties": {
    "gn:admin1_code":"02",
    "gn:asciiname":"Ifandra",
    "gn:country_code":"MG",
    "gn:dem":1054,
    "gn:feature_class":"P",
    "gn:feature_code":"PPL",
    "gn:name":"Ifandra",
    "gn:population":0,
    "gn:timezone":"Indian/Antananarivo",
    "iso:country":"MG",
    "wof:name":"Ifandra",
    "wof:placetype":"locality"
},
  "geometry": {"coordinates":[46.28333,-20.66667],"type":"Point"}
}