{
  "type": "Feature",
  "properties": {
    "gn:admin1_code":"03",
    "gn:asciiname":"Maroleo",
    "gn:cc2":"MG",
    "gn:country_code":"MG",
    "gn:dem":14,
    "gn:feature_class":"P",
    "gn:feature_code":"PPL",
    "gn:name":"Maroleo",
    "gn:population":0,
    "gn:timezone":"Indian/Antananarivo",
    "iso:country":"MG",
    "name:und_x_variant":[
        "Mahaleo",
        "Maroleo"
    ],
    "wof:name":"Maroleo",
    "wof:placetype":"locality"
},
  "geometry": {"coordinates":[45.23333,-16.15],"type":"Point"}
}