{
  "type": "Feature",
  "properties": {
    "gn:admin1_code":"03",
    "gn:asciiname":"Androtrabe",
    "gn:country_code":"MG",
    "gn:dem":528,
    "gn:feature_class":"P",
    "gn:feature_code":"PPL",
    "gn:name":"Androtrabe",
    "gn:population":0,
    "gn:timezone":"Indian/Antananarivo",
    "iso:country":"MG",
    "wof:name":"Androtrabe",
    "wof:placetype":"locality"
},
  "geometry": {"coordinates":[45.35,-17.95],"type":"Point"}
}