{
  "type": "Feature",
  "properties": {
    "gn:admin1_code":"02",
    "gn:asciiname":"Amby",
    "gn:country_code":"MG",
    "gn:dem":1229,
    "gn:feature_class":"P",
    "gn:feature_code":"PPL",
    "gn:name":"Amby",
    "gn:population":0,
    "gn:timezone":"Indian/Antananarivo",
    "iso:country":"MG",
    "wof:name":"Amby",
    "wof:placetype":"locality"
},
  "geometry": {"coordinates":[47.03333,-20.36667000000001],"type":"Point"}
}