{
  "type": "Feature",
  "properties": {
    "gn:admin1_code":"02",
    "gn:asciiname":"Amby",
    "gn:country_code":"MG",
    "gn:dem":1229,
    "gn:feature_class":"P",
    "gn:feature_code":"PPL",
    "gn:name":"Amby",
    "gn:population":0,
    "gn:timezone":"Indian/Antananarivo",
    "iso:country":"MG",
    "name:bar_x_preferred":[
        "Amby"
    ],
    "name:ceb_x_preferred":[
        "Amby"
    ],
    "name:fas_x_preferred":[
        "\u0627\u0645\u0628\u06cc"
    ],
    "name:fra_x_preferred":[
        "Amby"
    ],
    "name:lim_x_preferred":[
        "Amie"
    ],
    "name:nld_x_preferred":[
        "Amby"
    ],
    "wof:name":"Amby",
    "wof:placetype":"locality"
},
  "geometry": {"coordinates":[47.03333,-20.36667000000001],"type":"Point"}
}