{
  "type": "Feature",
  "properties": {
    "gn:admin1_code":"03",
    "gn:asciiname":"Ambodimadirokely",
    "gn:country_code":"MG",
    "gn:dem":347,
    "gn:feature_class":"P",
    "gn:feature_code":"PPL",
    "gn:name":"Ambodimadirokely",
    "gn:population":0,
    "gn:timezone":"Indian/Antananarivo",
    "iso:country":"MG",
    "wof:name":"Ambodimadirokely",
    "wof:placetype":"locality"
},
  "geometry": {"coordinates":[48.96667,-15.88333],"type":"Point"}
}