{
  "type": "Feature",
  "properties": {
    "gn:admin1_code":"02",
    "gn:asciiname":"Mahazoarivo",
    "gn:country_code":"MG",
    "gn:dem":1482,
    "gn:feature_class":"P",
    "gn:feature_code":"PPL",
    "gn:name":"Mahazoarivo",
    "gn:population":0,
    "gn:timezone":"Indian/Antananarivo",
    "iso:country":"MG",
    "name:fra_x_preferred":[
        "Mahazoarivo"
    ],
    "name:ita_x_preferred":[
        "Mahazoarivo"
    ],
    "name:mlg_x_preferred":[
        "Mahazoarivo"
    ],
    "name:nld_x_preferred":[
        "Mahazoarivo"
    ],
    "wof:name":"Mahazoarivo",
    "wof:placetype":"locality"
},
  "geometry": {"coordinates":[47.43333,-20.38333],"type":"Point"}
}