{
  "type": "Feature",
  "properties": {
    "gn:admin1_code":"01",
    "gn:asciiname":"Andranomilolo",
    "gn:cc2":"MG",
    "gn:country_code":"MG",
    "gn:dem":397,
    "gn:feature_class":"P",
    "gn:feature_code":"PPL",
    "gn:name":"Andranomilolo",
    "gn:population":0,
    "gn:timezone":"Indian/Antananarivo",
    "iso:country":"MG",
    "name:und_x_variant":[
        "Andranomololo",
        "Andranomilolo"
    ],
    "wof:name":"Andranomilolo",
    "wof:placetype":"locality"
},
  "geometry": {"coordinates":[49.43333,-14.35],"type":"Point"}
}