{
  "type": "Feature",
  "properties": {
    "gn:admin1_code":"02",
    "gn:asciiname":"Kianjanomby",
    "gn:country_code":"MG",
    "gn:dem":312,
    "gn:feature_class":"P",
    "gn:feature_code":"PPL",
    "gn:name":"Kianjanomby",
    "gn:population":0,
    "gn:timezone":"Indian/Antananarivo",
    "iso:country":"MG",
    "wof:name":"Kianjanomby",
    "wof:placetype":"locality"
},
  "geometry": {"coordinates":[47.53333,-21.76667],"type":"Point"}
}