{
  "type": "Feature",
  "properties": {
    "gn:admin1_code":"04",
    "gn:asciiname":"Beforona",
    "gn:cc2":"MG",
    "gn:country_code":"MG",
    "gn:dem":547,
    "gn:feature_class":"P",
    "gn:feature_code":"PPL",
    "gn:name":"Beforona",
    "gn:population":0,
    "gn:timezone":"Indian/Antananarivo",
    "iso:country":"MG",
    "name:und_x_variant":[
        "Beforono",
        "Beforona"
    ],
    "wof:name":"Beforona",
    "wof:placetype":"locality"
},
  "geometry": {"coordinates":[48.58333,-18.96667],"type":"Point"}
}