{
  "type": "Feature",
  "properties": {
    "gn:admin1_code":"02",
    "gn:asciiname":"Fenevory",
    "gn:cc2":"MG",
    "gn:country_code":"MG",
    "gn:dem":1165,
    "gn:feature_class":"P",
    "gn:feature_code":"PPL",
    "gn:name":"Fenevory",
    "gn:population":0,
    "gn:timezone":"Indian/Antananarivo",
    "iso:country":"MG",
    "name:und_x_variant":[
        "Fenovory",
        "Fenevory"
    ],
    "wof:name":"Fenevory",
    "wof:placetype":"locality"
},
  "geometry": {"coordinates":[46.93333,-21.98333],"type":"Point"}
}