{
  "type": "Feature",
  "properties": {
    "gn:admin1_code":"02",
    "gn:asciiname":"Mavogisa",
    "gn:country_code":"MG",
    "gn:dem":168,
    "gn:feature_class":"P",
    "gn:feature_code":"PPL",
    "gn:name":"Mavogisa",
    "gn:population":0,
    "gn:timezone":"Indian/Antananarivo",
    "iso:country":"MG",
    "wof:name":"Mavogisa",
    "wof:placetype":"locality"
},
  "geometry": {"coordinates":[48.08333,-21.38333],"type":"Point"}
}