{
  "type": "Feature",
  "properties": {
    "gn:admin1_code":"03",
    "gn:asciiname":"Antselitokakely",
    "gn:country_code":"MG",
    "gn:dem":345,
    "gn:feature_class":"P",
    "gn:feature_code":"PPL",
    "gn:name":"Antselitokakely",
    "gn:population":0,
    "gn:timezone":"Indian/Antananarivo",
    "iso:country":"MG",
    "wof:name":"Antselitokakely",
    "wof:placetype":"locality"
},
  "geometry": {"coordinates":[44.98333,-17.16667],"type":"Point"}
}