{
  "type": "Feature",
  "properties": {
    "gn:admin1_code":"05",
    "gn:asciiname":"Fonenana",
    "gn:country_code":"MG",
    "gn:dem":1315,
    "gn:feature_class":"P",
    "gn:feature_code":"PPL",
    "gn:name":"Fonenana",
    "gn:population":0,
    "gn:timezone":"Indian/Antananarivo",
    "iso:country":"MG",
    "wof:name":"Fonenana",
    "wof:placetype":"locality"
},
  "geometry": {"coordinates":[47.28333,-18.98333],"type":"Point"}
}