{
  "type": "Feature",
  "properties": {
    "gn:admin1_code":"2.0",
    "gn:asciiname":"Soatanimbary",
    "gn:country_code":"MG",
    "gn:dem":798,
    "gn:feature_class":"P",
    "gn:feature_code":"PPL",
    "gn:name":"Soatanimbary",
    "gn:population":0,
    "gn:timezone":"Indian/Antananarivo",
    "iso:country":"MG",
    "wof:name":"Soatanimbary",
    "wof:placetype":"locality"
},
  "geometry": {"coordinates":[46.23333,-21.61667000000001],"type":"Point"}
}