{
  "type": "Feature",
  "properties": {
    "gn:admin1_code":"01",
    "gn:asciiname":"Mangatsahatsa",
    "gn:country_code":"MG",
    "gn:dem":73,
    "gn:feature_class":"P",
    "gn:feature_code":"PPL",
    "gn:name":"Mangatsahatsa",
    "gn:population":0,
    "gn:timezone":"Indian/Antananarivo",
    "iso:country":"MG",
    "wof:name":"Mangatsahatsa",
    "wof:placetype":"locality"
},
  "geometry": {"coordinates":[50.05,-14.61667],"type":"Point"}
}