{
  "type": "Feature",
  "properties": {
    "gn:admin1_code":"02",
    "gn:asciiname":"Mahazoarivo",
    "gn:country_code":"MG",
    "gn:dem":1137,
    "gn:feature_class":"P",
    "gn:feature_code":"PPL",
    "gn:name":"Mahazoarivo",
    "gn:population":0,
    "gn:timezone":"Indian/Antananarivo",
    "iso:country":"MG",
    "wof:name":"Mahazoarivo",
    "wof:placetype":"locality"
},
  "geometry": {"coordinates":[46.93333,-20.18333],"type":"Point"}
}