{
  "type": "Feature",
  "properties": {
    "gn:admin1_code":"2.0",
    "gn:asciiname":"Sahabe",
    "gn:country_code":"MG",
    "gn:dem":20,
    "gn:feature_class":"P",
    "gn:feature_code":"PPL",
    "gn:name":"Sahabe",
    "gn:population":0,
    "gn:timezone":"Indian/Antananarivo",
    "iso:country":"MG",
    "wof:name":"Sahabe",
    "wof:placetype":"locality"
},
  "geometry": {"coordinates":[48.18333,-21.66667],"type":"Point"}
}