{
  "type": "Feature",
  "properties": {
    "gn:admin1_code":"03",
    "gn:asciiname":"Andrafiabe",
    "gn:country_code":"MG",
    "gn:dem":181,
    "gn:feature_class":"P",
    "gn:feature_code":"PPL",
    "gn:name":"Andrafiabe",
    "gn:population":0,
    "gn:timezone":"Indian/Antananarivo",
    "iso:country":"MG",
    "wof:name":"Andrafiabe",
    "wof:placetype":"locality"
},
  "geometry": {"coordinates":[44.53333,-18.28333],"type":"Point"}
}