{
  "type": "Feature",
  "properties": {
    "gn:admin1_code":"01",
    "gn:asciiname":"Antanantanana",
    "gn:cc2":"MG",
    "gn:country_code":"MG",
    "gn:dem":194,
    "gn:feature_class":"P",
    "gn:feature_code":"PPL",
    "gn:name":"Antanantanana",
    "gn:population":0,
    "gn:timezone":"Indian/Antananarivo",
    "iso:country":"MG",
    "name:und_x_variant":[
        "Antanantainana",
        "Antanantanana"
    ],
    "wof:name":"Antanantanana",
    "wof:placetype":"locality"
},
  "geometry": {"coordinates":[49.91667,-13.56667],"type":"Point"}
}