{
  "type": "Feature",
  "properties": {
    "gn:admin1_code":"4.0",
    "gn:asciiname":"Tananjaza",
    "gn:country_code":"MG",
    "gn:dem":895,
    "gn:feature_class":"P",
    "gn:feature_code":"PPL",
    "gn:name":"Tananjaza",
    "gn:population":0,
    "gn:timezone":"Indian/Antananarivo",
    "iso:country":"MG",
    "wof:name":"Tananjaza",
    "wof:placetype":"locality"
},
  "geometry": {"coordinates":[48.01667,-18.98333],"type":"Point"}
}