{
  "type": "Feature",
  "properties": {
    "gn:admin1_code":"03",
    "gn:asciiname":"Ambatolafia",
    "gn:country_code":"MG",
    "gn:dem":88,
    "gn:feature_class":"P",
    "gn:feature_code":"PPL",
    "gn:name":"Ambatolafia",
    "gn:population":0,
    "gn:timezone":"Indian/Antananarivo",
    "iso:country":"MG",
    "wof:name":"Ambatolafia",
    "wof:placetype":"locality"
},
  "geometry": {"coordinates":[46.03333,-16.41667],"type":"Point"}
}