{
  "type": "Feature",
  "properties": {
    "gn:admin1_code":"06",
    "gn:asciiname":"Ankilimany",
    "gn:country_code":"MG",
    "gn:dem":83,
    "gn:feature_class":"P",
    "gn:feature_code":"PPL",
    "gn:name":"Ankilimany",
    "gn:population":0,
    "gn:timezone":"Indian/Antananarivo",
    "iso:country":"MG",
    "wof:name":"Ankilimany",
    "wof:placetype":"locality"
},
  "geometry": {"coordinates":[45.71667,-25.33333],"type":"Point"}
}