{
  "type": "Feature",
  "properties": {
    "gn:admin1_code":"05",
    "gn:asciiname":"Ambatotsipihina",
    "gn:country_code":"MG",
    "gn:dem":1575,
    "gn:feature_class":"P",
    "gn:feature_code":"PPL",
    "gn:name":"Ambatotsipihina",
    "gn:population":0,
    "gn:timezone":"Indian/Antananarivo",
    "iso:country":"MG",
    "name:azb_x_preferred":[
        "\u0627\u0645\u0628\u0627\u062a\u0627\u062a\u0633\u06cc\u067e\u06cc\u0647\u0646\u0627"
    ],
    "name:bul_x_preferred":[
        "\u0410\u043c\u0431\u0430\u0442\u0443\u0446\u0438\u043f\u0438\u0445\u0438\u043d\u0430"
    ],
    "name:fas_x_preferred":[
        "\u0627\u0645\u0628\u0627\u062a\u0627\u062a\u0633\u06cc\u067e\u06cc\u0647\u0646\u0627"
    ],
    "name:fra_x_preferred":[
        "Ambatotsipihina"
    ],
    "name:ita_x_preferred":[
        "Ambatotsipihina"
    ],
    "name:mlg_x_preferred":[
        "Ambatotsipihina"
    ],
    "name:nld_x_preferred":[
        "Ambatotsipihina"
    ],
    "name:pol_x_preferred":[
        "Ambatotsipihina"
    ],
    "wof:name":"Ambatotsipihina",
    "wof:placetype":"locality"
},
  "geometry": {"coordinates":[47.35,-19.51667],"type":"Point"}
}