{
  "type": "Feature",
  "properties": {
    "gn:admin1_code":"06",
    "gn:asciiname":"Bemangarahara Atsimo",
    "gn:country_code":"MG",
    "gn:dem":146,
    "gn:feature_class":"P",
    "gn:feature_code":"PPL",
    "gn:name":"Bemangarahara Atsimo",
    "gn:population":0,
    "gn:timezone":"Indian/Antananarivo",
    "iso:country":"MG",
    "wof:name":"Bemangarahara Atsimo",
    "wof:placetype":"locality"
},
  "geometry": {"coordinates":[44.75,-21.71667],"type":"Point"}
}