{
  "type": "Feature",
  "properties": {
    "gn:admin1_code":"4.0",
    "gn:asciiname":"Vohimarina",
    "gn:country_code":"MG",
    "gn:dem":923,
    "gn:feature_class":"P",
    "gn:feature_code":"PPL",
    "gn:name":"Vohimarina",
    "gn:population":0,
    "gn:timezone":"Indian/Antananarivo",
    "iso:country":"MG",
    "wof:name":"Vohimarina",
    "wof:placetype":"locality"
},
  "geometry": {"coordinates":[48.53333,-16.95],"type":"Point"}
}