{
  "type": "Feature",
  "properties": {
    "gn:admin1_code":"03",
    "gn:asciiname":"Anjanaborona",
    "gn:country_code":"MG",
    "gn:dem":21,
    "gn:feature_class":"P",
    "gn:feature_code":"PPL",
    "gn:name":"Anjanaborona",
    "gn:population":0,
    "gn:timezone":"Indian/Antananarivo",
    "iso:country":"MG",
    "wof:name":"Anjanaborona",
    "wof:placetype":"locality"
},
  "geometry": {"coordinates":[46.51667,-15.68333],"type":"Point"}
}