{
  "type": "Feature",
  "properties": {
    "gn:admin1_code":"03",
    "gn:asciiname":"Amparihimahitsy",
    "gn:cc2":"MG",
    "gn:country_code":"MG",
    "gn:dem":14,
    "gn:feature_class":"P",
    "gn:feature_code":"PPL",
    "gn:name":"Amparihimahitsy",
    "gn:population":0,
    "gn:timezone":"Indian/Antananarivo",
    "iso:country":"MG",
    "name:und_x_variant":[
        "Amparimahitsy",
        "Amparihimahitsy"
    ],
    "wof:name":"Amparihimahitsy",
    "wof:placetype":"locality"
},
  "geometry": {"coordinates":[46.41667,-15.75],"type":"Point"}
}