{
  "type": "Feature",
  "properties": {
    "gn:admin1_code":"04",
    "gn:asciiname":"Marovato",
    "gn:country_code":"MG",
    "gn:dem":129,
    "gn:feature_class":"P",
    "gn:feature_code":"PPL",
    "gn:name":"Marovato",
    "gn:population":0,
    "gn:timezone":"Indian/Antananarivo",
    "iso:country":"MG",
    "name:ceb_x_preferred":[
        "Marovato"
    ],
    "name:fra_x_preferred":[
        "Marovato"
    ],
    "name:ita_x_preferred":[
        "Marovato"
    ],
    "name:nld_x_preferred":[
        "Marovato"
    ],
    "name:swe_x_preferred":[
        "Marovato"
    ],
    "wof:name":"Marovato",
    "wof:placetype":"locality"
},
  "geometry": {"coordinates":[49.35,-17.43333],"type":"Point"}
}