{
  "type": "Feature",
  "properties": {
    "gn:admin1_code":"04",
    "gn:asciiname":"Ambodiara III",
    "gn:cc2":"MG",
    "gn:country_code":"MG",
    "gn:dem":639,
    "gn:feature_class":"P",
    "gn:feature_code":"PPL",
    "gn:name":"Ambodiara III",
    "gn:population":0,
    "gn:timezone":"Indian/Antananarivo",
    "iso:country":"MG",
    "name:und_x_variant":[
        "Ambodihara",
        "Ambodiara III"
    ],
    "wof:name":"Ambodiara III",
    "wof:placetype":"locality"
},
  "geometry": {"coordinates":[48.43333,-19.35],"type":"Point"}
}