{
  "type": "Feature",
  "properties": {
    "gn:admin1_code":"03",
    "gn:asciiname":"Inango",
    "gn:country_code":"MG",
    "gn:dem":221,
    "gn:feature_class":"P",
    "gn:feature_code":"PPL",
    "gn:name":"Inango",
    "gn:population":0,
    "gn:timezone":"Indian/Antananarivo",
    "iso:country":"MG",
    "wof:name":"Inango",
    "wof:placetype":"locality"
},
  "geometry": {"coordinates":[48.28333,-15.55],"type":"Point"}
}