{
  "type": "Feature",
  "properties": {
    "gn:admin1_code":"06",
    "gn:asciiname":"Namakia",
    "gn:country_code":"MG",
    "gn:dem":22,
    "gn:feature_class":"P",
    "gn:feature_code":"PPL",
    "gn:name":"Namakia",
    "gn:population":0,
    "gn:timezone":"Indian/Antananarivo",
    "iso:country":"MG",
    "wof:name":"Namakia",
    "wof:placetype":"locality"
},
  "geometry": {"coordinates":[43.56667,-21.65],"type":"Point"}
}