{
  "type": "Feature",
  "properties": {
    "gn:admin1_code":"03",
    "gn:asciiname":"Mangakana",
    "gn:country_code":"MG",
    "gn:dem":649,
    "gn:feature_class":"P",
    "gn:feature_code":"PPL",
    "gn:name":"Mangakana",
    "gn:population":0,
    "gn:timezone":"Indian/Antananarivo",
    "iso:country":"MG",
    "wof:name":"Mangakana",
    "wof:placetype":"locality"
},
  "geometry": {"coordinates":[48.85,-14.91667],"type":"Point"}
}