{
  "type": "Feature",
  "properties": {
    "gn:admin1_code":"01",
    "gn:asciiname":"Andriralalana",
    "gn:country_code":"MG",
    "gn:dem":76,
    "gn:feature_class":"P",
    "gn:feature_code":"PPL",
    "gn:name":"Andriralalana",
    "gn:population":0,
    "gn:timezone":"Indian/Antananarivo",
    "iso:country":"MG",
    "wof:name":"Andriralalana",
    "wof:placetype":"locality"
},
  "geometry": {"coordinates":[48.15,-13.73333],"type":"Point"}
}