{
  "type": "Feature",
  "properties": {
    "gn:admin1_code":"1.0",
    "gn:asciiname":"Saharenana Ambany",
    "gn:cc2":"MG",
    "gn:country_code":"MG",
    "gn:dem":181,
    "gn:feature_class":"P",
    "gn:feature_code":"PPL",
    "gn:name":"Saharenana Ambany",
    "gn:population":0,
    "gn:timezone":"Indian/Antananarivo",
    "iso:country":"MG",
    "name:und_x_variant":[
        "Saharainanambany",
        "Saharainambany",
        "Saharenana Ambany"
    ],
    "wof:name":"Saharenana Ambany",
    "wof:placetype":"locality"
},
  "geometry": {"coordinates":[49.38333,-12.58333],"type":"Point"}
}