{
  "type": "Feature",
  "properties": {
    "gn:admin1_code":"04",
    "gn:asciiname":"Manompana",
    "gn:country_code":"MG",
    "gn:dem":11,
    "gn:feature_class":"P",
    "gn:feature_code":"PPL",
    "gn:name":"Manompana",
    "gn:population":0,
    "gn:timezone":"Indian/Antananarivo",
    "iso:country":"MG",
    "name:azb_x_preferred":[
        "\u0645\u0627\u0646\u0648\u0645\u067e\u0627\u0646\u0627"
    ],
    "name:fas_x_preferred":[
        "\u0645\u0627\u0646\u0648\u0645\u067e\u0627\u0646\u0627"
    ],
    "name:fra_x_preferred":[
        "Manompana"
    ],
    "name:ita_x_preferred":[
        "Manompana"
    ],
    "name:mlg_x_preferred":[
        "Manompana"
    ],
    "name:nld_x_preferred":[
        "Manompana"
    ],
    "name:ukr_x_preferred":[
        "\u041c\u0430\u043d\u043e\u043c\u043f\u0430\u043d\u0430"
    ],
    "wof:name":"Manompana",
    "wof:placetype":"locality"
},
  "geometry": {"coordinates":[49.73333,-16.68333],"type":"Point"}
}