{
  "type": "Feature",
  "properties": {
    "gn:admin1_code":"01",
    "gn:asciiname":"Ampasimbengy",
    "gn:country_code":"MG",
    "gn:dem":425,
    "gn:feature_class":"P",
    "gn:feature_code":"PPL",
    "gn:name":"Ampasimbengy",
    "gn:population":0,
    "gn:timezone":"Indian/Antananarivo",
    "iso:country":"MG",
    "wof:name":"Ampasimbengy",
    "wof:placetype":"locality"
},
  "geometry": {"coordinates":[49.15,-12.78333],"type":"Point"}
}