{
  "type": "Feature",
  "properties": {
    "gn:admin1_code":"06",
    "gn:asciiname":"Antanandava",
    "gn:country_code":"MG",
    "gn:dem":297,
    "gn:feature_class":"P",
    "gn:feature_code":"PPL",
    "gn:name":"Antanandava",
    "gn:population":0,
    "gn:timezone":"Indian/Antananarivo",
    "iso:country":"MG",
    "wof:name":"Antanandava",
    "wof:placetype":"locality"
},
  "geometry": {"coordinates":[45.23333,-18.06667],"type":"Point"}
}