{
  "type": "Feature",
  "properties": {
    "gn:admin1_code":"01",
    "gn:asciiname":"Ambodimanga",
    "gn:country_code":"MG",
    "gn:dem":28,
    "gn:feature_class":"P",
    "gn:feature_code":"PPL",
    "gn:name":"Ambodimanga",
    "gn:population":0,
    "gn:timezone":"Indian/Antananarivo",
    "iso:country":"MG",
    "wof:name":"Ambodimanga",
    "wof:placetype":"locality"
},
  "geometry": {"coordinates":[49.23333,-12.25],"type":"Point"}
}