{
  "type": "Feature",
  "properties": {
    "gn:admin1_code":"06",
    "gn:asciiname":"Behatsaka",
    "gn:cc2":"MG",
    "gn:country_code":"MG",
    "gn:dem":135,
    "gn:feature_class":"P",
    "gn:feature_code":"PPL",
    "gn:name":"Behatsaka",
    "gn:population":0,
    "gn:timezone":"Indian/Antananarivo",
    "iso:country":"MG",
    "name:und_x_variant":[
        "Behatsaky",
        "Behatsaka"
    ],
    "wof:name":"Behatsaka",
    "wof:placetype":"locality"
},
  "geometry": {"coordinates":[44.51667,-21.78333],"type":"Point"}
}