{
  "type": "Feature",
  "properties": {
    "gn:admin1_code":"04",
    "gn:asciiname":"Ambohitranefitra",
    "gn:country_code":"MG",
    "gn:dem":666,
    "gn:feature_class":"P",
    "gn:feature_code":"PPL",
    "gn:name":"Ambohitranefitra",
    "gn:population":0,
    "gn:timezone":"Indian/Antananarivo",
    "iso:country":"MG",
    "wof:name":"Ambohitranefitra",
    "wof:placetype":"locality"
},
  "geometry": {"coordinates":[48.55,-19.03333],"type":"Point"}
}