{
  "type": "Feature",
  "properties": {
    "gn:admin1_code":"06",
    "gn:asciiname":"Maintiabo",
    "gn:country_code":"MG",
    "gn:dem":337,
    "gn:feature_class":"P",
    "gn:feature_code":"PPL",
    "gn:name":"Maintiabo",
    "gn:population":0,
    "gn:timezone":"Indian/Antananarivo",
    "iso:country":"MG",
    "wof:name":"Maintiabo",
    "wof:placetype":"locality"
},
  "geometry": {"coordinates":[45.58333,-24.73333],"type":"Point"}
}