{
  "type": "Feature",
  "properties": {
    "gn:country":"MG",
    "gn:fcode":"PPL",
    "gn:pop":21036,
    "iso:country":"MG",
    "name:ceb_x_preferred":[
        "Fenoarivo Atsinanana"
    ],
    "name:dan_x_preferred":[
        "Fenoarivo Atsinanana"
    ],
    "name:deu_x_preferred":[
        "Fenoarivo Atsinanana"
    ],
    "name:eng_x_preferred":[
        "Fenoarivo Atsinanana"
    ],
    "name:fra_x_preferred":[
        "Fenoarivo Atsinanana"
    ],
    "name:hrv_x_preferred":[
        "Fenoarivo Atsinanana"
    ],
    "name:ita_x_preferred":[
        "Fenoarivo Atsinanana"
    ],
    "name:jpn_x_preferred":[
        "\u30d5\u30a7\u30ce\u30a2\u30ea\u30f4\u30a9\u30fb\u30a2\u30c4\u30a3\u30ca\u30ca\u30ca"
    ],
    "name:mlg_x_preferred":[
        "Fenoarivo Atsinanana"
    ],
    "name:nld_x_preferred":[
        "Fenoarivo Atsinanana"
    ],
    "name:pol_x_preferred":[
        "Fenoarivo Atsinanana"
    ],
    "name:por_x_preferred":[
        "F\u00e9n\u00e9rive Est"
    ],
    "name:rus_x_preferred":[
        "\u0424\u0435\u043d\u0443\u0430\u0440\u0438\u0432\u0443-\u0410\u0446\u0438\u043d\u0430\u043d\u0430\u043d\u0430"
    ],
    "name:swe_x_preferred":[
        "Fenoarivo Atsinanana"
    ],
    "name:unk_x_variant":[
        "F\u00e9n\u00e9rive-Est"
    ],
    "name:urd_x_preferred":[
        "\u0641\u06cc\u0646\u0648\u0627\u0631\u06cc\u0648\u0648 \u0622\u062a\u0633\u06cc\u0646\u0627\u0646\u0627\u0646\u0627"
    ],
    "name:zho_x_preferred":[
        "\u8cbb\u52aa\u963f\u91cc\u6b66-\u963f\u9f4a\u7d0d\u7d0d\u7d0d"
    ],
    "qs:name":"Fenoarivo Atsinanana",
    "qs:photos_9r":0,
    "qs:photos_sr":0,
    "qs:pop_sr":"7",
    "wd:wordcount":154,
    "wof:name":"Fenoarivo Atsinanana",
    "wof:placetype":"locality",
    "wof:population":21036
},
  "geometry": {"coordinates":[49.40826,-17.38095],"type":"Point"}
}