{
  "type": "Feature",
  "properties": {
    "gn:admin1_code":"6.0",
    "gn:asciiname":"Tamboholava",
    "gn:country_code":"MG",
    "gn:dem":783,
    "gn:feature_class":"P",
    "gn:feature_code":"PPL",
    "gn:name":"Tamboholava",
    "gn:population":0,
    "gn:timezone":"Indian/Antananarivo",
    "iso:country":"MG",
    "wof:name":"Tamboholava",
    "wof:placetype":"locality"
},
  "geometry": {"coordinates":[45.53333,-22.86667000000001],"type":"Point"}
}