{
  "type": "Feature",
  "properties": {
    "gn:admin1_code":"02",
    "gn:asciiname":"Antsiriloa",
    "gn:country_code":"MG",
    "gn:dem":888,
    "gn:feature_class":"P",
    "gn:feature_code":"PPL",
    "gn:name":"Antsiriloa",
    "gn:population":0,
    "gn:timezone":"Indian/Antananarivo",
    "iso:country":"MG",
    "wof:name":"Antsiriloa",
    "wof:placetype":"locality"
},
  "geometry": {"coordinates":[46.45,-21.61667000000001],"type":"Point"}
}