{
  "type": "Feature",
  "properties": {
    "gn:admin1_code":"04",
    "gn:asciiname":"Andranomena",
    "gn:country_code":"MG",
    "gn:dem":758,
    "gn:feature_class":"P",
    "gn:feature_code":"PPL",
    "gn:name":"Andranomena",
    "gn:population":0,
    "gn:timezone":"Indian/Antananarivo",
    "iso:country":"MG",
    "name:fra_x_preferred":[
        "Andranomena"
    ],
    "name:ita_x_preferred":[
        "Andranomena"
    ],
    "name:nld_x_preferred":[
        "Andranomena"
    ],
    "wof:name":"Andranomena",
    "wof:placetype":"locality"
},
  "geometry": {"coordinates":[48.51667,-17.53333],"type":"Point"}
}