{
  "type": "Feature",
  "properties": {
    "gn:admin1_code":"02",
    "gn:asciiname":"Mahabe",
    "gn:country_code":"MG",
    "gn:dem":81,
    "gn:feature_class":"P",
    "gn:feature_code":"PPL",
    "gn:name":"Mahabe",
    "gn:population":0,
    "gn:timezone":"Indian/Antananarivo",
    "iso:country":"MG",
    "name:ceb_x_preferred":[
        "Mahabe"
    ],
    "name:fra_x_preferred":[
        "Mahabe"
    ],
    "name:ita_x_preferred":[
        "Mahabe"
    ],
    "name:mlg_x_preferred":[
        "Mahabe"
    ],
    "name:nld_x_preferred":[
        "Mahabe"
    ],
    "name:swe_x_preferred":[
        "Mahabe"
    ],
    "wof:name":"Mahabe",
    "wof:placetype":"locality"
},
  "geometry": {"coordinates":[47.26667,-23.31667],"type":"Point"}
}