{
  "type": "Feature",
  "properties": {
    "gn:admin1_code":"04",
    "gn:asciiname":"Antsiranantsara",
    "gn:country_code":"MG",
    "gn:dem":72,
    "gn:feature_class":"P",
    "gn:feature_code":"PPL",
    "gn:name":"Antsiranantsara",
    "gn:population":0,
    "gn:timezone":"Indian/Antananarivo",
    "iso:country":"MG",
    "wof:name":"Antsiranantsara",
    "wof:placetype":"locality"
},
  "geometry": {"coordinates":[49.35,-17.78333],"type":"Point"}
}