{
  "type": "Feature",
  "properties": {
    "gn:admin1_code":"05",
    "gn:asciiname":"Ambohitsaratelo",
    "gn:country_code":"MG",
    "gn:dem":1300,
    "gn:feature_class":"P",
    "gn:feature_code":"PPL",
    "gn:name":"Ambohitsaratelo",
    "gn:population":0,
    "gn:timezone":"Indian/Antananarivo",
    "iso:country":"MG",
    "wof:name":"Ambohitsaratelo",
    "wof:placetype":"locality"
},
  "geometry": {"coordinates":[47.31667,-19.01667],"type":"Point"}
}