{
  "type": "Feature",
  "properties": {
    "gn:admin1_code":"02",
    "gn:asciiname":"Amparihy Atsinanana",
    "gn:cc2":"MG",
    "gn:country_code":"MG",
    "gn:dem":29,
    "gn:feature_class":"P",
    "gn:feature_code":"PPL",
    "gn:name":"Amparihy Atsinanana",
    "gn:population":0,
    "gn:timezone":"Indian/Antananarivo",
    "iso:country":"MG",
    "name:azb_x_preferred":[
        "\u0627\u0645\u067e\u0627\u0631\u0647\u06cc \u0627\u06cc\u0633\u062a"
    ],
    "name:fas_x_preferred":[
        "\u0627\u0645\u067e\u0627\u0631\u0647\u06cc \u0627\u06cc\u0633\u062a"
    ],
    "name:fra_x_preferred":[
        "Amparihy Est"
    ],
    "name:ita_x_preferred":[
        "Amparihy Est"
    ],
    "name:mlg_x_preferred":[
        "Amparihy Est"
    ],
    "name:nld_x_preferred":[
        "Amparihy Est"
    ],
    "name:und_x_variant":[
        "Imarihy",
        "Amparihy",
        "Amparihy Atsinanana"
    ],
    "wof:name":"Amparihy Atsinanana",
    "wof:placetype":"locality"
},
  "geometry": {"coordinates":[47.33333,-23.95],"type":"Point"}
}