{
  "type": "Feature",
  "properties": {
    "gn:admin1_code":"03",
    "gn:asciiname":"Bedingadingana",
    "gn:country_code":"MG",
    "gn:dem":685,
    "gn:feature_class":"P",
    "gn:feature_code":"PPL",
    "gn:name":"Bedingadingana",
    "gn:population":0,
    "gn:timezone":"Indian/Antananarivo",
    "iso:country":"MG",
    "wof:name":"Bedingadingana",
    "wof:placetype":"locality"
},
  "geometry": {"coordinates":[47.35,-17.73333],"type":"Point"}
}