{
  "type": "Feature",
  "properties": {
    "gn:admin1_code":"01",
    "gn:asciiname":"Bobakilandikely",
    "gn:country_code":"MG",
    "gn:dem":313,
    "gn:feature_class":"P",
    "gn:feature_code":"PPL",
    "gn:name":"Bobakilandikely",
    "gn:population":0,
    "gn:timezone":"Indian/Antananarivo",
    "iso:country":"MG",
    "wof:name":"Bobakilandikely",
    "wof:placetype":"locality"
},
  "geometry": {"coordinates":[49.05,-12.61667],"type":"Point"}
}