{
  "type": "Feature",
  "properties": {
    "gn:admin1_code":"03",
    "gn:asciiname":"Matavirano",
    "gn:country_code":"MG",
    "gn:dem":22,
    "gn:feature_class":"P",
    "gn:feature_code":"PPL",
    "gn:name":"Matavirano",
    "gn:population":0,
    "gn:timezone":"Indian/Antananarivo",
    "iso:country":"MG",
    "wof:name":"Matavirano",
    "wof:placetype":"locality"
},
  "geometry": {"coordinates":[44.18333,-18.21667],"type":"Point"}
}