{
  "type": "Feature",
  "properties": {
    "gn:admin1_code":"03",
    "gn:asciiname":"Andebadebakely",
    "gn:country_code":"MG",
    "gn:dem":145,
    "gn:feature_class":"P",
    "gn:feature_code":"PPL",
    "gn:name":"Andebadebakely",
    "gn:population":0,
    "gn:timezone":"Indian/Antananarivo",
    "iso:country":"MG",
    "wof:name":"Andebadebakely",
    "wof:placetype":"locality"
},
  "geometry": {"coordinates":[46.33333,-17.35],"type":"Point"}
}