{
  "type": "Feature",
  "properties": {
    "gn:admin1_code":"02",
    "gn:asciiname":"Ambia",
    "gn:country_code":"MG",
    "gn:dem":693,
    "gn:feature_class":"P",
    "gn:feature_code":"PPL",
    "gn:name":"Ambia",
    "gn:population":0,
    "gn:timezone":"Indian/Antananarivo",
    "iso:country":"MG",
    "wof:name":"Ambia",
    "wof:placetype":"locality"
},
  "geometry": {"coordinates":[46.18333,-22.36667000000001],"type":"Point"}
}