{
  "type": "Feature",
  "properties": {
    "gn:admin1_code":"5.0",
    "gn:asciiname":"Tsarazaza",
    "gn:country_code":"MG",
    "gn:dem":1325,
    "gn:feature_class":"P",
    "gn:feature_code":"PPL",
    "gn:name":"Tsarazaza",
    "gn:population":0,
    "gn:timezone":"Indian/Antananarivo",
    "iso:country":"MG",
    "name:fra_x_preferred":[
        "Tsarazaza"
    ],
    "name:ita_x_preferred":[
        "Tsarazaza"
    ],
    "name:mlg_x_preferred":[
        "Tsarazaza"
    ],
    "name:nld_x_preferred":[
        "Tsarazaza"
    ],
    "wof:name":"Tsarazaza",
    "wof:placetype":"locality"
},
  "geometry": {"coordinates":[46.71667,-19.38333],"type":"Point"}
}