{
  "type": "Feature",
  "properties": {
    "gn:admin1_code":"01",
    "gn:asciiname":"Mafaikakazo",
    "gn:country_code":"MG",
    "gn:dem":242,
    "gn:feature_class":"P",
    "gn:feature_code":"PPL",
    "gn:name":"Mafaikakazo",
    "gn:population":0,
    "gn:timezone":"Indian/Antananarivo",
    "iso:country":"MG",
    "wof:name":"Mafaikakazo",
    "wof:placetype":"locality"
},
  "geometry": {"coordinates":[49.88333,-14.83333],"type":"Point"}
}