{
  "type": "Feature",
  "properties": {
    "gn:admin1_code":"04",
    "gn:asciiname":"Marofinaritra",
    "gn:cc2":"MG",
    "gn:country_code":"MG",
    "gn:dem":223,
    "gn:feature_class":"P",
    "gn:feature_code":"PPL",
    "gn:name":"Marofinaritra",
    "gn:population":0,
    "gn:timezone":"Indian/Antananarivo",
    "iso:country":"MG",
    "name:azb_x_preferred":[
        "\u0645\u0627\u0631\u0648\u0641\u0646\u0627\u0631\u06cc\u062a\u0627"
    ],
    "name:fas_x_preferred":[
        "\u0645\u0627\u0631\u0648\u0641\u0646\u0627\u0631\u06cc\u062a\u0627"
    ],
    "name:fra_x_preferred":[
        "Marofinaritra"
    ],
    "name:ita_x_preferred":[
        "Marofinaritra"
    ],
    "name:mlg_x_preferred":[
        "Marofinaritra"
    ],
    "name:nld_x_preferred":[
        "Marofinaritra"
    ],
    "name:und_x_variant":[
        "Morofinaritra",
        "Marofinaritra"
    ],
    "wof:name":"Marofinaritra",
    "wof:placetype":"locality"
},
  "geometry": {"coordinates":[49.31667,-17.55],"type":"Point"}
}