{
  "type": "Feature",
  "properties": {
    "gn:admin1_code":"06",
    "gn:asciiname":"Ambahivahy",
    "gn:country_code":"MG",
    "gn:dem":277,
    "gn:feature_class":"P",
    "gn:feature_code":"PPL",
    "gn:name":"Ambahivahy",
    "gn:population":0,
    "gn:timezone":"Indian/Antananarivo",
    "iso:country":"MG",
    "wof:name":"Ambahivahy",
    "wof:placetype":"locality"
},
  "geometry": {"coordinates":[45.01667,-24.51667],"type":"Point"}
}