{
  "type": "Feature",
  "properties": {
    "gn:admin1_code":"03",
    "gn:asciiname":"Kalandy",
    "gn:cc2":"MG",
    "gn:country_code":"MG",
    "gn:dem":506,
    "gn:feature_class":"P",
    "gn:feature_code":"PPL",
    "gn:name":"Kalandy",
    "gn:population":0,
    "gn:timezone":"Indian/Antananarivo",
    "iso:country":"MG",
    "name:und_x_variant":[
        "Kalendy",
        "Kalandy"
    ],
    "wof:name":"Kalandy",
    "wof:placetype":"locality"
},
  "geometry": {"coordinates":[48.73333,-15.75],"type":"Point"}
}