{
  "type": "Feature",
  "properties": {
    "gn:admin1_code":"02",
    "gn:asciiname":"Panatsiva",
    "gn:country_code":"MG",
    "gn:dem":79,
    "gn:feature_class":"P",
    "gn:feature_code":"PPL",
    "gn:name":"Panatsiva",
    "gn:population":0,
    "gn:timezone":"Indian/Antananarivo",
    "iso:country":"MG",
    "wof:name":"Panatsiva",
    "wof:placetype":"locality"
},
  "geometry": {"coordinates":[47.45,-23.06667],"type":"Point"}
}