{
  "type": "Feature",
  "properties": {
    "gn:admin1_code":"01",
    "gn:asciiname":"Ankitsaka",
    "gn:country_code":"MG",
    "gn:dem":107,
    "gn:feature_class":"P",
    "gn:feature_code":"PPL",
    "gn:name":"Ankitsaka",
    "gn:population":0,
    "gn:timezone":"Indian/Antananarivo",
    "iso:country":"MG",
    "wof:name":"Ankitsaka",
    "wof:placetype":"locality"
},
  "geometry": {"coordinates":[49.98333,-14.43333],"type":"Point"}
}