{
  "type": "Feature",
  "properties": {
    "gn:admin1_code":"04",
    "gn:asciiname":"Ambohimanjaka",
    "gn:country_code":"MG",
    "gn:dem":670,
    "gn:feature_class":"P",
    "gn:feature_code":"PPL",
    "gn:name":"Ambohimanjaka",
    "gn:population":0,
    "gn:timezone":"Indian/Antananarivo",
    "iso:country":"MG",
    "wof:name":"Ambohimanjaka",
    "wof:placetype":"locality"
},
  "geometry": {"coordinates":[47.98333,-19.46667],"type":"Point"}
}