{
  "type": "Feature",
  "properties": {
    "gn:admin1_code":"05",
    "gn:asciiname":"Ambohiriana",
    "gn:country_code":"MG",
    "gn:dem":1249,
    "gn:feature_class":"P",
    "gn:feature_code":"PPL",
    "gn:name":"Ambohiriana",
    "gn:population":0,
    "gn:timezone":"Indian/Antananarivo",
    "iso:country":"MG",
    "wof:name":"Ambohiriana",
    "wof:placetype":"locality"
},
  "geometry": {"coordinates":[47.25,-18.91667],"type":"Point"}
}