{
  "type": "Feature",
  "properties": {
    "gn:admin1_code":"03",
    "gn:asciiname":"Bemanevika",
    "gn:country_code":"MG",
    "gn:dem":856,
    "gn:feature_class":"P",
    "gn:feature_code":"PPL",
    "gn:name":"Bemanevika",
    "gn:population":0,
    "gn:timezone":"Indian/Antananarivo",
    "iso:country":"MG",
    "name:fra_x_preferred":[
        "Bemanevika"
    ],
    "name:ita_x_preferred":[
        "Bemanevika Est"
    ],
    "name:mlg_x_preferred":[
        "Bemanevika"
    ],
    "name:nld_x_preferred":[
        "Bemanevika"
    ],
    "wof:name":"Bemanevika",
    "wof:placetype":"locality"
},
  "geometry": {"coordinates":[49.33333,-14.98333],"type":"Point"}
}