{
  "type": "Feature",
  "properties": {
    "gn:admin1_code":"06",
    "gn:asciiname":"Ampihalia",
    "gn:country_code":"MG",
    "gn:dem":121,
    "gn:feature_class":"P",
    "gn:feature_code":"PPL",
    "gn:name":"Ampihalia",
    "gn:population":0,
    "gn:timezone":"Indian/Antananarivo",
    "iso:country":"MG",
    "wof:name":"Ampihalia",
    "wof:placetype":"locality"
},
  "geometry": {"coordinates":[43.85,-23.21667],"type":"Point"}
}