{
  "type": "Feature",
  "properties": {
    "gn:admin1_code":"03",
    "gn:asciiname":"Antsohihy",
    "gn:country_code":"MG",
    "gn:dem":16,
    "gn:feature_class":"P",
    "gn:feature_code":"PPL",
    "gn:name":"Antsohihy",
    "gn:population":0,
    "gn:timezone":"Indian/Antananarivo",
    "iso:country":"MG",
    "wof:name":"Antsohihy",
    "wof:placetype":"locality"
},
  "geometry": {"coordinates":[46.76667,-16.11667000000001],"type":"Point"}
}