{
  "type": "Feature",
  "properties": {
    "gn:admin1_code":"05",
    "gn:asciiname":"Morafeno",
    "gn:country_code":"MG",
    "gn:dem":806,
    "gn:feature_class":"P",
    "gn:feature_code":"PPL",
    "gn:name":"Morafeno",
    "gn:population":0,
    "gn:timezone":"Indian/Antananarivo",
    "iso:country":"MG",
    "wof:name":"Morafeno",
    "wof:placetype":"locality"
},
  "geometry": {"coordinates":[46.28333,-18.93333],"type":"Point"}
}