{
  "type": "Feature",
  "properties": {
    "gn:admin1_code":"06",
    "gn:asciiname":"Bevelatsy",
    "gn:country_code":"MG",
    "gn:dem":685,
    "gn:feature_class":"P",
    "gn:feature_code":"PPL",
    "gn:name":"Bevelatsy",
    "gn:population":0,
    "gn:timezone":"Indian/Antananarivo",
    "iso:country":"MG",
    "wof:name":"Bevelatsy",
    "wof:placetype":"locality"
},
  "geometry": {"coordinates":[45.75,-23.46667],"type":"Point"}
}