{
  "type": "Feature",
  "properties": {
    "gn:admin1_code":"06",
    "gn:asciiname":"Ambatomainty",
    "gn:country_code":"MG",
    "gn:dem":495,
    "gn:feature_class":"P",
    "gn:feature_code":"PPL",
    "gn:name":"Ambatomainty",
    "gn:population":0,
    "gn:timezone":"Indian/Antananarivo",
    "iso:country":"MG",
    "name:azb_x_preferred":[
        "\u0627\u0645\u0628\u0627\u062a\u0648\u0645\u0627\u0646\u062a\u06cc"
    ],
    "name:fas_x_preferred":[
        "\u0627\u0645\u0628\u0627\u062a\u0648\u0645\u0627\u0646\u062a\u06cc"
    ],
    "name:fra_x_preferred":[
        "Ambatomainty"
    ],
    "name:ita_x_preferred":[
        "Ambatomainty"
    ],
    "name:mlg_x_preferred":[
        "Ambatomainty"
    ],
    "name:nld_x_preferred":[
        "Ambatomainty"
    ],
    "name:pol_x_preferred":[
        "Ambatomainty"
    ],
    "name:spa_x_preferred":[
        "Ambatomainty"
    ],
    "name:zho_x_preferred":[
        "\u5b89\u5df4\u5716\u9081\u56e0\u8482"
    ],
    "wof:name":"Ambatomainty",
    "wof:placetype":"locality"
},
  "geometry": {"coordinates":[45.15,-24.15],"type":"Point"}
}