{
  "type": "Feature",
  "properties": {
    "gn:admin1_code":"2.0",
    "gn:asciiname":"Sahafandrana",
    "gn:country_code":"MG",
    "gn:dem":404,
    "gn:feature_class":"P",
    "gn:feature_code":"PPL",
    "gn:name":"Sahafandrana",
    "gn:population":0,
    "gn:timezone":"Indian/Antananarivo",
    "iso:country":"MG",
    "wof:name":"Sahafandrana",
    "wof:placetype":"locality"
},
  "geometry": {"coordinates":[48.03333,-20.66667],"type":"Point"}
}