{
  "type": "Feature",
  "properties": {
    "gn:admin1_code":"02",
    "gn:asciiname":"Ambohimahatsinjo",
    "gn:cc2":"MG",
    "gn:country_code":"MG",
    "gn:dem":847,
    "gn:feature_class":"P",
    "gn:feature_code":"PPL",
    "gn:name":"Ambohimahatsinjo",
    "gn:population":0,
    "gn:timezone":"Indian/Antananarivo",
    "iso:country":"MG",
    "name:und_x_variant":[
        "Ambalamahatsinjo",
        "Ambohimahatsinjo"
    ],
    "wof:name":"Ambohimahatsinjo",
    "wof:placetype":"locality"
},
  "geometry": {"coordinates":[46.61667,-21.93333],"type":"Point"}
}