{
  "type": "Feature",
  "properties": {
    "gn:admin1_code":"5.0",
    "gn:asciiname":"Vatovorikely",
    "gn:country_code":"MG",
    "gn:dem":868,
    "gn:feature_class":"P",
    "gn:feature_code":"PPL",
    "gn:name":"Vatovorikely",
    "gn:population":0,
    "gn:timezone":"Indian/Antananarivo",
    "iso:country":"MG",
    "wof:name":"Vatovorikely",
    "wof:placetype":"locality"
},
  "geometry": {"coordinates":[46.08333,-19.61667000000001],"type":"Point"}
}