{
  "type": "Feature",
  "properties": {
    "gn:admin1_code":"2.0",
    "gn:asciiname":"Tolongoina",
    "gn:cc2":"MG",
    "gn:country_code":"MG",
    "gn:dem":442,
    "gn:feature_class":"P",
    "gn:feature_code":"PPL",
    "gn:name":"Tolongoina",
    "gn:population":0,
    "gn:timezone":"Indian/Antananarivo",
    "iso:country":"MG",
    "name:deu_x_preferred":[
        "Tolongoina"
    ],
    "name:fra_x_preferred":[
        "Tolongoina"
    ],
    "name:ita_x_preferred":[
        "Tolongoina"
    ],
    "name:mlg_x_preferred":[
        "Tolongoina"
    ],
    "name:nld_x_preferred":[
        "Tolongoina"
    ],
    "name:und_x_variant":[
        "Talongoina"
    ],
    "wof:name":"Tolongoina",
    "wof:placetype":"locality"
},
  "geometry": {"coordinates":[47.51667,-21.55],"type":"Point"}
}