{
  "type": "Feature",
  "properties": {
    "gn:admin1_code":"5.0",
    "gn:asciiname":"Tsaramody",
    "gn:country_code":"MG",
    "gn:dem":812,
    "gn:feature_class":"P",
    "gn:feature_code":"PPL",
    "gn:name":"Tsaramody",
    "gn:population":0,
    "gn:timezone":"Indian/Antananarivo",
    "iso:country":"MG",
    "wof:name":"Tsaramody",
    "wof:placetype":"locality"
},
  "geometry": {"coordinates":[46.26667,-19.56667],"type":"Point"}
}