{
  "type": "Feature",
  "properties": {
    "gn:admin1_code":"04",
    "gn:asciiname":"Ankoba",
    "gn:country_code":"MG",
    "gn:dem":159,
    "gn:feature_class":"P",
    "gn:feature_code":"PPL",
    "gn:name":"Ankoba",
    "gn:population":0,
    "gn:timezone":"Indian/Antananarivo",
    "iso:country":"MG",
    "wof:name":"Ankoba",
    "wof:placetype":"locality"
},
  "geometry": {"coordinates":[49.58333,-16.11667000000001],"type":"Point"}
}