{
  "type": "Feature",
  "properties": {
    "gn:admin1_code":"01",
    "gn:asciiname":"Ampapamena",
    "gn:country_code":"MG",
    "gn:dem":57,
    "gn:feature_class":"P",
    "gn:feature_code":"PPL",
    "gn:name":"Ampapamena",
    "gn:population":0,
    "gn:timezone":"Indian/Antananarivo",
    "iso:country":"MG",
    "wof:name":"Ampapamena",
    "wof:placetype":"locality"
},
  "geometry": {"coordinates":[49.91667,-14.33333],"type":"Point"}
}