{
  "type": "Feature",
  "properties": {
    "gn:admin1_code":"03",
    "gn:asciiname":"Ankilimihohoky",
    "gn:country_code":"MG",
    "gn:dem":13,
    "gn:feature_class":"P",
    "gn:feature_code":"PPL",
    "gn:name":"Ankilimihohoky",
    "gn:population":0,
    "gn:timezone":"Indian/Antananarivo",
    "iso:country":"MG",
    "wof:name":"Ankilimihohoky",
    "wof:placetype":"locality"
},
  "geometry": {"coordinates":[44.43333,-18.83333],"type":"Point"}
}