{
  "type": "Feature",
  "properties": {
    "gn:admin1_code":"04",
    "gn:asciiname":"Ranomafana",
    "gn:country_code":"MG",
    "gn:dem":85,
    "gn:feature_class":"P",
    "gn:feature_code":"PPL",
    "gn:name":"Ranomafana",
    "gn:population":0,
    "gn:timezone":"Indian/Antananarivo",
    "iso:country":"MG",
    "name:deu_x_preferred":[
        "Ranomafana"
    ],
    "name:fra_x_preferred":[
        "Ranomafana"
    ],
    "name:ita_x_preferred":[
        "Ranomafana"
    ],
    "name:nld_x_preferred":[
        "Ranomafana"
    ],
    "name:pol_x_preferred":[
        "Ranomafana"
    ],
    "name:rus_x_preferred":[
        "\u0420\u0430\u043d\u0443\u043c\u0430\u0444\u0430\u043d\u0430"
    ],
    "wof:name":"Ranomafana",
    "wof:placetype":"locality"
},
  "geometry": {"coordinates":[48.83333,-18.95],"type":"Point"}
}