{
  "type": "Feature",
  "properties": {
    "gn:admin1_code":"04",
    "gn:asciiname":"Ranomafana",
    "gn:country_code":"MG",
    "gn:dem":85,
    "gn:feature_class":"P",
    "gn:feature_code":"PPL",
    "gn:name":"Ranomafana",
    "gn:population":0,
    "gn:timezone":"Indian/Antananarivo",
    "iso:country":"MG",
    "wof:name":"Ranomafana",
    "wof:placetype":"locality"
},
  "geometry": {"coordinates":[48.83333,-18.95],"type":"Point"}
}