{
  "type": "Feature",
  "properties": {
    "gn:admin1_code":"06",
    "gn:asciiname":"Ankilifolo",
    "gn:country_code":"MG",
    "gn:dem":254,
    "gn:feature_class":"P",
    "gn:feature_code":"PPL",
    "gn:name":"Ankilifolo",
    "gn:population":0,
    "gn:timezone":"Indian/Antananarivo",
    "iso:country":"MG",
    "wof:name":"Ankilifolo",
    "wof:placetype":"locality"
},
  "geometry": {"coordinates":[44.88333,-21.53333],"type":"Point"}
}