{
  "type": "Feature",
  "properties": {
    "gn:admin1_code":"03",
    "gn:asciiname":"Marovovo",
    "gn:country_code":"MG",
    "gn:dem":149,
    "gn:feature_class":"P",
    "gn:feature_code":"PPL",
    "gn:name":"Marovovo",
    "gn:population":0,
    "gn:timezone":"Indian/Antananarivo",
    "iso:country":"MG",
    "wof:name":"Marovovo",
    "wof:placetype":"locality"
},
  "geometry": {"coordinates":[46.45,-16.46667],"type":"Point"}
}