{
  "type": "Feature",
  "properties": {
    "iso:country":"MG",
    "name:bul_x_preferred":[
        "\u0410\u043d\u0434\u043e\u0432\u043e\u0440\u0430\u043d\u0442\u043e"
    ],
    "name:ceb_x_preferred":[
        "Andovoranto"
    ],
    "name:eng_x_preferred":[
        "Andevoranto"
    ],
    "name:fra_x_preferred":[
        "Andevoranto"
    ],
    "name:ita_x_preferred":[
        "Andevoranto"
    ],
    "name:mlg_x_preferred":[
        "Andevoranto"
    ],
    "name:nld_x_preferred":[
        "Andevoranto"
    ],
    "name:swe_x_preferred":[
        "Andovoranto"
    ],
    "name:unk_x_variant":[
        "Andevorante"
    ],
    "qs:gn_country":"MG",
    "qs:gn_fcode":"PPL",
    "qs:gn_pop":10429,
    "qs:name":"Andevoranto",
    "qs:name_adm0":"Madagascar",
    "qs:name_adm1":"Toamasina",
    "qs:photos":0,
    "qs:photos_1k":0,
    "qs:photos_9k":0,
    "qs:photos_9r":0,
    "qs:photos_all":0,
    "qs:photos_sr":0,
    "qs:placetype":"Town",
    "qs:pop_sr":"6",
    "qs:woe_adm0":23424883,
    "wd:wordcount":181,
    "wof:name":"Andevoranto",
    "wof:placetype":"locality",
    "wof:population":10429
},
  "geometry": {"coordinates":[49.1094,-18.95443],"type":"Point"}
}