{
  "type": "Feature",
  "properties": {
    "gn:admin1_code":"03",
    "gn:asciiname":"Ampanikely",
    "gn:country_code":"MG",
    "gn:dem":265,
    "gn:feature_class":"P",
    "gn:feature_code":"PPL",
    "gn:name":"Ampanikely",
    "gn:population":0,
    "gn:timezone":"Indian/Antananarivo",
    "iso:country":"MG",
    "wof:name":"Ampanikely",
    "wof:placetype":"locality"
},
  "geometry": {"coordinates":[45.03333,-18.13333],"type":"Point"}
}