{
  "type": "Feature",
  "properties": {
    "gn:admin1_code":"02",
    "gn:asciiname":"Ikatelo",
    "gn:country_code":"MG",
    "gn:dem":1108,
    "gn:feature_class":"P",
    "gn:feature_code":"PPL",
    "gn:name":"Ikatelo",
    "gn:population":0,
    "gn:timezone":"Indian/Antananarivo",
    "iso:country":"MG",
    "wof:name":"Ikatelo",
    "wof:placetype":"locality"
},
  "geometry": {"coordinates":[46.95,-20.35],"type":"Point"}
}