{
  "type": "Feature",
  "properties": {
    "iso:country":"MG",
    "name:deu_x_preferred":[
        "Androka"
    ],
    "name:eng_x_preferred":[
        "Androka"
    ],
    "name:fra_x_preferred":[
        "Androka"
    ],
    "name:ita_x_preferred":[
        "Androka"
    ],
    "name:mlg_x_preferred":[
        "Androka"
    ],
    "name:nld_x_preferred":[
        "Androka"
    ],
    "name:spa_x_preferred":[
        "Androka"
    ],
    "name:zho_x_preferred":[
        "\u5b89\u5fb7\u9b6f\u5361"
    ],
    "ne:ADM0CAP":0.0,
    "ne:ADM0NAME":"Madagascar",
    "ne:ADM0_A3":"MDG",
    "ne:ADM1NAME":"Toliary",
    "ne:ADMIN1_COD":0,
    "ne:CAPALT":0,
    "ne:CHANGED":1,
    "ne:CHECKME":0,
    "ne:COMPARE":0,
    "ne:DIFFASCII":0,
    "ne:DIFFNOTE":"Location adjusted. Changed scale rank.",
    "ne:ELEVATION":0.0,
    "ne:FEATURECLA":"Populated place",
    "ne:GEONAMEID":-1,
    "ne:GEONAMESNO":"No GeoNames match due to small population, not in GeoNames, or poor NEV placement.",
    "ne:GN_POP":0,
    "ne:GTOPO30":0.0,
    "ne:ISO_A2":"MG",
    "ne:LABELRANK":6,
    "ne:LATITUDE":-25.021946,
    "ne:LONGITUDE":44.074947,
    "ne:LS_MATCH":1,
    "ne:LS_NAME":"Androka",
    "ne:MAX_AREAKM":1.0,
    "ne:MAX_AREAMI":0.0,
    "ne:MAX_BBXMAX":44.083333,
    "ne:MAX_BBXMIN":44.075,
    "ne:MAX_BBYMAX":-25.025,
    "ne:MAX_BBYMIN":-25.033333,
    "ne:MAX_NATSCA":20.0,
    "ne:MAX_PERKM":4.0,
    "ne:MAX_PERMI":2.0,
    "ne:MAX_POP10":174,
    "ne:MAX_POP20":174,
    "ne:MAX_POP300":0,
    "ne:MAX_POP310":0,
    "ne:MAX_POP50":0,
    "ne:MEAN_BBXC":44.079167,
    "ne:MEAN_BBYC":-25.029167,
    "ne:MEGACITY":0,
    "ne:MIN_AREAKM":1.0,
    "ne:MIN_AREAMI":0.0,
    "ne:MIN_BBXMAX":44.083333,
    "ne:MIN_BBXMIN":44.075,
    "ne:MIN_BBYMAX":-25.025,
    "ne:MIN_BBYMIN":-25.033333,
    "ne:MIN_PERKM":4.0,
    "ne:MIN_PERMI":2.0,
    "ne:NAME":"Androka",
    "ne:NAMEASCII":"Androka",
    "ne:NAMEDIFF":0,
    "ne:NATSCALE":30,
    "ne:POP1950":0,
    "ne:POP1955":0,
    "ne:POP1960":0,
    "ne:POP1965":0,
    "ne:POP1970":0,
    "ne:POP1975":0,
    "ne:POP1980":0,
    "ne:POP1985":0,
    "ne:POP1990":0,
    "ne:POP1995":0,
    "ne:POP2000":0,
    "ne:POP2005":0,
    "ne:POP2010":0,
    "ne:POP2015":0,
    "ne:POP2020":0,
    "ne:POP2025":0,
    "ne:POP2050":0,
    "ne:POP_MAX":174,
    "ne:POP_MIN":174,
    "ne:POP_OTHER":0,
    "ne:RANK_MAX":1,
    "ne:RANK_MIN":1,
    "ne:SCALERANK":6,
    "ne:SOV0NAME":"Madagascar",
    "ne:SOV_A3":"MDG",
    "ne:UN_FID":0,
    "ne:UN_LAT":0.0,
    "ne:UN_LONG":0.0,
    "ne:WORLDCITY":0,
    "ne:min_zoom":6.0,
    "wof:name":"Androka",
    "wof:placetype":"locality"
},
  "geometry": {"coordinates":[44.07494694361941,-25.02194622806104],"type":"Point"}
}