{
  "type": "Feature",
  "properties": {
    "gn:admin1_code":"1.0",
    "gn:asciiname":"Tanetimbiavy",
    "gn:country_code":"MG",
    "gn:dem":434,
    "gn:feature_class":"P",
    "gn:feature_code":"PPL",
    "gn:name":"Tanetimbiavy",
    "gn:population":0,
    "gn:timezone":"Indian/Antananarivo",
    "iso:country":"MG",
    "wof:name":"Tanetimbiavy",
    "wof:placetype":"locality"
},
  "geometry": {"coordinates":[49.58333,-14.11667],"type":"Point"}
}