{
  "type": "Feature",
  "properties": {
    "gn:admin1_code":"04",
    "gn:asciiname":"Mizahamioraka",
    "gn:country_code":"MG",
    "gn:dem":44,
    "gn:feature_class":"P",
    "gn:feature_code":"PPL",
    "gn:name":"Mizahamioraka",
    "gn:population":0,
    "gn:timezone":"Indian/Antananarivo",
    "iso:country":"MG",
    "wof:name":"Mizahamioraka",
    "wof:placetype":"locality"
},
  "geometry": {"coordinates":[49.08333,-18.75],"type":"Point"}
}