{
  "type": "Feature",
  "properties": {
    "gn:admin1_code":"06",
    "gn:asciiname":"Masiakampy",
    "gn:cc2":"MG",
    "gn:country_code":"MG",
    "gn:dem":400,
    "gn:feature_class":"P",
    "gn:feature_code":"PPL",
    "gn:name":"Masiakampy",
    "gn:population":0,
    "gn:timezone":"Indian/Antananarivo",
    "iso:country":"MG",
    "name:und_x_variant":[
        "Matsiakampy",
        "Masiakampy"
    ],
    "wof:name":"Masiakampy",
    "wof:placetype":"locality"
},
  "geometry": {"coordinates":[44.43333,-21.48333],"type":"Point"}
}