{
  "type": "Feature",
  "properties": {
    "gn:admin1_code":"02",
    "gn:asciiname":"Mahasoa",
    "gn:country_code":"MG",
    "gn:dem":839,
    "gn:feature_class":"P",
    "gn:feature_code":"PPL",
    "gn:name":"Mahasoa",
    "gn:population":0,
    "gn:timezone":"Indian/Antananarivo",
    "iso:country":"MG",
    "name:fra_x_preferred":[
        "Mahasoa"
    ],
    "name:ita_x_preferred":[
        "Mahasoa"
    ],
    "name:mlg_x_preferred":[
        "Mahasoa"
    ],
    "name:nld_x_preferred":[
        "Mahasoa"
    ],
    "wof:name":"Mahasoa",
    "wof:placetype":"locality"
},
  "geometry": {"coordinates":[46.56667,-21.36667000000001],"type":"Point"}
}