{
  "type": "Feature",
  "properties": {
    "gn:admin1_code":"06",
    "gn:asciiname":"Analatelo",
    "gn:country_code":"MG",
    "gn:dem":82,
    "gn:feature_class":"P",
    "gn:feature_code":"PPL",
    "gn:name":"Analatelo",
    "gn:population":0,
    "gn:timezone":"Indian/Antananarivo",
    "iso:country":"MG",
    "wof:name":"Analatelo",
    "wof:placetype":"locality"
},
  "geometry": {"coordinates":[43.91667,-21.96667],"type":"Point"}
}