{
  "type": "Feature",
  "properties": {
    "gn:admin1_code":"2.0",
    "gn:asciiname":"Sahavatoana",
    "gn:cc2":"MG",
    "gn:country_code":"MG",
    "gn:dem":1256,
    "gn:feature_class":"P",
    "gn:feature_code":"PPL",
    "gn:name":"Sahavatoana",
    "gn:population":0,
    "gn:timezone":"Indian/Antananarivo",
    "iso:country":"MG",
    "name:und_x_variant":[
        "Savatoana",
        "Sahavatoana"
    ],
    "wof:name":"Sahavatoana",
    "wof:placetype":"locality"
},
  "geometry": {"coordinates":[46.75,-20.45],"type":"Point"}
}