{
  "type": "Feature",
  "properties": {
    "gn:admin1_code":"06",
    "gn:asciiname":"Ranomafana",
    "gn:country_code":"MG",
    "gn:dem":91,
    "gn:feature_class":"P",
    "gn:feature_code":"PPL",
    "gn:name":"Ranomafana",
    "gn:population":0,
    "gn:timezone":"Indian/Antananarivo",
    "iso:country":"MG",
    "name:fra_x_preferred":[
        "Ranomafana"
    ],
    "name:ita_x_preferred":[
        "Ranomafana"
    ],
    "name:mlg_x_preferred":[
        "Ranomafana"
    ],
    "name:nld_x_preferred":[
        "Ranomafana"
    ],
    "name:pol_x_preferred":[
        "Ranomafana"
    ],
    "wof:name":"Ranomafana",
    "wof:placetype":"locality"
},
  "geometry": {"coordinates":[46.95698,-24.56598],"type":"Point"}
}