{
  "type": "Feature",
  "properties": {
    "gn:admin1_code":"03",
    "gn:asciiname":"Ankilitoka",
    "gn:country_code":"MG",
    "gn:dem":278,
    "gn:feature_class":"P",
    "gn:feature_code":"PPL",
    "gn:name":"Ankilitoka",
    "gn:population":0,
    "gn:timezone":"Indian/Antananarivo",
    "iso:country":"MG",
    "wof:name":"Ankilitoka",
    "wof:placetype":"locality"
},
  "geometry": {"coordinates":[45.13333,-17.93332999999999],"type":"Point"}
}