{
  "type": "Feature",
  "properties": {
    "gn:admin1_code":"05",
    "gn:asciiname":"Ampanidralambo",
    "gn:country_code":"MG",
    "gn:dem":1454,
    "gn:feature_class":"P",
    "gn:feature_code":"PPL",
    "gn:name":"Ampanidralambo",
    "gn:population":0,
    "gn:timezone":"Indian/Antananarivo",
    "iso:country":"MG",
    "wof:name":"Ampanidralambo",
    "wof:placetype":"locality"
},
  "geometry": {"coordinates":[47.61667,-18.75],"type":"Point"}
}