{
  "type": "Feature",
  "properties": {
    "gn:admin1_code":"06",
    "gn:asciiname":"Ankalomboro",
    "gn:country_code":"MG",
    "gn:dem":425,
    "gn:feature_class":"P",
    "gn:feature_code":"PPL",
    "gn:name":"Ankalomboro",
    "gn:population":0,
    "gn:timezone":"Indian/Antananarivo",
    "iso:country":"MG",
    "wof:name":"Ankalomboro",
    "wof:placetype":"locality"
},
  "geometry": {"coordinates":[45.45,-24.43333],"type":"Point"}
}