{
  "type": "Feature",
  "properties": {
    "gn:admin1_code":"05",
    "gn:asciiname":"Ambalareketa",
    "gn:country_code":"MG",
    "gn:dem":1078,
    "gn:feature_class":"P",
    "gn:feature_code":"PPL",
    "gn:name":"Ambalareketa",
    "gn:population":0,
    "gn:timezone":"Indian/Antananarivo",
    "iso:country":"MG",
    "wof:name":"Ambalareketa",
    "wof:placetype":"locality"
},
  "geometry": {"coordinates":[46.58333,-19.75],"type":"Point"}
}