{
  "type": "Feature",
  "properties": {
    "gn:admin1_code":"06",
    "gn:asciiname":"Ambolofoty",
    "gn:cc2":"MG",
    "gn:country_code":"MG",
    "gn:dem":9,
    "gn:feature_class":"P",
    "gn:feature_code":"PPL",
    "gn:name":"Ambolofoty",
    "gn:population":0,
    "gn:timezone":"Indian/Antananarivo",
    "iso:country":"MG",
    "name:und_x_variant":[
        "Ambolofotsy",
        "Ambolofoty"
    ],
    "wof:name":"Ambolofoty",
    "wof:placetype":"locality"
},
  "geometry": {"coordinates":[43.86667,-23.53333],"type":"Point"}
}