{
  "type": "Feature",
  "properties": {
    "gn:asciiname":"Alakamisy Andrianovona",
    "gn:country_code":"MG",
    "gn:dem":1319,
    "gn:feature_class":"P",
    "gn:feature_code":"PPL",
    "gn:name":"Alakamisy Andrianovona",
    "gn:population":0,
    "gn:timezone":"Indian/Antananarivo",
    "iso:country":"MG",
    "wof:name":"Alakamisy Andrianovona",
    "wof:placetype":"locality"
},
  "geometry": {"coordinates":[46.75884,-19.72466],"type":"Point"}
}