{
  "type": "Feature",
  "properties": {
    "gn:admin1_code":"06",
    "gn:asciiname":"Anjoha",
    "gn:country_code":"MG",
    "gn:dem":155,
    "gn:feature_class":"P",
    "gn:feature_code":"PPL",
    "gn:name":"Anjoha",
    "gn:population":0,
    "gn:timezone":"Indian/Antananarivo",
    "iso:country":"MG",
    "wof:name":"Anjoha",
    "wof:placetype":"locality"
},
  "geometry": {"coordinates":[45.31667,-19.36667000000001],"type":"Point"}
}