{
  "type": "Feature",
  "properties": {
    "gn:admin1_code":"06",
    "gn:asciiname":"Benonoka",
    "gn:country_code":"MG",
    "gn:dem":543,
    "gn:feature_class":"P",
    "gn:feature_code":"PPL",
    "gn:name":"Benonoka",
    "gn:population":0,
    "gn:timezone":"Indian/Antananarivo",
    "iso:country":"MG",
    "wof:name":"Benonoka",
    "wof:placetype":"locality"
},
  "geometry": {"coordinates":[45.65,-24.15],"type":"Point"}
}