{
  "type": "Feature",
  "properties": {
    "gn:admin1_code":"05",
    "gn:asciiname":"Ambaniranotsilena",
    "gn:country_code":"MG",
    "gn:dem":1192,
    "gn:feature_class":"P",
    "gn:feature_code":"PPL",
    "gn:name":"Ambaniranotsilena",
    "gn:population":0,
    "gn:timezone":"Indian/Antananarivo",
    "iso:country":"MG",
    "wof:name":"Ambaniranotsilena",
    "wof:placetype":"locality"
},
  "geometry": {"coordinates":[46.53333,-18.56667],"type":"Point"}
}