{
  "type": "Feature",
  "properties": {
    "gn:admin1_code":"02",
    "gn:asciiname":"Ankarefobe",
    "gn:country_code":"MG",
    "gn:dem":270,
    "gn:feature_class":"P",
    "gn:feature_code":"PPL",
    "gn:name":"Ankarefobe",
    "gn:population":0,
    "gn:timezone":"Indian/Antananarivo",
    "iso:country":"MG",
    "wof:name":"Ankarefobe",
    "wof:placetype":"locality"
},
  "geometry": {"coordinates":[47.43333,-21.91667],"type":"Point"}
}