{
  "type": "Feature",
  "properties": {
    "gn:admin1_code":"4.0",
    "gn:asciiname":"Vohibaboaka",
    "gn:country_code":"MG",
    "gn:dem":100,
    "gn:feature_class":"P",
    "gn:feature_code":"PPL",
    "gn:name":"Vohibaboaka",
    "gn:population":0,
    "gn:timezone":"Indian/Antananarivo",
    "iso:country":"MG",
    "wof:name":"Vohibaboaka",
    "wof:placetype":"locality"
},
  "geometry": {"coordinates":[48.71667,-19.36667000000001],"type":"Point"}
}