{
  "type": "Feature",
  "properties": {
    "gn:admin1_code":"6.0",
    "gn:asciiname":"Voronkafatra",
    "gn:cc2":"MG",
    "gn:country_code":"MG",
    "gn:dem":802,
    "gn:feature_class":"P",
    "gn:feature_code":"PPL",
    "gn:name":"Voronkafatra",
    "gn:population":0,
    "gn:timezone":"Indian/Antananarivo",
    "iso:country":"MG",
    "name:und_x_variant":[
        "Vorokafitsa",
        "Voronkafotra",
        "Voronkafatra"
    ],
    "wof:name":"Voronkafatra",
    "wof:placetype":"locality"
},
  "geometry": {"coordinates":[45.93333,-23.48333],"type":"Point"}
}