{
  "type": "Feature",
  "properties": {
    "gn:admin1_code":"06",
    "gn:asciiname":"Bobaka",
    "gn:cc2":"MG",
    "gn:country_code":"MG",
    "gn:dem":34,
    "gn:feature_class":"P",
    "gn:feature_code":"PPL",
    "gn:name":"Bobaka",
    "gn:population":0,
    "gn:timezone":"Indian/Antananarivo",
    "iso:country":"MG",
    "name:und_x_variant":[
        "Bobaky",
        "Bobaka"
    ],
    "wof:name":"Bobaka",
    "wof:placetype":"locality"
},
  "geometry": {"coordinates":[46.76667,-25.05],"type":"Point"}
}