{
  "type": "Feature",
  "properties": {
    "gn:admin1_code":"04",
    "gn:asciiname":"Ambodivoahangy",
    "gn:country_code":"MG",
    "gn:dem":726,
    "gn:feature_class":"P",
    "gn:feature_code":"PPL",
    "gn:name":"Ambodivoahangy",
    "gn:population":0,
    "gn:timezone":"Indian/Antananarivo",
    "iso:country":"MG",
    "wof:name":"Ambodivoahangy",
    "wof:placetype":"locality"
},
  "geometry": {"coordinates":[48.58333,-18.73333],"type":"Point"}
}