{
  "type": "Feature",
  "properties": {
    "gn:admin1_code":"01",
    "gn:asciiname":"Belamandy",
    "gn:country_code":"MG",
    "gn:dem":104,
    "gn:feature_class":"P",
    "gn:feature_code":"PPL",
    "gn:name":"Belamandy",
    "gn:population":0,
    "gn:timezone":"Indian/Antananarivo",
    "iso:country":"MG",
    "wof:name":"Belamandy",
    "wof:placetype":"locality"
},
  "geometry": {"coordinates":[48.26251,-13.21856],"type":"Point"}
}