{
  "type": "Feature",
  "properties": {
    "gn:admin1_code":"05",
    "gn:asciiname":"Ambodirano Atsimo",
    "gn:country_code":"MG",
    "gn:dem":1480,
    "gn:feature_class":"P",
    "gn:feature_code":"PPL",
    "gn:name":"Ambodirano Atsimo",
    "gn:population":0,
    "gn:timezone":"Indian/Antananarivo",
    "iso:country":"MG",
    "wof:name":"Ambodirano Atsimo",
    "wof:placetype":"locality"
},
  "geometry": {"coordinates":[47.68333,-19.73333],"type":"Point"}
}