{
  "type": "Feature",
  "properties": {
    "gn:admin1_code":"03",
    "gn:asciiname":"Ambahita",
    "gn:country_code":"MG",
    "gn:dem":64,
    "gn:feature_class":"P",
    "gn:feature_code":"PPL",
    "gn:name":"Ambahita",
    "gn:population":0,
    "gn:timezone":"Indian/Antananarivo",
    "iso:country":"MG",
    "name:azb_x_preferred":[
        "\u0627\u0645\u0628\u0627\u0647\u06cc\u062a\u0627"
    ],
    "name:fas_x_preferred":[
        "\u0627\u0645\u0628\u0627\u0647\u06cc\u062a\u0627"
    ],
    "name:fra_x_preferred":[
        "Ambahita"
    ],
    "name:ita_x_preferred":[
        "Ambahita"
    ],
    "name:mlg_x_preferred":[
        "Ambahita"
    ],
    "name:nld_x_preferred":[
        "Ambahita"
    ],
    "wof:name":"Ambahita",
    "wof:placetype":"locality"
},
  "geometry": {"coordinates":[44.63333,-17.38332999999999],"type":"Point"}
}