{
  "type": "Feature",
  "properties": {
    "gn:admin1_code":"03",
    "gn:asciiname":"Andranovorimpanjava",
    "gn:country_code":"MG",
    "gn:dem":316,
    "gn:feature_class":"P",
    "gn:feature_code":"PPL",
    "gn:name":"Andranovorimpanjava",
    "gn:population":0,
    "gn:timezone":"Indian/Antananarivo",
    "iso:country":"MG",
    "wof:name":"Andranovorimpanjava",
    "wof:placetype":"locality"
},
  "geometry": {"coordinates":[45.31667,-17.83333],"type":"Point"}
}