{
  "type": "Feature",
  "properties": {
    "gn:admin1_code":"03",
    "gn:asciiname":"Antsahabe",
    "gn:country_code":"MG",
    "gn:dem":947,
    "gn:feature_class":"P",
    "gn:feature_code":"PPL",
    "gn:name":"Antsahabe",
    "gn:population":0,
    "gn:timezone":"Indian/Antananarivo",
    "iso:country":"MG",
    "wof:name":"Antsahabe",
    "wof:placetype":"locality"
},
  "geometry": {"coordinates":[47.63333,-17.81667000000001],"type":"Point"}
}