{
  "type": "Feature",
  "properties": {
    "gn:admin1_code":"06",
    "gn:asciiname":"Ambinany",
    "gn:country_code":"MG",
    "gn:dem":621,
    "gn:feature_class":"P",
    "gn:feature_code":"PPL",
    "gn:name":"Ambinany",
    "gn:population":0,
    "gn:timezone":"Indian/Antananarivo",
    "iso:country":"MG",
    "name:azb_x_preferred":[
        "\u0627\u0645\u0628\u06cc\u0646\u0627\u0646\u06cc"
    ],
    "name:fas_x_preferred":[
        "\u0627\u0645\u0628\u06cc\u0646\u0627\u0646\u06cc"
    ],
    "name:fra_x_preferred":[
        "Ambinany"
    ],
    "name:ita_x_preferred":[
        "Ambinany"
    ],
    "name:mlg_x_preferred":[
        "Ambinany"
    ],
    "name:nld_x_preferred":[
        "Ambinany"
    ],
    "name:zho_x_preferred":[
        "\u5b89\u6bd4\u7d0d\u5c3c"
    ],
    "wof:name":"Ambinany",
    "wof:placetype":"locality"
},
  "geometry": {"coordinates":[45.65,-23.65],"type":"Point"}
}