{
  "type": "Feature",
  "properties": {
    "gn:admin1_code":"2.0",
    "gn:asciiname":"Solila",
    "gn:cc2":"MG",
    "gn:country_code":"MG",
    "gn:dem":779,
    "gn:feature_class":"P",
    "gn:feature_code":"PPL",
    "gn:name":"Solila",
    "gn:population":0,
    "gn:timezone":"Indian/Antananarivo",
    "iso:country":"MG",
    "name:fra_x_preferred":[
        "Solila"
    ],
    "name:ita_x_preferred":[
        "Solila"
    ],
    "name:mlg_x_preferred":[
        "Solila"
    ],
    "name:nld_x_preferred":[
        "Solila"
    ],
    "name:und_x_variant":[
        "Solla"
    ],
    "wof:name":"Solila",
    "wof:placetype":"locality"
},
  "geometry": {"coordinates":[46.61667,-21.41667],"type":"Point"}
}