{
  "type": "Feature",
  "properties": {
    "gn:admin1_code":"05",
    "gn:asciiname":"Ambalavato",
    "gn:country_code":"MG",
    "gn:dem":1286,
    "gn:feature_class":"P",
    "gn:feature_code":"PPL",
    "gn:name":"Ambalavato",
    "gn:population":0,
    "gn:timezone":"Indian/Antananarivo",
    "iso:country":"MG",
    "name:azb_x_preferred":[
        "\u0627\u0645\u0628\u0627\u0644\u0627\u0648\u0627\u062a\u0648"
    ],
    "name:fas_x_preferred":[
        "\u0627\u0645\u0628\u0627\u0644\u0627\u0648\u0627\u062a\u0648"
    ],
    "name:fra_x_preferred":[
        "Ambalavato"
    ],
    "name:ita_x_preferred":[
        "Ambalavato"
    ],
    "name:mlg_x_preferred":[
        "Ambalavato"
    ],
    "name:nld_x_preferred":[
        "Ambalavato"
    ],
    "wof:name":"Ambalavato",
    "wof:placetype":"locality"
},
  "geometry": {"coordinates":[46.63333,-19.93333],"type":"Point"}
}