{
  "type": "Feature",
  "properties": {
    "gn:admin1_code":"03",
    "gn:asciiname":"Belambo",
    "gn:country_code":"MG",
    "gn:dem":140,
    "gn:feature_class":"P",
    "gn:feature_code":"PPL",
    "gn:name":"Belambo",
    "gn:population":0,
    "gn:timezone":"Indian/Antananarivo",
    "iso:country":"MG",
    "name:ceb_x_preferred":[
        "Belambo"
    ],
    "name:ita_x_preferred":[
        "Belambo"
    ],
    "name:nld_x_preferred":[
        "Belambo"
    ],
    "name:swe_x_preferred":[
        "Belambo"
    ],
    "wof:name":"Belambo",
    "wof:placetype":"locality"
},
  "geometry": {"coordinates":[46.26667,-16.58333],"type":"Point"}
}