{
  "type": "Feature",
  "properties": {
    "gn:admin1_code":"06",
    "gn:asciiname":"Besaonjo",
    "gn:country_code":"MG",
    "gn:dem":360,
    "gn:feature_class":"P",
    "gn:feature_code":"PPL",
    "gn:name":"Besaonjo",
    "gn:population":0,
    "gn:timezone":"Indian/Antananarivo",
    "iso:country":"MG",
    "wof:name":"Besaonjo",
    "wof:placetype":"locality"
},
  "geometry": {"coordinates":[44.91667,-24.36667000000001],"type":"Point"}
}