{
  "type": "Feature",
  "properties": {
    "gn:admin1_code":"6.0",
    "gn:asciiname":"Taflamena",
    "gn:country_code":"MG",
    "gn:dem":212,
    "gn:feature_class":"P",
    "gn:feature_code":"PPL",
    "gn:name":"Taflamena",
    "gn:population":0,
    "gn:timezone":"Indian/Antananarivo",
    "iso:country":"MG",
    "wof:name":"Taflamena",
    "wof:placetype":"locality"
},
  "geometry": {"coordinates":[45.01667,-24.75],"type":"Point"}
}