{
  "type": "Feature",
  "properties": {
    "gn:admin1_code":"06",
    "gn:asciiname":"Ankilivalokely",
    "gn:cc2":"MG",
    "gn:country_code":"MG",
    "gn:dem":505,
    "gn:feature_class":"P",
    "gn:feature_code":"PPL",
    "gn:name":"Ankilivalokely",
    "gn:population":0,
    "gn:timezone":"Indian/Antananarivo",
    "iso:country":"MG",
    "name:und_x_variant":[
        "Ankllivalokely",
        "Ankilivalokely"
    ],
    "wof:name":"Ankilivalokely",
    "wof:placetype":"locality"
},
  "geometry": {"coordinates":[44.95,-22.25],"type":"Point"}
}