{
  "type": "Feature",
  "properties": {
    "gn:admin1_code":"03",
    "gn:asciiname":"Keliloha",
    "gn:cc2":"MG",
    "gn:country_code":"MG",
    "gn:dem":657,
    "gn:feature_class":"P",
    "gn:feature_code":"PPL",
    "gn:name":"Keliloha",
    "gn:population":0,
    "gn:timezone":"Indian/Antananarivo",
    "iso:country":"MG",
    "name:und_x_variant":[
        "Ikeliloha",
        "Keliloha"
    ],
    "wof:name":"Keliloha",
    "wof:placetype":"locality"
},
  "geometry": {"coordinates":[47.66667,-17.26667],"type":"Point"}
}