{
  "type": "Feature",
  "properties": {
    "gn:admin1_code":"2.0",
    "gn:asciiname":"Volafotsy",
    "gn:country_code":"MG",
    "gn:dem":1130,
    "gn:feature_class":"P",
    "gn:feature_code":"PPL",
    "gn:name":"Volafotsy",
    "gn:population":0,
    "gn:timezone":"Indian/Antananarivo",
    "iso:country":"MG",
    "wof:name":"Volafotsy",
    "wof:placetype":"locality"
},
  "geometry": {"coordinates":[47.01667,-21.81667],"type":"Point"}
}