{
  "type": "Feature",
  "properties": {
    "gn:admin1_code":"06",
    "gn:asciiname":"Lahaveloka",
    "gn:cc2":"MG",
    "gn:country_code":"MG",
    "gn:dem":75,
    "gn:feature_class":"P",
    "gn:feature_code":"PPL",
    "gn:name":"Lahaveloka",
    "gn:population":0,
    "gn:timezone":"Indian/Antananarivo",
    "iso:country":"MG",
    "name:und_x_variant":[
        "Lavaheloka",
        "Lahaveloka"
    ],
    "wof:name":"Lahaveloka",
    "wof:placetype":"locality"
},
  "geometry": {"coordinates":[44.91667,-19.91667],"type":"Point"}
}