{
  "type": "Feature",
  "properties": {
    "gn:admin1_code":"03",
    "gn:asciiname":"Beanambalazana",
    "gn:country_code":"MG",
    "gn:dem":650,
    "gn:feature_class":"P",
    "gn:feature_code":"PPL",
    "gn:name":"Beanambalazana",
    "gn:population":0,
    "gn:timezone":"Indian/Antananarivo",
    "iso:country":"MG",
    "wof:name":"Beanambalazana",
    "wof:placetype":"locality"
},
  "geometry": {"coordinates":[47.98333,-17.11667000000001],"type":"Point"}
}