{
  "type": "Feature",
  "properties": {
    "gn:admin1_code":"04",
    "gn:asciiname":"Mariarano",
    "gn:country_code":"MG",
    "gn:dem":10,
    "gn:feature_class":"P",
    "gn:feature_code":"PPL",
    "gn:name":"Mariarano",
    "gn:population":0,
    "gn:timezone":"Indian/Antananarivo",
    "iso:country":"MG",
    "wof:name":"Mariarano",
    "wof:placetype":"locality"
},
  "geometry": {"coordinates":[49.63333,-15.35],"type":"Point"}
}