{
  "type": "Feature",
  "properties": {
    "gn:admin1_code":"05",
    "gn:asciiname":"Antanimboanjo",
    "gn:country_code":"MG",
    "gn:dem":1062,
    "gn:feature_class":"P",
    "gn:feature_code":"PPL",
    "gn:name":"Antanimboanjo",
    "gn:population":0,
    "gn:timezone":"Indian/Antananarivo",
    "iso:country":"MG",
    "wof:name":"Antanimboanjo",
    "wof:placetype":"locality"
},
  "geometry": {"coordinates":[47.75,-18.28333],"type":"Point"}
}