{
  "type": "Feature",
  "properties": {
    "gn:admin1_code":"4.0",
    "gn:asciiname":"Tanambao II",
    "gn:cc2":"MG",
    "gn:country_code":"MG",
    "gn:dem":468,
    "gn:feature_class":"P",
    "gn:feature_code":"PPL",
    "gn:name":"Tanambao II",
    "gn:population":0,
    "gn:timezone":"Indian/Antananarivo",
    "iso:country":"MG",
    "name:und_x_variant":[
        "Tanambao",
        "Tanambao II"
    ],
    "wof:name":"Tanambao II",
    "wof:placetype":"locality"
},
  "geometry": {"coordinates":[48.21667,-20.28333],"type":"Point"}
}