{
  "type": "Feature",
  "properties": {
    "gn:admin1_code":"6.0",
    "gn:asciiname":"Tanile",
    "gn:cc2":"MG",
    "gn:country_code":"MG",
    "gn:dem":386,
    "gn:feature_class":"P",
    "gn:feature_code":"PPL",
    "gn:name":"Tanile",
    "gn:population":0,
    "gn:timezone":"Indian/Antananarivo",
    "iso:country":"MG",
    "name:und_x_variant":[
        "Tanilehy",
        "Tanile"
    ],
    "wof:name":"Tanile",
    "wof:placetype":"locality"
},
  "geometry": {"coordinates":[44.31667,-23.23333],"type":"Point"}
}