{
  "type": "Feature",
  "properties": {
    "gn:admin1_code":"03",
    "gn:asciiname":"Ankilahila",
    "gn:country_code":"MG",
    "gn:dem":28,
    "gn:feature_class":"P",
    "gn:feature_code":"PPL",
    "gn:name":"Ankilahila",
    "gn:population":0,
    "gn:timezone":"Indian/Antananarivo",
    "iso:country":"MG",
    "wof:name":"Ankilahila",
    "wof:placetype":"locality"
},
  "geometry": {"coordinates":[46.71667,-16.43333],"type":"Point"}
}