{
  "type": "Feature",
  "properties": {
    "gn:admin1_code":"06",
    "gn:asciiname":"Ambahifrakoa",
    "gn:cc2":"MG",
    "gn:country_code":"MG",
    "gn:dem":87,
    "gn:feature_class":"P",
    "gn:feature_code":"PPL",
    "gn:name":"Ambahifrakoa",
    "gn:population":0,
    "gn:timezone":"Indian/Antananarivo",
    "iso:country":"MG",
    "name:und_x_variant":[
        "Ambahitrakoa",
        "Ambahifrakoa"
    ],
    "wof:name":"Ambahifrakoa",
    "wof:placetype":"locality"
},
  "geometry": {"coordinates":[44.85,-19.81667],"type":"Point"}
}