{
  "type": "Feature",
  "properties": {
    "gn:admin1_code":"03",
    "gn:asciiname":"Antsohermakanga",
    "gn:cc2":"MG",
    "gn:country_code":"MG",
    "gn:dem":30,
    "gn:feature_class":"P",
    "gn:feature_code":"PPL",
    "gn:name":"Antsohermakanga",
    "gn:population":0,
    "gn:timezone":"Indian/Antananarivo",
    "iso:country":"MG",
    "name:und_x_variant":[
        "Antsoherinakanga",
        "Antsohermakanga"
    ],
    "wof:name":"Antsohermakanga",
    "wof:placetype":"locality"
},
  "geometry": {"coordinates":[46.91667,-16.46667],"type":"Point"}
}