{
  "type": "Feature",
  "properties": {
    "gn:admin1_code":"05",
    "gn:asciiname":"Anosiarivo",
    "gn:country_code":"MG",
    "gn:dem":1462,
    "gn:feature_class":"P",
    "gn:feature_code":"PPL",
    "gn:name":"Anosiarivo",
    "gn:population":0,
    "gn:timezone":"Indian/Antananarivo",
    "iso:country":"MG",
    "wof:name":"Anosiarivo",
    "wof:placetype":"locality"
},
  "geometry": {"coordinates":[47.03333,-19.91667],"type":"Point"}
}