{
  "type": "Feature",
  "properties": {
    "gn:admin1_code":"01",
    "gn:asciiname":"Ampopo",
    "gn:cc2":"MG",
    "gn:country_code":"MG",
    "gn:dem":212,
    "gn:feature_class":"P",
    "gn:feature_code":"PPL",
    "gn:name":"Ampopo",
    "gn:population":0,
    "gn:timezone":"Indian/Antananarivo",
    "iso:country":"MG",
    "name:und_x_variant":[
        "Ampaopao",
        "Ampopo"
    ],
    "wof:name":"Ampopo",
    "wof:placetype":"locality"
},
  "geometry": {"coordinates":[48.05,-13.71667],"type":"Point"}
}