{
  "type": "Feature",
  "properties": {
    "gn:admin1_code":"06",
    "gn:asciiname":"Asosa",
    "gn:country_code":"MG",
    "gn:dem":348,
    "gn:feature_class":"P",
    "gn:feature_code":"PPL",
    "gn:name":"Asosa",
    "gn:population":0,
    "gn:timezone":"Indian/Antananarivo",
    "iso:country":"MG",
    "name:amh_x_preferred":[
        "\u12a0\u1236\u1233"
    ],
    "name:bel_x_preferred":[
        "\u0410\u0441\u043e\u0441\u0430"
    ],
    "name:ceb_x_preferred":[
        "\u0100sosa"
    ],
    "name:deu_x_preferred":[
        "Asosa"
    ],
    "name:ell_x_preferred":[
        "\u0391\u03c3\u03cc\u03c3\u03b1"
    ],
    "name:fra_x_preferred":[
        "Asosa"
    ],
    "name:hrv_x_preferred":[
        "Asosa"
    ],
    "name:ita_x_preferred":[
        "Asosa"
    ],
    "name:kat_x_preferred":[
        "\u10d0\u10e1\u10dd\u10e1\u10d0"
    ],
    "name:kor_x_preferred":[
        "\uc544\uc18c\uc0ac"
    ],
    "name:nld_x_preferred":[
        "Asosa"
    ],
    "name:nno_x_preferred":[
        "Asosa"
    ],
    "name:pol_x_preferred":[
        "Asosa"
    ],
    "name:ron_x_preferred":[
        "Asosa"
    ],
    "name:rus_x_preferred":[
        "\u0410\u0441\u043e\u0441\u0430"
    ],
    "name:spa_x_preferred":[
        "Asosa"
    ],
    "name:srp_x_preferred":[
        "\u0410\u0441\u043e\u0441\u0430"
    ],
    "name:swe_x_preferred":[
        "Asosa"
    ],
    "name:urd_x_preferred":[
        "\u0627\u0633\u0648\u0633\u0627"
    ],
    "name:zho_x_preferred":[
        "\u963f\u7d22\u8428"
    ],
    "wof:name":"Asosa",
    "wof:placetype":"locality"
},
  "geometry": {"coordinates":[45.16667,-24.41667],"type":"Point"}
}