{
  "type": "Feature",
  "properties": {
    "gn:admin1_code":"06",
    "gn:asciiname":"Asosa",
    "gn:country_code":"MG",
    "gn:dem":348,
    "gn:feature_class":"P",
    "gn:feature_code":"PPL",
    "gn:name":"Asosa",
    "gn:population":0,
    "gn:timezone":"Indian/Antananarivo",
    "iso:country":"MG",
    "wof:name":"Asosa",
    "wof:placetype":"locality"
},
  "geometry": {"coordinates":[45.16667,-24.41667],"type":"Point"}
}