{
  "type": "Feature",
  "properties": {
    "gn:admin1_code":"05",
    "gn:asciiname":"Antambono",
    "gn:country_code":"MG",
    "gn:dem":1598,
    "gn:feature_class":"P",
    "gn:feature_code":"PPL",
    "gn:name":"Antambono",
    "gn:population":0,
    "gn:timezone":"Indian/Antananarivo",
    "iso:country":"MG",
    "wof:name":"Antambono",
    "wof:placetype":"locality"
},
  "geometry": {"coordinates":[47.48333,-19.66667],"type":"Point"}
}