{
  "type": "Feature",
  "properties": {
    "gn:admin1_code":"06",
    "gn:asciiname":"Ambohibe",
    "gn:country_code":"MG",
    "gn:dem":3,
    "gn:feature_class":"P",
    "gn:feature_code":"PPL",
    "gn:name":"Ambohibe",
    "gn:population":0,
    "gn:timezone":"Indian/Antananarivo",
    "iso:country":"MG",
    "name:azb_x_preferred":[
        "\u0627\u0645\u0628\u0648\u0647\u06cc\u0628"
    ],
    "name:fas_x_preferred":[
        "\u0627\u0645\u0628\u0648\u0647\u06cc\u0628"
    ],
    "name:fra_x_preferred":[
        "Ambohibe"
    ],
    "name:ita_x_preferred":[
        "Ambohibe"
    ],
    "name:mlg_x_preferred":[
        "Ambohibe"
    ],
    "name:nld_x_preferred":[
        "Ambohibe"
    ],
    "wof:name":"Ambohibe",
    "wof:placetype":"locality"
},
  "geometry": {"coordinates":[43.51667,-21.35],"type":"Point"}
}