{
  "type": "Feature",
  "properties": {
    "gn:admin1_code":"06",
    "gn:asciiname":"Ankofa",
    "gn:country_code":"MG",
    "gn:dem":12,
    "gn:feature_class":"P",
    "gn:feature_code":"PPL",
    "gn:name":"Ankofa",
    "gn:population":0,
    "gn:timezone":"Indian/Antananarivo",
    "iso:country":"MG",
    "wof:name":"Ankofa",
    "wof:placetype":"locality"
},
  "geometry": {"coordinates":[46.98333,-24.93333],"type":"Point"}
}