{
  "type": "Feature",
  "properties": {
    "gn:admin1_code":"06",
    "gn:asciiname":"Kintso",
    "gn:cc2":"MG",
    "gn:country_code":"MG",
    "gn:dem":104,
    "gn:feature_class":"P",
    "gn:feature_code":"PPL",
    "gn:name":"Kintso",
    "gn:population":0,
    "gn:timezone":"Indian/Antananarivo",
    "iso:country":"MG",
    "name:und_x_variant":[
        "Kinlso",
        "Kintso"
    ],
    "wof:name":"Kintso",
    "wof:placetype":"locality"
},
  "geometry": {"coordinates":[46.06667,-24.61667000000001],"type":"Point"}
}