{
  "type": "Feature",
  "properties": {
    "gn:admin1_code":"05",
    "gn:asciiname":"Amparihisoa",
    "gn:country_code":"MG",
    "gn:dem":870,
    "gn:feature_class":"P",
    "gn:feature_code":"PPL",
    "gn:name":"Amparihisoa",
    "gn:population":0,
    "gn:timezone":"Indian/Antananarivo",
    "iso:country":"MG",
    "wof:name":"Amparihisoa",
    "wof:placetype":"locality"
},
  "geometry": {"coordinates":[46.08333,-18.65],"type":"Point"}
}