{
  "type": "Feature",
  "properties": {
    "gn:admin1_code":"02",
    "gn:asciiname":"Mandroso",
    "gn:country_code":"MG",
    "gn:dem":1032,
    "gn:feature_class":"P",
    "gn:feature_code":"PPL",
    "gn:name":"Mandroso",
    "gn:population":0,
    "gn:timezone":"Indian/Antananarivo",
    "iso:country":"MG",
    "wof:name":"Mandroso",
    "wof:placetype":"locality"
},
  "geometry": {"coordinates":[46.95,-21.03333],"type":"Point"}
}