{
  "type": "Feature",
  "properties": {
    "gn:admin1_code":"04",
    "gn:asciiname":"Makoina",
    "gn:cc2":"MG",
    "gn:country_code":"MG",
    "gn:dem":469,
    "gn:feature_class":"P",
    "gn:feature_code":"PPL",
    "gn:name":"Makoina",
    "gn:population":0,
    "gn:timezone":"Indian/Antananarivo",
    "iso:country":"MG",
    "name:und_x_variant":[
        "Makoino",
        "Makoina"
    ],
    "wof:name":"Makoina",
    "wof:placetype":"locality"
},
  "geometry": {"coordinates":[48.23333,-16.41667],"type":"Point"}
}