{
  "type": "Feature",
  "properties": {
    "gn:admin1_code":"6.0",
    "gn:asciiname":"Sakahala",
    "gn:country_code":"MG",
    "gn:dem":276,
    "gn:feature_class":"P",
    "gn:feature_code":"PPL",
    "gn:name":"Sakahala",
    "gn:population":0,
    "gn:timezone":"Indian/Antananarivo",
    "iso:country":"MG",
    "wof:name":"Sakahala",
    "wof:placetype":"locality"
},
  "geometry": {"coordinates":[46.95,-24.38333],"type":"Point"}
}