{
  "type": "Feature",
  "properties": {
    "gn:admin1_code":"02",
    "gn:asciiname":"Antarambiby",
    "gn:country_code":"MG",
    "gn:dem":1106,
    "gn:feature_class":"P",
    "gn:feature_code":"PPL",
    "gn:name":"Antarambiby",
    "gn:population":0,
    "gn:timezone":"Indian/Antananarivo",
    "iso:country":"MG",
    "wof:name":"Antarambiby",
    "wof:placetype":"locality"
},
  "geometry": {"coordinates":[47.33333,-21.65],"type":"Point"}
}