{
  "type": "Feature",
  "properties": {
    "gn:admin1_code":"03",
    "gn:asciiname":"Bemololo",
    "gn:country_code":"MG",
    "gn:dem":640,
    "gn:feature_class":"P",
    "gn:feature_code":"PPL",
    "gn:name":"Bemololo",
    "gn:population":0,
    "gn:timezone":"Indian/Antananarivo",
    "iso:country":"MG",
    "wof:name":"Bemololo",
    "wof:placetype":"locality"
},
  "geometry": {"coordinates":[47.73333,-17.35],"type":"Point"}
}