{
  "type": "Feature",
  "properties": {
    "gn:admin1_code":"02",
    "gn:asciiname":"Ambondrobe",
    "gn:country_code":"MG",
    "gn:dem":917,
    "gn:feature_class":"P",
    "gn:feature_code":"PPL",
    "gn:name":"Ambondrobe",
    "gn:population":0,
    "gn:timezone":"Indian/Antananarivo",
    "iso:country":"MG",
    "wof:name":"Ambondrobe",
    "wof:placetype":"locality"
},
  "geometry": {"coordinates":[45.58333,-22.66667],"type":"Point"}
}