{
  "type": "Feature",
  "properties": {
    "gn:admin1_code":"2.0",
    "gn:asciiname":"Tsiazombily",
    "gn:country_code":"MG",
    "gn:dem":368,
    "gn:feature_class":"P",
    "gn:feature_code":"PPL",
    "gn:name":"Tsiazombily",
    "gn:population":0,
    "gn:timezone":"Indian/Antananarivo",
    "iso:country":"MG",
    "wof:name":"Tsiazombily",
    "wof:placetype":"locality"
},
  "geometry": {"coordinates":[48.31667,-20.43333],"type":"Point"}
}