{
  "type": "Feature",
  "properties": {
    "gn:admin1_code":"01",
    "gn:asciiname":"Maromokotsa",
    "gn:country_code":"MG",
    "gn:dem":12,
    "gn:feature_class":"P",
    "gn:feature_code":"PPL",
    "gn:name":"Maromokotsa",
    "gn:population":0,
    "gn:timezone":"Indian/Antananarivo",
    "iso:country":"MG",
    "wof:name":"Maromokotsa",
    "wof:placetype":"locality"
},
  "geometry": {"coordinates":[48.83333,-13.38333],"type":"Point"}
}