{
  "type": "Feature",
  "properties": {
    "gn:admin1_code":"02",
    "gn:asciiname":"Anjoho",
    "gn:country_code":"MG",
    "gn:dem":921,
    "gn:feature_class":"P",
    "gn:feature_code":"PPL",
    "gn:name":"Anjoho",
    "gn:population":0,
    "gn:timezone":"Indian/Antananarivo",
    "iso:country":"MG",
    "wof:name":"Anjoho",
    "wof:placetype":"locality"
},
  "geometry": {"coordinates":[46.68333,-23.71667],"type":"Point"}
}