{
  "type": "Feature",
  "properties": {
    "gn:admin1_code":"04",
    "gn:asciiname":"Antalaviana",
    "gn:country_code":"MG",
    "gn:dem":1007,
    "gn:feature_class":"P",
    "gn:feature_code":"PPL",
    "gn:name":"Antalaviana",
    "gn:population":0,
    "gn:timezone":"Indian/Antananarivo",
    "iso:country":"MG",
    "wof:name":"Antalaviana",
    "wof:placetype":"locality"
},
  "geometry": {"coordinates":[48.73333,-17.86667000000001],"type":"Point"}
}