{
  "type": "Feature",
  "properties": {
    "gn:admin1_code":"06",
    "gn:asciiname":"Bejaha",
    "gn:country_code":"MG",
    "gn:dem":268,
    "gn:feature_class":"P",
    "gn:feature_code":"PPL",
    "gn:name":"Bejaha",
    "gn:population":0,
    "gn:timezone":"Indian/Antananarivo",
    "iso:country":"MG",
    "wof:name":"Bejaha",
    "wof:placetype":"locality"
},
  "geometry": {"coordinates":[45.15,-21.88333],"type":"Point"}
}