{
  "type": "Feature",
  "properties": {
    "gn:admin1_code":"2.0",
    "gn:asciiname":"Tsiandalovana",
    "gn:country_code":"MG",
    "gn:dem":607,
    "gn:feature_class":"P",
    "gn:feature_code":"PPL",
    "gn:name":"Tsiandalovana",
    "gn:population":0,
    "gn:timezone":"Indian/Antananarivo",
    "iso:country":"MG",
    "wof:name":"Tsiandalovana",
    "wof:placetype":"locality"
},
  "geometry": {"coordinates":[46.96667,-23.01667],"type":"Point"}
}