{
  "type": "Feature",
  "properties": {
    "gn:admin1_code":"02",
    "gn:asciiname":"Andranomavo",
    "gn:country_code":"MG",
    "gn:dem":585,
    "gn:feature_class":"P",
    "gn:feature_code":"PPL",
    "gn:name":"Andranomavo",
    "gn:population":0,
    "gn:timezone":"Indian/Antananarivo",
    "iso:country":"MG",
    "name:fra_x_preferred":[
        "Andranomavo"
    ],
    "name:ita_x_preferred":[
        "Andranomavo"
    ],
    "name:mlg_x_preferred":[
        "Andranomavo"
    ],
    "name:nld_x_preferred":[
        "Andranomavo"
    ],
    "wof:name":"Andranomavo",
    "wof:placetype":"locality"
},
  "geometry": {"coordinates":[46.01667,-20.93333],"type":"Point"}
}