{
  "type": "Feature",
  "properties": {
    "gn:admin1_code":"01",
    "gn:asciiname":"Bekalamaka",
    "gn:country_code":"MG",
    "gn:dem":441,
    "gn:feature_class":"P",
    "gn:feature_code":"PPL",
    "gn:name":"Bekalamaka",
    "gn:population":0,
    "gn:timezone":"Indian/Antananarivo",
    "iso:country":"MG",
    "wof:name":"Bekalamaka",
    "wof:placetype":"locality"
},
  "geometry": {"coordinates":[49.66667,-14.15],"type":"Point"}
}