{
  "type": "Feature",
  "properties": {
    "gn:admin1_code":"05",
    "gn:asciiname":"Mananetivohitra",
    "gn:country_code":"MG",
    "gn:dem":1632,
    "gn:feature_class":"P",
    "gn:feature_code":"PPL",
    "gn:name":"Mananetivohitra",
    "gn:population":0,
    "gn:timezone":"Indian/Antananarivo",
    "iso:country":"MG",
    "wof:name":"Mananetivohitra",
    "wof:placetype":"locality"
},
  "geometry": {"coordinates":[46.83333,-19.41667],"type":"Point"}
}