{
  "type": "Feature",
  "properties": {
    "gn:admin1_code":"06",
    "gn:asciiname":"Ampanambato",
    "gn:country_code":"MG",
    "gn:dem":356,
    "gn:feature_class":"P",
    "gn:feature_code":"PPL",
    "gn:name":"Ampanambato",
    "gn:population":0,
    "gn:timezone":"Indian/Antananarivo",
    "iso:country":"MG",
    "wof:name":"Ampanambato",
    "wof:placetype":"locality"
},
  "geometry": {"coordinates":[45.25,-22.15],"type":"Point"}
}