{
  "type": "Feature",
  "properties": {
    "gn:admin1_code":"01",
    "gn:asciiname":"Andrafia",
    "gn:country_code":"MG",
    "gn:dem":46,
    "gn:feature_class":"P",
    "gn:feature_code":"PPL",
    "gn:name":"Andrafia",
    "gn:population":0,
    "gn:timezone":"Indian/Antananarivo",
    "iso:country":"MG",
    "wof:name":"Andrafia",
    "wof:placetype":"locality"
},
  "geometry": {"coordinates":[48.91667,-12.71667],"type":"Point"}
}