{
  "type": "Feature",
  "properties": {
    "gn:admin1_code":"05",
    "gn:asciiname":"Antsatrana",
    "gn:country_code":"MG",
    "gn:dem":740,
    "gn:feature_class":"P",
    "gn:feature_code":"PPL",
    "gn:name":"Antsatrana",
    "gn:population":0,
    "gn:timezone":"Indian/Antananarivo",
    "iso:country":"MG",
    "wof:name":"Antsatrana",
    "wof:placetype":"locality"
},
  "geometry": {"coordinates":[46.73333,-17.83333],"type":"Point"}
}