{
  "type": "Feature",
  "properties": {
    "gn:admin1_code":"03",
    "gn:asciiname":"Analabe",
    "gn:country_code":"MG",
    "gn:dem":1081,
    "gn:feature_class":"P",
    "gn:feature_code":"PPL",
    "gn:name":"Analabe",
    "gn:population":0,
    "gn:timezone":"Indian/Antananarivo",
    "iso:country":"MG",
    "wof:name":"Analabe",
    "wof:placetype":"locality"
},
  "geometry": {"coordinates":[48.88333,-14.58333],"type":"Point"}
}