{
  "type": "Feature",
  "properties": {
    "gn:admin1_code":"06",
    "gn:asciiname":"Bekopaka",
    "gn:country_code":"MG",
    "gn:dem":137,
    "gn:feature_class":"P",
    "gn:feature_code":"PPL",
    "gn:name":"Bekopaka",
    "gn:population":0,
    "gn:timezone":"Indian/Antananarivo",
    "iso:country":"MG",
    "name:deu_x_preferred":[
        "Bekopaka"
    ],
    "name:fra_x_preferred":[
        "Bekopaka"
    ],
    "name:nld_x_preferred":[
        "Bekopaka"
    ],
    "name:pol_x_preferred":[
        "Bekopaka"
    ],
    "wof:name":"Bekopaka",
    "wof:placetype":"locality"
},
  "geometry": {"coordinates":[45.33333,-19.31667],"type":"Point"}
}