{
  "type": "Feature",
  "properties": {
    "gn:admin1_code":"05",
    "gn:asciiname":"Ankatsaka",
    "gn:country_code":"MG",
    "gn:dem":378,
    "gn:feature_class":"P",
    "gn:feature_code":"PPL",
    "gn:name":"Ankatsaka",
    "gn:population":0,
    "gn:timezone":"Indian/Antananarivo",
    "iso:country":"MG",
    "wof:name":"Ankatsaka",
    "wof:placetype":"locality"
},
  "geometry": {"coordinates":[45.71667,-19.71667],"type":"Point"}
}