{
  "type": "Feature",
  "properties": {
    "gn:admin1_code":"06",
    "gn:asciiname":"Analamaiky",
    "gn:country_code":"MG",
    "gn:dem":305,
    "gn:feature_class":"P",
    "gn:feature_code":"PPL",
    "gn:name":"Analamaiky",
    "gn:population":0,
    "gn:timezone":"Indian/Antananarivo",
    "iso:country":"MG",
    "wof:name":"Analamaiky",
    "wof:placetype":"locality"
},
  "geometry": {"coordinates":[44.48333,-22.15],"type":"Point"}
}