{
  "type": "Feature",
  "properties": {
    "gn:admin1_code":"06",
    "gn:asciiname":"Ambasy",
    "gn:country_code":"MG",
    "gn:dem":126,
    "gn:feature_class":"P",
    "gn:feature_code":"PPL",
    "gn:name":"Ambasy",
    "gn:population":0,
    "gn:timezone":"Indian/Antananarivo",
    "iso:country":"MG",
    "wof:name":"Ambasy",
    "wof:placetype":"locality"
},
  "geometry": {"coordinates":[45.86667,-25.33333],"type":"Point"}
}