{
  "type": "Feature",
  "properties": {
    "gn:admin1_code":"02",
    "gn:asciiname":"Maroantova",
    "gn:country_code":"MG",
    "gn:dem":125,
    "gn:feature_class":"P",
    "gn:feature_code":"PPL",
    "gn:name":"Maroantova",
    "gn:population":0,
    "gn:timezone":"Indian/Antananarivo",
    "iso:country":"MG",
    "wof:name":"Maroantova",
    "wof:placetype":"locality"
},
  "geometry": {"coordinates":[48.08333,-20.75],"type":"Point"}
}