{
  "type": "Feature",
  "properties": {
    "gn:admin1_code":"03",
    "gn:asciiname":"Ambalanomby",
    "gn:country_code":"MG",
    "gn:dem":341,
    "gn:feature_class":"P",
    "gn:feature_code":"PPL",
    "gn:name":"Ambalanomby",
    "gn:population":0,
    "gn:timezone":"Indian/Antananarivo",
    "iso:country":"MG",
    "wof:name":"Ambalanomby",
    "wof:placetype":"locality"
},
  "geometry": {"coordinates":[47.63333,-16.78333],"type":"Point"}
}