{
  "type": "Feature",
  "properties": {
    "gn:admin1_code":"01",
    "gn:asciiname":"Marofototro",
    "gn:country_code":"MG",
    "gn:dem":320,
    "gn:feature_class":"P",
    "gn:feature_code":"PPL",
    "gn:name":"Marofototro",
    "gn:population":0,
    "gn:timezone":"Indian/Antananarivo",
    "iso:country":"MG",
    "wof:name":"Marofototro",
    "wof:placetype":"locality"
},
  "geometry": {"coordinates":[49.88333,-13.93333],"type":"Point"}
}