{
  "type": "Feature",
  "properties": {
    "gn:admin1_code":"04",
    "gn:asciiname":"Bezampy",
    "gn:country_code":"MG",
    "gn:dem":192,
    "gn:feature_class":"P",
    "gn:feature_code":"PPL",
    "gn:name":"Bezampy",
    "gn:population":0,
    "gn:timezone":"Indian/Antananarivo",
    "iso:country":"MG",
    "wof:name":"Bezampy",
    "wof:placetype":"locality"
},
  "geometry": {"coordinates":[48.76667,-18.61667000000001],"type":"Point"}
}