{
  "type": "Feature",
  "properties": {
    "gn:admin1_code":"02",
    "gn:asciiname":"Ambohitsara",
    "gn:country_code":"MG",
    "gn:dem":366,
    "gn:feature_class":"P",
    "gn:feature_code":"PPL",
    "gn:name":"Ambohitsara",
    "gn:population":0,
    "gn:timezone":"Indian/Antananarivo",
    "iso:country":"MG",
    "wof:name":"Ambohitsara",
    "wof:placetype":"locality"
},
  "geometry": {"coordinates":[47.78333,-21.38333],"type":"Point"}
}