{
  "type": "Feature",
  "properties": {
    "gn:admin1_code":"5.0",
    "gn:asciiname":"Trafonomby",
    "gn:country_code":"MG",
    "gn:dem":1927,
    "gn:feature_class":"P",
    "gn:feature_code":"PPL",
    "gn:name":"Trafonomby",
    "gn:population":0,
    "gn:timezone":"Indian/Antananarivo",
    "iso:country":"MG",
    "wof:name":"Trafonomby",
    "wof:placetype":"locality"
},
  "geometry": {"coordinates":[47.51667,-19.93333],"type":"Point"}
}