{
  "type": "Feature",
  "properties": {
    "gn:admin1_code":"06",
    "gn:asciiname":"Analamatsaky",
    "gn:country_code":"MG",
    "gn:dem":186,
    "gn:feature_class":"P",
    "gn:feature_code":"PPL",
    "gn:name":"Analamatsaky",
    "gn:population":0,
    "gn:timezone":"Indian/Antananarivo",
    "iso:country":"MG",
    "wof:name":"Analamatsaky",
    "wof:placetype":"locality"
},
  "geometry": {"coordinates":[46.61667,-25.01667],"type":"Point"}
}