{
  "type": "Feature",
  "properties": {
    "gn:admin1_code":"04",
    "gn:asciiname":"Andovokabe",
    "gn:country_code":"MG",
    "gn:dem":136,
    "gn:feature_class":"P",
    "gn:feature_code":"PPL",
    "gn:name":"Andovokabe",
    "gn:population":0,
    "gn:timezone":"Indian/Antananarivo",
    "iso:country":"MG",
    "wof:name":"Andovokabe",
    "wof:placetype":"locality"
},
  "geometry": {"coordinates":[49.01667,-18.55],"type":"Point"}
}