{
  "type": "Feature",
  "properties": {
    "gn:admin1_code":"02",
    "gn:asciiname":"Ambalavero",
    "gn:country_code":"MG",
    "gn:dem":82,
    "gn:feature_class":"P",
    "gn:feature_code":"PPL",
    "gn:name":"Ambalavero",
    "gn:population":0,
    "gn:timezone":"Indian/Antananarivo",
    "iso:country":"MG",
    "name:azb_x_preferred":[
        "\u0627\u0645\u0628\u0627\u0644\u0627\u0648\u0631\u0648"
    ],
    "name:fas_x_preferred":[
        "\u0627\u0645\u0628\u0627\u0644\u0627\u0648\u0631\u0648"
    ],
    "name:fra_x_preferred":[
        "Ambalavero"
    ],
    "name:ita_x_preferred":[
        "Ambalavero"
    ],
    "name:mlg_x_preferred":[
        "Ambalavero"
    ],
    "name:nld_x_preferred":[
        "Ambalavero"
    ],
    "wof:name":"Ambalavero",
    "wof:placetype":"locality"
},
  "geometry": {"coordinates":[47.91667,-21.25],"type":"Point"}
}