{
  "type": "Feature",
  "properties": {
    "gn:admin1_code":"02",
    "gn:asciiname":"Ambalavero",
    "gn:country_code":"MG",
    "gn:dem":82,
    "gn:feature_class":"P",
    "gn:feature_code":"PPL",
    "gn:name":"Ambalavero",
    "gn:population":0,
    "gn:timezone":"Indian/Antananarivo",
    "iso:country":"MG",
    "wof:name":"Ambalavero",
    "wof:placetype":"locality"
},
  "geometry": {"coordinates":[47.91667,-21.25],"type":"Point"}
}