{
  "type": "Feature",
  "properties": {
    "gn:admin1_code":"01",
    "gn:asciiname":"Ampanefena",
    "gn:cc2":"MG",
    "gn:country_code":"MG",
    "gn:dem":61,
    "gn:feature_class":"P",
    "gn:feature_code":"PPL",
    "gn:name":"Ampanefena",
    "gn:population":0,
    "gn:timezone":"Indian/Antananarivo",
    "iso:country":"MG",
    "name:und_x_variant":[
        "Ampanefeno",
        "Ampanefena"
    ],
    "wof:name":"Ampanefena",
    "wof:placetype":"locality"
},
  "geometry": {"coordinates":[49.96667,-13.86667],"type":"Point"}
}