{
  "type": "Feature",
  "properties": {
    "gn:admin1_code":"01",
    "gn:asciiname":"Ampanefena",
    "gn:cc2":"MG",
    "gn:country_code":"MG",
    "gn:dem":61,
    "gn:feature_class":"P",
    "gn:feature_code":"PPL",
    "gn:name":"Ampanefena",
    "gn:population":0,
    "gn:timezone":"Indian/Antananarivo",
    "iso:country":"MG",
    "name:azb_x_preferred":[
        "\u0627\u0645\u067e\u0627\u0646\u06cc\u0641\u0646\u0627"
    ],
    "name:fas_x_preferred":[
        "\u0627\u0645\u067e\u0627\u0646\u06cc\u0641\u0646\u0627"
    ],
    "name:fra_x_preferred":[
        "Ampanefena"
    ],
    "name:ita_x_preferred":[
        "Ampanefena"
    ],
    "name:mlg_x_preferred":[
        "Ampanefena"
    ],
    "name:nld_x_preferred":[
        "Ampanefena"
    ],
    "name:und_x_variant":[
        "Ampanefeno"
    ],
    "wof:name":"Ampanefena",
    "wof:placetype":"locality"
},
  "geometry": {"coordinates":[49.96667,-13.86667],"type":"Point"}
}