{
  "type": "Feature",
  "properties": {
    "gn:admin1_code":"03",
    "gn:asciiname":"Angoaka Avaratra",
    "gn:cc2":"MG",
    "gn:country_code":"MG",
    "gn:dem":72,
    "gn:feature_class":"P",
    "gn:feature_code":"PPL",
    "gn:name":"Angoaka Avaratra",
    "gn:population":0,
    "gn:timezone":"Indian/Antananarivo",
    "iso:country":"MG",
    "name:und_x_variant":[
        "Angoaka North",
        "Angoaka Avaratra"
    ],
    "wof:name":"Angoaka Avaratra",
    "wof:placetype":"locality"
},
  "geometry": {"coordinates":[47.46667,-15.21667],"type":"Point"}
}