{
  "type": "Feature",
  "properties": {
    "gn:admin1_code":"03",
    "gn:asciiname":"Marotolana",
    "gn:cc2":"MG",
    "gn:country_code":"MG",
    "gn:dem":121,
    "gn:feature_class":"P",
    "gn:feature_code":"PPL",
    "gn:name":"Marotolana",
    "gn:population":0,
    "gn:timezone":"Indian/Antananarivo",
    "iso:country":"MG",
    "name:und_x_variant":[
        "Marotaolana",
        "Marotolana"
    ],
    "wof:name":"Marotolana",
    "wof:placetype":"locality"
},
  "geometry": {"coordinates":[46.15,-16.43333],"type":"Point"}
}