{
  "type": "Feature",
  "properties": {
    "gn:admin1_code":"04",
    "gn:asciiname":"Ambodiraboso",
    "gn:country_code":"MG",
    "gn:dem":661,
    "gn:feature_class":"P",
    "gn:feature_code":"PPL",
    "gn:name":"Ambodiraboso",
    "gn:population":0,
    "gn:timezone":"Indian/Antananarivo",
    "iso:country":"MG",
    "wof:name":"Ambodiraboso",
    "wof:placetype":"locality"
},
  "geometry": {"coordinates":[48.33333,-19.61667000000001],"type":"Point"}
}