{
  "type": "Feature",
  "properties": {
    "gn:admin1_code":"03",
    "gn:asciiname":"Amparihisoa Sud",
    "gn:country_code":"MG",
    "gn:dem":742,
    "gn:feature_class":"P",
    "gn:feature_code":"PPL",
    "gn:name":"Amparihisoa Sud",
    "gn:population":0,
    "gn:timezone":"Indian/Antananarivo",
    "iso:country":"MG",
    "wof:name":"Amparihisoa Sud",
    "wof:placetype":"locality"
},
  "geometry": {"coordinates":[46.05,-17.78333],"type":"Point"}
}