{
  "type": "Feature",
  "properties": {
    "gn:admin1_code":"06",
    "gn:asciiname":"Mahazoarivo",
    "gn:country_code":"MG",
    "gn:dem":365,
    "gn:feature_class":"P",
    "gn:feature_code":"PPL",
    "gn:name":"Mahazoarivo",
    "gn:population":0,
    "gn:timezone":"Indian/Antananarivo",
    "iso:country":"MG",
    "wof:name":"Mahazoarivo",
    "wof:placetype":"locality"
},
  "geometry": {"coordinates":[46.28333,-23.96667],"type":"Point"}
}