{
  "type": "Feature",
  "properties": {
    "gn:admin1_code":"04",
    "gn:asciiname":"Ambodimantaly",
    "gn:cc2":"MG",
    "gn:country_code":"MG",
    "gn:dem":364,
    "gn:feature_class":"P",
    "gn:feature_code":"PPL",
    "gn:name":"Ambodimantaly",
    "gn:population":0,
    "gn:timezone":"Indian/Antananarivo",
    "iso:country":"MG",
    "name:und_x_variant":[
        "Ambodimantalia",
        "Ambodimantaly"
    ],
    "wof:name":"Ambodimantaly",
    "wof:placetype":"locality"
},
  "geometry": {"coordinates":[48.81667,-18.61667000000001],"type":"Point"}
}