{
  "type": "Feature",
  "properties": {
    "gn:admin1_code":"04",
    "gn:asciiname":"Mahamanaha",
    "gn:country_code":"MG",
    "gn:dem":946,
    "gn:feature_class":"P",
    "gn:feature_code":"PPL",
    "gn:name":"Mahamanaha",
    "gn:population":0,
    "gn:timezone":"Indian/Antananarivo",
    "iso:country":"MG",
    "wof:name":"Mahamanaha",
    "wof:placetype":"locality"
},
  "geometry": {"coordinates":[48.28333,-18.91667],"type":"Point"}
}