{
  "type": "Feature",
  "properties": {
    "gn:admin1_code":"06",
    "gn:asciiname":"Bekinana-Toby",
    "gn:country_code":"MG",
    "gn:dem":1076,
    "gn:feature_class":"P",
    "gn:feature_code":"PPL",
    "gn:name":"Bekinana-Toby",
    "gn:population":0,
    "gn:timezone":"Indian/Antananarivo",
    "iso:country":"MG",
    "wof:name":"Bekinana-Toby",
    "wof:placetype":"locality"
},
  "geometry": {"coordinates":[46.38333,-23.23333],"type":"Point"}
}