{
  "type": "Feature",
  "properties": {
    "gn:admin1_code":"06",
    "gn:asciiname":"Betamenaky",
    "gn:country_code":"MG",
    "gn:dem":266,
    "gn:feature_class":"P",
    "gn:feature_code":"PPL",
    "gn:name":"Betamenaky",
    "gn:population":0,
    "gn:timezone":"Indian/Antananarivo",
    "iso:country":"MG",
    "wof:name":"Betamenaky",
    "wof:placetype":"locality"
},
  "geometry": {"coordinates":[46.45,-24.13333],"type":"Point"}
}