{
  "type": "Feature",
  "properties": {
    "gn:admin1_code":"03",
    "gn:asciiname":"Andovodava",
    "gn:country_code":"MG",
    "gn:dem":273,
    "gn:feature_class":"P",
    "gn:feature_code":"PPL",
    "gn:name":"Andovodava",
    "gn:population":0,
    "gn:timezone":"Indian/Antananarivo",
    "iso:country":"MG",
    "wof:name":"Andovodava",
    "wof:placetype":"locality"
},
  "geometry": {"coordinates":[48.31667,-15.63333],"type":"Point"}
}