{
  "type": "Feature",
  "properties": {
    "gn:admin1_code":"2.0",
    "gn:asciiname":"Tsararano",
    "gn:country_code":"MG",
    "gn:dem":50,
    "gn:feature_class":"P",
    "gn:feature_code":"PPL",
    "gn:name":"Tsararano",
    "gn:population":0,
    "gn:timezone":"Indian/Antananarivo",
    "iso:country":"MG",
    "wof:name":"Tsararano",
    "wof:placetype":"locality"
},
  "geometry": {"coordinates":[48.15,-21.35],"type":"Point"}
}