{
  "type": "Feature",
  "properties": {
    "gn:admin1_code":"6.0",
    "gn:asciiname":"Rock",
    "gn:country_code":"MG",
    "gn:dem":19,
    "gn:feature_class":"P",
    "gn:feature_code":"PPL",
    "gn:name":"Rock",
    "gn:population":0,
    "gn:timezone":"Indian/Antananarivo",
    "iso:country":"MG",
    "name:als_x_preferred":[
        "Rock"
    ],
    "name:arg_x_preferred":[
        "Rock"
    ],
    "name:bar_x_preferred":[
        "Rock"
    ],
    "name:ceb_x_preferred":[
        "Rock"
    ],
    "name:ces_x_preferred":[
        "Rock"
    ],
    "name:deu_x_preferred":[
        "Rock"
    ],
    "name:est_x_preferred":[
        "Rock"
    ],
    "name:fas_x_preferred":[
        "\u0631\u0627\u06a9"
    ],
    "name:fra_x_preferred":[
        "Rock"
    ],
    "name:glg_x_preferred":[
        "Rock"
    ],
    "name:heb_x_preferred":[
        "\u05e8\u05d5\u05e7"
    ],
    "name:ita_x_preferred":[
        "Rock"
    ],
    "name:jpn_x_preferred":[
        "\u30ed\u30c3\u30af"
    ],
    "name:kat_x_preferred":[
        "\u10e0\u10dd\u10d9\u10d8"
    ],
    "name:msa_x_preferred":[
        "Rock"
    ],
    "name:nds_x_preferred":[
        "Rock"
    ],
    "name:pol_x_preferred":[
        "Rock"
    ],
    "name:ron_x_preferred":[
        "Rock"
    ],
    "name:rus_x_preferred":[
        "Rock"
    ],
    "name:sco_x_preferred":[
        "Rock"
    ],
    "name:spa_x_preferred":[
        "Rock"
    ],
    "name:swe_x_preferred":[
        "Rock"
    ],
    "name:tgl_x_preferred":[
        "Rock"
    ],
    "name:tur_x_preferred":[
        "Rock"
    ],
    "name:vie_x_preferred":[
        "Rock"
    ],
    "name:zho_x_preferred":[
        "Rock"
    ],
    "wof:name":"Rock",
    "wof:placetype":"locality"
},
  "geometry": {"coordinates":[44.86667,-19.76667],"type":"Point"}
}