{
  "type": "Feature",
  "properties": {
    "gn:admin1_code":"03",
    "gn:asciiname":"Ambinanykajobo",
    "gn:country_code":"MG",
    "gn:dem":664,
    "gn:feature_class":"P",
    "gn:feature_code":"PPL",
    "gn:name":"Ambinanykajobo",
    "gn:population":0,
    "gn:timezone":"Indian/Antananarivo",
    "iso:country":"MG",
    "wof:name":"Ambinanykajobo",
    "wof:placetype":"locality"
},
  "geometry": {"coordinates":[48.88333,-15.45],"type":"Point"}
}