{
  "type": "Feature",
  "properties": {
    "gn:admin1_code":"06",
    "gn:asciiname":"Ankilivalo Nord",
    "gn:cc2":"MG",
    "gn:country_code":"MG",
    "gn:dem":179,
    "gn:feature_class":"P",
    "gn:feature_code":"PPL",
    "gn:name":"Ankilivalo Nord",
    "gn:population":0,
    "gn:timezone":"Indian/Antananarivo",
    "iso:country":"MG",
    "name:und_x_variant":[
        "Ankilivalo",
        "Ankilivalo Nord"
    ],
    "wof:name":"Ankilivalo Nord",
    "wof:placetype":"locality"
},
  "geometry": {"coordinates":[45.63333,-25.15],"type":"Point"}
}