{
  "type": "Feature",
  "properties": {
    "gn:admin1_code":"6.0",
    "gn:asciiname":"Sahatany",
    "gn:cc2":"MG",
    "gn:country_code":"MG",
    "gn:dem":102,
    "gn:feature_class":"P",
    "gn:feature_code":"PPL",
    "gn:name":"Sahatany",
    "gn:population":0,
    "gn:timezone":"Indian/Antananarivo",
    "iso:country":"MG",
    "name:und_x_variant":[
        "Sakatany",
        "Sahatany"
    ],
    "wof:name":"Sahatany",
    "wof:placetype":"locality"
},
  "geometry": {"coordinates":[46.88333,-24.63333],"type":"Point"}
}