{
  "type": "Feature",
  "properties": {
    "gn:admin1_code":"05",
    "gn:asciiname":"Bepoaka-Manazary",
    "gn:cc2":"MG",
    "gn:country_code":"MG",
    "gn:dem":870,
    "gn:feature_class":"P",
    "gn:feature_code":"PPL",
    "gn:name":"Bepoaka-Manazary",
    "gn:population":0,
    "gn:timezone":"Indian/Antananarivo",
    "iso:country":"MG",
    "name:und_x_variant":[
        "Bepoaka Ambony",
        "Bepoaka-Manazary"
    ],
    "wof:name":"Bepoaka-Manazary",
    "wof:placetype":"locality"
},
  "geometry": {"coordinates":[45.83333,-18.55],"type":"Point"}
}