{
  "type": "Feature",
  "properties": {
    "gn:admin1_code":"02",
    "gn:asciiname":"Marohazo",
    "gn:country_code":"MG",
    "gn:dem":740,
    "gn:feature_class":"P",
    "gn:feature_code":"PPL",
    "gn:name":"Marohazo",
    "gn:population":0,
    "gn:timezone":"Indian/Antananarivo",
    "iso:country":"MG",
    "name:ceb_x_preferred":[
        "Marohazo"
    ],
    "name:fra_x_preferred":[
        "Marohazo"
    ],
    "name:ita_x_preferred":[
        "Marohazo"
    ],
    "name:mlg_x_preferred":[
        "Marohazo"
    ],
    "name:nld_x_preferred":[
        "Marohazo"
    ],
    "name:swe_x_preferred":[
        "Marohazo"
    ],
    "wof:name":"Marohazo",
    "wof:placetype":"locality"
},
  "geometry": {"coordinates":[46.15,-22.53333],"type":"Point"}
}