{
  "type": "Feature",
  "properties": {
    "gn:admin1_code":"06",
    "gn:asciiname":"Ipiko",
    "gn:country_code":"MG",
    "gn:dem":291,
    "gn:feature_class":"P",
    "gn:feature_code":"PPL",
    "gn:name":"Ipiko",
    "gn:population":0,
    "gn:timezone":"Indian/Antananarivo",
    "iso:country":"MG",
    "wof:name":"Ipiko",
    "wof:placetype":"locality"
},
  "geometry": {"coordinates":[45.36667,-24.68333],"type":"Point"}
}