{
  "type": "Feature",
  "properties": {
    "gn:admin1_code":"3.0",
    "gn:asciiname":"Vilamatsa",
    "gn:cc2":"MG",
    "gn:country_code":"MG",
    "gn:dem":-9999,
    "gn:feature_class":"P",
    "gn:feature_code":"PPL",
    "gn:name":"Vilamatsa",
    "gn:population":0,
    "gn:timezone":"Indian/Antananarivo",
    "iso:country":"MG",
    "name:und_x_variant":[
        "Vitamatsaha",
        "Vilamatsaha",
        "Vilamatsana",
        "Vilamatsa"
    ],
    "wof:name":"Vilamatsa",
    "wof:placetype":"locality"
},
  "geometry": {"coordinates":[44.48333,-16.18333],"type":"Point"}
}