{
  "type": "Feature",
  "properties": {
    "gn:admin1_code":"06",
    "gn:asciiname":"Belanitra",
    "gn:country_code":"MG",
    "gn:dem":386,
    "gn:feature_class":"P",
    "gn:feature_code":"PPL",
    "gn:name":"Belanitra",
    "gn:population":0,
    "gn:timezone":"Indian/Antananarivo",
    "iso:country":"MG",
    "wof:name":"Belanitra",
    "wof:placetype":"locality"
},
  "geometry": {"coordinates":[45.65,-21.08333],"type":"Point"}
}