{
  "type": "Feature",
  "properties": {
    "gn:admin1_code":"04",
    "gn:asciiname":"Marovintsy",
    "gn:country_code":"MG",
    "gn:dem":27,
    "gn:feature_class":"P",
    "gn:feature_code":"PPL",
    "gn:name":"Marovintsy",
    "gn:population":0,
    "gn:timezone":"Indian/Antananarivo",
    "iso:country":"MG",
    "wof:name":"Marovintsy",
    "wof:placetype":"locality"
},
  "geometry": {"coordinates":[48.95,-19.23333],"type":"Point"}
}