{
  "type": "Feature",
  "properties": {
    "gn:admin1_code":"06",
    "gn:asciiname":"Bevia",
    "gn:country_code":"MG",
    "gn:dem":1081,
    "gn:feature_class":"P",
    "gn:feature_code":"PPL",
    "gn:name":"Bevia",
    "gn:population":0,
    "gn:timezone":"Indian/Antananarivo",
    "iso:country":"MG",
    "wof:name":"Bevia",
    "wof:placetype":"locality"
},
  "geometry": {"coordinates":[46.45,-23.05],"type":"Point"}
}