{
  "type": "Feature",
  "properties": {
    "gn:admin1_code":"06",
    "gn:asciiname":"Anirinihamba",
    "gn:country_code":"MG",
    "gn:dem":158,
    "gn:feature_class":"P",
    "gn:feature_code":"PPL",
    "gn:name":"Anirinihamba",
    "gn:population":0,
    "gn:timezone":"Indian/Antananarivo",
    "iso:country":"MG",
    "wof:name":"Anirinihamba",
    "wof:placetype":"locality"
},
  "geometry": {"coordinates":[44.81667,-25.15],"type":"Point"}
}