{
  "type": "Feature",
  "properties": {
    "gn:admin1_code":"05",
    "gn:asciiname":"Ambohitromby",
    "gn:country_code":"MG",
    "gn:dem":843,
    "gn:feature_class":"P",
    "gn:feature_code":"PPL",
    "gn:name":"Ambohitromby",
    "gn:population":0,
    "gn:timezone":"Indian/Antananarivo",
    "iso:country":"MG",
    "wof:name":"Ambohitromby",
    "wof:placetype":"locality"
},
  "geometry": {"coordinates":[46.31667,-17.96667],"type":"Point"}
}