{
  "type": "Feature",
  "properties": {
    "gn:admin1_code":"02",
    "gn:asciiname":"Ambato",
    "gn:country_code":"MG",
    "gn:dem":594,
    "gn:feature_class":"P",
    "gn:feature_code":"PPL",
    "gn:name":"Ambato",
    "gn:population":0,
    "gn:timezone":"Indian/Antananarivo",
    "iso:country":"MG",
    "name:ceb_x_preferred":[
        "Ambato"
    ],
    "name:deu_x_preferred":[
        "Ambato"
    ],
    "name:epo_x_preferred":[
        "Ambato"
    ],
    "name:hye_x_preferred":[
        "\u0531\u0574\u0562\u0561\u057f\u0578"
    ],
    "name:nld_x_preferred":[
        "Ambato"
    ],
    "name:nno_x_preferred":[
        "Ambato"
    ],
    "name:rus_x_preferred":[
        "\u0410\u043c\u0431\u0430\u0442\u043e"
    ],
    "name:slk_x_preferred":[
        "Ambato"
    ],
    "name:swe_x_preferred":[
        "Ambato"
    ],
    "name:tur_x_preferred":[
        "Ambato"
    ],
    "wof:name":"Ambato",
    "wof:placetype":"locality"
},
  "geometry": {"coordinates":[47.03333,-22.53333],"type":"Point"}
}