{
  "type": "Feature",
  "properties": {
    "gn:admin1_code":"02",
    "gn:asciiname":"Manombo Atsinanana",
    "gn:country_code":"MG",
    "gn:dem":876,
    "gn:feature_class":"P",
    "gn:feature_code":"PPL",
    "gn:name":"Manombo Atsinanana",
    "gn:population":0,
    "gn:timezone":"Indian/Antananarivo",
    "iso:country":"MG",
    "wof:name":"Manombo Atsinanana",
    "wof:placetype":"locality"
},
  "geometry": {"coordinates":[46.95,-23.96667],"type":"Point"}
}