{
  "type": "Feature",
  "properties": {
    "gn:admin1_code":"03",
    "gn:asciiname":"Marobanty",
    "gn:country_code":"MG",
    "gn:dem":13,
    "gn:feature_class":"P",
    "gn:feature_code":"PPL",
    "gn:name":"Marobanty",
    "gn:population":0,
    "gn:timezone":"Indian/Antananarivo",
    "iso:country":"MG",
    "wof:name":"Marobanty",
    "wof:placetype":"locality"
},
  "geometry": {"coordinates":[45.95,-15.93333],"type":"Point"}
}