{
  "type": "Feature",
  "properties": {
    "gn:admin1_code":"05",
    "gn:asciiname":"Ambatofotsy",
    "gn:country_code":"MG",
    "gn:dem":745,
    "gn:feature_class":"P",
    "gn:feature_code":"PPL",
    "gn:name":"Ambatofotsy",
    "gn:population":0,
    "gn:timezone":"Indian/Antananarivo",
    "iso:country":"MG",
    "name:azb_x_preferred":[
        "\u0627\u0645\u0628\u0627\u062a\u0648\u0641\u0648\u062a\u0633\u06cc"
    ],
    "name:fas_x_preferred":[
        "\u0627\u0645\u0628\u0627\u062a\u0648\u0641\u0648\u062a\u0633\u06cc"
    ],
    "name:fra_x_preferred":[
        "Ambatofotsy"
    ],
    "name:ita_x_preferred":[
        "Ambatofotsy"
    ],
    "name:mlg_x_preferred":[
        "Ambatofotsy"
    ],
    "name:nld_x_preferred":[
        "Ambatofotsy"
    ],
    "wof:name":"Ambatofotsy",
    "wof:placetype":"locality"
},
  "geometry": {"coordinates":[46.05,-19.13333],"type":"Point"}
}