{
  "type": "Feature",
  "properties": {
    "gn:admin1_code":"6.0",
    "gn:asciiname":"Soamarebe",
    "gn:country_code":"MG",
    "gn:dem":126,
    "gn:feature_class":"P",
    "gn:feature_code":"PPL",
    "gn:name":"Soamarebe",
    "gn:population":0,
    "gn:timezone":"Indian/Antananarivo",
    "iso:country":"MG",
    "wof:name":"Soamarebe",
    "wof:placetype":"locality"
},
  "geometry": {"coordinates":[44.61667,-21.71667],"type":"Point"}
}