{
  "type": "Feature",
  "properties": {
    "gn:admin1_code":"03",
    "gn:asciiname":"Ambizy",
    "gn:country_code":"MG",
    "gn:dem":42,
    "gn:feature_class":"P",
    "gn:feature_code":"PPL",
    "gn:name":"Ambizy",
    "gn:population":0,
    "gn:timezone":"Indian/Antananarivo",
    "iso:country":"MG",
    "wof:name":"Ambizy",
    "wof:placetype":"locality"
},
  "geometry": {"coordinates":[44.18333,-17.98333],"type":"Point"}
}