{
  "type": "Feature",
  "properties": {
    "gn:admin1_code":"03",
    "gn:asciiname":"Antanimbaritsara",
    "gn:country_code":"MG",
    "gn:dem":1007,
    "gn:feature_class":"P",
    "gn:feature_code":"PPL",
    "gn:name":"Antanimbaritsara",
    "gn:population":0,
    "gn:timezone":"Indian/Antananarivo",
    "iso:country":"MG",
    "wof:name":"Antanimbaritsara",
    "wof:placetype":"locality"
},
  "geometry": {"coordinates":[47.65,-17.51667],"type":"Point"}
}