{
  "type": "Feature",
  "properties": {
    "gn:admin1_code":"02",
    "gn:asciiname":"Fasina",
    "gn:country_code":"MG",
    "gn:dem":1600,
    "gn:feature_class":"P",
    "gn:feature_code":"PPL",
    "gn:name":"Fasina",
    "gn:population":0,
    "gn:timezone":"Indian/Antananarivo",
    "iso:country":"MG",
    "wof:name":"Fasina",
    "wof:placetype":"locality"
},
  "geometry": {"coordinates":[47.68333,-20.13333],"type":"Point"}
}