{
  "type": "Feature",
  "properties": {
    "gn:admin1_code":"03",
    "gn:asciiname":"Matomondriha",
    "gn:country_code":"MG",
    "gn:dem":299,
    "gn:feature_class":"P",
    "gn:feature_code":"PPL",
    "gn:name":"Matomondriha",
    "gn:population":0,
    "gn:timezone":"Indian/Antananarivo",
    "iso:country":"MG",
    "wof:name":"Matomondriha",
    "wof:placetype":"locality"
},
  "geometry": {"coordinates":[44.85,-19.03333],"type":"Point"}
}