{
  "type": "Feature",
  "properties": {
    "gn:admin1_code":"05",
    "gn:asciiname":"Kinajy",
    "gn:cc2":"MG",
    "gn:country_code":"MG",
    "gn:dem":901,
    "gn:feature_class":"P",
    "gn:feature_code":"PPL",
    "gn:name":"Kinajy",
    "gn:population":0,
    "gn:timezone":"Indian/Antananarivo",
    "iso:country":"MG",
    "name:und_x_variant":[
        "Kinay",
        "Kinajy"
    ],
    "wof:name":"Kinajy",
    "wof:placetype":"locality"
},
  "geometry": {"coordinates":[47.01667,-18.01667],"type":"Point"}
}