{
  "type": "Feature",
  "properties": {
    "gn:admin1_code":"03",
    "gn:asciiname":"Ampararanokely",
    "gn:country_code":"MG",
    "gn:dem":454,
    "gn:feature_class":"P",
    "gn:feature_code":"PPL",
    "gn:name":"Ampararanokely",
    "gn:population":0,
    "gn:timezone":"Indian/Antananarivo",
    "iso:country":"MG",
    "wof:name":"Ampararanokely",
    "wof:placetype":"locality"
},
  "geometry": {"coordinates":[46.21667,-17.53333],"type":"Point"}
}