{
  "type": "Feature",
  "properties": {
    "gn:admin1_code":"04",
    "gn:asciiname":"Andapa",
    "gn:country_code":"MG",
    "gn:dem":13,
    "gn:feature_class":"P",
    "gn:feature_code":"PPL",
    "gn:name":"Andapa",
    "gn:population":0,
    "gn:timezone":"Indian/Antananarivo",
    "iso:country":"MG",
    "wof:name":"Andapa",
    "wof:placetype":"locality"
},
  "geometry": {"coordinates":[49.65,-16.73333],"type":"Point"}
}