{
  "type": "Feature",
  "properties": {
    "gn:admin1_code":"2.0",
    "gn:asciiname":"Tamiana",
    "gn:country_code":"MG",
    "gn:dem":1077,
    "gn:feature_class":"P",
    "gn:feature_code":"PPL",
    "gn:name":"Tamiana",
    "gn:population":0,
    "gn:timezone":"Indian/Antananarivo",
    "iso:country":"MG",
    "wof:name":"Tamiana",
    "wof:placetype":"locality"
},
  "geometry": {"coordinates":[47.05,-21.31667],"type":"Point"}
}