{
  "type": "Feature",
  "properties": {
    "gn:admin1_code":"04",
    "gn:asciiname":"Andonabe-Ranomena",
    "gn:cc2":"MG",
    "gn:country_code":"MG",
    "gn:dem":553,
    "gn:feature_class":"P",
    "gn:feature_code":"PPL",
    "gn:name":"Andonabe-Ranomena",
    "gn:population":0,
    "gn:timezone":"Indian/Antananarivo",
    "iso:country":"MG",
    "name:und_x_variant":[
        "Andonabe",
        "Andonabe-Ranomena"
    ],
    "wof:name":"Andonabe-Ranomena",
    "wof:placetype":"locality"
},
  "geometry": {"coordinates":[48.03333,-19.76667],"type":"Point"}
}