{
  "type": "Feature",
  "properties": {
    "gn:admin1_code":"02",
    "gn:asciiname":"Andondona",
    "gn:country_code":"MG",
    "gn:dem":1371,
    "gn:feature_class":"P",
    "gn:feature_code":"PPL",
    "gn:name":"Andondona",
    "gn:population":0,
    "gn:timezone":"Indian/Antananarivo",
    "iso:country":"MG",
    "wof:name":"Andondona",
    "wof:placetype":"locality"
},
  "geometry": {"coordinates":[46.31667,-20.51667],"type":"Point"}
}