{
  "type": "Feature",
  "properties": {
    "gn:admin1_code":"06",
    "gn:asciiname":"Beadala",
    "gn:country_code":"MG",
    "gn:dem":382,
    "gn:feature_class":"P",
    "gn:feature_code":"PPL",
    "gn:name":"Beadala",
    "gn:population":0,
    "gn:timezone":"Indian/Antananarivo",
    "iso:country":"MG",
    "wof:name":"Beadala",
    "wof:placetype":"locality"
},
  "geometry": {"coordinates":[46.31667,-24.38333],"type":"Point"}
}