{
  "type": "Feature",
  "properties": {
    "gn:admin1_code":"02",
    "gn:asciiname":"Marokoriaka",
    "gn:country_code":"MG",
    "gn:dem":16,
    "gn:feature_class":"P",
    "gn:feature_code":"PPL",
    "gn:name":"Marokoriaka",
    "gn:population":0,
    "gn:timezone":"Indian/Antananarivo",
    "iso:country":"MG",
    "wof:name":"Marokoriaka",
    "wof:placetype":"locality"
},
  "geometry": {"coordinates":[47.71667,-22.11667000000001],"type":"Point"}
}