{
  "type": "Feature",
  "properties": {
    "gn:admin1_code":"06",
    "gn:asciiname":"Marofohy",
    "gn:country_code":"MG",
    "gn:dem":139,
    "gn:feature_class":"P",
    "gn:feature_code":"PPL",
    "gn:name":"Marofohy",
    "gn:population":0,
    "gn:timezone":"Indian/Antananarivo",
    "iso:country":"MG",
    "wof:name":"Marofohy",
    "wof:placetype":"locality"
},
  "geometry": {"coordinates":[45.93333,-25.25],"type":"Point"}
}