{
  "type": "Feature",
  "properties": {
    "gn:admin1_code":"05",
    "gn:asciiname":"Manandona",
    "gn:cc2":"MG",
    "gn:country_code":"MG",
    "gn:dem":1571,
    "gn:feature_class":"P",
    "gn:feature_code":"PPL",
    "gn:name":"Manandona",
    "gn:population":0,
    "gn:timezone":"Indian/Antananarivo",
    "iso:country":"MG",
    "name:und_x_variant":[
        "Manandon",
        "Manandona"
    ],
    "wof:name":"Manandona",
    "wof:placetype":"locality"
},
  "geometry": {"coordinates":[47.06667,-20.05],"type":"Point"}
}