{
  "type": "Feature",
  "properties": {
    "gn:admin1_code":"4.0",
    "gn:asciiname":"Vavony",
    "gn:country_code":"MG",
    "gn:dem":28,
    "gn:feature_class":"P",
    "gn:feature_code":"PPL",
    "gn:name":"Vavony",
    "gn:population":0,
    "gn:timezone":"Indian/Antananarivo",
    "iso:country":"MG",
    "wof:name":"Vavony",
    "wof:placetype":"locality"
},
  "geometry": {"coordinates":[49.18333,-18.78333],"type":"Point"}
}