{
  "type": "Feature",
  "properties": {
    "gn:admin1_code":"03",
    "gn:asciiname":"Marokira",
    "gn:country_code":"MG",
    "gn:dem":43,
    "gn:feature_class":"P",
    "gn:feature_code":"PPL",
    "gn:name":"Marokira",
    "gn:population":0,
    "gn:timezone":"Indian/Antananarivo",
    "iso:country":"MG",
    "wof:name":"Marokira",
    "wof:placetype":"locality"
},
  "geometry": {"coordinates":[46.88333,-15.78333],"type":"Point"}
}