{
  "type": "Feature",
  "properties": {
    "gn:admin1_code":"04",
    "gn:asciiname":"Amporoforo",
    "gn:country_code":"MG",
    "gn:dem":253,
    "gn:feature_class":"P",
    "gn:feature_code":"PPL",
    "gn:name":"Amporoforo",
    "gn:population":0,
    "gn:timezone":"Indian/Antananarivo",
    "iso:country":"MG",
    "wof:name":"Amporoforo",
    "wof:placetype":"locality"
},
  "geometry": {"coordinates":[49.13333,-17.83333],"type":"Point"}
}