{
  "type": "Feature",
  "properties": {
    "gn:admin1_code":"05",
    "gn:asciiname":"Manazary",
    "gn:cc2":"MG",
    "gn:country_code":"MG",
    "gn:dem":1297,
    "gn:feature_class":"P",
    "gn:feature_code":"PPL",
    "gn:name":"Manazary",
    "gn:population":0,
    "gn:timezone":"Indian/Antananarivo",
    "iso:country":"MG",
    "name:und_x_variant":[
        "Fiakarantsoa-Manazary",
        "Manazary"
    ],
    "wof:name":"Manazary",
    "wof:placetype":"locality"
},
  "geometry": {"coordinates":[46.86667,-19.05],"type":"Point"}
}