{
  "type": "Feature",
  "properties": {
    "gn:admin1_code":"6.0",
    "gn:asciiname":"Tandroka Atsimo",
    "gn:cc2":"MG",
    "gn:country_code":"MG",
    "gn:dem":419,
    "gn:feature_class":"P",
    "gn:feature_code":"PPL",
    "gn:name":"Tandroka Atsimo",
    "gn:population":0,
    "gn:timezone":"Indian/Antananarivo",
    "iso:country":"MG",
    "name:und_x_variant":[
        "Itandraka",
        "Tandroka Sud",
        "Tandroka",
        "Tandroka Atsimo"
    ],
    "wof:name":"Tandroka Atsimo",
    "wof:placetype":"locality"
},
  "geometry": {"coordinates":[44.55,-22.25],"type":"Point"}
}