{
  "type": "Feature",
  "properties": {
    "gn:admin1_code":"6.0",
    "gn:asciiname":"Sihanakapaha",
    "gn:country_code":"MG",
    "gn:dem":160,
    "gn:feature_class":"P",
    "gn:feature_code":"PPL",
    "gn:name":"Sihanakapaha",
    "gn:population":0,
    "gn:timezone":"Indian/Antananarivo",
    "iso:country":"MG",
    "wof:name":"Sihanakapaha",
    "wof:placetype":"locality"
},
  "geometry": {"coordinates":[45.18333,-25.08333],"type":"Point"}
}