{
  "type": "Feature",
  "properties": {
    "gn:admin1_code":"06",
    "gn:asciiname":"Mihovotra",
    "gn:country_code":"MG",
    "gn:dem":54,
    "gn:feature_class":"P",
    "gn:feature_code":"PPL",
    "gn:name":"Mihovotra",
    "gn:population":0,
    "gn:timezone":"Indian/Antananarivo",
    "iso:country":"MG",
    "wof:name":"Mihovotra",
    "wof:placetype":"locality"
},
  "geometry": {"coordinates":[43.63333,-21.98333],"type":"Point"}
}