{
  "type": "Feature",
  "properties": {
    "gn:admin1_code":"06",
    "gn:asciiname":"Ambendra",
    "gn:country_code":"MG",
    "gn:dem":121,
    "gn:feature_class":"P",
    "gn:feature_code":"PPL",
    "gn:name":"Ambendra",
    "gn:population":0,
    "gn:timezone":"Indian/Antananarivo",
    "iso:country":"MG",
    "wof:name":"Ambendra",
    "wof:placetype":"locality"
},
  "geometry": {"coordinates":[45.33333,-19.03333],"type":"Point"}
}