{
  "type": "Feature",
  "properties": {
    "gn:admin1_code":"02",
    "gn:asciiname":"Manakana",
    "gn:country_code":"MG",
    "gn:dem":1516,
    "gn:feature_class":"P",
    "gn:feature_code":"PPL",
    "gn:name":"Manakana",
    "gn:population":0,
    "gn:timezone":"Indian/Antananarivo",
    "iso:country":"MG",
    "wof:name":"Manakana",
    "wof:placetype":"locality"
},
  "geometry": {"coordinates":[47.65,-20.25],"type":"Point"}
}