{
  "type": "Feature",
  "properties": {
    "gn:admin1_code":"01",
    "gn:asciiname":"Ambalavelona",
    "gn:country_code":"MG",
    "gn:dem":327,
    "gn:feature_class":"P",
    "gn:feature_code":"PPL",
    "gn:name":"Ambalavelona",
    "gn:population":0,
    "gn:timezone":"Indian/Antananarivo",
    "iso:country":"MG",
    "wof:name":"Ambalavelona",
    "wof:placetype":"locality"
},
  "geometry": {"coordinates":[49.78333,-14.68333],"type":"Point"}
}