{
  "type": "Feature",
  "properties": {
    "gn:admin1_code":"05",
    "gn:asciiname":"Kelimahery",
    "gn:country_code":"MG",
    "gn:dem":851,
    "gn:feature_class":"P",
    "gn:feature_code":"PPL",
    "gn:name":"Kelimahery",
    "gn:population":0,
    "gn:timezone":"Indian/Antananarivo",
    "iso:country":"MG",
    "wof:name":"Kelimahery",
    "wof:placetype":"locality"
},
  "geometry": {"coordinates":[46.28333,-18.01667],"type":"Point"}
}