{
  "type": "Feature",
  "properties": {
    "gn:admin1_code":"05",
    "gn:asciiname":"Ambohimarina",
    "gn:country_code":"MG",
    "gn:dem":1255,
    "gn:feature_class":"P",
    "gn:feature_code":"PPL",
    "gn:name":"Ambohimarina",
    "gn:population":0,
    "gn:timezone":"Indian/Antananarivo",
    "iso:country":"MG",
    "name:azb_x_preferred":[
        "\u0627\u0645\u0628\u0648\u0647\u06cc\u0645\u0627\u0631\u06cc\u0646\u0627"
    ],
    "name:fas_x_preferred":[
        "\u0627\u0645\u0628\u0648\u0647\u06cc\u0645\u0627\u0631\u06cc\u0646\u0627"
    ],
    "name:fra_x_preferred":[
        "Ambohimarina"
    ],
    "name:ita_x_preferred":[
        "Ambohimarina"
    ],
    "name:mlg_x_preferred":[
        "Ambohimarina"
    ],
    "name:nld_x_preferred":[
        "Ambohimarina"
    ],
    "wof:name":"Ambohimarina",
    "wof:placetype":"locality"
},
  "geometry": {"coordinates":[47.15,-18.56667],"type":"Point"}
}