{
  "type": "Feature",
  "properties": {
    "gn:admin1_code":"03",
    "gn:asciiname":"Antantiloky",
    "gn:cc2":"MG",
    "gn:country_code":"MG",
    "gn:dem":41,
    "gn:feature_class":"P",
    "gn:feature_code":"PPL",
    "gn:name":"Antantiloky",
    "gn:population":0,
    "gn:timezone":"Indian/Antananarivo",
    "iso:country":"MG",
    "name:und_x_variant":[
        "Antatileky",
        "Antantiloky"
    ],
    "wof:name":"Antantiloky",
    "wof:placetype":"locality"
},
  "geometry": {"coordinates":[47.46667,-15.15],"type":"Point"}
}