{
  "type": "Feature",
  "properties": {
    "gn:country":"MG",
    "gn:fcode":"PPL",
    "gn:population":21982,
    "iso:country":"MG",
    "name:bul_x_preferred":[
        "\u0410\u0440\u0438\u0432\u043e\u043d\u0438\u043c\u0430\u043c\u043e"
    ],
    "name:ceb_x_preferred":[
        "Arivonimamo"
    ],
    "name:eng_x_preferred":[
        "Arivonimamo"
    ],
    "name:fra_x_preferred":[
        "Arivonimamo"
    ],
    "name:ita_x_preferred":[
        "Arivonimamo"
    ],
    "name:jpn_x_preferred":[
        "\u30a2\u30ea\u30f4\u30a9\u30cb\u30de\u30e2"
    ],
    "name:mlg_x_preferred":[
        "Arivonimamo"
    ],
    "name:nld_x_preferred":[
        "Arivonimamo"
    ],
    "name:pol_x_preferred":[
        "Arivonimamo"
    ],
    "name:rus_x_preferred":[
        "\u0410\u0440\u0438\u0432\u0443\u043d\u0438\u043c\u0430\u043c\u0443"
    ],
    "name:spa_x_preferred":[
        "Arivonimamo"
    ],
    "name:swe_x_preferred":[
        "Arivonimamo"
    ],
    "name:und_x_variant":[
        "Arivonimamy"
    ],
    "name:zho_x_preferred":[
        "\u963f\u91cc\u6b66\u5c3c\u99ac\u7a46"
    ],
    "qs:name":"Arivonimamo",
    "qs:photos_9r":0,
    "qs:photos_sr":0,
    "qs:pop_sr":"7",
    "wd:wordcount":88,
    "wof:name":"Arivonimamo",
    "wof:placetype":"locality",
    "wof:population":21982
},
  "geometry": {"coordinates":[47.18333,-19.01667],"type":"Point"}
}