{
  "type": "Feature",
  "properties": {
    "gn:admin1_code":"2.0",
    "gn:asciiname":"Telolonaka",
    "gn:country_code":"MG",
    "gn:dem":33,
    "gn:feature_class":"P",
    "gn:feature_code":"PPL",
    "gn:name":"Telolonaka",
    "gn:population":0,
    "gn:timezone":"Indian/Antananarivo",
    "iso:country":"MG",
    "wof:name":"Telolonaka",
    "wof:placetype":"locality"
},
  "geometry": {"coordinates":[47.51667,-22.63333],"type":"Point"}
}