{
  "type": "Feature",
  "properties": {
    "gn:admin1_code":"03",
    "gn:asciiname":"Linta",
    "gn:cc2":"MG",
    "gn:country_code":"MG",
    "gn:dem":455,
    "gn:feature_class":"P",
    "gn:feature_code":"PPL",
    "gn:name":"Linta",
    "gn:population":0,
    "gn:timezone":"Indian/Antananarivo",
    "iso:country":"MG",
    "name:und_x_variant":[
        "Ilinta",
        "Linta"
    ],
    "wof:name":"Linta",
    "wof:placetype":"locality"
},
  "geometry": {"coordinates":[48.98333,-15.56667],"type":"Point"}
}