{
  "type": "Feature",
  "properties": {
    "gn:admin1_code":"01",
    "gn:asciiname":"Antainaomby",
    "gn:country_code":"MG",
    "gn:dem":8,
    "gn:feature_class":"P",
    "gn:feature_code":"PPL",
    "gn:name":"Antainaomby",
    "gn:population":0,
    "gn:timezone":"Indian/Antananarivo",
    "iso:country":"MG",
    "wof:name":"Antainaomby",
    "wof:placetype":"locality"
},
  "geometry": {"coordinates":[50.46667,-15.36667],"type":"Point"}
}