{
  "type": "Feature",
  "properties": {
    "gn:admin1_code":"06",
    "gn:asciiname":"Bepeha",
    "gn:cc2":"MG",
    "gn:country_code":"MG",
    "gn:dem":908,
    "gn:feature_class":"P",
    "gn:feature_code":"PPL",
    "gn:name":"Bepeha",
    "gn:population":0,
    "gn:timezone":"Indian/Antananarivo",
    "iso:country":"MG",
    "name:und_x_variant":[
        "Bepea",
        "Bepeha"
    ],
    "wof:name":"Bepeha",
    "wof:placetype":"locality"
},
  "geometry": {"coordinates":[45.95,-23.01667],"type":"Point"}
}