{
  "type": "Feature",
  "properties": {
    "gn:admin1_code":"2.0",
    "gn:asciiname":"Sakarivo",
    "gn:country_code":"MG",
    "gn:dem":6,
    "gn:feature_class":"P",
    "gn:feature_code":"PPL",
    "gn:name":"Sakarivo",
    "gn:population":0,
    "gn:timezone":"Indian/Antananarivo",
    "iso:country":"MG",
    "wof:name":"Sakarivo",
    "wof:placetype":"locality"
},
  "geometry": {"coordinates":[48.23333,-21.55],"type":"Point"}
}