{
  "type": "Feature",
  "properties": {
    "gn:admin1_code":"5.0",
    "gn:asciiname":"Tsimiandrifazaina",
    "gn:country_code":"MG",
    "gn:dem":913,
    "gn:feature_class":"P",
    "gn:feature_code":"PPL",
    "gn:name":"Tsimiandrifazaina",
    "gn:population":0,
    "gn:timezone":"Indian/Antananarivo",
    "iso:country":"MG",
    "wof:name":"Tsimiandrifazaina",
    "wof:placetype":"locality"
},
  "geometry": {"coordinates":[46.36667,-18.21667],"type":"Point"}
}