{
  "type": "Feature",
  "properties": {
    "gn:admin1_code":"03",
    "gn:asciiname":"Ambodivoara",
    "gn:country_code":"MG",
    "gn:dem":675,
    "gn:feature_class":"P",
    "gn:feature_code":"PPL",
    "gn:name":"Ambodivoara",
    "gn:population":0,
    "gn:timezone":"Indian/Antananarivo",
    "iso:country":"MG",
    "wof:name":"Ambodivoara",
    "wof:placetype":"locality"
},
  "geometry": {"coordinates":[47.65,-17.26667],"type":"Point"}
}