{
  "type": "Feature",
  "properties": {
    "gn:admin1_code":"04",
    "gn:asciiname":"Ambatoloaka Avaratra",
    "gn:country_code":"MG",
    "gn:dem":564,
    "gn:feature_class":"P",
    "gn:feature_code":"PPL",
    "gn:name":"Ambatoloaka Avaratra",
    "gn:population":0,
    "gn:timezone":"Indian/Antananarivo",
    "iso:country":"MG",
    "wof:name":"Ambatoloaka Avaratra",
    "wof:placetype":"locality"
},
  "geometry": {"coordinates":[48.11667,-16.31667],"type":"Point"}
}