{
  "type": "Feature",
  "properties": {
    "gn:admin1_code":"06",
    "gn:asciiname":"Ambatolahinaory",
    "gn:country_code":"MG",
    "gn:dem":112,
    "gn:feature_class":"P",
    "gn:feature_code":"PPL",
    "gn:name":"Ambatolahinaory",
    "gn:population":0,
    "gn:timezone":"Indian/Antananarivo",
    "iso:country":"MG",
    "wof:name":"Ambatolahinaory",
    "wof:placetype":"locality"
},
  "geometry": {"coordinates":[44.76667,-24.93333],"type":"Point"}
}