{
  "type": "Feature",
  "properties": {
    "gn:admin1_code":"03",
    "gn:asciiname":"Antsakabary",
    "gn:country_code":"MG",
    "gn:dem":506,
    "gn:feature_class":"P",
    "gn:feature_code":"PPL",
    "gn:name":"Antsakabary",
    "gn:population":0,
    "gn:timezone":"Indian/Antananarivo",
    "iso:country":"MG",
    "name:fra_x_preferred":[
        "Antsakabary"
    ],
    "name:ita_x_preferred":[
        "Antsakabary"
    ],
    "name:mlg_x_preferred":[
        "Antsakabary"
    ],
    "name:nld_x_preferred":[
        "Antsakabary"
    ],
    "wof:name":"Antsakabary",
    "wof:placetype":"locality"
},
  "geometry": {"coordinates":[48.93333,-15.05],"type":"Point"}
}