{
  "type": "Feature",
  "properties": {
    "gn:admin1_code":"6.0",
    "gn:asciiname":"Tsianarona",
    "gn:country_code":"MG",
    "gn:dem":403,
    "gn:feature_class":"P",
    "gn:feature_code":"PPL",
    "gn:name":"Tsianarona",
    "gn:population":0,
    "gn:timezone":"Indian/Antananarivo",
    "iso:country":"MG",
    "wof:name":"Tsianarona",
    "wof:placetype":"locality"
},
  "geometry": {"coordinates":[45.08333,-23.75],"type":"Point"}
}