{
  "type": "Feature",
  "properties": {
    "gn:admin1_code":"5.0",
    "gn:asciiname":"Soarano",
    "gn:country_code":"MG",
    "gn:dem":1218,
    "gn:feature_class":"P",
    "gn:feature_code":"PPL",
    "gn:name":"Soarano",
    "gn:population":0,
    "gn:timezone":"Indian/Antananarivo",
    "iso:country":"MG",
    "wof:name":"Soarano",
    "wof:placetype":"locality"
},
  "geometry": {"coordinates":[46.61667,-18.58333],"type":"Point"}
}