{
  "type": "Feature",
  "properties": {
    "gn:admin1_code":"02",
    "gn:asciiname":"Ambatomivarina",
    "gn:country_code":"MG",
    "gn:dem":97,
    "gn:feature_class":"P",
    "gn:feature_code":"PPL",
    "gn:name":"Ambatomivarina",
    "gn:population":0,
    "gn:timezone":"Indian/Antananarivo",
    "iso:country":"MG",
    "wof:name":"Ambatomivarina",
    "wof:placetype":"locality"
},
  "geometry": {"coordinates":[48.35,-20.56667],"type":"Point"}
}