{
  "type": "Feature",
  "properties": {
    "gn:admin1_code":"04",
    "gn:asciiname":"Ambinanyriana",
    "gn:country_code":"MG",
    "gn:dem":442,
    "gn:feature_class":"P",
    "gn:feature_code":"PPL",
    "gn:name":"Ambinanyriana",
    "gn:population":0,
    "gn:timezone":"Indian/Antananarivo",
    "iso:country":"MG",
    "wof:name":"Ambinanyriana",
    "wof:placetype":"locality"
},
  "geometry": {"coordinates":[49.03333,-17.53333],"type":"Point"}
}