{
  "type": "Feature",
  "properties": {
    "gn:admin1_code":"01",
    "gn:asciiname":"Mahaverika",
    "gn:country_code":"MG",
    "gn:dem":601,
    "gn:feature_class":"P",
    "gn:feature_code":"PPL",
    "gn:name":"Mahaverika",
    "gn:population":0,
    "gn:timezone":"Indian/Antananarivo",
    "iso:country":"MG",
    "wof:name":"Mahaverika",
    "wof:placetype":"locality"
},
  "geometry": {"coordinates":[49.53333,-14.65],"type":"Point"}
}