{
  "type": "Feature",
  "properties": {
    "gn:admin1_code":"6.0",
    "gn:asciiname":"Vohitelo",
    "gn:cc2":"MG",
    "gn:country_code":"MG",
    "gn:dem":181,
    "gn:feature_class":"P",
    "gn:feature_code":"PPL",
    "gn:name":"Vohitelo",
    "gn:population":0,
    "gn:timezone":"Indian/Antananarivo",
    "iso:country":"MG",
    "name:und_x_variant":[
        "Malainakoho",
        "Vohitelo"
    ],
    "wof:name":"Vohitelo",
    "wof:placetype":"locality"
},
  "geometry": {"coordinates":[45.35,-21.61667000000001],"type":"Point"}
}