{
  "type": "Feature",
  "properties": {
    "gn:admin1_code":"03",
    "gn:asciiname":"Ambodisakoana",
    "gn:cc2":"MG",
    "gn:country_code":"MG",
    "gn:dem":62,
    "gn:feature_class":"P",
    "gn:feature_code":"PPL",
    "gn:name":"Ambodisakoana",
    "gn:population":0,
    "gn:timezone":"Indian/Antananarivo",
    "iso:country":"MG",
    "name:azb_x_preferred":[
        "\u0627\u0645\u0628\u0648\u062f\u06cc\u0633\u0627\u06a9\u0648\u0627\u0646\u0627"
    ],
    "name:fas_x_preferred":[
        "\u0627\u0645\u0628\u0648\u062f\u06cc\u0633\u0627\u06a9\u0648\u0627\u0646\u0627"
    ],
    "name:fra_x_preferred":[
        "Ambodisakoana"
    ],
    "name:ita_x_preferred":[
        "Ambodisakoana"
    ],
    "name:mlg_x_preferred":[
        "Ambodisakoana"
    ],
    "name:nld_x_preferred":[
        "Ambodisakoana"
    ],
    "name:und_x_variant":[
        "Ambodisakoa"
    ],
    "wof:name":"Ambodisakoana",
    "wof:placetype":"locality"
},
  "geometry": {"coordinates":[47.96667,-15.41667],"type":"Point"}
}