{
  "type": "Feature",
  "properties": {
    "gn:admin1_code":"5.0",
    "gn:asciiname":"Vohimanitra",
    "gn:country_code":"MG",
    "gn:dem":997,
    "gn:feature_class":"P",
    "gn:feature_code":"PPL",
    "gn:name":"Vohimanitra",
    "gn:population":0,
    "gn:timezone":"Indian/Antananarivo",
    "iso:country":"MG",
    "name:ceb_x_preferred":[
        "Vohimanitra"
    ],
    "name:fra_x_preferred":[
        "Vohimanitra"
    ],
    "name:ita_x_preferred":[
        "Vohimanitra"
    ],
    "name:mlg_x_preferred":[
        "Vohimanitra"
    ],
    "name:nld_x_preferred":[
        "Vohimanitra"
    ],
    "name:swe_x_preferred":[
        "Vohimanitra"
    ],
    "wof:name":"Vohimanitra",
    "wof:placetype":"locality"
},
  "geometry": {"coordinates":[47.15,-17.93332999999999],"type":"Point"}
}