{
  "type": "Feature",
  "properties": {
    "gn:admin1_code":"03",
    "gn:asciiname":"Ambodiampana",
    "gn:country_code":"MG",
    "gn:dem":1029,
    "gn:feature_class":"P",
    "gn:feature_code":"PPL",
    "gn:name":"Ambodiampana",
    "gn:population":0,
    "gn:timezone":"Indian/Antananarivo",
    "iso:country":"MG",
    "name:fra_x_preferred":[
        "Ambodiampana"
    ],
    "name:ita_x_preferred":[
        "Ambodiampana"
    ],
    "name:nld_x_preferred":[
        "Ambodiampana"
    ],
    "wof:name":"Ambodiampana",
    "wof:placetype":"locality"
},
  "geometry": {"coordinates":[48.68333,-14.65],"type":"Point"}
}