{
  "type": "Feature",
  "properties": {
    "gn:admin1_code":"03",
    "gn:asciiname":"Antsarivary",
    "gn:country_code":"MG",
    "gn:dem":317,
    "gn:feature_class":"P",
    "gn:feature_code":"PPL",
    "gn:name":"Antsarivary",
    "gn:population":0,
    "gn:timezone":"Indian/Antananarivo",
    "iso:country":"MG",
    "wof:name":"Antsarivary",
    "wof:placetype":"locality"
},
  "geometry": {"coordinates":[45.55,-17.66667],"type":"Point"}
}