{
  "type": "Feature",
  "properties": {
    "gn:admin1_code":"3.0",
    "gn:asciiname":"Zaratsimana",
    "gn:cc2":"MG",
    "gn:country_code":"MG",
    "gn:dem":9,
    "gn:feature_class":"P",
    "gn:feature_code":"PPL",
    "gn:name":"Zaratsimana",
    "gn:population":0,
    "gn:timezone":"Indian/Antananarivo",
    "iso:country":"MG",
    "name:und_x_variant":[
        "Zaraisimana",
        "Zaratsimana"
    ],
    "wof:name":"Zaratsimana",
    "wof:placetype":"locality"
},
  "geometry": {"coordinates":[44.31667,-19.08333],"type":"Point"}
}