{
  "type": "Feature",
  "properties": {
    "gn:admin1_code":"04",
    "gn:asciiname":"Ambatomalady",
    "gn:cc2":"MG",
    "gn:country_code":"MG",
    "gn:dem":118,
    "gn:feature_class":"P",
    "gn:feature_code":"PPL",
    "gn:name":"Ambatomalady",
    "gn:population":0,
    "gn:timezone":"Indian/Antananarivo",
    "iso:country":"MG",
    "name:und_x_variant":[
        "Ambatomaladia",
        "Ambatomalady"
    ],
    "wof:name":"Ambatomalady",
    "wof:placetype":"locality"
},
  "geometry": {"coordinates":[48.68333,-19.65],"type":"Point"}
}