{
  "type": "Feature",
  "properties": {
    "gn:admin1_code":"06",
    "gn:asciiname":"Betsinefo",
    "gn:country_code":"MG",
    "gn:dem":807,
    "gn:feature_class":"P",
    "gn:feature_code":"PPL",
    "gn:name":"Betsinefo",
    "gn:population":0,
    "gn:timezone":"Indian/Antananarivo",
    "iso:country":"MG",
    "wof:name":"Betsinefo",
    "wof:placetype":"locality"
},
  "geometry": {"coordinates":[45.86667,-23.03333],"type":"Point"}
}