{
  "type": "Feature",
  "properties": {
    "gn:admin1_code":"03",
    "gn:asciiname":"Namakia",
    "gn:country_code":"MG",
    "gn:dem":-9999,
    "gn:feature_class":"P",
    "gn:feature_code":"PPL",
    "gn:name":"Namakia",
    "gn:population":0,
    "gn:timezone":"Indian/Antananarivo",
    "iso:country":"MG",
    "wof:name":"Namakia",
    "wof:placetype":"locality"
},
  "geometry": {"coordinates":[46.73333,-15.33333],"type":"Point"}
}