{
  "type": "Feature",
  "properties": {
    "gn:admin1_code":"03",
    "gn:asciiname":"Anadaho",
    "gn:country_code":"MG",
    "gn:dem":814,
    "gn:feature_class":"P",
    "gn:feature_code":"PPL",
    "gn:name":"Anadaho",
    "gn:population":0,
    "gn:timezone":"Indian/Antananarivo",
    "iso:country":"MG",
    "wof:name":"Anadaho",
    "wof:placetype":"locality"
},
  "geometry": {"coordinates":[47.28333,-17.08333],"type":"Point"}
}