{
  "type": "Feature",
  "properties": {
    "gn:admin1_code":"04",
    "gn:asciiname":"Ampitabe",
    "gn:country_code":"MG",
    "gn:dem":218,
    "gn:feature_class":"P",
    "gn:feature_code":"PPL",
    "gn:name":"Ampitabe",
    "gn:population":0,
    "gn:timezone":"Indian/Antananarivo",
    "iso:country":"MG",
    "wof:name":"Ampitabe",
    "wof:placetype":"locality"
},
  "geometry": {"coordinates":[48.45,-19.78333],"type":"Point"}
}