{
  "type": "Feature",
  "properties": {
    "gn:admin1_code":"01",
    "gn:asciiname":"Ankobalava",
    "gn:country_code":"MG",
    "gn:dem":92,
    "gn:feature_class":"P",
    "gn:feature_code":"PPL",
    "gn:name":"Ankobalava",
    "gn:population":0,
    "gn:timezone":"Indian/Antananarivo",
    "iso:country":"MG",
    "wof:name":"Ankobalava",
    "wof:placetype":"locality"
},
  "geometry": {"coordinates":[49.91667,-14.31667],"type":"Point"}
}