{
  "type": "Feature",
  "properties": {
    "gn:admin1_code":"04",
    "gn:asciiname":"Mangabe",
    "gn:country_code":"MG",
    "gn:dem":945,
    "gn:feature_class":"P",
    "gn:feature_code":"PPL",
    "gn:name":"Mangabe",
    "gn:population":0,
    "gn:timezone":"Indian/Antananarivo",
    "iso:country":"MG",
    "wof:name":"Mangabe",
    "wof:placetype":"locality"
},
  "geometry": {"coordinates":[48.13333,-19.05],"type":"Point"}
}