{
  "type": "Feature",
  "properties": {
    "gn:admin1_code":"6.0",
    "gn:asciiname":"Tsianaloka",
    "gn:country_code":"MG",
    "gn:dem":97,
    "gn:feature_class":"P",
    "gn:feature_code":"PPL",
    "gn:name":"Tsianaloka",
    "gn:population":0,
    "gn:timezone":"Indian/Antananarivo",
    "iso:country":"MG",
    "wof:name":"Tsianaloka",
    "wof:placetype":"locality"
},
  "geometry": {"coordinates":[45.16667,-18.95],"type":"Point"}
}