{
  "type": "Feature",
  "properties": {
    "gn:admin1_code":"04",
    "gn:asciiname":"Ambatomilona",
    "gn:cc2":"MG",
    "gn:country_code":"MG",
    "gn:dem":52,
    "gn:feature_class":"P",
    "gn:feature_code":"PPL",
    "gn:name":"Ambatomilona",
    "gn:population":0,
    "gn:timezone":"Indian/Antananarivo",
    "iso:country":"MG",
    "name:und_x_variant":[
        "Ambatomiloana",
        "Ambatomilona"
    ],
    "wof:name":"Ambatomilona",
    "wof:placetype":"locality"
},
  "geometry": {"coordinates":[49.81667,-16.21667],"type":"Point"}
}