{
  "type": "Feature",
  "properties": {
    "gn:admin1_code":"6.0",
    "gn:asciiname":"Zantelo",
    "gn:cc2":"MG",
    "gn:country_code":"MG",
    "gn:dem":218,
    "gn:feature_class":"P",
    "gn:feature_code":"PPL",
    "gn:name":"Zantelo",
    "gn:population":0,
    "gn:timezone":"Indian/Antananarivo",
    "iso:country":"MG",
    "name:und_x_variant":[
        "Zahantelo",
        "Zantel",
        "Zantelo"
    ],
    "wof:name":"Zantelo",
    "wof:placetype":"locality"
},
  "geometry": {"coordinates":[45.78333,-25.13333],"type":"Point"}
}