{
  "type": "Feature",
  "properties": {
    "gn:admin1_code":"02",
    "gn:asciiname":"Bemongo",
    "gn:country_code":"MG",
    "gn:dem":799,
    "gn:feature_class":"P",
    "gn:feature_code":"PPL",
    "gn:name":"Bemongo",
    "gn:population":0,
    "gn:timezone":"Indian/Antananarivo",
    "iso:country":"MG",
    "wof:name":"Bemongo",
    "wof:placetype":"locality"
},
  "geometry": {"coordinates":[46.61667,-21.46667],"type":"Point"}
}