{
  "type": "Feature",
  "properties": {
    "gn:admin1_code":"02",
    "gn:asciiname":"Mandritsara",
    "gn:country_code":"MG",
    "gn:dem":11,
    "gn:feature_class":"P",
    "gn:feature_code":"PPL",
    "gn:name":"Mandritsara",
    "gn:population":0,
    "gn:timezone":"Indian/Antananarivo",
    "iso:country":"MG",
    "name:ben_x_preferred":[
        "\u09ae\u09cd\u09af\u09be\u09a8\u09cd\u09a6\u09cd\u09b0\u09bf\u09a4\u09b8\u09be\u09b0\u09be"
    ],
    "name:ceb_x_preferred":[
        "Mandritsara"
    ],
    "name:deu_x_preferred":[
        "Mandritsara"
    ],
    "name:ell_x_preferred":[
        "\u039c\u03b1\u03bd\u03b4\u03c1\u03b9\u03c4\u03c3\u03ac\u03c1\u03b1"
    ],
    "name:fas_x_preferred":[
        "\u0645\u0646\u062f\u0631\u06cc\u062a\u0633\u0627\u0631\u0627"
    ],
    "name:fra_x_preferred":[
        "Mandritsara"
    ],
    "name:heb_x_preferred":[
        "\u05de\u05e0\u05d3\u05e8\u05d9\u05d8\u05e1\u05e8\u05d4"
    ],
    "name:hin_x_preferred":[
        "\u092e\u0902\u0926\u094d\u0930\u093f\u0924\u094d\u0938\u093e\u0930\u093e"
    ],
    "name:hun_x_preferred":[
        "Mandritsara"
    ],
    "name:ind_x_preferred":[
        "Mandritsara"
    ],
    "name:ita_x_preferred":[
        "Mandritsara"
    ],
    "name:kor_x_preferred":[
        "\ub9cc\ub4dc\ub9ac\ucc28\ub77c"
    ],
    "name:mlg_x_preferred":[
        "Mandritsara"
    ],
    "name:nld_x_preferred":[
        "Mandritsara"
    ],
    "name:rus_x_preferred":[
        "\u041c\u0430\u043d\u0434\u0440\u0438\u0442\u0437\u0430\u0440\u0430"
    ],
    "name:spa_x_preferred":[
        "Mandritsara"
    ],
    "name:swe_x_preferred":[
        "Mandritsara"
    ],
    "name:tur_x_preferred":[
        "Mandritsara"
    ],
    "name:ukr_x_preferred":[
        "\u041c\u0430\u043d\u0434\u0440\u0456\u0442\u0441\u0430\u0440\u0430"
    ],
    "name:urd_x_preferred":[
        "\u0645\u0646\u062f\u0631\u062a\u0633\u0627\u0631\u0627"
    ],
    "name:vie_x_preferred":[
        "Mandritsara"
    ],
    "name:zho_x_preferred":[
        "\u66fc\u5fb7\u91cc\u5bdf\u62c9"
    ],
    "wof:name":"Mandritsara",
    "wof:placetype":"locality"
},
  "geometry": {"coordinates":[47.53333,-23.48333],"type":"Point"}
}