{
  "type": "Feature",
  "properties": {
    "gn:admin1_code":"02",
    "gn:asciiname":"Mandritsara",
    "gn:country_code":"MG",
    "gn:dem":11,
    "gn:feature_class":"P",
    "gn:feature_code":"PPL",
    "gn:name":"Mandritsara",
    "gn:population":0,
    "gn:timezone":"Indian/Antananarivo",
    "iso:country":"MG",
    "name:ceb_x_preferred":[
        "Mandritsara"
    ],
    "name:deu_x_preferred":[
        "Mandritsara"
    ],
    "name:fra_x_preferred":[
        "Mandritsara"
    ],
    "name:ita_x_preferred":[
        "Mandritsara"
    ],
    "name:mlg_x_preferred":[
        "Mandritsara"
    ],
    "name:nld_x_preferred":[
        "Mandritsara"
    ],
    "name:spa_x_preferred":[
        "Mandritsara"
    ],
    "name:swe_x_preferred":[
        "Mandritsara"
    ],
    "name:zho_x_preferred":[
        "\u66fc\u5fb7\u91cc\u5bdf\u62c9"
    ],
    "wof:name":"Mandritsara",
    "wof:placetype":"locality"
},
  "geometry": {"coordinates":[47.53333,-23.48333],"type":"Point"}
}