{
  "type": "Feature",
  "properties": {
    "gn:admin1_code":"03",
    "gn:asciiname":"Ambalatany",
    "gn:cc2":"MG",
    "gn:country_code":"MG",
    "gn:dem":1084,
    "gn:feature_class":"P",
    "gn:feature_code":"PPL",
    "gn:name":"Ambalatany",
    "gn:population":0,
    "gn:timezone":"Indian/Antananarivo",
    "iso:country":"MG",
    "name:azb_x_preferred":[
        "\u0627\u0645\u0628\u0627\u0644\u0627\u062a\u0646\u06cc"
    ],
    "name:fas_x_preferred":[
        "\u0627\u0645\u0628\u0627\u0644\u0627\u062a\u0646\u06cc"
    ],
    "name:fra_x_preferred":[
        "Ambalatany"
    ],
    "name:ita_x_preferred":[
        "Ambalatany"
    ],
    "name:mlg_x_preferred":[
        "Ambalatany"
    ],
    "name:nld_x_preferred":[
        "Ambalatany"
    ],
    "name:und_x_variant":[
        "Ambalabany",
        "Ambalatany"
    ],
    "wof:name":"Ambalatany",
    "wof:placetype":"locality"
},
  "geometry": {"coordinates":[48.96667,-14.56667],"type":"Point"}
}