{
  "type": "Feature",
  "properties": {
    "gn:admin1_code":"02",
    "gn:asciiname":"Ambalafary",
    "gn:country_code":"MG",
    "gn:dem":59,
    "gn:feature_class":"P",
    "gn:feature_code":"PPL",
    "gn:name":"Ambalafary",
    "gn:population":0,
    "gn:timezone":"Indian/Antananarivo",
    "iso:country":"MG",
    "wof:name":"Ambalafary",
    "wof:placetype":"locality"
},
  "geometry": {"coordinates":[47.43333,-23.26667],"type":"Point"}
}