{
  "type": "Feature",
  "properties": {
    "gn:admin1_code":"05",
    "gn:asciiname":"Analamahitsy",
    "gn:country_code":"MG",
    "gn:dem":1270,
    "gn:feature_class":"P",
    "gn:feature_code":"PPL",
    "gn:name":"Analamahitsy",
    "gn:population":0,
    "gn:timezone":"Indian/Antananarivo",
    "iso:country":"MG",
    "wof:name":"Analamahitsy",
    "wof:placetype":"locality"
},
  "geometry": {"coordinates":[47.55,-18.86667000000001],"type":"Point"}
}