{
  "type": "Feature",
  "properties": {
    "gn:admin1_code":"04",
    "gn:asciiname":"Ampitabe II",
    "gn:cc2":"MG",
    "gn:country_code":"MG",
    "gn:dem":436,
    "gn:feature_class":"P",
    "gn:feature_code":"PPL",
    "gn:name":"Ampitabe II",
    "gn:population":0,
    "gn:timezone":"Indian/Antananarivo",
    "iso:country":"MG",
    "name:und_x_variant":[
        "Ampitabe",
        "Ampitabe II"
    ],
    "wof:name":"Ampitabe II",
    "wof:placetype":"locality"
},
  "geometry": {"coordinates":[48.31667,-20.15],"type":"Point"}
}