{
  "type": "Feature",
  "properties": {
    "gn:admin1_code":"03",
    "gn:asciiname":"Anosibe",
    "gn:country_code":"MG",
    "gn:dem":47,
    "gn:feature_class":"P",
    "gn:feature_code":"PPL",
    "gn:name":"Anosibe",
    "gn:population":0,
    "gn:timezone":"Indian/Antananarivo",
    "iso:country":"MG",
    "wof:name":"Anosibe",
    "wof:placetype":"locality"
},
  "geometry": {"coordinates":[44.71667,-16.95],"type":"Point"}
}