{
  "type": "Feature",
  "properties": {
    "gn:admin1_code":"02",
    "gn:asciiname":"Mahasila",
    "gn:country_code":"MG",
    "gn:dem":1199,
    "gn:feature_class":"P",
    "gn:feature_code":"PPL",
    "gn:name":"Mahasila",
    "gn:population":0,
    "gn:timezone":"Indian/Antananarivo",
    "iso:country":"MG",
    "wof:name":"Mahasila",
    "wof:placetype":"locality"
},
  "geometry": {"coordinates":[46.83333,-21.58333],"type":"Point"}
}