{
  "type": "Feature",
  "properties": {
    "gn:admin1_code":"6.0",
    "gn:asciiname":"Tsiavia",
    "gn:country_code":"MG",
    "gn:dem":219,
    "gn:feature_class":"P",
    "gn:feature_code":"PPL",
    "gn:name":"Tsiavia",
    "gn:population":0,
    "gn:timezone":"Indian/Antananarivo",
    "iso:country":"MG",
    "wof:name":"Tsiavia",
    "wof:placetype":"locality"
},
  "geometry": {"coordinates":[44.58333,-24.45],"type":"Point"}
}