{
  "type": "Feature",
  "properties": {
    "gn:admin1_code":"06",
    "gn:asciiname":"Antongo",
    "gn:country_code":"MG",
    "gn:dem":303,
    "gn:feature_class":"P",
    "gn:feature_code":"PPL",
    "gn:name":"Antongo",
    "gn:population":0,
    "gn:timezone":"Indian/Antananarivo",
    "iso:country":"MG",
    "wof:name":"Antongo",
    "wof:placetype":"locality"
},
  "geometry": {"coordinates":[44.71667,-23.75],"type":"Point"}
}