{
  "type": "Feature",
  "properties": {
    "gn:admin1_code":"04",
    "gn:asciiname":"Marijao",
    "gn:country_code":"MG",
    "gn:dem":905,
    "gn:feature_class":"P",
    "gn:feature_code":"PPL",
    "gn:name":"Marijao",
    "gn:population":0,
    "gn:timezone":"Indian/Antananarivo",
    "iso:country":"MG",
    "wof:name":"Marijao",
    "wof:placetype":"locality"
},
  "geometry": {"coordinates":[48.28333,-17.13332999999999],"type":"Point"}
}