{
  "type": "Feature",
  "properties": {
    "gn:admin1_code":"06",
    "gn:asciiname":"Ampanihy",
    "gn:country_code":"MG",
    "gn:dem":80,
    "gn:feature_class":"P",
    "gn:feature_code":"PPL",
    "gn:name":"Ampanihy",
    "gn:population":0,
    "gn:timezone":"Indian/Antananarivo",
    "iso:country":"MG",
    "wof:name":"Ampanihy",
    "wof:placetype":"locality"
},
  "geometry": {"coordinates":[45.05,-19.16667],"type":"Point"}
}