{
  "type": "Feature",
  "properties": {
    "gn:admin1_code":"4.0",
    "gn:asciiname":"Sahajinja",
    "gn:country_code":"MG",
    "gn:dem":15,
    "gn:feature_class":"P",
    "gn:feature_code":"PPL",
    "gn:name":"Sahajinja",
    "gn:population":0,
    "gn:timezone":"Indian/Antananarivo",
    "iso:country":"MG",
    "wof:name":"Sahajinja",
    "wof:placetype":"locality"
},
  "geometry": {"coordinates":[49.61667,-15.48333],"type":"Point"}
}