{
  "type": "Feature",
  "properties": {
    "gn:admin1_code":"06",
    "gn:asciiname":"Esifaka",
    "gn:cc2":"MG",
    "gn:country_code":"MG",
    "gn:dem":344,
    "gn:feature_class":"P",
    "gn:feature_code":"PPL",
    "gn:name":"Esifaka",
    "gn:population":0,
    "gn:timezone":"Indian/Antananarivo",
    "iso:country":"MG",
    "name:und_x_variant":[
        "Esifaky",
        "Esifaka"
    ],
    "wof:name":"Esifaka",
    "wof:placetype":"locality"
},
  "geometry": {"coordinates":[44.35,-24.28333],"type":"Point"}
}