{
  "type": "Feature",
  "properties": {
    "gn:admin1_code":"06",
    "gn:asciiname":"Anofandravoay",
    "gn:cc2":"MG",
    "gn:country_code":"MG",
    "gn:dem":190,
    "gn:feature_class":"P",
    "gn:feature_code":"PPL",
    "gn:name":"Anofandravoay",
    "gn:population":0,
    "gn:timezone":"Indian/Antananarivo",
    "iso:country":"MG",
    "name:und_x_variant":[
        "Anafondravoay",
        "Anofandravoay"
    ],
    "wof:name":"Anofandravoay",
    "wof:placetype":"locality"
},
  "geometry": {"coordinates":[45.95,-25.21667],"type":"Point"}
}