{
  "type": "Feature",
  "properties": {
    "gn:admin1_code":"03",
    "gn:asciiname":"Ambodidimaka",
    "gn:country_code":"MG",
    "gn:dem":50,
    "gn:feature_class":"P",
    "gn:feature_code":"PPL",
    "gn:name":"Ambodidimaka",
    "gn:population":0,
    "gn:timezone":"Indian/Antananarivo",
    "iso:country":"MG",
    "wof:name":"Ambodidimaka",
    "wof:placetype":"locality"
},
  "geometry": {"coordinates":[47.95,-14.38333],"type":"Point"}
}