{
  "type": "Feature",
  "properties": {
    "gn:admin1_code":"05",
    "gn:asciiname":"Ambozontany",
    "gn:country_code":"MG",
    "gn:dem":1708,
    "gn:feature_class":"P",
    "gn:feature_code":"PPL",
    "gn:name":"Ambozontany",
    "gn:population":0,
    "gn:timezone":"Indian/Antananarivo",
    "iso:country":"MG",
    "wof:name":"Ambozontany",
    "wof:placetype":"locality"
},
  "geometry": {"coordinates":[46.85,-19.93333],"type":"Point"}
}