{
  "type": "Feature",
  "properties": {
    "gn:country":"MG",
    "gn:fcode":"PPL",
    "gn:population":19605,
    "iso:country":"MG",
    "name:eng_x_preferred":[
        "Fenoarivobe"
    ],
    "name:fra_x_preferred":[
        "Fenoarivobe"
    ],
    "name:ita_x_preferred":[
        "Fenoarivobe"
    ],
    "name:mlg_x_preferred":[
        "Fenoarivobe"
    ],
    "name:nld_x_preferred":[
        "Fenoarivobe"
    ],
    "name:pol_x_preferred":[
        "Fenoarivobe"
    ],
    "name:spa_x_preferred":[
        "Fenoarivobe"
    ],
    "name:swe_x_preferred":[
        "Fenoarivobe"
    ],
    "name:und_x_variant":[
        "Fenoarivo Afovoany"
    ],
    "qs:name":"Fenoarivo Be",
    "qs:photos_9r":0,
    "qs:photos_sr":0,
    "qs:pop_sr":"6",
    "wof:name":"Fenoarivo Be",
    "wof:placetype":"locality",
    "wof:population":19605
},
  "geometry": {"coordinates":[46.56667,-18.43333],"type":"Point"}
}