{
  "type": "Feature",
  "properties": {
    "gn:admin1_code":"03",
    "gn:asciiname":"Anjobojobo",
    "gn:cc2":"MG",
    "gn:country_code":"MG",
    "gn:dem":386,
    "gn:feature_class":"P",
    "gn:feature_code":"PPL",
    "gn:name":"Anjobojobo",
    "gn:population":0,
    "gn:timezone":"Indian/Antananarivo",
    "iso:country":"MG",
    "name:und_x_variant":[
        "Anjokozoko",
        "Anjobojobo"
    ],
    "wof:name":"Anjobojobo",
    "wof:placetype":"locality"
},
  "geometry": {"coordinates":[47.63333,-16.88332999999999],"type":"Point"}
}