{
  "type": "Feature",
  "properties": {
    "gn:admin1_code":"06",
    "gn:asciiname":"Bereoka",
    "gn:cc2":"MG",
    "gn:country_code":"MG",
    "gn:dem":4,
    "gn:feature_class":"P",
    "gn:feature_code":"PPL",
    "gn:name":"Bereoka",
    "gn:population":0,
    "gn:timezone":"Indian/Antananarivo",
    "iso:country":"MG",
    "name:und_x_variant":[
        "Bereoaka",
        "Bereoka"
    ],
    "wof:name":"Bereoka",
    "wof:placetype":"locality"
},
  "geometry": {"coordinates":[43.81667,-23.56667],"type":"Point"}
}