{
  "type": "Feature",
  "properties": {
    "gn:admin1_code":"05",
    "gn:asciiname":"Mahatsinjo",
    "gn:country_code":"MG",
    "gn:dem":1261,
    "gn:feature_class":"P",
    "gn:feature_code":"PPL",
    "gn:name":"Mahatsinjo",
    "gn:population":0,
    "gn:timezone":"Indian/Antananarivo",
    "iso:country":"MG",
    "wof:name":"Mahatsinjo",
    "wof:placetype":"locality"
},
  "geometry": {"coordinates":[46.81667,-18.63333],"type":"Point"}
}