{
  "type": "Feature",
  "properties": {
    "gn:admin1_code":"03",
    "gn:asciiname":"Antsahampanana",
    "gn:country_code":"MG",
    "gn:dem":701,
    "gn:feature_class":"P",
    "gn:feature_code":"PPL",
    "gn:name":"Antsahampanana",
    "gn:population":0,
    "gn:timezone":"Indian/Antananarivo",
    "iso:country":"MG",
    "wof:name":"Antsahampanana",
    "wof:placetype":"locality"
},
  "geometry": {"coordinates":[46.93333,-17.68332999999999],"type":"Point"}
}