{
  "type": "Feature",
  "properties": {
    "gn:admin1_code":"03",
    "gn:asciiname":"Andebodatsaka",
    "gn:country_code":"MG",
    "gn:dem":252,
    "gn:feature_class":"P",
    "gn:feature_code":"PPL",
    "gn:name":"Andebodatsaka",
    "gn:population":0,
    "gn:timezone":"Indian/Antananarivo",
    "iso:country":"MG",
    "wof:name":"Andebodatsaka",
    "wof:placetype":"locality"
},
  "geometry": {"coordinates":[48.31667,-15.08333],"type":"Point"}
}