{
  "type": "Feature",
  "properties": {
    "gn:admin1_code":"06",
    "gn:asciiname":"Anadabo",
    "gn:country_code":"MG",
    "gn:dem":59,
    "gn:feature_class":"P",
    "gn:feature_code":"PPL",
    "gn:name":"Anadabo",
    "gn:population":0,
    "gn:timezone":"Indian/Antananarivo",
    "iso:country":"MG",
    "wof:name":"Anadabo",
    "wof:placetype":"locality"
},
  "geometry": {"coordinates":[43.96667,-21.93333],"type":"Point"}
}