{
  "type": "Feature",
  "properties": {
    "gn:admin1_code":"6.0",
    "gn:asciiname":"Vohitsova Sud",
    "gn:country_code":"MG",
    "gn:dem":172,
    "gn:feature_class":"P",
    "gn:feature_code":"PPL",
    "gn:name":"Vohitsova Sud",
    "gn:population":0,
    "gn:timezone":"Indian/Antananarivo",
    "iso:country":"MG",
    "wof:name":"Vohitsova Sud",
    "wof:placetype":"locality"
},
  "geometry": {"coordinates":[45.88333,-24.68333],"type":"Point"}
}