{
  "type": "Feature",
  "properties": {
    "gn:admin1_code":"4.0",
    "gn:asciiname":"Vatovelona",
    "gn:cc2":"MG",
    "gn:country_code":"MG",
    "gn:dem":716,
    "gn:feature_class":"P",
    "gn:feature_code":"PPL",
    "gn:name":"Vatovelona",
    "gn:population":0,
    "gn:timezone":"Indian/Antananarivo",
    "iso:country":"MG",
    "name:und_x_variant":[
        "Ambinanyvatovelo",
        "Vatovelona"
    ],
    "wof:name":"Vatovelona",
    "wof:placetype":"locality"
},
  "geometry": {"coordinates":[48.98333,-17.63332999999999],"type":"Point"}
}