{
  "type": "Feature",
  "properties": {
    "gn:admin1_code":"6.0",
    "gn:asciiname":"Tsingafy",
    "gn:country_code":"MG",
    "gn:dem":655,
    "gn:feature_class":"P",
    "gn:feature_code":"PPL",
    "gn:name":"Tsingafy",
    "gn:population":0,
    "gn:timezone":"Indian/Antananarivo",
    "iso:country":"MG",
    "wof:name":"Tsingafy",
    "wof:placetype":"locality"
},
  "geometry": {"coordinates":[45.81667,-19.65],"type":"Point"}
}