{
  "type": "Feature",
  "properties": {
    "gn:admin1_code":"04",
    "gn:asciiname":"Ambohinaorina",
    "gn:country_code":"MG",
    "gn:dem":789,
    "gn:feature_class":"P",
    "gn:feature_code":"PPL",
    "gn:name":"Ambohinaorina",
    "gn:population":0,
    "gn:timezone":"Indian/Antananarivo",
    "iso:country":"MG",
    "wof:name":"Ambohinaorina",
    "wof:placetype":"locality"
},
  "geometry": {"coordinates":[48.21667,-17.91667],"type":"Point"}
}