{
  "type": "Feature",
  "properties": {
    "gn:admin1_code":"04",
    "gn:asciiname":"Morafeno",
    "gn:country_code":"MG",
    "gn:dem":928,
    "gn:feature_class":"P",
    "gn:feature_code":"PPL",
    "gn:name":"Morafeno",
    "gn:population":0,
    "gn:timezone":"Indian/Antananarivo",
    "iso:country":"MG",
    "name:fra_x_preferred":[
        "Morafeno"
    ],
    "name:ita_x_preferred":[
        "Morafeno"
    ],
    "name:nld_x_preferred":[
        "Morafeno"
    ],
    "wof:name":"Morafeno",
    "wof:placetype":"locality"
},
  "geometry": {"coordinates":[48.66667,-17.78333],"type":"Point"}
}