{
  "type": "Feature",
  "properties": {
    "gn:admin1_code":"02",
    "gn:asciiname":"Berano",
    "gn:country_code":"MG",
    "gn:dem":579,
    "gn:feature_class":"P",
    "gn:feature_code":"PPL",
    "gn:name":"Berano",
    "gn:population":0,
    "gn:timezone":"Indian/Antananarivo",
    "iso:country":"MG",
    "wof:name":"Berano",
    "wof:placetype":"locality"
},
  "geometry": {"coordinates":[46.96667,-23.43333],"type":"Point"}
}