{
  "type": "Feature",
  "properties": {
    "gn:admin1_code":"06",
    "gn:asciiname":"Ambalasaraka",
    "gn:country_code":"MG",
    "gn:dem":521,
    "gn:feature_class":"P",
    "gn:feature_code":"PPL",
    "gn:name":"Ambalasaraka",
    "gn:population":0,
    "gn:timezone":"Indian/Antananarivo",
    "iso:country":"MG",
    "wof:name":"Ambalasaraka",
    "wof:placetype":"locality"
},
  "geometry": {"coordinates":[45.66667,-24.25],"type":"Point"}
}