{
  "type": "Feature",
  "properties": {
    "gn:admin1_code":"02",
    "gn:asciiname":"Ionadita",
    "gn:country_code":"MG",
    "gn:dem":1169,
    "gn:feature_class":"P",
    "gn:feature_code":"PPL",
    "gn:name":"Ionadita",
    "gn:population":0,
    "gn:timezone":"Indian/Antananarivo",
    "iso:country":"MG",
    "wof:name":"Ionadita",
    "wof:placetype":"locality"
},
  "geometry": {"coordinates":[47.18333,-21.05],"type":"Point"}
}