{
  "type": "Feature",
  "properties": {
    "gn:admin1_code":"03",
    "gn:asciiname":"Anosikely",
    "gn:country_code":"MG",
    "gn:dem":96,
    "gn:feature_class":"P",
    "gn:feature_code":"PPL",
    "gn:name":"Anosikely",
    "gn:population":0,
    "gn:timezone":"Indian/Antananarivo",
    "iso:country":"MG",
    "wof:name":"Anosikely",
    "wof:placetype":"locality"
},
  "geometry": {"coordinates":[46.45,-17.25],"type":"Point"}
}