{
  "type": "Feature",
  "properties": {
    "gn:admin1_code":"06",
    "gn:asciiname":"Matsinjorano",
    "gn:country_code":"MG",
    "gn:dem":191,
    "gn:feature_class":"P",
    "gn:feature_code":"PPL",
    "gn:name":"Matsinjorano",
    "gn:population":0,
    "gn:timezone":"Indian/Antananarivo",
    "iso:country":"MG",
    "wof:name":"Matsinjorano",
    "wof:placetype":"locality"
},
  "geometry": {"coordinates":[44.65,-20.83333],"type":"Point"}
}