{
  "type": "Feature",
  "properties": {
    "gn:admin1_code":"02",
    "gn:asciiname":"Madiolamba",
    "gn:country_code":"MG",
    "gn:dem":22,
    "gn:feature_class":"P",
    "gn:feature_code":"PPL",
    "gn:name":"Madiolamba",
    "gn:population":0,
    "gn:timezone":"Indian/Antananarivo",
    "iso:country":"MG",
    "wof:name":"Madiolamba",
    "wof:placetype":"locality"
},
  "geometry": {"coordinates":[48.13333,-21.41667],"type":"Point"}
}