{
  "type": "Feature",
  "properties": {
    "gn:admin1_code":"06",
    "gn:asciiname":"Betavolo",
    "gn:country_code":"MG",
    "gn:dem":278,
    "gn:feature_class":"P",
    "gn:feature_code":"PPL",
    "gn:name":"Betavolo",
    "gn:population":0,
    "gn:timezone":"Indian/Antananarivo",
    "iso:country":"MG",
    "wof:name":"Betavolo",
    "wof:placetype":"locality"
},
  "geometry": {"coordinates":[44.65,-23.28333],"type":"Point"}
}