{
  "type": "Feature",
  "properties": {
    "gn:admin1_code":"05",
    "gn:asciiname":"Mahazina",
    "gn:country_code":"MG",
    "gn:dem":1840,
    "gn:feature_class":"P",
    "gn:feature_code":"PPL",
    "gn:name":"Mahazina",
    "gn:population":0,
    "gn:timezone":"Indian/Antananarivo",
    "iso:country":"MG",
    "wof:name":"Mahazina",
    "wof:placetype":"locality"
},
  "geometry": {"coordinates":[46.86667,-19.63333],"type":"Point"}
}