{
  "type": "Feature",
  "properties": {
    "gn:admin1_code":"04",
    "gn:asciiname":"Mahadia",
    "gn:country_code":"MG",
    "gn:dem":517,
    "gn:feature_class":"P",
    "gn:feature_code":"PPL",
    "gn:name":"Mahadia",
    "gn:population":0,
    "gn:timezone":"Indian/Antananarivo",
    "iso:country":"MG",
    "wof:name":"Mahadia",
    "wof:placetype":"locality"
},
  "geometry": {"coordinates":[48.18333,-20.03333],"type":"Point"}
}