{
  "type": "Feature",
  "properties": {
    "gn:admin1_code":"02",
    "gn:asciiname":"Nihaonana",
    "gn:country_code":"MG",
    "gn:dem":565,
    "gn:feature_class":"P",
    "gn:feature_code":"PPL",
    "gn:name":"Nihaonana",
    "gn:population":0,
    "gn:timezone":"Indian/Antananarivo",
    "iso:country":"MG",
    "wof:name":"Nihaonana",
    "wof:placetype":"locality"
},
  "geometry": {"coordinates":[47.13333,-22.66667],"type":"Point"}
}