{
  "type": "Feature",
  "properties": {
    "gn:admin1_code":"5.0",
    "gn:asciiname":"Tsimatahodaza",
    "gn:country_code":"MG",
    "gn:dem":1173,
    "gn:feature_class":"P",
    "gn:feature_code":"PPL",
    "gn:name":"Tsimatahodaza",
    "gn:population":0,
    "gn:timezone":"Indian/Antananarivo",
    "iso:country":"MG",
    "wof:name":"Tsimatahodaza",
    "wof:placetype":"locality"
},
  "geometry": {"coordinates":[46.91667,-18.58333],"type":"Point"}
}