{
  "type": "Feature",
  "properties": {
    "gn:admin1_code":"06",
    "gn:asciiname":"Andranofotsy",
    "gn:country_code":"MG",
    "gn:dem":184,
    "gn:feature_class":"P",
    "gn:feature_code":"PPL",
    "gn:name":"Andranofotsy",
    "gn:population":0,
    "gn:timezone":"Indian/Antananarivo",
    "iso:country":"MG",
    "name:fra_x_preferred":[
        "Andranofotsy"
    ],
    "name:ita_x_preferred":[
        "Andranofotsy"
    ],
    "name:mlg_x_preferred":[
        "Andranofotsy"
    ],
    "name:nld_x_preferred":[
        "Andranofotsy"
    ],
    "wof:name":"Andranofotsy",
    "wof:placetype":"locality"
},
  "geometry": {"coordinates":[45.01667,-20.56667],"type":"Point"}
}