{
  "type": "Feature",
  "properties": {
    "gn:admin1_code":"06",
    "gn:asciiname":"Ampisopiso",
    "gn:country_code":"MG",
    "gn:dem":268,
    "gn:feature_class":"P",
    "gn:feature_code":"PPL",
    "gn:name":"Ampisopiso",
    "gn:population":0,
    "gn:timezone":"Indian/Antananarivo",
    "iso:country":"MG",
    "wof:name":"Ampisopiso",
    "wof:placetype":"locality"
},
  "geometry": {"coordinates":[46.21667,-25.11667000000001],"type":"Point"}
}