{
  "type": "Feature",
  "properties": {
    "gn:admin1_code":"06",
    "gn:asciiname":"Montombositra",
    "gn:cc2":"MG",
    "gn:country_code":"MG",
    "gn:dem":123,
    "gn:feature_class":"P",
    "gn:feature_code":"PPL",
    "gn:name":"Montombositra",
    "gn:population":0,
    "gn:timezone":"Indian/Antananarivo",
    "iso:country":"MG",
    "name:und_x_variant":[
        "Montovositra",
        "Montombositra"
    ],
    "wof:name":"Montombositra",
    "wof:placetype":"locality"
},
  "geometry": {"coordinates":[45.25,-25.28333],"type":"Point"}
}