{
  "type": "Feature",
  "properties": {
    "gn:admin1_code":"06",
    "gn:asciiname":"Ambonara",
    "gn:country_code":"MG",
    "gn:dem":183,
    "gn:feature_class":"P",
    "gn:feature_code":"PPL",
    "gn:name":"Ambonara",
    "gn:population":0,
    "gn:timezone":"Indian/Antananarivo",
    "iso:country":"MG",
    "wof:name":"Ambonara",
    "wof:placetype":"locality"
},
  "geometry": {"coordinates":[45.71667,-20.53333],"type":"Point"}
}