{
  "type": "Feature",
  "properties": {
    "gn:admin1_code":"04",
    "gn:asciiname":"Manasoa",
    "gn:country_code":"MG",
    "gn:dem":156,
    "gn:feature_class":"P",
    "gn:feature_code":"PPL",
    "gn:name":"Manasoa",
    "gn:population":0,
    "gn:timezone":"Indian/Antananarivo",
    "iso:country":"MG",
    "wof:name":"Manasoa",
    "wof:placetype":"locality"
},
  "geometry": {"coordinates":[49.13333,-17.35],"type":"Point"}
}