{
  "type": "Feature",
  "properties": {
    "gn:admin1_code":"03",
    "gn:asciiname":"Ankatoka",
    "gn:country_code":"MG",
    "gn:dem":44,
    "gn:feature_class":"P",
    "gn:feature_code":"PPL",
    "gn:name":"Ankatoka",
    "gn:population":0,
    "gn:timezone":"Indian/Antananarivo",
    "iso:country":"MG",
    "wof:name":"Ankatoka",
    "wof:placetype":"locality"
},
  "geometry": {"coordinates":[47.63333,-15.96667],"type":"Point"}
}