{
  "type": "Feature",
  "properties": {
    "gn:admin1_code":"7670856",
    "gn:admin2_code":"7670898",
    "gn:asciiname":"Ambohijafy",
    "gn:country_code":"MG",
    "gn:dem":1248,
    "gn:feature_class":"P",
    "gn:feature_code":"PPL",
    "gn:name":"Ambohijafy",
    "gn:population":0,
    "gn:timezone":"Indian/Antananarivo",
    "iso:country":"MG",
    "wof:name":"Ambohijafy",
    "wof:placetype":"locality"
},
  "geometry": {"coordinates":[47.48812,-18.90445],"type":"Point"}
}