{
  "type": "Feature",
  "properties": {
    "gn:admin1_code":"04",
    "gn:asciiname":"Ambodivolo",
    "gn:country_code":"MG",
    "gn:dem":316,
    "gn:feature_class":"P",
    "gn:feature_code":"PPL",
    "gn:name":"Ambodivolo",
    "gn:population":0,
    "gn:timezone":"Indian/Antananarivo",
    "iso:country":"MG",
    "wof:name":"Ambodivolo",
    "wof:placetype":"locality"
},
  "geometry": {"coordinates":[48.98333,-17.51667],"type":"Point"}
}