{
  "type": "Feature",
  "properties": {
    "gn:admin1_code":"04",
    "gn:asciiname":"Mangalahala",
    "gn:country_code":"MG",
    "gn:dem":756,
    "gn:feature_class":"P",
    "gn:feature_code":"PPL",
    "gn:name":"Mangalahala",
    "gn:population":0,
    "gn:timezone":"Indian/Antananarivo",
    "iso:country":"MG",
    "wof:name":"Mangalahala",
    "wof:placetype":"locality"
},
  "geometry": {"coordinates":[48.41667,-17.73333],"type":"Point"}
}