{
  "type": "Feature",
  "properties": {
    "gn:admin1_code":"02",
    "gn:asciiname":"Fenoarivo",
    "gn:country_code":"MG",
    "gn:dem":749,
    "gn:feature_class":"P",
    "gn:feature_code":"PPL",
    "gn:name":"Fenoarivo",
    "gn:population":0,
    "gn:timezone":"Indian/Antananarivo",
    "iso:country":"MG",
    "name:fra_x_preferred":[
        "Fenoarivo"
    ],
    "name:ita_x_preferred":[
        "Fenoarivo"
    ],
    "name:mlg_x_preferred":[
        "Fenoarivo"
    ],
    "name:nld_x_preferred":[
        "Fenoarivo"
    ],
    "name:pol_x_preferred":[
        "Fenoarivo"
    ],
    "wof:name":"Fenoarivo",
    "wof:placetype":"locality"
},
  "geometry": {"coordinates":[46.38333,-21.71667],"type":"Point"}
}