{
  "type": "Feature",
  "properties": {
    "gn:asciiname":"Tsimalazo",
    "gn:country_code":"MG",
    "gn:dem":8,
    "gn:feature_class":"P",
    "gn:feature_code":"PPL",
    "gn:name":"Tsimalazo",
    "gn:population":0,
    "gn:timezone":"Indian/Antananarivo",
    "iso:country":"MG",
    "wof:name":"Tsimalazo",
    "wof:placetype":"locality"
},
  "geometry": {"coordinates":[47.816,-22.349],"type":"Point"}
}