{
  "type": "Feature",
  "properties": {
    "gn:admin1_code":"04",
    "gn:asciiname":"Manambato",
    "gn:country_code":"MG",
    "gn:dem":18,
    "gn:feature_class":"P",
    "gn:feature_code":"PPL",
    "gn:name":"Manambato",
    "gn:population":0,
    "gn:timezone":"Indian/Antananarivo",
    "iso:country":"MG",
    "name:fra_x_preferred":[
        "Manambato"
    ],
    "name:ita_x_preferred":[
        "Manambato"
    ],
    "name:nld_x_preferred":[
        "Manambato"
    ],
    "wof:name":"Manambato",
    "wof:placetype":"locality"
},
  "geometry": {"coordinates":[49.83333,-16.53333],"type":"Point"}
}