{
  "type": "Feature",
  "properties": {
    "gn:admin1_code":"03",
    "gn:asciiname":"Amboabangy",
    "gn:country_code":"MG",
    "gn:dem":26,
    "gn:feature_class":"P",
    "gn:feature_code":"PPL",
    "gn:name":"Amboabangy",
    "gn:population":0,
    "gn:timezone":"Indian/Antananarivo",
    "iso:country":"MG",
    "wof:name":"Amboabangy",
    "wof:placetype":"locality"
},
  "geometry": {"coordinates":[47.98333,-14.45],"type":"Point"}
}