{
  "type": "Feature",
  "properties": {
    "gn:admin1_code":"06",
    "gn:asciiname":"Marofoty",
    "gn:country_code":"MG",
    "gn:dem":35,
    "gn:feature_class":"P",
    "gn:feature_code":"PPL",
    "gn:name":"Marofoty",
    "gn:population":0,
    "gn:timezone":"Indian/Antananarivo",
    "iso:country":"MG",
    "name:fra_x_preferred":[
        "Marofoty"
    ],
    "name:ita_x_preferred":[
        "Marofoty"
    ],
    "name:mlg_x_preferred":[
        "Marofoty"
    ],
    "name:nld_x_preferred":[
        "Marofoty"
    ],
    "wof:name":"Marofoty",
    "wof:placetype":"locality"
},
  "geometry": {"coordinates":[43.56667,-22.93333],"type":"Point"}
}