{
  "type": "Feature",
  "properties": {
    "gn:admin1_code":"06",
    "gn:asciiname":"Bemelo",
    "gn:cc2":"MG",
    "gn:country_code":"MG",
    "gn:dem":451,
    "gn:feature_class":"P",
    "gn:feature_code":"PPL",
    "gn:name":"Bemelo",
    "gn:population":0,
    "gn:timezone":"Indian/Antananarivo",
    "iso:country":"MG",
    "name:und_x_variant":[
        "Bemeloha",
        "Bemelo"
    ],
    "wof:name":"Bemelo",
    "wof:placetype":"locality"
},
  "geometry": {"coordinates":[45.38333,-24.11667000000001],"type":"Point"}
}