{
  "type": "Feature",
  "properties": {
    "gn:admin1_code":"06",
    "gn:asciiname":"Antsasavilahy",
    "gn:country_code":"MG",
    "gn:dem":20,
    "gn:feature_class":"P",
    "gn:feature_code":"PPL",
    "gn:name":"Antsasavilahy",
    "gn:population":0,
    "gn:timezone":"Indian/Antananarivo",
    "iso:country":"MG",
    "wof:name":"Antsasavilahy",
    "wof:placetype":"locality"
},
  "geometry": {"coordinates":[44.58333,-25.26667],"type":"Point"}
}