{
  "type": "Feature",
  "properties": {
    "gn:admin1_code":"06",
    "gn:asciiname":"Fenoambany",
    "gn:country_code":"MG",
    "gn:dem":246,
    "gn:feature_class":"P",
    "gn:feature_code":"PPL",
    "gn:name":"Fenoambany",
    "gn:population":0,
    "gn:timezone":"Indian/Antananarivo",
    "iso:country":"MG",
    "name:fra_x_preferred":[
        "Fenoambany"
    ],
    "name:ita_x_preferred":[
        "Fenoambany"
    ],
    "name:mlg_x_preferred":[
        "Fenoambany"
    ],
    "name:nld_x_preferred":[
        "Fenoambany"
    ],
    "wof:name":"Fenoambany",
    "wof:placetype":"locality"
},
  "geometry": {"coordinates":[44.56667,-23.33333],"type":"Point"}
}