{
  "type": "Feature",
  "properties": {
    "gn:admin1_code":"03",
    "gn:asciiname":"Ambabaky",
    "gn:cc2":"MG",
    "gn:country_code":"MG",
    "gn:dem":123,
    "gn:feature_class":"P",
    "gn:feature_code":"PPL",
    "gn:name":"Ambabaky",
    "gn:population":0,
    "gn:timezone":"Indian/Antananarivo",
    "iso:country":"MG",
    "name:und_x_variant":[
        "Ambabaka",
        "Ambabaky"
    ],
    "wof:name":"Ambabaky",
    "wof:placetype":"locality"
},
  "geometry": {"coordinates":[45.73333,-16.58333],"type":"Point"}
}