{
  "type": "Feature",
  "properties": {
    "iso:country":"MG",
    "name:eng_x_preferred":[
        "Amboasarikely"
    ],
    "qs:gn_adm0_cc":"MG",
    "qs:gn_fcode":"PPLX",
    "qs:gn_local":1070940,
    "qs:gn_nam_loc":"Antananarivo",
    "qs:gn_namadm1":"05",
    "qs:gn_name":"Amboasarikely",
    "qs:local_max":1202,
    "qs:local_sum":1694,
    "qs:localhoods":7,
    "qs:name":"Amboasarikely",
    "qs:name_adm0":"Madagascar",
    "qs:name_adm1":"Antananarivo",
    "qs:name_adm2":"Antananarivo Avaradrano",
    "qs:name_local":"Antananarivo",
    "qs:photo_max":62,
    "qs:photo_sum":272,
    "qs:placetype":"Suburb",
    "qs:quad_count":16,
    "qs:woe_adm0":23424883,
    "qs:woe_adm1":2346150,
    "qs:woe_adm2":23706533,
    "qs:woe_lau":0,
    "qs:woe_local":1358594,
    "qs:woe_ver":"7.10.0",
    "wof:lang":[
        "eng"
    ],
    "wof:name":"Amboasarikely",
    "wof:placetype":"neighbourhood"
},
  "geometry": {"coordinates":[47.51338,-18.894707],"type":"Point"}
}