{
  "type": "Feature",
  "properties": {
    "gn:admin1_code":"02",
    "gn:asciiname":"Fotakiloha",
    "gn:country_code":"MG",
    "gn:dem":948,
    "gn:feature_class":"P",
    "gn:feature_code":"PPL",
    "gn:name":"Fotakiloha",
    "gn:population":0,
    "gn:timezone":"Indian/Antananarivo",
    "iso:country":"MG",
    "wof:name":"Fotakiloha",
    "wof:placetype":"locality"
},
  "geometry": {"coordinates":[46.68333,-21.85],"type":"Point"}
}