{
  "type": "Feature",
  "properties": {
    "gn:admin1_code":"5.0",
    "gn:asciiname":"Vakivoha",
    "gn:country_code":"MG",
    "gn:dem":1301,
    "gn:feature_class":"P",
    "gn:feature_code":"PPL",
    "gn:name":"Vakivoha",
    "gn:population":0,
    "gn:timezone":"Indian/Antananarivo",
    "iso:country":"MG",
    "wof:name":"Vakivoha",
    "wof:placetype":"locality"
},
  "geometry": {"coordinates":[47.13333,-18.96667],"type":"Point"}
}