{
  "type": "Feature",
  "properties": {
    "gn:admin1_code":"01",
    "gn:asciiname":"Bekona",
    "gn:country_code":"MG",
    "gn:dem":14,
    "gn:feature_class":"P",
    "gn:feature_code":"PPL",
    "gn:name":"Bekona",
    "gn:population":0,
    "gn:timezone":"Indian/Antananarivo",
    "iso:country":"MG",
    "wof:name":"Bekona",
    "wof:placetype":"locality"
},
  "geometry": {"coordinates":[47.98333,-14.05],"type":"Point"}
}