{
  "type": "Feature",
  "properties": {
    "gn:admin1_code":"01",
    "gn:asciiname":"Ampanavoana",
    "gn:cc2":"MG",
    "gn:country_code":"MG",
    "gn:dem":-9999,
    "gn:feature_class":"P",
    "gn:feature_code":"PPL",
    "gn:name":"Ampanavoana",
    "gn:population":0,
    "gn:timezone":"Indian/Antananarivo",
    "iso:country":"MG",
    "name:und_x_variant":[
        "Ampanovohana",
        "Ampanavoana"
    ],
    "wof:name":"Ampanavoana",
    "wof:placetype":"locality"
},
  "geometry": {"coordinates":[50.36667,-15.68333],"type":"Point"}
}