{
  "type": "Feature",
  "properties": {
    "gn:admin1_code":"05",
    "gn:asciiname":"Ambodifarihy",
    "gn:country_code":"MG",
    "gn:dem":759,
    "gn:feature_class":"P",
    "gn:feature_code":"PPL",
    "gn:name":"Ambodifarihy",
    "gn:population":0,
    "gn:timezone":"Indian/Antananarivo",
    "iso:country":"MG",
    "wof:name":"Ambodifarihy",
    "wof:placetype":"locality"
},
  "geometry": {"coordinates":[46.03333,-19.08333],"type":"Point"}
}