{
  "type": "Feature",
  "properties": {
    "gn:admin1_code":"06",
    "gn:asciiname":"Marovotry",
    "gn:country_code":"MG",
    "gn:dem":473,
    "gn:feature_class":"P",
    "gn:feature_code":"PPL",
    "gn:name":"Marovotry",
    "gn:population":0,
    "gn:timezone":"Indian/Antananarivo",
    "iso:country":"MG",
    "wof:name":"Marovotry",
    "wof:placetype":"locality"
},
  "geometry": {"coordinates":[44.46667,-23.21667],"type":"Point"}
}