{
  "type": "Feature",
  "properties": {
    "gn:admin1_code":"01",
    "gn:asciiname":"Ankirity",
    "gn:country_code":"MG",
    "gn:dem":28,
    "gn:feature_class":"P",
    "gn:feature_code":"PPL",
    "gn:name":"Ankirity",
    "gn:population":0,
    "gn:timezone":"Indian/Antananarivo",
    "iso:country":"MG",
    "wof:name":"Ankirity",
    "wof:placetype":"locality"
},
  "geometry": {"coordinates":[50.35,-15.56667],"type":"Point"}
}