{
  "type": "Feature",
  "properties": {
    "gn:admin1_code":"06",
    "gn:asciiname":"Ankaranabo Avaratra",
    "gn:cc2":"MG",
    "gn:country_code":"MG",
    "gn:dem":422,
    "gn:feature_class":"P",
    "gn:feature_code":"PPL",
    "gn:name":"Ankaranabo Avaratra",
    "gn:population":0,
    "gn:timezone":"Indian/Antananarivo",
    "iso:country":"MG",
    "name:fra_x_preferred":[
        "Ankaranabo Nord"
    ],
    "name:ita_x_preferred":[
        "Ankaranabo Nord"
    ],
    "name:mlg_x_preferred":[
        "Ankaranabo Nord"
    ],
    "name:nld_x_preferred":[
        "Ankaranabo Nord"
    ],
    "name:und_x_variant":[
        "Ankaranabo Nord",
        "Ankaranabo Avaratra"
    ],
    "wof:name":"Ankaranabo Avaratra",
    "wof:placetype":"locality"
},
  "geometry": {"coordinates":[45.28333,-24.18333],"type":"Point"}
}