{
  "type": "Feature",
  "properties": {
    "gn:admin1_code":"06",
    "gn:asciiname":"Bezavo",
    "gn:country_code":"MG",
    "gn:dem":37,
    "gn:feature_class":"P",
    "gn:feature_code":"PPL",
    "gn:name":"Bezavo",
    "gn:population":0,
    "gn:timezone":"Indian/Antananarivo",
    "iso:country":"MG",
    "wof:name":"Bezavo",
    "wof:placetype":"locality"
},
  "geometry": {"coordinates":[44.58333,-25.13333],"type":"Point"}
}