{
  "type": "Feature",
  "properties": {
    "gn:admin1_code":"02",
    "gn:asciiname":"Nihaonana",
    "gn:country_code":"MG",
    "gn:dem":37,
    "gn:feature_class":"P",
    "gn:feature_code":"PPL",
    "gn:name":"Nihaonana",
    "gn:population":0,
    "gn:timezone":"Indian/Antananarivo",
    "iso:country":"MG",
    "name:fra_x_preferred":[
        "Nihaonana"
    ],
    "name:ita_x_preferred":[
        "Nihaonana"
    ],
    "name:mlg_x_preferred":[
        "Nihaonana"
    ],
    "name:nld_x_preferred":[
        "Nihaonana"
    ],
    "wof:name":"Nihaonana",
    "wof:placetype":"locality"
},
  "geometry": {"coordinates":[48.05,-21.55],"type":"Point"}
}