{
  "type": "Feature",
  "properties": {
    "gn:admin1_code":"01",
    "gn:asciiname":"Anjavinihavana",
    "gn:cc2":"MG",
    "gn:country_code":"MG",
    "gn:dem":575,
    "gn:feature_class":"P",
    "gn:feature_code":"PPL",
    "gn:name":"Anjavinihavana",
    "gn:population":0,
    "gn:timezone":"Indian/Antananarivo",
    "iso:country":"MG",
    "name:und_x_variant":[
        "Anjavimihavana",
        "Anjavinihavana"
    ],
    "wof:name":"Anjavinihavana",
    "wof:placetype":"locality"
},
  "geometry": {"coordinates":[49.25,-12.53333],"type":"Point"}
}