{
  "type": "Feature",
  "properties": {
    "gn:admin1_code":"6.0",
    "gn:asciiname":"Tampolo Andrefana",
    "gn:cc2":"MG",
    "gn:country_code":"MG",
    "gn:dem":11,
    "gn:feature_class":"P",
    "gn:feature_code":"PPL",
    "gn:name":"Tampolo Andrefana",
    "gn:population":0,
    "gn:timezone":"Indian/Antananarivo",
    "iso:country":"MG",
    "name:und_x_variant":[
        "Tampolo Ouest",
        "Tampolo",
        "Tampolo Andrefana"
    ],
    "wof:name":"Tampolo Andrefana",
    "wof:placetype":"locality"
},
  "geometry": {"coordinates":[43.71667,-21.48333],"type":"Point"}
}