{
  "type": "Feature",
  "properties": {
    "gn:admin1_code":"04",
    "gn:asciiname":"Manarirano",
    "gn:country_code":"MG",
    "gn:dem":437,
    "gn:feature_class":"P",
    "gn:feature_code":"PPL",
    "gn:name":"Manarirano",
    "gn:population":0,
    "gn:timezone":"Indian/Antananarivo",
    "iso:country":"MG",
    "wof:name":"Manarirano",
    "wof:placetype":"locality"
},
  "geometry": {"coordinates":[49.41667,-16.31667],"type":"Point"}
}