{
  "type": "Feature",
  "properties": {
    "gn:admin1_code":"02",
    "gn:asciiname":"Analamary",
    "gn:country_code":"MG",
    "gn:dem":95,
    "gn:feature_class":"P",
    "gn:feature_code":"PPL",
    "gn:name":"Analamary",
    "gn:population":0,
    "gn:timezone":"Indian/Antananarivo",
    "iso:country":"MG",
    "wof:name":"Analamary",
    "wof:placetype":"locality"
},
  "geometry": {"coordinates":[47.38333,-23.15],"type":"Point"}
}