{
  "type": "Feature",
  "properties": {
    "gn:admin1_code":"02",
    "gn:asciiname":"Anaviavy",
    "gn:country_code":"MG",
    "gn:dem":759,
    "gn:feature_class":"P",
    "gn:feature_code":"PPL",
    "gn:name":"Anaviavy",
    "gn:population":0,
    "gn:timezone":"Indian/Antananarivo",
    "iso:country":"MG",
    "wof:name":"Anaviavy",
    "wof:placetype":"locality"
},
  "geometry": {"coordinates":[47.05,-22.35],"type":"Point"}
}