{
  "type": "Feature",
  "properties": {
    "gn:admin1_code":"04",
    "gn:asciiname":"Ambatomaneno",
    "gn:country_code":"MG",
    "gn:dem":85,
    "gn:feature_class":"P",
    "gn:feature_code":"PPL",
    "gn:name":"Ambatomaneno",
    "gn:population":0,
    "gn:timezone":"Indian/Antananarivo",
    "iso:country":"MG",
    "wof:name":"Ambatomaneno",
    "wof:placetype":"locality"
},
  "geometry": {"coordinates":[49.21667,-17.36667000000001],"type":"Point"}
}