{
  "type": "Feature",
  "properties": {
    "gn:admin1_code":"04",
    "gn:asciiname":"Mantrikiny",
    "gn:country_code":"MG",
    "gn:dem":734,
    "gn:feature_class":"P",
    "gn:feature_code":"PPL",
    "gn:name":"Mantrikiny",
    "gn:population":0,
    "gn:timezone":"Indian/Antananarivo",
    "iso:country":"MG",
    "wof:name":"Mantrikiny",
    "wof:placetype":"locality"
},
  "geometry": {"coordinates":[47.88333,-20.35],"type":"Point"}
}