{
  "type": "Feature",
  "properties": {
    "gn:admin1_code":"04",
    "gn:asciiname":"Amboditavolo",
    "gn:cc2":"MG",
    "gn:country_code":"MG",
    "gn:dem":447,
    "gn:feature_class":"P",
    "gn:feature_code":"PPL",
    "gn:name":"Amboditavolo",
    "gn:population":0,
    "gn:timezone":"Indian/Antananarivo",
    "iso:country":"MG",
    "name:und_x_variant":[
        "Amboditavoto",
        "Amboditavolo"
    ],
    "wof:name":"Amboditavolo",
    "wof:placetype":"locality"
},
  "geometry": {"coordinates":[49.53333,-15.81667],"type":"Point"}
}