{
  "type": "Feature",
  "properties": {
    "gn:admin1_code":"06",
    "gn:asciiname":"Ambiabe",
    "gn:cc2":"MG",
    "gn:country_code":"MG",
    "gn:dem":136,
    "gn:feature_class":"P",
    "gn:feature_code":"PPL",
    "gn:name":"Ambiabe",
    "gn:population":0,
    "gn:timezone":"Indian/Antananarivo",
    "iso:country":"MG",
    "name:und_x_variant":[
        "Amhiabe",
        "Ambiabe"
    ],
    "wof:name":"Ambiabe",
    "wof:placetype":"locality"
},
  "geometry": {"coordinates":[44.15,-21.25],"type":"Point"}
}