{
  "type": "Feature",
  "properties": {
    "gn:admin1_code":"06",
    "gn:asciiname":"Maintapaka",
    "gn:country_code":"MG",
    "gn:dem":93,
    "gn:feature_class":"P",
    "gn:feature_code":"PPL",
    "gn:name":"Maintapaka",
    "gn:population":0,
    "gn:timezone":"Indian/Antananarivo",
    "iso:country":"MG",
    "wof:name":"Maintapaka",
    "wof:placetype":"locality"
},
  "geometry": {"coordinates":[44.05,-21.18333],"type":"Point"}
}