{
  "type": "Feature",
  "properties": {
    "gn:admin1_code":"02",
    "gn:asciiname":"Bedihy",
    "gn:country_code":"MG",
    "gn:dem":1463,
    "gn:feature_class":"P",
    "gn:feature_code":"PPL",
    "gn:name":"Bedihy",
    "gn:population":0,
    "gn:timezone":"Indian/Antananarivo",
    "iso:country":"MG",
    "wof:name":"Bedihy",
    "wof:placetype":"locality"
},
  "geometry": {"coordinates":[46.93333,-20.61667000000001],"type":"Point"}
}