{
  "type": "Feature",
  "properties": {
    "gn:admin1_code":"06",
    "gn:asciiname":"Haboke",
    "gn:country_code":"MG",
    "gn:dem":272,
    "gn:feature_class":"P",
    "gn:feature_code":"PPL",
    "gn:name":"Haboke",
    "gn:population":0,
    "gn:timezone":"Indian/Antananarivo",
    "iso:country":"MG",
    "wof:name":"Haboke",
    "wof:placetype":"locality"
},
  "geometry": {"coordinates":[44.45,-24.68333],"type":"Point"}
}