{
  "type": "Feature",
  "properties": {
    "gn:admin1_code":"06",
    "gn:asciiname":"Kiliarivo",
    "gn:country_code":"MG",
    "gn:dem":381,
    "gn:feature_class":"P",
    "gn:feature_code":"PPL",
    "gn:name":"Kiliarivo",
    "gn:population":0,
    "gn:timezone":"Indian/Antananarivo",
    "iso:country":"MG",
    "wof:name":"Kiliarivo",
    "wof:placetype":"locality"
},
  "geometry": {"coordinates":[45.13333,-22.01667],"type":"Point"}
}