{
  "type": "Feature",
  "properties": {
    "gn:admin1_code":"06",
    "gn:asciiname":"Ampandra II",
    "gn:cc2":"MG",
    "gn:country_code":"MG",
    "gn:dem":521,
    "gn:feature_class":"P",
    "gn:feature_code":"PPL",
    "gn:name":"Ampandra II",
    "gn:population":0,
    "gn:timezone":"Indian/Antananarivo",
    "iso:country":"MG",
    "name:und_x_variant":[
        "Ampandra 2",
        "Ampandra II"
    ],
    "wof:name":"Ampandra II",
    "wof:placetype":"locality"
},
  "geometry": {"coordinates":[44.55,-22.95],"type":"Point"}
}