{
  "type": "Feature",
  "properties": {
    "gn:admin1_code":"02",
    "gn:asciiname":"Marofototra",
    "gn:country_code":"MG",
    "gn:dem":65,
    "gn:feature_class":"P",
    "gn:feature_code":"PPL",
    "gn:name":"Marofototra",
    "gn:population":0,
    "gn:timezone":"Indian/Antananarivo",
    "iso:country":"MG",
    "name:fra_x_preferred":[
        "Marofototra"
    ],
    "name:ita_x_preferred":[
        "Marofototra"
    ],
    "name:mlg_x_preferred":[
        "Marofototra"
    ],
    "name:nld_x_preferred":[
        "Marofototra"
    ],
    "wof:name":"Marofototra",
    "wof:placetype":"locality"
},
  "geometry": {"coordinates":[48.16667,-20.86667000000001],"type":"Point"}
}