{
  "type": "Feature",
  "properties": {
    "gn:admin1_code":"05",
    "gn:asciiname":"Imerintsiatosika",
    "gn:country_code":"MG",
    "gn:dem":1296,
    "gn:feature_class":"P",
    "gn:feature_code":"PPL",
    "gn:name":"Imerintsiatosika",
    "gn:population":0,
    "gn:timezone":"Indian/Antananarivo",
    "iso:country":"MG",
    "name:fra_x_preferred":[
        "Imerintsiatosika"
    ],
    "name:mlg_x_preferred":[
        "Imerintsiatosika"
    ],
    "name:nld_x_preferred":[
        "Imeritsitosika"
    ],
    "wof:name":"Imerintsiatosika",
    "wof:placetype":"locality"
},
  "geometry": {"coordinates":[47.31667,-18.98333],"type":"Point"}
}