{
  "type": "Feature",
  "properties": {
    "gn:admin1_code":"3.0",
    "gn:asciiname":"Tsimalia",
    "gn:country_code":"MG",
    "gn:dem":13,
    "gn:feature_class":"P",
    "gn:feature_code":"PPL",
    "gn:name":"Tsimalia",
    "gn:population":0,
    "gn:timezone":"Indian/Antananarivo",
    "iso:country":"MG",
    "wof:name":"Tsimalia",
    "wof:placetype":"locality"
},
  "geometry": {"coordinates":[44.56667,-16.65],"type":"Point"}
}