{
  "type": "Feature",
  "properties": {
    "gn:admin1_code":"03",
    "gn:asciiname":"Anjiamangerana",
    "gn:country_code":"MG",
    "gn:dem":184,
    "gn:feature_class":"P",
    "gn:feature_code":"PPL",
    "gn:name":"Anjiamangerana",
    "gn:population":0,
    "gn:timezone":"Indian/Antananarivo",
    "iso:country":"MG",
    "wof:name":"Anjiamangerana",
    "wof:placetype":"locality"
},
  "geometry": {"coordinates":[47.66667,-15.16667],"type":"Point"}
}