{
  "type": "Feature",
  "properties": {
    "gn:admin1_code":"4.0",
    "gn:asciiname":"Tanambaa-Vohitsimanga",
    "gn:country_code":"MG",
    "gn:dem":69,
    "gn:feature_class":"P",
    "gn:feature_code":"PPL",
    "gn:name":"Tanambaa-Vohitsimanga",
    "gn:population":0,
    "gn:timezone":"Indian/Antananarivo",
    "iso:country":"MG",
    "wof:name":"Tanambaa-Vohitsimanga",
    "wof:placetype":"locality"
},
  "geometry": {"coordinates":[49.28333,-17.03333],"type":"Point"}
}