{
  "type": "Feature",
  "properties": {
    "gn:admin1_code":"04",
    "gn:asciiname":"Andilana Avaratra",
    "gn:cc2":"MG",
    "gn:country_code":"MG",
    "gn:dem":756,
    "gn:feature_class":"P",
    "gn:feature_code":"PPL",
    "gn:name":"Andilana Avaratra",
    "gn:population":0,
    "gn:timezone":"Indian/Antananarivo",
    "iso:country":"MG",
    "name:und_x_variant":[
        "Andilana",
        "Andilana Avaratra"
    ],
    "wof:name":"Andilana Avaratra",
    "wof:placetype":"locality"
},
  "geometry": {"coordinates":[48.55,-17.35],"type":"Point"}
}