{
  "type": "Feature",
  "properties": {
    "gn:admin1_code":"06",
    "gn:asciiname":"Malangiriaka",
    "gn:cc2":"MG",
    "gn:country_code":"MG",
    "gn:dem":57,
    "gn:feature_class":"P",
    "gn:feature_code":"PPL",
    "gn:name":"Malangiriaka",
    "gn:population":0,
    "gn:timezone":"Indian/Antananarivo",
    "iso:country":"MG",
    "name:und_x_variant":[
        "Malangirinka",
        "Malangiriaka"
    ],
    "wof:name":"Malangiriaka",
    "wof:placetype":"locality"
},
  "geometry": {"coordinates":[43.91667,-24.58333],"type":"Point"}
}