{
  "type": "Feature",
  "properties": {
    "gn:admin1_code":"05",
    "gn:asciiname":"Anjamana",
    "gn:country_code":"MG",
    "gn:dem":1679,
    "gn:feature_class":"P",
    "gn:feature_code":"PPL",
    "gn:name":"Anjamana",
    "gn:population":0,
    "gn:timezone":"Indian/Antananarivo",
    "iso:country":"MG",
    "wof:name":"Anjamana",
    "wof:placetype":"locality"
},
  "geometry": {"coordinates":[47.18333,-19.68333],"type":"Point"}
}