{
  "type": "Feature",
  "properties": {
    "gn:admin1_code":"03",
    "gn:asciiname":"Besaony",
    "gn:country_code":"MG",
    "gn:dem":49,
    "gn:feature_class":"P",
    "gn:feature_code":"PPL",
    "gn:name":"Besaony",
    "gn:population":0,
    "gn:timezone":"Indian/Antananarivo",
    "iso:country":"MG",
    "wof:name":"Besaony",
    "wof:placetype":"locality"
},
  "geometry": {"coordinates":[47.16667,-16.48333],"type":"Point"}
}