{
  "type": "Feature",
  "properties": {
    "gn:admin1_code":"06",
    "gn:asciiname":"Andriabe",
    "gn:country_code":"MG",
    "gn:dem":772,
    "gn:feature_class":"P",
    "gn:feature_code":"PPL",
    "gn:name":"Andriabe",
    "gn:population":0,
    "gn:timezone":"Indian/Antananarivo",
    "iso:country":"MG",
    "wof:name":"Andriabe",
    "wof:placetype":"locality"
},
  "geometry": {"coordinates":[45.75,-23.91667],"type":"Point"}
}