{
  "type": "Feature",
  "properties": {
    "gn:admin1_code":"05",
    "gn:asciiname":"Merimanjaka",
    "gn:country_code":"MG",
    "gn:dem":1230,
    "gn:feature_class":"P",
    "gn:feature_code":"PPL",
    "gn:name":"Merimanjaka",
    "gn:population":0,
    "gn:timezone":"Indian/Antananarivo",
    "iso:country":"MG",
    "wof:name":"Merimanjaka",
    "wof:placetype":"locality"
},
  "geometry": {"coordinates":[47.33333,-18.38333],"type":"Point"}
}