{
  "type": "Feature",
  "properties": {
    "gn:admin1_code":"04",
    "gn:asciiname":"Angoja",
    "gn:country_code":"MG",
    "gn:dem":755,
    "gn:feature_class":"P",
    "gn:feature_code":"PPL",
    "gn:name":"Angoja",
    "gn:population":0,
    "gn:timezone":"Indian/Antananarivo",
    "iso:country":"MG",
    "wof:name":"Angoja",
    "wof:placetype":"locality"
},
  "geometry": {"coordinates":[48.48333,-17.65],"type":"Point"}
}