{
  "type": "Feature",
  "properties": {
    "gn:admin1_code":"02",
    "gn:asciiname":"Menaretra",
    "gn:country_code":"MG",
    "gn:dem":55,
    "gn:feature_class":"P",
    "gn:feature_code":"PPL",
    "gn:name":"Menaretra",
    "gn:population":0,
    "gn:timezone":"Indian/Antananarivo",
    "iso:country":"MG",
    "wof:name":"Menaretra",
    "wof:placetype":"locality"
},
  "geometry": {"coordinates":[47.38333,-23.46667],"type":"Point"}
}