{
  "type": "Feature",
  "properties": {
    "gn:admin1_code":"2.0",
    "gn:asciiname":"Verangerana",
    "gn:country_code":"MG",
    "gn:dem":5,
    "gn:feature_class":"P",
    "gn:feature_code":"PPL",
    "gn:name":"Verangerana",
    "gn:population":0,
    "gn:timezone":"Indian/Antananarivo",
    "iso:country":"MG",
    "wof:name":"Verangerana",
    "wof:placetype":"locality"
},
  "geometry": {"coordinates":[48.21667,-21.63333],"type":"Point"}
}