{
  "type": "Feature",
  "properties": {
    "gn:admin1_code":"03",
    "gn:asciiname":"Antsaviny",
    "gn:country_code":"MG",
    "gn:dem":136,
    "gn:feature_class":"P",
    "gn:feature_code":"PPL",
    "gn:name":"Antsaviny",
    "gn:population":0,
    "gn:timezone":"Indian/Antananarivo",
    "iso:country":"MG",
    "wof:name":"Antsaviny",
    "wof:placetype":"locality"
},
  "geometry": {"coordinates":[48.15,-14.33333],"type":"Point"}
}