{
  "type": "Feature",
  "properties": {
    "gn:admin1_code":"06",
    "gn:asciiname":"Matsandry Atsimo",
    "gn:cc2":"MG",
    "gn:country_code":"MG",
    "gn:dem":22,
    "gn:feature_class":"P",
    "gn:feature_code":"PPL",
    "gn:name":"Matsandry Atsimo",
    "gn:population":0,
    "gn:timezone":"Indian/Antananarivo",
    "iso:country":"MG",
    "name:und_x_variant":[
        "Mahatsanary",
        "Matsandry",
        "Mahatsandty",
        "Matsandry Atsimo"
    ],
    "wof:name":"Matsandry Atsimo",
    "wof:placetype":"locality"
},
  "geometry": {"coordinates":[44.48333,-25.26667],"type":"Point"}
}