{
  "type": "Feature",
  "properties": {
    "gn:admin1_code":"6.0",
    "gn:asciiname":"Vatovary",
    "gn:country_code":"MG",
    "gn:dem":18,
    "gn:feature_class":"P",
    "gn:feature_code":"PPL",
    "gn:name":"Vatovary",
    "gn:population":0,
    "gn:timezone":"Indian/Antananarivo",
    "iso:country":"MG",
    "wof:name":"Vatovary",
    "wof:placetype":"locality"
},
  "geometry": {"coordinates":[46.85,-24.95],"type":"Point"}
}