{
  "type": "Feature",
  "properties": {
    "gn:country":"MG",
    "gn:fcode":"PPL",
    "gn:pop":36082,
    "iso:country":"MG",
    "name:ceb_x_preferred":[
        "Amboasary"
    ],
    "name:deu_x_preferred":[
        "Amboasary"
    ],
    "name:eng_x_preferred":[
        "Amboasary"
    ],
    "name:fas_x_preferred":[
        "\u0627\u0645\u0628\u0648\u0627\u0633\u0627\u0631\u06cc"
    ],
    "name:fra_x_preferred":[
        "Amboasary"
    ],
    "name:nld_x_preferred":[
        "Amboasary"
    ],
    "name:pol_x_preferred":[
        "Amboasary"
    ],
    "name:spa_x_preferred":[
        "Amboasary"
    ],
    "name:swe_x_preferred":[
        "Amboasary"
    ],
    "name:unk_x_variant":[
        "Amboasary Sud"
    ],
    "qs:name":"Amboasary",
    "qs:photos_9r":0,
    "qs:photos_sr":0,
    "qs:pop_sr":"7",
    "wd:wordcount":46,
    "wof:name":"Amboasary",
    "wof:placetype":"locality",
    "wof:population":36082
},
  "geometry": {"coordinates":[46.38333,-25.03333],"type":"Point"}
}