{
  "type": "Feature",
  "properties": {
    "gn:admin1_code":"06",
    "gn:asciiname":"Antsakoandrevangone",
    "gn:cc2":"MG",
    "gn:country_code":"MG",
    "gn:dem":4,
    "gn:feature_class":"P",
    "gn:feature_code":"PPL",
    "gn:name":"Antsakoandrevangone",
    "gn:population":0,
    "gn:timezone":"Indian/Antananarivo",
    "iso:country":"MG",
    "name:und_x_variant":[
        "Antaskoandrevangone",
        "Antsakoandrevangone"
    ],
    "wof:name":"Antsakoandrevangone",
    "wof:placetype":"locality"
},
  "geometry": {"coordinates":[43.35,-21.78333],"type":"Point"}
}