{
  "type": "Feature",
  "properties": {
    "gn:admin1_code":"6.0",
    "gn:asciiname":"Sihanamaro",
    "gn:country_code":"MG",
    "gn:dem":198,
    "gn:feature_class":"P",
    "gn:feature_code":"PPL",
    "gn:name":"Sihanamaro",
    "gn:population":0,
    "gn:timezone":"Indian/Antananarivo",
    "iso:country":"MG",
    "wof:name":"Sihanamaro",
    "wof:placetype":"locality"
},
  "geometry": {"coordinates":[45.76667,-25.18333],"type":"Point"}
}