{
  "type": "Feature",
  "properties": {
    "gn:admin1_code":"04",
    "gn:asciiname":"Ambodivoasihy",
    "gn:country_code":"MG",
    "gn:dem":10,
    "gn:feature_class":"P",
    "gn:feature_code":"PPL",
    "gn:name":"Ambodivoasihy",
    "gn:population":0,
    "gn:timezone":"Indian/Antananarivo",
    "iso:country":"MG",
    "wof:name":"Ambodivoasihy",
    "wof:placetype":"locality"
},
  "geometry": {"coordinates":[49.65,-16.75],"type":"Point"}
}