{
  "type": "Feature",
  "properties": {
    "gn:admin1_code":"01",
    "gn:asciiname":"Ambodiampa",
    "gn:country_code":"MG",
    "gn:dem":27,
    "gn:feature_class":"P",
    "gn:feature_code":"PPL",
    "gn:name":"Ambodiampa",
    "gn:population":0,
    "gn:timezone":"Indian/Antananarivo",
    "iso:country":"MG",
    "wof:name":"Ambodiampa",
    "wof:placetype":"locality"
},
  "geometry": {"coordinates":[49.08333,-13.08333],"type":"Point"}
}