{
  "type": "Feature",
  "properties": {
    "gn:admin1_code":"02",
    "gn:asciiname":"Nosoa",
    "gn:country_code":"MG",
    "gn:dem":8,
    "gn:feature_class":"P",
    "gn:feature_code":"PPL",
    "gn:name":"Nosoa",
    "gn:population":0,
    "gn:timezone":"Indian/Antananarivo",
    "iso:country":"MG",
    "wof:name":"Nosoa",
    "wof:placetype":"locality"
},
  "geometry": {"coordinates":[47.48333,-23.76667],"type":"Point"}
}