{
  "type": "Feature",
  "properties": {
    "gn:admin1_code":"04",
    "gn:asciiname":"Andavakamenarana",
    "gn:cc2":"MG",
    "gn:country_code":"MG",
    "gn:dem":18,
    "gn:feature_class":"P",
    "gn:feature_code":"PPL",
    "gn:name":"Andavakamenarana",
    "gn:population":0,
    "gn:timezone":"Indian/Antananarivo",
    "iso:country":"MG",
    "name:und_x_variant":[
        "Andavamenara",
        "Andavakamenarana"
    ],
    "wof:name":"Andavakamenarana",
    "wof:placetype":"locality"
},
  "geometry": {"coordinates":[49.13333,-18.88333],"type":"Point"}
}