{
  "type": "Feature",
  "properties": {
    "gn:admin1_code":"02",
    "gn:asciiname":"Hazomena",
    "gn:country_code":"MG",
    "gn:dem":51,
    "gn:feature_class":"P",
    "gn:feature_code":"PPL",
    "gn:name":"Hazomena",
    "gn:population":0,
    "gn:timezone":"Indian/Antananarivo",
    "iso:country":"MG",
    "wof:name":"Hazomena",
    "wof:placetype":"locality"
},
  "geometry": {"coordinates":[47.55,-22.21667],"type":"Point"}
}