{
  "type": "Feature",
  "properties": {
    "gn:admin1_code":"06",
    "gn:asciiname":"Ambondro-Mandeha",
    "gn:country_code":"MG",
    "gn:dem":455,
    "gn:feature_class":"P",
    "gn:feature_code":"PPL",
    "gn:name":"Ambondro-Mandeha",
    "gn:population":0,
    "gn:timezone":"Indian/Antananarivo",
    "iso:country":"MG",
    "wof:name":"Ambondro-Mandeha",
    "wof:placetype":"locality"
},
  "geometry": {"coordinates":[44.48333,-23.11667000000001],"type":"Point"}
}