{
  "type": "Feature",
  "properties": {
    "gn:admin1_code":"04",
    "gn:asciiname":"Ambohipeno",
    "gn:country_code":"MG",
    "gn:dem":43,
    "gn:feature_class":"P",
    "gn:feature_code":"PPL",
    "gn:name":"Ambohipeno",
    "gn:population":0,
    "gn:timezone":"Indian/Antananarivo",
    "iso:country":"MG",
    "wof:name":"Ambohipeno",
    "wof:placetype":"locality"
},
  "geometry": {"coordinates":[48.73333,-19.41667],"type":"Point"}
}