{
  "type": "Feature",
  "properties": {
    "gn:admin1_code":"06",
    "gn:asciiname":"Manalihara",
    "gn:country_code":"MG",
    "gn:dem":333,
    "gn:feature_class":"P",
    "gn:feature_code":"PPL",
    "gn:name":"Manalihara",
    "gn:population":0,
    "gn:timezone":"Indian/Antananarivo",
    "iso:country":"MG",
    "wof:name":"Manalihara",
    "wof:placetype":"locality"
},
  "geometry": {"coordinates":[45.48333,-24.65],"type":"Point"}
}