{
  "type": "Feature",
  "properties": {
    "gn:admin1_code":"05",
    "gn:asciiname":"Antamboho",
    "gn:country_code":"MG",
    "gn:dem":1139,
    "gn:feature_class":"P",
    "gn:feature_code":"PPL",
    "gn:name":"Antamboho",
    "gn:population":0,
    "gn:timezone":"Indian/Antananarivo",
    "iso:country":"MG",
    "wof:name":"Antamboho",
    "wof:placetype":"locality"
},
  "geometry": {"coordinates":[47.03333,-18.63333],"type":"Point"}
}