{
  "type": "Feature",
  "properties": {
    "gn:admin1_code":"06",
    "gn:asciiname":"Benonoka",
    "gn:country_code":"MG",
    "gn:dem":859,
    "gn:feature_class":"P",
    "gn:feature_code":"PPL",
    "gn:name":"Benonoka",
    "gn:population":0,
    "gn:timezone":"Indian/Antananarivo",
    "iso:country":"MG",
    "wof:name":"Benonoka",
    "wof:placetype":"locality"
},
  "geometry": {"coordinates":[45.73333,-24.05],"type":"Point"}
}