{
  "type": "Feature",
  "properties": {
    "gn:admin1_code":"05",
    "gn:asciiname":"Mahatsinjorano",
    "gn:country_code":"MG",
    "gn:dem":530,
    "gn:feature_class":"P",
    "gn:feature_code":"PPL",
    "gn:name":"Mahatsinjorano",
    "gn:population":0,
    "gn:timezone":"Indian/Antananarivo",
    "iso:country":"MG",
    "wof:name":"Mahatsinjorano",
    "wof:placetype":"locality"
},
  "geometry": {"coordinates":[46.05,-19.93333],"type":"Point"}
}