{
  "type": "Feature",
  "properties": {
    "gn:admin1_code":"02",
    "gn:asciiname":"Manaovasoa",
    "gn:country_code":"MG",
    "gn:dem":1006,
    "gn:feature_class":"P",
    "gn:feature_code":"PPL",
    "gn:name":"Manaovasoa",
    "gn:population":0,
    "gn:timezone":"Indian/Antananarivo",
    "iso:country":"MG",
    "wof:name":"Manaovasoa",
    "wof:placetype":"locality"
},
  "geometry": {"coordinates":[45.91667,-22.55],"type":"Point"}
}