{
  "type": "Feature",
  "properties": {
    "gn:admin1_code":"03",
    "gn:asciiname":"Ambarijeby Atsimo",
    "gn:cc2":"MG",
    "gn:country_code":"MG",
    "gn:dem":38,
    "gn:feature_class":"P",
    "gn:feature_code":"PPL",
    "gn:name":"Ambarijeby Atsimo",
    "gn:population":0,
    "gn:timezone":"Indian/Antananarivo",
    "iso:country":"MG",
    "name:und_x_variant":[
        "Ambarijeby",
        "Ambarijeby Atsimo"
    ],
    "wof:name":"Ambarijeby Atsimo",
    "wof:placetype":"locality"
},
  "geometry": {"coordinates":[47.95,-15.43333],"type":"Point"}
}