{
  "type": "Feature",
  "properties": {
    "gn:admin1_code":"1.0",
    "gn:asciiname":"Saramby",
    "gn:cc2":"MG",
    "gn:country_code":"MG",
    "gn:dem":43,
    "gn:feature_class":"P",
    "gn:feature_code":"PPL",
    "gn:name":"Saramby",
    "gn:population":0,
    "gn:timezone":"Indian/Antananarivo",
    "iso:country":"MG",
    "name:und_x_variant":[
        "Soramby",
        "Saramby"
    ],
    "wof:name":"Saramby",
    "wof:placetype":"locality"
},
  "geometry": {"coordinates":[50.05,-14.51667],"type":"Point"}
}