{
  "type": "Feature",
  "properties": {
    "gn:admin1_code":"03",
    "gn:asciiname":"Antanatanamirafy",
    "gn:country_code":"MG",
    "gn:dem":55,
    "gn:feature_class":"P",
    "gn:feature_code":"PPL",
    "gn:name":"Antanatanamirafy",
    "gn:population":0,
    "gn:timezone":"Indian/Antananarivo",
    "iso:country":"MG",
    "wof:name":"Antanatanamirafy",
    "wof:placetype":"locality"
},
  "geometry": {"coordinates":[44.76667,-19.08333],"type":"Point"}
}