{
  "type": "Feature",
  "properties": {
    "gn:admin1_code":"3.0",
    "gn:asciiname":"Tsarabanja",
    "gn:country_code":"MG",
    "gn:dem":78,
    "gn:feature_class":"P",
    "gn:feature_code":"PPL",
    "gn:name":"Tsarabanja",
    "gn:population":0,
    "gn:timezone":"Indian/Antananarivo",
    "iso:country":"MG",
    "wof:name":"Tsarabanja",
    "wof:placetype":"locality"
},
  "geometry": {"coordinates":[45.18333,-16.61667000000001],"type":"Point"}
}