{
  "type": "Feature",
  "properties": {
    "gn:admin1_code":"04",
    "gn:asciiname":"Morarano",
    "gn:country_code":"MG",
    "gn:dem":542,
    "gn:feature_class":"P",
    "gn:feature_code":"PPL",
    "gn:name":"Morarano",
    "gn:population":0,
    "gn:timezone":"Indian/Antananarivo",
    "iso:country":"MG",
    "wof:name":"Morarano",
    "wof:placetype":"locality"
},
  "geometry": {"coordinates":[48.78333,-19.25],"type":"Point"}
}