{
  "type": "Feature",
  "properties": {
    "gn:admin1_code":"06",
    "gn:asciiname":"Helibondro",
    "gn:country_code":"MG",
    "gn:dem":50,
    "gn:feature_class":"P",
    "gn:feature_code":"PPL",
    "gn:name":"Helibondro",
    "gn:population":0,
    "gn:timezone":"Indian/Antananarivo",
    "iso:country":"MG",
    "wof:name":"Helibondro",
    "wof:placetype":"locality"
},
  "geometry": {"coordinates":[46.36667,-24.96667],"type":"Point"}
}