{
  "type": "Feature",
  "properties": {
    "gn:admin1_code":"01",
    "gn:asciiname":"Ambalamahoga",
    "gn:cc2":"MG",
    "gn:country_code":"MG",
    "gn:dem":19,
    "gn:feature_class":"P",
    "gn:feature_code":"PPL",
    "gn:name":"Ambalamahoga",
    "gn:population":0,
    "gn:timezone":"Indian/Antananarivo",
    "iso:country":"MG",
    "name:und_x_variant":[
        "Ambalamahogo",
        "Ambalamahoga"
    ],
    "wof:name":"Ambalamahoga",
    "wof:placetype":"locality"
},
  "geometry": {"coordinates":[48.38333,-13.73333],"type":"Point"}
}