{
  "type": "Feature",
  "properties": {
    "gn:admin1_code":"02",
    "gn:asciiname":"Analamanga",
    "gn:cc2":"MG",
    "gn:country_code":"MG",
    "gn:dem":291,
    "gn:feature_class":"P",
    "gn:feature_code":"PPL",
    "gn:name":"Analamanga",
    "gn:population":0,
    "gn:timezone":"Indian/Antananarivo",
    "iso:country":"MG",
    "name:und_x_variant":[
        "Ambalamanga",
        "Analamanga"
    ],
    "wof:name":"Analamanga",
    "wof:placetype":"locality"
},
  "geometry": {"coordinates":[47.23333,-22.93333],"type":"Point"}
}