{
  "type": "Feature",
  "properties": {
    "gn:admin1_code":"02",
    "gn:asciiname":"Analamanga",
    "gn:cc2":"MG",
    "gn:country_code":"MG",
    "gn:dem":291,
    "gn:feature_class":"P",
    "gn:feature_code":"PPL",
    "gn:name":"Analamanga",
    "gn:population":0,
    "gn:timezone":"Indian/Antananarivo",
    "iso:country":"MG",
    "name:ara_x_preferred":[
        "\u0623\u0646\u0627\u0644\u0627\u0645\u0627\u0646\u062c\u0627"
    ],
    "name:ben_x_preferred":[
        "\u0986\u09a8\u09be\u09b2\u09be\u09ae\u09be\u0982\u0997\u09be"
    ],
    "name:bre_x_preferred":[
        "Analamanga"
    ],
    "name:bul_x_preferred":[
        "\u0410\u043d\u0430\u043b\u0430\u043c\u0430\u043d\u0433\u0430"
    ],
    "name:ceb_x_preferred":[
        "Analamanga Region"
    ],
    "name:dan_x_preferred":[
        "Analamanga"
    ],
    "name:deu_x_preferred":[
        "Analamanga"
    ],
    "name:ell_x_preferred":[
        "\u0391\u03bd\u03b1\u03bb\u03b1\u03bc\u03ac\u03bd\u03b3\u03ba\u03b1"
    ],
    "name:epo_x_preferred":[
        "Analamanga"
    ],
    "name:fas_x_preferred":[
        "\u0622\u0646\u0627\u0644\u0627\u0645\u0627\u0646\u06af\u0627"
    ],
    "name:fra_x_preferred":[
        "Analamanga"
    ],
    "name:heb_x_preferred":[
        "\u05d0\u05e0\u05d0\u05dc\u05de\u05d0\u05e0\u05d2\u05d4"
    ],
    "name:hin_x_preferred":[
        "\u0905\u0928\u093e\u0932\u092e\u0902\u0917\u093e"
    ],
    "name:ind_x_preferred":[
        "Analamanga"
    ],
    "name:jpn_x_preferred":[
        "\u30a2\u30ca\u30e9\u30de\u30f3\u30ac\u5730\u57df\u570f"
    ],
    "name:kor_x_preferred":[
        "\uc544\ub0a0\ub77c\ub9dd\uac00 \uad6c"
    ],
    "name:mal_x_preferred":[
        "\u0d05\u0d28\u0d32\u0d2e\u0d19"
    ],
    "name:mlg_x_preferred":[
        "Analamanga"
    ],
    "name:nld_x_preferred":[
        "Analamanga"
    ],
    "name:nor_x_preferred":[
        "Analamanga"
    ],
    "name:pol_x_preferred":[
        "Analamanga"
    ],
    "name:por_x_preferred":[
        "Analamanga"
    ],
    "name:ron_x_preferred":[
        "Regiunea Analamanga"
    ],
    "name:swa_x_preferred":[
        "Analamanga"
    ],
    "name:swe_x_preferred":[
        "Analamanga"
    ],
    "name:tur_x_preferred":[
        "Analamanga"
    ],
    "name:und_x_variant":[
        "Ambalamanga"
    ],
    "name:urd_x_preferred":[
        "\u0622\u0646\u0627\u0644\u0627\u0645\u0627\u0646\u06af\u0627"
    ],
    "name:vie_x_preferred":[
        "Analamanga"
    ],
    "name:zho_x_preferred":[
        "\u963f\u90a3\u62c9\u8292\u52a0\u5340"
    ],
    "wof:name":"Analamanga",
    "wof:placetype":"locality"
},
  "geometry": {"coordinates":[47.23333,-22.93333],"type":"Point"}
}