{
  "type": "Feature",
  "properties": {
    "gn:admin1_code":"2.0",
    "gn:asciiname":"Vohitromby",
    "gn:country_code":"MG",
    "gn:dem":2,
    "gn:feature_class":"P",
    "gn:feature_code":"PPL",
    "gn:name":"Vohitromby",
    "gn:population":0,
    "gn:timezone":"Indian/Antananarivo",
    "iso:country":"MG",
    "name:fra_x_preferred":[
        "Vohitromby"
    ],
    "name:ita_x_preferred":[
        "Vohitromby"
    ],
    "name:mlg_x_preferred":[
        "Vohitromby"
    ],
    "name:nld_x_preferred":[
        "Vohitromby"
    ],
    "wof:name":"Vohitromby",
    "wof:placetype":"locality"
},
  "geometry": {"coordinates":[47.76667,-22.86667000000001],"type":"Point"}
}