{
  "type": "Feature",
  "properties": {
    "gn:admin1_code":"03",
    "gn:asciiname":"Ankiakabe",
    "gn:country_code":"MG",
    "gn:dem":343,
    "gn:feature_class":"P",
    "gn:feature_code":"PPL",
    "gn:name":"Ankiakabe",
    "gn:population":0,
    "gn:timezone":"Indian/Antananarivo",
    "iso:country":"MG",
    "wof:name":"Ankiakabe",
    "wof:placetype":"locality"
},
  "geometry": {"coordinates":[48.51667,-15.71667],"type":"Point"}
}