{
  "type": "Feature",
  "properties": {
    "gn:admin1_code":"05",
    "gn:asciiname":"Anjezika",
    "gn:country_code":"MG",
    "gn:dem":1360,
    "gn:feature_class":"P",
    "gn:feature_code":"PPL",
    "gn:name":"Anjezika",
    "gn:population":0,
    "gn:timezone":"Indian/Antananarivo",
    "iso:country":"MG",
    "wof:name":"Anjezika",
    "wof:placetype":"locality"
},
  "geometry": {"coordinates":[47.86667,-18.58333],"type":"Point"}
}