{
  "type": "Feature",
  "properties": {
    "gn:admin1_code":"04",
    "gn:asciiname":"Ambodiadabo",
    "gn:country_code":"MG",
    "gn:dem":502,
    "gn:feature_class":"P",
    "gn:feature_code":"PPL",
    "gn:name":"Ambodiadabo",
    "gn:population":0,
    "gn:timezone":"Indian/Antananarivo",
    "iso:country":"MG",
    "name:fra_x_preferred":[
        "Ambodiadabo"
    ],
    "name:ita_x_preferred":[
        "Ambodiadabo"
    ],
    "name:nld_x_preferred":[
        "Ambodiadabo"
    ],
    "wof:name":"Ambodiadabo",
    "wof:placetype":"locality"
},
  "geometry": {"coordinates":[48.23333,-16.58333],"type":"Point"}
}