{
  "type": "Feature",
  "properties": {
    "gn:admin1_code":"03",
    "gn:asciiname":"Andrafiavelo",
    "gn:country_code":"MG",
    "gn:dem":294,
    "gn:feature_class":"P",
    "gn:feature_code":"PPL",
    "gn:name":"Andrafiavelo",
    "gn:population":0,
    "gn:timezone":"Indian/Antananarivo",
    "iso:country":"MG",
    "wof:name":"Andrafiavelo",
    "wof:placetype":"locality"
},
  "geometry": {"coordinates":[45.26667,-17.85],"type":"Point"}
}