{
  "type": "Feature",
  "properties": {
    "gn:admin1_code":"6.0",
    "gn:asciiname":"Tsiahohoka",
    "gn:country_code":"MG",
    "gn:dem":647,
    "gn:feature_class":"P",
    "gn:feature_code":"PPL",
    "gn:name":"Tsiahohoka",
    "gn:population":0,
    "gn:timezone":"Indian/Antananarivo",
    "iso:country":"MG",
    "wof:name":"Tsiahohoka",
    "wof:placetype":"locality"
},
  "geometry": {"coordinates":[45.78333,-21.83333],"type":"Point"}
}