{
  "type": "Feature",
  "properties": {
    "gn:admin1_code":"05",
    "gn:asciiname":"Ambohitrakely",
    "gn:country_code":"MG",
    "gn:dem":1192,
    "gn:feature_class":"P",
    "gn:feature_code":"PPL",
    "gn:name":"Ambohitrakely",
    "gn:population":0,
    "gn:timezone":"Indian/Antananarivo",
    "iso:country":"MG",
    "wof:name":"Ambohitrakely",
    "wof:placetype":"locality"
},
  "geometry": {"coordinates":[47.08333,-18.11667000000001],"type":"Point"}
}