{
  "type": "Feature",
  "properties": {
    "gn:admin1_code":"06",
    "gn:asciiname":"Andranobe",
    "gn:country_code":"MG",
    "gn:dem":112,
    "gn:feature_class":"P",
    "gn:feature_code":"PPL",
    "gn:name":"Andranobe",
    "gn:population":0,
    "gn:timezone":"Indian/Antananarivo",
    "iso:country":"MG",
    "wof:name":"Andranobe",
    "wof:placetype":"locality"
},
  "geometry": {"coordinates":[44.31667,-23.46667],"type":"Point"}
}