{
  "type": "Feature",
  "properties": {
    "gn:admin1_code":"04",
    "gn:asciiname":"Ambodihazomamy",
    "gn:country_code":"MG",
    "gn:dem":458,
    "gn:feature_class":"P",
    "gn:feature_code":"PPL",
    "gn:name":"Ambodihazomamy",
    "gn:population":0,
    "gn:timezone":"Indian/Antananarivo",
    "iso:country":"MG",
    "wof:name":"Ambodihazomamy",
    "wof:placetype":"locality"
},
  "geometry": {"coordinates":[49.48333,-15.55],"type":"Point"}
}