{
  "type": "Feature",
  "properties": {
    "gn:admin1_code":"03",
    "gn:asciiname":"Ambohimitsinjo",
    "gn:country_code":"MG",
    "gn:dem":894,
    "gn:feature_class":"P",
    "gn:feature_code":"PPL",
    "gn:name":"Ambohimitsinjo",
    "gn:population":0,
    "gn:timezone":"Indian/Antananarivo",
    "iso:country":"MG",
    "name:azb_x_preferred":[
        "\u0627\u0645\u0628\u0648\u0647\u06cc\u0645\u06cc\u062a\u0633\u06cc\u0646\u062c\u0648"
    ],
    "name:fas_x_preferred":[
        "\u0627\u0645\u0628\u0648\u0647\u06cc\u0645\u06cc\u062a\u0633\u06cc\u0646\u062c\u0648"
    ],
    "name:fra_x_preferred":[
        "Ambohimitsinjo"
    ],
    "name:ita_x_preferred":[
        "Ambohimitsinjo"
    ],
    "name:mlg_x_preferred":[
        "Ambohimitsinjo"
    ],
    "name:nld_x_preferred":[
        "Ambohimitsinjo"
    ],
    "wof:name":"Ambohimitsinjo",
    "wof:placetype":"locality"
},
  "geometry": {"coordinates":[49.16667,-15.16667],"type":"Point"}
}