{
  "type": "Feature",
  "properties": {
    "gn:admin1_code":"04",
    "gn:asciiname":"Ambatomiarina",
    "gn:country_code":"MG",
    "gn:dem":121,
    "gn:feature_class":"P",
    "gn:feature_code":"PPL",
    "gn:name":"Ambatomiarina",
    "gn:population":0,
    "gn:timezone":"Indian/Antananarivo",
    "iso:country":"MG",
    "wof:name":"Ambatomiarina",
    "wof:placetype":"locality"
},
  "geometry": {"coordinates":[48.78333,-18.86667000000001],"type":"Point"}
}