{
  "type": "Feature",
  "properties": {
    "gn:admin1_code":"04",
    "gn:asciiname":"Andilanatoby",
    "gn:cc2":"MG",
    "gn:country_code":"MG",
    "gn:dem":791,
    "gn:feature_class":"P",
    "gn:feature_code":"PPL",
    "gn:name":"Andilanatoby",
    "gn:population":0,
    "gn:timezone":"Indian/Antananarivo",
    "iso:country":"MG",
    "name:fra_x_preferred":[
        "Andilanatoby"
    ],
    "name:ita_x_preferred":[
        "Andilanatoby"
    ],
    "name:mlg_x_preferred":[
        "Andilanatoby"
    ],
    "name:nld_x_preferred":[
        "Andilanatoby"
    ],
    "name:und_x_variant":[
        "Anvilalatoby"
    ],
    "wof:name":"Andilanatoby",
    "wof:placetype":"locality"
},
  "geometry": {"coordinates":[48.23333,-17.93332999999999],"type":"Point"}
}