{
  "type": "Feature",
  "properties": {
    "gn:admin1_code":"01",
    "gn:asciiname":"Andranotsimaty",
    "gn:country_code":"MG",
    "gn:dem":613,
    "gn:feature_class":"P",
    "gn:feature_code":"PPL",
    "gn:name":"Andranotsimaty",
    "gn:population":0,
    "gn:timezone":"Indian/Antananarivo",
    "iso:country":"MG",
    "wof:name":"Andranotsimaty",
    "wof:placetype":"locality"
},
  "geometry": {"coordinates":[49.18333,-12.73333],"type":"Point"}
}