{
  "type": "Feature",
  "properties": {
    "gn:admin1_code":"3.0",
    "gn:asciiname":"Romiaka",
    "gn:cc2":"MG",
    "gn:country_code":"MG",
    "gn:dem":327,
    "gn:feature_class":"P",
    "gn:feature_code":"PPL",
    "gn:name":"Romiaka",
    "gn:population":0,
    "gn:timezone":"Indian/Antananarivo",
    "iso:country":"MG",
    "name:und_x_variant":[
        "Romieka",
        "Romiaka"
    ],
    "wof:name":"Romiaka",
    "wof:placetype":"locality"
},
  "geometry": {"coordinates":[48.75,-15.96667],"type":"Point"}
}