{
  "type": "Feature",
  "properties": {
    "gn:admin1_code":"06",
    "gn:asciiname":"Etsirihy",
    "gn:country_code":"MG",
    "gn:dem":32,
    "gn:feature_class":"P",
    "gn:feature_code":"PPL",
    "gn:name":"Etsirihy",
    "gn:population":0,
    "gn:timezone":"Indian/Antananarivo",
    "iso:country":"MG",
    "wof:name":"Etsirihy",
    "wof:placetype":"locality"
},
  "geometry": {"coordinates":[47.11667,-24.71667],"type":"Point"}
}