{
  "type": "Feature",
  "properties": {
    "gn:admin1_code":"2.0",
    "gn:asciiname":"Sahamoro",
    "gn:cc2":"MG",
    "gn:country_code":"MG",
    "gn:dem":5,
    "gn:feature_class":"P",
    "gn:feature_code":"PPL",
    "gn:name":"Sahamoro",
    "gn:population":0,
    "gn:timezone":"Indian/Antananarivo",
    "iso:country":"MG",
    "name:und_x_variant":[
        "Samoro",
        "Sahamoro"
    ],
    "wof:name":"Sahamoro",
    "wof:placetype":"locality"
},
  "geometry": {"coordinates":[47.53333,-23.61667000000001],"type":"Point"}
}