{
  "type": "Feature",
  "properties": {
    "gn:admin1_code":"06",
    "gn:asciiname":"Manaravolo",
    "gn:cc2":"MG",
    "gn:country_code":"MG",
    "gn:dem":586,
    "gn:feature_class":"P",
    "gn:feature_code":"PPL",
    "gn:name":"Manaravolo",
    "gn:population":0,
    "gn:timezone":"Indian/Antananarivo",
    "iso:country":"MG",
    "name:und_x_variant":[
        "Manaravola",
        "Manaravolo"
    ],
    "wof:name":"Manaravolo",
    "wof:placetype":"locality"
},
  "geometry": {"coordinates":[45.63333,-23.98333],"type":"Point"}
}