{
  "type": "Feature",
  "properties": {
    "gn:admin1_code":"03",
    "gn:asciiname":"Madiromirafy",
    "gn:country_code":"MG",
    "gn:dem":34,
    "gn:feature_class":"P",
    "gn:feature_code":"PPL",
    "gn:name":"Madiromirafy",
    "gn:population":0,
    "gn:timezone":"Indian/Antananarivo",
    "iso:country":"MG",
    "wof:name":"Madiromirafy",
    "wof:placetype":"locality"
},
  "geometry": {"coordinates":[46.83333,-16.83333],"type":"Point"}
}