{
  "type": "Feature",
  "properties": {
    "gn:asciiname":"Camp Robin",
    "gn:country_code":"MG",
    "gn:dem":1388,
    "gn:feature_class":"P",
    "gn:feature_code":"PPL",
    "gn:name":"Camp Robin",
    "gn:population":0,
    "gn:timezone":"Indian/Antananarivo",
    "iso:country":"MG",
    "name:fra_x_preferred":[
        "Camp Robin"
    ],
    "name:ita_x_preferred":[
        "Camp Robin"
    ],
    "name:mlg_x_preferred":[
        "Camp Robin"
    ],
    "name:nld_x_preferred":[
        "Camp Robin"
    ],
    "wof:name":"Camp Robin",
    "wof:placetype":"locality"
},
  "geometry": {"coordinates":[47.13333,-20.91667],"type":"Point"}
}