{
  "type": "Feature",
  "properties": {
    "gn:admin1_code":"01",
    "gn:asciiname":"Manantenina",
    "gn:country_code":"MG",
    "gn:dem":85,
    "gn:feature_class":"P",
    "gn:feature_code":"PPL",
    "gn:name":"Manantenina",
    "gn:population":0,
    "gn:timezone":"Indian/Antananarivo",
    "iso:country":"MG",
    "name:deu_x_preferred":[
        "Manantenina"
    ],
    "name:fra_x_preferred":[
        "Manantenina"
    ],
    "name:ita_x_preferred":[
        "Manantenina"
    ],
    "name:mlg_x_preferred":[
        "Manantenina"
    ],
    "name:nld_x_preferred":[
        "Manantenina"
    ],
    "wof:name":"Manantenina",
    "wof:placetype":"locality"
},
  "geometry": {"coordinates":[49.81667,-14.48333],"type":"Point"}
}