{
  "type": "Feature",
  "properties": {
    "gn:admin1_code":"05",
    "gn:asciiname":"Bemasoandro",
    "gn:country_code":"MG",
    "gn:dem":1265,
    "gn:feature_class":"P",
    "gn:feature_code":"PPL",
    "gn:name":"Bemasoandro",
    "gn:population":0,
    "gn:timezone":"Indian/Antananarivo",
    "iso:country":"MG",
    "wof:name":"Bemasoandro",
    "wof:placetype":"locality"
},
  "geometry": {"coordinates":[47.28333,-18.71667],"type":"Point"}
}