{
  "type": "Feature",
  "properties": {
    "gn:admin1_code":"2.0",
    "gn:asciiname":"Vohibe",
    "gn:country_code":"MG",
    "gn:dem":40,
    "gn:feature_class":"P",
    "gn:feature_code":"PPL",
    "gn:name":"Vohibe",
    "gn:population":0,
    "gn:timezone":"Indian/Antananarivo",
    "iso:country":"MG",
    "wof:name":"Vohibe",
    "wof:placetype":"locality"
},
  "geometry": {"coordinates":[47.45,-23.31667],"type":"Point"}
}