{
  "type": "Feature",
  "properties": {
    "gn:admin1_code":"05",
    "gn:asciiname":"Antambiazina",
    "gn:country_code":"MG",
    "gn:dem":1649,
    "gn:feature_class":"P",
    "gn:feature_code":"PPL",
    "gn:name":"Antambiazina",
    "gn:population":0,
    "gn:timezone":"Indian/Antananarivo",
    "iso:country":"MG",
    "wof:name":"Antambiazina",
    "wof:placetype":"locality"
},
  "geometry": {"coordinates":[47.35,-19.73333],"type":"Point"}
}