{
  "type": "Feature",
  "properties": {
    "gn:admin1_code":"04",
    "gn:asciiname":"Antsahalalina",
    "gn:country_code":"MG",
    "gn:dem":15,
    "gn:feature_class":"P",
    "gn:feature_code":"PPL",
    "gn:name":"Antsahalalina",
    "gn:population":0,
    "gn:timezone":"Indian/Antananarivo",
    "iso:country":"MG",
    "name:deu_x_preferred":[
        "Antsahalalina"
    ],
    "name:ita_x_preferred":[
        "Antsahalalina"
    ],
    "name:nld_x_preferred":[
        "Antsahalalina"
    ],
    "name:por_x_preferred":[
        "Antsahalalina"
    ],
    "wof:name":"Antsahalalina",
    "wof:placetype":"locality"
},
  "geometry": {"coordinates":[48.88333,-19.31667],"type":"Point"}
}