{
  "type": "Feature",
  "properties": {
    "gn:admin1_code":"01",
    "gn:asciiname":"Kongony",
    "gn:country_code":"MG",
    "gn:dem":67,
    "gn:feature_class":"P",
    "gn:feature_code":"PPL",
    "gn:name":"Kongony",
    "gn:population":0,
    "gn:timezone":"Indian/Antananarivo",
    "iso:country":"MG",
    "wof:name":"Kongony",
    "wof:placetype":"locality"
},
  "geometry": {"coordinates":[48.08333,-13.66667],"type":"Point"}
}