{
  "type": "Feature",
  "properties": {
    "gn:admin1_code":"05",
    "gn:asciiname":"Antohomadinika",
    "gn:country_code":"MG",
    "gn:dem":1006,
    "gn:feature_class":"P",
    "gn:feature_code":"PPL",
    "gn:name":"Antohomadinika",
    "gn:population":0,
    "gn:timezone":"Indian/Antananarivo",
    "iso:country":"MG",
    "wof:name":"Antohomadinika",
    "wof:placetype":"locality"
},
  "geometry": {"coordinates":[46.56667,-19.23333],"type":"Point"}
}