{
  "type": "Feature",
  "properties": {
    "gn:admin1_code":"04",
    "gn:asciiname":"Ambinanibehasina",
    "gn:country_code":"MG",
    "gn:dem":934,
    "gn:feature_class":"P",
    "gn:feature_code":"PPL",
    "gn:name":"Ambinanibehasina",
    "gn:population":0,
    "gn:timezone":"Indian/Antananarivo",
    "iso:country":"MG",
    "wof:name":"Ambinanibehasina",
    "wof:placetype":"locality"
},
  "geometry": {"coordinates":[48.43333,-18.98333],"type":"Point"}
}