{
  "type": "Feature",
  "properties": {
    "gn:admin1_code":"05",
    "gn:asciiname":"Ambohipolo",
    "gn:country_code":"MG",
    "gn:dem":1199,
    "gn:feature_class":"P",
    "gn:feature_code":"PPL",
    "gn:name":"Ambohipolo",
    "gn:population":0,
    "gn:timezone":"Indian/Antananarivo",
    "iso:country":"MG",
    "wof:name":"Ambohipolo",
    "wof:placetype":"locality"
},
  "geometry": {"coordinates":[46.65,-19.71667],"type":"Point"}
}