{
  "type": "Feature",
  "properties": {
    "gn:admin1_code":"06",
    "gn:asciiname":"Reakaly",
    "gn:country_code":"MG",
    "gn:dem":254,
    "gn:feature_class":"P",
    "gn:feature_code":"PPL",
    "gn:name":"Reakaly",
    "gn:population":0,
    "gn:timezone":"Indian/Antananarivo",
    "iso:country":"MG",
    "wof:name":"Reakaly",
    "wof:placetype":"locality"
},
  "geometry": {"coordinates":[44.56667,-24.66667],"type":"Point"}
}