{
  "type": "Feature",
  "properties": {
    "gn:admin1_code":"03",
    "gn:asciiname":"Berentsina",
    "gn:cc2":"MG",
    "gn:country_code":"MG",
    "gn:dem":297,
    "gn:feature_class":"P",
    "gn:feature_code":"PPL",
    "gn:name":"Berentsina",
    "gn:population":0,
    "gn:timezone":"Indian/Antananarivo",
    "iso:country":"MG",
    "name:und_x_variant":[
        "Berintsy",
        "Berentsina"
    ],
    "wof:name":"Berentsina",
    "wof:placetype":"locality"
},
  "geometry": {"coordinates":[48.53333,-15.08333],"type":"Point"}
}