{
  "type": "Feature",
  "properties": {
    "gn:admin1_code":"01",
    "gn:asciiname":"Ampondralava",
    "gn:country_code":"MG",
    "gn:dem":20,
    "gn:feature_class":"P",
    "gn:feature_code":"PPL",
    "gn:name":"Ampondralava",
    "gn:population":0,
    "gn:timezone":"Indian/Antananarivo",
    "iso:country":"MG",
    "name:azb_x_preferred":[
        "\u0627\u0645\u067e\u0627\u0646\u062f\u0631\u0627\u0644\u0627\u0648\u0627"
    ],
    "name:ceb_x_preferred":[
        "Ampondralava"
    ],
    "name:fas_x_preferred":[
        "\u0627\u0645\u067e\u0627\u0646\u062f\u0631\u0627\u0644\u0627\u0648\u0627"
    ],
    "name:fra_x_preferred":[
        "Ampondralava"
    ],
    "name:ita_x_preferred":[
        "Ampondralava"
    ],
    "name:nld_x_preferred":[
        "Ampondralava"
    ],
    "name:swe_x_preferred":[
        "Ampondralava"
    ],
    "wof:name":"Ampondralava",
    "wof:placetype":"locality"
},
  "geometry": {"coordinates":[48.93333,-13.16667],"type":"Point"}
}