{
  "type": "Feature",
  "properties": {
    "gn:admin1_code":"01",
    "gn:asciiname":"Ampondralava",
    "gn:country_code":"MG",
    "gn:dem":20,
    "gn:feature_class":"P",
    "gn:feature_code":"PPL",
    "gn:name":"Ampondralava",
    "gn:population":0,
    "gn:timezone":"Indian/Antananarivo",
    "iso:country":"MG",
    "wof:name":"Ampondralava",
    "wof:placetype":"locality"
},
  "geometry": {"coordinates":[48.93333,-13.16667],"type":"Point"}
}