{
  "type": "Feature",
  "properties": {
    "gn:admin1_code":"5.0",
    "gn:asciiname":"Soanierana",
    "gn:country_code":"MG",
    "gn:dem":1386,
    "gn:feature_class":"P",
    "gn:feature_code":"PPL",
    "gn:name":"Soanierana",
    "gn:population":0,
    "gn:timezone":"Indian/Antananarivo",
    "iso:country":"MG",
    "wof:name":"Soanierana",
    "wof:placetype":"locality"
},
  "geometry": {"coordinates":[46.76667,-19.01667],"type":"Point"}
}