{
  "type": "Feature",
  "properties": {
    "gn:admin1_code":"6.0",
    "gn:asciiname":"Taikoaka",
    "gn:cc2":"MG",
    "gn:country_code":"MG",
    "gn:dem":41,
    "gn:feature_class":"P",
    "gn:feature_code":"PPL",
    "gn:name":"Taikoaka",
    "gn:population":0,
    "gn:timezone":"Indian/Antananarivo",
    "iso:country":"MG",
    "name:und_x_variant":[
        "Antekoaka",
        "Taikoaka"
    ],
    "wof:name":"Taikoaka",
    "wof:placetype":"locality"
},
  "geometry": {"coordinates":[43.76667,-23.28333],"type":"Point"}
}