{
  "type": "Feature",
  "properties": {
    "gn:admin1_code":"05",
    "gn:asciiname":"Androvakely",
    "gn:country_code":"MG",
    "gn:dem":1525,
    "gn:feature_class":"P",
    "gn:feature_code":"PPL",
    "gn:name":"Androvakely",
    "gn:population":0,
    "gn:timezone":"Indian/Antananarivo",
    "iso:country":"MG",
    "wof:name":"Androvakely",
    "wof:placetype":"locality"
},
  "geometry": {"coordinates":[47.06667,-19.88333],"type":"Point"}
}