{
  "type": "Feature",
  "properties": {
    "gn:admin1_code":"06",
    "gn:asciiname":"Benonoky",
    "gn:country_code":"MG",
    "gn:dem":377,
    "gn:feature_class":"P",
    "gn:feature_code":"PPL",
    "gn:name":"Benonoky",
    "gn:population":0,
    "gn:timezone":"Indian/Antananarivo",
    "iso:country":"MG",
    "wof:name":"Benonoky",
    "wof:placetype":"locality"
},
  "geometry": {"coordinates":[46.28333,-23.93333],"type":"Point"}
}