{
  "type": "Feature",
  "properties": {
    "gn:admin1_code":"01",
    "gn:asciiname":"Ambatoharanana",
    "gn:cc2":"MG",
    "gn:country_code":"MG",
    "gn:dem":19,
    "gn:feature_class":"P",
    "gn:feature_code":"PPL",
    "gn:name":"Ambatoharanana",
    "gn:population":0,
    "gn:timezone":"Indian/Antananarivo",
    "iso:country":"MG",
    "name:und_x_variant":[
        "Ambatoharangana",
        "Ambatoharana",
        "Ambatoharanana"
    ],
    "wof:name":"Ambatoharanana",
    "wof:placetype":"locality"
},
  "geometry": {"coordinates":[48.68333,-13.53333],"type":"Point"}
}