{
  "type": "Feature",
  "properties": {
    "gn:admin1_code":"02",
    "gn:asciiname":"Ambolo",
    "gn:country_code":"MG",
    "gn:dem":1370,
    "gn:feature_class":"P",
    "gn:feature_code":"PPL",
    "gn:name":"Ambolo",
    "gn:population":0,
    "gn:timezone":"Indian/Antananarivo",
    "iso:country":"MG",
    "wof:name":"Ambolo",
    "wof:placetype":"locality"
},
  "geometry": {"coordinates":[47.13333,-21.25],"type":"Point"}
}