{
  "type": "Feature",
  "properties": {
    "gn:admin1_code":"01",
    "gn:asciiname":"Marofotra",
    "gn:country_code":"MG",
    "gn:dem":103,
    "gn:feature_class":"P",
    "gn:feature_code":"PPL",
    "gn:name":"Marofotra",
    "gn:population":0,
    "gn:timezone":"Indian/Antananarivo",
    "iso:country":"MG",
    "wof:name":"Marofotra",
    "wof:placetype":"locality"
},
  "geometry": {"coordinates":[49.65,-13.23333],"type":"Point"}
}