{
  "type": "Feature",
  "properties": {
    "gn:admin1_code":"06",
    "gn:asciiname":"Naninora",
    "gn:cc2":"MG",
    "gn:country_code":"MG",
    "gn:dem":809,
    "gn:feature_class":"P",
    "gn:feature_code":"PPL",
    "gn:name":"Naninora",
    "gn:population":0,
    "gn:timezone":"Indian/Antananarivo",
    "iso:country":"MG",
    "name:und_x_variant":[
        "Nanirora",
        "Naninora"
    ],
    "wof:name":"Naninora",
    "wof:placetype":"locality"
},
  "geometry": {"coordinates":[46.08333,-23.21667],"type":"Point"}
}