{
  "type": "Feature",
  "properties": {
    "gn:admin1_code":"02",
    "gn:asciiname":"Imikaiky",
    "gn:country_code":"MG",
    "gn:dem":566,
    "gn:feature_class":"P",
    "gn:feature_code":"PPL",
    "gn:name":"Imikaiky",
    "gn:population":0,
    "gn:timezone":"Indian/Antananarivo",
    "iso:country":"MG",
    "wof:name":"Imikaiky",
    "wof:placetype":"locality"
},
  "geometry": {"coordinates":[47.01667,-23.33333],"type":"Point"}
}