{
  "type": "Feature",
  "properties": {
    "gn:admin1_code":"04",
    "gn:asciiname":"Nosivola",
    "gn:country_code":"MG",
    "gn:dem":986,
    "gn:feature_class":"P",
    "gn:feature_code":"PPL",
    "gn:name":"Nosivola",
    "gn:population":0,
    "gn:timezone":"Indian/Antananarivo",
    "iso:country":"MG",
    "wof:name":"Nosivola",
    "wof:placetype":"locality"
},
  "geometry": {"coordinates":[48.65,-17.71667],"type":"Point"}
}