{
  "type": "Feature",
  "properties": {
    "gn:admin1_code":"05",
    "gn:asciiname":"Andranovelona",
    "gn:country_code":"MG",
    "gn:dem":1229,
    "gn:feature_class":"P",
    "gn:feature_code":"PPL",
    "gn:name":"Andranovelona",
    "gn:population":0,
    "gn:timezone":"Indian/Antananarivo",
    "iso:country":"MG",
    "wof:name":"Andranovelona",
    "wof:placetype":"locality"
},
  "geometry": {"coordinates":[46.66667,-18.61667000000001],"type":"Point"}
}