{
  "type": "Feature",
  "properties": {
    "gn:admin1_code":"02",
    "gn:asciiname":"Ampasimbola",
    "gn:country_code":"MG",
    "gn:dem":398,
    "gn:feature_class":"P",
    "gn:feature_code":"PPL",
    "gn:name":"Ampasimbola",
    "gn:population":0,
    "gn:timezone":"Indian/Antananarivo",
    "iso:country":"MG",
    "wof:name":"Ampasimbola",
    "wof:placetype":"locality"
},
  "geometry": {"coordinates":[48.01667,-20.63333],"type":"Point"}
}