{
  "type": "Feature",
  "properties": {
    "gn:admin1_code":"04",
    "gn:asciiname":"Mahasoa",
    "gn:country_code":"MG",
    "gn:dem":114,
    "gn:feature_class":"P",
    "gn:feature_code":"PPL",
    "gn:name":"Mahasoa",
    "gn:population":0,
    "gn:timezone":"Indian/Antananarivo",
    "iso:country":"MG",
    "wof:name":"Mahasoa",
    "wof:placetype":"locality"
},
  "geometry": {"coordinates":[48.61667,-19.33333],"type":"Point"}
}