{
  "type": "Feature",
  "properties": {
    "gn:admin1_code":"05",
    "gn:asciiname":"Maritampona",
    "gn:country_code":"MG",
    "gn:dem":762,
    "gn:feature_class":"P",
    "gn:feature_code":"PPL",
    "gn:name":"Maritampona",
    "gn:population":0,
    "gn:timezone":"Indian/Antananarivo",
    "iso:country":"MG",
    "wof:name":"Maritampona",
    "wof:placetype":"locality"
},
  "geometry": {"coordinates":[45.61667,-18.96667],"type":"Point"}
}