{
  "type": "Feature",
  "properties": {
    "gn:admin1_code":"04",
    "gn:asciiname":"Marosampana",
    "gn:country_code":"MG",
    "gn:dem":45,
    "gn:feature_class":"P",
    "gn:feature_code":"PPL",
    "gn:name":"Marosampana",
    "gn:population":0,
    "gn:timezone":"Indian/Antananarivo",
    "iso:country":"MG",
    "wof:name":"Marosampana",
    "wof:placetype":"locality"
},
  "geometry": {"coordinates":[48.91667,-19.33333],"type":"Point"}
}