{
  "type": "Feature",
  "properties": {
    "gn:admin1_code":"06",
    "gn:asciiname":"Ankaranabo",
    "gn:country_code":"MG",
    "gn:dem":113,
    "gn:feature_class":"P",
    "gn:feature_code":"PPL",
    "gn:name":"Ankaranabo",
    "gn:population":0,
    "gn:timezone":"Indian/Antananarivo",
    "iso:country":"MG",
    "wof:name":"Ankaranabo",
    "wof:placetype":"locality"
},
  "geometry": {"coordinates":[46.03333,-24.61667000000001],"type":"Point"}
}