{
  "type": "Feature",
  "properties": {
    "gn:admin1_code":"06",
    "gn:asciiname":"Andranomatavy",
    "gn:country_code":"MG",
    "gn:dem":257,
    "gn:feature_class":"P",
    "gn:feature_code":"PPL",
    "gn:name":"Andranomatavy",
    "gn:population":0,
    "gn:timezone":"Indian/Antananarivo",
    "iso:country":"MG",
    "wof:name":"Andranomatavy",
    "wof:placetype":"locality"
},
  "geometry": {"coordinates":[45.18333,-20.15],"type":"Point"}
}