{
  "type": "Feature",
  "properties": {
    "gn:admin1_code":"01",
    "gn:asciiname":"Ankiakahely",
    "gn:country_code":"MG",
    "gn:dem":400,
    "gn:feature_class":"P",
    "gn:feature_code":"PPL",
    "gn:name":"Ankiakahely",
    "gn:population":0,
    "gn:timezone":"Indian/Antananarivo",
    "iso:country":"MG",
    "wof:name":"Ankiakahely",
    "wof:placetype":"locality"
},
  "geometry": {"coordinates":[49.51667,-14.35],"type":"Point"}
}