{
  "type": "Feature",
  "properties": {
    "gn:admin1_code":"03",
    "gn:asciiname":"Adabatelo",
    "gn:country_code":"MG",
    "gn:dem":70,
    "gn:feature_class":"P",
    "gn:feature_code":"PPL",
    "gn:name":"Adabatelo",
    "gn:population":0,
    "gn:timezone":"Indian/Antananarivo",
    "iso:country":"MG",
    "wof:name":"Adabatelo",
    "wof:placetype":"locality"
},
  "geometry": {"coordinates":[45.16667,-16.63332999999999],"type":"Point"}
}