{
  "type": "Feature",
  "properties": {
    "gn:admin1_code":"06",
    "gn:asciiname":"Amberomena",
    "gn:country_code":"MG",
    "gn:dem":452,
    "gn:feature_class":"P",
    "gn:feature_code":"PPL",
    "gn:name":"Amberomena",
    "gn:population":0,
    "gn:timezone":"Indian/Antananarivo",
    "iso:country":"MG",
    "wof:name":"Amberomena",
    "wof:placetype":"locality"
},
  "geometry": {"coordinates":[44.55,-22.35],"type":"Point"}
}