{
  "type": "Feature",
  "properties": {
    "gn:admin1_code":"03",
    "gn:asciiname":"Ambodimandresy",
    "gn:country_code":"MG",
    "gn:dem":933,
    "gn:feature_class":"P",
    "gn:feature_code":"PPL",
    "gn:name":"Ambodimandresy",
    "gn:population":0,
    "gn:timezone":"Indian/Antananarivo",
    "iso:country":"MG",
    "wof:name":"Ambodimandresy",
    "wof:placetype":"locality"
},
  "geometry": {"coordinates":[49.13333,-15.25],"type":"Point"}
}