{
  "type": "Feature",
  "properties": {
    "gn:admin1_code":"03",
    "gn:asciiname":"Ambodimandresy",
    "gn:country_code":"MG",
    "gn:dem":933,
    "gn:feature_class":"P",
    "gn:feature_code":"PPL",
    "gn:name":"Ambodimandresy",
    "gn:population":0,
    "gn:timezone":"Indian/Antananarivo",
    "iso:country":"MG",
    "name:azb_x_preferred":[
        "\u0627\u0645\u0628\u0648\u062f\u06cc\u0645\u0627\u0646\u062f\u0631\u0633\u06cc"
    ],
    "name:fas_x_preferred":[
        "\u0627\u0645\u0628\u0648\u062f\u06cc\u0645\u0627\u0646\u062f\u0631\u0633\u06cc"
    ],
    "name:fra_x_preferred":[
        "Ambodimandresy"
    ],
    "name:ita_x_preferred":[
        "Ambodimandresy"
    ],
    "name:mlg_x_preferred":[
        "Ambodimandresy"
    ],
    "name:nld_x_preferred":[
        "Ambodimandresy"
    ],
    "wof:name":"Ambodimandresy",
    "wof:placetype":"locality"
},
  "geometry": {"coordinates":[49.13333,-15.25],"type":"Point"}
}