{
  "type": "Feature",
  "properties": {
    "gn:admin1_code":"02",
    "gn:asciiname":"Ambalakely",
    "gn:country_code":"MG",
    "gn:dem":1079,
    "gn:feature_class":"P",
    "gn:feature_code":"PPL",
    "gn:name":"Ambalakely",
    "gn:population":0,
    "gn:timezone":"Indian/Antananarivo",
    "iso:country":"MG",
    "wof:name":"Ambalakely",
    "wof:placetype":"locality"
},
  "geometry": {"coordinates":[47.16667,-21.41667],"type":"Point"}
}