{
  "type": "Feature",
  "properties": {
    "gn:admin1_code":"02",
    "gn:asciiname":"Ambalakely",
    "gn:country_code":"MG",
    "gn:dem":1079,
    "gn:feature_class":"P",
    "gn:feature_code":"PPL",
    "gn:name":"Ambalakely",
    "gn:population":0,
    "gn:timezone":"Indian/Antananarivo",
    "iso:country":"MG",
    "name:azb_x_preferred":[
        "\u0627\u0645\u0628\u0627\u0644\u0627\u06a9\u0644\u06cc"
    ],
    "name:fas_x_preferred":[
        "\u0627\u0645\u0628\u0627\u0644\u0627\u06a9\u0644\u06cc"
    ],
    "name:fra_x_preferred":[
        "Ambalakely"
    ],
    "name:ita_x_preferred":[
        "Ambalakely"
    ],
    "name:mlg_x_preferred":[
        "Ambalakely"
    ],
    "name:nld_x_preferred":[
        "Ambalakely"
    ],
    "wof:name":"Ambalakely",
    "wof:placetype":"locality"
},
  "geometry": {"coordinates":[47.16667,-21.41667],"type":"Point"}
}