{
  "type": "Feature",
  "properties": {
    "gn:admin1_code":"05",
    "gn:asciiname":"Ambohitapaka",
    "gn:country_code":"MG",
    "gn:dem":993,
    "gn:feature_class":"P",
    "gn:feature_code":"PPL",
    "gn:name":"Ambohitapaka",
    "gn:population":0,
    "gn:timezone":"Indian/Antananarivo",
    "iso:country":"MG",
    "wof:name":"Ambohitapaka",
    "wof:placetype":"locality"
},
  "geometry": {"coordinates":[46.51667,-19.58333],"type":"Point"}
}