{
  "type": "Feature",
  "properties": {
    "gn:admin1_code":"01",
    "gn:asciiname":"Joja",
    "gn:cc2":"MG",
    "gn:country_code":"MG",
    "gn:dem":97,
    "gn:feature_class":"P",
    "gn:feature_code":"PPL",
    "gn:name":"Joja",
    "gn:population":0,
    "gn:timezone":"Indian/Antananarivo",
    "iso:country":"MG",
    "name:und_x_variant":[
        "Jojabe",
        "Joja"
    ],
    "wof:name":"Joja",
    "wof:placetype":"locality"
},
  "geometry": {"coordinates":[48.21667,-13.81667],"type":"Point"}
}