{
  "type": "Feature",
  "properties": {
    "gn:admin1_code":"03",
    "gn:asciiname":"Anjialava",
    "gn:cc2":"MG",
    "gn:country_code":"MG",
    "gn:dem":39,
    "gn:feature_class":"P",
    "gn:feature_code":"PPL",
    "gn:name":"Anjialava",
    "gn:population":0,
    "gn:timezone":"Indian/Antananarivo",
    "iso:country":"MG",
    "name:fra_x_preferred":[
        "Anjialava"
    ],
    "name:ita_x_preferred":[
        "Anjialava"
    ],
    "name:mlg_x_preferred":[
        "Anjialava"
    ],
    "name:nld_x_preferred":[
        "Anjialava"
    ],
    "name:und_x_variant":[
        "Anjialavo"
    ],
    "wof:name":"Anjialava",
    "wof:placetype":"locality"
},
  "geometry": {"coordinates":[47.56667,-15.81667],"type":"Point"}
}