{
  "type": "Feature",
  "properties": {
    "gn:admin1_code":"3.0",
    "gn:asciiname":"Tsaramandroso",
    "gn:cc2":"MG",
    "gn:country_code":"MG",
    "gn:dem":46,
    "gn:feature_class":"P",
    "gn:feature_code":"PPL",
    "gn:name":"Tsaramandroso",
    "gn:population":0,
    "gn:timezone":"Indian/Antananarivo",
    "iso:country":"MG",
    "name:fra_x_preferred":[
        "Tsaramandroso"
    ],
    "name:ita_x_preferred":[
        "Tsaramandroso"
    ],
    "name:mlg_x_preferred":[
        "Tsaramandroso"
    ],
    "name:nld_x_preferred":[
        "Tsaramandroso"
    ],
    "name:und_x_variant":[
        "Tanamba",
        "Tsaramandroso"
    ],
    "wof:name":"Tsaramandroso",
    "wof:placetype":"locality"
},
  "geometry": {"coordinates":[46.88333,-15.73333],"type":"Point"}
}