{
  "type": "Feature",
  "properties": {
    "gn:admin1_code":"06",
    "gn:asciiname":"Analalava",
    "gn:country_code":"MG",
    "gn:dem":365,
    "gn:feature_class":"P",
    "gn:feature_code":"PPL",
    "gn:name":"Analalava",
    "gn:population":0,
    "gn:timezone":"Indian/Antananarivo",
    "iso:country":"MG",
    "wof:name":"Analalava",
    "wof:placetype":"locality"
},
  "geometry": {"coordinates":[45.26667,-24.31667],"type":"Point"}
}