{
  "type": "Feature",
  "properties": {
    "gn:admin1_code":"6.0",
    "gn:asciiname":"Tsitakabasia",
    "gn:country_code":"MG",
    "gn:dem":45,
    "gn:feature_class":"P",
    "gn:feature_code":"PPL",
    "gn:name":"Tsitakabasia",
    "gn:population":0,
    "gn:timezone":"Indian/Antananarivo",
    "iso:country":"MG",
    "wof:name":"Tsitakabasia",
    "wof:placetype":"locality"
},
  "geometry": {"coordinates":[44.61667,-19.73333],"type":"Point"}
}