{
  "type": "Feature",
  "properties": {
    "gn:admin1_code":"05",
    "gn:asciiname":"Analamiranga",
    "gn:country_code":"MG",
    "gn:dem":870,
    "gn:feature_class":"P",
    "gn:feature_code":"PPL",
    "gn:name":"Analamiranga",
    "gn:population":0,
    "gn:timezone":"Indian/Antananarivo",
    "iso:country":"MG",
    "wof:name":"Analamiranga",
    "wof:placetype":"locality"
},
  "geometry": {"coordinates":[46.21667,-19.38333],"type":"Point"}
}