{
  "type": "Feature",
  "properties": {
    "gn:admin1_code":"03",
    "gn:asciiname":"Ambaladera",
    "gn:country_code":"MG",
    "gn:dem":982,
    "gn:feature_class":"P",
    "gn:feature_code":"PPL",
    "gn:name":"Ambaladera",
    "gn:population":0,
    "gn:timezone":"Indian/Antananarivo",
    "iso:country":"MG",
    "wof:name":"Ambaladera",
    "wof:placetype":"locality"
},
  "geometry": {"coordinates":[49.23333,-14.73333],"type":"Point"}
}