{
  "type": "Feature",
  "properties": {
    "gn:admin1_code":"06",
    "gn:asciiname":"Bevoay",
    "gn:country_code":"MG",
    "gn:dem":614,
    "gn:feature_class":"P",
    "gn:feature_code":"PPL",
    "gn:name":"Bevoay",
    "gn:population":0,
    "gn:timezone":"Indian/Antananarivo",
    "iso:country":"MG",
    "name:fra_x_preferred":[
        "Bevoay"
    ],
    "name:ita_x_preferred":[
        "Bevoay"
    ],
    "name:mlg_x_preferred":[
        "Bevoay"
    ],
    "name:nld_x_preferred":[
        "Bevoay"
    ],
    "wof:name":"Bevoay",
    "wof:placetype":"locality"
},
  "geometry": {"coordinates":[45.58333,-23.35],"type":"Point"}
}