{
  "type": "Feature",
  "properties": {
    "gn:admin1_code":"4.0",
    "gn:asciiname":"Sahafitahana",
    "gn:country_code":"MG",
    "gn:dem":912,
    "gn:feature_class":"P",
    "gn:feature_code":"PPL",
    "gn:name":"Sahafitahana",
    "gn:population":0,
    "gn:timezone":"Indian/Antananarivo",
    "iso:country":"MG",
    "wof:name":"Sahafitahana",
    "wof:placetype":"locality"
},
  "geometry": {"coordinates":[48.21667,-18.98333],"type":"Point"}
}