{
  "type": "Feature",
  "properties": {
    "gn:admin1_code":"01",
    "gn:asciiname":"Antsahamivory",
    "gn:country_code":"MG",
    "gn:dem":842,
    "gn:feature_class":"P",
    "gn:feature_code":"PPL",
    "gn:name":"Antsahamivory",
    "gn:population":0,
    "gn:timezone":"Indian/Antananarivo",
    "iso:country":"MG",
    "wof:name":"Antsahamivory",
    "wof:placetype":"locality"
},
  "geometry": {"coordinates":[49.45,-14.16667],"type":"Point"}
}