{
  "type": "Feature",
  "properties": {
    "gn:admin1_code":"3.0",
    "gn:asciiname":"Tsaratanana",
    "gn:country_code":"MG",
    "gn:dem":318,
    "gn:feature_class":"P",
    "gn:feature_code":"PPL",
    "gn:name":"Tsaratanana",
    "gn:population":0,
    "gn:timezone":"Indian/Antananarivo",
    "iso:country":"MG",
    "wof:name":"Tsaratanana",
    "wof:placetype":"locality"
},
  "geometry": {"coordinates":[48.85,-15.95],"type":"Point"}
}