{
  "type": "Feature",
  "properties": {
    "gn:admin1_code":"02",
    "gn:asciiname":"Ialinaloha",
    "gn:country_code":"MG",
    "gn:dem":889,
    "gn:feature_class":"P",
    "gn:feature_code":"PPL",
    "gn:name":"Ialinaloha",
    "gn:population":0,
    "gn:timezone":"Indian/Antananarivo",
    "iso:country":"MG",
    "wof:name":"Ialinaloha",
    "wof:placetype":"locality"
},
  "geometry": {"coordinates":[46.83333,-23.78333],"type":"Point"}
}