{
  "type": "Feature",
  "properties": {
    "gn:admin1_code":"03",
    "gn:asciiname":"Beamalona",
    "gn:country_code":"MG",
    "gn:dem":308,
    "gn:feature_class":"P",
    "gn:feature_code":"PPL",
    "gn:name":"Beamalona",
    "gn:population":0,
    "gn:timezone":"Indian/Antananarivo",
    "iso:country":"MG",
    "wof:name":"Beamalona",
    "wof:placetype":"locality"
},
  "geometry": {"coordinates":[47.96667,-16.05],"type":"Point"}
}