{
  "type": "Feature",
  "properties": {
    "gn:admin1_code":"05",
    "gn:asciiname":"Betaimboraka",
    "gn:country_code":"MG",
    "gn:dem":916,
    "gn:feature_class":"P",
    "gn:feature_code":"PPL",
    "gn:name":"Betaimboraka",
    "gn:population":0,
    "gn:timezone":"Indian/Antananarivo",
    "iso:country":"MG",
    "wof:name":"Betaimboraka",
    "wof:placetype":"locality"
},
  "geometry": {"coordinates":[45.86667,-18.36667000000001],"type":"Point"}
}