{
  "type": "Feature",
  "properties": {
    "gn:admin1_code":"03",
    "gn:asciiname":"Ankisompy",
    "gn:cc2":"MG",
    "gn:country_code":"MG",
    "gn:dem":161,
    "gn:feature_class":"P",
    "gn:feature_code":"PPL",
    "gn:name":"Ankisompy",
    "gn:population":0,
    "gn:timezone":"Indian/Antananarivo",
    "iso:country":"MG",
    "name:und_x_variant":[
        "Ankisopy",
        "Ankisompy"
    ],
    "wof:name":"Ankisompy",
    "wof:placetype":"locality"
},
  "geometry": {"coordinates":[47.38333,-15.83333],"type":"Point"}
}