{
  "type": "Feature",
  "properties": {
    "gn:admin1_code":"01",
    "gn:asciiname":"Maromokotra",
    "gn:country_code":"MG",
    "gn:dem":31,
    "gn:feature_class":"P",
    "gn:feature_code":"PPL",
    "gn:name":"Maromokotra",
    "gn:population":0,
    "gn:timezone":"Indian/Antananarivo",
    "iso:country":"MG",
    "wof:name":"Maromokotra",
    "wof:placetype":"locality"
},
  "geometry": {"coordinates":[47.95,-14.01667],"type":"Point"}
}