{
  "type": "Feature",
  "properties": {
    "gn:admin1_code":"06",
    "gn:asciiname":"Antsiratsira",
    "gn:country_code":"MG",
    "gn:dem":925,
    "gn:feature_class":"P",
    "gn:feature_code":"PPL",
    "gn:name":"Antsiratsira",
    "gn:population":0,
    "gn:timezone":"Indian/Antananarivo",
    "iso:country":"MG",
    "wof:name":"Antsiratsira",
    "wof:placetype":"locality"
},
  "geometry": {"coordinates":[45.53333,-18.45],"type":"Point"}
}