{
  "type": "Feature",
  "properties": {
    "gn:admin1_code":"2.0",
    "gn:asciiname":"Sandraimoro",
    "gn:cc2":"MG",
    "gn:country_code":"MG",
    "gn:dem":119,
    "gn:feature_class":"P",
    "gn:feature_code":"PPL",
    "gn:name":"Sandraimoro",
    "gn:population":0,
    "gn:timezone":"Indian/Antananarivo",
    "iso:country":"MG",
    "name:und_x_variant":[
        "Sanoriamora",
        "Sandraimoro"
    ],
    "wof:name":"Sandraimoro",
    "wof:placetype":"locality"
},
  "geometry": {"coordinates":[47.96667,-21.61667000000001],"type":"Point"}
}