{
  "type": "Feature",
  "properties": {
    "gn:admin1_code":"2.0",
    "gn:asciiname":"Soaserana",
    "gn:country_code":"MG",
    "gn:dem":704,
    "gn:feature_class":"P",
    "gn:feature_code":"PPL",
    "gn:name":"Soaserana",
    "gn:population":0,
    "gn:timezone":"Indian/Antananarivo",
    "iso:country":"MG",
    "wof:name":"Soaserana",
    "wof:placetype":"locality"
},
  "geometry": {"coordinates":[45.35,-22.73333],"type":"Point"}
}