{
  "type": "Feature",
  "properties": {
    "gn:admin1_code":"06",
    "gn:asciiname":"Fenovahoaka",
    "gn:country_code":"MG",
    "gn:dem":135,
    "gn:feature_class":"P",
    "gn:feature_code":"PPL",
    "gn:name":"Fenovahoaka",
    "gn:population":0,
    "gn:timezone":"Indian/Antananarivo",
    "iso:country":"MG",
    "wof:name":"Fenovahoaka",
    "wof:placetype":"locality"
},
  "geometry": {"coordinates":[46.91667,-24.53333],"type":"Point"}
}