{
  "type": "Feature",
  "properties": {
    "gn:admin1_code":"03",
    "gn:asciiname":"Ambohidriana",
    "gn:country_code":"MG",
    "gn:dem":291,
    "gn:feature_class":"P",
    "gn:feature_code":"PPL",
    "gn:name":"Ambohidriana",
    "gn:population":0,
    "gn:timezone":"Indian/Antananarivo",
    "iso:country":"MG",
    "wof:name":"Ambohidriana",
    "wof:placetype":"locality"
},
  "geometry": {"coordinates":[47.83333,-16.23333],"type":"Point"}
}