{
  "type": "Feature",
  "properties": {
    "gn:admin1_code":"04",
    "gn:asciiname":"Betsimanoina",
    "gn:country_code":"MG",
    "gn:dem":868,
    "gn:feature_class":"P",
    "gn:feature_code":"PPL",
    "gn:name":"Betsimanoina",
    "gn:population":0,
    "gn:timezone":"Indian/Antananarivo",
    "iso:country":"MG",
    "wof:name":"Betsimanoina",
    "wof:placetype":"locality"
},
  "geometry": {"coordinates":[48.03333,-18.75],"type":"Point"}
}