{
  "type": "Feature",
  "properties": {
    "gn:admin1_code":"02",
    "gn:asciiname":"Belemboka",
    "gn:cc2":"MG",
    "gn:country_code":"MG",
    "gn:dem":683,
    "gn:feature_class":"P",
    "gn:feature_code":"PPL",
    "gn:name":"Belemboka",
    "gn:population":0,
    "gn:timezone":"Indian/Antananarivo",
    "iso:country":"MG",
    "name:und_x_variant":[
        "Belemoka",
        "Belemboka"
    ],
    "wof:name":"Belemboka",
    "wof:placetype":"locality"
},
  "geometry": {"coordinates":[46.58333,-22.55],"type":"Point"}
}