{
  "type": "Feature",
  "properties": {
    "gn:admin1_code":"02",
    "gn:asciiname":"Maroharatra",
    "gn:country_code":"MG",
    "gn:dem":122,
    "gn:feature_class":"P",
    "gn:feature_code":"PPL",
    "gn:name":"Maroharatra",
    "gn:population":0,
    "gn:timezone":"Indian/Antananarivo",
    "iso:country":"MG",
    "name:fra_x_preferred":[
        "Maroharatra"
    ],
    "name:ita_x_preferred":[
        "Maroharatra"
    ],
    "name:mlg_x_preferred":[
        "Maroharatra"
    ],
    "name:nld_x_preferred":[
        "Maroharatra"
    ],
    "wof:name":"Maroharatra",
    "wof:placetype":"locality"
},
  "geometry": {"coordinates":[48.26667,-20.78333],"type":"Point"}
}