{
  "type": "Feature",
  "properties": {
    "gn:admin1_code":"04",
    "gn:asciiname":"Andilamenakely",
    "gn:country_code":"MG",
    "gn:dem":943,
    "gn:feature_class":"P",
    "gn:feature_code":"PPL",
    "gn:name":"Andilamenakely",
    "gn:population":0,
    "gn:timezone":"Indian/Antananarivo",
    "iso:country":"MG",
    "wof:name":"Andilamenakely",
    "wof:placetype":"locality"
},
  "geometry": {"coordinates":[48.06667,-18.06667],"type":"Point"}
}