{
  "type": "Feature",
  "properties": {
    "gn:admin1_code":"02",
    "gn:asciiname":"Antsindra",
    "gn:country_code":"MG",
    "gn:dem":436,
    "gn:feature_class":"P",
    "gn:feature_code":"PPL",
    "gn:name":"Antsindra",
    "gn:population":0,
    "gn:timezone":"Indian/Antananarivo",
    "iso:country":"MG",
    "wof:name":"Antsindra",
    "wof:placetype":"locality"
},
  "geometry": {"coordinates":[47.73333,-20.98333],"type":"Point"}
}