{
  "type": "Feature",
  "properties": {
    "iso:country":"MG",
    "name:bul_x_preferred":[
        "\u0411\u0435\u043b\u044f\u0437\u0430\u0443"
    ],
    "name:eng_x_preferred":[
        "Belazao"
    ],
    "name:fra_x_preferred":[
        "Belazao"
    ],
    "name:mlg_x_preferred":[
        "Belazao"
    ],
    "name:nld_x_preferred":[
        "Belazao"
    ],
    "name:pol_x_preferred":[
        "Belazao"
    ],
    "qs:gn_country":"MG",
    "qs:gn_fcode":"PPL",
    "qs:gn_pop":0,
    "qs:name":"Belazao",
    "qs:name_adm0":"Madagascar",
    "qs:name_adm1":"Antananarivo",
    "qs:photos":163,
    "qs:photos_1k":33,
    "qs:photos_9k":1,
    "qs:photos_9r":4,
    "qs:photos_all":163,
    "qs:photos_sr":4,
    "qs:placetype":"Town",
    "qs:pop_sr":"0",
    "qs:woe_adm0":23424883,
    "wd:wordcount":128,
    "wof:name":"Belazao",
    "wof:placetype":"locality"
},
  "geometry": {"coordinates":[46.96667,-19.88333],"type":"Point"}
}