{
  "type": "Feature",
  "properties": {
    "gn:admin1_code":"04",
    "gn:asciiname":"Fiadanana",
    "gn:country_code":"MG",
    "gn:dem":782,
    "gn:feature_class":"P",
    "gn:feature_code":"PPL",
    "gn:name":"Fiadanana",
    "gn:population":0,
    "gn:timezone":"Indian/Antananarivo",
    "iso:country":"MG",
    "wof:name":"Fiadanana",
    "wof:placetype":"locality"
},
  "geometry": {"coordinates":[47.95,-19.86667000000001],"type":"Point"}
}