{
  "type": "Feature",
  "properties": {
    "gn:admin1_code":"01",
    "gn:asciiname":"Ampasimitera",
    "gn:country_code":"MG",
    "gn:dem":8,
    "gn:feature_class":"P",
    "gn:feature_code":"PPL",
    "gn:name":"Ampasimitera",
    "gn:population":0,
    "gn:timezone":"Indian/Antananarivo",
    "iso:country":"MG",
    "wof:name":"Ampasimitera",
    "wof:placetype":"locality"
},
  "geometry": {"coordinates":[48.51667,-13.58333],"type":"Point"}
}