{
  "type": "Feature",
  "properties": {
    "gn:admin1_code":"02",
    "gn:asciiname":"Ampizaramaso",
    "gn:country_code":"MG",
    "gn:dem":701,
    "gn:feature_class":"P",
    "gn:feature_code":"PPL",
    "gn:name":"Ampizaramaso",
    "gn:population":0,
    "gn:timezone":"Indian/Antananarivo",
    "iso:country":"MG",
    "wof:name":"Ampizaramaso",
    "wof:placetype":"locality"
},
  "geometry": {"coordinates":[46.81667,-22.31667],"type":"Point"}
}