{
  "type": "Feature",
  "properties": {
    "gn:admin1_code":"06",
    "gn:asciiname":"Ankazomena",
    "gn:country_code":"MG",
    "gn:dem":106,
    "gn:feature_class":"P",
    "gn:feature_code":"PPL",
    "gn:name":"Ankazomena",
    "gn:population":0,
    "gn:timezone":"Indian/Antananarivo",
    "iso:country":"MG",
    "wof:name":"Ankazomena",
    "wof:placetype":"locality"
},
  "geometry": {"coordinates":[43.83333,-23.43333],"type":"Point"}
}