{
  "type": "Feature",
  "properties": {
    "gn:admin1_code":"02",
    "gn:asciiname":"Ambohibao",
    "gn:country_code":"MG",
    "gn:dem":1067,
    "gn:feature_class":"P",
    "gn:feature_code":"PPL",
    "gn:name":"Ambohibao",
    "gn:population":0,
    "gn:timezone":"Indian/Antananarivo",
    "iso:country":"MG",
    "wof:name":"Ambohibao",
    "wof:placetype":"locality"
},
  "geometry": {"coordinates":[47.08333,-21.01667],"type":"Point"}
}