{
  "type": "Feature",
  "properties": {
    "gn:admin1_code":"06",
    "gn:asciiname":"Efame",
    "gn:country_code":"MG",
    "gn:dem":180,
    "gn:feature_class":"P",
    "gn:feature_code":"PPL",
    "gn:name":"Efame",
    "gn:population":0,
    "gn:timezone":"Indian/Antananarivo",
    "iso:country":"MG",
    "wof:name":"Efame",
    "wof:placetype":"locality"
},
  "geometry": {"coordinates":[46.08333,-25.21667],"type":"Point"}
}