{
  "type": "Feature",
  "properties": {
    "gn:admin1_code":"05",
    "gn:asciiname":"Ambohitsoa",
    "gn:country_code":"MG",
    "gn:dem":1322,
    "gn:feature_class":"P",
    "gn:feature_code":"PPL",
    "gn:name":"Ambohitsoa",
    "gn:population":0,
    "gn:timezone":"Indian/Antananarivo",
    "iso:country":"MG",
    "wof:name":"Ambohitsoa",
    "wof:placetype":"locality"
},
  "geometry": {"coordinates":[47.58333,-19.05],"type":"Point"}
}