{
  "type": "Feature",
  "properties": {
    "gn:admin1_code":"06",
    "gn:asciiname":"Bevitiky",
    "gn:country_code":"MG",
    "gn:dem":184,
    "gn:feature_class":"P",
    "gn:feature_code":"PPL",
    "gn:name":"Bevitiky",
    "gn:population":0,
    "gn:timezone":"Indian/Antananarivo",
    "iso:country":"MG",
    "name:fra_x_preferred":[
        "Bevitiky"
    ],
    "name:ita_x_preferred":[
        "Bevitiky"
    ],
    "name:mlg_x_preferred":[
        "Bevitiky"
    ],
    "name:nld_x_preferred":[
        "Bevitiky"
    ],
    "wof:name":"Bevitiky",
    "wof:placetype":"locality"
},
  "geometry": {"coordinates":[44.86667,-24.75],"type":"Point"}
}