{
  "type": "Feature",
  "properties": {
    "gn:admin1_code":"03",
    "gn:asciiname":"Ankosibe",
    "gn:country_code":"MG",
    "gn:dem":421,
    "gn:feature_class":"P",
    "gn:feature_code":"PPL",
    "gn:name":"Ankosibe",
    "gn:population":0,
    "gn:timezone":"Indian/Antananarivo",
    "iso:country":"MG",
    "wof:name":"Ankosibe",
    "wof:placetype":"locality"
},
  "geometry": {"coordinates":[48.98333,-15.58333],"type":"Point"}
}