{
  "type": "Feature",
  "properties": {
    "gn:admin1_code":"01",
    "gn:asciiname":"Amponaomby",
    "gn:cc2":"MG",
    "gn:country_code":"MG",
    "gn:dem":958,
    "gn:feature_class":"P",
    "gn:feature_code":"PPL",
    "gn:name":"Amponaomby",
    "gn:population":0,
    "gn:timezone":"Indian/Antananarivo",
    "iso:country":"MG",
    "name:und_x_variant":[
        "Ampoanomby",
        "Amponaomby"
    ],
    "wof:name":"Amponaomby",
    "wof:placetype":"locality"
},
  "geometry": {"coordinates":[49.53333,-14.83333],"type":"Point"}
}