{
  "type": "Feature",
  "properties": {
    "gn:admin1_code":"6.0",
    "gn:asciiname":"Sakoapolo",
    "gn:country_code":"MG",
    "gn:dem":162,
    "gn:feature_class":"P",
    "gn:feature_code":"PPL",
    "gn:name":"Sakoapolo",
    "gn:population":0,
    "gn:timezone":"Indian/Antananarivo",
    "iso:country":"MG",
    "wof:name":"Sakoapolo",
    "wof:placetype":"locality"
},
  "geometry": {"coordinates":[44.83333,-23.55],"type":"Point"}
}