{
  "type": "Feature",
  "properties": {
    "gn:admin1_code":"02",
    "gn:asciiname":"Mahavelona",
    "gn:country_code":"MG",
    "gn:dem":286,
    "gn:feature_class":"P",
    "gn:feature_code":"PPL",
    "gn:name":"Mahavelona",
    "gn:population":0,
    "gn:timezone":"Indian/Antananarivo",
    "iso:country":"MG",
    "name:ceb_x_preferred":[
        "Mahavelona"
    ],
    "name:fra_x_preferred":[
        "Foulpointe"
    ],
    "name:hrv_x_preferred":[
        "Mahavelona"
    ],
    "name:ind_x_preferred":[
        "Mahavelona"
    ],
    "name:ita_x_preferred":[
        "Foul Poite"
    ],
    "name:nld_x_preferred":[
        "Mahavelona"
    ],
    "name:swe_x_preferred":[
        "Mahavelona"
    ],
    "wof:name":"Mahavelona",
    "wof:placetype":"locality"
},
  "geometry": {"coordinates":[48.08333,-20.81667],"type":"Point"}
}