{
  "type": "Feature",
  "properties": {
    "gn:admin1_code":"03",
    "gn:asciiname":"Menazomby",
    "gn:country_code":"MG",
    "gn:dem":1021,
    "gn:feature_class":"P",
    "gn:feature_code":"PPL",
    "gn:name":"Menazomby",
    "gn:population":0,
    "gn:timezone":"Indian/Antananarivo",
    "iso:country":"MG",
    "wof:name":"Menazomby",
    "wof:placetype":"locality"
},
  "geometry": {"coordinates":[47.78333,-16.75],"type":"Point"}
}