{
  "type": "Feature",
  "properties": {
    "gn:admin1_code":"06",
    "gn:asciiname":"Mandabe Atsimo",
    "gn:cc2":"MG",
    "gn:country_code":"MG",
    "gn:dem":354,
    "gn:feature_class":"P",
    "gn:feature_code":"PPL",
    "gn:name":"Mandabe Atsimo",
    "gn:population":0,
    "gn:timezone":"Indian/Antananarivo",
    "iso:country":"MG",
    "name:und_x_variant":[
        "Mandabe Sud",
        "Mandabe Atsimo"
    ],
    "wof:name":"Mandabe Atsimo",
    "wof:placetype":"locality"
},
  "geometry": {"coordinates":[45.06667,-22.05],"type":"Point"}
}