{
  "type": "Feature",
  "properties": {
    "gn:admin1_code":"01",
    "gn:asciiname":"Ambahivahikely",
    "gn:country_code":"MG",
    "gn:dem":467,
    "gn:feature_class":"P",
    "gn:feature_code":"PPL",
    "gn:name":"Ambahivahikely",
    "gn:population":0,
    "gn:timezone":"Indian/Antananarivo",
    "iso:country":"MG",
    "wof:name":"Ambahivahikely",
    "wof:placetype":"locality"
},
  "geometry": {"coordinates":[49.26667,-12.56667],"type":"Point"}
}