{
  "type": "Feature",
  "properties": {
    "gn:admin1_code":"06",
    "gn:asciiname":"Relova",
    "gn:country_code":"MG",
    "gn:dem":284,
    "gn:feature_class":"P",
    "gn:feature_code":"PPL",
    "gn:name":"Relova",
    "gn:population":0,
    "gn:timezone":"Indian/Antananarivo",
    "iso:country":"MG",
    "wof:name":"Relova",
    "wof:placetype":"locality"
},
  "geometry": {"coordinates":[45.16667,-24.71667],"type":"Point"}
}