{
  "type": "Feature",
  "properties": {
    "gn:admin1_code":"05",
    "gn:asciiname":"Avaradoha",
    "gn:country_code":"MG",
    "gn:dem":1254,
    "gn:feature_class":"P",
    "gn:feature_code":"PPL",
    "gn:name":"Avaradoha",
    "gn:population":0,
    "gn:timezone":"Indian/Antananarivo",
    "iso:country":"MG",
    "wof:name":"Avaradoha",
    "wof:placetype":"locality"
},
  "geometry": {"coordinates":[47.53333,-18.88333],"type":"Point"}
}