{
  "type": "Feature",
  "properties": {
    "gn:admin1_code":"03",
    "gn:asciiname":"Betsitindry",
    "gn:cc2":"MG",
    "gn:country_code":"MG",
    "gn:dem":299,
    "gn:feature_class":"P",
    "gn:feature_code":"PPL",
    "gn:name":"Betsitindry",
    "gn:population":0,
    "gn:timezone":"Indian/Antananarivo",
    "iso:country":"MG",
    "name:und_x_variant":[
        "Betsilindry",
        "Betsitindry"
    ],
    "wof:name":"Betsitindry",
    "wof:placetype":"locality"
},
  "geometry": {"coordinates":[48.36667,-15.48333],"type":"Point"}
}