{
  "type": "Feature",
  "properties": {
    "gn:admin1_code":"6.0",
    "gn:asciiname":"Toby",
    "gn:country_code":"MG",
    "gn:dem":49,
    "gn:feature_class":"P",
    "gn:feature_code":"PPL",
    "gn:name":"Toby",
    "gn:population":0,
    "gn:timezone":"Indian/Antananarivo",
    "iso:country":"MG",
    "wof:name":"Toby",
    "wof:placetype":"locality"
},
  "geometry": {"coordinates":[46.48333,-25.03333],"type":"Point"}
}