{
  "type": "Feature",
  "properties": {
    "gn:admin1_code":"06",
    "gn:asciiname":"Antsivavy",
    "gn:country_code":"MG",
    "gn:dem":49,
    "gn:feature_class":"P",
    "gn:feature_code":"PPL",
    "gn:name":"Antsivavy",
    "gn:population":0,
    "gn:timezone":"Indian/Antananarivo",
    "iso:country":"MG",
    "wof:name":"Antsivavy",
    "wof:placetype":"locality"
},
  "geometry": {"coordinates":[46.23333,-24.86667000000001],"type":"Point"}
}