{
  "type": "Feature",
  "properties": {
    "gn:admin1_code":"06",
    "gn:asciiname":"Ampandra Atsimo",
    "gn:country_code":"MG",
    "gn:dem":561,
    "gn:feature_class":"P",
    "gn:feature_code":"PPL",
    "gn:name":"Ampandra Atsimo",
    "gn:population":0,
    "gn:timezone":"Indian/Antananarivo",
    "iso:country":"MG",
    "wof:name":"Ampandra Atsimo",
    "wof:placetype":"locality"
},
  "geometry": {"coordinates":[43.91667,-22.53333],"type":"Point"}
}