{
  "type": "Feature",
  "properties": {
    "gn:admin1_code":"06",
    "gn:asciiname":"Ankilitelo",
    "gn:country_code":"MG",
    "gn:dem":199,
    "gn:feature_class":"P",
    "gn:feature_code":"PPL",
    "gn:name":"Ankilitelo",
    "gn:population":0,
    "gn:timezone":"Indian/Antananarivo",
    "iso:country":"MG",
    "wof:name":"Ankilitelo",
    "wof:placetype":"locality"
},
  "geometry": {"coordinates":[44.76667,-23.63333],"type":"Point"}
}