{
  "type": "Feature",
  "properties": {
    "iso:country":"MG",
    "qs:gn_pop":0,
    "qs:name":"Betty-Plage",
    "qs:name_adm0":"Madagascar",
    "qs:name_adm1":"Toamasina",
    "qs:photos":55,
    "qs:photos_1k":11,
    "qs:photos_9k":1,
    "qs:photos_9r":2,
    "qs:photos_all":55,
    "qs:photos_sr":2,
    "qs:placetype":"Town",
    "qs:pop_sr":"0",
    "qs:woe_adm0":23424883,
    "wof:name":"Betty-Plage",
    "wof:placetype":"locality"
},
  "geometry": {"coordinates":[49.86763,-16.930705],"type":"Point"}
}