{
  "type": "Feature",
  "properties": {
    "gn:admin1_code":"01",
    "gn:asciiname":"Ambonaramavo",
    "gn:country_code":"MG",
    "gn:dem":29,
    "gn:feature_class":"P",
    "gn:feature_code":"PPL",
    "gn:name":"Ambonaramavo",
    "gn:population":0,
    "gn:timezone":"Indian/Antananarivo",
    "iso:country":"MG",
    "wof:name":"Ambonaramavo",
    "wof:placetype":"locality"
},
  "geometry": {"coordinates":[49.86667,-13.63333],"type":"Point"}
}