{
  "type": "Feature",
  "properties": {
    "gn:admin1_code":"2.0",
    "gn:asciiname":"Tsinjorano",
    "gn:country_code":"MG",
    "gn:dem":1184,
    "gn:feature_class":"P",
    "gn:feature_code":"PPL",
    "gn:name":"Tsinjorano",
    "gn:population":0,
    "gn:timezone":"Indian/Antananarivo",
    "iso:country":"MG",
    "wof:name":"Tsinjorano",
    "wof:placetype":"locality"
},
  "geometry": {"coordinates":[46.95,-20.31667],"type":"Point"}
}