{
  "type": "Feature",
  "properties": {
    "gn:admin1_code":"02",
    "gn:asciiname":"Ambararata",
    "gn:country_code":"MG",
    "gn:dem":587,
    "gn:feature_class":"P",
    "gn:feature_code":"PPL",
    "gn:name":"Ambararata",
    "gn:population":0,
    "gn:timezone":"Indian/Antananarivo",
    "iso:country":"MG",
    "wof:name":"Ambararata",
    "wof:placetype":"locality"
},
  "geometry": {"coordinates":[46.73333,-22.88333],"type":"Point"}
}