{
  "type": "Feature",
  "properties": {
    "gn:admin1_code":"03",
    "gn:asciiname":"Ambohimahasoa",
    "gn:country_code":"MG",
    "gn:dem":654,
    "gn:feature_class":"P",
    "gn:feature_code":"PPL",
    "gn:name":"Ambohimahasoa",
    "gn:population":0,
    "gn:timezone":"Indian/Antananarivo",
    "iso:country":"MG",
    "wof:name":"Ambohimahasoa",
    "wof:placetype":"locality"
},
  "geometry": {"coordinates":[47.45,-17.73333],"type":"Point"}
}