{
  "type": "Feature",
  "properties": {
    "gn:admin1_code":"03",
    "gn:asciiname":"Ambohimahasoa",
    "gn:country_code":"MG",
    "gn:dem":654,
    "gn:feature_class":"P",
    "gn:feature_code":"PPL",
    "gn:name":"Ambohimahasoa",
    "gn:population":0,
    "gn:timezone":"Indian/Antananarivo",
    "iso:country":"MG",
    "name:ceb_x_preferred":[
        "Ambohimahasoa"
    ],
    "name:deu_x_preferred":[
        "Ambohimahasoa"
    ],
    "name:fra_x_preferred":[
        "Ambohimahasoa"
    ],
    "name:ita_x_preferred":[
        "Ambohimahasoa"
    ],
    "name:mlg_x_preferred":[
        "Ambohimahasoa"
    ],
    "name:nld_x_preferred":[
        "Ambohimahasoa"
    ],
    "name:pol_x_preferred":[
        "Ambohimahasoa"
    ],
    "name:swe_x_preferred":[
        "Ambohimahasoa"
    ],
    "name:zho_x_preferred":[
        "\u5b89\u5e03\u5e0c\u99ac\u54c8\u8607\u963f"
    ],
    "wof:name":"Ambohimahasoa",
    "wof:placetype":"locality"
},
  "geometry": {"coordinates":[47.45,-17.73333],"type":"Point"}
}