{
  "type": "Feature",
  "properties": {
    "gn:admin1_code":"03",
    "gn:asciiname":"Antanamena",
    "gn:country_code":"MG",
    "gn:dem":188,
    "gn:feature_class":"P",
    "gn:feature_code":"PPL",
    "gn:name":"Antanamena",
    "gn:population":0,
    "gn:timezone":"Indian/Antananarivo",
    "iso:country":"MG",
    "wof:name":"Antanamena",
    "wof:placetype":"locality"
},
  "geometry": {"coordinates":[47.91667,-14.36667],"type":"Point"}
}