{
  "type": "Feature",
  "properties": {
    "gn:admin1_code":"2.0",
    "gn:asciiname":"Vohimasy",
    "gn:cc2":"MG",
    "gn:country_code":"MG",
    "gn:dem":16,
    "gn:feature_class":"P",
    "gn:feature_code":"PPL",
    "gn:name":"Vohimasy",
    "gn:population":0,
    "gn:timezone":"Indian/Antananarivo",
    "iso:country":"MG",
    "name:und_x_variant":[
        "Vohimasina",
        "Vohimasy"
    ],
    "wof:name":"Vohimasy",
    "wof:placetype":"locality"
},
  "geometry": {"coordinates":[47.75,-22.81667],"type":"Point"}
}