{
  "type": "Feature",
  "properties": {
    "gn:admin1_code":"03",
    "gn:asciiname":"Ambonary",
    "gn:country_code":"MG",
    "gn:dem":553,
    "gn:feature_class":"P",
    "gn:feature_code":"PPL",
    "gn:name":"Ambonary",
    "gn:population":0,
    "gn:timezone":"Indian/Antananarivo",
    "iso:country":"MG",
    "wof:name":"Ambonary",
    "wof:placetype":"locality"
},
  "geometry": {"coordinates":[45.46667,-17.88332999999999],"type":"Point"}
}