{
  "type": "Feature",
  "properties": {
    "gn:admin1_code":"4.0",
    "gn:asciiname":"Sahazomena",
    "gn:country_code":"MG",
    "gn:dem":262,
    "gn:feature_class":"P",
    "gn:feature_code":"PPL",
    "gn:name":"Sahazomena",
    "gn:population":0,
    "gn:timezone":"Indian/Antananarivo",
    "iso:country":"MG",
    "wof:name":"Sahazomena",
    "wof:placetype":"locality"
},
  "geometry": {"coordinates":[49.01667,-17.43333],"type":"Point"}
}