{
  "type": "Feature",
  "properties": {
    "gn:admin1_code":"06",
    "gn:asciiname":"Matara",
    "gn:country_code":"MG",
    "gn:dem":195,
    "gn:feature_class":"P",
    "gn:feature_code":"PPL",
    "gn:name":"Matara",
    "gn:population":0,
    "gn:timezone":"Indian/Antananarivo",
    "iso:country":"MG",
    "wof:name":"Matara",
    "wof:placetype":"locality"
},
  "geometry": {"coordinates":[45.26667,-25.53333],"type":"Point"}
}