{
  "type": "Feature",
  "properties": {
    "gn:admin1_code":"06",
    "gn:asciiname":"Matara",
    "gn:country_code":"MG",
    "gn:dem":195,
    "gn:feature_class":"P",
    "gn:feature_code":"PPL",
    "gn:name":"Matara",
    "gn:population":0,
    "gn:timezone":"Indian/Antananarivo",
    "iso:country":"MG",
    "name:ceb_x_preferred":[
        "Matara"
    ],
    "name:ind_x_preferred":[
        "Matara"
    ],
    "name:ita_x_preferred":[
        "Matara"
    ],
    "name:nld_x_preferred":[
        "Matara"
    ],
    "name:pol_x_preferred":[
        "Matara"
    ],
    "name:por_x_preferred":[
        "Matar\u00e1"
    ],
    "name:rus_x_preferred":[
        "\u041c\u0430\u0442\u0430\u0440\u0430"
    ],
    "name:spa_x_preferred":[
        "Matar\u00e1"
    ],
    "name:swe_x_preferred":[
        "Matara"
    ],
    "wof:name":"Matara",
    "wof:placetype":"locality"
},
  "geometry": {"coordinates":[45.26667,-25.53333],"type":"Point"}
}