{
  "type": "Feature",
  "properties": {
    "gn:admin1_code":"03",
    "gn:asciiname":"Ampombimakoalahy",
    "gn:country_code":"MG",
    "gn:dem":72,
    "gn:feature_class":"P",
    "gn:feature_code":"PPL",
    "gn:name":"Ampombimakoalahy",
    "gn:population":0,
    "gn:timezone":"Indian/Antananarivo",
    "iso:country":"MG",
    "wof:name":"Ampombimakoalahy",
    "wof:placetype":"locality"
},
  "geometry": {"coordinates":[48.06667,-15.03333],"type":"Point"}
}