{
  "type": "Feature",
  "properties": {
    "gn:admin1_code":"01",
    "gn:asciiname":"Lomote",
    "gn:country_code":"MG",
    "gn:dem":-9999,
    "gn:feature_class":"P",
    "gn:feature_code":"PPL",
    "gn:name":"Lomote",
    "gn:population":0,
    "gn:timezone":"Indian/Antananarivo",
    "iso:country":"MG",
    "wof:name":"Lomote",
    "wof:placetype":"locality"
},
  "geometry": {"coordinates":[49.15,-12.18333],"type":"Point"}
}