{
  "type": "Feature",
  "properties": {
    "gn:admin1_code":"04",
    "gn:asciiname":"Ambalavoahangy",
    "gn:country_code":"MG",
    "gn:dem":893,
    "gn:feature_class":"P",
    "gn:feature_code":"PPL",
    "gn:name":"Ambalavoahangy",
    "gn:population":0,
    "gn:timezone":"Indian/Antananarivo",
    "iso:country":"MG",
    "wof:name":"Ambalavoahangy",
    "wof:placetype":"locality"
},
  "geometry": {"coordinates":[49.11667,-15.58333],"type":"Point"}
}