{
  "type": "Feature",
  "properties": {
    "gn:admin1_code":"03",
    "gn:asciiname":"Beravony",
    "gn:cc2":"MG",
    "gn:country_code":"MG",
    "gn:dem":43,
    "gn:feature_class":"P",
    "gn:feature_code":"PPL",
    "gn:name":"Beravony",
    "gn:population":0,
    "gn:timezone":"Indian/Antananarivo",
    "iso:country":"MG",
    "name:und_x_variant":[
        "Benavony",
        "Beravony"
    ],
    "wof:name":"Beravony",
    "wof:placetype":"locality"
},
  "geometry": {"coordinates":[47.75,-15.83333],"type":"Point"}
}