{
  "type": "Feature",
  "properties": {
    "gn:admin1_code":"04",
    "gn:asciiname":"Ambodiatafana",
    "gn:cc2":"MG",
    "gn:country_code":"MG",
    "gn:dem":26,
    "gn:feature_class":"P",
    "gn:feature_code":"PPL",
    "gn:name":"Ambodiatafana",
    "gn:population":0,
    "gn:timezone":"Indian/Antananarivo",
    "iso:country":"MG",
    "name:und_x_variant":[
        "Antanambe",
        "Ambodiatafana"
    ],
    "wof:name":"Ambodiatafana",
    "wof:placetype":"locality"
},
  "geometry": {"coordinates":[50.01667,-16.71667],"type":"Point"}
}