{
  "type": "Feature",
  "properties": {
    "gn:admin1_code":"6.0",
    "gn:asciiname":"Zavo",
    "gn:country_code":"MG",
    "gn:dem":95,
    "gn:feature_class":"P",
    "gn:feature_code":"PPL",
    "gn:name":"Zavo",
    "gn:population":0,
    "gn:timezone":"Indian/Antananarivo",
    "iso:country":"MG",
    "wof:name":"Zavo",
    "wof:placetype":"locality"
},
  "geometry": {"coordinates":[44.91667,-25.36667000000001],"type":"Point"}
}