{
  "type": "Feature",
  "properties": {
    "gn:admin1_code":"01",
    "gn:asciiname":"Bobantsetry",
    "gn:country_code":"MG",
    "gn:dem":38,
    "gn:feature_class":"P",
    "gn:feature_code":"PPL",
    "gn:name":"Bobantsetry",
    "gn:population":0,
    "gn:timezone":"Indian/Antananarivo",
    "iso:country":"MG",
    "wof:name":"Bobantsetry",
    "wof:placetype":"locality"
},
  "geometry": {"coordinates":[48.78333,-13.58333],"type":"Point"}
}