{
  "type": "Feature",
  "properties": {
    "gn:admin1_code":"06",
    "gn:asciiname":"Anjamahitsy",
    "gn:country_code":"MG",
    "gn:dem":289,
    "gn:feature_class":"P",
    "gn:feature_code":"PPL",
    "gn:name":"Anjamahitsy",
    "gn:population":0,
    "gn:timezone":"Indian/Antananarivo",
    "iso:country":"MG",
    "wof:name":"Anjamahitsy",
    "wof:placetype":"locality"
},
  "geometry": {"coordinates":[45.03333,-20.85],"type":"Point"}
}