{
  "type": "Feature",
  "properties": {
    "gn:admin1_code":"02",
    "gn:asciiname":"Antapandrano",
    "gn:cc2":"MG",
    "gn:country_code":"MG",
    "gn:dem":175,
    "gn:feature_class":"P",
    "gn:feature_code":"PPL",
    "gn:name":"Antapandrano",
    "gn:population":0,
    "gn:timezone":"Indian/Antananarivo",
    "iso:country":"MG",
    "name:und_x_variant":[
        "Andapandrano",
        "Antapandrano"
    ],
    "wof:name":"Antapandrano",
    "wof:placetype":"locality"
},
  "geometry": {"coordinates":[48.05,-20.93333],"type":"Point"}
}