{
  "type": "Feature",
  "properties": {
    "gn:admin1_code":"05",
    "gn:asciiname":"Mahafaliomby",
    "gn:country_code":"MG",
    "gn:dem":1841,
    "gn:feature_class":"P",
    "gn:feature_code":"PPL",
    "gn:name":"Mahafaliomby",
    "gn:population":0,
    "gn:timezone":"Indian/Antananarivo",
    "iso:country":"MG",
    "wof:name":"Mahafaliomby",
    "wof:placetype":"locality"
},
  "geometry": {"coordinates":[46.91667,-19.76667],"type":"Point"}
}