{
  "type": "Feature",
  "properties": {
    "gn:admin1_code":"02",
    "gn:asciiname":"Ambohimisafy",
    "gn:cc2":"MG",
    "gn:country_code":"MG",
    "gn:dem":487,
    "gn:feature_class":"P",
    "gn:feature_code":"PPL",
    "gn:name":"Ambohimisafy",
    "gn:population":0,
    "gn:timezone":"Indian/Antananarivo",
    "iso:country":"MG",
    "name:azb_x_preferred":[
        "\u0627\u0645\u0628\u0648\u0647\u06cc\u0645\u0627\u0633\u0627\u0641\u06cc"
    ],
    "name:fas_x_preferred":[
        "\u0627\u0645\u0628\u0648\u0647\u06cc\u0645\u0627\u0633\u0627\u0641\u06cc"
    ],
    "name:fra_x_preferred":[
        "Ambohimisafy"
    ],
    "name:ita_x_preferred":[
        "Ambohimisafy"
    ],
    "name:mlg_x_preferred":[
        "Ambohimisafy"
    ],
    "name:nld_x_preferred":[
        "Ambohimisafy"
    ],
    "name:und_x_variant":[
        "Ambohimisaty",
        "Ambohimisafy"
    ],
    "wof:name":"Ambohimisafy",
    "wof:placetype":"locality"
},
  "geometry": {"coordinates":[47.53333,-21.51667],"type":"Point"}
}