{
  "type": "Feature",
  "properties": {
    "gn:admin1_code":"04",
    "gn:asciiname":"Marotetezana",
    "gn:country_code":"MG",
    "gn:dem":61,
    "gn:feature_class":"P",
    "gn:feature_code":"PPL",
    "gn:name":"Marotetezana",
    "gn:population":0,
    "gn:timezone":"Indian/Antananarivo",
    "iso:country":"MG",
    "wof:name":"Marotetezana",
    "wof:placetype":"locality"
},
  "geometry": {"coordinates":[49.31667,-18.08333],"type":"Point"}
}