{
  "type": "Feature",
  "properties": {
    "gn:admin1_code":"04",
    "gn:asciiname":"Bejabora",
    "gn:country_code":"MG",
    "gn:dem":1062,
    "gn:feature_class":"P",
    "gn:feature_code":"PPL",
    "gn:name":"Bejabora",
    "gn:population":0,
    "gn:timezone":"Indian/Antananarivo",
    "iso:country":"MG",
    "wof:name":"Bejabora",
    "wof:placetype":"locality"
},
  "geometry": {"coordinates":[48.55,-17.85],"type":"Point"}
}