{
  "type": "Feature",
  "properties": {
    "gn:admin1_code":"02",
    "gn:asciiname":"Ankarimbelo",
    "gn:cc2":"MG",
    "gn:country_code":"MG",
    "gn:dem":116,
    "gn:feature_class":"P",
    "gn:feature_code":"PPL",
    "gn:name":"Ankarimbelo",
    "gn:population":0,
    "gn:timezone":"Indian/Antananarivo",
    "iso:country":"MG",
    "name:fra_x_preferred":[
        "Ankarimbelo"
    ],
    "name:ita_x_preferred":[
        "Ankarimbelo"
    ],
    "name:mlg_x_preferred":[
        "Ankarimbelo"
    ],
    "name:nld_x_preferred":[
        "Ankarimbelo"
    ],
    "name:und_x_variant":[
        "Ankarimbolo",
        "Ankarimbelona"
    ],
    "wof:name":"Ankarimbelo",
    "wof:placetype":"locality"
},
  "geometry": {"coordinates":[47.33333,-22.13333],"type":"Point"}
}