{
  "type": "Feature",
  "properties": {
    "gn:admin1_code":"04",
    "gn:asciiname":"Ambohibato",
    "gn:country_code":"MG",
    "gn:dem":911,
    "gn:feature_class":"P",
    "gn:feature_code":"PPL",
    "gn:name":"Ambohibato",
    "gn:population":0,
    "gn:timezone":"Indian/Antananarivo",
    "iso:country":"MG",
    "wof:name":"Ambohibato",
    "wof:placetype":"locality"
},
  "geometry": {"coordinates":[48.01667,-18.63333],"type":"Point"}
}