{
  "type": "Feature",
  "properties": {
    "gn:admin1_code":"2.0",
    "gn:asciiname":"Vatomasina",
    "gn:country_code":"MG",
    "gn:dem":6,
    "gn:feature_class":"P",
    "gn:feature_code":"PPL",
    "gn:name":"Vatomasina",
    "gn:population":0,
    "gn:timezone":"Indian/Antananarivo",
    "iso:country":"MG",
    "wof:name":"Vatomasina",
    "wof:placetype":"locality"
},
  "geometry": {"coordinates":[48.08333,-21.76667],"type":"Point"}
}