{
  "type": "Feature",
  "properties": {
    "gn:admin1_code":"6.0",
    "gn:asciiname":"Soafasy",
    "gn:country_code":"MG",
    "gn:dem":274,
    "gn:feature_class":"P",
    "gn:feature_code":"PPL",
    "gn:name":"Soafasy",
    "gn:population":0,
    "gn:timezone":"Indian/Antananarivo",
    "iso:country":"MG",
    "wof:name":"Soafasy",
    "wof:placetype":"locality"
},
  "geometry": {"coordinates":[45.06667,-21.88333],"type":"Point"}
}