{
  "type": "Feature",
  "properties": {
    "gn:admin1_code":"01",
    "gn:asciiname":"Ampanasana Ambevy",
    "gn:country_code":"MG",
    "gn:dem":11,
    "gn:feature_class":"P",
    "gn:feature_code":"PPL",
    "gn:name":"Ampanasana Ambevy",
    "gn:population":0,
    "gn:timezone":"Indian/Antananarivo",
    "iso:country":"MG",
    "wof:name":"Ampanasana Ambevy",
    "wof:placetype":"locality"
},
  "geometry": {"coordinates":[49.96667,-13.46667],"type":"Point"}
}