{
  "type": "Feature",
  "properties": {
    "gn:admin1_code":"03",
    "gn:asciiname":"Morafeno",
    "gn:cc2":"MG",
    "gn:country_code":"MG",
    "gn:dem":60,
    "gn:feature_class":"P",
    "gn:feature_code":"PPL",
    "gn:name":"Morafeno",
    "gn:population":0,
    "gn:timezone":"Indian/Antananarivo",
    "iso:country":"MG",
    "name:fra_x_preferred":[
        "Morafeno"
    ],
    "name:ita_x_preferred":[
        "Morafeno"
    ],
    "name:nld_x_preferred":[
        "Morafeno"
    ],
    "name:und_x_variant":[
        "Marafeno",
        "Morafeno"
    ],
    "wof:name":"Morafeno",
    "wof:placetype":"locality"
},
  "geometry": {"coordinates":[46.06667,-16.46667],"type":"Point"}
}