{
  "type": "Feature",
  "properties": {
    "gn:admin1_code":"05",
    "gn:asciiname":"Anbanimaso",
    "gn:country_code":"MG",
    "gn:dem":1229,
    "gn:feature_class":"P",
    "gn:feature_code":"PPL",
    "gn:name":"Anbanimaso",
    "gn:population":0,
    "gn:timezone":"Indian/Antananarivo",
    "iso:country":"MG",
    "wof:name":"Anbanimaso",
    "wof:placetype":"locality"
},
  "geometry": {"coordinates":[47.46667,-18.63333],"type":"Point"}
}