{
  "type": "Feature",
  "properties": {
    "gn:admin1_code":"02",
    "gn:asciiname":"Andanoa",
    "gn:country_code":"MG",
    "gn:dem":724,
    "gn:feature_class":"P",
    "gn:feature_code":"PPL",
    "gn:name":"Andanoa",
    "gn:population":0,
    "gn:timezone":"Indian/Antananarivo",
    "iso:country":"MG",
    "wof:name":"Andanoa",
    "wof:placetype":"locality"
},
  "geometry": {"coordinates":[45.88333,-21.11667000000001],"type":"Point"}
}