{
  "type": "Feature",
  "properties": {
    "gn:admin1_code":"04",
    "gn:asciiname":"Maromandia",
    "gn:country_code":"MG",
    "gn:dem":68,
    "gn:feature_class":"P",
    "gn:feature_code":"PPL",
    "gn:name":"Maromandia",
    "gn:population":0,
    "gn:timezone":"Indian/Antananarivo",
    "iso:country":"MG",
    "name:fra_x_preferred":[
        "Maromandia"
    ],
    "name:ita_x_preferred":[
        "Maromandia"
    ],
    "name:mlg_x_preferred":[
        "Maromandia"
    ],
    "name:nld_x_preferred":[
        "Maromandia"
    ],
    "wof:name":"Maromandia",
    "wof:placetype":"locality"
},
  "geometry": {"coordinates":[49.38333,-17.03333],"type":"Point"}
}