{
  "type": "Feature",
  "properties": {
    "gn:admin1_code":"04",
    "gn:asciiname":"Marosanja",
    "gn:country_code":"MG",
    "gn:dem":803,
    "gn:feature_class":"P",
    "gn:feature_code":"PPL",
    "gn:name":"Marosanja",
    "gn:population":0,
    "gn:timezone":"Indian/Antananarivo",
    "iso:country":"MG",
    "wof:name":"Marosanja",
    "wof:placetype":"locality"
},
  "geometry": {"coordinates":[47.83333,-20.01667],"type":"Point"}
}