{
  "type": "Feature",
  "properties": {
    "gn:admin1_code":"06",
    "gn:asciiname":"Analamikaiky",
    "gn:country_code":"MG",
    "gn:dem":85,
    "gn:feature_class":"P",
    "gn:feature_code":"PPL",
    "gn:name":"Analamikaiky",
    "gn:population":0,
    "gn:timezone":"Indian/Antananarivo",
    "iso:country":"MG",
    "wof:name":"Analamikaiky",
    "wof:placetype":"locality"
},
  "geometry": {"coordinates":[45.66667,-25.31667],"type":"Point"}
}