{
  "type": "Feature",
  "properties": {
    "gn:admin1_code":"06",
    "gn:asciiname":"Fangoloana Ambany",
    "gn:country_code":"MG",
    "gn:dem":505,
    "gn:feature_class":"P",
    "gn:feature_code":"PPL",
    "gn:name":"Fangoloana Ambany",
    "gn:population":0,
    "gn:timezone":"Indian/Antananarivo",
    "iso:country":"MG",
    "wof:name":"Fangoloana Ambany",
    "wof:placetype":"locality"
},
  "geometry": {"coordinates":[45.35,-23.96667],"type":"Point"}
}