{
  "type": "Feature",
  "properties": {
    "gn:admin1_code":"03",
    "gn:asciiname":"Dokolahy-Andimaky",
    "gn:cc2":"MG",
    "gn:country_code":"MG",
    "gn:dem":335,
    "gn:feature_class":"P",
    "gn:feature_code":"PPL",
    "gn:name":"Dokolahy-Andimaky",
    "gn:population":0,
    "gn:timezone":"Indian/Antananarivo",
    "iso:country":"MG",
    "name:und_x_variant":[
        "Andimaky-Dokolahy",
        "Dekolahy",
        "Dokolahy-Andimaka",
        "Dokolahy-Andimaky"
    ],
    "wof:name":"Dokolahy-Andimaky",
    "wof:placetype":"locality"
},
  "geometry": {"coordinates":[44.56667,-18.26667],"type":"Point"}
}