{
  "type": "Feature",
  "properties": {
    "gn:admin1_code":"06",
    "gn:asciiname":"Analamisampy Ambany",
    "gn:country_code":"MG",
    "gn:dem":191,
    "gn:feature_class":"P",
    "gn:feature_code":"PPL",
    "gn:name":"Analamisampy Ambany",
    "gn:population":0,
    "gn:timezone":"Indian/Antananarivo",
    "iso:country":"MG",
    "wof:name":"Analamisampy Ambany",
    "wof:placetype":"locality"
},
  "geometry": {"coordinates":[43.66667,-22.48333],"type":"Point"}
}