{
  "type": "Feature",
  "properties": {
    "gn:admin1_code":"1.0",
    "gn:asciiname":"Sealazaina",
    "gn:country_code":"MG",
    "gn:dem":44,
    "gn:feature_class":"P",
    "gn:feature_code":"PPL",
    "gn:name":"Sealazaina",
    "gn:population":0,
    "gn:timezone":"Indian/Antananarivo",
    "iso:country":"MG",
    "wof:name":"Sealazaina",
    "wof:placetype":"locality"
},
  "geometry": {"coordinates":[49.76667,-13.01667],"type":"Point"}
}