{
  "type": "Feature",
  "properties": {
    "gn:admin1_code":"02",
    "gn:asciiname":"Ambatoharanana",
    "gn:country_code":"MG",
    "gn:dem":70,
    "gn:feature_class":"P",
    "gn:feature_code":"PPL",
    "gn:name":"Ambatoharanana",
    "gn:population":0,
    "gn:timezone":"Indian/Antananarivo",
    "iso:country":"MG",
    "name:azb_x_preferred":[
        "\u0627\u0645\u0628\u0627\u062a\u0648\u0647\u0627\u0631\u0627\u0646\u0627\u0646\u0627"
    ],
    "name:fas_x_preferred":[
        "\u0627\u0645\u0628\u0627\u062a\u0648\u0647\u0627\u0631\u0627\u0646\u0627\u0646\u0627"
    ],
    "name:fra_x_preferred":[
        "Ambatoharanana"
    ],
    "name:ita_x_preferred":[
        "Ambatoharanana"
    ],
    "name:mlg_x_preferred":[
        "Ambatoharanana"
    ],
    "name:nld_x_preferred":[
        "Ambatoharanana"
    ],
    "wof:name":"Ambatoharanana",
    "wof:placetype":"locality"
},
  "geometry": {"coordinates":[47.66667,-22.16667],"type":"Point"}
}