{
  "type": "Feature",
  "properties": {
    "gn:admin1_code":"4.0",
    "gn:asciiname":"Tanambao-Tanjona",
    "gn:cc2":"MG",
    "gn:country_code":"MG",
    "gn:dem":22,
    "gn:feature_class":"P",
    "gn:feature_code":"PPL",
    "gn:name":"Tanambao-Tanjona",
    "gn:population":0,
    "gn:timezone":"Indian/Antananarivo",
    "iso:country":"MG",
    "name:und_x_variant":[
        "Antanambao",
        "Tanambao-Tanjona"
    ],
    "wof:name":"Tanambao-Tanjona",
    "wof:placetype":"locality"
},
  "geometry": {"coordinates":[49.71667,-15.91667],"type":"Point"}
}