{
  "type": "Feature",
  "properties": {
    "gn:admin1_code":"04",
    "gn:asciiname":"Ambohidronono",
    "gn:country_code":"MG",
    "gn:dem":868,
    "gn:feature_class":"P",
    "gn:feature_code":"PPL",
    "gn:name":"Ambohidronono",
    "gn:population":0,
    "gn:timezone":"Indian/Antananarivo",
    "iso:country":"MG",
    "name:azb_x_preferred":[
        "\u0627\u0645\u0628\u0648\u0647\u06cc\u062f\u0631\u0648\u0646\u0627\u0646\u0648"
    ],
    "name:fas_x_preferred":[
        "\u0627\u0645\u0628\u0648\u0647\u06cc\u062f\u0631\u0648\u0646\u0627\u0646\u0648"
    ],
    "name:fra_x_preferred":[
        "Ambohidronono"
    ],
    "name:ita_x_preferred":[
        "Ambohidronono"
    ],
    "name:mlg_x_preferred":[
        "Ambohidronono"
    ],
    "name:nld_x_preferred":[
        "Ambohidronono"
    ],
    "wof:name":"Ambohidronono",
    "wof:placetype":"locality"
},
  "geometry": {"coordinates":[48.03333,-18.75],"type":"Point"}
}