{
  "type": "Feature",
  "properties": {
    "gn:admin1_code":"01",
    "gn:asciiname":"Antanamandriry",
    "gn:country_code":"MG",
    "gn:dem":118,
    "gn:feature_class":"P",
    "gn:feature_code":"PPL",
    "gn:name":"Antanamandriry",
    "gn:population":0,
    "gn:timezone":"Indian/Antananarivo",
    "iso:country":"MG",
    "wof:name":"Antanamandriry",
    "wof:placetype":"locality"
},
  "geometry": {"coordinates":[49.86667,-13.75],"type":"Point"}
}