{
  "type": "Feature",
  "properties": {
    "gn:admin1_code":"06",
    "gn:asciiname":"Mikaika",
    "gn:country_code":"MG",
    "gn:dem":300,
    "gn:feature_class":"P",
    "gn:feature_code":"PPL",
    "gn:name":"Mikaika",
    "gn:population":0,
    "gn:timezone":"Indian/Antananarivo",
    "iso:country":"MG",
    "wof:name":"Mikaika",
    "wof:placetype":"locality"
},
  "geometry": {"coordinates":[45.98333,-24.15],"type":"Point"}
}