{
  "type": "Feature",
  "properties": {
    "gn:admin1_code":"05",
    "gn:asciiname":"Morarivo",
    "gn:country_code":"MG",
    "gn:dem":827,
    "gn:feature_class":"P",
    "gn:feature_code":"PPL",
    "gn:name":"Morarivo",
    "gn:population":0,
    "gn:timezone":"Indian/Antananarivo",
    "iso:country":"MG",
    "wof:name":"Morarivo",
    "wof:placetype":"locality"
},
  "geometry": {"coordinates":[46.28333,-19.31667],"type":"Point"}
}