{
  "type": "Feature",
  "properties": {
    "gn:admin1_code":"6.0",
    "gn:asciiname":"Vohidroy",
    "gn:country_code":"MG",
    "gn:dem":399,
    "gn:feature_class":"P",
    "gn:feature_code":"PPL",
    "gn:name":"Vohidroy",
    "gn:population":0,
    "gn:timezone":"Indian/Antananarivo",
    "iso:country":"MG",
    "wof:name":"Vohidroy",
    "wof:placetype":"locality"
},
  "geometry": {"coordinates":[45.46667,-24.53333],"type":"Point"}
}