{
  "type": "Feature",
  "properties": {
    "gn:admin1_code":"03",
    "gn:asciiname":"Anantaka",
    "gn:country_code":"MG",
    "gn:dem":238,
    "gn:feature_class":"P",
    "gn:feature_code":"PPL",
    "gn:name":"Anantaka",
    "gn:population":0,
    "gn:timezone":"Indian/Antananarivo",
    "iso:country":"MG",
    "wof:name":"Anantaka",
    "wof:placetype":"locality"
},
  "geometry": {"coordinates":[48.38333,-15.55],"type":"Point"}
}