{
  "type": "Feature",
  "properties": {
    "gn:admin1_code":"06",
    "gn:asciiname":"Besavoa-Beabobo",
    "gn:cc2":"MG",
    "gn:country_code":"MG",
    "gn:dem":346,
    "gn:feature_class":"P",
    "gn:feature_code":"PPL",
    "gn:name":"Besavoa-Beabobo",
    "gn:population":0,
    "gn:timezone":"Indian/Antananarivo",
    "iso:country":"MG",
    "name:und_x_variant":[
        "Besaroa Beabobo",
        "Besavoa-Beabobo"
    ],
    "wof:name":"Besavoa-Beabobo",
    "wof:placetype":"locality"
},
  "geometry": {"coordinates":[45.08333,-22.08333],"type":"Point"}
}