{
  "type": "Feature",
  "properties": {
    "gn:admin1_code":"06",
    "gn:asciiname":"Amberokely",
    "gn:country_code":"MG",
    "gn:dem":633,
    "gn:feature_class":"P",
    "gn:feature_code":"PPL",
    "gn:name":"Amberokely",
    "gn:population":0,
    "gn:timezone":"Indian/Antananarivo",
    "iso:country":"MG",
    "wof:name":"Amberokely",
    "wof:placetype":"locality"
},
  "geometry": {"coordinates":[45.66667,-19.31667],"type":"Point"}
}