{
  "type": "Feature",
  "properties": {
    "gn:admin1_code":"6.0",
    "gn:asciiname":"Songary",
    "gn:country_code":"MG",
    "gn:dem":309,
    "gn:feature_class":"P",
    "gn:feature_code":"PPL",
    "gn:name":"Songary",
    "gn:population":0,
    "gn:timezone":"Indian/Antananarivo",
    "iso:country":"MG",
    "wof:name":"Songary",
    "wof:placetype":"locality"
},
  "geometry": {"coordinates":[44.35,-23.21667],"type":"Point"}
}