{
  "type": "Feature",
  "properties": {
    "gn:admin1_code":"05",
    "gn:asciiname":"Ambohitriniandriana",
    "gn:country_code":"MG",
    "gn:dem":1416,
    "gn:feature_class":"P",
    "gn:feature_code":"PPL",
    "gn:name":"Ambohitriniandriana",
    "gn:population":0,
    "gn:timezone":"Indian/Antananarivo",
    "iso:country":"MG",
    "wof:name":"Ambohitriniandriana",
    "wof:placetype":"locality"
},
  "geometry": {"coordinates":[47.63333,-18.85],"type":"Point"}
}