{
  "type": "Feature",
  "properties": {
    "gn:admin1_code":"2.0",
    "gn:asciiname":"Tsiafarobe",
    "gn:country_code":"MG",
    "gn:dem":1214,
    "gn:feature_class":"P",
    "gn:feature_code":"PPL",
    "gn:name":"Tsiafarobe",
    "gn:population":0,
    "gn:timezone":"Indian/Antananarivo",
    "iso:country":"MG",
    "wof:name":"Tsiafarobe",
    "wof:placetype":"locality"
},
  "geometry": {"coordinates":[46.75,-20.33333],"type":"Point"}
}