{
  "type": "Feature",
  "properties": {
    "gn:admin1_code":"06",
    "gn:asciiname":"Ankera-Sarodrano",
    "gn:country_code":"MG",
    "gn:dem":404,
    "gn:feature_class":"P",
    "gn:feature_code":"PPL",
    "gn:name":"Ankera-Sarodrano",
    "gn:population":0,
    "gn:timezone":"Indian/Antananarivo",
    "iso:country":"MG",
    "wof:name":"Ankera-Sarodrano",
    "wof:placetype":"locality"
},
  "geometry": {"coordinates":[44.61667,-23.13333],"type":"Point"}
}