{
  "type": "Feature",
  "properties": {
    "gn:admin1_code":"06",
    "gn:asciiname":"Bekino",
    "gn:country_code":"MG",
    "gn:dem":169,
    "gn:feature_class":"P",
    "gn:feature_code":"PPL",
    "gn:name":"Bekino",
    "gn:population":0,
    "gn:timezone":"Indian/Antananarivo",
    "iso:country":"MG",
    "wof:name":"Bekino",
    "wof:placetype":"locality"
},
  "geometry": {"coordinates":[45.11667,-21.71667],"type":"Point"}
}