{
  "type": "Feature",
  "properties": {
    "gn:admin1_code":"05",
    "gn:asciiname":"Ilempona",
    "gn:cc2":"MG",
    "gn:country_code":"MG",
    "gn:dem":1571,
    "gn:feature_class":"P",
    "gn:feature_code":"PPL",
    "gn:name":"Ilempona",
    "gn:population":0,
    "gn:timezone":"Indian/Antananarivo",
    "iso:country":"MG",
    "name:und_x_variant":[
        "Gare d\u2019 Ilempona",
        "Ilempona"
    ],
    "wof:name":"Ilempona",
    "wof:placetype":"locality"
},
  "geometry": {"coordinates":[47.31667,-19.65],"type":"Point"}
}