{
  "type": "Feature",
  "properties": {
    "gn:admin1_code":"02",
    "gn:asciiname":"Ankerambe",
    "gn:country_code":"MG",
    "gn:dem":1342,
    "gn:feature_class":"P",
    "gn:feature_code":"PPL",
    "gn:name":"Ankerambe",
    "gn:population":0,
    "gn:timezone":"Indian/Antananarivo",
    "iso:country":"MG",
    "wof:name":"Ankerambe",
    "wof:placetype":"locality"
},
  "geometry": {"coordinates":[47.35,-20.38333],"type":"Point"}
}