{
  "type": "Feature",
  "properties": {
    "gn:admin1_code":"6.0",
    "gn:asciiname":"Talatavalo",
    "gn:cc2":"MG",
    "gn:country_code":"MG",
    "gn:dem":87,
    "gn:feature_class":"P",
    "gn:feature_code":"PPL",
    "gn:name":"Talatavalo",
    "gn:population":0,
    "gn:timezone":"Indian/Antananarivo",
    "iso:country":"MG",
    "name:und_x_variant":[
        "Telatavalo",
        "Talatalavalo",
        "Talatavalo"
    ],
    "wof:name":"Talatavalo",
    "wof:placetype":"locality"
},
  "geometry": {"coordinates":[43.83333,-21.81667],"type":"Point"}
}