{
  "type": "Feature",
  "properties": {
    "gn:admin1_code":"05",
    "gn:asciiname":"Kamolandy",
    "gn:cc2":"MG",
    "gn:country_code":"MG",
    "gn:dem":664,
    "gn:feature_class":"P",
    "gn:feature_code":"PPL",
    "gn:name":"Kamolandy",
    "gn:population":0,
    "gn:timezone":"Indian/Antananarivo",
    "iso:country":"MG",
    "name:und_x_variant":[
        "Kamilandy",
        "Kamolandy"
    ],
    "wof:name":"Kamolandy",
    "wof:placetype":"locality"
},
  "geometry": {"coordinates":[45.93333,-18.05],"type":"Point"}
}