{
  "type": "Feature",
  "properties": {
    "gn:admin1_code":"06",
    "gn:asciiname":"Boka-Tanambao",
    "gn:cc2":"MG",
    "gn:country_code":"MG",
    "gn:dem":483,
    "gn:feature_class":"P",
    "gn:feature_code":"PPL",
    "gn:name":"Boka-Tanambao",
    "gn:population":0,
    "gn:timezone":"Indian/Antananarivo",
    "iso:country":"MG",
    "name:und_x_variant":[
        "Boka",
        "Boka-Tanambao"
    ],
    "wof:name":"Boka-Tanambao",
    "wof:placetype":"locality"
},
  "geometry": {"coordinates":[44.53333,-22.86667000000001],"type":"Point"}
}