{
  "type": "Feature",
  "properties": {
    "gn:admin1_code":"06",
    "gn:asciiname":"Midiho",
    "gn:country_code":"MG",
    "gn:dem":80,
    "gn:feature_class":"P",
    "gn:feature_code":"PPL",
    "gn:name":"Midiho",
    "gn:population":0,
    "gn:timezone":"Indian/Antananarivo",
    "iso:country":"MG",
    "wof:name":"Midiho",
    "wof:placetype":"locality"
},
  "geometry": {"coordinates":[43.66667,-22.13333],"type":"Point"}
}