{
  "type": "Feature",
  "properties": {
    "gn:admin1_code":"04",
    "gn:asciiname":"Manambahiny",
    "gn:cc2":"MG",
    "gn:country_code":"MG",
    "gn:dem":937,
    "gn:feature_class":"P",
    "gn:feature_code":"PPL",
    "gn:name":"Manambahiny",
    "gn:population":0,
    "gn:timezone":"Indian/Antananarivo",
    "iso:country":"MG",
    "name:und_x_variant":[
        "Manakaambahiny",
        "Manambahiny"
    ],
    "wof:name":"Manambahiny",
    "wof:placetype":"locality"
},
  "geometry": {"coordinates":[48.38333,-18.45],"type":"Point"}
}