{
  "type": "Feature",
  "properties": {
    "gn:admin1_code":"3.0",
    "gn:asciiname":"Sambiravo",
    "gn:cc2":"MG",
    "gn:country_code":"MG",
    "gn:dem":26,
    "gn:feature_class":"P",
    "gn:feature_code":"PPL",
    "gn:name":"Sambiravo",
    "gn:population":0,
    "gn:timezone":"Indian/Antananarivo",
    "iso:country":"MG",
    "name:und_x_variant":[
        "Simbirano",
        "Sambiravo"
    ],
    "wof:name":"Sambiravo",
    "wof:placetype":"locality"
},
  "geometry": {"coordinates":[45.33333,-16.13332999999999],"type":"Point"}
}