{
  "type": "Feature",
  "properties": {
    "gn:admin1_code":"4.0",
    "gn:asciiname":"Sahandray",
    "gn:country_code":"MG",
    "gn:dem":107,
    "gn:feature_class":"P",
    "gn:feature_code":"PPL",
    "gn:name":"Sahandray",
    "gn:population":0,
    "gn:timezone":"Indian/Antananarivo",
    "iso:country":"MG",
    "wof:name":"Sahandray",
    "wof:placetype":"locality"
},
  "geometry": {"coordinates":[49.26667,-17.18333],"type":"Point"}
}