{
  "type": "Feature",
  "properties": {
    "gn:admin1_code":"02",
    "gn:asciiname":"Miray",
    "gn:country_code":"MG",
    "gn:dem":802,
    "gn:feature_class":"P",
    "gn:feature_code":"PPL",
    "gn:name":"Miray",
    "gn:population":0,
    "gn:timezone":"Indian/Antananarivo",
    "iso:country":"MG",
    "wof:name":"Miray",
    "wof:placetype":"locality"
},
  "geometry": {"coordinates":[46.66667,-21.55],"type":"Point"}
}