{
  "type": "Feature",
  "properties": {
    "gn:admin1_code":"04",
    "gn:asciiname":"Ambinanytelo",
    "gn:country_code":"MG",
    "gn:dem":970,
    "gn:feature_class":"P",
    "gn:feature_code":"PPL",
    "gn:name":"Ambinanytelo",
    "gn:population":0,
    "gn:timezone":"Indian/Antananarivo",
    "iso:country":"MG",
    "wof:name":"Ambinanytelo",
    "wof:placetype":"locality"
},
  "geometry": {"coordinates":[48.53333,-16.83333],"type":"Point"}
}