{
  "type": "Feature",
  "properties": {
    "gn:admin1_code":"03",
    "gn:asciiname":"Anjlamananazy",
    "gn:cc2":"MG",
    "gn:country_code":"MG",
    "gn:dem":411,
    "gn:feature_class":"P",
    "gn:feature_code":"PPL",
    "gn:name":"Anjlamananazy",
    "gn:population":0,
    "gn:timezone":"Indian/Antananarivo",
    "iso:country":"MG",
    "name:und_x_variant":[
        "Anjiamananazy",
        "Anjlamananazy"
    ],
    "wof:name":"Anjlamananazy",
    "wof:placetype":"locality"
},
  "geometry": {"coordinates":[44.86667,-17.38332999999999],"type":"Point"}
}