{
  "type": "Feature",
  "properties": {
    "gn:admin1_code":"2.0",
    "gn:asciiname":"Vatolapana",
    "gn:country_code":"MG",
    "gn:dem":7,
    "gn:feature_class":"P",
    "gn:feature_code":"PPL",
    "gn:name":"Vatolapana",
    "gn:population":0,
    "gn:timezone":"Indian/Antananarivo",
    "iso:country":"MG",
    "wof:name":"Vatolapana",
    "wof:placetype":"locality"
},
  "geometry": {"coordinates":[47.83333,-22.33333],"type":"Point"}
}