{
  "type": "Feature",
  "properties": {
    "gn:admin1_code":"03",
    "gn:asciiname":"Ambolobozo",
    "gn:cc2":"MG",
    "gn:country_code":"MG",
    "gn:dem":165,
    "gn:feature_class":"P",
    "gn:feature_code":"PPL",
    "gn:name":"Ambolobozo",
    "gn:population":0,
    "gn:timezone":"Indian/Antananarivo",
    "iso:country":"MG",
    "name:und_x_variant":[
        "Ambolibazo",
        "Ambolobozo"
    ],
    "wof:name":"Ambolobozo",
    "wof:placetype":"locality"
},
  "geometry": {"coordinates":[47.81667,-14.41667],"type":"Point"}
}