{
  "type": "Feature",
  "properties": {
    "gn:admin1_code":"05",
    "gn:asciiname":"Ankerana",
    "gn:country_code":"MG",
    "gn:dem":1268,
    "gn:feature_class":"P",
    "gn:feature_code":"PPL",
    "gn:name":"Ankerana",
    "gn:population":0,
    "gn:timezone":"Indian/Antananarivo",
    "iso:country":"MG",
    "name:fra_x_preferred":[
        "Ankerana"
    ],
    "name:ita_x_preferred":[
        "Ankerana"
    ],
    "name:mlg_x_preferred":[
        "Ankerana"
    ],
    "name:nld_x_preferred":[
        "Ankerana"
    ],
    "wof:name":"Ankerana",
    "wof:placetype":"locality"
},
  "geometry": {"coordinates":[47.06667,-18.88333],"type":"Point"}
}