{
  "type": "Feature",
  "properties": {
    "iso:country":"MG",
    "name:bul_x_preferred":[
        "\u0420\u0430\u043d\u0443\u043c\u0430\u0444\u0430\u043d\u0430"
    ],
    "name:deu_x_preferred":[
        "Ranomafana"
    ],
    "name:eng_x_preferred":[
        "Ranomafana"
    ],
    "name:fra_x_preferred":[
        "Ranomafana"
    ],
    "name:ita_x_preferred":[
        "Ranomafana"
    ],
    "name:mlg_x_preferred":[
        "Ranomafana"
    ],
    "name:nld_x_preferred":[
        "Ranomafana"
    ],
    "name:pol_x_preferred":[
        "Ranomafana"
    ],
    "name:rus_x_preferred":[
        "\u0420\u0430\u043d\u0443\u043c\u0430\u0444\u0430\u043d\u0430"
    ],
    "qs:gn_country":"MG",
    "qs:gn_fcode":"PPL",
    "qs:gn_pop":0,
    "qs:name":"Ranomafana",
    "qs:name_adm0":"Madagascar",
    "qs:name_adm1":"Fianarantsoa",
    "qs:photos":985,
    "qs:photos_1k":200,
    "qs:photos_9k":4,
    "qs:photos_9r":6,
    "qs:photos_all":985,
    "qs:photos_sr":10,
    "qs:placetype":"Town",
    "qs:pop_sr":"0",
    "qs:woe_adm0":23424883,
    "wof:name":"Ranomafana",
    "wof:placetype":"locality"
},
  "geometry": {"coordinates":[47.45,-21.25],"type":"Point"}
}