{
  "type": "Feature",
  "properties": {
    "gn:admin1_code":"05",
    "gn:asciiname":"Fieferana",
    "gn:country_code":"MG",
    "gn:dem":1238,
    "gn:feature_class":"P",
    "gn:feature_code":"PPL",
    "gn:name":"Fieferana",
    "gn:population":0,
    "gn:timezone":"Indian/Antananarivo",
    "iso:country":"MG",
    "wof:name":"Fieferana",
    "wof:placetype":"locality"
},
  "geometry": {"coordinates":[47.23333,-18.48333],"type":"Point"}
}