{
  "type": "Feature",
  "properties": {
    "gn:admin1_code":"05",
    "gn:asciiname":"Mananjary",
    "gn:country_code":"MG",
    "gn:dem":930,
    "gn:feature_class":"P",
    "gn:feature_code":"PPL",
    "gn:name":"Mananjary",
    "gn:population":0,
    "gn:timezone":"Indian/Antananarivo",
    "iso:country":"MG",
    "name:ceb_x_preferred":[
        "Mananjary"
    ],
    "name:nld_x_preferred":[
        "Mananjary"
    ],
    "name:pol_x_preferred":[
        "Mananjary"
    ],
    "name:rus_x_preferred":[
        "\u041c\u0430\u043d\u0430\u043d\u0434\u0437\u0430\u0440\u0438"
    ],
    "name:swe_x_preferred":[
        "Mananjary"
    ],
    "wof:name":"Mananjary",
    "wof:placetype":"locality"
},
  "geometry": {"coordinates":[47.61667,-18.28333],"type":"Point"}
}