{
  "type": "Feature",
  "properties": {
    "gn:admin1_code":"05",
    "gn:asciiname":"Mananjary",
    "gn:country_code":"MG",
    "gn:dem":930,
    "gn:feature_class":"P",
    "gn:feature_code":"PPL",
    "gn:name":"Mananjary",
    "gn:population":0,
    "gn:timezone":"Indian/Antananarivo",
    "iso:country":"MG",
    "name:ben_x_preferred":[
        "\u09ae\u09be\u09a8\u09be\u09a8\u099c\u09be\u09b0\u09bf"
    ],
    "name:ceb_x_preferred":[
        "Mananjary"
    ],
    "name:ell_x_preferred":[
        "\u039c\u03b1\u03bd\u03b1\u03bd\u03c4\u03b6\u03ac\u03c1\u03b9"
    ],
    "name:fas_x_preferred":[
        "\u0645\u0646\u0627\u0646\u062c\u0631\u06cc"
    ],
    "name:heb_x_preferred":[
        "\u05de\u05e0\u05e0\u05d2'\u05e8\u05d4"
    ],
    "name:hin_x_preferred":[
        "\u092e\u0928\u093e\u0902\u091c\u0930\u0940"
    ],
    "name:hun_x_preferred":[
        "Mananjary"
    ],
    "name:ind_x_preferred":[
        "Mananjary"
    ],
    "name:kor_x_preferred":[
        "\ub9c8\ub09c\uc790\ub9ac"
    ],
    "name:nld_x_preferred":[
        "Mananjary"
    ],
    "name:pol_x_preferred":[
        "Mananjary"
    ],
    "name:rus_x_preferred":[
        "\u041c\u0430\u043d\u0430\u043d\u0434\u0437\u0430\u0440\u0438"
    ],
    "name:spa_x_preferred":[
        "Mananjary"
    ],
    "name:swe_x_preferred":[
        "Mananjary"
    ],
    "name:tur_x_preferred":[
        "Mananjary"
    ],
    "name:ukr_x_preferred":[
        "\u041c\u0430\u043d\u0430\u043d\u0434\u0436\u0430\u0440\u0456"
    ],
    "name:urd_x_preferred":[
        "\u0645\u0627\u0646\u0627\u0646\u062c\u0627\u0631\u06cc"
    ],
    "name:vie_x_preferred":[
        "Mananjary"
    ],
    "wof:name":"Mananjary",
    "wof:placetype":"locality"
},
  "geometry": {"coordinates":[47.61667,-18.28333],"type":"Point"}
}