{
  "type": "Feature",
  "properties": {
    "gn:admin1_code":"04",
    "gn:asciiname":"Androrangavola",
    "gn:country_code":"MG",
    "gn:dem":766,
    "gn:feature_class":"P",
    "gn:feature_code":"PPL",
    "gn:name":"Androrangavola",
    "gn:population":0,
    "gn:timezone":"Indian/Antananarivo",
    "iso:country":"MG",
    "wof:name":"Androrangavola",
    "wof:placetype":"locality"
},
  "geometry": {"coordinates":[47.91667,-20.15],"type":"Point"}
}