{
  "type": "Feature",
  "properties": {
    "gn:admin1_code":"6.0",
    "gn:asciiname":"Tanandava Atsimo",
    "gn:cc2":"MG",
    "gn:country_code":"MG",
    "gn:dem":34,
    "gn:feature_class":"P",
    "gn:feature_code":"PPL",
    "gn:name":"Tanandava Atsimo",
    "gn:population":0,
    "gn:timezone":"Indian/Antananarivo",
    "iso:country":"MG",
    "name:und_x_variant":[
        "Antanandava",
        "Antanandavo",
        "Tanandava Atsimo"
    ],
    "wof:name":"Tanandava Atsimo",
    "wof:placetype":"locality"
},
  "geometry": {"coordinates":[46.45,-25.13333],"type":"Point"}
}